{
    "original": "KAIJSER, Gunnar, Major, Direktör, Stockholm, f Grava, Värml, 28/2 80 av rekt Th K o Alma Löhr, gm Maja öman. Offex 00, t fortif 01, kapt 10, major 30, ur akt tj 17, AIHS 02—06, lär KS 09—17, kommend t österr-ung armén 16. V. vkst dir byggn.AB Torssell &amp; Co 17—23, tjg vat.f.styr 23—25, v. vkst dir Vallevikens cementfabr 26—32, vkst dir Skarpö el distr.AB sed. 28, Sthlms fastigh.äg.frn sed. 32, ordf Skarpöborgs fastigh.äg.frn 30—32. Av trycket: Lärob i krigsbyggn.konst f kgl krigssk 17. RSO, skidm g, idr.m g.",
    "translated": "KAIJSER, Gunnar, Major, Director, Stockholm, born in Grava, Värmland, on 28/2 1880, son of the Reverend Th. K and Alma Löhr, married to Maja Öman. Joined the military in 1900, became a Second Lieutenant in 1901, Captain in 1910, and Major in 1930. Retired from active service in 1917. Served in the Royal Institute of Military Science (AIHS) from 1902 to 1906, as a teacher at the Military College (KS) from 1909 to 1917, and as a commanding officer in the Austro-Hungarian Army in 1916. Was Vice Director of Construction at Torssell & Co. AB from 1917 to 1923, served in the water defense force from 1923 to 1925, and was Vice Director at Vallevikens Cement Factory from 1926 to 1932. Became Vice Director of Skarpö Electricity Distribution Co. AB in 1928, and owned properties in Stockholm from 1932. Chairman of Skarpöborgs Property Owners Association from 1930 to 1932. Published \"Lärob i krigsbyggn.konst\" (Textbook on Military Construction) for the Royal Military Academy in 1917. Received the Royal Order of the Seraphim (RSO), participated in skiing competitions, and was involved in sports.\n\nNote: \"xx m. partner's name\" indicates the person married in the year 19xx.",
    "structured": {
        "@context": "https://schema.org",
        "@type": "Person",
        "name": "Gunnar Kaijser",
        "jobTitle": "Major, Director",
        "birthPlace": "Grava, Värmland",
        "birthDate": "1880-02-28",
        "parents": [
            {
                "@type": "Person",
                "name": "Th. K Kaijser (Reverend)"
            },
            {
                "@type": "Person",
                "name": "Alma Löhr"
            }
        ],
        "spouse": {
            "@type": "Person",
            "name": "Maja Öman"
        },
        "affiliations": [
            {
                "@type": "Organization",
                "name": "Austro-Hungarian Army",
                "startDate": "1916",
                "endDate": "1917"
            },
            {
                "@type": "Organization",
                "name": "Royal Institute of Military Science (AIHS)",
                "startDate": "1902",
                "endDate": "1906"
            },
            {
                "@type": "Organization",
                "name": "Military College (KS)",
                "startDate": "1909",
                "endDate": "1917"
            },
            {
                "@type": "Organization",
                "name": "Torssell & Co. AB",
                "jobTitle": "Vice Director of Construction",
                "startDate": "1917",
                "endDate": "1923"
            },
            {
                "@type": "Organization",
                "name": "Water Defense Force",
                "startDate": "1923",
                "endDate": "1925"
            },
            {
                "@type": "Organization",
                "name": "Vallevikens Cement Factory",
                "jobTitle": "Vice Director",
                "startDate": "1926",
                "endDate": "1932"
            },
            {
                "@type": "Organization",
                "name": "Skarpö Electricity Distribution Co. AB",
                "jobTitle": "Vice Director",
                "startDate": "1928"
            },
            {
                "@type": "Organization",
                "name": "Stockholm Property Owners Association",
                "jobTitle": "Owner",
                "startDate": "1932"
            },
            {
                "@type": "Organization",
                "name": "Skarpöborgs Property Owners Association",
                "jobTitle": "Chairman",
                "startDate": "1930",
                "endDate": "1932"
            }
        ],
        "education": [
            {
                "@type": "Organization",
                "name": "Royal Military Academy",
                "awards": [
                    {
                        "@type": "Order",
                        "name": "Royal Order of the Seraphim"
                    }
                ],
                "startDate": "1917"
            }
        ],
        "worksPublished": [
            {
                "@type": "CreativeWork",
                "name": "Lärob i krigsbyggn.konst",
                "datePublished": "1917"
            }
        ],
        "memberOf": [
            {
                "@type": "SportsTeam",
                "name": "Skiing Team"
            },
            {
                "@type": "SportsTeam",
                "name": "Sports Team"
            }
        ]
    },
    "occupations": {
        "career": [
            {
                "occupational_title": "Officer Candidate",
                "workplace": "Swedish Military",
                "industry": "Defense",
                "start_date": "1900"
            },
            {
                "occupational_title": "Second Lieutenant",
                "workplace": "Swedish Military",
                "industry": "Defense",
                "start_date": "1901"
            },
            {
                "occupational_title": "Captain",
                "workplace": "Swedish Military",
                "industry": "Defense",
                "start_date": "1910"
            },
            {
                "occupational_title": "Major",
                "workplace": "Swedish Military",
                "industry": "Defense",
                "start_date": "1930"
            },
            {
                "occupational_title": "Retired",
                "workplace": "Swedish Military",
                "industry": "Defense",
                "start_date": "1917"
            },
            {
                "occupational_title": "Teacher",
                "workplace": "Military College (KS)",
                "industry": "Education",
                "start_date": "1909"
            },
            {
                "occupational_title": "Commanding Officer",
                "workplace": "Austro-Hungarian Army",
                "industry": "Defense",
                "start_date": "1916"
            },
            {
                "occupational_title": "Vice Director of Construction",
                "workplace": "Torssell & Co. AB",
                "industry": "Construction",
                "start_date": "1917"
            },
            {
                "occupational_title": "Water Defense force member",
                "workplace": "",
                "industry": "Defense",
                "start_date": "1923"
            },
            {
                "occupational_title": "Vice Director",
                "workplace": "Vallevikens Cement Factory",
                "industry": "Construction",
                "start_date": "1926"
            },
            {
                "occupational_title": "Vice Director",
                "workplace": "Skarpö Electricity Distribution Co. AB",
                "industry": "Electricity",
                "start_date": "1928"
            },
            {
                "occupational_title": "",
                "workplace": "Stockholm Properties",
                "industry": "Real Estate",
                "start_date": "1932"
            }
        ]
    }
}