{
    "original": "HÖCKENSTRÖM, Albert Erik Wilhelm, Civilingenjör, Lidingö, f Bollnäs 11/7 84 av lok-för L H o Kristin Tufvesson, gm Emy Högström. CTL (E) 00—05. Anst v Luth &amp; Roséns Elektr AB samt byggn.ing v Skogens Kol AB Kilafors 07—10, ing o driftsled v AB Träkol Vansbro 10—18, disp f o deläg i Apparat AB Vansbro 15—19, inneh sed. 19 eg ing.-fma i Lidingö f konsult, ind- o bol.utredn samt värderingar. Utfört träkolningsverk eft egna pat o konstr f bl a AB Träkol 13, Skönviks AB 16, Uddeholms AB 17, Export AB 17, Skinnskattebergs Bruks AB 18, Bro Ångsågs AB 19 samt ett större antal verk f koin av ved o töre 14—19. Inneh ett flert pat å trä-kpln.området, destillationsapparater, gasreningsapparater mm. Styr.ordf i Apparat AB Vansbro 15—18, AB Leidesdorffska Fiskred-skapsfabr 25—33. Styr.led Lidingö stads folk-sk.styr 28—30, deleg i ind.verksutredn f Lidingö 28—30, styr.led i el- o vattenverken fr 30. Led Sv Tekn.frn. Init.tag t Sthlms Sport-fiskeklb o dess ordf 26—33, ordf i Sv Sportfiskares Riksfrb 33—43.",
    "translated": "HÖCKENSTRÖM, Albert Erik Wilhelm, Civil Engineer, Lidingö, born in Bollnäs on July 11, 1884, son of L.H. and Kristin Tufvesson. Married to Emy Högström. Employed at Luth & Rosén's Electric Company, as a construction engineer at Skogens Kol AB Kilafors from 1907 to 1910, as an engineer and operations manager at AB Träkol in Vansbro from 1910 to 1918, as a dispatcher and partial owner at Apparat AB in Vansbro from 1915 to 1919, and self-employed as an engineering consultant, conducting industrial and company assessments, and evaluations in Lidingö from 1919. Constructed charcoal works based on own patents and designs for AB Träkol in 1913, Skönviks AB in 1916, Uddeholms AB and Export AB in 1917, Skinnskattebergs Bruks AB in 1918, Bro Ångsågs AB in 1919, and numerous other works involving wood and bark from 1914 to 1919. Holds several patents in the field of wood carbonization, distillation apparatus, gas purification devices, and more. Served as chairman of Apparat AB in Vansbro from 1915 to 1918, and of AB Leidesdorffska Fiskred-skapsfabr from 1925 to 1933. Served on the board of Lidingö's public school authority from 1928 to 1930, as a delegate in the industrial working group for Lidingö from 1928 to 1930, and on the board of electricity and water plants from 1930. Member of the Swedish Technical Association. Initiated the Stockholm Sport Fishing Club and served as its chairman from 1926 to 1933, and served as the chairman of the Swedish Sport Fishing Association from 1933 to 1943.",
    "structured": {
        "@context": "https://schema.org",
        "@type": "Person",
        "name": "Albert Erik Wilhelm Höckenström",
        "jobTitle": "Civil Engineer",
        "address": {
            "@type": "PostalAddress",
            "addressLocality": "Lidingö"
        },
        "birthDate": "1884-07-11",
        "parent": [
            {
                "@type": "Person",
                "name": "L.H. Höckenström"
            },
            {
                "@type": "Person",
                "name": "Kristin Tufvesson"
            }
        ],
        "spouse": {
            "@type": "Person",
            "name": "Emy Högström"
        },
        "memberOf": [
            {
                "@type": "Organization",
                "name": "Luth & Rosén's Electric Company"
            },
            {
                "@type": "Organization",
                "name": "Skogens Kol AB Kilafors",
                "startDate": "1907",
                "endDate": "1910",
                "jobTitle": "Construction Engineer"
            },
            {
                "@type": "Organization",
                "name": "AB Träkol Vansbro",
                "startDate": "1910",
                "endDate": "1918",
                "jobTitle": "Engineer, Operations Manager"
            },
            {
                "@type": "Organization",
                "name": "Apparat AB Vansbro",
                "startDate": "1915",
                "endDate": "1919",
                "jobTitle": "Dispatcher, Partial Owner",
                "description": "Chairman (1915-1918)"
            },
            {
                "@type": "Organization",
                "name": "Lidingö Engineering Consulting",
                "startDate": "1919",
                "jobTitle": "Self-Employed"
            },
            {
                "@type": "Organization",
                "name": "AB Leidesdorffska Fiskred-skapsfabr",
                "startDate": "1925",
                "endDate": "1933",
                "jobTitle": "Chairman"
            }
        ],
        "patent": [
            {
                "@type": "Patent",
                "name": "Charcoal Production in Wood Carbonization Plants",
                "dateFiled": "1913"
            },
            {
                "@type": "Patent",
                "name": "Distillation Apparatus",
                "dateFiled": "unknown"
            },
            {
                "@type": "Patent",
                "name": "Gas Purification Devices",
                "dateFiled": "unknown"
            }
        ],
        "education": {
            "@type": "Organization",
            "name": "Swedish Technical Association"
        },
        "sportsTeam": [
            {
                "@type": "SportsTeam",
                "name": "Stockholm Sport Fishing Club",
                "startDate": "1926",
                "endDate": "1933",
                "jobTitle": "Chairman"
            },
            {
                "@type": "SportsTeam",
                "name": "Swedish Sport Fishing Association",
                "startDate": "1933",
                "endDate": "1943",
                "jobTitle": "Chairman"
            }
        ],
        "workLocation": [
            {
                "@type": "Place",
                "name": "Lidingö"
            }
        ],
        "boardMember": [
            {
                "@type": "Organization",
                "name": "Lidingö Public School Authority",
                "startDate": "1928",
                "endDate": "1930",
                "jobTitle": "Board Member"
            },
            {
                "@type": "Organization",
                "name": "Electricity and Water Plants",
                "startDate": "1930",
                "jobTitle": "Board Member"
            }
        ]
    },
    "occupations": {
        "career": [
            {
                "occupational_title": "Civil Engineer",
                "workplace": "Lidingö",
                "industry": "Engineering",
                "start_date": "Unknown"
            },
            {
                "occupational_title": "Construction Engineer",
                "workplace": "Skogens Kol AB Kilafors",
                "industry": "Construction",
                "start_date": "1907"
            },
            {
                "occupational_title": "Engineer and Operations Manager",
                "workplace": "AB Träkol Vansbro",
                "industry": "Wood Carbonization",
                "start_date": "1910"
            },
            {
                "occupational_title": "Dispatcher and Partial Owner",
                "workplace": "Apparat AB Vansbro",
                "industry": "Engineering",
                "start_date": "1915"
            },
            {
                "occupational_title": "Engineering Consultant",
                "workplace": "Lidingö",
                "industry": "Consulting",
                "start_date": "1919"
            },
            {
                "occupational_title": "Chairman",
                "workplace": "Apparat AB Vansbro",
                "industry": "Engineering",
                "start_date": "1915"
            },
            {
                "occupational_title": "Chairman",
                "workplace": "AB Leidesdorffska Fiskred-skapsfabr",
                "industry": "Fishing Equipment",
                "start_date": "1925"
            },
            {
                "occupational_title": "Board Member",
                "workplace": "Lidingö's Public School Authority",
                "industry": "Education",
                "start_date": "1928"
            },
            {
                "occupational_title": "Delegate",
                "workplace": "Industrial Working Group for Lidingö",
                "industry": "Government",
                "start_date": "1928"
            },
            {
                "occupational_title": "Board Member",
                "workplace": "Electricity and Water Plants",
                "industry": "Utilities",
                "start_date": "1930"
            }
        ]
    }
}