{
    "original": "KALLÄNDER, Marcus Natanael, Fil Måg-, Civilingenjör, Stockholm, f Husby-Långhundra, Sthlms l, 31/5 92 av kyrkoh C F K o Helena Celdén, gm Inger Lehre. Studex Upps 11, fil mag Upps 18, spec.stud KTH 19—20, ord stud 20—22 (maskinbyggn o mek tekn). Ing v Värmelednings AB Celsius i Gbg 24—28, vkst dir f Oljeeldnings AB Marcus Kalländer 1 Sthlm sed. 29.",
    "translated": "KALLÄNDER, Marcus Natanael, B.Sc., Civil Engineer, Stockholm, b. Husby-Långhundra, Stockholm County, May 31, 1892, son of the Reverend C.F.K. Kalländer and Helena Celdén, married to Inger Lehre. Completed secondary education in Uppsala in 1911, obtained a bachelor's degree in Uppsala in 1918, specialized studies at the Royal Institute of Technology (KTH) in 1919-1920, and conducted further studies from 1920 to 1922 (with a focus on mechanical engineering). Worked as an engineer at Värmelednings AB Celsius in Gothenburg from 1924 to 1928 and has been the managing director of Oljeeldnings AB Marcus Kalländer in Stockholm since 1929.",
    "structured": {
        "name": "Marcus Natanael Kalländer",
        "birthDate": "1892-05-31",
        "birthPlace": {
            "address": {
                "addressLocality": "Husby-Långhundra",
                "addressRegion": "Stockholm County"
            }
        },
        "parent": [
            {
                "name": "C.F.K. Kalländer",
                "jobTitle": "Reverend"
            },
            {
                "name": "Helena Celdén"
            }
        ],
        "spouse": {
            "name": "Inger Lehre"
        },
        "education": [
            {
                "institution": {
                    "name": "Uppsala University"
                },
                "degree": "Secondary Education",
                "endDate": "1911"
            },
            {
                "institution": {
                    "name": "Uppsala University"
                },
                "degree": "B.Sc.",
                "endDate": "1918"
            },
            {
                "institution": {
                    "name": "Royal Institute of Technology (KTH)"
                },
                "studyType": "Specialized Studies",
                "endDate": "1920-1922",
                "areaServed": "Mechanical Engineering"
            }
        ],
        "work": [
            {
                "employer": {
                    "name": "Värmelednings AB Celsius"
                },
                "jobTitle": "Engineer",
                "startDate": "1924",
                "endDate": "1928",
                "areaServed": "Gothenburg"
            },
            {
                "employer": {
                    "name": "Oljeeldnings AB Marcus Kalländer"
                },
                "jobTitle": "Managing Director",
                "startDate": "1929",
                "areaServed": "Stockholm"
            }
        ]
    },
    "occupations": {
        "career": [
            {
                "occupational_title": "B.Sc.",
                "workplace": "N/A",
                "industry": "N/A",
                "start_date": "N/A"
            },
            {
                "occupational_title": "Civil Engineer",
                "workplace": "N/A",
                "industry": "N/A",
                "start_date": "N/A"
            },
            {
                "occupational_title": "Engineer",
                "workplace": "Värmelednings AB Celsius",
                "industry": "Mechanical Engineering",
                "start_date": "1924"
            },
            {
                "occupational_title": "Managing Director",
                "workplace": "Oljeeldnings AB Marcus Kalländer",
                "industry": "Oil Burning",
                "start_date": "1929"
            }
        ]
    }
}