{
    "original": "NYSTRÖM, John Emil Emanuel, Grosshandlare, Norrköping, f S:t Olai, östergötl l, 24/8 90 av spinnmäst F E N o Clara Andersson, gm Märta Forsberg. Hdlsutbildn. Kontorist i fma Werner Ericssons Pappersaff en gros i Norrkp (grund 00), senare resande i samma fma, övertog den 18 und namn Werner Ericssons Eftr John Nyström, Papper en gros. Styr.led i Sv Såp- &amp; Tvålfabr AB i Norrkp 18. Styr.led i östergötl Fabr- o Grossistfrb o ordf 1 dess papperssektion, medlem i Sv Pappers-grosshandl.frns avd i Sthlm, i Sv Pappers-grossistfrb i Sthlm o i Hdlsfrn i Norrkp, medl av Norrkps Köpm.frn o led av dess gransk-ningsnmd f ackordsärenden. Led av tax.nmd. Rev i Bostadsfrn Rörläggaren i Norrkp. Frimurare, Odd Fellow (skattmäst i Log nr 19 Louis De Geer i Norrkp 34—41), styr.suppl i Sällsk VGB i Norrkp o dess rev 40. Resor: Norge 35, Tyskl 36, Danm 39. Hobbies: Det egna arbetet, resor.",
    "translated": "NYSTRÖM, John Emil Emanuel, Merchant, Norrköping, born in S:t Olai, Östergötland County, on August 24, 1890, son of master spinner F E N and Clara Andersson, married to Märta Forsberg. Commercial training. Office clerk at Werner Ericsson's Wholesale Paper Store in Norrköping (established in 1900), later became a traveling representative for the same company. Took over and changed the name to Werner Ericsson's Successor John Nyström, Wholesale Paper. Board member of the Swedish Soap and Soap Factory Ltd in Norrköping since 1918. Board member of the Östergötland Factory and Wholesale Association and chairman of its paper section. Member of the Swedish Paper Wholesale Association in Stockholm, the Swedish Paper Wholesale Association in Stockholm, and the Norrköping Trade Association. Member of the Norrköping Merchants' Association and a member of its review board for piecework matters. Member of the taxation committee. Auditor at the Housing Association Rörläggaren in Norrköping. Freemason, Odd Fellow (treasurer in Lodge No. 19 Louis De Geer in Norrköping from 1934 to 1941). Deputy board member of the Society VGB in Norrköping and auditor in 1940. Travels: Norway 1935, Germany 1936, Denmark 1939. Hobbies: His own work, traveling.",
    "structured": {
        "@context": "https://schema.org",
        "@type": "Person",
        "name": "John Emil Emanuel Nyström",
        "givenName": "John Emil Emanuel",
        "familyName": "Nyström",
        "gender": "Male",
        "birthDate": "1890-08-24",
        "birthPlace": {
            "@type": "Place",
            "name": "S:t Olai, Östergötland County, Sweden"
        },
        "description": "Merchant",
        "parents": [
            {
                "@type": "Person",
                "name": "F E N",
                "jobTitle": "Master Spinner"
            },
            {
                "@type": "Person",
                "name": "Clara Andersson"
            }
        ],
        "spouse": {
            "@type": "Person",
            "name": "Märta Forsberg"
        },
        "education": {
            "@type": "EducationalOccupationalCredential",
            "credentialCategory": "hs",
            "description": "Commercial Training"
        },
        "worksFor": {
            "@type": "Organization",
            "name": "Werner Ericsson's Wholesale Paper Store",
            "foundingDate": "1900"
        },
        "jobTitle": "Office Clerk, Traveling Representative",
        "memberOf": [
            {
                "@type": "Organization",
                "name": "Swedish Soap and Soap Factory Ltd",
                "foundingDate": "1918",
                "boardMember": true
            },
            {
                "@type": "Organization",
                "name": "Östergötland Factory and Wholesale Association",
                "boardMember": true,
                "chairman": "Paper Section"
            },
            {
                "@type": "Organization",
                "name": "Swedish Paper Wholesale Association",
                "memberOf": [
                    {
                        "@type": "Place",
                        "name": "Stockholm"
                    }
                ]
            },
            {
                "@type": "Organization",
                "name": "Norrköping Trade Association",
                "memberOf": [
                    {
                        "@type": "Place",
                        "name": "Norrköping"
                    }
                ]
            },
            {
                "@type": "Organization",
                "name": "Norrköping Merchants' Association",
                "memberOf": [
                    {
                        "@type": "Place",
                        "name": "Norrköping"
                    }
                ]
            },
            {
                "@type": "Organization",
                "name": "Sällsk VGB",
                "memberOf": [
                    {
                        "@type": "Place",
                        "name": "Norrköping"
                    }
                ],
                "audit": true
            }
        ],
        "auditor": [
            {
                "@type": "Organization",
                "name": "Housing Association Rörläggaren",
                "description": "Norwegian Auditor"
            }
        ],
        "additionalProperty": [
            {
                "name": "Frimurare",
                "value": true
            },
            {
                "name": "Odd Fellow",
                "value": true,
                "additionalProperty": [
                    {
                        "name": "Lodge No.",
                        "value": "19 Louis De Geer"
                    },
                    {
                        "name": "Location",
                        "value": "Norrköping"
                    },
                    {
                        "name": "Treasurer",
                        "value": "1934-1941"
                    }
                ]
            }
        ],
        "travels": [
            {
                "@type": "Place",
                "name": "Norway",
                "startDate": "1935"
            },
            {
                "@type": "Place",
                "name": "Germany",
                "startDate": "1936"
            },
            {
                "@type": "Place",
                "name": "Denmark",
                "startDate": "1939"
            }
        ],
        "hobbies": "His own work, traveling"
    },
    "occupations": {
        "career": [
            {
                "occupational_title": "Office Clerk",
                "workplace": "Werner Ericsson's Wholesale Paper Store",
                "industry": "Wholesale",
                "start_date": "1900"
            },
            {
                "occupational_title": "Traveling Representative",
                "workplace": "Werner Ericsson's Wholesale Paper Store",
                "industry": "Wholesale",
                "start_date": "unknown"
            },
            {
                "occupational_title": "Merchant",
                "workplace": "Werner Ericsson's Successor John Nyström, Wholesale Paper",
                "industry": "Wholesale",
                "start_date": "unknown"
            }
        ]
    }
}