{
    "original": "CLAESON, Per Richard, Fabrikör, Uddebo, f Uddebo, Tranemo, Älvsb l, 30/6 65 av fabr P A C o Augusta Sundström, gm Anna Bårström. Jönkp hal, stud textilind Tyskl. Anst Uddebo Trikåfabr AB 85. Grund Uddebo Möbeltyg Väfveri 95, driver nu dta tills m sonen disp Helge C. Ag Villa Furuhall, fabr.hus, arb-bost o skogsfastigh f väv. Led Kinds vägstyr 00—25, Vgl o N Hall hdlskamm, Tranemo kyrkoflm o sk.råd, styr.led Älvsb l lungsotssanat, Svenljunga sjukstuga; Uddebo AB (fd Udde-bo Trikåfabr AB), Falkenbergs jvks AB (vkst dir 25—30), Tullinge AB, Tostarps Träförädl AB, Svenljunga Omnibus AB. Styr.led ett flert frn. FI nöjes-, stud- o af f.re s Norge, Danm, Finl, östersjöprov, Tyskl, Österr, Schweiz, Ital, Engl. RNO, RVO. C :s farfar, riksdagsman i bondeståndet, drev handvävnad i Tostarp, Tranemo. Då C:s sonson nu är anst i Uddebo Möbeltyg har släkten drivit textilverksamhet i 5 generationer.",
    "translated": "CLAESON, Per Richard, Manufacturer, Uddebo, born in Uddebo, Tranemo, Älvsborg County, on June 30, 1865, to P A C and Augusta Sundström. Married to Anna Bårström. Completed primary education, studied textile industry in Germany. Employed at Uddebo Trikåfabr AB since 1885. Founded Uddebo Möbeltyg Väfveri in 1895 and currently runs the business together with his son, Helge C. Resides at Villa Furuhall, a factory house, and owns a residential and forest property for weaving purposes. Served as a member of the Kinds road board from 1900 to 1925, member of the Vgl and N Hall trade chambers, Tranemo church film and school board, and governing board of Älvsborg County tuberculosis sanatorium and Svenljunga hospital. Also served on the boards of Uddebo AB (formerly Uddebo Trikåfabr AB), Falkenbergs jvks AB (as a managing director from 1925 to 1930), Tullinge AB, Tostarps Träförädl AB, and Svenljunga Omnibus AB. Board member of several entertainment, educational, and professional organizations in Norway, Denmark, Finland, Baltic countries, Germany, Austria, Switzerland, Italy, and England. Awarded RNO (Royal Order of the Northern Star) and RVO (Royal Order of Vasa). C's paternal grandfather, a member of the peasant estate in the parliament, engaged in hand weaving in Tostarp, Tranemo. With C's grandson currently employed at Uddebo Möbeltyg, the family has been involved in the textile industry for five generations.",
    "structured": {
        "@context": "https://schema.org",
        "@type": "Person",
        "name": "Per Richard Claeson",
        "givenName": "Per Richard",
        "familyName": "Claeson",
        "birthDate": "1865-06-30",
        "birthPlace": {
            "@type": "Place",
            "name": "Uddebo, Tranemo, Älvsborg County"
        },
        "parents": [
            {
                "@type": "Person",
                "name": "P A C"
            },
            {
                "@type": "Person",
                "name": "Augusta Sundström"
            }
        ],
        "spouse": [
            {
                "@type": "Person",
                "name": "Anna Bårström"
            }
        ],
        "education": [
            {
                "@type": "EducationalOccupationalCredential",
                "name": "Primary Education"
            },
            {
                "@type": "EducationalOccupationalCredential",
                "name": "Textile Industry Studies in Germany"
            }
        ],
        "occupation": {
            "@type": "OrganizationRole",
            "roleName": "Manufacturer",
            "namedPosition": "Fabrikör"
        },
        "worksFor": {
            "@type": "Organization",
            "name": "Uddebo Möbeltyg Väfveri"
        },
        "owns": [
            {
                "@type": "Place",
                "name": "Villa Furuhall"
            },
            {
                "@type": "RealEstateAgent",
                "name": "Arb-bost o skogsfastigh f väv"
            }
        ],
        "memberOf": [
            {
                "@type": "Organization",
                "name": "Kinds vägstyr",
                "startDate": "1900",
                "endDate": "1925"
            },
            {
                "@type": "Organization",
                "name": "Vgl o N Hall hdlskamm"
            },
            {
                "@type": "Organization",
                "name": "Tranemo kyrkoflm o sk.råd"
            },
            {
                "@type": "Organization",
                "name": "Älvsb l lungsotssanat"
            },
            {
                "@type": "Organization",
                "name": "Svenljunga sjukstuga"
            },
            {
                "@type": "Organization",
                "name": "Uddebo AB"
            },
            {
                "@type": "Organization",
                "name": "Falkenbergs jvks AB",
                "startDate": "1925",
                "endDate": "1930"
            },
            {
                "@type": "Organization",
                "name": "Tullinge AB"
            },
            {
                "@type": "Organization",
                "name": "Tostarps Träförädl AB"
            },
            {
                "@type": "Organization",
                "name": "Svenljunga Omnibus AB"
            },
            {
                "@type": "Organization",
                "name": "FI nöjes-, stud- o af f.re s Norge, Danm, Finl, östersjöprov, Tyskl, Österr, Schweiz, Ital, Engl"
            }
        ],
        "awards": [
            {
                "@type": "Order",
                "name": "Royal Order of the Northern Star",
                "category": "RNO"
            },
            {
                "@type": "Order",
                "name": "Royal Order of Vasa",
                "category": "RVO"
            }
        ],
        "relatedTo": {
            "@type": "Person",
            "name": "C's paternal grandfather",
            "description": "A member of the peasant estate in the parliament and engaged in hand weaving in Tostarp, Tranemo."
        },
        "descendants": {
            "@type": "Person",
            "name": "C's grandson",
            "description": "Currently employed at Uddebo Möbeltyg"
        },
        "familyBusiness": {
            "@type": "Organization",
            "name": "Textile Industry",
            "description": "The family has been involved in the textile industry for five generations."
        }
    },
    "occupations": {
        "career": [
            {
                "occupational_title": "Manufacturer",
                "workplace": "Uddebo Trikåfabr AB",
                "industry": "Textile",
                "start_date": "1885"
            },
            {
                "occupational_title": "Founder",
                "workplace": "Uddebo Möbeltyg Väfveri",
                "industry": "Textile",
                "start_date": "1895"
            },
            {
                "occupational_title": "Managing Director",
                "workplace": "Falkenbergs jvks AB",
                "industry": "Textile",
                "start_date": "1925"
            },
            {
                "occupational_title": "Board Member",
                "workplace": "Uddebo AB (formerly Uddebo Trikåfabr AB)",
                "industry": "Textile",
                "start_date": "n/a"
            },
            {
                "occupational_title": "Board Member",
                "workplace": "Tullinge AB",
                "industry": "n/a",
                "start_date": "n/a"
            },
            {
                "occupational_title": "Board Member",
                "workplace": "Tostarps Träförädl AB",
                "industry": "n/a",
                "start_date": "n/a"
            },
            {
                "occupational_title": "Board Member",
                "workplace": "Svenljunga Omnibus AB",
                "industry": "n/a",
                "start_date": "n/a"
            }
        ]
    }
}