{
    "original": "EINERTII, Eric Gustaf Einar, Direktör, Mariestad, f Renneslöf, Hall län, 15/3 90 av Carl Petersson o Anna Johansson, gm Elisabeth Whitefield. Kont.ch AB Frick &amp; Oldny, Malmö, 19—24, kamr systembol Halmst 24—38, disp systembol Falköp 38, vkst dir systemAB, Mariest, förest Skarab läns kristidsstyr kontr.byrå sed. 40. Styr.led Skarab läns nykt.-nmdrs centr.org, led nykt.nnidn i Mariest, Istlöjtu, ordf Mariest Istfrn ungd.avd U 60, styr.suppl Mariestads Istfrn. Frimurare, W6, NN, 7.B; IstSM. Hobby: Trädg.odl.",
    "translated": "EINERTII, Eric Gustaf Einar, Director, Mariestad, born in Renneslöf, Halland County, on March 15, 1890, to Carl Petersson and Anna Johansson, married to Elisabeth Whitefield. Worked as a accountant at AB Frick & Oldny, Malmö, from 1919 to 1924, then as a clerk at Systembolaget in Halmstad from 1924 to 1938, followed by a position as a dispatcher at Systembolaget in Falköping in 1938. Became a Deputy Managing Director at SystemAB in Mariestad and managed the contracting office of Skaraborg County during the war from 1940 until now. Serves on the board of the Skaraborg County Temperance Movement's Central Organization and is a board member of the Temperance Association in Mariestad. He is also the Chairman of the Mariestad Youth Department of the Swedish Temperance Association and a substitute board member of the Mariestad Temperance Society. He is a Freemason (W6, NN, 7.B) and has received the First Class Military Service Medal. Hobbies include gardening.",
    "structured": {
        "@context": "https://schema.org",
        "@type": "Person",
        "givenName": "Eric Gustaf Einar",
        "familyName": "Einertii",
        "birthDate": "1890-03-15",
        "birthPlace": {
            "@type": "Place",
            "name": "Renneslöf, Halland County"
        },
        "parents": [
            {
                "@type": "Person",
                "name": "Carl Petersson",
                "sameAs": ""
            },
            {
                "@type": "Person",
                "name": "Anna Johansson",
                "sameAs": ""
            }
        ],
        "spouse": {
            "@type": "Person",
            "name": "Elisabeth Whitefield",
            "sameAs": ""
        },
        "jobTitle": "Director",
        "worksFor": {
            "@type": "Organization",
            "name": "AB Frick & Oldny"
        },
        "workLocation": {
            "@type": "Place",
            "name": "Mariestad"
        },
        "memberOf": {
            "@type": "Organization",
            "name": "Frimurare",
            "sameAs": ""
        },
        "affiliation": [
            {
                "@type": "Organization",
                "name": "Skaraborg County Temperance Movement's Central Organization",
                "memberOf": {
                    "@type": "Organization",
                    "name": "Skaraborg County Temperance Movement's Central Organization",
                    "sameAs": ""
                }
            },
            {
                "@type": "Organization",
                "name": "Temperance Association in Mariestad",
                "memberOf": {
                    "@type": "Organization",
                    "name": "Temperance Association in Mariestad",
                    "sameAs": ""
                }
            },
            {
                "@type": "Organization",
                "name": "Mariestad Youth Department of the Swedish Temperance Association",
                "memberOf": {
                    "@type": "Organization",
                    "name": "Mariestad Youth Department of the Swedish Temperance Association",
                    "sameAs": ""
                },
                "roleName": "Chairman"
            },
            {
                "@type": "Organization",
                "name": "Mariestad Temperance Society",
                "memberOf": {
                    "@type": "Organization",
                    "name": "Mariestad Temperance Society",
                    "sameAs": ""
                },
                "roleName": "Substitute Board Member"
            }
        ],
        "honorificPrefix": "Director",
        "award": [
            {
                "@type": "Medal",
                "name": "First Class Military Service Medal"
            }
        ],
        "description": "Hobbies include gardening."
    },
    "occupations": {
        "career": [
            {
                "occupational_title": "Accountant",
                "workplace": "AB Frick & Oldny",
                "industry": "Malmö",
                "start_date": "1919"
            },
            {
                "occupational_title": "Clerk",
                "workplace": "Systembolaget",
                "industry": "Halmstad",
                "start_date": "1924"
            },
            {
                "occupational_title": "Dispatcher",
                "workplace": "Systembolaget",
                "industry": "Falköping",
                "start_date": "1938"
            },
            {
                "occupational_title": "Deputy Managing Director",
                "workplace": "SystemAB",
                "industry": "Mariestad",
                "start_date": "1940"
            },
            {
                "occupational_title": "Contracting Office Manager",
                "workplace": "Skaraborg County",
                "industry": "Mariestad",
                "start_date": "1940"
            }
        ]
    }
}