{
    "original": "FROHM, Gustaf Reinhold, Direktör, Stockholm, f 30/12 90 av skräddarna A F o Elna Ohlsson, gm Frida Lindgren. Studex Malmö 10. Tjm i Brand- o Lifförs.AB Skåne 10—18, i Förs.AB Mälaren 18—19, kont.ch v Skånes gen.ag i Sthlm 19—40, dir där sed. 40. Styr.led i E Rydbeck AB, Tariffrn f ansv.försäkr mfl branscher, led Sv försäkr.frns utbildn.-nmd. Ordf Sv brottn.frb, skattm Sv olymp komm, led Svgifrfrb :s överstyr. RVO, Tyskl-OlHt2kl, Franska stat:s GM f fys fostran, Riksidr.frbs ftjt g, Sv brottn.frbs, Skånes idr.frbs o bol Skånes ftjGM:er.",
    "translated": "FROHM, Gustaf Reinhold, Director, Stockholm, b. 30/12 1890, son of tailors A F and Elna Ohlsson, m. Frida Lindgren. Graduate of Malmö School 1910. Employed at Brand- and Life Insurance AB Skåne 1910-1918, at Försäkrings AB Mälaren 1918-1919. Became head clerk at Skånes General Agency in Stockholm 1919-1940, and director there since 1940. Member of the board of E. Rydbeck AB, Tariff Union for liability insurance and other industries, and the Swedish insurance industry's education committee. Chairman of the Swedish Wrestling Federation, treasurer of the Swedish Olympic Committee, and member of the board of the Swedish Gymnastics Federation. Receipient of the Royal Order of the Vasa, Officer of the German Olympic Order 2nd class, and recipient of the French state's Gold Medal for physical education. Honorary member of the Swedish Gymnastics Association, Skånes Sports Association, and the Federation of Skåne Gymnastics Clubs.",
    "structured": {
        "@context": "https://schema.org",
        "@type": "Person",
        "name": "Gustaf Reinhold Frohm",
        "birthDate": "1890-12-30",
        "birthPlace": "Stockholm",
        "parents": [
            "A F",
            "Elna Ohlsson"
        ],
        "spouse": "Frida Lindgren",
        "education": {
            "@type": "EducationalOccupationalCredential",
            "name": "Malmö School",
            "alumniOf": "Malmö School",
            "startDate": "1910",
            "endDate": "1910"
        },
        "occupation": [
            {
                "@type": "OrganizationRole",
                "roleName": "Director",
                "startDate": "1940",
                "affiliation": {
                    "@type": "Organization",
                    "name": "Skånes General Agency"
                },
                "memberOf": [
                    {
                        "@type": "Organization",
                        "name": "E. Rydbeck AB"
                    },
                    {
                        "@type": "Organization",
                        "name": "Tariff Union"
                    }
                ]
            },
            {
                "@type": "OrganizationRole",
                "roleName": "Head clerk",
                "startDate": "1919",
                "endDate": "1940",
                "affiliation": {
                    "@type": "Organization",
                    "name": "Skånes General Agency"
                }
            },
            {
                "@type": "OrganizationRole",
                "roleName": "Employee",
                "startDate": "1910",
                "endDate": "1918",
                "affiliation": [
                    {
                        "@type": "Organization",
                        "name": "Brand- and Life Insurance AB Skåne"
                    },
                    {
                        "@type": "Organization",
                        "name": "Försäkrings AB Mälaren"
                    }
                ]
            }
        ],
        "boardMember": [
            {
                "@type": "Organization",
                "name": "E. Rydbeck AB"
            },
            {
                "@type": "Organization",
                "name": "Tariff Union"
            },
            {
                "@type": "Organization",
                "name": "Swedish insurance industry's education committee"
            },
            {
                "@type": "Organization",
                "name": "Swedish Wrestling Federation"
            },
            {
                "@type": "Organization",
                "name": "Swedish Olympic Committee"
            },
            {
                "@type": "Organization",
                "name": "Swedish Gymnastics Federation"
            },
            {
                "@type": "Organization",
                "name": "Swedish Gymnastics Association"
            },
            {
                "@type": "Organization",
                "name": "Skånes Sports Association"
            },
            {
                "@type": "Organization",
                "name": "Federation of Skåne Gymnastics Clubs"
            }
        ],
        "awards": [
            {
                "@type": "Order",
                "name": "Royal Order of the Vasa",
                "description": "RVO"
            },
            {
                "@type": "Order",
                "name": "German Olympic Order",
                "description": "2nd class"
            },
            {
                "@type": "Order",
                "name": "French state's Gold Medal",
                "description": "for physical education"
            }
        ]
    },
    "occupations": {
        "career": [
            {
                "occupational_title": "Tailor",
                "workplace": "A F and Elna Ohlsson",
                "industry": "Tailoring",
                "start_date": null
            },
            {
                "occupational_title": "Head Clerk",
                "workplace": "Skånes General Agency",
                "industry": "Insurance",
                "start_date": "1919"
            },
            {
                "occupational_title": "Director",
                "workplace": "Skånes General Agency",
                "industry": "Insurance",
                "start_date": "1940"
            }
        ]
    }
}