{
    "original": "GUSTAFSSON, Nils Gustaf Albert, Tekn. Dr, Civilingenjör, Stockholm, f Södkpg 15/1 98 av överl Alb G o Hanna Fröling, gm Signe Lundberg. Studex Nrkpg 17, KTH 21, tekn dr 38. Ass o 1. ass i läran om förbränn.mot v KTH 23—25, ch Sv ackum.AB Jungners förgas- o filteravd samt bilprovn.anläggn 25— 36, konsult ing där 37—39, föreläsn Sthlms hantv.inst sed. 31, förest Sthlms tekn inst:s maskintekn fackavd m mot.tekn sed. 33, lär v Gen Motors nord AB sed. 35. Styr.led Sv teknol.frn 36—41, ordf i dess avd f mek 39— 41, exp i 37 års gasgen,komm, led gengas-nmdn, tekn ch stat bränslekommiss gengasbyrå sed. 39, led o sakk i ett flert komm. FI pat rör förgasare f förbränn.mot mm. Av trycket: Motorhandbok, Förbränn.motorer, Förg f autom.mot (IVA handl 150), Bilmot o mot.bränsle, red Tekn Tidskr avd Autom o mot.tekn, medarb Nord fam.bok, Bonniers konvers.lex, Nord fam.boks sportlex, ett 100-t art i fackämn.",
    "translated": "GUSTAFSSON, Nils Gustaf Albert, Ph.D., Civil Engineer, Stockholm, born in Söderköping on January 15, 1898, to Colonel Albert G and Hanna Fröling, married Signe Lundberg. Passed matriculation examination in Norrköping in 1917, graduated from KTH (Royal Institute of Technology) in 1921, obtained Ph.D. in 1938. Assistant and 1st assistant in the study of combustion engines at KTH from 1923 to 1925, head of accumulators and filters division at Sv ackumulator AB Jungner's carburetor and filter department, as well as automobile inspection facility from 1925 to 1936. Consultant engineer at Ing 1937-1939, lecturer at Stockholm Crafts Institute since 1931, head of Stockholm Technical Institute's mechanical engineering department specializing in combustion engines since 1933, teacher at General Motors Nord AB since 1935. Board member of the Swedish Society of Technology from 1936 to 1941, chairman of its mechanical department from 1939 to 1941, expert in the 1937 gas generator committee, member of the gasification board and technical chief of the fuel commission's gasification office since 1939, member and expert in several committees regarding carburetors for combustion engines, etc. Published works include: Motor Handbook, Combustion Engines, Carburetors for Automobile Engines (IVA Trade No. 150), Automotive Engines and Fuels, editor of the Automotive and Engine Technology division in Teknisk Tidskrift (Technical Journal), contributor to Nordisk Familjebok (Nordic Family Book), Bonniers Conversational Lexicon, and Nordisk Familjeboks Sportlexikon (Nordic Family Book's Sports Lexicon), author of over 100 articles in specialized subjects.",
    "structured": {
        "@context": "https://schema.org",
        "@type": "Person",
        "name": "Nils Gustaf Albert Gustafsson",
        "birthDate": "1898-01-15",
        "birthPlace": "Söderköping",
        "deathDate": "YYYY-MM-DD",
        "nationality": "Swedish",
        "education": [
            {
                "@type": "CollegeOrUniversity",
                "name": "KTH Royal Institute of Technology",
                "location": "Stockholm"
            }
        ],
        "alumniOf": [
            {
                "@type": "CollegeOrUniversity",
                "name": "Norrköping"
            }
        ],
        "affiliation": [
            {
                "@type": "Organization",
                "name": "Sv ackumulator AB Jungner",
                "position": "Head of Accumulators and Filters Division",
                "startDate": "1925",
                "endDate": "1936"
            },
            {
                "@type": "Organization",
                "name": "General Motors Nord AB",
                "position": "Teacher",
                "startDate": "1935"
            }
        ],
        "worksFor": [
            {
                "@type": "Organization",
                "name": "KTH Royal Institute of Technology",
                "position": "Assistant",
                "startDate": "1923",
                "endDate": "1925"
            },
            {
                "@type": "Organization",
                "name": "KTH Royal Institute of Technology",
                "position": "1st Assistant",
                "startDate": "1925",
                "endDate": "1936"
            },
            {
                "@type": "Organization",
                "name": "Ing",
                "position": "Consultant Engineer",
                "startDate": "1937",
                "endDate": "1939"
            },
            {
                "@type": "Organization",
                "name": "Stockholm Crafts Institute",
                "position": "Lecturer",
                "startDate": "1931"
            },
            {
                "@type": "Organization",
                "name": "Stockholm Technical Institute",
                "department": "Mechanical Engineering",
                "position": "Head",
                "startDate": "1933"
            },
            {
                "@type": "Organization",
                "name": "Swedish Society of Technology",
                "position": "Board Member",
                "startDate": "1936",
                "endDate": "1941"
            }
        ],
        "memberOf": [
            {
                "@type": "Organization",
                "name": "1937 Gas Generator Committee"
            },
            {
                "@type": "Organization",
                "name": "Gasification Board"
            },
            {
                "@type": "Organization",
                "name": "Fuel Commission's Gasification Office"
            }
        ],
        "author": [
            {
                "@type": "Book",
                "name": "Motor Handbook"
            },
            {
                "@type": "Book",
                "name": "Combustion Engines"
            },
            {
                "@type": "Book",
                "name": "Carburetors for Automobile Engines",
                "identifier": "IVA Trade No. 150"
            },
            {
                "@type": "Book",
                "name": "Automotive Engines and Fuels"
            }
        ],
        "editor": [
            {
                "@type": "Periodical",
                "name": "Teknisk Tidskrift",
                "division": "Automotive and Engine Technology"
            },
            {
                "@type": "Periodical",
                "name": "Nordisk Familjebok",
                "identifier": "Nordic Family Book"
            },
            {
                "@type": "Periodical",
                "name": "Bonniers Conversational Lexicon"
            },
            {
                "@type": "Periodical",
                "name": "Nordisk Familjeboks Sportlexikon",
                "identifier": "Nordic Family Book's Sports Lexicon"
            }
        ],
        "numberOfArticles": "100"
    },
    "occupations": {
        "career": [
            {
                "occupational_title": "Assistant",
                "workplace": "KTH",
                "industry": "Education",
                "start_date": "1923"
            },
            {
                "occupational_title": "First Assistant",
                "workplace": "KTH",
                "industry": "Education",
                "start_date": "1925"
            },
            {
                "occupational_title": "Head of Accumulators and Filters Division",
                "workplace": "Sv ackumulator AB Jungner",
                "industry": "Automotive",
                "start_date": "1925"
            },
            {
                "occupational_title": "Head of Automobile Inspection Facility",
                "workplace": "Sv ackumulator AB Jungner",
                "industry": "Automotive",
                "start_date": "1925"
            },
            {
                "occupational_title": "Consultant Engineer",
                "workplace": "Ing",
                "industry": "Engineering",
                "start_date": "1937"
            },
            {
                "occupational_title": "Lecturer",
                "workplace": "Stockholm Crafts Institute",
                "industry": "Education",
                "start_date": "1931"
            },
            {
                "occupational_title": "Head of Mechanical Engineering Department (specializing in combustion engines)",
                "workplace": "Stockholm Technical Institute",
                "industry": "Education",
                "start_date": "1933"
            },
            {
                "occupational_title": "Teacher",
                "workplace": "General Motors Nord AB",
                "industry": "Automotive",
                "start_date": "1935"
            },
            {
                "occupational_title": "Board Member",
                "workplace": "Swedish Society of Technology",
                "industry": "Technology",
                "start_date": "1936"
            },
            {
                "occupational_title": "Chairman of Mechanical Department",
                "workplace": "Swedish Society of Technology",
                "industry": "Technology",
                "start_date": "1939"
            },
            {
                "occupational_title": "Expert",
                "workplace": "Gas Generator Committee",
                "industry": "Technology",
                "start_date": "1937"
            },
            {
                "occupational_title": "Member and Expert",
                "workplace": "Gasification Board",
                "industry": "Technology",
                "start_date": "1939"
            },
            {
                "occupational_title": "Technical Chief",
                "workplace": "Fuel Commission's Gasification Office",
                "industry": "Technology",
                "start_date": "1939"
            }
        ]
    }
}