{
    "original": "EKESIÖÖ, Karl Johan Erik, Direktör, Stockholm, f Eklångens gård, Sörml, 19/8 83 av godsäg J A E o Amanda Johansson, gm Eva Brunfors. Eft avsl stud v bl a Tekn sk i Etuna 97—00 prakt i skogs- o trävarubr 01—06. Bokh o förv Nynäs gods 06—09. Startade 09 Trävarufirman Ekesiöö &amp; Blom, 18 ändrad till Trävarufirman Karl Ekesiöö, 22 ombildad till AB och övertog Högelin &amp; Seippels brädgård i Sthlm; en av Sthlms största ni 4 försäljn.brädg, huvuduppl i Frihamnen o huv.brädg m såg o hyvl v Albano: vkst dir där sed. 22. Ag Skogshyddan, Ti* ringe, Sörml. Led Sthlms Trävaruhdlsfrr ordf ds priskté sed. fi år, styr.led Sthlms Byggnadsleverantörfrb, deleg ktén f utarb av lev.best f byggn.virke i ktén f byggstandardi-seringen o d :o f spec.best t sorter.regl f såg o hyvl trav mfl uppdr. Resor: Tyskl, Danm 10, Danm, Norge 26—37, Tyskl, Danm 38. RVO, Sthlms Skyttefrb ftjGM; Odd Fellow, Sthlms Byggn.frn, KAK.",
    "translated": "EKESIÖÖ, Karl Johan Erik, Director, Stockholm, born at Eklångens gård, Sörml, on August 19, 1883, to landowner J A E and Amanda Johansson, married to Eva Brunfors. After completing studies at various technical schools, including Tekn sk in Etuna from 1897 to 1900, he gained practical experience in the forestry and timber industry from 1901 to 1906. He worked as a bookkeeper and manager at Nynäs estate from 1906 to 1909. In 1909, he founded the timber firm Ekesiöö & Blom, which was later renamed Karl Ekesiöö Timber Firm in 1918. In 1922, the company became a joint-stock company and acquired Högelin & Seippels sawmill in Stockholm. It became one of the largest timber trading companies in Stockholm, with its main office in the Free Port and a main sawmill and planing mill in Albano. He served as the company's managing director from then on. He also served as a director of Skogshyddan, a timber company in Ti*ringe, Sörmland. He was a member of the board of directors and chairman of the pricing committee of Stockholm Timber Merchants' Association for several years. He also served on the board of directors of Stockholm Building Suppliers' Association and participated in the committees responsible for developing timber supply standards and specific regulations for sawing and planing techniques. He undertook trips to Germany and Denmark in 1910, Denmark and Norway from 1926 to 1937, and Germany and Denmark in 1938. He received the Royal Order of Vasa (RVO) and was honored by Stockholm Shooting Association. He was a member of the Odd Fellows, Stockholm Building Association, and the Royal Automobile Club (KAK).",
    "structured": {
        "@context": "http://schema.org",
        "@type": "Person",
        "name": "Karl Johan Erik Ekesiöö",
        "jobTitle": "Director",
        "birthDate": "1883-08-19",
        "birthPlace": "Eklångens gård, Sörml",
        "parents": [
            {
                "@type": "Person",
                "name": "J A E",
                "jobTitle": "Landowner"
            },
            {
                "@type": "Person",
                "name": "Amanda Johansson"
            }
        ],
        "spouse": {
            "@type": "Person",
            "name": "Eva Brunfors"
        },
        "education": [
            {
                "@type": "EducationalOccupationalCredential",
                "educationLevel": "Technical school",
                "alumniOf": "Tekn sk, Etuna",
                "startDate": "1897",
                "endDate": "1900"
            }
        ],
        "workExperience": [
            {
                "@type": "Occupation",
                "title": "Forestry and Timber Industry",
                "startDate": "1901",
                "endDate": "1906"
            },
            {
                "@type": "Occupation",
                "title": "Bookkeeper and Manager",
                "employer": "Nynäs estate",
                "startDate": "1906",
                "endDate": "1909"
            },
            {
                "@type": "OrganizationRole",
                "roleName": "Founder",
                "startDate": "1909",
                "endDate": "1918",
                "organization": {
                    "@type": "Organization",
                    "name": "Ekesiöö & Blom",
                    "alternateName": "Karl Ekesiöö Timber Firm"
                }
            },
            {
                "@type": "OrganizationRole",
                "roleName": "Managing Director",
                "startDate": "1918",
                "endDate": "1922",
                "organization": {
                    "@type": "Organization",
                    "name": "Karl Ekesiöö Timber Firm",
                    "alternateName": "AB"
                }
            },
            {
                "@type": "OrganizationRole",
                "roleName": "Managing Director",
                "startDate": "1922",
                "organization": {
                    "@type": "Organization",
                    "name": "Karl Ekesiöö Timber Firm",
                    "alternateName": "AB"
                },
                "subOrganization": {
                    "@type": "Organization",
                    "name": "Högelin & Seippels brädgård",
                    "address": {
                        "@type": "PostalAddress",
                        "addressLocality": "Stockholm"
                    }
                }
            },
            {
                "@type": "OrganizationRole",
                "roleName": "Managing Director",
                "startDate": "1922",
                "organization": {
                    "@type": "Organization",
                    "name": "Albano",
                    "address": {
                        "@type": "PostalAddress",
                        "addressLocality": "Stockholm"
                    }
                },
                "subOrganization": {
                    "@type": "Organization",
                    "name": "Karl Ekesiöö Timber Firm",
                    "alternateName": "AB"
                }
            },
            {
                "@type": "OrganizationRole",
                "roleName": "Director",
                "startDate": "1922",
                "endDate": "Present",
                "organization": {
                    "@type": "Organization",
                    "name": "Ag Skogshyddan",
                    "address": {
                        "@type": "PostalAddress",
                        "addressLocality": "Ti*ringe, Sörmland"
                    }
                }
            },
            {
                "@type": "OrganizationRole",
                "roleName": "Chairman",
                "startDate": "Unknown",
                "organization": {
                    "@type": "Organization",
                    "name": "Sthlms Trävaruhdlsfrr"
                }
            },
            {
                "@type": "OrganizationRole",
                "roleName": "Member",
                "startDate": "Unknown",
                "organization": {
                    "@type": "Organization",
                    "name": "Sthlms Byggnadsleverantörfrb"
                }
            }
        ],
        "memberOf": [
            {
                "@type": "Organization",
                "name": "Stockholm Timber Merchants' Association"
            },
            {
                "@type": "Organization",
                "name": "Stockholm Building Suppliers' Association"
            }
        ],
        "honorificSuffix": "RVO",
        "sameAs": [
            {
                "@type": "Organization",
                "name": "Stockholm Shooting Association"
            },
            {
                "@type": "Organization",
                "name": "Odd Fellow"
            },
            {
                "@type": "Organization",
                "name": "Stockholm Building Association"
            },
            {
                "@type": "Organization",
                "name": "Royal Automobile Club (KAK)"
            }
        ],
        "hasOccupation": [
            {
                "@type": "Occupation",
                "name": "Bookkeeper"
            },
            {
                "@type": "Occupation",
                "name": "Manager"
            }
        ],
        "hasTravelExperience": [
            {
                "@type": "Place",
                "name": "Germany"
            },
            {
                "@type": "Place",
                "name": "Denmark"
            },
            {
                "@type": "Place",
                "name": "Norway"
            }
        ]
    },
    "occupations": {
        "career": [
            {
                "occupational_title": "Director",
                "workplace": "Stockholm",
                "industry": "",
                "start_date": ""
            },
            {
                "occupational_title": "Practical experience in forestry and timber industry",
                "workplace": "",
                "industry": "Forestry and timber",
                "start_date": "1901"
            },
            {
                "occupational_title": "Bookkeeper and manager",
                "workplace": "Nynäs estate",
                "industry": "",
                "start_date": "1906"
            },
            {
                "occupational_title": "Founder of Ekesiöö & Blom (later Karl Ekesiöö Timber Firm)",
                "workplace": "Stockholm",
                "industry": "Timber trading",
                "start_date": "1909"
            },
            {
                "occupational_title": "Managing director",
                "workplace": "",
                "industry": "",
                "start_date": "1922"
            }
        ]
    }
}