{
    "original": "HEDBERG, Hans Emanuel, Kapten, Saltsjö-Duvnäs, f Örnsköldsvik 14/4 05 av adv K G H o Annie Öhman, gm Marga Wester-dahl. Studex Hsand 24, sjöoffex 27, flygsk Ljungbyhed 30—31, KSHS 33—34. Fänr 27, ulöjtn 29, löjtn 30, kapt 39. Bitr dir AB Stille-Werner, Sthlm. Resor: Tyskl, Holl, Belg, Frankr, Span, Port, Nord-, Väst- o Sydafr, Egypt, Grekl, Ital, Engl, Balticum mfl. Frimurare, KAK, KSAK, KSSS mfl. Hobbies: Jakt, fiske, fäktning, tennis.",
    "translated": "HEDBERG, Hans Emanuel, Captain, Saltsjö-Duvnäs, born in Örnsköldsvik on April 14, 1905, son of lawyer K G H and Annie Öhman, married to Marga Westerdahl. He graduated from Handelsflottans Sjöfartsskola (Merchant Navy Maritime School) in 1924, became a naval officer in 1927, and trained as a pilot at Ljungbyhed Air Force Base from 1930 to 1931. He attended the Royal Swedish Naval Staff College from 1933 to 1934. He was promoted to Second Lieutenant in 1927, First Lieutenant in 1929, and Captain in 1939. He served as a deputy director at AB Stille-Werner in Stockholm. He has traveled to Germany, the Netherlands, Belgium, France, Spain, Portugal, the Nordic countries, West and South Africa, Egypt, Greece, Italy, England, the Baltics, and other places. He is a Freemason and a member of Kungliga Automobilklubben (The Royal Automobile Club), Kungliga Svenska Aero-Klubben (The Royal Swedish Aero Club), Kungliga Svenska Segel-Sällskapet (The Royal Swedish Yacht Club), and others. His hobbies include hunting, fishing, fencing, and tennis.",
    "structured": {
        "@context": "https://schema.org",
        "@type": "Person",
        "name": "Hans Emanuel Hedberg",
        "birthDate": "1905-04-14",
        "birthPlace": "Örnsköldsvik",
        "description": "Captain, Saltsjö-Duvnäs",
        "parent": [
            {
                "name": "K G H",
                "jobTitle": "Lawyer"
            },
            {
                "name": "Annie Öhman"
            }
        ],
        "spouse": [
            {
                "@type": "Person",
                "name": "Marga Westerdahl"
            }
        ],
        "education": [
            {
                "@type": "EducationalOccupationalCredential",
                "credentialCategory": "Degree",
                "name": "Handelsflottans Sjöfartsskola",
                "startDate": "1924"
            },
            {
                "@type": "EducationalOccupationalCredential",
                "credentialCategory": "Degree",
                "name": "Ljungbyhed Air Force Base",
                "startDate": "1930",
                "endDate": "1931"
            },
            {
                "@type": "EducationalOccupationalCredential",
                "credentialCategory": "Degree",
                "name": "Royal Swedish Naval Staff College",
                "startDate": "1933",
                "endDate": "1934"
            }
        ],
        "jobTitle": "Captain",
        "worksFor": {
            "@type": "Organization",
            "name": "AB Stille-Werner"
        },
        "membership": [
            {
                "@type": "Organization",
                "name": "Freemasonry"
            },
            {
                "@type": "Organization",
                "name": "Kungliga Automobilklubben"
            },
            {
                "@type": "Organization",
                "name": "Kungliga Svenska Aero-Klubben"
            },
            {
                "@type": "Organization",
                "name": "Kungliga Svenska Segel-Sällskapet"
            }
        ],
        "hobbies": [
            "Hunting",
            "Fishing",
            "Fencing",
            "Tennis"
        ],
        "birthCountry": "Sweden",
        "nationality": "Swedish",
        "sameAs": {
            "@type": "URL",
            "url": "https://example.com/hans-emanuel-hedberg"
        },
        "hasOfferCatalog": {
            "@type": "OfferCatalog",
            "name": "Travel Destinations",
            "itemListElement": [
                {
                    "@type": "Offer",
                    "name": "Germany"
                },
                {
                    "@type": "Offer",
                    "name": "Netherlands"
                },
                {
                    "@type": "Offer",
                    "name": "Belgium"
                },
                {
                    "@type": "Offer",
                    "name": "France"
                },
                {
                    "@type": "Offer",
                    "name": "Spain"
                },
                {
                    "@type": "Offer",
                    "name": "Portugal"
                },
                {
                    "@type": "Offer",
                    "name": "Nordic Countries"
                },
                {
                    "@type": "Offer",
                    "name": "South Africa"
                },
                {
                    "@type": "Offer",
                    "name": "West Africa"
                },
                {
                    "@type": "Offer",
                    "name": "Egypt"
                },
                {
                    "@type": "Offer",
                    "name": "Greece"
                },
                {
                    "@type": "Offer",
                    "name": "Italy"
                },
                {
                    "@type": "Offer",
                    "name": "England"
                },
                {
                    "@type": "Offer",
                    "name": "Baltic Countries"
                }
            ]
        }
    },
    "occupations": {
        "career": [
            {
                "occupational_title": "Captain",
                "workplace": "Saltsjö-Duvnäs",
                "industry": "Merchant Navy",
                "start_date": "1924"
            },
            {
                "occupational_title": "Naval Officer",
                "workplace": "Royal Swedish Navy",
                "industry": "Military",
                "start_date": "1927"
            },
            {
                "occupational_title": "Pilot",
                "workplace": "Ljungbyhed Air Force Base",
                "industry": "Military",
                "start_date": "1930"
            },
            {
                "occupational_title": "Deputy Director",
                "workplace": "AB Stille-Werner",
                "industry": "Unknown",
                "start_date": "Unknown"
            }
        ]
    }
}