{
    "original": "GENBERG, Erik Waldemar, Civilingenjör, Norrköping, f Solna, Sthlms l, 22/9 99 av överste K A G o Gerda Högman, gm Maria Heist. Studex Kristianstad 17, KTH (kemi) 19—23. Resoffex 19, fänr i Vendes art.reg:s res 19, ulöjtn 21, löjtn 23, kapt 40. Prakt v St Kopparb Bergsl AB :s cellulosafabr Skutskär 23—24, driftsing v Sv Oljeslageri AB Henriksdal 24—25, v Rudolph Jacobssons kem fabr 26—27, färgeritekn utbildn Danm o Tyskl samt anst v AB Lundby Skönfärgeri o Kem Tvättanst 27—28, driftsing v AB Fören Yllefabr :a Norrkp 28—34, stud spektroskopi, färgmätn mm v univ Jena 32, övering o drifts-ch v Holmens Bruks- &amp; Fabr AB :s bomullsavd Norrkp sed. 34. Styr.led i Norrkps kommunala mellansk o h folksk. Led av luftskyddsnmdn. Sekr i Norrkps Luftv.frn. Led Sv Tekn.frn. Av trycket: Tvättn.system f sulfatmassa (Sv Papperstidn 24), Extraktionsförsök m bituminösa avlagringar fr Höganäs (IVA:s handl 25), Om färgblandning (Polhemsskr 29, publ 1 Tekn Tidskr 30), Substantivität u Färbe-theorie (Melliands Textilberichte 31), Textilindis kem hjälpprodukter (Färgeritekn 32), Bestimmung der Luftfeuchtigkeit mit dem Psychrometer (Gerlands Beiträge zur Geophy-sik 32), Some complementary colour relations (Proc Phys Soc 33), Det trikromatiska färgsystemets huvuddrag (Tekn Tidskr 33), Ekon verkn.grad (ibid 36). Resor: Finl, Tyskl, Österr, Schweiz, Jugoslav, Engl, Frankr, Belg, Holl 30—38. Hobby: Botanik.",
    "translated": "GENBERG, Erik Waldemar, Civil Engineer, Norrköping, b. in Solna, Stockholm County, on September 22, 1899, son of Colonel K A G and Gerda Högman, married to Maria Heist. Graduated from Kristianstad at 17, studied chemistry at the Royal Institute of Technology (KTH) from 1919 to 1923. Commissioned officer in 1919, second lieutenant in Vendes Artillery Regiment's reserve in 1921, lieutenant in 1923, captain in 1940. Worked practically for Stora Kopparberg Bergslagen AB's cellulose factory in Skutskär from 1923 to 1924, as a manager at the Swedish Oil Mill in Henriksdal from 1924 to 1925, at Rudolph Jacobsson's chemical factory from 1926 to 1927, received training in dye technology in Denmark and Germany, and worked for AB Lundby Skönfärgeri and Kem Tvättanst from 1927 to 1928. Then served as a manager at AB Fören Yllefabriks in Norrköping from 1928 to 1934, studied spectroscopy, color measurement, and more at the University of Jena in 1932, and became superintendent and operations manager at Holmens Bruks- & Fabriks AB's cotton department in Norrköping from 1934 onwards. Served on the board of directors of the municipal intermediate and primary schools in Norrköping, and was a member of the air defense council. Secretary of the Norrköping Air Force Association and a member of the Swedish Technical Society. His written works include: \"Washing system for sulfate pulp\" (published in the Swedish Paper Journal in 1924), \"Extraction experiments with bituminous deposits from Höganäs\" (published in the Proceedings of the Royal Swedish Academy of Engineering Sciences in 1925), \"On color mixing\" (published in Polhems Review in 1929 and in the Technical Journal in 1930), \"Substantivity and color theory\" (published in Melliand's Textile Reports in 1931), \"Chemical auxiliary products for the textile industry\" (published in Dye Technology in 1932), \"Determination of air humidity with a psychrometer\" (published in Gerland's Contributions to Geophysics in 1932), \"Some complementary color relations\" (published in the Proceedings of the Physical Society in 1933), \"The main features of the trichromatic color system\" (published in the Technical Journal in 1933), \"Economic efficiency\" (published in the same journal in 1936). Traveled to Finland, Germany, Austria, Switzerland, Yugoslavia, England, France, Belgium, and the Netherlands from 1930 to 1938. Hobby: Botany.",
    "structured": {
        "@context": "https://schema.org",
        "@type": "Person",
        "name": "Erik Waldemar Genberg",
        "givenName": "Erik Waldemar",
        "familyName": "Genberg",
        "birthDate": "1899-09-22",
        "birthPlace": {
            "@type": "Place",
            "address": {
                "@type": "PostalAddress",
                "addressLocality": "Solna",
                "addressRegion": "Stockholm County"
            }
        },
        "description": "Civil Engineer",
        "spouse": {
            "@type": "Person",
            "name": "Maria Heist"
        },
        "parents": [
            {
                "@type": "Person",
                "name": "Colonel K A G"
            },
            {
                "@type": "Person",
                "name": "Gerda Högman"
            }
        ],
        "education": {
            "@type": "EducationalOccupationalCredential",
            "credentialCategory": "Bachelor's Degree",
            "educationalLevel": "Undergraduate",
            "alumniOf": [
                {
                    "@type": "EducationalOrganization",
                    "name": "Kristianstad",
                    "endDate": "1917"
                },
                {
                    "@type": "EducationalOrganization",
                    "name": "Royal Institute of Technology (KTH)",
                    "mainEntityOfPage": "https://www.kth.se/",
                    "startDate": "1919",
                    "endDate": "1923",
                    "hasCourse": [
                        {
                            "@type": "Course",
                            "name": "Chemistry"
                        }
                    ]
                }
            ]
        },
        "worksFor": [
            {
                "@type": "Organization",
                "name": "Stora Kopparberg Bergslagen AB",
                "department": "Cellulose Factory",
                "startDate": "1923",
                "endDate": "1924",
                "location": {
                    "@type": "Place",
                    "address": {
                        "@type": "PostalAddress",
                        "addressLocality": "Skutskär"
                    }
                }
            },
            {
                "@type": "Organization",
                "name": "Swedish Oil Mill",
                "jobTitle": "Manager",
                "startDate": "1924",
                "endDate": "1925",
                "location": {
                    "@type": "Place",
                    "address": {
                        "@type": "PostalAddress",
                        "addressLocality": "Henriksdal"
                    }
                }
            },
            {
                "@type": "Organization",
                "name": "Rudolph Jacobsson's Chemical Factory",
                "jobTitle": "Manager",
                "startDate": "1926",
                "endDate": "1927"
            },
            {
                "@type": "Organization",
                "name": "AB Lundby Skönfärgeri",
                "jobTitle": "Employee",
                "startDate": "1927",
                "endDate": "1928"
            },
            {
                "@type": "Organization",
                "name": "AB Fören Yllefabriks",
                "jobTitle": "Manager",
                "startDate": "1928",
                "endDate": "1934",
                "location": {
                    "@type": "Place",
                    "address": {
                        "@type": "PostalAddress",
                        "addressLocality": "Norrköping"
                    }
                }
            },
            {
                "@type": "Organization",
                "name": "Holmens Bruks- & Fabriks AB",
                "department": "Cotton Department",
                "jobTitle": "Superintendent and Operations Manager",
                "startDate": "1934"
            }
        ],
        "memberOf": [
            {
                "@type": "Organization",
                "name": "Norrköping Air Force Association",
                "roleName": "Secretary"
            },
            {
                "@type": "Organization",
                "name": "Swedish Technical Society",
                "roleName": "Member"
            }
        ],
        "boardMember": [
            {
                "@type": "Organization",
                "name": "Municipal Intermediate Schools of Norrköping"
            },
            {
                "@type": "Organization",
                "name": "Municipal Primary Schools of Norrköping"
            }
        ],
        "worksWritten": [
            {
                "@type": "Article",
                "headline": "Washing system for sulfate pulp",
                "workExample": "Swedish Paper Journal, 1924"
            },
            {
                "@type": "Article",
                "headline": "Extraction experiments with bituminous deposits from Höganäs",
                "workExample": "Proceedings of the Royal Swedish Academy of Engineering Sciences, 1925"
            },
            {
                "@type": "Article",
                "headline": "On color mixing",
                "workExample": [
                    "Polhems Review, 1929",
                    "Technical Journal, 1930"
                ]
            },
            {
                "@type": "Article",
                "headline": "Substantivity and color theory",
                "workExample": "Melliand's Textile Reports, 1931"
            },
            {
                "@type": "Article",
                "headline": "Chemical auxiliary products for the textile industry",
                "workExample": "Dye Technology, 1932"
            },
            {
                "@type": "Article",
                "headline": "Determination of air humidity with a psychrometer",
                "workExample": "Gerland's Contributions to Geophysics, 1932"
            },
            {
                "@type": "Article",
                "headline": "Some complementary color relations",
                "workExample": "Proceedings of the Physical Society, 1933"
            },
            {
                "@type": "Article",
                "headline": "The main features of the trichromatic color system",
                "workExample": "Technical Journal, 1933"
            },
            {
                "@type": "Article",
                "headline": "Economic efficiency",
                "workExample": "Technical Journal, 1936"
            }
        ],
        "travelled": [
            "Finland",
            "Germany",
            "Austria",
            "Switzerland",
            "Yugoslavia",
            "England",
            "France",
            "Belgium",
            "Netherlands"
        ],
        "hobbies": [
            "Botany"
        ]
    },
    "occupations": {
        "career": [
            {
                "occupational_title": "Civil Engineer",
                "workplace": "Norrköping",
                "industry": "Engineering",
                "start_date": "1923"
            },
            {
                "occupational_title": "Practical Worker",
                "workplace": "Stora Kopparberg Bergslagen AB's cellulose factory",
                "industry": "Cellulose production",
                "start_date": "1923"
            },
            {
                "occupational_title": "Manager",
                "workplace": "Swedish Oil Mill",
                "industry": "Oil production",
                "start_date": "1924"
            },
            {
                "occupational_title": "Manager",
                "workplace": "Rudolph Jacobsson's chemical factory",
                "industry": "Chemical production",
                "start_date": "1926"
            },
            {
                "occupational_title": "Employee",
                "workplace": "AB Lundby Skönfärgeri and Kem Tvättanst",
                "industry": "Textile industry",
                "start_date": "1927"
            },
            {
                "occupational_title": "Manager",
                "workplace": "AB Fören Yllefabriks",
                "industry": "Textile industry",
                "start_date": "1928"
            },
            {
                "occupational_title": "Superintendent and Operations Manager",
                "workplace": "Holmens Bruks- & Fabriks AB's cotton department",
                "industry": "Textile industry",
                "start_date": "1934"
            }
        ]
    }
}