{
    "original": "OLSSÖN, Kobert Alexis, Direktör, Malmö, f Mmö 21/3 79 av restauratör O O o Franzisca Bose, gm Hanna Högfeldt. Malmö hal, priv underv i ty spr. Anst fma Thomée &amp; Co 95, vkst dir där 18, etabl sped.fma Robert A Olsson &amp; Co 21, omb denna t AB 22, driv av h disrör i mindre omf, vkst dir o styr.led AB Becks imp, Hdls- &amp; red.AB Toca, fastigh.AB Abro. Resor: Tyskl, Danm, Holl, Belg v öl tillf. Frimurare (IX), Odd Fellow (veter o mångår tjm), DruidO, PB, Skånefrn 79 års män (skattm), ProPGM, Dansk ftjGM. Hobbies: Teater, musik, resor, mitt arbete.",
    "translated": "OLSSÖN, Kobert Alexis, Director, Malmö, b. MMö (Malmö) 21/3 1879, son of restaurateur O O and Franzisca Bose, married to Hanna Högfeldt. Malmö High School, privately taught German. Employed by Thomée & Co in 1895, promoted to director in 1918, established forwarding company Robert A Olsson & Co in 1921, agent for this company in AB (Aktiebolaget) 22, operated as district manager in a smaller capacity, grew as director and board member of AB Becks Import, Commercial and Editorial Manager of AB Toca, real estate company AB Abro. Traveled to Germany, Denmark, the Netherlands, Belgium for beer occasions. Freemason (IX), Odd Fellow (veteran and long-serving member), Druid Order, PB (Unknown abbreviation), Skånefrån (tax collector) for men of the year 1879, District Grand Master (fraternity title), Danish Foreign Trade Grand Master. Hobbies include theater, music, travel, and my work. \n\nNote: The abbreviation \"v\" is used to represent \"från\" meaning from in Swedish, and the abbreviation \"gm\" means married.",
    "structured": {
        "@context": "https://schema.org",
        "@type": "Person",
        "givenName": "Kobert",
        "additionalName": "Alexis",
        "familyName": "Olssön",
        "jobTitle": "Director",
        "address": {
            "@type": "PostalAddress",
            "addressLocality": "Malmö"
        },
        "birthDate": "1879-03-21",
        "parent": [
            {
                "@type": "Person",
                "name": "O O Olssön",
                "jobTitle": "Restaurateur"
            },
            {
                "@type": "Person",
                "name": "Franzisca Bose"
            }
        ],
        "spouse": {
            "@type": "Person",
            "name": "Hanna Högfeldt"
        },
        "education": {
            "@type": "EducationalOrganization",
            "name": "Malmö High School"
        },
        "knowsLanguage": [
            {
                "@type": "Language",
                "name": "German"
            }
        ],
        "work": [
            {
                "@type": "Organization",
                "name": "Thomée & Co",
                "startDate": "1895-01-01",
                "endDate": "1918-01-01",
                "jobTitle": "Employee"
            },
            {
                "@type": "Organization",
                "name": "Robert A Olsson & Co",
                "startDate": "1921-01-01",
                "jobTitle": "Established forwarding company"
            },
            {
                "@type": "Organization",
                "name": "AB",
                "jobTitle": "Agent"
            },
            {
                "@type": "Organization",
                "name": "AB Becks Import",
                "jobTitle": "Director and Board Member"
            },
            {
                "@type": "Organization",
                "name": "AB Toca",
                "jobTitle": "Commercial and Editorial Manager"
            },
            {
                "@type": "Organization",
                "name": "AB Abro",
                "jobTitle": "Real Estate Company"
            }
        ],
        "memberOf": [
            {
                "@type": "Organization",
                "name": "Freemasons",
                "startDate": "Unknown",
                "roleName": "IX"
            },
            {
                "@type": "Organization",
                "name": "Odd Fellow",
                "roleName": "Veteran and long-serving member"
            },
            {
                "@type": "Organization",
                "name": "Druid Order"
            },
            {
                "@type": "Organization",
                "name": "PB"
            },
            {
                "@type": "Organization",
                "name": "Skånefrån",
                "startDate": "Unknown",
                "roleName": "Tax collector for men of the year 1879"
            },
            {
                "@type": "Organization",
                "name": "District Grand Master",
                "roleName": "Danish Foreign Trade Grand Master"
            }
        ],
        "hobbies": [
            "Theater",
            "Music",
            "Travel",
            "Work"
        ]
    },
    "occupations": {
        "career": [
            {
                "occupational_title": "Employee",
                "workplace": "Thomée & Co",
                "industry": "Unknown",
                "start_date": "1895"
            },
            {
                "occupational_title": "Director",
                "workplace": "Thomée & Co",
                "industry": "Unknown",
                "start_date": "1918"
            },
            {
                "occupational_title": "Established forwarding company owner",
                "workplace": "Robert A Olsson & Co",
                "industry": "Unknown",
                "start_date": "1921"
            },
            {
                "occupational_title": "Agent",
                "workplace": "AB (Aktiebolaget)",
                "industry": "Unknown",
                "start_date": "1922"
            },
            {
                "occupational_title": "District manager",
                "workplace": "Unknown",
                "industry": "Unknown",
                "start_date": "Unknown"
            },
            {
                "occupational_title": "Director and board member",
                "workplace": "AB Becks Import",
                "industry": "Unknown",
                "start_date": "Unknown"
            },
            {
                "occupational_title": "Commercial and Editorial Manager",
                "workplace": "AB Toca",
                "industry": "Unknown",
                "start_date": "Unknown"
            },
            {
                "occupational_title": "Real estate company AB Abro",
                "workplace": "Unknown",
                "industry": "Unknown",
                "start_date": "Unknown"
            }
        ]
    }
}