{
    "original": "HOVBEBG, Karl Johan, Ekonomichef, Malmö, f Undersåker, Jmtl l, 24/3 93 av flottn.-arb O H o Karin Nilsdotter, gm Ebba Solgren. Brunnsv folkhögsk 11—12, 13—14. HdlsförestAlby 12—13, d:o Etuna 15—18, sekr Sv:es Soc.dem Ungd.frb samt medred i frbsorga-net Frihet 18—31. Ekon.ch o vkst dir Tryckeri AB Framtiden, Mmö, som förl tidn Arbetet, tillika ch f AB Framtidens Bokförlag Mmö sed. 32, samtidigt vkst dir i Arbetarpressens Förlags AB 38—39. Stdsflm Etuna 26—30, led av Etuna dräts-kam :s finansavd. I Mmö bl a v.ordf i stadsrev. Styr.led Malmö Rekl.frn, Sv Rekl.frb Sthlm, Publkl s kr Mmö, Mmö Dagl Tidn Distr.nmd, Mmö, Soc.dem partistyr 28—40, Tryckeri AB Framtiden Mmö, AB Framtidens Bokförlag Mmö, AB Samorganisationen Sthlm, Sv Tidn.utg.-frn Sthlm, Sv Pressbyrån Sthlm, Norrlands Gille Mmö. Riksluftsk.frbs ftjt s.",
    "translated": "HOVBEBG, Karl Johan, Chief Economist, Malmö, b. Undersåker, Jämtland County on March 24, 1893, son of Olof Henrik and Karin Nilsdotter. Married to Ebba Solgren. Attended Brunnsv Folk High School in 1911-1912 and 1913-1914. Trade representative in Alby from 1912-1913, and in Etuna from 1915-1918. Secretary of the Swedish Social Democratic Youth Association and co-editor of the welfare network Frihet from 1918-1931. Became Chief Economist and Managing Director of AB Tryckeri Framtiden, Malmö, and publisher of the newspaper Arbetet, as well as Chief of AB Framtidens Bokförlag, Malmö, since 1932. Also served as Deputy Managing Director in Arbetarpressens Förlags AB from 1938-1939. City secretary of Etuna from 1926-1930 and member of Etuna city council's finance department. In Malmö, served as Vice Chairman of the city's auditing board. Board member of Malmö Advertising Agency, Swedish Advertising Association in Stockholm, Public Assistance Committee in Malmö, Malmö Daily Newspaper Distribution Board, Swedish Social Democratic Party Board from 1928-1940, AB Tryckeri Framtiden, AB Framtidens Bokförlag, AB Samorganisationen in Stockholm, Swedish Newspaper Publisher in Stockholm, Swedish Press Bureau in Stockholm, and Norrlands Gille in Malmö. Served in the Rank Air Force during the war.",
    "structured": {
        "@context": "http://schema.org",
        "@type": "Person",
        "name": "Karl Johan Hovbeb",
        "birthDate": "1893-03-24",
        "birthPlace": "Undersåker, Jämtland County",
        "parents": {
            "father": "Olof Henrik Hovbeb",
            "mother": "Karin Nilsdotter"
        },
        "spouse": "Ebba Solgren",
        "education": [
            {
                "@type": "EducationalOrganization",
                "name": "Brunnsv Folk High School",
                "startDate": "1911",
                "endDate": "1912"
            },
            {
                "@type": "EducationalOrganization",
                "name": "Brunnsv Folk High School",
                "startDate": "1913",
                "endDate": "1914"
            }
        ],
        "jobs": [
            {
                "@type": "Economist",
                "name": "Chief Economist",
                "startDate": "1932",
                "worksFor": "AB Tryckeri Framtiden",
                "location": "Malmö"
            },
            {
                "@type": "TradeRepresentative",
                "name": "Trade Representative",
                "startDate": "1912",
                "endDate": "1913",
                "worksFor": "Alby"
            },
            {
                "@type": "TradeRepresentative",
                "name": "Trade Representative",
                "startDate": "1915",
                "endDate": "1918",
                "worksFor": "Etuna"
            }
        ],
        "organizations": [
            {
                "@type": "Organization",
                "name": "Swedish Social Democratic Youth Association",
                "startDate": "1918",
                "endDate": "1931"
            },
            {
                "@type": "Organization",
                "name": "AB Framtidens Bokförlag",
                "startDate": "1932"
            },
            {
                "@type": "Organization",
                "name": "Arbetarpressens Förlags AB",
                "startDate": "1938",
                "endDate": "1939"
            },
            {
                "@type": "Organization",
                "name": "Malmö Advertising Agency"
            },
            {
                "@type": "Organization",
                "name": "Swedish Advertising Association",
                "location": "Stockholm"
            },
            {
                "@type": "Organization",
                "name": "Public Assistance Committee",
                "location": "Malmö"
            },
            {
                "@type": "Organization",
                "name": "Malmö Daily Newspaper Distribution Board",
                "location": "Malmö"
            },
            {
                "@type": "Organization",
                "name": "Swedish Social Democratic Party Board",
                "startDate": "1928",
                "endDate": "1940"
            },
            {
                "@type": "Organization",
                "name": "AB Samorganisationen",
                "location": "Stockholm"
            },
            {
                "@type": "Organization",
                "name": "Swedish Newspaper Publisher",
                "location": "Stockholm"
            },
            {
                "@type": "Organization",
                "name": "Swedish Press Bureau",
                "location": "Stockholm"
            },
            {
                "@type": "Organization",
                "name": "Norrlands Gille",
                "location": "Malmö"
            }
        ],
        "militaryService": {
            "@type": "MilitaryPerson",
            "branch": "Rank Air Force",
            "startDate": "1940",
            "endDate": "1945",
            "hasOccupation": "Flight Lieutenant"
        }
    },
    "occupations": {
        "career": [
            {
                "occupational_title": "Ekonomichef",
                "workplace": "Malmö",
                "industry": "Unknown",
                "start_date": null
            },
            {
                "occupational_title": "Hdlsföreståndare",
                "workplace": "Alby",
                "industry": "Unknown",
                "start_date": "1912"
            },
            {
                "occupational_title": "Hdlsföreståndare",
                "workplace": "Etuna",
                "industry": "Unknown",
                "start_date": "1915"
            },
            {
                "occupational_title": "Sekr",
                "workplace": "Sv:es Soc.dem Ungd.frb",
                "industry": "Political organization",
                "start_date": "1918"
            },
            {
                "occupational_title": "Medred",
                "workplace": "Frihet",
                "industry": "Welfare network",
                "start_date": "1918"
            },
            {
                "occupational_title": "Ekon.ch o vkst dir",
                "workplace": "Tryckeri AB Framtiden",
                "industry": "Printing and publishing",
                "start_date": "1932"
            },
            {
                "occupational_title": "Ch f",
                "workplace": "AB Framtidens Bokförlag",
                "industry": "Publishing",
                "start_date": "1932"
            },
            {
                "occupational_title": "Vkst dir",
                "workplace": "Arbetarpressens Förlags AB",
                "industry": "Publishing",
                "start_date": "1938"
            }
        ]
    }
}