{
    "original": "JOHANSSON, Einar Leornard, Fabrikör, Sala, f Möklinta, Västm l, 16/8 98 av fabr L J o Johanna Andersson, gm Karin Nordin. Bergslag verkmäst- o tekn.sk. Verkmäst i fad smides- o vagnfabr.rör 18, eg fma, Einar Johanssons Bil &amp; Mek verkst, Sala, sed. 26. Stdsflm, beredn.utsk, ordf Sala luftsk.nmd, Sala stads yrkessk, v. ordf el- o vattenvkt, led folksk.styr, arbetslösh.komm. Led Bil-verkst Riksfrbs centralstyr o ds vkst utsk, ordf Västml Bilverkst.frn. Odd Fellow, Tempelriddare.",
    "translated": "JOHANSSON, Einar Leonard, Industrialist, Sala, born in Möklinta, Västmanland County, on August 16, 1898 to factory owner L.J. and Johanna Andersson. Married to Karin Nordin. Foreman and technical school graduate in the Bergslagen region. Worked as a foreman in his father's forging and carriage factory until 1918, when he started his own company, Einar Johansson's Car &amp; Mechanical Workshop, in Sala. Member of the City Film Committee, preparatory committee, and chairman of the Sala Air School Committee and the Sala City Vocational School. Vice Chairman of the Electrical and Water Inspection Board. Member of the local school board and the unemployment committee. Member of the Central Board of the National Association of Car Workshops and its growth committee. Chairman of the Western Sweden Association of Car Workshops. Member of the Odd Fellows and the Templar Knights.",
    "structured": {
        "@context": "https://schema.org",
        "@type": "Person",
        "name": "Einar Leonard Johansson",
        "jobTitle": "Foreman",
        "givenName": "Einar Leonard",
        "familyName": "Johansson",
        "birthDate": "1898-08-16",
        "birthPlace": {
            "@type": "Place",
            "address": {
                "@type": "PostalAddress",
                "addressLocality": "Möklinta",
                "addressRegion": "Västmanland County",
                "addressCountry": "Sweden"
            }
        },
        "description": "Einar Leornard Johansson was an industrialist from Sala. He was born on August 16, 1898, in Möklinta, Västmanland County. He was the son of factory owner L.J. Johansson and Johanna Andersson. He married Karin Nordin.",
        "memberOf": [
            {
                "@type": "Organization",
                "name": "Odd Fellows"
            },
            {
                "@type": "Organization",
                "name": "Templar Knights"
            }
        ],
        "worksFor": [
            {
                "@type": "Organization",
                "name": "Einar Johanssons Bil & Mek verkst"
            }
        ],
        "education": [
            {
                "@type": "EducationalOrganization",
                "name": "Bergslag Verkmäst- o tekn.sk"
            }
        ],
        "occupation": {
            "@type": "Organization",
            "name": "Einar Johanssons Bil & Mek verkst"
        },
        "nationality": "Swedish",
        "spouse": "Karin Nordin",
        "birthSurname": "Andersson",
        "address": {
            "@type": "PostalAddress",
            "addressLocality": "Sala",
            "addressCountry": "Sweden"
        },
        "startDate": "1918",
        "affiliation": [
            {
                "@type": "Organization",
                "name": "City Film Committee"
            },
            {
                "@type": "Organization",
                "name": "Preparatory Committee"
            },
            {
                "@type": "Organization",
                "name": "Sala Air School Committee",
                "jobTitle": "Chairman"
            },
            {
                "@type": "Organization",
                "name": "Sala City Vocational School",
                "jobTitle": "Chairman"
            },
            {
                "@type": "Organization",
                "name": "Electrical and Water Inspection Board",
                "jobTitle": "Vice Chairman"
            },
            {
                "@type": "Organization",
                "name": "Local School Board",
                "jobTitle": "Member"
            },
            {
                "@type": "Organization",
                "name": "Unemployment Committee",
                "jobTitle": "Member"
            },
            {
                "@type": "Organization",
                "name": "Central Board of the National Association of Car Workshops",
                "jobTitle": "Member"
            },
            {
                "@type": "Organization",
                "name": "Growth Committee",
                "jobTitle": "Member"
            },
            {
                "@type": "Organization",
                "name": "Western Sweden Association of Car Workshops",
                "jobTitle": "Chairman"
            }
        ]
    },
    "occupations": {
        "career": [
            {
                "occupational_title": "Foreman",
                "workplace": "Father's forging and carriage factory",
                "industry": "Manufacturing",
                "start_date": "Until 1918"
            },
            {
                "occupational_title": "Industrialist",
                "workplace": "Einar Johansson's Car & Mechanical Workshop",
                "industry": "Automotive",
                "start_date": "Since 1918"
            }
        ]
    }
}