{
    "original": "JAKOBSSON, Martin, Direktör, Gullringen, f Linköping 9/12 92. Ljungstedtska friskolan, hdlssk. Anst i bl a Linkp, österbymo o Kisa, ch f Gullringeiis träförädl.kont Sthlm, avd.ch h ds eftr AB Sv Trähus Sthlm, sed. 43 dir f Gullringens Träförädling o AB Alsterfors glasbruk, Målerås. Fd led Sunds komm.flm o valnmd, rev komm-, kyrko- o sk.kass, förest österbymo föreläsn.frn, ordf Kisa arb.lösh.-kommitté. JANEMARK. Sten Ludvig, Kamrer, Uppsala, f Upps 5/2 07. Upps ensk lärov o Upps stads hdlssk. Anst i AB Nord Metallduksvä-veriet sed. 25. Odd Fellow, Merkurii-Sällsk i Upps. Hobby: Sport.",
    "translated": "JAKOBSSON, Martin, Director, Gullringen, born in Linköping on December 9, 1892. Educated at Ljungstedtska School and commercial school. Employed in various positions including in Linköping, Österbymo, and Kisa, then head of the wood processing department at Gullringen timber factory in Stockholm. Later became division chief and director of AB Swedish Timber Houses in Stockholm. Since 1943, director of Gullringens Wood Processing and AB Alsterfors Glassworks, Målerås. Former board member of Sund municipality and electoral committee. Also served on municipal, church, and school funds committees. Gave lectures in Österbymo and served as chairman of Kisa unemployment committee. JANEMARK. Sten Ludvig, Accountant, Uppsala, born in Uppsala on February 5, 1907. Educated at Uppsala private school and Uppsala city commercial school. Employed at AB Nord Metallduksväveriet since 1925. Member of the Odd Fellow and Merkurii Society in Uppsala. Hobby: Sports.",
    "structured": {
        "@context": "https://schema.org",
        "@type": "Person",
        "name": "Martin Jakobsson",
        "jobTitle": "Director",
        "address": {
            "@type": "PostalAddress",
            "addressLocality": "Gullringen",
            "addressCountry": "Sweden"
        },
        "birthDate": "1892-12-09",
        "birthPlace": {
            "@type": "City",
            "name": "Linköping"
        },
        "educationalBackground": [
            {
                "@type": "EducationalOrganization",
                "name": "Ljungstedtska School"
            },
            {
                "@type": "EducationalOrganization",
                "name": "Commercial School"
            }
        ],
        "employmentHistory": [
            {
                "@type": "Organization",
                "name": "Linköping"
            },
            {
                "@type": "Organization",
                "name": "Österbymo"
            },
            {
                "@type": "Organization",
                "name": "Kisa"
            },
            {
                "@type": "Organization",
                "name": "Gullringen timber factory",
                "department": "Wood Processing Department",
                "location": "Stockholm"
            },
            {
                "@type": "Organization",
                "name": "AB Swedish Timber Houses",
                "location": "Stockholm",
                "position": "Division Chief"
            },
            {
                "@type": "Organization",
                "name": "Gullringens Wood Processing"
            },
            {
                "@type": "Organization",
                "name": "AB Alsterfors Glassworks",
                "location": "Målerås"
            }
        ],
        "boardMemberIn": [
            {
                "@type": "Organization",
                "name": "Sund Municipality"
            }
        ],
        "lecturerIn": [
            {
                "@type": "City",
                "name": "Österbymo"
            }
        ],
        "committeeMemberIn": [
            {
                "@type": "Organization",
                "name": "Kisa Unemployment Committee"
            }
        ],
        "hobby": "Sports"
    },
    "occupations": {
        "career": [
            {
                "occupational_title": "Director",
                "workplace": "Gullringens Träförädling",
                "industry": "Wood processing",
                "start_date": "1943"
            },
            {
                "occupational_title": "Director",
                "workplace": "AB Alsterfors Glassworks",
                "industry": "Glass manufacturing",
                "start_date": "1943"
            },
            {
                "occupational_title": "Head of Wood Processing Department",
                "workplace": "Gullringen timber factory",
                "industry": "Wood processing",
                "start_date": ""
            },
            {
                "occupational_title": "Division Chief",
                "workplace": "AB Sv Trähus",
                "industry": "Timber houses",
                "start_date": ""
            },
            {
                "occupational_title": "Salesman",
                "workplace": "Linköping",
                "industry": "Unknown",
                "start_date": ""
            },
            {
                "occupational_title": "Salesman",
                "workplace": "Österbymo",
                "industry": "Unknown",
                "start_date": ""
            },
            {
                "occupational_title": "Salesman",
                "workplace": "Kisa",
                "industry": "Unknown",
                "start_date": ""
            }
        ]
    }
}