{
    "original": "HEDIN, John Erik, Disponent, Mariestad, f Badelunda 28/5 71 av lantbr E A Petterson o Augusta Hedin, gm (2) Dagmar Hillfors. Ex KTH (mek) 91, ritkont- o verkst.prakt Köpgs mek verkst 91—97. övering o ritkont.ch Lidköp mek verkst 97—04, övert o omb denna 04, dettas disp 04—12, init.tag t kraftAB Gullspång-Munkfors 06 o dettas disp 06—42. Styr.ordf KraftAB Gullsp-Munkf, Örebro el AB, Gullsp el.kem AB, Sv AB Gasaccumulator, AB Tidn f Skarab l, styr.led Bergsl gemens kraftförvaltn, Örebro kraftförmedl, Sv vattenkraftfrn, Skarab skyt.frb (fd ordf), fd styr.led Jordbr.bkns centralstyr, Lidkps porslfabr o Sv elkraftfrn, Skyt.frbs överstyr:s vkst utsk mm. 2:a kamm 25—28, ldst.man, v. ordf Lidkps stdsflm, stdsflm i Mariest 15—42 (ordf 23—42). Av trycket: Rädda Sveriges folk (34). KNO2kl, KVO1kl, patrstGM, Skyt.frb:ns överstyr ftjGM, Skarab skyt.frbs HedinGM, fl fjt M fr skyt.frn:ar mm, Friv skyt.väs:s ftj.plakett s.",
    "translated": "HEDIN, John Erik, Manager, Mariestad, born in Badelunda on May 28, 1871, to farmer E A Petterson and Augusta Hedin, married (2) to Dagmar Hillfors. Former student at the Royal Institute of Technology (mechanical engineering) in 1891, worked as a drafting and workshop apprentice at Köpings Mechanical Workshop from 1891 to 1897. Chief engineer and drafting manager at Lidköping Mechanical Workshop from 1897 to 1904, taking over and managing the workshop from 1904 to 1912, and then served as the manager for Kraft AB Gullspång-Munkfors from 1906 to 1942. Chairman of the board for Kraft AB Gullspång-Munkfors, Örebro Electric Co, Gullspång electric and chemical Co, Swedish Gasaccumulator Co, AB Tidningen för Skaraborgs län, board member of Bergslagens joint power management, Örebro power mediator, Swedish hydropower industry, Skaraborg Shooting Association (former chairman), former board member of the Agricultural Bank Central Board, Lidköping porcelain factory, and Swedish electric power industry, and Chief of the Shooting Association's supreme committee for growth and development, etc. Member of the Second Chamber of the Swedish Parliament from 1925 to 1928, senior member and vice chairman of Lidköping City Council, city council member in Mariestad from 1915 to 1942 (chairman from 1923 to 1942). Author of the book \"Rädda Sveriges folk\" (Save Sweden's people) in 1934. Knight of the Order of the North Star - 2nd Class, Knight of the Royal Order of Vasa - 1st Class, Patriotic Medal in Gold, Shooting Association's supreme committee gold medal, Shooting Association's Hedin gold medal, multiple military medals for shooting achievements, etc., Volunteer Shooting Association's military plaque, etc.",
    "structured": {
        "@context": "https://schema.org",
        "@type": "Person",
        "name": "John Erik Hedin",
        "jobTitle": "Manager",
        "birthDate": "1871-05-28",
        "birthPlace": "Badelunda",
        "memberOf": {
            "@type": "Organization",
            "name": "KraftAB Gullspång-Munkfors",
            "jobTitle": "Manager"
        },
        "education": {
            "@type": "EducationalOrganization",
            "name": "Royal Institute of Technology",
            "alumniOf": {
                "@type": "EducationalOccupationalCredential",
                "credentialCategory": "diploma",
                "description": "Mechanical Engineering"
            },
            "startDate": "1891",
            "endDate": "1891"
        },
        "spouse": "Dagmar Hillfors",
        "parents": [
            {
                "@type": "Person",
                "name": "E A Petterson",
                "birthDate": "",
                "birthPlace": ""
            },
            {
                "@type": "Person",
                "name": "Augusta Hedin",
                "birthDate": "",
                "birthPlace": ""
            }
        ],
        "worksFor": [
            {
                "@type": "Organization",
                "name": "Köpings Mechanical Workshop",
                "jobTitle": "Drafting and Workshop Apprentice",
                "startDate": "1891",
                "endDate": "1897"
            },
            {
                "@type": "Organization",
                "name": "Lidköping Mechanical Workshop",
                "jobTitle": "Chief Engineer and Drafting Manager",
                "startDate": "1897",
                "endDate": "1904"
            }
        ],
        "boardMember": [
            {
                "@type": "Organization",
                "name": "KraftAB Gullspång-Munkfors",
                "jobTitle": "Chairman of the Board",
                "startDate": "1906",
                "endDate": "1942"
            },
            {
                "@type": "Organization",
                "name": "Örebro Electric Co",
                "jobTitle": "Chairman of the Board"
            },
            {
                "@type": "Organization",
                "name": "Gullspång Electric and Chemical Co",
                "jobTitle": "Chairman of the Board"
            },
            {
                "@type": "Organization",
                "name": "Swedish Gasaccumulator Co",
                "jobTitle": "Chairman of the Board"
            },
            {
                "@type": "Organization",
                "name": "AB Tidningen för Skaraborgs län",
                "jobTitle": "Board Member"
            },
            {
                "@type": "Organization",
                "name": "Bergslagens Joint Power Management",
                "jobTitle": "Board Member"
            },
            {
                "@type": "Organization",
                "name": "Örebro Power Mediator",
                "jobTitle": "Board Member"
            },
            {
                "@type": "Organization",
                "name": "Swedish Hydropower Industry",
                "jobTitle": "Board Member"
            },
            {
                "@type": "Organization",
                "name": "Skaraborg Shooting Association",
                "jobTitle": "Former Chairman"
            },
            {
                "@type": "Organization",
                "name": "Agricultural Bank Central Board",
                "jobTitle": "Former Board Member"
            },
            {
                "@type": "Organization",
                "name": "Lidköping Porcelain Factory",
                "jobTitle": "Former Board Member"
            },
            {
                "@type": "Organization",
                "name": "Swedish Electric Power Industry",
                "jobTitle": "Former Board Member"
            },
            {
                "@type": "Organization",
                "name": "Shooting Association's Supreme Committee for Growth and Development",
                "jobTitle": "Chief"
            }
        ],
        "politicalCareer": [
            {
                "@type": "Organization",
                "name": "Second Chamber of the Swedish Parliament",
                "jobTitle": "Member",
                "startDate": "1925",
                "endDate": "1928"
            },
            {
                "@type": "Organization",
                "name": "Lidköping City Council",
                "jobTitle": "Senior Member and Vice Chairman"
            },
            {
                "@type": "Organization",
                "name": "Mariestad City Council",
                "jobTitle": "City Council Member",
                "startDate": "1915",
                "endDate": "1942"
            }
        ],
        "author": {
            "@type": "CreativeWork",
            "name": "Rädda Sveriges folk",
            "description": "Save Sweden's people",
            "datePublished": "1934"
        },
        "awards": [
            {
                "@type": "Order",
                "name": "Order of the North Star",
                "category": "KNO2kl"
            },
            {
                "@type": "Order",
                "name": "Royal Order of Vasa",
                "category": "KVO1kl"
            },
            {
                "@type": "Medal",
                "name": "Patriotic Medal",
                "category": "patrstGM"
            },
            {
                "@type": "Medal",
                "name": "Shooting Association's Supreme Committee Gold Medal",
                "category": "Skyt.frb",
                "supremeCommittee": true
            },
            {
                "@type": "Medal",
                "name": "Shooting Association's Hedin Gold Medal",
                "category": "Skarab skyt.frbs HedinGM"
            },
            {
                "@type": "Medal",
                "name": "Volunteer Shooting Association's Military Plaque",
                "category": "Friv skyt.väs:s ftj.plakett s"
            }
        ]
    },
    "occupations": {
        "career": [
            {
                "occupational_title": "Manager",
                "workplace": "Kraft AB Gullspång-Munkfors",
                "industry": "Energy",
                "start_date": "1906"
            },
            {
                "occupational_title": "Chief Engineer and Drafting Manager",
                "workplace": "Lidköping Mechanical Workshop",
                "industry": "Mechanical Engineering",
                "start_date": "1897"
            },
            {
                "occupational_title": "Drafting and Workshop Apprentice",
                "workplace": "Köpings Mechanical Workshop",
                "industry": "Mechanical Engineering",
                "start_date": "1891"
            }
        ]
    }
}