{
    "original": "EKLUND, Ernst Johan, Skeppsmäklare, Malmö, f Hbg 27/5 94 av fastigh.äg A E o Bothilda Lagersson, gm Karin Engström. Realex Hbg 11, Hbgs hdlsgymn 11—13. Korresp h Witt &amp; Co Hbg 13—14, korresp o be-frakt h Hoffman &amp; Molzen Wismar 14, korresp h Tycho Roberg Gbg 15, korresp o befrakt h Engström, Widmark &amp; Co Gbg 15—18, korresp o skpsmäkl h Skpsmäkl- &amp; Transp.AB Malmö 18—20, skpsmäkl o kont.ch sed. 21 h Simon Edström AB (gr 91). Odd Fellow; sekr i frisksportklubben Vikingen, Mmö. Hobbies: Friluftsliv, frisksport, gymnastik, trädgårdsodling.",
    "translated": "EKLUND, Ernst Johan, Shipbroker, Malmö, born in Helsingborg on May 27, 1894, son of property owner A E and Bothilda Lagersson, married to Karin Engström. Completed Realgymnasium in Helsingborg in 1911 and Helsingborg's Commercial Gymnasium from 1911-1913. Worked as a correspondent at Witt & Co in Helsingborg from 1913-1914, correspondent and freight agent at Hoffman & Molzen in Wismar in 1914, correspondent at Tycho Roberg in Gothenburg in 1915, correspondent and freight agent at Engström, Widmark & Co in Gothenburg from 1915-1918. Worked as a correspondent and shipbroker at Shipbroker & Transport AB in Malmö from 1918-1920. From 1921 until the present, employed as a shipbroker and office manager at Simon Edström AB (since 1891). Member of the Odd Fellow lodge; secretary of the athletic club Vikingen, Malmö. Hobbies: Outdoor activities, athletics, gymnastics, and gardening. Note: \"gr\" signifies a founding year of the company or organization.",
    "structured": {
        "@context": "https://schema.org",
        "@type": "Person",
        "name": "Ernst Johan Eklund",
        "birthDate": "1894-05-27",
        "birthPlace": "Helsingborg",
        "nationality": "Swedish",
        "description": "Shipbroker",
        "affiliation": {
            "@type": "Organization",
            "name": "Simon Edström AB",
            "foundingDate": "1891",
            "members": "1"
        },
        "education": [
            {
                "@type": "HighSchool",
                "name": "Realex Helsingborg",
                "endDate": "1911"
            },
            {
                "@type": "HighSchool",
                "name": "Helsingborg's Commercial Gymnasium",
                "startDate": "1911",
                "endDate": "1913"
            }
        ],
        "work": [
            {
                "@type": "Corporation",
                "name": "Witt & Co",
                "position": "Correspondent",
                "location": "Helsingborg",
                "startDate": "1913",
                "endDate": "1914"
            },
            {
                "@type": "Corporation",
                "name": "Hoffman & Molzen",
                "position": "Correspondent and Freight Agent",
                "location": "Wismar",
                "startDate": "1914",
                "endDate": "1914"
            },
            {
                "@type": "Corporation",
                "name": "Tycho Roberg",
                "position": "Correspondent",
                "location": "Gothenburg",
                "startDate": "1915",
                "endDate": "1915"
            },
            {
                "@type": "Corporation",
                "name": "Engström, Widmark & Co",
                "position": "Correspondent and Freight Agent",
                "location": "Gothenburg",
                "startDate": "1915",
                "endDate": "1918"
            },
            {
                "@type": "Corporation",
                "name": "Shipbroker & Transport AB",
                "position": "Correspondent and Shipbroker",
                "location": "Malmö",
                "startDate": "1918",
                "endDate": "1920"
            },
            {
                "@type": "Corporation",
                "name": "Simon Edström AB",
                "position": "Shipbroker and Office Manager",
                "location": "Malmö",
                "startDate": "1921"
            }
        ],
        "memberOf": [
            {
                "@type": "Organization",
                "name": "Odd Fellow",
                "member": "true"
            },
            {
                "@type": "Organization",
                "name": "Vikingen Athletic Club",
                "member": "true",
                "position": "Secretary"
            }
        ],
        "hobbies": [
            "Outdoor activities",
            "Athletics",
            "Gymnastics",
            "Gardening"
        ]
    },
    "occupations": {
        "career": [
            {
                "occupational_title": "Shipbroker",
                "workplace": "Witt & Co",
                "industry": "Shipping",
                "start_date": "1913"
            },
            {
                "occupational_title": "Correspondent and Freight Agent",
                "workplace": "Hoffman & Molzen",
                "industry": "Shipping",
                "start_date": "1914"
            },
            {
                "occupational_title": "Correspondent",
                "workplace": "Tycho Roberg",
                "industry": "Shipping",
                "start_date": "1915"
            },
            {
                "occupational_title": "Correspondent and Freight Agent",
                "workplace": "Engström, Widmark & Co",
                "industry": "Shipping",
                "start_date": "1915"
            },
            {
                "occupational_title": "Correspondent and Shipbroker",
                "workplace": "Shipbroker & Transport AB",
                "industry": "Shipping",
                "start_date": "1918"
            },
            {
                "occupational_title": "Shipbroker and Office Manager",
                "workplace": "Simon Edström AB",
                "industry": "Shipping",
                "start_date": "1921"
            }
        ]
    }
}