{
    "original": "NORMAN, Per Axel August, Kanaldirektör, Civilingenjör, Trollhättan, f Spånga, Sthlms l, 9/2 80 av Ijtn A N o Hilda Lundh, gm Helga Schultz. Studex 99, ex KTH (v o v) 03. Bitr ing h prof C J Magnell 03—05, avd.ing v stat kraftvksbyggn i Thtn 05—10 o Thtte kanals ombyggnad 10—13, arbetschefassist där 13—16, arb.ch v Södertälje kanals ombyggn 16—19, övering.assist v Vat.f.styr:s byggnadsbyrå Sthlm 19—20, 1. byrådir 20—27, tf kanal- dir Thtte kanalvk 27—-30, kanaldir sed. 30. Ordf fi bostadsfrn upa Sthlm 19—27, Thtns badhusAB sed. 27, led Gbg hamnstyr sed. 27, Älvsb l N hush.sällsk:s fiskeristyr 28, ordf sed. 36, v. ordf fiskerinmdn f Vänern sed. 37, suppl Stat vattenf.vks tjgnmd sed. 28, ordf Thtns ing.klubb 16 o 28—32, bol.m Thtns brännv.bol 29—38, förvaltn.m i E o A G Nyd-qvists fond f Pauvre Hont sed. 30, dräts.kamm sed. 30, ordf brandstyr 30—33, stdflm sed. 31, v. ordf sed. 37, länshj.komm i Älvsb l 31—33, huv.m Thtns sparbk sed. 31, stat omb i Säffle kanaldir sed. 32, ordf Thtns mod. Valm.frb 34—38, Idstm 35—38, led Älvsb l arb.förmedl sed. 39, styr f samrealsk i Thtn sed. 42, Maria Alberts stift 1892 sed. 37. KVO-2kl, RNO, Odd Fellow, Göt Frb, SvRK, Sv tekn.frn, Frn f inre vattenvägar, Thtns ing.klubb, Samf Sv-Finl, Älvsb l N hush.sällsk, Eldbeg.frn.",
    "translated": "NORMAN, Per Axel August, Canal Director, Civil Engineer, Trollhättan, born in Spånga, Stockholm County, on February 9, 1880, son of Ijtn A N and Hilda Lundh, married to Helga Schultz. Studied until 1899 and graduated from KTH (Royal Institute of Technology) in 1903. Assistant to Professor C J Magnell from 1903 to 1905, department engineer for state power plant construction in Trollhättan from 1905 to 1910, involved in the reconstruction of Trollhättan Canal from 1910 to 1913, assistant works manager there from 1913 to 1916, works manager for the reconstruction of Södertälje Canal from 1916 to 1919, deputy chief engineer at the Waterworks Directorate in Stockholm from 1919 to 1920, 1st bureau director from 1920 to 1927, acting canal director of Trollhättan Canal from 1927 to 1930, and canal director from 1930 onwards. Chairman of the housing association in Stockholm from 1919 to 1927, board member of Thtns Badhus AB since 1927, board member of Gothenburg Port Authority since 1927, board member of Älvsborg County Houseowners' Association's fisheries board from 1928, chairman from 1936, vice chairman of the Fisheries Board for Lake Vänern from 1937, supplemental member of the National Water Resources Board from 1928, chairman of Thtns Engineering Club in 1916 and from 1928 to 1932, board member of Thtns Brännvinsbolag (distillery company) from 1929 to 1938, administrator of E and A G Nydqvist's Pauvre Hont fund since 1930, member of the Municipal Council since 1930, chairman of the Fire Department from 1930 to 1933, member of the City Council since 1931, vice chairman since 1937, member of Älvsborg County Welfare Committee from 1931 to 1933, head of Trollhättan Savings Bank since 1931, official representative of the State in Säffle Canal Directorate since 1932, chairman of Trollhättan Modern Voting Association from 1934 to 1938, member from 1935 to 1938, board member of Älvsborg County Labor Exchange from 1939, member of the board of the coeducational school in Trollhättan since 1942, member of Maria Alberts Foundation 1892 since 1937. Knight of the Royal Order of Vasa 2nd Class, Knight of the Royal Norwegian Order, member of the Odd Fellow fraternity, member of Göta Society for Homeland, member of the Royal Swedish Academy of Engineering Sciences, member of the Inland Waterways Association, member of Thtns Engineering Club, member of the Sweden-Finland Society, member of Älvsborg County Houseowners' Association, honorary member of the Volunteer Fire Brigade.",
    "structured": {
        "@context": "https://schema.org",
        "@type": "Person",
        "name": "Per Axel August Norman",
        "birthDate": "1880-02-09",
        "birthPlace": "Spånga, Stockholm County",
        "nationality": "Swedish",
        "occupation": [
            "Canal Director",
            "Civil Engineer"
        ],
        "education": [
            {
                "@type": "EducationalOrganization",
                "name": "Royal Institute of Technology",
                "location": "Stockholm",
                "endDate": "1903"
            }
        ],
        "parents": [
            {
                "@type": "Person",
                "name": "Ijtn A N"
            },
            {
                "@type": "Person",
                "name": "Hilda Lundh"
            }
        ],
        "spouse": {
            "@type": "Person",
            "name": "Helga Schultz"
        },
        "work": [
            {
                "@type": "Organization",
                "name": "C J Magnell",
                "role": "Assistant",
                "startDate": "1903",
                "endDate": "1905"
            },
            {
                "@type": "Organization",
                "name": "State Power Plant Construction",
                "role": "Department Engineer",
                "location": "Trollhättan",
                "startDate": "1905",
                "endDate": "1910"
            },
            {
                "@type": "Organization",
                "name": "Trollhättan Canal Reconstruction",
                "role": "Involved in Reconstruction",
                "location": "Trollhättan",
                "startDate": "1910",
                "endDate": "1913"
            },
            {
                "@type": "Organization",
                "name": "Trollhättan Canal",
                "role": "Assistant Works Manager",
                "location": "Trollhättan",
                "startDate": "1913",
                "endDate": "1916"
            },
            {
                "@type": "Organization",
                "name": "Södertälje Canal Reconstruction",
                "role": "Works Manager",
                "location": "Södertälje",
                "startDate": "1916",
                "endDate": "1919"
            },
            {
                "@type": "Organization",
                "name": "Waterworks Directorate",
                "role": "Deputy Chief Engineer",
                "location": "Stockholm",
                "startDate": "1919",
                "endDate": "1920"
            },
            {
                "@type": "Organization",
                "name": "Trollhättan Canal",
                "role": "Acting Canal Director",
                "location": "Trollhättan",
                "startDate": "1927",
                "endDate": "1930"
            },
            {
                "@type": "Organization",
                "name": "Trollhättan Canal",
                "role": "Canal Director",
                "location": "Trollhättan",
                "startDate": "1930"
            }
        ],
        "membership": [
            {
                "@type": "Organization",
                "name": "Housing Association",
                "role": "Chairman",
                "location": "Stockholm",
                "startDate": "1919",
                "endDate": "1927"
            },
            {
                "@type": "Organization",
                "name": "Thtns Badhus AB",
                "role": "Board Member",
                "location": "Trollhättan",
                "startDate": "1927"
            },
            {
                "@type": "Organization",
                "name": "Gothenburg Port Authority",
                "role": "Board Member",
                "location": "Gothenburg",
                "startDate": "1927"
            },
            {
                "@type": "Organization",
                "name": "Älvsborg County Houseowners' Association",
                "role": "Board Member",
                "location": "Älvsborg",
                "startDate": "1928"
            },
            {
                "@type": "Organization",
                "name": "Fisheries Board for Lake Vänern",
                "role": "Vice Chairman",
                "startDate": "1937"
            },
            {
                "@type": "Organization",
                "name": "National Water Resources Board",
                "role": "Supplemental Member",
                "startDate": "1928"
            },
            {
                "@type": "Organization",
                "name": "Thtns Engineering Club",
                "role": "Board Member",
                "location": "Trollhättan",
                "startDate": "1916",
                "endDate": "1932"
            },
            {
                "@type": "Organization",
                "name": "Thtns Brännvinsbolag",
                "role": "Board Member",
                "startDate": "1929",
                "endDate": "1938"
            },
            {
                "@type": "Organization",
                "name": "E and A G Nydqvist's Pauvre Hont Fund",
                "role": "Administrator",
                "startDate": "1930"
            },
            {
                "@type": "Organization",
                "name": "Municipal Council",
                "role": "Member",
                "location": "Trollhättan",
                "startDate": "1930"
            },
            {
                "@type": "Organization",
                "name": "Fire Department",
                "role": "Chairman",
                "location": "Trollhättan",
                "startDate": "1930",
                "endDate": "1933"
            },
            {
                "@type": "Organization",
                "name": "City Council",
                "role": "Member",
                "location": "Trollhättan",
                "startDate": "1931"
            },
            {
                "@type": "Organization",
                "name": "Älvsborg County Welfare Committee",
                "role": "Member",
                "location": "Älvsborg",
                "startDate": "1931",
                "endDate": "1933"
            },
            {
                "@type": "Organization",
                "name": "Trollhättan Savings Bank",
                "role": "Head",
                "location": "Trollhättan",
                "startDate": "1931"
            },
            {
                "@type": "Organization",
                "name": "Säffle Canal Directorate",
                "role": "Official Representative",
                "location": "Säffle",
                "startDate": "1932"
            },
            {
                "@type": "Organization",
                "name": "Trollhättan Modern Voting Association",
                "role": "Chairman",
                "startDate": "1934",
                "endDate": "1938"
            },
            {
                "@type": "Organization",
                "name": "Älvsborg County Labor Exchange",
                "role": "Board Member",
                "location": "Älvsborg",
                "startDate": "1939"
            },
            {
                "@type": "Organization",
                "name": "Coeducational School",
                "role": "Board Member",
                "location": "Trollhättan",
                "startDate": "1942"
            },
            {
                "@type": "Organization",
                "name": "Maria Alberts Foundation 1892",
                "role": "Member",
                "startDate": "1937"
            }
        ],
        "award": [
            {
                "@type": "Order",
                "name": "Royal Order of Vasa",
                "ranking": "2nd Class",
                "dateAwarded": "Unknown"
            },
            {
                "@type": "Order",
                "name": "Royal Norwegian Order",
                "ranking": "Unknown",
                "dateAwarded": "Unknown"
            },
            {
                "@type": "Organization",
                "name": "Odd Fellow",
                "role": "Member"
            },
            {
                "@type": "Organization",
                "name": "Göta Society for Homeland",
                "role": "Member"
            },
            {
                "@type": "Organization",
                "name": "Royal Swedish Academy of Engineering Sciences",
                "role": "Member"
            },
            {
                "@type": "Organization",
                "name": "Inland Waterways Association",
                "role": "Member"
            },
            {
                "@type": "Organization",
                "name": "Sweden-Finland Society",
                "role": "Member"
            },
            {
                "@type": "Organization",
                "name": "Älvsborg County Houseowners' Association",
                "role": "Member"
            },
            {
                "@type": "Organization",
                "name": "Volunteer Fire Brigade",
                "role": "Honorary Member"
            }
        ]
    },
    "occupations": {
        "career": [
            {
                "occupational_title": "Assistant to Professor",
                "workplace": "C J Magnell",
                "industry": "Education",
                "start_date": "1903"
            },
            {
                "occupational_title": "Department Engineer",
                "workplace": "State Power Plant Construction in Trollhättan",
                "industry": "Energy",
                "start_date": "1905"
            },
            {
                "occupational_title": "Involved in the Reconstruction",
                "workplace": "Trollhättan Canal",
                "industry": "Infrastructure",
                "start_date": "1910"
            },
            {
                "occupational_title": "Assistant Works Manager",
                "workplace": "Trollhättan Canal",
                "industry": "Infrastructure",
                "start_date": "1913"
            },
            {
                "occupational_title": "Works Manager",
                "workplace": "Södertälje Canal",
                "industry": "Infrastructure",
                "start_date": "1916"
            },
            {
                "occupational_title": "Deputy Chief Engineer",
                "workplace": "Waterworks Directorate in Stockholm",
                "industry": "Government",
                "start_date": "1919"
            },
            {
                "occupational_title": "1st Bureau Director",
                "workplace": "Waterworks Directorate in Stockholm",
                "industry": "Government",
                "start_date": "1920"
            },
            {
                "occupational_title": "Acting Canal Director",
                "workplace": "Trollhättan Canal",
                "industry": "Infrastructure",
                "start_date": "1927"
            },
            {
                "occupational_title": "Canal Director",
                "workplace": "Trollhättan Canal",
                "industry": "Infrastructure",
                "start_date": "1930"
            }
        ]
    }
}