{
    "original": "NYSTRÖM, Carl Gustaf. Direktör, Lidingö-Brevik, f Svendborg, Danm, 4/6 90 av prof G A N o Dagmar Weber, gm Edith Höglund. Realex Svendborg, hdlssk Odense. Hdlsutb Odense 06—09, Sthlmsrepr f Loeser &amp; Wolf Berlin 09—11, af f.res Ryssl 12—13, eg agent.-rör Moskva 14, vkst dir AB Keros Riga 15, d:o v dta Södertälje.AB 16—18. Gr AB C G Nyström &amp; Co, chokl, konf o karam, 17, m dtrbol AB Nyco o AB Adeceka, styr.ordf o vkst dir dsa. Ag fastighfrn Fabriksväg 2 Hagalund. Resor i de fi eur länd, spec hela Ryssl o Sibir smt Kina o Japan fore o und världskriget 14—18. RVO, ProPatrstGM; Frimurare (IX), KSSS, SXK, KSSS långsegl.kté 41. Hobby: Segling.",
    "translated": "NYSTRÖM, Carl Gustaf. Director, Lidingö-Brevik, born in Svendborg, Denmark, on June 4, 1890, son of Professor G.A.N and Dagmar Weber. Married to Edith Höglund. Attended Realex in Svendborg and commerce school in Odense. Completed commerce education in Odense from 1906 to 1909. Stockholm representative for Loeser & Wolf Berlin from 1909 to 1911, then employee of f.res Ryssl from 1912 to 1913. Became a representative for a Moscow agency in 1914 and a growth director for AB Keros Riga in 1915. Held the same position in AB Södertälje 1916 to 1918. Established AB C.G Nyström & Co, a chocolate, confectionery, and candy company in 1917, and also managed the subsidiary companies AB Nyco and AB Adeceka. Currently holds positions as Chairman of the Board and growth director for these companies. Owns a property on Fabriksväg 2 Hagalund. Traveled extensively throughout Europe, particularly Russia and Siberia, as well as China and Japan before and during World War I (1914-1918). Received the Royal Order of the Polar Star (RVO) and Pro Patria Gold Medal. Member of the Freemasons (IX), Swedish Cruising Club (KSSS), Royal Swedish Yacht Club (SXK), and KSSS Long-Distance Sailing Club since 1941. Hobby: Sailing.",
    "structured": {
        "@context": "https://schema.org",
        "@type": "Person",
        "name": "Carl Gustaf Nyström",
        "jobTitle": "Director",
        "birthDate": "1890-06-04",
        "birthPlace": "Svendborg, Denmark",
        "parents": [
            {
                "@type": "Person",
                "name": "Professor G.A.N",
                "jobTitle": "Father"
            },
            {
                "@type": "Person",
                "name": "Dagmar Weber",
                "jobTitle": "Mother"
            }
        ],
        "spouse": {
            "@type": "Person",
            "name": "Edith Höglund"
        },
        "education": [
            {
                "@type": "EducationalOrganization",
                "name": "Realex Svendborg"
            },
            {
                "@type": "EducationalOrganization",
                "name": "Commerce School Odense"
            }
        ],
        "workExperience": [
            {
                "@type": "Organization",
                "name": "Loeser & Wolf Berlin",
                "jobTitle": "Stockholm Representative",
                "startDate": "1909",
                "endDate": "1911"
            },
            {
                "@type": "Organization",
                "name": "f.res Ryssl",
                "jobTitle": "Employee",
                "startDate": "1912",
                "endDate": "1913"
            },
            {
                "@type": "Organization",
                "name": "Moscow Agency",
                "jobTitle": "Representative",
                "startDate": "1914"
            },
            {
                "@type": "Organization",
                "name": "AB Keros Riga",
                "jobTitle": "Growth Director",
                "startDate": "1915"
            },
            {
                "@type": "Organization",
                "name": "AB Södertälje",
                "jobTitle": "Growth Director",
                "startDate": "1916",
                "endDate": "1918"
            },
            {
                "@type": "Organization",
                "name": "AB C.G Nyström & Co",
                "jobTitle": "Chairman of the Board"
            },
            {
                "@type": "Organization",
                "name": "AB Nyco"
            },
            {
                "@type": "Organization",
                "name": "AB Adeceka"
            }
        ],
        "address": {
            "@type": "PostalAddress",
            "streetAddress": "Fabriksväg 2",
            "addressLocality": "Hagalund"
        },
        "memberOf": [
            {
                "@type": "Organization",
                "name": "Freemasons (IX)"
            },
            {
                "@type": "Organization",
                "name": "Swedish Cruising Club (KSSS)"
            },
            {
                "@type": "Organization",
                "name": "Royal Swedish Yacht Club (SXK)"
            },
            {
                "@type": "Organization",
                "name": "KSSS Long-Distance Sailing Club",
                "startDate": "1941"
            }
        ],
        "hobby": "Sailing"
    },
    "occupations": {
        "career": [
            {
                "occupational_title": "Director",
                "workplace": "Lidingö-Brevik",
                "industry": "",
                "start_date": ""
            },
            {
                "occupational_title": "Stockholm representative",
                "workplace": "Loeser & Wolf Berlin",
                "industry": "",
                "start_date": "1909"
            },
            {
                "occupational_title": "Employee",
                "workplace": "f.res Ryssl",
                "industry": "",
                "start_date": "1912"
            },
            {
                "occupational_title": "Representative for a Moscow agency",
                "workplace": "",
                "industry": "",
                "start_date": "1914"
            },
            {
                "occupational_title": "Growth director",
                "workplace": "AB Keros Riga",
                "industry": "",
                "start_date": "1915"
            },
            {
                "occupational_title": "Growth director",
                "workplace": "AB Södertälje",
                "industry": "",
                "start_date": "1916"
            },
            {
                "occupational_title": "Established AB C.G Nyström & Co",
                "workplace": "",
                "industry": "Chocolate, confectionery, and candy",
                "start_date": "1917"
            }
        ]
    }
}