{
    "original": "LJUNGBERG, Fredrik Hjalmar, Direktör, Jönköping, f Tidah 28/5 79 av stins F L o Ida Bergström, gm Violet Nurse. Anst Vul-cans tändst.fabr, Tidah o Gbg. 97—02, Trum-mer &amp; Co Succ Ltd London 03, vkst dir där27, do STAB sed. 32. V. ordf där sed 38, ordf AB Fören sv tändst.fabr, AB Gerh Arehns mek verkst, Katrinef AB o AB Tidan, styr.led AB överums br. Resor: Ind, Ceylon, Austr, Malacka, Holl Ind, USA, Ryssl, fi europ länd. KVO2kl, RNO. Hobbies: Golf, bridge.",
    "translated": "Surname: Ljungberg\nGiven Name: Fredrik Hjalmar\nOccupation: Director\nResidence: Jönköping\nBorn: Tidah, May 28, 1879, to railway superintendent F L and Ida Bergström\nMarried to: Violet Nurse (year of marriage not provided)\nEmployment: Vulcan spark plug factory, Tidah and Gothenburg, 1897-1902; Trummer & Co Succ Ltd, London, 1903; promoted to director, 1927; currently employed at STAB (exact nature of employment not provided)\nVice Chairperson, STAB, since 1938\nChairperson, AB Fören sv tändst.fabr (Swedish Spark Plug Company), AB Gerh Arehns mek verkst (Gerh Arehn Mechanical Workshop Company), Katrinef AB, and AB Tidan\nBoard member, AB överums br (Overums Brewery Company)\nTraveled to: India, Ceylon, Australia, Malacca, Dutch Indies, USA, Russia, various European countries\nRecognitions: Royal Order of Vasa, 2nd Class; Royal Order of the North Star\nHobbies: Golf, bridge",
    "structured": {
        "@context": "https://schema.org/",
        "@type": "Person",
        "name": "Fredrik Hjalmar Ljungberg",
        "jobTitle": "Director",
        "address": {
            "@type": "PostalAddress",
            "addressLocality": "Jönköping"
        },
        "birthDate": "1879-05-28",
        "birthPlace": "Tidah",
        "parents": [
            {
                "@type": "Person",
                "name": "F L Ljungberg",
                "jobTitle": "Railway Superintendent"
            },
            {
                "@type": "Person",
                "name": "Ida Bergström"
            }
        ],
        "spouse": {
            "@type": "Person",
            "name": "Violet Nurse"
        },
        "employmentHistory": [
            {
                "@type": "Organization",
                "name": "Vulcan Spark Plug Factory",
                "address": {
                    "@type": "PostalAddress",
                    "addressLocality": "Tidah"
                },
                "startDate": "1897",
                "endDate": "1902"
            },
            {
                "@type": "Organization",
                "name": "Trummer & Co Succ Ltd",
                "address": {
                    "@type": "PostalAddress",
                    "addressLocality": "London"
                },
                "startDate": "1903"
            },
            {
                "@type": "Organization",
                "name": "STAB",
                "startDate": "1927"
            }
        ],
        "boardMemberIn": [
            {
                "@type": "Organization",
                "name": "AB Fören sv tändst.fabr"
            },
            {
                "@type": "Organization",
                "name": "AB Gerh Arehns mek verkst"
            },
            {
                "@type": "Organization",
                "name": "Katrinef AB"
            },
            {
                "@type": "Organization",
                "name": "AB Tidan"
            },
            {
                "@type": "Organization",
                "name": "AB överums br"
            }
        ],
        "travelHistory": [
            "India",
            "Ceylon",
            "Australia",
            "Malacca",
            "Dutch Indies",
            "USA",
            "Russia"
        ],
        "recognitions": [
            {
                "@type": "Order",
                "name": "Royal Order of Vasa",
                "description": "2nd Class"
            },
            {
                "@type": "Order",
                "name": "Royal Order of the North Star"
            }
        ],
        "hobbies": [
            "Golf",
            "Bridge"
        ]
    },
    "occupations": {
        "career": [
            {
                "occupational_title": "Direktör",
                "workplace": "STAB",
                "industry": "Unknown (exact nature of employment not provided)",
                "start_date": null
            },
            {
                "occupational_title": "V. ordf",
                "workplace": "STAB",
                "industry": "Unknown (exact nature of employment not provided)",
                "start_date": "1938"
            },
            {
                "occupational_title": "Anst",
                "workplace": "Vulcan spark plug factory",
                "industry": "Tändst.fabr (Spark Plug Factory)",
                "start_date": "1897"
            },
            {
                "occupational_title": "Anst",
                "workplace": "Vulcan spark plug factory",
                "industry": "Tändst.fabr (Spark Plug Factory)",
                "start_date": "1898"
            },
            {
                "occupational_title": "Anst",
                "workplace": "Trummer & Co Succ Ltd",
                "industry": "Unknown (exact nature of employment not provided)",
                "start_date": "1903"
            },
            {
                "occupational_title": "Dir",
                "workplace": "Trummer & Co Succ Ltd",
                "industry": "Unknown (exact nature of employment not provided)",
                "start_date": "1927"
            }
        ]
    }
}