{
    "original": "OLANDER, August Wilhelm, Kamrer, Nybro, f Långared, Älvsb län, 27/9 90 av korpral J O o Maria Larsson, gm Ruth Ohlsson. Språk-te hdlsinst. Anst fma Nordström &amp; Tinggren Gbg 09—14, Wald Zachrissons boktr.AB Gbg 14—18, AB Sture Ljungdahl &amp; Co Nybro sed. 18, styr.led o v. vkst dir där. Styr.led AB Nybro wellkartong, AB Kalksandtegelfabr, Frn Sv kuvertfabr, Nybro miss.förs, styr.ordf Fp lo-kalavd. V. ordf stdsflm, suppl dräts.kamm, led beredn.utsk etc, led folksk.styr, v. ordf elvkt, ordf tomtvärd.komm. Resor: USA 33, Tyskl, Engl, Frankr, Schweiz, Österr, Tjeckoslov mfl europ länd.",
    "translated": "OLANDER, August Wilhelm, Bale, Nybro, born in Långared, Älvsborg county, on September 27th, 1890, to corporal J O and Maria Larsson, married to Ruth Ohlsson. Language and trade education. Employed at Nordström & Tinggren in Gothenburg from 1909 to 1914, Wald Zachrissons bookprinting company AB in Gothenburg from 1914 to 1918, AB Sture Ljungdahl & Co in Nybro since 1918, serving as a board member and acting managing director there. Board member of AB Nybro wellkartong, AB Kalksandtegelfabr, and the Swedish envelope factory in Nybro, missionary congregation in Nybro, chairman of the Fp local youth organization. Vice-chairman of the district film association, substitute for the finance committee, member of the preparatory committee, etc., member of the public school board, vice-chairman of the electric power board, chairman of the land administrator committee. Travelled to USA in 1933, Germany, England, France, Switzerland, Austria, Czechoslovakia, and other European countries.",
    "structured": {
        "@context": "https://schema.org",
        "@type": "Person",
        "name": "August Wilhelm OLANDER",
        "birthDate": "1890-09-27",
        "birthPlace": {
            "@type": "Place",
            "name": "Långared, Älvsborg county"
        },
        "parent": [
            {
                "@type": "Person",
                "name": "J O",
                "relation": "corporal"
            },
            {
                "@type": "Person",
                "name": "Maria Larsson"
            }
        ],
        "spouse": {
            "@type": "Person",
            "name": "Ruth Ohlsson"
        },
        "education": {
            "@type": "EducationalOccupationalCredential",
            "educationLevel": "Language and trade"
        },
        "employment": [
            {
                "@type": "Organization",
                "name": "Nordström & Tinggren",
                "location": "Gothenburg",
                "startDate": "1909",
                "endDate": "1914"
            },
            {
                "@type": "Organization",
                "name": "Wald Zachrissons bookprinting company AB",
                "location": "Gothenburg",
                "startDate": "1914",
                "endDate": "1918"
            },
            {
                "@type": "Organization",
                "name": "AB Sture Ljungdahl & Co",
                "location": "Nybro",
                "startDate": "1918"
            }
        ],
        "boardMemberIn": [
            {
                "@type": "Organization",
                "name": "AB Nybro wellkartong"
            },
            {
                "@type": "Organization",
                "name": "AB Kalksandtegelfabr"
            },
            {
                "@type": "Organization",
                "name": "Swedish envelope factory"
            }
        ],
        "missionaryCongregation": [
            {
                "@type": "Organization",
                "name": "Nybro missionary congregation"
            }
        ],
        "organizationAffiliations": [
            {
                "@type": "Organization",
                "name": "Fp local youth organization",
                "roleName": "Chairman"
            },
            {
                "@type": "Organization",
                "name": "District film association",
                "roleName": "Vice Chairman"
            },
            {
                "@type": "Organization",
                "name": "Finance committee",
                "roleName": "Substitute"
            },
            {
                "@type": "Organization",
                "name": "Preparatory committee"
            },
            {
                "@type": "Organization",
                "name": "Public school board"
            },
            {
                "@type": "Organization",
                "name": "Electric power board",
                "roleName": "Vice Chairman"
            },
            {
                "@type": "Organization",
                "name": "Land administrator committee",
                "roleName": "Chairman"
            }
        ],
        "travel": [
            "USA 1933",
            "Germany",
            "England",
            "France",
            "Switzerland",
            "Austria",
            "Czechoslovakia",
            "other European countries"
        ]
    },
    "occupations": {
        "career": [
            {
                "occupational_title": "Clerk",
                "workplace": "Nordström & Tinggren",
                "industry": "Trade",
                "start_date": "1909"
            },
            {
                "occupational_title": "Clerk",
                "workplace": "Wald Zachrissons bookprinting company AB",
                "industry": "Printing",
                "start_date": "1914"
            },
            {
                "occupational_title": "Accountant",
                "workplace": "AB Sture Ljungdahl & Co",
                "industry": "Unknown",
                "start_date": "1918"
            }
        ]
    }
}