{
    "original": "AHLSTRÖM, Ragnar, Civilingenjör, Stockholm, f Stockholm 8/1 96 av med lic G A A A o Ellen Frost, gm Dagmar Stridbeck. Studex Djursholm 15, KTH (VoV) 16—20. Fänr i Fort res 17, ulöjtn 20, avsk 25. löjtn VVK 24, kapt 31, avsk 43. Studier USA o Tyskl 20—22. Anst Kreuger &amp; Tolls Byggn.AB 23—28 o 29—32 (poSth ing Hammarforsens kraftv.byggn 25—28, arb.ch kraftv.byggn Avesta 29—32), posth ing Lanforsens kraftv.byggn 28—29, posth ing Tranebergsbron 32— 34, arb.ch Sthlms hamnstyr nybyggn 34—39, ch Järpströmmens kraftv.byggn, AB Svart-hålsforsen sed. 39. Ag villafastigh i Bromma. Av trycket: Upps i tekn tidskr. Led Sv Tekn.-föreningen. RVO.",
    "translated": "AHLSTRÖM, Ragnar, Civil Engineer, Stockholm, b. Stockholm 8/1 1896, son of G.A.A.A. and Ellen Frost. Married to Dagmar Stridbeck. Studied at Djursholm School until 1915, KTH (Royal Institute of Technology) 1916-1920. Second Lieutenant in the Army Fortress Corps in 1917, Lieutenant in 1920, retired in 1925. Lieutenant in the Voluntary Motor Vehicle Corps in 1924, Captain in 1931, retired in 1943. Studied in the USA and Germany from 1920-1922. Employed at Kreuger & Tolls Construction Co. from 1923-1928 and 1929-1932 (involved in the construction of Hammarforsens power plant from 1925-1928, chief engineer at the Avesta power plant from 1929-1932), chief engineer at the Lanforsens power plant from 1928-1929, chief engineer at the Tranebergs Bridge project from 1932-1934, chief engineer at the Stockholm Port Authority's new construction projects from 1934-1939, chief engineer at the Järpströmmens power plant, AB Svart-hålsforsen since 1939. Owner of a villa property in Bromma. Published in technical journals. Member of the Swedish Technical Association. Awarded the Royal Order of Vasa.",
    "structured": {
        "@context": "https://schema.org",
        "@type": "Person",
        "name": "Ragnar Ahlström",
        "birthDate": "1896-01-08",
        "birthPlace": {
            "@type": "City",
            "name": "Stockholm"
        },
        "parent": [
            {
                "@type": "Person",
                "name": "G.A.A.A.",
                "familyName": "Ahlström"
            },
            {
                "@type": "Person",
                "name": "Ellen Frost"
            }
        ],
        "spouse": {
            "@type": "Person",
            "name": "Dagmar Stridbeck"
        },
        "education": [
            {
                "@type": "EducationalOrganization",
                "name": "Djursholm School",
                "endDate": "1915"
            },
            {
                "@type": "EducationalOrganization",
                "name": "Royal Institute of Technology (KTH)",
                "startDate": "1916",
                "endDate": "1920"
            }
        ],
        "occupation": {
            "@type": "Person",
            "name": "Civil Engineer"
        },
        "memberOf": {
            "@type": "Organization",
            "name": "Swedish Technical Association"
        },
        "awards": {
            "@type": "Order",
            "name": "Royal Order of Vasa"
        },
        "worksFor": [
            {
                "@type": "Organization",
                "name": "Kreuger & Tolls Construction Co.",
                "startDate": "1923",
                "endDate": "1928"
            },
            {
                "@type": "Organization",
                "name": "Kreuger & Tolls Construction Co.",
                "startDate": "1929",
                "endDate": "1932"
            },
            {
                "@type": "Organization",
                "name": "Lanforsens power plant",
                "startDate": "1928",
                "endDate": "1929"
            },
            {
                "@type": "Organization",
                "name": "Tranebergs Bridge project",
                "startDate": "1932",
                "endDate": "1934"
            },
            {
                "@type": "Organization",
                "name": "Stockholm Port Authority",
                "startDate": "1934",
                "endDate": "1939"
            },
            {
                "@type": "Organization",
                "name": "Järpströmmens power plant, AB Svart-hålsforsen",
                "startDate": "1939"
            }
        ],
        "retiredFrom": [
            {
                "@type": "Organization",
                "name": "Army Fortress Corps",
                "startDate": "1925"
            },
            {
                "@type": "Organization",
                "name": "Voluntary Motor Vehicle Corps",
                "startDate": "1943"
            }
        ],
        "studyAbroad": [
            {
                "@type": "Country",
                "name": "USA",
                "startDate": "1920",
                "endDate": "1922"
            },
            {
                "@type": "Country",
                "name": "Germany",
                "startDate": "1920",
                "endDate": "1922"
            }
        ],
        "owns": {
            "@type": "Place",
            "name": "Villa property in Bromma"
        }
    },
    "occupations": {
        "career": [
            {
                "occupational_title": "Civil Engineer",
                "workplace": "Kreuger & Tolls Byggn.AB",
                "industry": "Construction",
                "start_date": "1923"
            },
            {
                "occupational_title": "Chief Engineer",
                "workplace": "Hammarforsens kraftv.byggn",
                "industry": "Power Plant Construction",
                "start_date": "1925"
            },
            {
                "occupational_title": "Chief Engineer",
                "workplace": "Avesta",
                "industry": "Power Plant Construction",
                "start_date": "1929"
            },
            {
                "occupational_title": "Chief Engineer",
                "workplace": "Lanforsens kraftv.byggn",
                "industry": "Power Plant Construction",
                "start_date": "1928"
            },
            {
                "occupational_title": "Chief Engineer",
                "workplace": "Tranebergsbron",
                "industry": "Construction",
                "start_date": "1932"
            },
            {
                "occupational_title": "Chief Engineer",
                "workplace": "Sthlms hamnstyr nybyggn",
                "industry": "Construction",
                "start_date": "1934"
            },
            {
                "occupational_title": "Chief Engineer",
                "workplace": "Järpströmmens kraftv.byggn, AB Svart-hålsforsen",
                "industry": "Power Plant Construction",
                "start_date": "1939"
            }
        ]
    }
}