{
    "original": "EHRNBERG, Gösta, Direktör, Simrishamn, f Simrish 26/5 95 av dir A E o Hanna Tufves-son, gm Greta Jenner. Malmö tekn Rk, stud o prakt Danm, Tyskl, Engl, Belg o Frankr 13 —16 o 19—22. Vkst dir AB Ehrnberg &amp; Sons Läderfabr sed. 22 o AB Nord Läderfabr sed. 29, tillika vkst dir AB Randfabr Cimbria. Ordf i dessa samt i Simrish Tegelbr.AB, AB Cim-brish-Bladet, AB Hotell Svea, Simrish Fas-tigh.AB, lokaldir f Skand Bkn, Simrish Sparbk mfl; styr.led Läderutstansnings AB. Led av Ind.kommiss :s råd o av Arbetsmarkn.kom-miss:s råd. Ordf Sv Garveriidk.frn, Frn f Forum- o Hemb.vård i SO Skåne mfl; styr.led Ska Brandförsäkr.inr, Sv Ind.frb, Ska Spar-bksfrn, Skånes Hembygdsfrb; flm Sv Arb.-giv.frn, Sv Ind.frb, Ska, hdlskamm mm. Av trycket: En resa i La Plata-läuderna, Garvare-skrået, gamla garvare o garverier i Simrish, upps i tekn o kulturhist ämnen. KorrespLHA, Dess SM, StiftLVSL A Hazelius st SM.",
    "translated": "EHRNBERG, Gösta, Director, Simrishamn, b. Simrish 26/5 95 to director A E and Hanna Tufves-son, m. Greta Jenner. Malmö Technical School, studied and worked in Denmark, Germany, England, Belgium, and France from 1913-1916 and 1919-1922. Became managing director of AB Ehrnberg & Sons Leather Factory in 1922 and AB Nord Leather Factory in 1929, and also served as managing director of AB Randfabr Cimbria. Chairman of these companies as well as Simrish Brick Factory AB, AB Cim-brish-Bladet, AB Hotel Svea, Simrish Property AB, local director of Skand Bkn, Simrish Savings Bank, among others; board member of Leather Cutting AB. Member of the Industrial Commissioner's Council and the Labour Market Commission. Chairman of the Swedish Tannery Industry Association, the Forum and Homecare Association in Southern Skåne, among others; board member of Ska Insurance Company, Swedish Industrial Association, Ska Savings Bank, Skåne's Heritage Association; member of the Swedish Employers' Association, Swedish Industrial Association, Ska Trade Chamber, and more. Published works: A Journey in the La Plata Islands, The Tanners' Guild, Old Tanners and Tanneries in Simrish, writings on technical and cultural-historical subjects. Corresponding member of LHA, Dess SM, and StiftLVSL A Hazelius st SM.",
    "structured": {
        "@context": "https://schema.org",
        "@type": "Person",
        "givenName": "Gösta",
        "familyName": "Ehrnberg",
        "jobTitle": "Director",
        "birthDate": "1895-05-26",
        "birthPlace": "Simrish",
        "parents": [
            {
                "@type": "Person",
                "givenName": "A",
                "familyName": "Ehrnberg",
                "jobTitle": "Director"
            },
            {
                "@type": "Person",
                "givenName": "Hanna",
                "familyName": "Tufves-son"
            }
        ],
        "spouse": {
            "@type": "Person",
            "givenName": "Greta",
            "familyName": "Jenner"
        },
        "education": [
            {
                "@type": "EducationalOrganization",
                "name": "Malmö Technical School"
            }
        ],
        "workExperience": [
            {
                "@type": "OrganizationRole",
                "startDate": "1922",
                "endDate": null,
                "roleName": "Managing Director",
                "organization": {
                    "@type": "Organization",
                    "name": "AB Ehrnberg & Sons Leather Factory"
                }
            },
            {
                "@type": "OrganizationRole",
                "startDate": "1929",
                "endDate": null,
                "roleName": "Managing Director",
                "organization": {
                    "@type": "Organization",
                    "name": "AB Nord Leather Factory"
                }
            },
            {
                "@type": "OrganizationRole",
                "startDate": null,
                "endDate": null,
                "roleName": "Managing Director",
                "organization": {
                    "@type": "Organization",
                    "name": "AB Randfabr Cimbria"
                }
            }
        ],
        "memberOf": [
            {
                "@type": "Organization",
                "name": "AB Cim-brish-Bladet"
            },
            {
                "@type": "Organization",
                "name": "AB Hotel Svea"
            },
            {
                "@type": "Organization",
                "name": "Simrish Property AB"
            },
            {
                "@type": "Organization",
                "name": "Simrish Brick Factory AB"
            },
            {
                "@type": "Organization",
                "name": "Skand Bkn"
            },
            {
                "@type": "Organization",
                "name": "Simrish Savings Bank"
            },
            {
                "@type": "Organization",
                "name": "Leather Cutting AB"
            },
            {
                "@type": "Organization",
                "name": "Swedish Tannery Industry Association"
            },
            {
                "@type": "Organization",
                "name": "Forum and Homecare Association in Southern Skåne"
            },
            {
                "@type": "Organization",
                "name": "Ska Insurance Company"
            },
            {
                "@type": "Organization",
                "name": "Swedish Industrial Association"
            },
            {
                "@type": "Organization",
                "name": "Ska Savings Bank"
            },
            {
                "@type": "Organization",
                "name": "Skåne's Heritage Association"
            },
            {
                "@type": "Organization",
                "name": "Swedish Employers' Association"
            },
            {
                "@type": "Organization",
                "name": "Ska Trade Chamber"
            }
        ],
        "publication": [
            "A Journey in the La Plata Islands",
            "The Tanners' Guild",
            "Old Tanners and Tanneries in Simrish",
            "writings on technical and cultural-historical subjects"
        ]
    },
    "occupations": {
        "career": [
            {
                "occupational_title": "Director",
                "workplace": "AB Ehrnberg & Sons Leather Factory",
                "industry": "Leather Manufacturing",
                "start_date": "1922"
            },
            {
                "occupational_title": "Director",
                "workplace": "AB Nord Leather Factory",
                "industry": "Leather Manufacturing",
                "start_date": "1929"
            },
            {
                "occupational_title": "Managing Director",
                "workplace": "AB Randfabr Cimbria",
                "industry": "Manufacturing",
                "start_date": ""
            },
            {
                "occupational_title": "Chairman",
                "workplace": "Simrish Brick Factory AB",
                "industry": "Construction",
                "start_date": ""
            },
            {
                "occupational_title": "Chairman",
                "workplace": "AB Cim-brish-Bladet",
                "industry": "Publishing",
                "start_date": ""
            },
            {
                "occupational_title": "Chairman",
                "workplace": "AB Hotel Svea",
                "industry": "Hospitality",
                "start_date": ""
            },
            {
                "occupational_title": "Chairman",
                "workplace": "Simrish Property AB",
                "industry": "Real Estate",
                "start_date": ""
            },
            {
                "occupational_title": "Local Director",
                "workplace": "Skand Bkn",
                "industry": "Banking",
                "start_date": ""
            },
            {
                "occupational_title": "Local Director",
                "workplace": "Simrish Savings Bank",
                "industry": "Banking",
                "start_date": ""
            },
            {
                "occupational_title": "Board Member",
                "workplace": "Leather Cutting AB",
                "industry": "Manufacturing",
                "start_date": ""
            }
        ]
    }
}