{
    "original": "ERICSON, Gustaf Helge, fd Generaldirektör, Stockholm, f Borås 16/3 90 av handl G E o Gerda Gustafsson, gm (1) Greta Olsson, d 29, (2) frih:an Elisabeth von Stedingk. Ex KTH 12. Anst Telegrafv 13, linjeing 18, 1. byråing Tel.styr 20, anst AB L M Ericsson 28,verkstadsdir Tel.v 30, gen.dir o ch f Tel.v 39, vkst dir o styr.led i Tel.AB L M Ericsson sed. 42 o styr.led resp ordf i fi därtill anslutna företag. Sekr Tel.v ing.frn 20—27, styr.led Sv el.ing frn 24—26 o 31—34, v. ordf 31—33, styr.led Sv Tekn.frn 31—34, ordf stat uppfinn.-nmd 40—41, led stat ind.kommiss 41—42, styr.led livförsäkr.AB Thule 41, styr.ordf Tekn Muséet 42. LIVA.",
    "translated": "ERICSON, Gustaf Helge, former Director-General, Stockholm, born in Borås on March 16th, 1890, son of merchant G. E. and Gerda Gustafsson. Married (1) to Greta Olsson, deceased in 1929, (2) to Elisabeth von Stedingk, a noblewoman. Graduated from KTH (Royal Institute of Technology) in 1912. Employed at Telegrafv (Telegraph Administration) from 1913 as a line engineer, promoted to first bureau engineer at Tel.styr (Telegraph Board) in 1920. Joined AB L M Ericsson in 1928, became workshop manager at Tel.v (Telegraph Works) in 1930, promoted to General Director and Chairman of the Board at Tel.v in 1939, also served as workshop manager and board member in associated companies. Secretary at Tel.v engineering department from 1920 to 1927, board member of the Swedish Electrical Engineers Association from 1924 to 1926 and from 1931 to 1934, vice chairman from 1931 to 1933, board member of the Swedish Technical Society from 1931 to 1934, chairman of the state invention committee from 1940 to 1941, member of the state industrial commission from 1941 to 1942, board member of Thule Life Insurance Company in 1941, chairman of the Technical Museum since 1942. Still alive.",
    "structured": {
        "@context": "https://schema.org",
        "@type": "Person",
        "name": "Gustaf Helge Ericson",
        "givenName": "Gustaf Helge",
        "familyName": "Ericson",
        "birthDate": "1890-03-16",
        "birthPlace": "Borås, Sweden",
        "description": "Former Director-General",
        "nationality": "Swedish",
        "spouse": [
            {
                "@type": "Person",
                "name": "Greta Olsson",
                "deathDate": "1929"
            },
            {
                "@type": "Person",
                "name": "Elisabeth von Stedingk",
                "honorificSuffix": "freiherrlich"
            }
        ],
        "alumniOf": [
            {
                "@type": "Organization",
                "name": "KTH (Royal Institute of Technology)",
                "startDate": "1912"
            }
        ],
        "worksFor": [
            {
                "@type": "Organization",
                "name": "Telegrafv (Telegraph Administration)",
                "startDate": "1913",
                "endDate": "1920",
                "jobTitle": "Line Engineer"
            },
            {
                "@type": "Organization",
                "name": "AB L M Ericsson",
                "startDate": "1928"
            },
            {
                "@type": "Organization",
                "name": "Tel.v (Telegraph Works)",
                "startDate": "1930",
                "endDate": "1939",
                "jobTitle": "Workshop Manager"
            },
            {
                "@type": "Organization",
                "name": "Tel.v (Telegraph Works)",
                "startDate": "1939",
                "jobTitle": "General Director and Chairman of the Board"
            }
        ],
        "memberOf": [
            {
                "@type": "Organization",
                "name": "Telegrafv (Telegraph Administration)",
                "startDate": "1920",
                "endDate": "1927",
                "jobTitle": "Secretary"
            },
            {
                "@type": "Organization",
                "name": "Swedish Electrical Engineers Association",
                "startDate": "1924",
                "endDate": "1926",
                "jobTitle": "Board Member"
            },
            {
                "@type": "Organization",
                "name": "Swedish Electrical Engineers Association",
                "startDate": "1931",
                "endDate": "1934",
                "jobTitle": "Board Member"
            },
            {
                "@type": "Organization",
                "name": "Swedish Electrical Engineers Association",
                "startDate": "1931",
                "endDate": "1933",
                "jobTitle": "Vice Chairman"
            },
            {
                "@type": "Organization",
                "name": "Swedish Technical Society",
                "startDate": "1931",
                "endDate": "1934",
                "jobTitle": "Board Member"
            },
            {
                "@type": "Organization",
                "name": "State Invention Committee",
                "startDate": "1940",
                "endDate": "1941",
                "jobTitle": "Chairman"
            },
            {
                "@type": "Organization",
                "name": "State Industrial Commission",
                "startDate": "1941",
                "endDate": "1942",
                "jobTitle": "Member"
            },
            {
                "@type": "Organization",
                "name": "Thule Life Insurance Company",
                "startDate": "1941",
                "jobTitle": "Board Member"
            },
            {
                "@type": "Organization",
                "name": "Technical Museum",
                "startDate": "1942",
                "jobTitle": "Chairman"
            }
        ]
    },
    "occupations": {
        "career": [
            {
                "occupational_title": "Engineer",
                "workplace": "Telegrafv",
                "industry": "Telecommunication",
                "start_date": "1913"
            },
            {
                "occupational_title": "Bureau Engineer",
                "workplace": "Tel.styr",
                "industry": "Telecommunication",
                "start_date": "1920"
            },
            {
                "occupational_title": "Workshop Manager",
                "workplace": "AB L M Ericsson",
                "industry": "Telecommunication",
                "start_date": "1930"
            },
            {
                "occupational_title": "General Director and Chairman of the Board",
                "workplace": "Tel.v",
                "industry": "Telecommunication",
                "start_date": "1939"
            }
        ]
    }
}