{
    "original": "MYREN, Frans Oskar, Järnhandlare, Bengtsfors, f Nössemark, Dalsl, 1/12 78 av lantbr Elias Jonsson o Maria Lisa Andreasdtr, gm Ellen Severinsson. Karlskoga prakt lärov 97 —98, Hermods, teoret musikstud. Kontorist i Bengtsfors 01—11, kont.chef v Svaneholm® Bruk 11—19, d:o i Säffle 19—20, deläg o vkst dir i AB Petersons Järnhandel i Bengtsfors sed. 21. Organist o sångled i Halden 98—00, i Bengtsfors 02—11 o sed. 21, i Svanskog 11— 19. Ordf i pens.nmd, v. ordf i kommunalflm samt led av tax.nmd o barnav.nmd i Svanskog; led av kommunalflm i Bengtsfors 31— 34, av folksk.styr där 32—35 o dess ordf 34— 35. Styr.led i Bengtsfors Missionsförsaml 03— 11 o sed. 21, i Dalsl Missionsfrn sed. 26, sekr sed. 32, dirig f Dalsl Kristl Sångarfrb sed. 19. Resor: Danm 36, Tyskl o Tjeckoslov 37. Av trycket: sånghäft »Pilgrimens hemlängtan» (96), »Växlingar» (dikter 16), Dalsl Mis-sionsfrns 50-årsberättelse (36), »Förkämpar i Markernas fromhetsrörelser» (manus 42), ton-sättn. Hobbies: Musik, landskapsforskning.",
    "translated": "MYREN, Frans Oskar, Iron Merchant, Bengtsfors, born in Nössemark, Dalsland on December 1, 1878, to farmer Elias Jonsson and Maria Lisa Andreasdotter, married to Ellen Severinsson. Attended practical school in Karlskoga in 1897-1898, Hermods, theoretical music studies. Office clerk in Bengtsfors from 1901 to 1911, head of accounting at Svaneholm® Bruk from 1911 to 1919, the same position in Säffle from 1919 to 1920, co-owner and managing director of AB Petersons Järnhandel in Bengtsfors since 1921. Organist and choir leader in Halden from 1898 to 1900, in Bengtsfors from 1902 to 1911 and since 1921, in Svanskog from 1911 to 1919. Chairman of the pension committee, deputy chairman of the municipal committee, and member of the tax committee and child welfare committee in Svanskog. Member of the municipal committee in Bengtsfors from 1931 to 1934, of the elementary school board from 1932 to 1935, and its chairman from 1934 to 1935. Board member of Bengtsfors Mission Church from 1903 to 1911 and since 1921, of Dalsland Mission Society since 1926, secretary since 1932, conductor of Dalsland Christian Singers Association since 1919. Travelled to Denmark in 1936, Germany and Czechoslovakia in 1937. Published: songbook \"Pilgrim's Longing to Return Home\" (1896), \"Changes\" (poems, 1916), Dalsland Mission Society's 50-year report (1936), \"Promoters in the Fields of Devotion Movements\" (manuscript, 1942), composed music. Hobbies: Music, landscape research.",
    "structured": {
        "@context": "https://schema.org",
        "@type": "Person",
        "name": "Frans Oskar Myren",
        "birthDate": "1878-12-01",
        "birthPlace": "Nössemark, Dalsland",
        "nationality": "Swedish",
        "occupation": "Iron Merchant",
        "address": {
            "@type": "PostalAddress",
            "addressLocality": "Bengtsfors"
        },
        "parents": [
            {
                "@type": "Person",
                "name": "Elias Jonsson"
            },
            {
                "@type": "Person",
                "name": "Maria Lisa Andreasdotter"
            }
        ],
        "spouse": {
            "@type": "Person",
            "name": "Ellen Severinsson"
        },
        "education": [
            {
                "@type": "EducationalOccupationalCredential",
                "credentialCategory": "Practical School",
                "educationalLevel": "Karlskoga",
                "startDate": "1897",
                "endDate": "1898"
            },
            {
                "@type": "EducationalOccupationalCredential",
                "credentialCategory": "Theoretical Music Studies",
                "educationalAttainment": "Hermods"
            }
        ],
        "worksFor": [
            {
                "@type": "Organization",
                "name": "Svaneholm Bruk",
                "jobTitle": "Head of Accounting",
                "startDate": "1911",
                "endDate": "1919"
            },
            {
                "@type": "Organization",
                "name": "Säffle",
                "jobTitle": "Head of Accounting",
                "startDate": "1919",
                "endDate": "1920"
            },
            {
                "@type": "Organization",
                "name": "AB Petersons Järnhandel",
                "jobTitle": "Co-owner and Managing Director",
                "startDate": "1921"
            }
        ],
        "memberOf": [
            {
                "@type": "Organization",
                "name": "Halden",
                "jobTitle": "Organist and Choir Leader",
                "startDate": "1898",
                "endDate": "1900"
            },
            {
                "@type": "Organization",
                "name": "Bengtsfors",
                "jobTitle": "Organist and Choir Leader",
                "startDate": "1902",
                "endDate": "1911"
            },
            {
                "@type": "Organization",
                "name": "Svanskog",
                "jobTitle": "Organist and Choir Leader",
                "startDate": "1911",
                "endDate": "1919"
            }
        ],
        "committeeMemberships": [
            {
                "@type": "Organization",
                "name": "Svanskog",
                "jobTitle": "Chairman of Pension Committee",
                "startDate": "Unknown"
            },
            {
                "@type": "Organization",
                "name": "Svanskog",
                "jobTitle": "Deputy Chairman of Municipal Committee"
            },
            {
                "@type": "Organization",
                "name": "Svanskog",
                "jobTitle": "Member of Tax Committee"
            },
            {
                "@type": "Organization",
                "name": "Svanskog",
                "jobTitle": "Member of Child Welfare Committee"
            },
            {
                "@type": "Organization",
                "name": "Bengtsfors",
                "jobTitle": "Member of Municipal Committee",
                "startDate": "1931",
                "endDate": "1934"
            },
            {
                "@type": "Organization",
                "name": "Bengtsfors",
                "jobTitle": "Member of Elementary School Board",
                "startDate": "1932",
                "endDate": "1935"
            },
            {
                "@type": "Organization",
                "name": "Bengtsfors",
                "jobTitle": "Chairman of Elementary School Board",
                "startDate": "1934",
                "endDate": "1935"
            }
        ],
        "boardMemberships": [
            {
                "@type": "Organization",
                "name": "Bengtsfors Mission Church",
                "jobTitle": "Board Member",
                "startDate": "1903",
                "endDate": "1911"
            },
            {
                "@type": "Organization",
                "name": "Bengtsfors Mission Church",
                "jobTitle": "Board Member",
                "startDate": "1921"
            },
            {
                "@type": "Organization",
                "name": "Dalsland Mission Society",
                "jobTitle": "Board Member",
                "startDate": "1926"
            }
        ],
        "secretaryOfOrganization": {
            "@type": "Organization",
            "name": "Dalsland Mission Society",
            "jobTitle": "Secretary",
            "startDate": "1932"
        },
        "conductorOfOrganization": {
            "@type": "Organization",
            "name": "Dalsland Christian Singers Association",
            "jobTitle": "Conductor",
            "startDate": "1919"
        },
        "travels": [
            {
                "@type": "Place",
                "name": "Denmark",
                "startDate": "1936"
            },
            {
                "@type": "Place",
                "name": "Germany"
            },
            {
                "@type": "Place",
                "name": "Czechoslovakia",
                "startDate": "1937"
            }
        ],
        "publications": [
            "Pilgrim's Longing to Return Home (1896)",
            "Changes (poems, 1916)",
            "Dalsland Mission Society's 50-Year Report (1936)",
            "Promoters in the Fields of Devotion Movements (manuscript, 1942)"
        ],
        "hobbies": "Music, Landscape Research"
    },
    "occupations": {
        "career": [
            {
                "occupational_title": "Office Clerk",
                "workplace": "Bengtsfors",
                "industry": "Unknown",
                "start_date": "1901"
            },
            {
                "occupational_title": "Head of Accounting",
                "workplace": "Svaneholm® Bruk",
                "industry": "Iron industry",
                "start_date": "1911"
            },
            {
                "occupational_title": "Head of Accounting",
                "workplace": "Säffle",
                "industry": "Unknown",
                "start_date": "1919"
            },
            {
                "occupational_title": "Co-owner and Managing Director",
                "workplace": "AB Petersons Järnhandel",
                "industry": "Iron trade",
                "start_date": "1921"
            }
        ]
    }
}