{
    "original": "LEIJONHUFVUD, Stig Abraham, Friherre, Bergsingenjör, Äppelviken, f V :a Ryd, Upps 1. 27/11 00 av domänintendent friherre E G L o frih:an Louise Rålamb, gm Luisa Forabosco. Studex Upps 20, bergsingex KTH 26. Vik lär v bergssk i Falun 27, Jernkont :s stip i Österr 0 Tyskl 27—28, anst i bergsing.fma Hytten-berg Sthlm 28—29, lab.chef v J &amp; C G Bolinders Mek Verkst AB 29—33, forskn.resa t Engl, v Bolinders Fabr AB 33—34, ass o konsult injr 1 fma Volator, Lundberg &amp; Co, Sthlm 34—35. ensamrepr i Sthlm f fma Meyerhofer &amp; Co i Zurich samt f Elex AG där sed. 36 und eg fma. Av trycket: Medarb i Beyer-Desimons Flughafenanlagen (30), i Sv Tekn Uppslagsbok II, kap Ugnar (39), upps i tekn tidskr. Specialitet: Ugnsteknik o gasrening. Led Sv Tekn.frn.",
    "translated": "LEIJONHUFVUD, Stig Abraham, Baron, Mining Engineer, Äppelviken, born in Ryd, Uppsala, on November 27th, 1900, son of Estate Superintendent Baron E.G.L. Leijonhufvud and Baroness Louise Rålamb, married to Luisa Forabosco. Studied at Uppsala University in 1920, became a mining engineer at the Royal Institute of Technology in Stockholm in 1926. Worked as a teacher at the Bergsskolan in Falun in 1927, held a scholarship from Jernkont for studies in Austria and Germany from 1927 to 1928, employed at the engineering firm Hyttenberg in Stockholm from 1928 to 1929, lab manager at J&C G Bolinders Mechanical Works AB from 1929 to 1933, conducted research trips to England for Bolinders Fabr AB from 1933 to 1934, and worked as an assistant and consultant engineer for the company Volator, Lundberg & Co in Stockholm from 1934 to 1935. Sole representative in Stockholm for Meyerhofer & Co in Zurich and for Elex AG since 1936 in his own business. Published works include contributions to Beyer-Desimon's Airfield Facilities (1930), the Swedish Technical Encyclopedia II, chapter on ovens (1939), and articles in technical journals. Specialized in oven technology and gas purification. Member of the Swedish Engineering Society.",
    "structured": {
        "@context": "https://schema.org",
        "@type": "Person",
        "name": "Stig Abraham Leijonhufvud",
        "birthDate": "1900-11-27",
        "birthPlace": "Ryd, Uppsala",
        "nationality": "Swedish",
        "description": "Baron, Mining Engineer, specialized in oven technology and gas purification.",
        "spouse": "Luisa Forabosco",
        "education": [
            {
                "@type": "CollegeOrUniversity",
                "name": "Uppsala University",
                "startDate": "1920"
            },
            {
                "@type": "CollegeOrUniversity",
                "name": "Royal Institute of Technology",
                "startDate": "1926",
                "endDate": "1927"
            }
        ],
        "workExperience": [
            {
                "@type": "JobPosting",
                "title": "Teacher",
                "startDate": "1927",
                "endDate": "1927",
                "location": "Bergsskolan, Falun"
            },
            {
                "@type": "ScholarlyArticle",
                "name": "Jernkont Scholarship",
                "startDate": "1927",
                "endDate": "1928",
                "publisher": "Jernkont"
            },
            {
                "@type": "OrganizationRole",
                "title": "Lab Manager",
                "startDate": "1928",
                "endDate": "1929",
                "organization": {
                    "@type": "Organization",
                    "name": "J&C G Bolinders Mechanical Works AB",
                    "location": "Stockholm"
                }
            },
            {
                "@type": "OrganizationRole",
                "title": "Researcher",
                "startDate": "1933",
                "endDate": "1934",
                "organization": {
                    "@type": "Organization",
                    "name": "Bolinders Fabr AB",
                    "location": "England"
                }
            },
            {
                "@type": "OrganizationRole",
                "title": "Assistant and Consultant Engineer",
                "startDate": "1934",
                "endDate": "1935",
                "organization": {
                    "@type": "Organization",
                    "name": "Volator, Lundberg & Co",
                    "location": "Stockholm"
                }
            },
            {
                "@type": "OrganizationRole",
                "title": "Sole Representative",
                "startDate": "1936",
                "organization": [
                    {
                        "@type": "Organization",
                        "name": "Meyerhofer & Co",
                        "location": "Zurich"
                    },
                    {
                        "@type": "Organization",
                        "name": "Elex AG",
                        "location": "Stockholm"
                    }
                ]
            }
        ],
        "memberOf": [
            {
                "@type": "Organization",
                "name": "Swedish Engineering Society"
            }
        ],
        "publication": [
            {
                "@type": "Article",
                "name": "Beyer-Desimon's Airfield Facilities",
                "datePublished": "1930",
                "publisher": "Beyer-Desimon"
            },
            {
                "@type": "Article",
                "name": "Swedish Technical Encyclopedia",
                "datePublished": "1939",
                "about": "Ovens"
            }
        ]
    },
    "occupations": {
        "career": [
            {
                "occupational_title": "Bergsingenjör",
                "workplace": "Bergsskolan",
                "industry": "Education",
                "start_date": "1927"
            },
            {
                "occupational_title": "Stipendiary at Jernkont",
                "workplace": "Austria and Germany",
                "industry": "Mining",
                "start_date": "1927"
            },
            {
                "occupational_title": "Lab Chief",
                "workplace": "J & C G Bolinders Mek Verkst AB",
                "industry": "Engineering",
                "start_date": "1929"
            },
            {
                "occupational_title": "Researcher",
                "workplace": "Bolinders Fabr AB",
                "industry": "Engineering",
                "start_date": "1933"
            },
            {
                "occupational_title": "Assistant and Consultant Engineer",
                "workplace": "Volator, Lundberg & Co",
                "industry": "Engineering",
                "start_date": "1934"
            }
        ]
    }
}