{
    "original": "OHLSSON, Malte, Bankdirektör, Hässleholm, f N Åkarp, Krst l, 5/4 93 av Ola Johansson o Kristina Bengtsson, gm Ruth Håkansson. Folksk, självstud. Anst ss skogs- o sågvks-förm 27—32, dir Hshlm kred.frn fr 32, v. dir o deläg Hshlm torvströfabr M Ohlsson &amp; C:o, v. dir Fastigh.AB Kornet, inneh Hshlm kol-&amp; vedaff. V. styr.ordf Hshlm kred.frn, styr.led Hshlm hantv- &amp; ind.frn, Nordskå hem-bygdsfrn, styr.suppl Sv kred.frn :rs samman-slutn, rev Tidn.AB N Skåne. Fd led dräts.kamm, led lönenmd, nmdem V Göinge hds-rätt. Resor: Tyskl 21, 36, Norge 37, Danm ett 20-t ggr. SiriusO (VIII).",
    "translated": "OHLSSON, Malte, Bank Director, Hässleholm, born in Åkarp, Baptized 5/4 1893, son of Ola Johansson and Kristina Bengtsson, married to Ruth Håkansson. Primary school education, self-study. Employed in forestry and sawmill management from 1927 to 1932, then became director of Hässleholm credit association from 1932, also vice director and co-owner of Hässleholm peat straw factory M Ohlsson & Co., vice director of Real Estate AB Kornet, owner of Hässleholm coal and firewood business. Vice chairman of Hässleholm credit association, board member of Hässleholm trade and industry association, Nordskå (North Scania) local heritage association, member of the board of Swedish credit union federation. Former member of the finance committee, member of the salary committee, lay judge at Västra Göinge district court. Travel: Germany 1921, 1936, Norway 1937, Denmark around 20 times. Awarded the Sirius medal (eighth class).",
    "structured": {
        "@context": "https://schema.org",
        "@type": "Person",
        "name": "Malte Ohlsson",
        "jobTitle": "Bank Director",
        "address": {
            "@type": "PostalAddress",
            "addressLocality": "Hässleholm"
        },
        "birthDate": "1893-04-05",
        "birthPlace": "Åkarp",
        "parents": [
            {
                "@type": "Person",
                "name": "Ola Johansson"
            },
            {
                "@type": "Person",
                "name": "Kristina Bengtsson"
            }
        ],
        "spouse": {
            "@type": "Person",
            "name": "Ruth Håkansson"
        },
        "educationalLevel": "Primary school",
        "worksFor": [
            {
                "@type": "Organization",
                "name": "Hässleholm credit association"
            },
            {
                "@type": "Organization",
                "name": "Hässleholm peat straw factory M Ohlsson & Co."
            },
            {
                "@type": "Organization",
                "name": "Real Estate AB Kornet"
            }
        ],
        "owns": [
            {
                "@type": "Organization",
                "name": "Hässleholm coal and firewood business"
            }
        ],
        "affiliations": [
            {
                "@type": "Organization",
                "name": "Hässleholm trade and industry association"
            },
            {
                "@type": "Organization",
                "name": "Nordskå local heritage association"
            },
            {
                "@type": "Organization",
                "name": "Swedish credit union federation"
            }
        ],
        "former": [
            {
                "@type": "Organization",
                "name": "finance committee"
            },
            {
                "@type": "Organization",
                "name": "salary committee"
            },
            {
                "@type": "Organization",
                "name": "lay judge at Västra Göinge district court"
            }
        ],
        "awards": [
            {
                "@type": "Order",
                "name": "Sirius medal",
                "description": "Eighth class"
            }
        ],
        "travelHistory": [
            {
                "@type": "Place",
                "name": "Germany"
            },
            {
                "@type": "Place",
                "name": "Norway"
            },
            {
                "@type": "Place",
                "name": "Denmark"
            }
        ]
    },
    "occupations": {
        "career": [
            {
                "occupational_title": "Forestry and Sawmill Management",
                "workplace": "Unknown",
                "industry": "Forestry and Sawmill",
                "start_date": "1927"
            },
            {
                "occupational_title": "Director, Hässleholm Credit Association",
                "workplace": "Hässleholm",
                "industry": "Banking",
                "start_date": "1932"
            },
            {
                "occupational_title": "Vice Director and Co-owner, Hässleholm Peat Straw Factory M Ohlsson & Co.",
                "workplace": "Hässleholm",
                "industry": "Manufacturing (Peat Straw)",
                "start_date": "Unknown"
            },
            {
                "occupational_title": "Vice Director, Real Estate AB Kornet",
                "workplace": "Unknown",
                "industry": "Real Estate",
                "start_date": "Unknown"
            },
            {
                "occupational_title": "Owner, Hässleholm Coal and Firewood Business",
                "workplace": "Hässleholm",
                "industry": "Retail (Coal and Firewood)",
                "start_date": "Unknown"
            }
        ]
    }
}