{
    "original": "HAGNE, Carl Adolf Seth, Direktör, Göteborg, f V Frölunda, Gbg o Boh län, 7/1 91 av hemm.äg A Johanson o Johanna Andersson, gm Birgitta Lundgren. V:a Realsk Gbg, hdlsinst. Hdlsbitr fma Frans Lundin Gbg 10, d:o fma Gulin, Weidenborg &amp; Co 11—15. Dir i eget företag, AB Hagne, Weidenborg &amp; Co Gbg sed. dess start 16. Komp Weidenborg uttr ur fman 35, sonen Herbert Hagne intr ss medarb 43. Styr.led o kassör i Frn Gbgs Herrekiperingar. Resor: Norge, Danm, Engl, Tyskl, Frankr 23—32. Inneh Sv :es Köpm.-frbs ftjt g. Tillh Göta Coldin, W6, Bowl.kl 3:an Gbg mfl idr.sam.slutn o klubbar. Hobbies: Idrott, alla slag.",
    "translated": "HAGNE, Carl Adolf Seth, Director, Gothenburg, born in Frölunda, Gothenburg and Bohus County, on January 7, 1891, to home owners A Johanson and Johanna Andersson, married to Birgitta Lundgren. Attended Västra Real School in Gothenburg, trade institution. Worked as a sales assistant for Frans Lundin in Gothenburg from 1910, and for Gulin, Weidenborg & Co from 1911 to 1915. Became director of his own company, AB Hagne, Weidenborg & Co in Gothenburg since its establishment in 1916. Weidenborg left the company in 1935, and his son Herbert Hagne joined as an employee in 1943. He served as a board member and treasurer in Från Gothenburg's Gentlemen's Apparel. Traveled to Norway, Denmark, England, Germany, and France from 1923 to 1932. Holds positions in the Association of Gothenburg Merchants and Traders, Gothenburg Coldin Association, Bowl Club No. 3 in Gothenburg, and other sports and recreational organizations. Hobbies: Sports, all kinds.",
    "structured": {
        "@context": "https://schema.org",
        "@type": "Person",
        "name": "Carl Adolf Seth Hagne",
        "birthDate": "1891-01-07",
        "birthPlace": "Frölunda, Gothenburg, Gothenburg and Bohus County",
        "father": "A Johanson",
        "mother": "Johanna Andersson",
        "spouse": "Birgitta Lundgren",
        "education": [
            {
                "@type": "EducationalOrganization",
                "name": "Västra Real School",
                "location": "Gothenburg"
            }
        ],
        "workExperience": [
            {
                "@type": "Organization",
                "name": "Frans Lundin",
                "startDate": "1910",
                "endDate": "1911",
                "position": "Sales Assistant"
            },
            {
                "@type": "Organization",
                "name": "Gulin, Weidenborg & Co",
                "startDate": "1911",
                "endDate": "1915",
                "position": "Sales Assistant"
            },
            {
                "@type": "Organization",
                "name": "AB Hagne, Weidenborg & Co",
                "startDate": "1916",
                "position": "Director"
            }
        ],
        "businessMemberOf": {
            "@type": "Organization",
            "name": "Från Gothenburg's Gentlemen's Apparel",
            "position": [
                "Board Member",
                "Treasurer"
            ]
        },
        "travelHistory": [
            {
                "@type": "Place",
                "name": "Norway"
            },
            {
                "@type": "Place",
                "name": "Denmark"
            },
            {
                "@type": "Place",
                "name": "England"
            },
            {
                "@type": "Place",
                "name": "Germany"
            },
            {
                "@type": "Place",
                "name": "France"
            }
        ],
        "memberOf": [
            {
                "@type": "Organization",
                "name": "Association of Gothenburg Merchants and Traders"
            },
            {
                "@type": "Organization",
                "name": "Gothenburg Coldin Association"
            },
            {
                "@type": "Organization",
                "name": "Bowl Club No. 3",
                "description": "Gothenburg"
            }
        ],
        "hobbies": "Sports"
    },
    "occupations": {
        "career": [
            {
                "occupational_title": "Sales Assistant",
                "workplace": "Frans Lundin",
                "industry": "Trade",
                "start_date": "1910"
            },
            {
                "occupational_title": "Sales Assistant",
                "workplace": "Gulin, Weidenborg & Co",
                "industry": "Trade",
                "start_date": "1911"
            },
            {
                "occupational_title": "Director",
                "workplace": "AB Hagne, Weidenborg & Co",
                "industry": "Trade",
                "start_date": "1916"
            }
        ]
    }
}