{
    "original": "BRAG, Sigurd, Nils Otto, Disponent, Karlstad, f Kungsbacka 25/10 83 av fabr O B o Augusta Nilsson, gm Anna Rosén. Hdlsinst. Anst i Marks Linnemanufaktur AB Kungs-säter 02—08, Borås Tekn Vävsk, anst o stud i utl 08—12, tekn led v A J Borgs Väfveri AB Kinnahult 12—27, vkst dir o disp i Karlstads Spinneri &amp; Väfveri AB sed. 27. Led av Sv Arb.giv.frn o Karlst hdlskamm, Sv Textiltekn Riksfrb, Odd Fellow, Rotary, KAK, KMK mfl. Hobbies: Motorsport o fiske.",
    "translated": "BRAG, Sigurd, Nils Otto, Manager, Karlstad, born in Kungsbacka on October 25, 1883, to factory worker O B and Augusta Nilsson, married to Anna Rosén. Trade education. Worked at Marks Linnemanufaktur AB in Kungs-säter from 1902 to 1908, studied and worked abroad at Borås Tekn Vävsk from 1908 to 1912, technical manager at A J Borgs Väfveri AB in Kinnahult from 1912 to 1927, and then served as the director and manager at Karlstads Spinneri &amp; Väfveri AB since 1927. Active member of the Swedish Employers' Federation and the Karlstad Chamber of Commerce, Swedish Textile Technology Association, Odd Fellow, Rotary, KAK, KMK, and others. Hobbies: Motorsports and fishing.",
    "structured": {
        "@context": "https://schema.org",
        "@type": "Person",
        "name": "Sigurd Nils Otto Brag",
        "jobTitle": "Manager",
        "gender": "Male",
        "birthDate": "1883-10-25",
        "birthPlace": "Kungsbacka, Sweden",
        "father": {
            "@type": "Person",
            "name": "O B"
        },
        "mother": {
            "@type": "Person",
            "name": "Augusta Nilsson"
        },
        "spouse": {
            "@type": "Person",
            "name": "Anna Rosén"
        },
        "education": {
            "@type": "TradeSchool",
            "name": "Trade Education"
        },
        "memberOf": [
            {
                "@type": "Organization",
                "name": "Swedish Employers' Federation"
            },
            {
                "@type": "Organization",
                "name": "Karlstad Chamber of Commerce"
            },
            {
                "@type": "Organization",
                "name": "Swedish Textile Technology Association"
            },
            {
                "@type": "Organization",
                "name": "Odd Fellow"
            },
            {
                "@type": "Organization",
                "name": "Rotary"
            },
            {
                "@type": "Organization",
                "name": "KAK"
            },
            {
                "@type": "Organization",
                "name": "KMK"
            }
        ],
        "nationality": {
            "@type": "Country",
            "name": "Sweden"
        },
        "worksFor": {
            "@type": "Organization",
            "name": "Karlstads Spinneri & Väfveri AB",
            "jobTitle": "Director and Manager",
            "startDate": "1927"
        },
        "hobbies": [
            "Motorsports",
            "Fishing"
        ]
    },
    "occupations": {
        "career": [
            {
                "occupational_title": "Disponent",
                "workplace": "Marks Linnemanufaktur AB",
                "industry": "Textile",
                "start_date": "1902"
            },
            {
                "occupational_title": "Anst i Marks Linnemanufaktur AB",
                "workplace": "Kungs-säter",
                "industry": "Textile",
                "start_date": "1902"
            },
            {
                "occupational_title": "Borås Tekn Vävsk",
                "workplace": "Borås",
                "industry": "Textile",
                "start_date": "1908"
            },
            {
                "occupational_title": "Tekn led v A J Borgs Väfveri AB",
                "workplace": "Kinnahult",
                "industry": "Textile",
                "start_date": "1912"
            },
            {
                "occupational_title": "vkst dir o disp i Karlstads Spinneri & Väfveri AB",
                "workplace": "Karlstad",
                "industry": "Textile",
                "start_date": "1927"
            }
        ]
    }
}