{
    "original": "FRICK, Bo Rudolf, Direktör, Stockholm, f Jkp 1/10 94 av v. hhövd N F o Gertrud Hay, gm Helena Mannerhjärta. Studex 13, jur kand 21, fil kand 22. Tingstjg 22, tjm i bankirfma Merck, Finck &amp; Co Munchen 22—23, i Banque de Suéde et de Paris i Paris 23—24, i bankirfma J Henry Schröder &amp; Co London 24—25, i Sv hdlsbkn Sthlm 25—28, vkst dir Allm kred.försäkrs.AB Sthlm 29—34, sekr i exp.-kreditnmdn 33 o vkst dir där sed. 39, tillika vkst dir AB Industrikredit sed. 34. Sakk v förh i Moskva o Riga 41, suppl i clear.nmdn sed. 39. Res i off uppdr t Norge, Danm, Lettl, Tyskl, Engl, Frankr, Schweiz, Tjeckoslov 34—39. • Av trycket: Upps i facktidskr rör off o priv kred.försäkr. RNO, RVO.",
    "translated": "FRICK, Bo Rudolf, Director, Stockholm, b. Jönköping October 1, 1894, son of Vice Headmaster N F and Gertrud Hay, m. Helena Mannerheart. Graduated from high school at the age of 13, obtained a law degree in 1921, and a philosophy degree in 1922. Worked for the court in 1922, served as an employee in the banking firm Merck, Finck & Co in Munich from 1922 to 1923, worked in Banque de Suède et de Paris in Paris from 1923 to 1924, worked in the banking firm J Henry Schröder & Co in London from 1924 to 1925, worked at Sv handelsbanken Stockholm from 1925 to 1928, served as a managing director of Allmänna kreditförsäkrings AB Stockholm from 1929 to 1934, served as a secretary in the export credit board from 1933 and as a managing director there since 1939, also served as a managing director of AB Industrikredit since 1934. Served as an expert in Moscow and Riga in 1941, and as a substitute in the clearing board since 1939. Made official visits to Norway, Denmark, Latvia, Germany, England, France, Switzerland, and Czechoslovakia from 1934 to 1939. Published in specialized journals on official and private credit insurance. Recipient of the Royal Norwegian Order of St. Olav and the Order of Vasa.",
    "structured": {
        "@context": "https://schema.org",
        "@type": "Person",
        "name": "Bo Rudolf Frick",
        "jobTitle": "Director",
        "birthDate": "1894-10-01",
        "birthPlace": "Jönköping",
        "deathDate": null,
        "nationality": "Swedish",
        "parents": [
            {
                "@type": "Person",
                "name": "N. F. Frick",
                "jobTitle": "Vice Headmaster"
            },
            {
                "@type": "Person",
                "name": "Gertrud Hay"
            }
        ],
        "spouse": {
            "@type": "Person",
            "name": "Helena Mannerheart"
        },
        "education": [
            {
                "@type": "EducationalOccupationalCredential",
                "credentialCategory": "High school",
                "startDate": null,
                "endDate": null,
                "description": "Graduated at the age of 13"
            },
            {
                "@type": "EducationalOccupationalCredential",
                "credentialCategory": "Law degree",
                "startDate": "1921",
                "endDate": null
            },
            {
                "@type": "EducationalOccupationalCredential",
                "credentialCategory": "Philosophy degree",
                "startDate": "1922",
                "endDate": null
            }
        ],
        "worksFor": [
            {
                "@type": "Organization",
                "name": "Court",
                "startDate": "1922",
                "endDate": "1922"
            },
            {
                "@type": "Organization",
                "name": "Merck, Finck & Co",
                "location": "Munich",
                "startDate": "1922",
                "endDate": "1923"
            },
            {
                "@type": "Organization",
                "name": "Banque de Suède et de Paris",
                "location": "Paris",
                "startDate": "1923",
                "endDate": "1924"
            },
            {
                "@type": "Organization",
                "name": "J Henry Schröder & Co",
                "location": "London",
                "startDate": "1924",
                "endDate": "1925"
            },
            {
                "@type": "Organization",
                "name": "Sv handelsbanken Stockholm",
                "startDate": "1925",
                "endDate": "1928"
            },
            {
                "@type": "Organization",
                "name": "Allmänna kreditförsäkrings AB Stockholm",
                "startDate": "1929",
                "endDate": "1934",
                "jobTitle": "Managing Director"
            },
            {
                "@type": "Organization",
                "name": "Export Credit Board",
                "startDate": "1933",
                "endDate": null,
                "jobTitle": "Secretary"
            },
            {
                "@type": "Organization",
                "name": "AB Industrikredit",
                "startDate": "1934",
                "endDate": null,
                "jobTitle": "Managing Director"
            }
        ],
        "memberOf": [
            {
                "@type": "Organization",
                "name": "Clearing Board",
                "startDate": "1939",
                "endDate": null,
                "jobTitle": "Substitute"
            }
        ],
        "expertise": [
            "Official and private credit insurance"
        ],
        "awards": [
            {
                "@type": "Order",
                "name": "Royal Norwegian Order of St. Olav"
            },
            {
                "@type": "Order",
                "name": "Order of Vasa"
            }
        ],
        "sameAs": []
    },
    "occupations": {
        "career": [
            {
                "occupational_title": "Tjm i bankirfma",
                "workplace": "Merck, Finck & Co",
                "industry": "Banking",
                "start_date": "1922"
            },
            {
                "occupational_title": "Tjm i Banque de Suéde et de Paris",
                "workplace": "Paris",
                "industry": "Banking",
                "start_date": "1923"
            },
            {
                "occupational_title": "Tjm i bankirfma J Henry Schröder & Co",
                "workplace": "London",
                "industry": "Banking",
                "start_date": "1924"
            },
            {
                "occupational_title": "Tjm i Sv hdlsbkn",
                "workplace": "Stockholm",
                "industry": "Banking",
                "start_date": "1925"
            },
            {
                "occupational_title": "Vkst dir Allm kred.försäkrs.AB",
                "workplace": "Stockholm",
                "industry": "Insurance",
                "start_date": "1929"
            },
            {
                "occupational_title": "Sekr i exp.-kreditnmdn",
                "workplace": "Export Credit Board",
                "industry": "Government",
                "start_date": "1933"
            },
            {
                "occupational_title": "Vkst dir AB Industrikredit",
                "workplace": "Stockholm",
                "industry": "Finance",
                "start_date": "1934"
            },
            {
                "occupational_title": "Sakk v förh",
                "workplace": "Moscow",
                "industry": "Government",
                "start_date": "1941"
            }
        ]
    }
}