{
    "original": "ERICSON, Johan Teodor, Grosshandlare, Stockholm, f St Kil, Värml, 5/6 82, gm Ellen \"Lindqvist. Hdlssk Sthlm 02, stud i Tyskl, Engl Frankr 02—04. Anst i byggn.branschen i Sthlm 09—12, start eg trav- o byggn.mtrlrör i ’Sthlm, Fma Teodor Ericson, 12; ombud i Sthlm f AB Åtvidabergs Ind f parkettgolv f ed. 23; ensam försälj i Sv f Schröders Kork-solerings AB Ulvsunda sed. 30 samt styr.led denna fma. Styr.led i AB Ska Bkns Sthlms-sont 36. Av stdsflm vald rev f drätselnmd, stadskoll, gatunmd, hdls- o sjöf.nmd, inskriv-i.rev mfl, led av tax.nmd. Odd Fellow. RNO.",
    "translated": "ERICSON, Johan Teodor, merchant, Stockholm, born in St Kil, Värmland, on June 5th, 1882, married to Ellen \"Lindqvist. Attended trade school in Stockholm in 1902, studied in Germany, England, and France from 1902-1904. Employed in the construction industry in Stockholm from 1909-1912, started own business in carriage and building materials in Stockholm, named Teodor Ericson, in 1912; representative in Stockholm for AB Åtvidabergs Industries selling parquet flooring from 1923; sole salesperson in Sweden for Schröders Cork Insulation AB in Ulvsunda since 1930, and served on the board of directors. Board member of AB Ska Bkns Stockholm Branch in 1936. Elected member of various municipal committees, such as finance committee, city checks committee, street committee, trade and shipping committee, and others, as well as a member of the tax committee. Member of the Odd Fellow fraternity. Awarded with the Royal Order of the North Star (RNO).",
    "structured": {
        "@context": "https://schema.org",
        "@type": "Person",
        "name": "Johan Teodor Ericson",
        "jobTitle": "Merchant",
        "birthDate": "1882-06-05",
        "birthPlace": "St Kil, Värmland, Sweden",
        "spouse": {
            "@type": "Person",
            "name": "Ellen Lindqvist"
        },
        "education": [
            {
                "@type": "EducationalOrganization",
                "name": "Trade School",
                "location": "Stockholm, Sweden",
                "startDate": "1902",
                "endDate": "1902"
            },
            {
                "@type": "EducationalOrganization",
                "name": "Study Abroad",
                "location": "Germany, England, France",
                "startDate": "1902",
                "endDate": "1904"
            }
        ],
        "worksFor": [
            {
                "@type": "Organization",
                "name": "Construction Industry",
                "location": "Stockholm, Sweden",
                "startDate": "1909",
                "endDate": "1912"
            },
            {
                "@type": "Organization",
                "name": "Teodor Ericson",
                "industry": "Carriage and Building Materials",
                "location": "Stockholm, Sweden",
                "startDate": "1912"
            },
            {
                "@type": "Organization",
                "name": "AB Åtvidabergs Industries",
                "department": "Parquet Flooring",
                "location": "Stockholm, Sweden",
                "startDate": "1923"
            },
            {
                "@type": "Organization",
                "name": "Schröders Cork Insulation AB",
                "location": "Ulvsunda, Sweden",
                "startDate": "1930"
            },
            {
                "@type": "Organization",
                "name": "AB Ska Bkns Stockholm Branch",
                "location": "Stockholm, Sweden",
                "startDate": "1936"
            }
        ],
        "memberOf": [
            {
                "@type": "Organization",
                "name": "Odd Fellow"
            }
        ],
        "awards": [
            {
                "@type": "Order",
                "name": "Royal Order of the North Star (RNO)"
            }
        ]
    },
    "occupations": {
        "career": [
            {
                "occupational_title": "Merchant",
                "workplace": "Stockholm",
                "industry": null,
                "start_date": null
            },
            {
                "occupational_title": "Employee in the construction industry",
                "workplace": "Stockholm",
                "industry": "Building",
                "start_date": "1909"
            },
            {
                "occupational_title": "Founder and owner of carriage and building materials business",
                "workplace": "Stockholm",
                "industry": "Building",
                "start_date": "1912"
            },
            {
                "occupational_title": "Representative for AB Åtvidabergs Industries",
                "workplace": "Stockholm",
                "industry": "Parquet flooring",
                "start_date": "1923"
            },
            {
                "occupational_title": "Sole salesperson for Schröders Cork Insulation AB",
                "workplace": "Ulvsunda",
                "industry": "Cork insulation",
                "start_date": "1930"
            },
            {
                "occupational_title": "Board member of AB Ska Bkns Stockholm Branch",
                "workplace": null,
                "industry": null,
                "start_date": "1936"
            }
        ]
    }
}