{
    "original": "AHLIN, Stig Bertil, Civilingenjör, Landskrona, f Borås 25/12 04 av dir A A o Signe Jansson, gm Lisa Edström. Studex Sthlm 23, KTH (maskintekn o mek tekn) 25—28 o 31, extra stud 28—30. Anst IVA:s ångvärmeinst 31—52, AB Lavator Sthlm 32—33, ing AB Klippans Finpappersbr 33—36, Munksjö AB Jönkp 36—41, nu arb.studiech v öresundsvarvet AB Lkrona. Led Sv Tekn.frn.",
    "translated": "AHLIN, Stig Bertil, Civil Engineer, Landskrona, born in Borås on 25th December 1904, son of director A A and Signe Jansson, married to Lisa Edström. Graduated from Stockholm University in 1923, studied at the Royal Institute of Technology (Mechanical Engineering and Mechanical Technology) from 1925 to 1928 and in 1931, pursued additional studies from 1928 to 1930. Employed at the Steam Heating Institute of the Royal Swedish Academy of Engineering Sciences from 1931 to 1952, AB Lavator in Stockholm from 1932 to 1933, engineer at AB Klippans Finpappersbruk from 1933 to 1936, Munksjö AB in Jönköping from 1936 to 1941, currently engaged in work-study at Öresundsvarvet AB in Landskrona. Member of the Swedish Technical Association.",
    "structured": {
        "@context": "https://schema.org",
        "@type": "Person",
        "name": "Stig Bertil Ahlin",
        "birthDate": "1904-12-25",
        "birthPlace": "Borås, Sweden",
        "familyName": "Ahlin",
        "givenName": "Stig Bertil",
        "nationality": "Swedish",
        "educationalCredentialAwarded": "Civilingenjör",
        "alumniOf": [
            {
                "@type": "CollegeOrUniversity",
                "name": "Stockholm University",
                "startDate": "1925",
                "endDate": "1928"
            },
            {
                "@type": "CollegeOrUniversity",
                "name": "Royal Institute of Technology",
                "startDate": "1925",
                "endDate": "1928"
            }
        ],
        "spouse": {
            "@type": "Person",
            "name": "Lisa Edström"
        },
        "children": [],
        "parent": [
            {
                "@type": "Person",
                "name": "A A Ahlin"
            },
            {
                "@type": "Person",
                "name": "Signe Jansson"
            }
        ],
        "occupation": [
            {
                "@type": "OrganizationRole",
                "title": "Engineer",
                "startDate": "1931",
                "endDate": "1952",
                "namedPosition": "Steam Heating Institute of the Royal Swedish Academy of Engineering Sciences"
            },
            {
                "@type": "OrganizationRole",
                "title": "Engineer",
                "startDate": "1932",
                "endDate": "1933",
                "namedPosition": "AB Lavator"
            },
            {
                "@type": "OrganizationRole",
                "title": "Engineer",
                "startDate": "1933",
                "endDate": "1936",
                "namedPosition": "AB Klippans Finpappersbruk"
            },
            {
                "@type": "OrganizationRole",
                "title": "Engineer",
                "startDate": "1936",
                "endDate": "1941",
                "namedPosition": "Munksjö AB"
            },
            {
                "@type": "OrganizationRole",
                "title": "Work-Study",
                "startDate": "present",
                "namedPosition": "Öresundsvarvet AB"
            }
        ],
        "memberOf": {
            "@type": "Organization",
            "name": "Swedish Technical Association"
        }
    },
    "occupations": {
        "career": [
            {
                "occupational_title": "Civil Engineer",
                "workplace": "IVA's Steam Heating Institute",
                "industry": "Engineering",
                "start_date": "1931"
            },
            {
                "occupational_title": "Engineer",
                "workplace": "AB Lavator",
                "industry": "Unknown",
                "start_date": "1932"
            },
            {
                "occupational_title": "Engineer",
                "workplace": "AB Klippans Finpappersbruk",
                "industry": "Paper manufacturing",
                "start_date": "1933"
            },
            {
                "occupational_title": "Engineer",
                "workplace": "Munksjö AB",
                "industry": "Paper manufacturing",
                "start_date": "1936"
            },
            {
                "occupational_title": "Work-study",
                "workplace": "Öresundsvarvet AB",
                "industry": "Shipbuilding",
                "start_date": "Unknown"
            }
        ]
    }
}