{
    "original": "PETTERSSON, Bror Stefanus, Direktör, Karlstad, f Kungsåra, Västml l, 3/8 83 av lantbrukare W P o Maria Åhlén, gm Gunhild Olsson. Stud v V.ås tekn sk o Bröd Påhlmans hdlsinst Sthlm; 7 års red-, skeppsmäkl-, bk- 0 sped.prakt Engl o Tyskl. Anst ag.fma Hj Söderström Sthlm 02, skpsmklfma Rud Landqvist Sthlm 03—06, skpsmklfma Geo Latus &amp; Co Ltd Hull Engl 06—08, red- o skpsmklfma F G Reinhold Danzig 08—10, bk- o sped.-fma American Express Comp m b H Bremen Tyskl 10—13, O F Ahlmark &amp; Co eftr AB Krist (red, skpsmkl, sped, kolimp o ass, grund 1847, AB 17) sed. 14, vkst dir där 21. Styr.led sistn AB, Värml red.AB, Werml ensk bk AB, Krist stuv.AB, Riksfrn f svenskh bev 1 utl, Stift f hem o läsrum f sjöm; ordf i dir f Sjöm.h (samtl i Karlst). RVOlkl.",
    "translated": "PETTERSSON, Bror Stefanus, Director, Karlstad, b. Kungsåra, Västmanland county, 3/8 83, son of farmer W P and Maria Åhlén, m. Gunhild Olsson. Studied at Västerås Technical School and Bröd Påhlmans Commercial Institute in Stockholm; has 7 years of experience in editing, ship brokering, banking, and forwarding in English and German. Employed by Hj Söderström in Stockholm from 1902, ship brokering firm Rud Landqvist in Stockholm from 1903-1906, ship brokering firm Geo Latus &amp; Co Ltd in Hull, England from 1906-1908, editing and ship brokering firm F G Reinhold in Danzig from 1908-1910, banking and forwarding firm American Express Comp m b H in Bremen, Germany from 1910-1913. Employed by O F Ahlmark &amp; Co eftr AB in Kristinehamn (editor, ship broker, forwarder, coal importer, and agent, established in 1847, joint stock company since 1917) since 1914, promoted to managerial director in 1921. Currently serves on the board of AB, Värmland, Wermlands Enskilda Bank AB, Kristinehamn Steamship AB, National Association for the Promotion of Swedish Interests Abroad, Foundation for Seamen's Homes and Reading Rooms; chairman of the board of Karlstad Maritime Association. Awarded Royal Order of Vasa, Knight Class.",
    "structured": {
        "@context": "https://schema.org",
        "@type": "Person",
        "name": "Bror Stefanus Pettersson",
        "jobTitle": "Director",
        "birthPlace": "Kungsåra, Västmanland county",
        "birthDate": "1883-08-03",
        "parents": [
            {
                "@type": "Person",
                "name": "W P Pettersson",
                "jobTitle": "Farmer"
            },
            {
                "@type": "Person",
                "name": "Maria Åhlén"
            }
        ],
        "spouse": {
            "@type": "Person",
            "name": "Gunhild Olsson"
        },
        "education": {
            "@type": "EducationalOrganization",
            "name": "Västerås Technical School"
        },
        "educationCredential": {
            "@type": "EducationalOccupationalCredential",
            "name": "Bröd Påhlmans Commercial Institute",
            "description": "7 years of study in editing, ship brokering, banking, and forwarding in English and German"
        },
        "workExperience": [
            {
                "@type": "Organization",
                "name": "Hj Söderström",
                "jobTitle": "Employee",
                "startDate": "1902"
            },
            {
                "@type": "Organization",
                "name": "Rud Landqvist",
                "jobTitle": "Ship Brokering Firm",
                "startDate": "1903",
                "endDate": "1906"
            },
            {
                "@type": "Organization",
                "name": "Geo Latus & Co Ltd",
                "jobTitle": "Ship Brokering Firm",
                "location": "Hull, England",
                "startDate": "1906",
                "endDate": "1908"
            },
            {
                "@type": "Organization",
                "name": "F G Reinhold",
                "jobTitle": "Editing and Ship Brokering Firm",
                "location": "Danzig",
                "startDate": "1908",
                "endDate": "1910"
            },
            {
                "@type": "Organization",
                "name": "American Express Comp m b H",
                "jobTitle": "Banking and Forwarding Firm",
                "location": "Bremen, Germany",
                "startDate": "1910",
                "endDate": "1913"
            },
            {
                "@type": "Organization",
                "name": "O F Ahlmark & Co eftr AB",
                "jobTitle": "Managerial Director",
                "location": "Kristinehamn",
                "startDate": "1914",
                "endDate": "present",
                "description": "Editor, Ship Broker, Forwarder, Coal Importer, and Agent"
            }
        ],
        "boardMembership": [
            {
                "@type": "Organization",
                "name": "AB, Värmland"
            },
            {
                "@type": "Organization",
                "name": "Wermlands Enskilda Bank AB"
            },
            {
                "@type": "Organization",
                "name": "Kristinehamn Steamship AB"
            },
            {
                "@type": "Organization",
                "name": "National Association for the Promotion of Swedish Interests Abroad"
            },
            {
                "@type": "Organization",
                "name": "Foundation for Seamen's Homes and Reading Rooms"
            },
            {
                "@type": "Organization",
                "name": "Karlstad Maritime Association",
                "jobTitle": "Chairman of the board"
            }
        ],
        "awards": {
            "@type": "Order",
            "name": "Royal Order of Vasa",
            "grade": "Knight"
        }
    },
    "occupations": {
        "career": [
            {
                "occupational_title": "Editor",
                "workplace": "Hj Söderström",
                "industry": "Publishing",
                "start_date": "1902"
            },
            {
                "occupational_title": "Ship Broker",
                "workplace": "Rud Landqvist",
                "industry": "Shipping",
                "start_date": "1903"
            },
            {
                "occupational_title": "Ship Broker",
                "workplace": "Geo Latus & Co Ltd",
                "industry": "Shipping",
                "start_date": "1906"
            },
            {
                "occupational_title": "Editor & Ship Broker",
                "workplace": "F G Reinhold",
                "industry": "Shipping",
                "start_date": "1908"
            },
            {
                "occupational_title": "Banking & Forwarding",
                "workplace": "American Express Comp m b H",
                "industry": "Banking",
                "start_date": "1910"
            },
            {
                "occupational_title": "Editor, Ship Broker, Forwarder, Coal Importer & Agent",
                "workplace": "O F Ahlmark & Co eftr AB",
                "industry": "Shipping",
                "start_date": "1914"
            },
            {
                "occupational_title": "Managerial Director",
                "workplace": "O F Ahlmark & Co eftr AB",
                "industry": "Shipping",
                "start_date": "1921"
            }
        ]
    }
}