{
    "original": "HOFFSTEN, Carl-David, Bokförläggare, Stockholm, f Sthlm 1/4 73 av bokförl A V Carlson (Hoffsten) o Mathilda Dahlgren, gm Clara Lindquist. Mogh.ex Besk sk 91, Upps univ 91—94, Schartaus 94—95. Anst A V Carlsons bokförl 95, dir sed. 05, dir Nya Tryckeri AB (Lindbergs tryckeri AB) 05—17, dir Byggn AB Brunkeberg sed. 30, Fastigh AB C. P. Dahlgren sed. 28. Deläg Partibokbind o fastigh Sthlm. Led 3. distr pens.nmd t 35, kompch lst 16—23. Ordf Understödsfrn f sv bok-handl sed. 28, skattmäst Stift Bok- &amp; Musik-handl pens.fond sed 27, rev Sv Bokförlägg.-frn sed. 07, ordf Sthlm gymn- o fäktklb av 76 24—37. Resor: Tyskl 02, 23, Island 30, USA, Canada 38, Danm, Norge, Finl fi ggr. RVO; Frimurare, Timmerm.orden, m fi.",
    "translated": "HOFFSTEN, Carl-David, Publisher, Stockholm, born in Stockholm on April 1, 1873, to book publisher A V Carlson (Hoffsten) and Mathilda Dahlgren, married Clara Lindquist. Previously attended primary school in 1891, Uppsala University from 1891 to 1894, and Schartaus Business College from 1894 to 1895. Employed at A V Carlsons publishing house in 1895, became director in 1905, director at Nya Tryckeri AB (Lindbergs tryckeri AB) from 1905 to 1917, director at Byggn AB Brunkeberg since 1930, and director at Fastigh AB C. P. Dahlgren since 1928. Co-owner of Partibokbind and real estate in Stockholm. Member of the 3rd district pension committee from 1935, committee member of the chamber of commerce from 1916 to 1923. Chairman of the Assistance Fund for Swedish Booksellers since 1928, treasurer of the Foundation for Book and Music Retailers Pension Fund since 1927, auditor for the Swedish Publishers Association since 1907, chairman of the Stockholm Gymnastics and Fencing Club from 1924 to 1937. Traveled to Germany in 1902 and 1923, Iceland in 1930, USA and Canada in 1938, and Denmark, Norway, and Finland several times. Honored as Royal Swedish Order of Vasa (RVO). Member of the Freemasons, Carpenter's Guild, and others.",
    "structured": {
        "@context": "https://schema.org/",
        "@type": "Person",
        "name": "Carl-David Hoffsten",
        "jobTitle": "Publisher",
        "address": {
            "@type": "PostalAddress",
            "addressLocality": "Stockholm"
        },
        "birthDate": "1873-04-01",
        "birthPlace": "Stockholm",
        "parents": [
            {
                "@type": "Person",
                "name": "A V Carlson (Hoffsten)",
                "jobTitle": "Book Publisher"
            },
            {
                "@type": "Person",
                "name": "Mathilda Dahlgren"
            }
        ],
        "spouse": {
            "@type": "Person",
            "name": "Clara Lindquist"
        },
        "education": [
            {
                "@type": "EducationalOrganization",
                "name": "Primary School",
                "startDate": "1891",
                "endDate": "1891"
            },
            {
                "@type": "EducationalOrganization",
                "name": "Uppsala University",
                "startDate": "1891",
                "endDate": "1894"
            },
            {
                "@type": "EducationalOrganization",
                "name": "Schartaus Business College",
                "startDate": "1894",
                "endDate": "1895"
            }
        ],
        "work": [
            {
                "@type": "Organization",
                "name": "A V Carlsons Publishing House",
                "startDate": "1895",
                "endDate": "1905",
                "jobTitle": "Employee"
            },
            {
                "@type": "Organization",
                "name": "Nya Tryckeri AB (Lindbergs tryckeri AB)",
                "startDate": "1905",
                "endDate": "1917",
                "jobTitle": "Director"
            },
            {
                "@type": "Organization",
                "name": "Byggn AB Brunkeberg",
                "startDate": "1930",
                "jobTitle": "Director"
            },
            {
                "@type": "Organization",
                "name": "Fastigh AB C. P. Dahlgren",
                "startDate": "1928",
                "jobTitle": "Director"
            }
        ],
        "owns": [
            {
                "@type": "Organization",
                "name": "Partibokbind"
            },
            {
                "@type": "Organization",
                "name": "Real Estate (Stockholm)"
            }
        ],
        "memberOf": [
            "Freemasons",
            "Carpenter's Guild"
        ],
        "traveled": [
            {
                "@type": "Place",
                "name": "Germany",
                "startDate": "1902"
            },
            {
                "@type": "Place",
                "name": "Germany",
                "startDate": "1923"
            },
            {
                "@type": "Place",
                "name": "Iceland",
                "startDate": "1930"
            },
            {
                "@type": "Place",
                "name": "USA, Canada",
                "startDate": "1938"
            },
            {
                "@type": "Place",
                "name": "Denmark, Norway, Finland"
            }
        ],
        "award": "Royal Swedish Order of Vasa"
    },
    "occupations": {
        "career": [
            {
                "occupational_title": "Book publisher",
                "workplace": "A V Carlsons bokförl",
                "industry": "Publishing",
                "start_date": "1895"
            },
            {
                "occupational_title": "Director",
                "workplace": "A V Carlsons bokförl",
                "industry": "Publishing",
                "start_date": "1905"
            },
            {
                "occupational_title": "Director",
                "workplace": "Nya Tryckeri AB (Lindbergs tryckeri AB)",
                "industry": "Printing",
                "start_date": "1905"
            },
            {
                "occupational_title": "Director",
                "workplace": "Byggn AB Brunkeberg",
                "industry": "Construction",
                "start_date": "1930"
            },
            {
                "occupational_title": "Director",
                "workplace": "Fastigh AB C. P. Dahlgren",
                "industry": "Real Estate",
                "start_date": "1928"
            },
            {
                "occupational_title": "Co-owner",
                "workplace": "Partibokbind",
                "industry": "Bookbinding",
                "start_date": null
            },
            {
                "occupational_title": "Co-owner",
                "workplace": "Real estate in Stockholm",
                "industry": "Real Estate",
                "start_date": null
            }
        ]
    }
}