{
    "original": "FRIMAN, Carl Harry, Kapten, Stockholm, f Skövde 14/8 91 av kamrer P E F o Alma Muntzing, gm Märta Skog. Stud i Tyskl 10, 1 Engl 11, ex tekn sk Sthlm 12. Resoffex 15, fänr Vnorrl reg:s res 15, löjtn 18, kapt 30. Ing v A Karlson Metall- &amp; Maskin AB Sthlm 12—16, ch f maskinavd där sed. 16. Styr.led i Falu Mek Verkst AB 17—23. Ordf Tekn frn M S Sthlm 30—32 o 34—36, led Sv Tekn.frn. K m:ts ombud i Sthlms Skyttefrb sed. 34. Resor: Tyskl, Engl, Danm, Norge, Holl, Belg, Schweiz o Ital v öl tillf 10—39. Sthlms Skyt-tefrbs ftJM, Sthlms Lstfrbs ftJM, guldmärken i idrott, skidlöpn, Skytte, pistol (av militära), Arméns skytteM, RiksGM, Mästarmärke g. Hobbies: Arbetet, Skytte, idrott.",
    "translated": "FRIMAN, Carl Harry, Captain, Stockholm, born in Skövde on August 14, 1891, the son of treasurer P. E. F. and Alma Muntzing, married to Märta Skog. Studied in Germany for 10 months, in England for 11 months, and graduated from a technical school in Stockholm in 1912. Commissioned officer examination in 1915, second lieutenant in the reserve of the Northern Infantry Regiment in 1915, promoted to lieutenant in 1918, and to captain in 1930. Employed at A. Karlson Metall- & Machine Co. in Stockholm from 1912 to 1916, then became head of the machinery department there since 1916. Board member of Falu Mek Verkst AB from 1917 to 1923. Chairman of the Technical Society of Stockholm from 1930 to 1932 and 1934 to 1936, member of the Swedish Technical Association. Appointed as a representative by the Royal Majesty's delegate in Stockholm's Sharpshooting Association since 1934. Traveled to Germany, England, Denmark, Norway, Holland, Belgium, Switzerland, and Italy multiple times between 1910 and 1939. Achievements: Stockholm's Sharpshooting Association gold medal, Stockholm's Cross Country Skiing gold medal, marksmanship with gun and pistol (from the military), Army Sharpshooter medal, National Golden Cross in Shooting, Master's badge. Hobbies: Work, shooting, sports.",
    "structured": {
        "@context": "https://schema.org/",
        "@type": "Person",
        "name": "FRIMAN, Carl Harry",
        "birthDate": "1891-08-14",
        "birthPlace": "Skövde",
        "description": "Captain, Stockholm, son of treasurer P. E. F. and Alma Muntzing, married to Märta Skog.",
        "education": [
            {
                "@type": "EducationEvent",
                "schoolName": "Technical School Stockholm",
                "startDate": "1912",
                "endDate": "1912"
            },
            {
                "@type": "EducationEvent",
                "schoolName": "Germany",
                "startDate": "1910",
                "endDate": "1911",
                "description": "Studied for 10 months"
            },
            {
                "@type": "EducationEvent",
                "schoolName": "England",
                "startDate": "1911",
                "endDate": "1912",
                "description": "Studied for 11 months"
            }
        ],
        "work": [
            {
                "@type": "Organization",
                "name": "A. Karlson Metall- & Machine Co.",
                "startDate": "1912",
                "endDate": "1916",
                "description": "Employee"
            },
            {
                "@type": "Organization",
                "name": "A. Karlson Metall- & Machine Co.",
                "startDate": "1916",
                "description": "Head of Machinery Department"
            },
            {
                "@type": "Organization",
                "name": "Falu Mek Verkst AB",
                "startDate": "1917",
                "endDate": "1923",
                "description": "Board Member"
            }
        ],
        "membership": [
            {
                "@type": "Organization",
                "name": "Technical Society of Stockholm",
                "startDate": "1930",
                "endDate": "1932",
                "roleName": "Chairman"
            },
            {
                "@type": "Organization",
                "name": "Technical Society of Stockholm",
                "startDate": "1934",
                "endDate": "1936",
                "roleName": "Chairman"
            },
            {
                "@type": "Organization",
                "name": "Swedish Technical Association",
                "startDate": "unknown"
            },
            {
                "@type": "Organization",
                "name": "Stockholm's Sharpshooting Association",
                "startDate": "1934",
                "roleName": "Royal Majesty's Delegate Representative"
            }
        ],
        "travelHistory": [
            "Germany",
            "England",
            "Denmark",
            "Norway",
            "Holland",
            "Belgium",
            "Switzerland",
            "Italy"
        ],
        "awards": [
            "Stockholm's Sharpshooting Association gold medal",
            "Stockholm's Cross Country Skiing gold medal",
            "Marksmanship with gun and pistol (from the military)",
            "Army Sharpshooter medal",
            "National Golden Cross in Shooting",
            "Master's badge"
        ],
        "hobbies": [
            "Work",
            "Shooting",
            "Sports"
        ]
    },
    "occupations": {
        "career": [
            {
                "occupational_title": "Captain",
                "workplace": "Stockholm",
                "industry": "Military",
                "start_date": "1930"
            },
            {
                "occupational_title": "Commissioned Officer",
                "workplace": "Northern Infantry Regiment",
                "industry": "Military",
                "start_date": "1915"
            },
            {
                "occupational_title": "Second Lieutenant",
                "workplace": "Northern Infantry Regiment",
                "industry": "Military",
                "start_date": "1915"
            },
            {
                "occupational_title": "Lieutenant",
                "workplace": "Northern Infantry Regiment",
                "industry": "Military",
                "start_date": "1918"
            },
            {
                "occupational_title": "Employee",
                "workplace": "A. Karlson Metall- & Machine Co.",
                "industry": "Metallurgy and Mechanical Engineering",
                "start_date": "1912"
            },
            {
                "occupational_title": "Head of Machinery Department",
                "workplace": "A. Karlson Metall- & Machine Co.",
                "industry": "Metallurgy and Mechanical Engineering",
                "start_date": "1916"
            },
            {
                "occupational_title": "Board Member",
                "workplace": "Falu Mek Verkst AB",
                "industry": "Mechanical Engineering",
                "start_date": "1917"
            },
            {
                "occupational_title": "Chairman",
                "workplace": "Technical Society of Stockholm",
                "industry": "Professional Society",
                "start_date": "1930"
            }
        ]
    }
}