{
    "original": "BRÄUTIGAM, Olof August, Civilingenjör, Göteborg, f Gbg 21/3 10 av konsul J A B o Adéle Pettersson, gm Gunborg Kihlberg. Realex Gbg 26, ex Gbgs hdlsinst 28, CTI lägre avd 29—30, h avd 31—35. Driftsing h ESAB i Gbg. Styr.ordf Chalmers stud.kår 35. Led Sv Tekn.frn Sth o Tekn Samf Gbg. °von BRÖMSSEN, Ädoph Magnus, Civilingenjör, Stockholm, f Sthlm 23/7 64 av grhdl A M von B o Charlotta Koch, gm (2) Greta Aurell. Mogenh.ex NLatin 84, KTH (maskinbygg o mek tekn) 85—88. Anst Luth &amp; Roséns El AB 88—91, Schuckert &amp; Co Nurnberg 91—92, åter h Luth &amp; Rosén 92—13, dir där 11—13, inneh eg ing.fma i Sthlm sed. 13. Led Sv Tekn.frn.",
    "translated": "BRÄUTIGAM, Olof August, Civil Engineer, Gothenburg, born in Gothenburg on March 21, 1910, to consul J A B and Adéle Pettersson, married Gunborg Kihlberg. Real exam Gothenburg 1926, graduate of Gothenburg Commercial Institute 1928, lower department of CTI 1929-1930, higher department 1931-1935. Operating engineer at ESAB in Gothenburg. Board chairman of Chalmers Student Union 1935. Member of the Swedish Technical Association from Stockholm and the Technical Society of Gothenburg. °von BRÖMSSEN, Ädoph Magnus, Civil Engineer, Stockholm, born in Stockholm on July 23, 1864, son of Chief Engineer A M von B and Charlotta Koch, married (2) Greta Aurell. Completed secondary school at NLatin in 1884, studied mechanical engineering at the Royal Institute of Technology (KTH) from 1885 to 1888. Employed at Luth & Roséns El AB from 1888 to 1891, Schuckert & Co Nuremberg from 1891 to 1892, returned to Luth & Rosén from 1892 to 1913, director there from 1911 to 1913, currently owns own trading company in Stockholm since 1913. Member of the Swedish Technical Association from...",
    "structured": {
        "@context": "https://schema.org",
        "@type": "Person",
        "name": "Olof August Bräutigam",
        "birthDate": "1910-03-21",
        "birthPlace": "Gothenburg",
        "deathDate": null,
        "nationality": "Swedish",
        "jobTitle": "Civil Engineer",
        "description": "Olof August Bräutigam was a Swedish civil engineer. He was born on March 21, 1910, in Gothenburg to consul J A B and Adéle Pettersson. He was married to Gunborg Kihlberg.",
        "memberOf": [
            {
                "@type": "Organization",
                "name": "Swedish Technical Association",
                "location": "Stockholm"
            },
            {
                "@type": "Organization",
                "name": "Technical Society of Gothenburg",
                "location": "Gothenburg"
            }
        ],
        "education": [
            {
                "@type": "EducationalOccupationalCredential",
                "credentialCategory": "SecondarySchool",
                "credentialAwarded": "Secondary School Diploma",
                "educationalLevel": "SecondaryEducation",
                "awardedBy": {
                    "@type": "Organization",
                    "name": "NLatin"
                },
                "endDate": "1884"
            },
            {
                "@type": "EducationalOccupationalCredential",
                "credentialCategory": "Degree",
                "credentialAwarded": "Bachelor of Science in Mechanical Engineering",
                "educationalLevel": "BachelorDegree",
                "awardedBy": {
                    "@type": "Organization",
                    "name": "Royal Institute of Technology (KTH)"
                },
                "startDate": "1885",
                "endDate": "1888"
            }
        ],
        "work": [
            {
                "@type": "OrganizationRole",
                "startDate": "1926",
                "endDate": null,
                "roleName": "Real Exam - Gothenburg"
            },
            {
                "@type": "OrganizationRole",
                "startDate": "1928",
                "endDate": null,
                "roleName": "Graduate of Gothenburg Commercial Institute"
            },
            {
                "@type": "OrganizationRole",
                "startDate": "1929",
                "endDate": "1930",
                "roleName": "Lower Department of CTI"
            },
            {
                "@type": "OrganizationRole",
                "startDate": "1931",
                "endDate": "1935",
                "roleName": "Higher Department of CTI"
            },
            {
                "@type": "OrganizationRole",
                "startDate": null,
                "endDate": null,
                "roleName": "Operating Engineer at ESAB, Gothenburg"
            },
            {
                "@type": "OrganizationRole",
                "startDate": "1935",
                "endDate": null,
                "roleName": "Board Chairman of Chalmers Student Union"
            },
            {
                "@type": "OrganizationRole",
                "startDate": "1913",
                "endDate": null,
                "roleName": "Owner of trading company (currently)"
            }
        ],
        "spouse": {
            "@type": "Person",
            "name": "Gunborg Kihlberg"
        },
        "parents": [
            {
                "@type": "Person",
                "name": "J A B"
            },
            {
                "@type": "Person",
                "name": "Adéle Pettersson"
            }
        ]
    },
    "occupations": {
        "career": [
            {
                "occupational_title": "Civil Engineer",
                "workplace": "ESAB",
                "industry": "Engineering",
                "start_date": "1931"
            },
            {
                "occupational_title": "Board Chairman",
                "workplace": "Chalmers Student Union",
                "industry": "Education",
                "start_date": "1935"
            },
            {
                "occupational_title": "Operating Engineer",
                "workplace": "ESAB",
                "industry": "Engineering",
                "start_date": null
            },
            {
                "occupational_title": "Director",
                "workplace": "Luth & Rosén",
                "industry": "Electrical",
                "start_date": "1911"
            },
            {
                "occupational_title": "Owner",
                "workplace": "Own trading company",
                "industry": "Various",
                "start_date": "1913"
            }
        ]
    }
}