{
    "original": "ENGWALL, Pehr Viktor, Civilingenjör, Stockholm, f Gävle 9/9 91 av civ.ing K E E o Calla Gyllenhammar, gm (2) Brita Axelson. Mogenh.ex Gävle 09, KTH (V o V) 10—14. Byråing AB Vattenbyggn.byrån 14—16, vkst dir Baltiska Merkantil- o Ind AB 16—20, eg aff- o ing.verksamh 20—26, arb.ch AB Byggn.-varor 26—34, vkst dir f egna fman Ing.fma Pehr Engwall AB Sthlm sed. 34. Styr.led i Balt Merkantil- o Ind AB 16—20, Engwall &amp; Stråhle AB 18—27, Film AB Thule 25—27, AB Byggn.varor 26—30, Sv Maskin AB Greiff sed. 33, Axelson &amp; Engwall AB sed. 33, Ing.fma Pehr Engwall AB sed. 34, Sv Metalliserings AB sed. 35. Av trycket: Cementarbeten m Sika (29), Handbok f isoleringsarbeten m Sikapreparaten (32).",
    "translated": "ENGWALL, Pehr Viktor, Engineer, Stockholm, born in Gävle on September 9, 1891, son of civil engineer K E E and Calla Gyllenhammar, married (2) Brita Axelson. Graduated from Gävle High School in 1909, Royal Institute of Technology (V and V) from 1910 to 1914. Employed as an engineer at AB Vattenbyggnadsbyrån from 1914 to 1916, Assistant Managing Director at Baltic Mercantile and Industrial AB from 1916 to 1920, self-employed in business and engineering from 1920 to 1926, worked at AB Byggnadsvaror from 1926 to 1934, Vice Managing Director of his own company, Ing.fma Pehr Engwall AB Stockholm since 1934. Served on the board of Baltic Mercantile and Industrial AB from 1916 to 1920, Engwall & Stråhle AB from 1918 to 1927, Film AB Thule from 1925 to 1927, AB Byggnadsvaror from 1926 to 1930, Swedish Machine AB Greiff since 1933, Axelson & Engwall AB since 1933, Ing.fma Pehr Engwall AB since 1934, Swedish Metallizing AB since 1935. Published works include: Cement Works with Sika (1929), Handbook for Insulation Works with Sikapreparates (1932).",
    "structured": {
        "name": "Pehr Viktor Engwall",
        "jobTitle": "Engineer",
        "birthPlace": "Gävle",
        "birthDate": "1891-09-09",
        "parents": [
            {
                "name": "K E E Engwall",
                "jobTitle": "Civil Engineer"
            },
            {
                "name": "Calla Gyllenhammar"
            }
        ],
        "spouse": [
            {
                "name": "Brita Axelson"
            }
        ],
        "education": [
            {
                "name": "Gävle High School",
                "endDate": "1909"
            },
            {
                "name": "Royal Institute of Technology",
                "startDate": "1910",
                "endDate": "1914",
                "degree": "Civil Engineering"
            }
        ],
        "employmentHistory": [
            {
                "employer": "AB Vattenbyggnadsbyrån",
                "startDate": "1914",
                "endDate": "1916",
                "jobTitle": "Engineer"
            },
            {
                "employer": "Baltic Mercantile and Industrial AB",
                "startDate": "1916",
                "endDate": "1920",
                "jobTitle": "Assistant Managing Director"
            },
            {
                "startDate": "1920",
                "endDate": "1926",
                "jobTitle": "Self-employed in Business and Engineering"
            },
            {
                "employer": "AB Byggnadsvaror",
                "startDate": "1926",
                "endDate": "1934",
                "jobTitle": "Engineer"
            },
            {
                "employer": "Ing.fma Pehr Engwall AB",
                "startDate": "1934",
                "jobTitle": "Vice Managing Director"
            }
        ],
        "boardMember": [
            {
                "organization": "Baltic Mercantile and Industrial AB",
                "startDate": "1916",
                "endDate": "1920"
            },
            {
                "organization": "Engwall & Stråhle AB",
                "startDate": "1918",
                "endDate": "1927"
            },
            {
                "organization": "Film AB Thule",
                "startDate": "1925",
                "endDate": "1927"
            },
            {
                "organization": "AB Byggnadsvaror",
                "startDate": "1926",
                "endDate": "1930"
            },
            {
                "organization": "Swedish Machine AB Greiff",
                "startDate": "1933"
            },
            {
                "organization": "Axelson & Engwall AB",
                "startDate": "1933"
            },
            {
                "organization": "Ing.fma Pehr Engwall AB",
                "startDate": "1934"
            },
            {
                "organization": "Swedish Metallizing AB",
                "startDate": "1935"
            }
        ],
        "publishedWorks": [
            {
                "name": "Cement Works with Sika",
                "yearPublished": "1929"
            },
            {
                "name": "Handbook for Insulation Works with Sikapreparates",
                "yearPublished": "1932"
            }
        ]
    },
    "occupations": {
        "career": [
            {
                "occupational_title": "Engineer",
                "workplace": "AB Vattenbyggnadsbyrån",
                "industry": "Engineering",
                "start_date": "1914"
            },
            {
                "occupational_title": "Assistant Managing Director",
                "workplace": "Baltic Mercantile and Industrial AB",
                "industry": "Trade and Industry",
                "start_date": "1916"
            },
            {
                "occupational_title": "Self-Employed",
                "workplace": "Business and Engineering",
                "industry": "Various",
                "start_date": "1920"
            },
            {
                "occupational_title": "Engineer",
                "workplace": "AB Byggnadsvaror",
                "industry": "Construction Supplies",
                "start_date": "1926"
            },
            {
                "occupational_title": "Vice Managing Director",
                "workplace": "Ing.fma Pehr Engwall AB",
                "industry": "Engineering",
                "start_date": "1934"
            }
        ]
    }
}