{
    "original": "AHLBERG, Nils Berndt Henning, Direktör, Skövde, f ö Tunhem 23/5 93 av hemmansäg F Joel A o Emma Carlsson. Ultuna lantbr.sk. Bokh. på Augerums gård, Blek, 16—17, förvalt Sv:s Stärk.intress. egend, i Ramdala 18—25, v Sv Jordförmedl. 25—34, vkst dir Isakssonska Boktryck.AB, Skövde, 35, utg. Skarb. Läns Annonsblad, styr.led KraftAB Nykvarn-Tidan, styr.ordf Skövde el.verk, sekr o kass i Hush.sällsk kretsavd, styr.led FastighetsAB Terra, hvobef Skövde, ordf Skövde lstfören., styr.led Skövde konstfören mm. Resor: Norge, Danm, Finl, Estl, Tyskl. Frimurare (VIII), Skarab. lstförb. förtj.med. s, skyt.m. g, lst. idr.m. s. Hobby: Jakt.",
    "translated": "AHLBERG, Nils Berndt Henning, Director, Skövde, b. Tunhem 23/5 1893, son of farmer Joel A and Emma Carlsson. Studied agriculture at Ultuna. Worked as an accountant at Augerums gård, Blek, 1916-1917; managed Swedish Stärk.intress. properties in Ramdala 1918-1925; worked in the agricultural service of Sweden's Jordförmedl. 1925-1934; became the managing director of Isakssonska Boktryck.AB, Skövde, in 1935; published Skarb. Läns Annonsblad; served on the board of KraftAB Nykvarn-Tidan; served as chairman of Skövde el.verk; secretary and treasurer of the Hush.sällsk kretsavd; board member of FastighetsAB Terra; head of the Skövde county association; board member of Skövde konstfören and others. Traveled to Norway, Denmark, Finland, Estonia, and Germany. Freemason (VIII degree); received commendation from Skaraborg county federation, shooting medal, and sports medal. Hobby: Hunting.",
    "structured": {
        "@context": "https://schema.org",
        "@type": "Person",
        "name": "Nils Berndt Henning Ahlberg",
        "givenName": "Nils",
        "additionalName": "Berndt Henning",
        "familyName": "Ahlberg",
        "birthDate": "1893-05-23",
        "birthPlace": "Tunhem",
        "description": "Director",
        "address": {
            "@type": "PostalAddress",
            "addressLocality": "Skövde"
        },
        "parent": [
            {
                "@type": "Person",
                "name": "Joel A Ahlberg",
                "familyName": "Ahlberg",
                "givenName": "Joel",
                "jobTitle": "Farmer"
            },
            {
                "@type": "Person",
                "name": "Emma Carlsson",
                "familyName": "Carlsson",
                "givenName": "Emma"
            }
        ],
        "education": [
            {
                "@type": "EducationalOrganization",
                "name": "Ultuna",
                "description": "Studied agriculture"
            }
        ],
        "worksFor": [
            {
                "@type": "Organization",
                "name": "Augerums gård",
                "description": "Accountant",
                "startDate": "1916",
                "endDate": "1917"
            },
            {
                "@type": "Organization",
                "name": "Swedish Stärk.intress.",
                "description": "Managed properties",
                "startDate": "1918",
                "endDate": "1925"
            },
            {
                "@type": "Organization",
                "name": "Sweden's Jordförmedl.",
                "description": "Agricultural service",
                "startDate": "1925",
                "endDate": "1934"
            },
            {
                "@type": "Organization",
                "name": "Isakssonska Boktryck.AB",
                "description": "Managing Director",
                "startDate": "1935"
            }
        ],
        "memberOf": [
            {
                "@type": "Place",
                "name": "Norway"
            },
            {
                "@type": "Place",
                "name": "Denmark"
            },
            {
                "@type": "Place",
                "name": "Finland"
            },
            {
                "@type": "Place",
                "name": "Estonia"
            },
            {
                "@type": "Place",
                "name": "Germany"
            }
        ],
        "nationality": "Swedish",
        "gender": "Male",
        "honorificSuffix": "VIII degree",
        "hasOccupation": [
            {
                "@type": "Occupation",
                "name": "Jakt",
                "description": "Hunting"
            }
        ],
        "hasAwards": [
            {
                "@type": "Medal",
                "name": "commendation from Skaraborg county federation"
            },
            {
                "@type": "Medal",
                "name": "shooting medal"
            },
            {
                "@type": "Medal",
                "name": "sports medal"
            }
        ]
    },
    "occupations": {
        "career": [
            {
                "occupational_title": "Accountant",
                "workplace": "Augerums gård",
                "industry": "Agriculture",
                "start_date": "1916"
            },
            {
                "occupational_title": "Property Manager",
                "workplace": "Swedish Stärk.intress. properties (Ramdala)",
                "industry": "Agriculture",
                "start_date": "1918"
            },
            {
                "occupational_title": "Agricultural Service Worker",
                "workplace": "Sweden's Jordförmedl.",
                "industry": "Agriculture",
                "start_date": "1925"
            },
            {
                "occupational_title": "Managing Director",
                "workplace": "Isakssonska Boktryck.AB",
                "industry": "Printing",
                "start_date": "1935"
            }
        ]
    }
}