{
    "original": "KÄRNEKULL, Carl Olof, Direktör, över-ingrenjör, Stockholm, f Jkp 25/10 85 av skepps-klarer A Andersson o Mathilda Erikson, gm Astis Hamfeldt (d). Studex 07, ex KTH 12. Avd.ing ensk jvg 12—16, bitr ing SJ 17—19, disp.ass Avesta jvk 19—21, ordf Avesta byggn.-nmd 19, övering o chef Ind.byråns org.avd, Sv ind.frb sed. 21, dir där fr 44. Komm.-kt)ll USA-stip o IVA d :o 22, studieres England, Tyskland, Frankrike USA 27—38, sakk finansdep rör förv av flottans varv 28, för-sv.dep rör flygvapn verkst mm 31, marinför-valtn rör varvsorg v Sthlms örlogsv 33, sakk i org.fråg h Sthlms fastigh.nmd, ind.v.styr mfl 34—35, led Sthlm kommun omorg.komm:» expertdeleg 39—40, styr.led Sv tekn.frn 31—38, medstift dess avd f industr ekon o org 31, styr.led Sv konsult ing frn 37, ordf sed. 41, led Sv nät.komm f ration org fr 37, 1. v. ordf sed. 39, Sv repr v 7. internat kongr i ration org Washington 38. Styr.suppl i Statens hantv.inst sed. 44. Member of Amer Soc Mach Engineers. Av trycket: Modern arb.ledn 21. Om sparsamh inom industr drift 22, Den fabrikmäss driftens org 27, Hur man org ett af f.f öret 24 (4 uppl 38), Flytande tillv 30, Driftsekon 31, Planering inom stålind 38, Ration arb.ledn :s tillämpn på nybyggn av hdlsfartyg 40, art i tekn o ekon ämn, red Sv Ind.frb :s Rationalis Revy sed. 29. RVO. Hobby : Ordleksforskn.",
    "translated": "KÄRNEKULL, Carl Olof, Director, Senior Chief Engineer, Stockholm, born Jönköping 25/10 1885, son of ship clerk A Andersson and Mathilda Erikson, married to Astis Hamfeldt (deceased). Graduate 1907, ex Royal Institute of Technology (KTH) 1912. Department engineer at private railway 1912-1916, Assistant Engineer at Swedish Railways 1917-1919, Dispatcher Assistant at Avesta private railway 1919-1921, Chairman of Avesta Building Committee 1919, Senior Engineer and Head of Industrial Bureau's Organizational Department at Swedish Industrial Federation since 1921, Director since 1944. Commissioned Officer in the USA and member of the Royal Swedish Academy of Engineering Sciences since 1922, studied in England, Germany, France, and USA 1927-1938. Expert at the Financial Department regarding naval shipyards in 1928, at the Defense Department regarding Air Force workshops, etc. in 1931, Naval Administration for shipyard organization at Stockholm naval base in 1933, expert in organizational matters for the Stockholm Real Estate Committee, industrial plant control authority, etc. in 1934-1935, member of the Stockholm Municipal Reorganization Committee's expert delegation in 1939-1940, board member of the Swedish Technical Association 1931-1938, co-founder of its department of industrial economy and organization in 1931, board member of the Swedish Consulting Engineers from 1937, Chairman since 1941, member of the Swedish rationing organization from 1937, First Vice-Chairman since 1939, Swedish representative at the 7th International Congress on Organization in Washington in 1938. Board substitute at the State Craft Institute since 1944. Member of the American Society of Mechanical Engineers. Publications: Modern Industrial Management 1921, Organization of Economical Work within Industry 1922, Organizing a Departmental Business 1924 (4th edition 1938), Progressive Manufacturing 1930, Economic Operation 1931, Planning Within the Steel Industry 1938, Rational Management Applied to the Construction of Merchant Vessels 1940, articles in technical and economic subjects, editor of the Swedish Industrial Federation's Rationalization Review since 1929. Received the Royal Order of Vasa. Hobby: Wordplay research.",
    "structured": {
        "@context": "https://schema.org",
        "@type": "Person",
        "name": "Carl Olof Kärnekull",
        "birthDate": "1885-10-25",
        "birthPlace": "Jönköping",
        "deathDate": null,
        "nationality": "Swedish",
        "occupation": [
            "Director",
            "Senior Chief Engineer"
        ],
        "affiliation": [
            "Stockholm",
            "Royal Institute of Technology (KTH)",
            "Swedish Railways",
            "Avesta private railway",
            "Avesta Building Committee",
            "Swedish Industrial Federation",
            "Swedish Technical Association",
            "Swedish Consulting Engineers",
            "International Congress on Organization",
            "State Craft Institute",
            "American Society of Mechanical Engineers"
        ],
        "education": "Royal Institute of Technology (KTH)",
        "spouse": "Astis Hamfeldt",
        "parents": [
            {
                "name": "A Andersson",
                "relation": "father",
                "occupation": "Ship Clerk"
            },
            {
                "name": "Mathilda Erikson",
                "relation": "mother"
            }
        ],
        "publications": [
            "Modern Industrial Management",
            "Organization of Economical Work within Industry",
            "Organizing a Departmental Business",
            "Progressive Manufacturing",
            "Economic Operation",
            "Planning Within the Steel Industry",
            "Rational Management Applied to the Construction of Merchant Vessels",
            "articles in technical and economic subjects"
        ],
        "awards": [
            "Royal Order of Vasa"
        ],
        "hobbies": [
            "Wordplay research"
        ]
    },
    "occupations": {
        "career": [
            {
                "occupational_title": "Department Engineer",
                "workplace": "Private Railway",
                "industry": "Railways",
                "start_date": "1912"
            },
            {
                "occupational_title": "Assistant Engineer",
                "workplace": "Swedish Railways",
                "industry": "Railways",
                "start_date": "1917"
            },
            {
                "occupational_title": "Dispatcher Assistant",
                "workplace": "Avesta Private Railway",
                "industry": "Railways",
                "start_date": "1919"
            },
            {
                "occupational_title": "Chairman of Avesta Building Committee",
                "workplace": "Avesta",
                "industry": "Construction",
                "start_date": "1919"
            },
            {
                "occupational_title": "Senior Engineer and Head of Organizational Department",
                "workplace": "Swedish Industrial Federation",
                "industry": "Industrial",
                "start_date": "1921"
            },
            {
                "occupational_title": "Director",
                "workplace": "Swedish Industrial Federation",
                "industry": "Industrial",
                "start_date": "1944"
            },
            {
                "occupational_title": "Commissioned Officer",
                "workplace": "USA",
                "industry": "Military",
                "start_date": "1922"
            },
            {
                "occupational_title": "Member of Royal Swedish Academy of Engineering Sciences",
                "workplace": "N/A",
                "industry": "Engineering",
                "start_date": "1922"
            },
            {
                "occupational_title": "Expert at the Financial Department",
                "workplace": "N/A",
                "industry": "Government",
                "start_date": "1928"
            },
            {
                "occupational_title": "Expert at the Defense Department",
                "workplace": "N/A",
                "industry": "Government",
                "start_date": "1931"
            },
            {
                "occupational_title": "Expert at Naval Administration",
                "workplace": "Stockholm Naval Base",
                "industry": "Government",
                "start_date": "1933"
            },
            {
                "occupational_title": "Expert in Organizational Matters",
                "workplace": "N/A",
                "industry": "Government",
                "start_date": "1934"
            },
            {
                "occupational_title": "Member of Stockholm Municipal Reorganization Committee",
                "workplace": "Stockholm",
                "industry": "Government",
                "start_date": "1939"
            },
            {
                "occupational_title": "Board Member of Swedish Technical Association",
                "workplace": "N/A",
                "industry": "Professional Association",
                "start_date": "1931"
            },
            {
                "occupational_title": "Co-founder of Department of Industrial Economy and Organization",
                "workplace": "N/A",
                "industry": "Professional Association",
                "start_date": "1931"
            },
            {
                "occupational_title": "Board Member of Swedish Consulting Engineers",
                "workplace": "N/A",
                "industry": "Professional Association",
                "start_date": "1937"
            },
            {
                "occupational_title": "Chairman of Swedish Consulting Engineers",
                "workplace": "N/A",
                "industry": "Professional Association",
                "start_date": "1941"
            },
            {
                "occupational_title": "Member of Swedish Rationing Organization",
                "workplace": "N/A",
                "industry": "Government",
                "start_date": "1937"
            },
            {
                "occupational_title": "Swedish Representative at International Congress on Organization",
                "workplace": "Washington",
                "industry": "Government",
                "start_date": "1938"
            },
            {
                "occupational_title": "Board Substitute at State Craft Institute",
                "workplace": "N/A",
                "industry": "Education",
                "start_date": "1944"
            },
            {
                "occupational_title": "Member of American Society of Mechanical Engineers",
                "workplace": "N/A",
                "industry": "Professional Association",
                "start_date": "N/A"
            }
        ]
    }
}