{
    "original": "CLEMEDTSON, Jeppe, Direktör, Trensum, f Hällaryd, Blek, 26/6 85 av lantbr Sven C o Emelie Jeppsson, gm Svea Nilsson. Fhsk, lantm.sk, privatstud i Sv o utl. Ombudsm o vkst styr.led i Brandförsäkr.bol å landet inom Blek 18, vkst dir AB Blek lantmannafrb 26, d:o Sv stärkelseproducenters frn 27. Styr.led Lantm.frb i Karlsh, Sv stärkelseproduc :s frn, Sv lantmännens riksfrb. Landsbygdens för-säkr.bol Sthlm, Hällaryds sparbk, No Ska o Blek andelstorvströfrn, Karlsh stuv.AB (v. ordf o v. vkst dir). Led av 2:a kamm 21, l:a kamm 24—31 o 34 (h); fd v. ordf ldst, ordf Hällaryds kom.stämma o Blek-högerns frb. Ag jord- o skogsegend ö Hoka i Hällaryds 0 Asarums s mar. Studieres t Tyskl, Österr, Tjeckoslov, Holl, Danm, Norge, Finl. RNO, RVO, PatrstGM, Blek l hush.sällsk :s stGM, skytM mm.",
    "translated": "CLEMEDTSON, Jeppe, Director, Trensum, born in Hällaryd, Blekinge on June 26, 1885, son of farmer Sven C and Emelie Jeppsson, married to Svea Nilsson. Higher School Certificate (fhsk), agricultural studies (lantm.sk), private studies in Sweden and abroad. Representative and board member in the fire insurance company in the countryside within Blekinge since 1918, managing director of AB Blek Lantmannafrb (agricultural cooperative) since 1926, the same position in Svenska Stärkelseproducenters frn (Swedish starch producers) since 1927. Board member of Lantmännen Karlshamn, Svenska Stärkelseproducenters frn, and Svenska Lantmännens Riksfrb (Swedish Farmers' national association). Board member of Landsbygdens Försäkringsbolag in Stockholm, Hällaryds Sparbank (savings bank), Nordiska Ska och Blek Andelstorvströfrn (Nordic peat moss cooperative), and Karlshamn Stuv.AB (vice chairman and managing director assistant). Member of the Second Chamber of Parliament from 1921, First Chamber of Parliament from 1924 to 1931 and 1934 (conservative party); former vice chairman of the executive committee, chairman of Hällaryds constituency meeting, and Blekinge right-wing association. Owner of agricultural and forest properties in Hoka, Hällaryd, and Asarum's sea marsh. Study trips to Germany, Austria, Czechoslovakia, the Netherlands, Denmark, Norway, and Finland. RNO (Royal Norwegian Order), RVO (Royal Victorian Order), PatrstGM (Grand Master Patriotic Society), Blekinge Local History Society's grand master, marksman medalist, and more.",
    "structured": {
        "@context": "https://schema.org",
        "@type": "Person",
        "name": "Jeppe Clemedtson",
        "birthDate": "1885-06-26",
        "birthPlace": "Hällaryd, Blekinge, Sweden",
        "nationality": "Swedish",
        "parent": [
            {
                "@type": "Person",
                "name": "Sven C"
            },
            {
                "@type": "Person",
                "name": "Emelie Jeppsson"
            }
        ],
        "spouse": {
            "@type": "Person",
            "name": "Svea Nilsson"
        },
        "education": [
            {
                "@type": "EducationalOccupationalCredential",
                "credentialCategory": "Higher School Certificate",
                "educationalLevel": "fhsk"
            },
            {
                "@type": "EducationalOccupationalCredential",
                "credentialCategory": "Agricultural Studies",
                "educationalLevel": "lantm.sk"
            },
            {
                "@type": "EducationalOccupationalCredential",
                "credentialCategory": "Private Studies"
            }
        ],
        "occupation": [
            {
                "@type": "OrganizationRole",
                "title": "Director",
                "startDate": "1918"
            }
        ],
        "memberOf": [
            {
                "@type": "Organization",
                "name": "Fire Insurance Company"
            },
            {
                "@type": "Organization",
                "name": "AB Blek Lantmannafrb",
                "startDate": "1926",
                "roleName": "Managing Director"
            },
            {
                "@type": "Organization",
                "name": "Svenska Stärkelseproducenters frn",
                "startDate": "1927",
                "roleName": "Managing Director"
            },
            {
                "@type": "Organization",
                "name": "Lantmännen Karlshamn"
            },
            {
                "@type": "Organization",
                "name": "Svenska Lantmännens Riksfrb"
            },
            {
                "@type": "Organization",
                "name": "Landsbygdens Försäkringsbolag",
                "location": "Stockholm"
            },
            {
                "@type": "Organization",
                "name": "Hällaryds Sparbank"
            },
            {
                "@type": "Organization",
                "name": "Nordiska Ska och Blek Andelstorvströfrn"
            },
            {
                "@type": "Organization",
                "name": "Karlshamn Stuv.AB",
                "roleName": "Vice Chairman and Managing Director Assistant"
            },
            {
                "@type": "PoliticalParty",
                "name": "Conservative Party"
            },
            {
                "@type": "Organization",
                "name": "Hällaryds constituency meeting",
                "roleName": "Chairman"
            },
            {
                "@type": "Organization",
                "name": "Blekinge right-wing association",
                "roleName": "Chairman"
            }
        ],
        "owns": [
            {
                "@type": "Place",
                "name": "Hoka"
            },
            {
                "@type": "Place",
                "name": "Hällaryd"
            },
            {
                "@type": "Place",
                "name": "Asarum's sea marsh"
            }
        ],
        "memberOfOrganization": [
            {
                "@type": "Organization",
                "name": "Royal Norwegian Order",
                "awardCategory": "RNO"
            },
            {
                "@type": "Organization",
                "name": "Royal Victorian Order",
                "awardCategory": "RVO"
            },
            {
                "@type": "Organization",
                "name": "Patriotic Society",
                "awardCategory": "PatrstGM",
                "awardName": "Grand Master"
            },
            {
                "@type": "Organization",
                "name": "Blekinge Local History Society",
                "awardCategory": "Grand Master"
            }
        ],
        "hasOccupationSkill": {
            "@type": "Organization",
            "name": "Blekinge Local History Society",
            "skillName": "marksman"
        },
        "hasStudyAbroad": [
            "Germany",
            "Austria",
            "Czechoslovakia",
            "Netherlands",
            "Denmark",
            "Norway",
            "Finland"
        ]
    },
    "occupations": {
        "career": [
            {
                "occupational_title": "Director",
                "workplace": "Trensum",
                "industry": "",
                "start_date": ""
            },
            {
                "occupational_title": "Representative and Board Member",
                "workplace": "Fire insurance company in the countryside within Blekinge",
                "industry": "Insurance",
                "start_date": "1918"
            },
            {
                "occupational_title": "Managing Director",
                "workplace": "AB Blek Lantmannafrb",
                "industry": "Agricultural cooperative",
                "start_date": "1926"
            },
            {
                "occupational_title": "Managing Director",
                "workplace": "Svenska Stärkelseproducenters frn",
                "industry": "Starch production",
                "start_date": "1927"
            },
            {
                "occupational_title": "Board Member",
                "workplace": "Lantmännen Karlshamn",
                "industry": "Agriculture",
                "start_date": ""
            },
            {
                "occupational_title": "Board Member",
                "workplace": "Svenska Stärkelseproducenters frn",
                "industry": "Starch production",
                "start_date": ""
            },
            {
                "occupational_title": "Board Member",
                "workplace": "Svenska Lantmännens Riksfrb",
                "industry": "Agriculture",
                "start_date": ""
            },
            {
                "occupational_title": "Board Member",
                "workplace": "Landsbygdens Försäkringsbolag",
                "industry": "Insurance",
                "start_date": ""
            },
            {
                "occupational_title": "Board Member",
                "workplace": "Hällaryds Sparbank",
                "industry": "Banking",
                "start_date": ""
            },
            {
                "occupational_title": "Board Member",
                "workplace": "Nordiska Ska och Blek Andelstorvströfrn",
                "industry": "Cooperative",
                "start_date": ""
            },
            {
                "occupational_title": "Vice Chairman and Managing Director Assistant",
                "workplace": "Karlshamn Stuv.AB",
                "industry": "",
                "start_date": ""
            },
            {
                "occupational_title": "Member of the Second Chamber of Parliament",
                "workplace": "",
                "industry": "Government/Politics",
                "start_date": "1921"
            },
            {
                "occupational_title": "Member of the First Chamber of Parliament",
                "workplace": "",
                "industry": "Government/Politics",
                "start_date": "1924"
            }
        ]
    }
}