{
    "original": "DAHLGREN, Viktor Otto Richard, Direktör, Eskilstuna, f Lkrona 24/8 95 av disp W D o Alma Tour, gm Elsa Johansson. Studex Upps 14, avg.ex KTH 18. Assist KTH 18— 19, ing AB Separator Sthlm 18—20, ing Etu-iia StålpressningsAB 20—21, driftsing 21— 28, övering 28—31, vkst dir sed. 31. V. ordf styr f Maskinfackskolan i Etuna, styr.led Etuna Stålpressn AB o AB C E Johansson Etuna, v, ordf Tekn Frn Etuna. Studie- o aff.resor t Tyskl, Ital, Frankr, Engl. Rotary.",
    "translated": "DAHLGREN, Viktor Otto Richard, Director, Eskilstuna, born in Lkrona on August 24, 1895, son of W D and Alma Tour. Married to Elsa Johansson. Studied at Uppsala University until 1914, finished his engineering degree at the Royal Institute of Technology in 1918. Started as an assistant at KTH from 1918 to 1919, engineer at AB Separator in Stockholm from 1918 to 1920, engineer at Etuna StålpressningsAB from 1920 to 1921, head of operations from 1921 to 1928, promoted to senior engineer from 1928 to 1931, and has been a deputy director since 1931. Vice chairman of the board for the Machinery Training School in Etuna, board member of Etuna Stålpressn AB and AB C E Johansson Etuna, vice chairman of the Technology Association of Etuna. Studied and went on business trips to Germany, Italy, France, and England. Member of the Rotary Club.",
    "structured": {
        "@context": "http://schema.org",
        "@type": "Person",
        "name": "Viktor Otto Richard Dahlgren",
        "birthDate": "1895-08-24",
        "birthPlace": "Lkrona",
        "parent": [
            {
                "@type": "Person",
                "name": "W D Dahlgren"
            },
            {
                "@type": "Person",
                "name": "Alma Tour"
            }
        ],
        "spouse": {
            "@type": "Person",
            "name": "Elsa Johansson"
        },
        "education": [
            {
                "@type": "EducationalOrganization",
                "name": "Uppsala University",
                "endDate": "1914"
            },
            {
                "@type": "EducationalOrganization",
                "name": "Royal Institute of Technology",
                "startDate": "1914",
                "endDate": "1918"
            }
        ],
        "jobTitle": "Director",
        "worksFor": {
            "@type": "Organization",
            "name": "Eskilstuna"
        },
        "memberOf": {
            "@type": "Organization",
            "name": "Rotary Club"
        },
        "significantEvent": [
            {
                "@type": "Event",
                "name": "Started as Assistant at KTH",
                "startDate": "1918",
                "endDate": "1919"
            },
            {
                "@type": "Event",
                "name": "Engineer at AB Separator",
                "startDate": "1918",
                "endDate": "1920"
            },
            {
                "@type": "Event",
                "name": "Engineer at Etuna StålpressningsAB",
                "startDate": "1920",
                "endDate": "1921"
            },
            {
                "@type": "Event",
                "name": "Head of Operations at Etuna StålpressningsAB",
                "startDate": "1921",
                "endDate": "1928"
            },
            {
                "@type": "Event",
                "name": "Promoted to Senior Engineer",
                "startDate": "1928",
                "endDate": "1931"
            },
            {
                "@type": "Event",
                "name": "Deputy Director",
                "startDate": "1931"
            }
        ],
        "study": [
            {
                "@type": "Trip",
                "name": "Germany"
            },
            {
                "@type": "Trip",
                "name": "Italy"
            },
            {
                "@type": "Trip",
                "name": "France"
            },
            {
                "@type": "Trip",
                "name": "England"
            }
        ]
    },
    "occupations": {
        "career": [
            {
                "occupational_title": "Assistant",
                "workplace": "KTH",
                "industry": "Education",
                "start_date": "1918"
            },
            {
                "occupational_title": "Engineer",
                "workplace": "AB Separator",
                "industry": "Engineering",
                "start_date": "1918"
            },
            {
                "occupational_title": "Engineer",
                "workplace": "Etuna StålpressningsAB",
                "industry": "Engineering",
                "start_date": "1920"
            },
            {
                "occupational_title": "Head of Operations",
                "workplace": "Etuna StålpressningsAB",
                "industry": "Engineering",
                "start_date": "1921"
            },
            {
                "occupational_title": "Senior Engineer",
                "workplace": "Unknown",
                "industry": "Engineering",
                "start_date": "1928"
            },
            {
                "occupational_title": "Deputy Director",
                "workplace": "Unknown",
                "industry": "Unknown",
                "start_date": "1931"
            }
        ]
    }
}