{
    "original": "HALLIN, John Emil, Civilingenjör, Finspång, f V Karaby, Mmöh l, 2/4 90 av fabr N P H o Hilma Jacobsson, gm Margareta Andersson. Mog.ex Lund 09, KTH 09—12, avg.ex sistn år. Konstr Sthlms gasv 12, beräkn.ing AB Ljungströms Ångturbin 12—13 o vid Sv Turbinfabr AB Ljungström, Finsp, 13—15, chef f offertavd där 16—18, försäljn.chef där sed. 19. Led av taxerings- o länsprövn.nmdr, v. ordf i styr f Finsp vattenverk sed. 34, ordf sed. 42, ordf i byggn.nmdn sed. 40, led av köpingsflm sed. 43. Led av Sv Tekn.frn.",
    "translated": "HALLIN, John Emil, Civil Engineer, Finspång, born in Karaby, Mmöh district, April 2nd, 1890, son of factory worker N.P.H. and Hilma Jacobsson, married to Margareta Andersson. Graduated from Lund University in 1909, and from the Royal Institute of Technology (KTH) in 1909-1912. Completed advanced exams last year. Worked as a designer at Stockholm Gas Company in 1912, and as a calculation engineer at AB Ljungströms Steam Turbine from 1912-1913, and at the Swedish Turbine Company AB Ljungström, Finspång, from 1913-1915. Became head of the sales department there in 1919, after being the head of the quotation department from 1916-1918. Member of the Taxation and County Re-evaluation Board, vice-chairman of the board for Finspång Waterworks since 1934, chairman since 1942, chairman of the building committee since 1940, member of the town council since 1943. Member of the Swedish Engineering Association.",
    "structured": {
        "@context": "https://schema.org",
        "@type": "Person",
        "name": "John Emil Hallin",
        "jobTitle": "Civil Engineer",
        "birthDate": "1890-04-02",
        "birthPlace": "Karaby, Mmöh district",
        "parents": [
            {
                "@type": "Person",
                "name": "N.P.H."
            },
            {
                "@type": "Person",
                "name": "Hilma Jacobsson"
            }
        ],
        "spouse": {
            "@type": "Person",
            "name": "Margareta Andersson"
        },
        "education": [
            {
                "@type": "CollegeOrUniversity",
                "name": "Lund University",
                "endDate": "1909"
            },
            {
                "@type": "CollegeOrUniversity",
                "name": "Royal Institute of Technology (KTH)",
                "startDate": "1909",
                "endDate": "1912"
            }
        ],
        "work": [
            {
                "@type": "Organization",
                "name": "Stockholm Gas Company",
                "startDate": "1912",
                "endDate": "1912",
                "jobTitle": "Designer"
            },
            {
                "@type": "Organization",
                "name": "AB Ljungströms Steam Turbine",
                "startDate": "1912",
                "endDate": "1913",
                "jobTitle": "Calculation Engineer"
            },
            {
                "@type": "Organization",
                "name": "Swedish Turbine Company AB Ljungström",
                "startDate": "1913",
                "endDate": "1915",
                "jobTitle": "Calculation Engineer"
            },
            {
                "@type": "Organization",
                "name": "Swedish Turbine Company AB Ljungström",
                "startDate": "1916",
                "endDate": "1918",
                "jobTitle": "Quotation Department Head"
            },
            {
                "@type": "Organization",
                "name": "Swedish Turbine Company AB Ljungström",
                "startDate": "1919",
                "jobTitle": "Sales Department Head"
            }
        ],
        "memberOf": [
            {
                "@type": "Organization",
                "name": "Taxation and County Re-evaluation Board"
            },
            {
                "@type": "Organization",
                "name": "Finspång Waterworks",
                "roleName": "Vice Chairman",
                "startDate": "1934"
            },
            {
                "@type": "Organization",
                "name": "Finspång Waterworks",
                "roleName": "Chairman",
                "startDate": "1942"
            },
            {
                "@type": "Organization",
                "name": "Building Committee",
                "roleName": "Chairman",
                "startDate": "1940"
            },
            {
                "@type": "Organization",
                "name": "Town Council",
                "roleName": "Member",
                "startDate": "1943"
            },
            {
                "@type": "Organization",
                "name": "Swedish Engineering Association"
            }
        ]
    },
    "occupations": {
        "career": [
            {
                "occupational_title": "Designer",
                "workplace": "Stockholm Gas Company",
                "industry": "Gas industry",
                "start_date": "1912"
            },
            {
                "occupational_title": "Calculation Engineer",
                "workplace": "AB Ljungströms Steam Turbine",
                "industry": "Engineering",
                "start_date": "1912"
            },
            {
                "occupational_title": "Calculation Engineer",
                "workplace": "Swedish Turbine Company AB Ljungström",
                "industry": "Engineering",
                "start_date": "1913"
            },
            {
                "occupational_title": "Head of Quotation Department",
                "workplace": "Swedish Turbine Company AB Ljungström",
                "industry": "Engineering",
                "start_date": "1916"
            },
            {
                "occupational_title": "Head of Sales Department",
                "workplace": "Swedish Turbine Company AB Ljungström",
                "industry": "Engineering",
                "start_date": "1919"
            }
        ]
    }
}