{
    "original": "ROSENBERG, Harald Eugen, Direktör, Stockholm, f Grydt, Krst l, 5/11 98 av träd-gårdsmäst G O R o Mathilda Olsson, gm Ingrid Hansen. Studex 17, HHS 19. Dir.ass ME A 20, bitr dir 30, v. vkst dir sed. 42. Styr.-led Sv Slöjdfrn, ds facksektions nmd, v. ordf Sthlms Herrekip.frn, led Sv Reklamfrbs styr o opinionsnmd, styr.led Sthlms Köpm.frb, led Realisationsnmd. RVO, BKrO, Sv Istfrns cen-tralfarbs ftjSM. Hobby: Målning.",
    "translated": "ROSENBERG, Harald Eugen, Director, Stockholm, born Grydt, Krst I, 5th of November 1898, son of gardener G.O.R and Mathilda Olsson, married to Ingrid Hansen. Studied at the age of 17, completed HHS in 1919. Director's assistant at ME A in 1920, deputy director in 1930, acting director since 1942. Board leader of the Swedish Handicraft Association, member of the labor division, vice chairman of Stockholm's Gentleman's Equine Association, board member of the Swedish Advertising Association and the Opinion Committee, board leader of Stockholm's Merchants Association, member of the Liquidation Committee. Awarded the Order of Vasa, Knight of the Order of the Polar Star, Swedish Ice Sports Central Association's gold medal. Hobby: Painting.",
    "structured": {
        "@context": "https://schema.org",
        "@type": "Person",
        "name": "Harald Eugen Rosenberg",
        "birthDate": "1898-11-05",
        "birthPlace": "Grydt, Krst I",
        "familyName": "Rosenberg",
        "givenName": "Harald Eugen",
        "description": "Director",
        "nationality": "Swedish",
        "gender": "Male",
        "spouse": {
            "@type": "Person",
            "name": "Ingrid Hansen"
        },
        "parents": [
            {
                "@type": "Person",
                "name": "G.O.R."
            },
            {
                "@type": "Person",
                "name": "Mathilda Olsson"
            }
        ],
        "alumniOf": [
            {
                "@type": "HighSchool",
                "name": "Studex",
                "endDate": "1919"
            },
            {
                "@type": "CollegeOrUniversity",
                "name": "HHS",
                "endDate": "1919"
            }
        ],
        "worksFor": {
            "@type": "Organization",
            "name": "ME A"
        },
        "jobTitle": "Director's Assistant",
        "memberOf": [
            {
                "@type": "Organization",
                "name": "Swedish Handicraft Association",
                "roleName": "Board Leader"
            },
            {
                "@type": "Organization",
                "name": "Labor Division",
                "roleName": "Member"
            },
            {
                "@type": "Organization",
                "name": "Stockholm's Gentleman's Equine Association",
                "roleName": "Vice Chairman"
            },
            {
                "@type": "Organization",
                "name": "Swedish Advertising Association",
                "roleName": "Board Member"
            },
            {
                "@type": "Organization",
                "name": "Opinion Committee",
                "roleName": "Board Member"
            },
            {
                "@type": "Organization",
                "name": "Stockholm's Merchants Association",
                "roleName": "Board Leader"
            },
            {
                "@type": "Organization",
                "name": "Liquidation Committee",
                "roleName": "Member"
            }
        ],
        "awards": [
            {
                "@type": "Order",
                "name": "Order of Vasa",
                "awardDate": "UNKNOWN"
            },
            {
                "@type": "Order",
                "name": "Knight of the Order of the Polar Star",
                "awardDate": "UNKNOWN"
            },
            {
                "@type": "Organization",
                "name": "Swedish Ice Sports Central Association",
                "award": "Gold Medal"
            }
        ],
        "sameAs": []
    },
    "occupations": {
        "career": [
            {
                "occupational_title": "Director's assistant",
                "workplace": "ME A",
                "industry": "Unknown",
                "start_date": "1920"
            },
            {
                "occupational_title": "Deputy director",
                "workplace": "Unknown",
                "industry": "Unknown",
                "start_date": "1930"
            },
            {
                "occupational_title": "Acting director",
                "workplace": "Unknown",
                "industry": "Unknown",
                "start_date": "1942"
            }
        ]
    }
}