{
    "original": "JOHANSSON, Elias Verner, Direktör, Strömsund, f Ramsele, Vnorrl l, 10/1 82 av hemm.äg E J o Ingrid Eliedtr, gm Zulamith Sundelin. Hsands tekn elem.sk, Armour Inst of Techn i Chicago. Anst å olika platser i Sv o utl t 10, därefter ing o, sed. 20 vkst dir v AB Per Holms Elektricitetsverk. Styr.ordfdär o i Ströms Wattudals Turistfrn. Varit led av kyrko- o skolråd, v. ordf i kyrkoflm o kyrkostämma o led av fattigv.styr o landsting; är led av kommunalflm (fd v. ordf), v. ordf i kommnnalnmd (fd ordf), ordf i yrkes-sk.styr o luftskyddsnmdn samt led av ett flert utredn- o byggn.ktéer. Resor: USA 05 —08, Tyskl 08—09. Hobbies: Fiske, turistväsendet, sport.",
    "translated": "JOHANSSON, Elias Verner, Director, Strömsund, b. Ramsele, Vnorrl I, 10/1 82 son of home owner E J and Ingrid Eliedtr, m. Zulamith Sundelin. Attended technical elementary school, Armour Institute of Technology in Chicago. Employed at various places in Sweden and abroad until 10, then unemployed, then appointed deputy director at AB Per Holms Elektricitetsverk. Chairman of the board and director of Ströms Wattudals Tourist Union. Has been a member of church and school councils, vice chairman of church association and church assembly, and a member of the poor relief board and county council; currently a member of the municipal assembly (former vice chairman), vice chairman of the municipal committee (former chairman), chairman of the vocational school committee and the air defense committee, as well as a member of several investigation and building committees. Travel: USA 05-08, Germany 08-09. Hobbies: Fishing, tourism, sports.",
    "structured": {
        "@context": "https://schema.org",
        "@type": "Person",
        "name": "Elias Verner Johansson",
        "jobTitle": "Director",
        "birthDate": "1882-10-01",
        "birthPlace": "Ramsele, Västernorrland, Sweden",
        "parents": [
            {
                "@type": "Person",
                "name": "E. J. Johansson",
                "jobTitle": "Home Owner"
            },
            {
                "@type": "Person",
                "name": "Ingrid Eliedtr"
            }
        ],
        "spouse": {
            "@type": "Person",
            "name": "Zulamith Sundelin"
        },
        "education": [
            {
                "@type": "Organization",
                "name": "Technical Elementary School"
            },
            {
                "@type": "Organization",
                "name": "Armour Institute of Technology",
                "location": "Chicago"
            }
        ],
        "employmentHistory": [
            {
                "@type": "Organization",
                "name": "AB Per Holms Elektricitetsverk"
            }
        ],
        "organizations": [
            {
                "@type": "Organization",
                "name": "Ströms Wattudals Tourist Union",
                "jobTitle": "Chairman of the Board and Director"
            },
            {
                "@type": "Organization",
                "name": "Church Council"
            },
            {
                "@type": "Organization",
                "name": "School Council"
            },
            {
                "@type": "Organization",
                "name": "Church Association",
                "jobTitle": "Vice Chairman"
            },
            {
                "@type": "Organization",
                "name": "Church Assembly",
                "jobTitle": "Vice Chairman"
            },
            {
                "@type": "Organization",
                "name": "Poor Relief Board"
            },
            {
                "@type": "Organization",
                "name": "County Council"
            },
            {
                "@type": "Organization",
                "name": "Municipal Assembly",
                "jobTitle": "Member"
            },
            {
                "@type": "Organization",
                "name": "Municipal Committee",
                "jobTitle": "Vice Chairman"
            },
            {
                "@type": "Organization",
                "name": "Vocational School Committee",
                "jobTitle": "Chairman"
            },
            {
                "@type": "Organization",
                "name": "Air Defense Committee",
                "jobTitle": "Chairman"
            },
            {
                "@type": "Organization",
                "name": "Investigation Committees"
            },
            {
                "@type": "Organization",
                "name": "Building Committees"
            }
        ],
        "travelHistory": [
            {
                "@type": "Place",
                "name": "USA"
            },
            {
                "@type": "Place",
                "name": "Germany"
            }
        ],
        "hobbies": [
            "Fishing",
            "Tourism",
            "Sports"
        ]
    },
    "occupations": {
        "career": [
            {
                "occupational_title": "Technical Elementary School Student",
                "workplace": "",
                "industry": "",
                "start_date": ""
            },
            {
                "occupational_title": "Student at Armour Institute of Technology",
                "workplace": "Chicago",
                "industry": "",
                "start_date": ""
            },
            {
                "occupational_title": "Various Employments",
                "workplace": "",
                "industry": "",
                "start_date": ""
            },
            {
                "occupational_title": "Deputy Director",
                "workplace": "AB Per Holms Elektricitetsverk",
                "industry": "",
                "start_date": ""
            }
        ]
    }
}