{
    "original": "CLAESSON, Carl Anton Gunnar, Järnhandlare, Vaggeryd, f 31/5 88 av virkeshandl J A C 0 Lovisa Johansson, gm Anne Marie Svensson. Folksk, hdlssk. Anst fma Oscar Ljungberg Skillingaryd 03—08, Brålanda Järnhdl 0&amp;—09. Eg fma Vaggeryds Järnhdl sed 09, ag fastigh Fridensborg nr 2 Vaggeryd. Styr.led Vaggeryds el- o vattenvk, Jönkp l Byggnmtrlhandl.-frn, styr.suppl Smal Järnhand!.frn, styr.led ideella frn :ar; länsstyr rev i Byarums familje-bidr.nmd samt komm-, skol- o fattigv.kassor-na. Hvobef. Resor: Tyskl, Danm, Norge. Inneh fi utm.tecken i idr- o Skytte; hed.led V.F. Hobby: Skytte.",
    "translated": "CLAESSON, Carl Anton Gunnar, Iron Merchant, Vaggeryd, b. 31/5 1888 to timber merchant J.A.C. 0 Lovisa Johansson, married Anne Marie Svensson. Elementary school, trade school. Employed by Oscar Ljungberg Skillingaryd 1903-1908, Brålanda Iron Trade 1908-1909. Established own business, Vaggeryds Iron Trade, in 1909, owned property Fridensborg no. 2 Vaggeryd. Board member of Vaggeryd electricity and waterworks, Jönköping Building Materials Merchant Association, deputy board member of Smal Iron Merchant Association, board member of various non-profit organizations; county board member of the Byarum family welfare board and municipal, school, and welfare funds. Traveled to Germany, Denmark, and Norway. Holds several awards in sports and marksmanship; honored member of the National Veterans Association. Hobby: Marksmanship.",
    "structured": {
        "@context": "https://schema.org",
        "@type": "Person",
        "name": "Carl Anton Gunnar Claesson",
        "jobTitle": "Iron Merchant",
        "birthDate": "1888-05-31",
        "birthPlace": "Vaggeryd",
        "father": {
            "@type": "Person",
            "name": "J.A.C.",
            "jobTitle": "Timber Merchant"
        },
        "mother": {
            "@type": "Person",
            "name": "Lovisa Johansson"
        },
        "spouse": {
            "@type": "Person",
            "name": "Anne Marie Svensson"
        },
        "education": [
            {
                "@type": "EducationalOrganization",
                "name": "Elementary School"
            },
            {
                "@type": "EducationalOrganization",
                "name": "Trade School"
            }
        ],
        "employmentHistory": [
            {
                "@type": "Organization",
                "name": "Oscar Ljungberg Skillingaryd",
                "startDate": "1903",
                "endDate": "1908"
            },
            {
                "@type": "Organization",
                "name": "Brålanda Iron Trade",
                "startDate": "1908",
                "endDate": "1909"
            },
            {
                "@type": "Organization",
                "name": "Vaggeryds Iron Trade",
                "startDate": "1909"
            }
        ],
        "owns": {
            "@type": "RealEstate",
            "streetAddress": "Fridensborg no. 2",
            "addressLocality": "Vaggeryd"
        },
        "boardMember": [
            {
                "@type": "Organization",
                "name": "Vaggeryd Electricity and Waterworks"
            },
            {
                "@type": "Organization",
                "name": "Jönköping Building Materials Merchant Association"
            },
            {
                "@type": "Organization",
                "name": "Smal Iron Merchant Association",
                "boardMemberType": "Deputy"
            },
            {
                "@type": "Organization",
                "name": "Various non-profit organizations"
            },
            {
                "@type": "Organization",
                "name": "Byarum Family Welfare Board",
                "boardMemberType": "County"
            }
        ],
        "traveledTo": [
            "Germany",
            "Denmark",
            "Norway"
        ],
        "awards": [
            {
                "@type": "SportsAward",
                "name": "Various awards in sports and marksmanship"
            }
        ],
        "honors": [
            {
                "@type": "Organization",
                "name": "National Veterans Association",
                "honorificSuffix": "Honored Member"
            }
        ],
        "hobbies": [
            "Marksmanship"
        ]
    },
    "occupations": {
        "career": [
            {
                "occupational_title": "Iron Merchant",
                "workplace": "Vaggeryds Iron Trade",
                "industry": "Iron Trade",
                "start_date": "1909"
            },
            {
                "occupational_title": "Employee",
                "workplace": "Oscar Ljungberg Skillingaryd",
                "industry": "Unknown",
                "start_date": "1903"
            },
            {
                "occupational_title": "Employee",
                "workplace": "Brålanda Iron Trade",
                "industry": "Unknown",
                "start_date": "1908"
            }
        ]
    }
}