{
    "original": "NOKDENSTEN, Einar August, Bergsingenjör, Arboga, f Striberg, Nora bergsförs, 16/9&gt; 75 av dir A Larson o Amalia Wahlström, gm Karolina Månson. Studex Karol Ivkt Örebro» 95, KTH o Bergshögsk (avd bergsmek) 99-Byggn.ing v Stribergs o Dalkarlsbergs gruvor 99—01, d:o o gruving AB Gällivare Malmfält 01—06, d:o A/S Sydvaranger, Norge, 06—13^ övering o konstr.ch AB Arboga Mek Verkst 1$ —42, projektingenjör sed. 42. Styr.ordf Arboga stads elverk 8 år, ordf Gällivare-Malmbergets; Musiksällsk o Arboga Jaktklubb min. Resor: Norge, Finl, Danm, Tyskl, Belg, Schweiz, Ital,. Engl, USA (2 ggr). Av trycket: »Åsbobergs anrikningsverk» (08), »Sydvarangers järn-malmfält» (14). Hobbies: Resor (helst pr motorcykel), botanik, jakt, musik.",
    "translated": "NOKDENSTEN, Einar August, Mining Engineer, Arboga, born in Striberg, Nora bergsförs, on September 16th, 1875, son of director A Larson and Amalia Wahlström, married to Karolina Månson. Studied at Karolinska Institute of Technology in Örebro in 1895, and at the Royal Institute of Technology and Mining College (department of mining engineering) in 1899. Construction engineer at Stribergs and Dalkarlsbergs mines from 1899 to 1901, as well as in the mining AB Gällivare Malmfält from 1901 to 1906, and in the A/S Sydvaranger in Norway from 1906 to 1913. Overseeing and construction engineer at AB Arboga Mek Verkst from 1913 to 1942, and project engineer since 1942. Chairman of the Arboga City Power Plant for 8 years, and chairman of the Gällivare-Malmbergets Music Society and Arboga Hunting Club. Travels to Norway, Finland, Denmark, Germany, Belgium, Switzerland, Italy, England, and the USA (twice). Published works include \"Åsbobergs Ore Enrichment Plant\" (1908) and \"Sydvaranger's Iron Ore Fields\" (1914). Hobbies include traveling (especially by motorcycle), botany, hunting, and music.",
    "structured": {
        "@context": "https://schema.org",
        "@type": "Person",
        "name": "Einar August Nokdensten",
        "birthDate": "1875-09-16",
        "birthPlace": "Striberg, Nora bergsförs",
        "nationality": "Swedish",
        "occupation": "Mining Engineer",
        "description": "Mining engineer and construction engineer known for his work in various mining companies and as a project engineer.",
        "parents": [
            {
                "@type": "Person",
                "name": "A Larson"
            },
            {
                "@type": "Person",
                "name": "Amalia Wahlström"
            }
        ],
        "spouse": {
            "@type": "Person",
            "name": "Karolina Månson"
        },
        "alumniOf": [
            {
                "@type": "EducationalOrganization",
                "name": "Karolinska Institute of Technology",
                "location": "Örebro",
                "startDate": "1895"
            },
            {
                "@type": "EducationalOrganization",
                "name": "Royal Institute of Technology and Mining College",
                "location": "Stockholm",
                "startDate": "1899"
            }
        ],
        "works": [
            {
                "@type": "CreativeWork",
                "name": "Åsbobergs Ore Enrichment Plant",
                "datePublished": "1908"
            },
            {
                "@type": "CreativeWork",
                "name": "Sydvaranger's Iron Ore Fields",
                "datePublished": "1914"
            }
        ],
        "memberOf": [
            {
                "@type": "Organization",
                "name": "Gällivare-Malmbergets Music Society"
            },
            {
                "@type": "Organization",
                "name": "Arboga Hunting Club"
            }
        ],
        "hobbies": [
            "Traveling",
            "Botany",
            "Hunting",
            "Music"
        ],
        "residence": "Arboga",
        "travelledTo": [
            "Norway",
            "Finland",
            "Denmark",
            "Germany",
            "Belgium",
            "Switzerland",
            "Italy",
            "England",
            "USA"
        ]
    },
    "occupations": {
        "career": [
            {
                "occupational_title": "Mining Engineer",
                "workplace": "Stribergs and Dalkarlsbergs mines",
                "industry": "Mining",
                "start_date": "1899-01-01"
            },
            {
                "occupational_title": "Construction Engineer",
                "workplace": "AB Gällivare Malmfält",
                "industry": "Mining",
                "start_date": "1901-01-01"
            },
            {
                "occupational_title": "Construction Engineer",
                "workplace": "A/S Sydvaranger (Norway)",
                "industry": "Mining",
                "start_date": "1906-01-01"
            },
            {
                "occupational_title": "Overseeing and Construction Engineer",
                "workplace": "AB Arboga Mek Verkst",
                "industry": "Engineering",
                "start_date": "1913-01-01"
            },
            {
                "occupational_title": "Project Engineer",
                "workplace": "AB Arboga Mek Verkst",
                "industry": "Engineering",
                "start_date": "1942-01-01"
            }
        ]
    }
}