{
    "original": "LITTORIN, Konrad, Direktör, Örebro, f öbr 25/3 81 av skohandl C L o Maria Andersson, gm Anna Åström. Hal, hdlssk. I fma Ernst Littorin fr 02, deläg 13—27, dir öbr expr- &amp; hdlsAB sed. 28. Led planter.nmdn. Styr.ordf öbr l bränslehdlfrn. Lstkapt, ordf öbr Istfrn, led Sv Istfrnars centr.frbs vkst utsk. Resor: Tyskl, Engl, Frankr 12. Delt i olymp sp Aten 06, London 08, sv mast i raka hopp 06. KVO2kl, GV:s O1M, LstGM, öbr l Istfrbs GM, öbr l skyt.frbs GM, Sv-GldrRGM, skyt.m g. Hobbies: Botanik, böcker.",
    "translated": "LITTORIN, Konrad, Director, Örebro, born on March 25th, 1881, to shoemaker C.L. and Maria Andersson, married to Anna Åström. Completed secondary school. Started working for Ernst Littorin in 1902, became co-owner from 1913 to 1927, and has been the director of the Örebro Express and Trading Company since 1928. Member of the Board of Plant Nurseries. Chairman of the Board for the local fuel trading company. Lieutenant Captain, chairman of the Rifle Association, member of the Swedish Rifle Association's central committee for shooting growth. Traveled to Germany, England, and France in 1912. Participated in the Olympic Games in Athens in 1906, London in 1908, and won the Swedish championship in high jump in 1906. Knight of the Royal Order, First Class, recipient of the Royal Order of Merit, chairman of the Swedish Rifle Association, chairman of the Shooting Association, Swedish Gold Medal in Shooting. Hobbies: Botany, books.",
    "structured": {
        "@context": "https://schema.org",
        "@type": "Person",
        "name": "Konrad Littorin",
        "birthDate": "1881-03-25",
        "birthPlace": "Örebro",
        "deathDate": null,
        "father": {
            "@type": "Person",
            "name": "C.L. Littorin"
        },
        "mother": {
            "@type": "Person",
            "name": "Maria Andersson"
        },
        "spouse": {
            "@type": "Person",
            "name": "Anna Åström"
        },
        "education": {
            "@type": "EducationalOccupationalCredential",
            "credentialCategory": "SecondarySchool"
        },
        "occupation": "Director",
        "worksFor": {
            "@type": "Organization",
            "name": "Örebro Express and Trading Company"
        },
        "careerPriorTo": {
            "@type": "Organization",
            "name": "Ernst Littorin",
            "startDate": "1902",
            "endDate": "1913"
        },
        "careerDuring": {
            "@type": "Organization",
            "name": "Örebro Express and Trading Company",
            "startDate": "1928"
        },
        "memberOf": [
            {
                "@type": "Organization",
                "name": "Board of Plant Nurseries"
            },
            {
                "@type": "Organization",
                "name": "Rifle Association"
            },
            {
                "@type": "Organization",
                "name": "Swedish Rifle Association"
            }
        ],
        "positionsHeld": [
            {
                "@type": "OrganizationRole",
                "title": "Chairman",
                "namedPosition": "Board for the local fuel trading company"
            },
            {
                "@type": "OrganizationRole",
                "title": "Lieutenant Captain"
            },
            {
                "@type": "OrganizationRole",
                "title": "Chairman",
                "namedPosition": "Rifle Association"
            },
            {
                "@type": "OrganizationRole",
                "title": "Member",
                "namedPosition": "Swedish Rifle Association's central committee for shooting growth"
            }
        ],
        "nationality": "Swedish",
        "residence": "Örebro",
        "traveled": [
            {
                "@type": "Place",
                "name": "Germany"
            },
            {
                "@type": "Place",
                "name": "England"
            },
            {
                "@type": "Place",
                "name": "France"
            }
        ],
        "participatedIn": [
            {
                "@type": "Event",
                "name": "Olympic Games in Athens",
                "startDate": "1906"
            },
            {
                "@type": "Event",
                "name": "Olympic Games in London",
                "startDate": "1908"
            },
            {
                "@type": "Event",
                "name": "Swedish Championship in High Jump",
                "startDate": "1906"
            }
        ],
        "awards": [
            {
                "@type": "Order",
                "name": "Knight of the Royal Order, First Class"
            },
            {
                "@type": "Order",
                "name": "Royal Order of Merit"
            },
            {
                "@type": "Order",
                "name": "Swedish Gold Medal in Shooting"
            }
        ],
        "hobbies": [
            "Botany",
            "Books"
        ]
    },
    "occupations": {
        "career": [
            {
                "occupational_title": "Director",
                "workplace": "Örebro Express and Trading Company",
                "industry": "Express and Trading",
                "start_date": "1928"
            },
            {
                "occupational_title": "Co-owner",
                "workplace": "Ernst Littorin",
                "industry": "Unknown",
                "start_date": "1913"
            }
        ]
    }
}