{
    "original": "HEDE, Oscar Arvid, Ingenjör, Klippan, f Västra Sönnarslöv, Krst l, 15/10 85, gm Agda Nilsson. Ex Norrköpings tekn elem.sk 04, stud.res 04—06. Anst s näting v Malmö stads elvk, konsult ing o org 14—20. Init.tag o en av stift av omses Försäkr.bol Leire Sthlm 21, vkst dir där 21—35, styr.led o deläg AB Dynamis Malmö sed. 24. En av init.tag o styr.led Skånes El Kontrollfrn (Kraftkontrollen) Malmö, sekr i Malmöh l hushålln.sällsk komm f landsortselektrifier planmäss ordn 16, fd styr.led AB Skånska Spisbrödsfabr Krst, ordf o vkst led i Kraftvksfrn mbpa Sthlm 25.",
    "translated": "HEDE, Oscar Arvid, Engineer, Klippan, born in Västra Sönnarslöv, Christened on 15/10 1885, married to Agda Nilsson. Former student of Norrköping Technical Elementary School in 1904, studied as a resident student from 1904 to 1906. Employed as a network engineer for Malmö City Electricity Works, worked as a consultant engineer and organizer from 1914 to 1920. Co-founder and one of the directors of Leire Stockholm Insurance Company since 1921, served as the company's growth director from 1921 to 1935, and served on the board of directors and was a partial owner of AB Dynamis Malmö since 1924. Co-founder and board member of the Skånes El Control Company (Power Control) in Malmö, served as secretary in the Malmö County Household Society Committee for the comprehensive electrification plan for rural areas in 1916, former board member of AB Skånska Spisbrödsfabriken. Served as chairman and growth leader in the Power Plant Association for MBPA Stockholm in 1925.",
    "structured": {
        "@context": "https://schema.org",
        "@type": "Person",
        "name": "Oscar Arvid Hede",
        "jobTitle": "Engineer",
        "address": {
            "@type": "PostalAddress",
            "addressLocality": "Klippan"
        },
        "birthPlace": {
            "@type": "Place",
            "name": "Västra Sönnarslöv"
        },
        "birthDate": "1885-10-15",
        "spouse": {
            "@type": "Person",
            "name": "Agda Nilsson"
        },
        "alumniOf": {
            "@type": "CollegeOrUniversity",
            "name": "Norrköpings Tekniska Elementarskola"
        },
        "education": [
            {
                "@type": "EducationalOrganization",
                "name": "Norrköpings Tekniska Elementarskola",
                "startDate": "1904",
                "endDate": "1906"
            }
        ],
        "work": [
            {
                "@type": "Organization",
                "name": "Malmö City Electricity Works",
                "jobTitle": "Network Engineer",
                "startDate": "1914",
                "endDate": "1920"
            },
            {
                "@type": "Organization",
                "name": "AB Dynamis Malmö",
                "jobTitle": "Director, Partial Owner",
                "startDate": "1924"
            },
            {
                "@type": "Organization",
                "name": "Leire Stockholm Insurance Company",
                "jobTitle": "Director",
                "startDate": "1921",
                "endDate": "1935"
            },
            {
                "@type": "Organization",
                "name": "Skånes El Kontrollfrn (Kraftkontrollen) Malmö",
                "jobTitle": "Board Member"
            },
            {
                "@type": "Organization",
                "name": "AB Skånska Spisbrödsfabr",
                "jobTitle": "Board Member"
            }
        ],
        "memberOf": [
            {
                "@type": "Organization",
                "name": "Malmöhögs hushållningssällskap",
                "jobTitle": "Secretary",
                "startDate": "1916"
            },
            {
                "@type": "Organization",
                "name": "Power Plant Association for MBPA Stockholm",
                "jobTitle": "Chairman, Growth Leader",
                "startDate": "1925"
            }
        ]
    },
    "occupations": {
        "career": [
            {
                "occupational_title": "Engineer",
                "workplace": "Malmö City Electricity Works",
                "industry": "Electricity",
                "start_date": "1914"
            },
            {
                "occupational_title": "Consultant Engineer and Organizer",
                "workplace": "Malmö City Electricity Works",
                "industry": "Electricity",
                "start_date": "1914"
            },
            {
                "occupational_title": "Co-founder and Director",
                "workplace": "Leire Stockholm Insurance Company",
                "industry": "Insurance",
                "start_date": "1921"
            },
            {
                "occupational_title": "Growth Director",
                "workplace": "Leire Stockholm Insurance Company",
                "industry": "Insurance",
                "start_date": "1921"
            },
            {
                "occupational_title": "Board Member and Partial Owner",
                "workplace": "AB Dynamis Malmö",
                "industry": "Unknown",
                "start_date": "1924"
            },
            {
                "occupational_title": "Co-founder and Board Member",
                "workplace": "Skånes El Control Company (Power Control)",
                "industry": "Electricity",
                "start_date": "Unknown"
            },
            {
                "occupational_title": "Secretary",
                "workplace": "Malmö County Household Society Committee",
                "industry": "Unknown",
                "start_date": "1916"
            },
            {
                "occupational_title": "Board Member",
                "workplace": "AB Skånska Spisbrödsfabriken",
                "industry": "Unknown",
                "start_date": "Unknown"
            },
            {
                "occupational_title": "Chairman and Growth Leader",
                "workplace": "Power Plant Association for MBPA Stockholm",
                "industry": "Electricity",
                "start_date": "1925"
            }
        ]
    }
}