{
    "original": "MAGNUSSON, John Albert, Ombudsman, Hudiksvall, f Reftele, Jkp l, 22/9 85 av skräd. -m Magnus Arvidsson o Kristina Svensson, gm Astrid Svensson. Aff.anst 06—22, omb.m Sv köpmfrb 22—27, d:o Gävleb l köpmfrb sed. 27. Led stads- o kyrkoflm, ordf fat.v.styr, folksk.styr o Hdsv stads yrksk:r, v. ordf soc.vårdsnmdn o fam.bidr.nmdn, led krist.-nmdn, överförmynd. TR, Odd Fellow, IOGT, N Hälsingl pedagog sällsk (styr.led); Sv köpmfrbs ftjgm.",
    "translated": "MAGNUSSON, John Albert, Ombudsman, Hudiksvall, born in Reftele, Jönköping county, on September 22nd, 1885, son of Magnus Arvidsson and Kristina Svensson, married to Astrid Svensson. Employed in business 1906-1922, ombudsman for the Swedish Commercial Workers' Federation 1922-1927, and then for the Gävleborg county Commercial Workers' Federation from 1927 onwards. Member of city and church boards, chairman of the welfare committee, school board, and Hudiksvall vocational school board, vice-chairman of the social welfare committee and family support committee, member of the Christian committee, and trustee of the district court. Member of Odd Fellow, IOGT (International Order of Good Templars), and the Northern Hälsingland Pedagogical Society (board member). Member of the Swedish Commercial Workers' Federation's disciplinary committee.",
    "structured": {
        "@context": "https://schema.org",
        "@type": "Person",
        "name": "John Albert Magnusson",
        "jobTitle": "Ombudsman",
        "birthDate": "1885-09-22",
        "birthPlace": {
            "@type": "City",
            "name": "Reftele",
            "address": {
                "@type": "PostalAddress",
                "addressRegion": "Jönköping county"
            }
        },
        "parents": [
            {
                "@type": "Person",
                "name": "Magnus Arvidsson"
            },
            {
                "@type": "Person",
                "name": "Kristina Svensson"
            }
        ],
        "spouse": {
            "@type": "Person",
            "name": "Astrid Svensson"
        },
        "employmentHistory": [
            {
                "@type": "Organization",
                "name": "Business",
                "startDate": "1906",
                "endDate": "1922"
            },
            {
                "@type": "Organization",
                "name": "Swedish Commercial Workers' Federation",
                "startDate": "1922",
                "endDate": "1927"
            },
            {
                "@type": "Organization",
                "name": "Gävleborg county Commercial Workers' Federation",
                "startDate": "1927"
            }
        ],
        "memberOf": [
            {
                "@type": "Organization",
                "name": "City and Church Board"
            },
            {
                "@type": "Organization",
                "name": "Welfare Committee"
            },
            {
                "@type": "Organization",
                "name": "School Board"
            },
            {
                "@type": "Organization",
                "name": "Hudiksvall Vocational School Board"
            },
            {
                "@type": "Organization",
                "name": "Social Welfare Committee"
            },
            {
                "@type": "Organization",
                "name": "Family Support Committee"
            },
            {
                "@type": "Organization",
                "name": "Christian Committee"
            },
            {
                "@type": "Organization",
                "name": "District Court"
            },
            {
                "@type": "Organization",
                "name": "Odd Fellow"
            },
            {
                "@type": "Organization",
                "name": "International Order of Good Templars (IOGT)"
            },
            {
                "@type": "Organization",
                "name": "Northern Hälsingland Pedagogical Society"
            },
            {
                "@type": "Organization",
                "name": "Swedish Commercial Workers' Federation Disciplinary Committee"
            }
        ]
    },
    "occupations": {
        "career": [
            {
                "occupational_title": "Aff.anst",
                "workplace": "",
                "industry": "",
                "start_date": "1906"
            },
            {
                "occupational_title": "Omb.m Sv köpmfrb",
                "workplace": "",
                "industry": "",
                "start_date": "1922"
            },
            {
                "occupational_title": "Ombudsman",
                "workplace": "Gävleborg County Commercial Workers' Federation",
                "industry": "",
                "start_date": "1927"
            }
        ]
    }
}