{
    "original": "HOLMGREN, Charles Gustaf Emanuel, överste, Eskilstuna, f Sthlm 21/7 91 av J F H o Elin Peterson, gm Elsa Falk. Mog.ex 09, off.ex 11, A o IH :s allm o högre art.kurser 13—16, spec.kurs KTH :s facksk f bergsvetensk 18—20, utbildn t kontr.off v art 17—20. Ulöjtn Uppl art.reg 11, löjtn 16, kapt 25, trpt t Smal arméart.reg 28. Kontr.off v art m plac i Sthlm 20—25, i E.tuna 25—26, arb.off v Carl Gustafsstads gev.fakt 26—33, styresman f Carl Gustafs stads gev.fakt sed. 33. Major i armén 34, öv.-löjtn 37, trpt t Fälttygkåren 37, överste 41. Styr.ordf Maskinfacksk, E.tuna, insp E.tuna stads yrkesskolor, led av domkap Strnäs stift, led av kyrkoflm E.tuna, led av kyrkorådet E.tuna-Fors förs. Styr.ordf E.tuna Jernmanuf AB o Int Gevärs AB. Resor: Danm 21, 24, 27, 29, 31, 35, 41, Engl 30, Finl 37, 40, Frankr 30, Nederl 30, Norge 35, 37, 38, Schweiz 41, Tjeckosl 38, Tyskl 30, 38, 41. RSO, RVO, Sthlms sfb SM, RDDO, RNS:tOOlkl, LKKrVa.",
    "translated": "HOLMGREN, Charles Gustaf Emanuel, Colonel, Eskilstuna, born Stockholm 21/7 91 to J F H and Elin Peterson, married Elsa Falk. Graduated 1909, commissioned officer 1911, attended A and IH's general and advanced art courses 1913-1916, specialized course in mining engineering at KTH's technical school 1918-1920, trained as a contract officer in artillery 1917-1920. Second Lieutenant in the Uppland Artillery Regiment in 1911, Lieutenant in 1916, Captain in 1925, transferred to the Small Army Artillery Regiment in 1928. Contract officer in artillery stationed in Stockholm 1920-1925, in Eskilstuna 1925-1926, working officer at the Carl Gustaf City Gun Factory from 1926-1933, governor of the Carl Gustaf City Gun Factory since 1933. Major in the army in 1934, Lieutenant Colonel in 1937, transferred to the Field Artillery Regiment in 1937, Colonel in 1941. Chairman of the Machinery Technical School, Eskilstuna, inspector of the vocational schools in Eskilstuna, member of the ecclesiastical court of the Strängnäs Diocese, member of the church film board in Eskilstuna, member of the church council in Eskilstuna-Fors parish. Chairman of E.tuna Jernmanuf AB and Int Gevärs AB. Travelled to Denmark in 1921, 1924, 1927, 1929, 1931, 1935, 1941, England in 1930, Finland in 1937, 1940, France in 1930, the Netherlands in 1930, Norway in 1935, 1937, 1938, Switzerland in 1941, Czechoslovakia in 1938, Germany in 1930, 1938, 1941. Recipient of RSO, RVO, Stockholm Shooting Society's Silver Medal, RDDO, RNS Medal of the First Class, Cross of Honor of the Order of Vasa. Note: \"\\d\\d m. partner's name\" means married in the year 19xx.",
    "structured": {
        "@context": "https://schema.org",
        "@type": "Person",
        "name": "Charles Gustaf Emanuel Holmgren",
        "birthDate": "1891-07-21",
        "birthPlace": "Stockholm",
        "nationality": "Swedish",
        "spouse": [
            {
                "@type": "Person",
                "name": "Elsa Falk",
                "marriageDate": "1909"
            }
        ],
        "education": [
            {
                "@type": "EducationalOccupationalCredential",
                "name": "Specialized course in mining engineering",
                "educationalLevel": "Undergraduate",
                "educationalProgram": "KTH's technical school",
                "startDate": "1918",
                "endDate": "1920"
            },
            {
                "@type": "EducationalOccupationalCredential",
                "name": "General and advanced art courses",
                "educationalLevel": "Undergraduate",
                "educationalProgram": "A and IH's art courses",
                "startDate": "1913",
                "endDate": "1916"
            }
        ],
        "career": [
            {
                "@type": "MilitaryService",
                "title": "Second Lieutenant",
                "startDate": "1911",
                "endDate": "1916",
                "affiliation": "Uppland Artillery Regiment"
            },
            {
                "@type": "MilitaryService",
                "title": "Lieutenant",
                "startDate": "1916",
                "endDate": "1925",
                "affiliation": "Uppland Artillery Regiment"
            },
            {
                "@type": "MilitaryService",
                "title": "Captain",
                "startDate": "1925",
                "endDate": "1928",
                "affiliation": "Small Army Artillery Regiment"
            },
            {
                "@type": "MilitaryService",
                "title": "Contract Officer in Artillery",
                "startDate": "1920",
                "endDate": "1925",
                "affiliation": "Stockholm"
            },
            {
                "@type": "MilitaryService",
                "title": "Contract Officer in Artillery",
                "startDate": "1925",
                "endDate": "1926",
                "affiliation": "Eskilstuna"
            },
            {
                "@type": "MilitaryService",
                "title": "Working Officer",
                "startDate": "1926",
                "endDate": "1933",
                "affiliation": "Carl Gustaf City Gun Factory"
            },
            {
                "@type": "MilitaryService",
                "title": "Governor",
                "startDate": "1933",
                "affiliation": "Carl Gustaf City Gun Factory"
            },
            {
                "@type": "MilitaryService",
                "title": "Major",
                "startDate": "1934"
            },
            {
                "@type": "MilitaryService",
                "title": "Lieutenant Colonel",
                "startDate": "1937"
            },
            {
                "@type": "MilitaryService",
                "title": "Colonel",
                "startDate": "1941"
            }
        ],
        "organizations": [
            {
                "@type": "Organization",
                "name": "Machinery Technical School",
                "position": "Chairman",
                "location": "Eskilstuna"
            },
            {
                "@type": "Organization",
                "name": "E.tuna Jernmanuf AB",
                "position": "Chairman"
            },
            {
                "@type": "Organization",
                "name": "International Gevärs AB",
                "position": "Chairman"
            }
        ],
        "travels": [
            "Denmark (1921, 1924, 1927, 1929, 1931, 1935, 1941)",
            "England (1930)",
            "Finland (1937, 1940)",
            "France (1930)",
            "Netherlands (1930)",
            "Norway (1935, 1937, 1938)",
            "Switzerland (1941)",
            "Czechoslovakia (1938)",
            "Germany (1930, 1938, 1941)"
        ],
        "honors": [
            "RSO",
            "RVO",
            "Sthlms sfb SM",
            "RDDO",
            "RNS:tOOlkl",
            "LKKrVa"
        ]
    },
    "occupations": {
        "career": [
            {
                "occupational_title": "Commissioned Officer",
                "workplace": "Uppland Artillery Regiment",
                "industry": "Military",
                "start_date": "1911"
            },
            {
                "occupational_title": "Lieutenant",
                "workplace": "Uppland Artillery Regiment",
                "industry": "Military",
                "start_date": "1916"
            },
            {
                "occupational_title": "Captain",
                "workplace": "Small Army Artillery Regiment",
                "industry": "Military",
                "start_date": "1925"
            },
            {
                "occupational_title": "Contract Officer in Artillery",
                "workplace": "Stockholm",
                "industry": "Military",
                "start_date": "1920"
            },
            {
                "occupational_title": "Contract Officer in Artillery",
                "workplace": "Eskilstuna",
                "industry": "Military",
                "start_date": "1925"
            },
            {
                "occupational_title": "Working Officer",
                "workplace": "Carl Gustaf City Gun Factory",
                "industry": "Manufacturing",
                "start_date": "1926"
            },
            {
                "occupational_title": "Governor of Carl Gustaf City Gun Factory",
                "workplace": "Carl Gustaf City Gun Factory",
                "industry": "Manufacturing",
                "start_date": "1933"
            },
            {
                "occupational_title": "Major in the Army",
                "workplace": "Military",
                "industry": "Military",
                "start_date": "1934"
            },
            {
                "occupational_title": "Lieutenant Colonel",
                "workplace": "Field Artillery Regiment",
                "industry": "Military",
                "start_date": "1937"
            },
            {
                "occupational_title": "Colonel",
                "workplace": "Field Artillery Regiment",
                "industry": "Military",
                "start_date": "1941"
            }
        ]
    }
}