{
    "original": "BERGLING, Johan Albert, Byggnadsingenjör, Skara, f Tjällmo 11/12 76 av S O B o Johanna Samuelsson, gm Valborg Larsson. Tekn elem.sk Norrk, Byggn.yrk.sk (BYS) Sthlm. Anst arkit.kont Sthlm 06—08, arb.led v uppf av Ulriceh vintersanat 09—10, fabr o bostbyggn v AB Primus vkstdr L Essingen, Sthlm, 10—14, samt Skarab läns tuberk.-sjukh.byggn å St Ekeberg, Axvall, 14—16, kontrollant v uppf av museigyggn f Västerg fornm.frn Skara samt slaktbyggn i Skara 16 —18, uppf till- o ombyggn av lantmsk i Skara ef t egn ritn 16—18, senare eg byggn.-verks å bysgn f Skarab ensk bk Skara, Lidk mfl pltsr, kontr o tillsyn v fi byggn.företag. Utfört brandstat Skara eft egn ritn, ny-byggn f Hush. sällsk Skara o Egnellska stift Skövde, kontr v ombyggn av länsres o landst.huset Mariestad, nybggn f semin Skara, många priv byggn. Stdflm, v ordf dräts.kamm, ordf brandstyr, led av lokalstyr f Skara Ivk, flksk.styr, skolr, byggn.nmdn, div komm.uppdr. Styr.led Skarab läns stadshyp.frn. Huvudm Skarab läns sparbk Skara. Resor: Danm, Tyskl, Engl, Frankr.",
    "translated": "BERGLING, Johan Albert, Construction Engineer, Skara, born in Tjällmo on December 11, 1876, son of S O B and Johanna Samuelsson, married to Valborg Larsson. Technical elementary school in Norrk, Building trade school (BYS) in Stockholm. Employed at architectural office in Stockholm from 1906 to 1908, worked as a project manager in the construction of Ulriceh winter sanatorium from 1909 to 1910, construction of factories and residential buildings at AB Primus in Lidingö, Stockholm, from 1910 to 1914, as well as the construction of the tuberculosis hospital building at St Ekeberg, Axvall, Skara county, from 1914 to 1916. Also worked as a supervisor in the construction of museum buildings for Västergötland's ancient monuments in Skara, and the slaughterhouse building in Skara from 1916 to 1918. Involved in the construction and renovations of agricultural schools in Skara according to own designs from 1916 to 1918. Later became a building operator for Skaraborgs Enskilda Bank in Skara, Lidköping, and other places, as well as contracts and supervision for various construction companies. Carried out fire safety inspections in Skara according to own designs, construction of new buildings for the Housing Association in Skara and Egnellska Foundation in Skövde, renovation contract for the county council building in Mariestad, construction of a new seminar building in Skara, and many private buildings. Member of the board in the Municipal Finance Committee, chairman of the Fire Brigade, and member of various local committees in Skara, including the school board, building committee, and other municipal assignments. Also a board member of Skaraborg County Mortgage Bank. Main occupation at Skaraborg County Savings Bank in Skara. Traveled to Denmark, Germany, England, France.",
    "structured": {
        "@context": "https://schema.org",
        "@type": "Person",
        "name": "Johan Albert Bergling",
        "jobTitle": "Construction Engineer",
        "birthDate": "1876-12-11",
        "birthPlace": "Tjällmo, Sweden",
        "familyName": "Bergling",
        "givenName": "Johan Albert",
        "spouse": {
            "@type": "Person",
            "name": "Valborg Larsson"
        },
        "parents": [
            {
                "@type": "Person",
                "name": "S O B"
            },
            {
                "@type": "Person",
                "name": "Johanna Samuelsson"
            }
        ],
        "educationalCredentialAwarded": [
            {
                "@type": "EducationalOccupationalCredential",
                "name": "Technical elementary school diploma",
                "awardedBy": "Norrk"
            },
            {
                "@type": "EducationalOccupationalCredential",
                "name": "Building trade school diploma",
                "awardedBy": "Stockholm"
            }
        ],
        "workExperience": [
            {
                "@type": "OrganizationRole",
                "startDate": "1906",
                "endDate": "1908",
                "roleName": "Employee",
                "organization": {
                    "@type": "Organization",
                    "name": "Architectural Office",
                    "address": {
                        "@type": "PostalAddress",
                        "addressLocality": "Stockholm"
                    }
                }
            },
            {
                "@type": "OrganizationRole",
                "startDate": "1909",
                "endDate": "1910",
                "roleName": "Project Manager",
                "organization": {
                    "@type": "Organization",
                    "name": "Ulriceh Winter Sanatorium",
                    "address": {
                        "@type": "PostalAddress",
                        "addressLocality": "Stockholm"
                    }
                }
            },
            {
                "@type": "OrganizationRole",
                "startDate": "1910",
                "endDate": "1914",
                "roleName": "Constructor",
                "organization": {
                    "@type": "Organization",
                    "name": "AB Primus",
                    "address": {
                        "@type": "PostalAddress",
                        "addressLocality": "Lidingö, Stockholm"
                    }
                }
            },
            {
                "@type": "OrganizationRole",
                "startDate": "1914",
                "endDate": "1916",
                "roleName": "Builder",
                "organization": {
                    "@type": "Organization",
                    "name": "Skarab läns tuberk.-sjukh.byggn",
                    "address": {
                        "@type": "PostalAddress",
                        "addressLocality": "St Ekeberg, Axvall, Skara"
                    }
                }
            },
            {
                "@type": "OrganizationRole",
                "startDate": "1916",
                "endDate": "1918",
                "roleName": "Supervisor",
                "organization": {
                    "@type": "Organization",
                    "name": "Museum buildings for Västergötland's ancient monuments",
                    "address": {
                        "@type": "PostalAddress",
                        "addressLocality": "Skara"
                    }
                }
            },
            {
                "@type": "OrganizationRole",
                "startDate": "1916",
                "endDate": "1918",
                "roleName": "Building Operator",
                "organization": {
                    "@type": "Organization",
                    "name": "Skaraborgs Enskilda Bank",
                    "address": [
                        {
                            "@type": "PostalAddress",
                            "addressLocality": "Skara"
                        },
                        {
                            "@type": "PostalAddress",
                            "addressLocality": "Lidköping"
                        }
                    ]
                }
            }
        ],
        "nationality": "Swedish",
        "memberOf": [
            {
                "@type": "Organization",
                "name": "Municipal Finance Committee",
                "memberOf": {
                    "@type": "Organization",
                    "name": "Skara"
                },
                "roleName": "Vice Chairman"
            },
            {
                "@type": "Organization",
                "name": "Fire Brigade",
                "memberOf": {
                    "@type": "Organization",
                    "name": "Skara"
                },
                "roleName": "Chairman"
            },
            {
                "@type": "Organization",
                "name": "Skaraborg County Mortgage Bank",
                "memberOf": {
                    "@type": "Organization",
                    "name": "Skara"
                },
                "roleName": "Board Member"
            }
        ],
        "travelHistory": [
            "Denmark",
            "Germany",
            "England",
            "France"
        ]
    },
    "occupations": {
        "career": [
            {
                "occupational_title": "Construction Engineer",
                "workplace": "Architectural Office",
                "industry": "Construction",
                "start_date": "1906"
            },
            {
                "occupational_title": "Project Manager",
                "workplace": "Ulriceh Winter Sanatorium",
                "industry": "Construction",
                "start_date": "1909"
            },
            {
                "occupational_title": "Construction Engineer",
                "workplace": "AB Primus",
                "industry": "Construction",
                "start_date": "1910"
            },
            {
                "occupational_title": "Construction Engineer",
                "workplace": "St Ekeberg Tuberculosis Hospital",
                "industry": "Healthcare",
                "start_date": "1914"
            },
            {
                "occupational_title": "Supervisor",
                "workplace": "Museum Buildings for Västergötland's Ancient Monuments",
                "industry": "Heritage",
                "start_date": "1916"
            },
            {
                "occupational_title": "Supervisor",
                "workplace": "Skara Slaughterhouse",
                "industry": "Agriculture",
                "start_date": "1916"
            },
            {
                "occupational_title": "Building Operator",
                "workplace": "Skaraborgs Enskilda Bank",
                "industry": "Banking",
                "start_date": "Unknown"
            }
        ]
    }
}