{
    "original": "BONDESON, Lennart, Direktör, Svalöv, f Svalöv 7/6 81 av dir o riksdagsm Per B o Bengta Jönsson, gm Sigrid Johnsson. H a l till 96, hdlssk 96—97, Fridhems fhsk 97—98, lantm.sk 01—02, Alnarps lantbr.inst 03—05, hospitant v mej.inst där 05. Sed. 21 vkst dir i Per Bondessons Lantbr.AB (gr 99). Ordf i Sydv Skånes Andelsslakt.frn, i Sv Svinavels-frn o i Malmöh L Svinavelsfrn, 2 :e v. ordf i Fören Sk Andelsslakt :r (Scan) ; ordf Malmöh L Kontr.frns centralstyr; Styr.led i Nordv Sk:s Andelsslakt :r, i Sv Slakt.frb, ordf Malmöh L Mej.idk.frn, i Sydv Skånes Mej.frb, i Mjölk-propag, i Sk Bkn o i Brand- o Lifförs.AB Skåne; led av Malmöh L Hush.sällsk:» förv.utsk. V. ordf i Svalöfs mfl sockn sparbk sed. 29. Landstingsman sed. 39. Rev Sv landskomm frb sed. 40. Komm.stämmans ordf, l kamm (h) sed. 39. Resor: Danm, Norge, Finl, Tyskl, Holl, Engl, Skottl o Ung uppr ggr f stud av husdjurs-avel. Av trycket: Tidskr.art, spec betr svinskötsel. RVO, LLA, Malmöh L Skyt.frbs ftjGM, N:a Skånes Lstfrbs d :o, Sv Skyt.frbs d:o, Svalövs Skyt.frns d :o. Hobby: Resor.",
    "translated": "BONDESON, Lennart, Director, Svalöv, b. Svalöv 7/6 1881, son of director and member of parliament Per B and Bengta Jönsson, m. Sigrid Johnsson. Primary education until age 12, trade school 96-97, Fridhems agricultural school 97-98, agricultural school 01-02, Alnarp agricultural institute 03-05, trainee at dairy institute there in 05. Since 21, director of Per Bondesson's Agricultural AB (since 99). Chairman of the Southern Skåne Cooperative Meat Association, Swedish Swine Breeding Association, and Malmö Cooperative Swine Breeding Association, 2nd vice chairman of the Cooperative Meat Association Federation (Scan); chairman of the Malmö Cooperative Dairy Association Central Board; Board member of the Northern Skåne Cooperative Meat Association, Swedish Meat Industry Association; chairman of the Malmö Cooperative Dairy Industry Association, Southern Skåne Dairy Association, Milk Propagation Association, Skåne Bank and Fire and Life Insurance AB; member of the Malmö Cooperative Household Association's advisory committee. 2nd vice chairman of the Svalöf and other district savings bank since 29. County council member since 39. Audited the Swedish Municipalities Association since 40. Chairman of the municipal assembly, local council (conservative) since 39. Travels: Denmark, Norway, Finland, Germany, Holland, England, Scotland, and Hungary for the study of animal breeding. Published articles on pig farming. Royal Order of Vasa, Royal Swedish Academy of Agriculture and Forestry, Malmö Local Shooting Association's honorary gold medal, Northern Skåne Shooting Association's diploma, Swedish Shooting Association's diploma, Svalöv Shooting Association's diploma. Hobby: Travels.",
    "structured": {
        "@context": "https://schema.org",
        "@type": "Person",
        "name": "Lennart Bondeson",
        "jobTitle": "Director",
        "birthDate": "1881-06-07",
        "birthPlace": "Svalöv",
        "parent": [
            {
                "@type": "Person",
                "name": "Per Bondesson",
                "jobTitle": "Director"
            },
            {
                "@type": "Person",
                "name": "Bengta Jönsson"
            }
        ],
        "spouse": {
            "@type": "Person",
            "name": "Sigrid Johnsson"
        },
        "education": [
            {
                "@type": "EducationalOccupationalProgram",
                "startDate": "1893",
                "endDate": "1894",
                "institution": "Primary education"
            },
            {
                "@type": "EducationalOccupationalProgram",
                "startDate": "1896",
                "endDate": "1897",
                "institution": "Trade school"
            },
            {
                "@type": "EducationalOccupationalProgram",
                "startDate": "1897",
                "endDate": "1898",
                "institution": "Fridhems agricultural school"
            },
            {
                "@type": "EducationalOccupationalProgram",
                "startDate": "1901",
                "endDate": "1902",
                "institution": "Agricultural school"
            },
            {
                "@type": "EducationalOccupationalProgram",
                "startDate": "1903",
                "endDate": "1905",
                "institution": "Alnarp agricultural institute"
            }
        ],
        "workExperience": [
            {
                "@type": "OrganizationRole",
                "startDate": "1921",
                "roleName": "Director",
                "organization": {
                    "@type": "Organization",
                    "name": "Per Bondessons Lantbr.AB"
                }
            }
        ],
        "affiliation": [
            {
                "@type": "Organization",
                "name": "Southern Skåne Cooperative Meat Association",
                "roleName": "Chairman"
            },
            {
                "@type": "Organization",
                "name": "Swedish Swine Breeding Association",
                "roleName": "Chairman"
            },
            {
                "@type": "Organization",
                "name": "Malmö Cooperative Swine Breeding Association",
                "roleName": "Chairman"
            },
            {
                "@type": "Organization",
                "name": "Cooperative Meat Association Federation",
                "roleName": "2nd vice chairman"
            },
            {
                "@type": "Organization",
                "name": "Malmö Cooperative Dairy Association",
                "roleName": "Chairman"
            },
            {
                "@type": "Organization",
                "name": "Northern Skåne Cooperative Meat Association",
                "roleName": "Board member"
            },
            {
                "@type": "Organization",
                "name": "Swedish Meat Industry Association",
                "roleName": "Board member"
            },
            {
                "@type": "Organization",
                "name": "Southern Skåne Dairy Association",
                "roleName": "Chairman"
            },
            {
                "@type": "Organization",
                "name": "Milk Propagation Association",
                "roleName": "Chairman"
            },
            {
                "@type": "Organization",
                "name": "Skåne Bank",
                "roleName": "Chairman"
            },
            {
                "@type": "Organization",
                "name": "Fire and Life Insurance AB Skåne",
                "roleName": "Chairman"
            },
            {
                "@type": "Organization",
                "name": "Malmö Cooperative Household Association",
                "roleName": "Member"
            },
            {
                "@type": "Organization",
                "name": "Svalöf and other district savings bank",
                "roleName": "2nd vice chairman"
            }
        ],
        "awards": [
            {
                "@type": "Order",
                "name": "Royal Order of Vasa"
            },
            {
                "@type": "Medal",
                "name": "Malmö Local Shooting Association's honorary gold medal"
            },
            {
                "@type": "Diploma",
                "name": "Northern Skåne Shooting Association's diploma"
            },
            {
                "@type": "Diploma",
                "name": "Swedish Shooting Association's diploma"
            },
            {
                "@type": "Diploma",
                "name": "Svalöv Shooting Association's diploma"
            }
        ],
        "hobby": "Travels"
    },
    "occupations": {
        "career": [
            {
                "occupational_title": "Director",
                "workplace": "Per Bondesson's Agricultural AB",
                "industry": "Agriculture",
                "start_date": "1921"
            },
            {
                "occupational_title": "Chairman",
                "workplace": "Southern Skåne Cooperative Meat Association",
                "industry": "Agriculture",
                "start_date": null
            },
            {
                "occupational_title": "Chairman",
                "workplace": "Swedish Swine Breeding Association",
                "industry": "Agriculture",
                "start_date": null
            },
            {
                "occupational_title": "Chairman",
                "workplace": "Malmö Cooperative Swine Breeding Association",
                "industry": "Agriculture",
                "start_date": null
            },
            {
                "occupational_title": "2nd Vice Chairman",
                "workplace": "Cooperative Meat Association Federation",
                "industry": "Agriculture",
                "start_date": null
            },
            {
                "occupational_title": "Chairman",
                "workplace": "Malmö Cooperative Dairy Association Central Board",
                "industry": "Dairy",
                "start_date": null
            },
            {
                "occupational_title": "Board Member",
                "workplace": "Northern Skåne Cooperative Meat Association",
                "industry": "Agriculture",
                "start_date": null
            },
            {
                "occupational_title": "Board Member",
                "workplace": "Swedish Meat Industry Association",
                "industry": "Agriculture",
                "start_date": null
            },
            {
                "occupational_title": "Chairman",
                "workplace": "Malmö Cooperative Dairy Industry Association",
                "industry": "Dairy",
                "start_date": null
            },
            {
                "occupational_title": "Chairman",
                "workplace": "Southern Skåne Dairy Association",
                "industry": "Dairy",
                "start_date": null
            },
            {
                "occupational_title": "Chairman",
                "workplace": "Milk Propagation Association",
                "industry": "Dairy",
                "start_date": null
            },
            {
                "occupational_title": "Chairman",
                "workplace": "Skåne Bank",
                "industry": "Finance",
                "start_date": null
            },
            {
                "occupational_title": "Chairman",
                "workplace": "Fire and Life Insurance AB Skåne",
                "industry": "Insurance",
                "start_date": null
            }
        ]
    }
}