{
    "original": "ODQVIST, Folke Karl Gustaf, Professor, Djursholm, £ Sthlm 29/7 99 av reg.läk K A O o Inez Wahlén, gm Vera Traugott. Studex Sthlm 17, KTH (maskinbyggn o mek tekn) 18—22, StHS 19—28, fil kand 22, fil lic 25, fil dr 28. l:e ass å KTH:s ångtekn lab 22—24, ing v AB Electrolux’ kyltekn lab 26—29, lab.-ch v AB Nomy i Ulvsunda 29—36, doc i tekn mek v KTH 31—36, prof i hållfasthetslära där sed. 36 o prorektor sed. 43. Studentkårens insp sed. 42. Led av Flygtekn försöksanst :s byggn.kté fr 38 o av anst:s styr sed. 40, av Försvarets forskn.nmd sed. 43. Styr.led i Pen-delastic AB i Sundbyberg sed. 44. Publicerat ett flert upps o avhandl i IVA:s handl, Tekn Tidskr mfl in- o utl facktidskr.",
    "translated": "ODQVIST, Folke Karl Gustaf, Professor, Djursholm, £ Sthlm 29/7 99 av reg.läk K A O o Inez Wahlén, gm Vera Traugott. Studex Sthlm 17, KTH (maskinbyggn o mek tekn) 18—22, StHS 19—28, fil kand 22, fil lic 25, fil dr 28. l:e ass å KTH:s ångtekn lab 22—24, ing v AB Electrolux’ kyltekn lab 26—29, lab.-ch v AB Nomy i Ulvsunda 29—36, doc i tekn mek v KTH 31—36, prof i hållfasthetslära där sed. 36 o prorektor sed. 43. Studentkårens insp sed. 42. Led av Flygtekn försöksanst :s byggn.kté fr 38 o av anst:s styr sed. 40, av Försvarets forskn.nmd sed. 43. Styr.led i Pen-delastic AB i Sundbyberg sed. 44. Publicerat ett flert upps o avhandl i IVA:s handl, Tekn Tidskr mfl in- o utl facktidskr.\n\nODQVIST, Folke Karl Gustaf, Professor, Djursholm, £ Stockholm 29/7 99, born to the registered physician K A O and Inez Wahlén, married Vera Traugott. Completed studies in Stockholm in 1917, attended KTH (Royal Institute of Technology) for Mechanical Engineering and Mechanical Technology from 1918 until 1922, StHS (Stockholm School of Economics) from 1919 to 1928, obtained a Bachelor's degree in 1922, a licentiate degree in 1925, and a doctoral degree in 1928. Served as the first assistant at KTH's Steam Technology Laboratory from 1922 to 1924, engineer at AB Electrolux's Refrigeration Technology Laboratory from 1926 to 1929, laboratory chief at AB Nomy in Ulvsunda from 1929 to 1936, docent in technical mechanics at KTH from 1931 to 1936, professor of strength of materials there since 1936, and vice rector since 1943. Served as the student union's inspector since 1942. A board member of the Flight Technical Research Institute's construction committee since 1938 and a member of its board since 1940, as well as a member of the Defense Research Committee since 1943. Board member of Pen-delastic AB in Sundbyberg since 1944. Has published numerous papers and dissertations in the proceedings of the Royal Swedish Academy of Engineering Sciences, Teknisk Tidskrift (Technical Journal), and other national and international technical journals.",
    "structured": {
        "@context": "https://schema.org",
        "@type": "Person",
        "name": "Folke Karl Gustaf Odqvist",
        "birthDate": "1899-07-29",
        "birthPlace": "Djursholm, Sweden",
        "familyName": "Odqvist",
        "givenName": "Folke",
        "nationality": "Swedish",
        "jobTitle": "Professor",
        "address": {
            "@type": "PostalAddress",
            "addressCountry": "Sweden",
            "addressLocality": "Djursholm",
            "addressRegion": "Stockholm"
        },
        "parent": [
            {
                "@type": "Person",
                "name": "K A O",
                "jobTitle": "Registered Physician"
            },
            {
                "@type": "Person",
                "name": "Inez Wahlén"
            }
        ],
        "spouse": {
            "@type": "Person",
            "name": "Vera Traugott"
        },
        "education": [
            {
                "@type": "EducationalOccupationalCredential",
                "credentialCategory": "Degree",
                "educationalLevel": "Bachelor's degree",
                "startDate": "1918",
                "endDate": "1922",
                "provider": "Stockholm University"
            },
            {
                "@type": "EducationalOccupationalCredential",
                "credentialCategory": "Degree",
                "educationalLevel": "Licentiate degree",
                "startDate": "1922",
                "endDate": "1925",
                "provider": "Stockholm University"
            },
            {
                "@type": "EducationalOccupationalCredential",
                "credentialCategory": "Degree",
                "educationalLevel": "Doctoral degree",
                "startDate": "1925",
                "endDate": "1928",
                "provider": "Stockholm University"
            },
            {
                "@type": "EducationalOccupationalCredential",
                "credentialCategory": "Education",
                "educationalLevel": "Doctoral Studies",
                "startDate": "1919",
                "endDate": "1928",
                "provider": "Stockholm School of Economics"
            },
            {
                "@type": "EducationalOccupationalCredential",
                "credentialCategory": "Education",
                "educationalLevel": "Engineering Studies",
                "startDate": "1918",
                "endDate": "1922",
                "provider": "Royal Institute of Technology"
            }
        ],
        "employmentHistory": [
            {
                "@type": "OrganizationRole",
                "startDate": "1922",
                "endDate": "1924",
                "roleName": "First Assistant",
                "organization": {
                    "@type": "Organization",
                    "name": "Royal Institute of Technology",
                    "address": {
                        "@type": "PostalAddress",
                        "addressCountry": "Sweden"
                    }
                }
            },
            {
                "@type": "OrganizationRole",
                "startDate": "1926",
                "endDate": "1929",
                "roleName": "Engineer",
                "organization": {
                    "@type": "Organization",
                    "name": "AB Electrolux",
                    "address": {
                        "@type": "PostalAddress",
                        "addressCountry": "Sweden"
                    }
                }
            },
            {
                "@type": "OrganizationRole",
                "startDate": "1929",
                "endDate": "1936",
                "roleName": "Laboratory Chief",
                "organization": {
                    "@type": "Organization",
                    "name": "AB Nomy",
                    "address": {
                        "@type": "PostalAddress",
                        "addressCountry": "Sweden",
                        "addressLocality": "Ulvsunda"
                    }
                }
            },
            {
                "@type": "OrganizationRole",
                "startDate": "1931",
                "endDate": "1936",
                "roleName": "Docent",
                "organization": {
                    "@type": "Organization",
                    "name": "Royal Institute of Technology",
                    "address": {
                        "@type": "PostalAddress",
                        "addressCountry": "Sweden"
                    }
                }
            },
            {
                "@type": "OrganizationRole",
                "startDate": "1936",
                "roleName": "Professor",
                "organization": {
                    "@type": "Organization",
                    "name": "Royal Institute of Technology",
                    "address": {
                        "@type": "PostalAddress",
                        "addressCountry": "Sweden"
                    }
                }
            },
            {
                "@type": "OrganizationRole",
                "startDate": "1943",
                "roleName": "Vice Rector",
                "organization": {
                    "@type": "Organization",
                    "name": "Royal Institute of Technology",
                    "address": {
                        "@type": "PostalAddress",
                        "addressCountry": "Sweden"
                    }
                }
            },
            {
                "@type": "OrganizationRole",
                "startDate": "1942",
                "roleName": "Inspector",
                "organization": {
                    "@type": "Organization",
                    "name": "Student Union",
                    "address": {
                        "@type": "PostalAddress",
                        "addressCountry": "Sweden"
                    }
                }
            },
            {
                "@type": "OrganizationRole",
                "startDate": "1938",
                "roleName": "Board Member",
                "organization": {
                    "@type": "Organization",
                    "name": "Flight Technical Research Institute",
                    "address": {
                        "@type": "PostalAddress",
                        "addressCountry": "Sweden"
                    }
                }
            },
            {
                "@type": "OrganizationRole",
                "startDate": "1940",
                "roleName": "Board Member",
                "organization": {
                    "@type": "Organization",
                    "name": "Defense Research Committee",
                    "address": {
                        "@type": "PostalAddress",
                        "addressCountry": "Sweden"
                    }
                }
            },
            {
                "@type": "OrganizationRole",
                "startDate": "1944",
                "roleName": "Board Member",
                "organization": {
                    "@type": "Organization",
                    "name": "Pen-delastic AB",
                    "address": {
                        "@type": "PostalAddress",
                        "addressCountry": "Sweden",
                        "addressLocality": "Sundbyberg"
                    }
                }
            }
        ],
        "publication": [
            {
                "@type": "Periodical",
                "name": "Proceedings of the Royal Swedish Academy of Engineering Sciences"
            },
            {
                "@type": "Periodical",
                "name": "Teknisk Tidskrift"
            },
            {
                "@type": "Periodical",
                "name": "Other national and international technical journals"
            }
        ]
    },
    "occupations": {
        "career": [
            {
                "occupational_title": "First Assistant",
                "workplace": "KTH's Steam Technology Laboratory",
                "industry": "Academia",
                "start_date": "1922-01-01"
            },
            {
                "occupational_title": "Engineer",
                "workplace": "AB Electrolux's Refrigeration Technology Laboratory",
                "industry": "Appliance Manufacturing",
                "start_date": "1926-01-01"
            },
            {
                "occupational_title": "Laboratory Chief",
                "workplace": "AB Nomy in Ulvsunda",
                "industry": "Appliance Manufacturing",
                "start_date": "1929-01-01"
            },
            {
                "occupational_title": "Docent",
                "workplace": "KTH",
                "industry": "Academia",
                "start_date": "1931-01-01"
            },
            {
                "occupational_title": "Professor of Strength of Materials",
                "workplace": "KTH",
                "industry": "Academia",
                "start_date": "1936-01-01"
            },
            {
                "occupational_title": "Vice Rector",
                "workplace": "KTH",
                "industry": "Academia",
                "start_date": "1943-01-01"
            }
        ]
    }
}