{
    "original": "GILLE, Nils Jacob, Bergsingenjör, Disponent, Sandviken, f By, Kopparbergs l, 5/4 87 av bruksförvalt C J G o Mina Hedin, gm Stina Forsberg. Mog.ex Uppsala 06, ex bergshögsk 12. Jernkontorets arbetsstipendiat o studieresor utomlands 12—13 samt senare ofta återk bl a t USA 32 o Ryssl 36. Ing Sandvikens Jernverks AB 13—17, d :o h AB Åbjörn Anderson Svedala 17—28, disp o vkst dir See Fabriks AB, Sandviken, Sandvikens Dissousgas AB o Djupdals AB, Sandviken, sed. 28. Styr.led h Kjellberg &amp; Co AB, Sthlm, o Kungsfors Kraft AB, Storvik. V. ordf Sv Bågskjutn.frb, Sthlm, tidigare v. ordf Sv Tekn.frn l :e sekt o ordf i överstyr Sv Verkstäders Tjänstemannafrn. Av trycket: Ett flert upps om gjuteriteknik, om värmebehandl av stålrör mm. RVO, FFrK4kl. Hobbies: Friluftsliv, jakt, bågskjutning.",
    "translated": "GILLE, Nils Jacob, Mining Engineer, Manager, Sandviken, b By, Kopparbergs l, 5/4 87, son of works manager C J G and Mina Hedin, married to Stina Forsberg. Graduated from Uppsala University in 1906, and from the Royal School of Mines in 1912. Recipient of Jernkontoret's work scholarship and study trips abroad in 1912-1913, and later frequently traveled abroad including visits to the United States in 1932 and Russia in 1936. Employed at Sandvikens Jernverks AB from 1913 to 1917, then at AB Åbjörn Anderson Svedala from 1917 to 1928, serving as manager and director at See Fabriks AB, Sandviken, Sandvikens Dissousgas AB, and Djupdals AB, Sandviken since 1928. Also a board member of Kjellberg & Co AB, Stockholm, and Kungsfors Kraft AB, Storvik. Vice chairman of the Swedish Archery Association, Stockholm, former vice chairman of the Swedish Technical Association's 1st section, and chairman of the executive board of the Swedish Machinery Workers' Employees' Association. Published several articles on foundry technology, heat treatment of steel pipes, etc. Awarded with the Royal Order of Vasa (RVO) and the 4th class of the Swedish Red Cross (FFrK4kl). Hobbies include outdoor activities, hunting, and archery.",
    "structured": {
        "@context": "http://schema.org",
        "@type": "Person",
        "name": "Nils Jacob Gille",
        "birthDate": "1887-04-05",
        "jobTitle": "Mining Engineer",
        "nationality": "Swedish",
        "memberOf": [
            {
                "@type": "Organization",
                "name": "Sandvikens Jernverks AB",
                "startDate": "1913",
                "endDate": "1917"
            },
            {
                "@type": "Organization",
                "name": "AB Åbjörn Anderson Svedala",
                "startDate": "1917",
                "endDate": "1928"
            },
            {
                "@type": "Organization",
                "name": "See Fabriks AB",
                "startDate": "1928"
            },
            {
                "@type": "Organization",
                "name": "Sandvikens Dissousgas AB",
                "startDate": "1928"
            },
            {
                "@type": "Organization",
                "name": "Djupdals AB",
                "startDate": "1928",
                "location": "Sandviken"
            },
            {
                "@type": "Organization",
                "name": "Kjellberg & Co AB",
                "startDate": "unknown",
                "location": "Stockholm"
            },
            {
                "@type": "Organization",
                "name": "Kungsfors Kraft AB",
                "startDate": "unknown",
                "location": "Storvik"
            },
            {
                "@type": "Organization",
                "name": "Swedish Archery Association",
                "startDate": "unknown",
                "location": "Stockholm",
                "position": "Vice Chairman"
            },
            {
                "@type": "Organization",
                "name": "Swedish Technical Association",
                "startDate": "unknown",
                "position": "Former Vice Chairman"
            },
            {
                "@type": "Organization",
                "name": "Swedish Machinery Workers' Employees' Association",
                "startDate": "unknown",
                "position": "Chairman of the Executive Board"
            }
        ],
        "alumniOf": [
            {
                "@type": "CollegeOrUniversity",
                "name": "Uppsala University",
                "endDate": "1906"
            },
            {
                "@type": "CollegeOrUniversity",
                "name": "Royal School of Mines",
                "endDate": "1912"
            }
        ],
        "award": [
            {
                "@type": "Order",
                "name": "Royal Order of Vasa",
                "awardDate": "unknown",
                "description": "RVO"
            },
            {
                "@type": "Order",
                "name": "Swedish Red Cross",
                "awardDate": "unknown",
                "class": "4th Class",
                "description": "FFrK4kl"
            }
        ],
        "spouse": "Stina Forsberg",
        "parent": [
            {
                "@type": "Person",
                "name": "C J G",
                "jobTitle": "Works Manager"
            },
            {
                "@type": "Person",
                "name": "Mina Hedin"
            }
        ],
        "description": "Mining Engineer, Manager, Disponent",
        "sameAs": [
            "https://www.example.com/biography-page"
        ],
        "hobbies": [
            "Outdoor activities",
            "Hunting",
            "Archery"
        ]
    },
    "occupations": {
        "career": [
            {
                "occupational_title": "Mining Engineer",
                "workplace": "Sandvikens Jernverks AB",
                "industry": "Mining",
                "start_date": "1913"
            },
            {
                "occupational_title": "Manager",
                "workplace": "AB Åbjörn Anderson Svedala",
                "industry": "Manufacturing",
                "start_date": "1917"
            },
            {
                "occupational_title": "Director",
                "workplace": "See Fabriks AB",
                "industry": "Manufacturing",
                "start_date": "1928"
            },
            {
                "occupational_title": "Director",
                "workplace": "Sandvikens Dissousgas AB",
                "industry": "Manufacturing",
                "start_date": "1928"
            },
            {
                "occupational_title": "Director",
                "workplace": "Djupdals AB",
                "industry": "Manufacturing",
                "start_date": "1928"
            }
        ]
    }
}