{
    "original": "LUNDGREN, Elis Gustaf Filip, Bankdirektör, Hudiksvall, f Ånge 1/5 82 av handl G L 0 Karin Jonsson, gm Berta Högbom. Studex 01. Anst Sdsv ensk bk sed. 01, vkst dir Hdsv.-kont sed. 21. Ordf barnav.nmdn, led stdsflm, soc.v.nmdn, dräts.kamm o beredningsutsk, fd ordf stadsrev. Styr.led syst.AB i Hdsv, Gävleb 1 barnav.frb, fd styr.led Gävleb l ork.frn, dirig Hdsv sångarfrb, 2. dirig Gävleb l sång-arfrb. RVO. Hobbies: Sång och musik.",
    "translated": "LUNDGREN, Elis Gustaf Filip, Bank Director, Hudiksvall, born in Ånge on May 1, 1882, son of merchant G L 0 Karin Jonsson, married to Berta Högbom. Graduated in 1901. Employed at Södra Sveriges Enskilda Bank since 1901, promoted to Deputy Managing Director of Hudiksvall branch in 1921. Chairman of the Child Welfare Committee, member of the County Film Board, Social Welfare Committee, Finance Committee, and Preparatory Committee, former chairman of the City Audit Board. Board member of Sister AB in Hudiksvall, Gävle County Child Welfare Association, former board member of Gävle County Orchestra Association, conductor for Hudiksvall Singing Association, 2nd conductor for Gävle County Singing Association. Royal Order of Vasa. Hobbies: Singing and music.",
    "structured": {
        "@context": "https://schema.org",
        "@type": "Person",
        "name": "Elis Gustaf Filip Lundgren",
        "birthDate": "1882-05-01",
        "birthPlace": "Ånge, Sweden",
        "description": "Bank Director",
        "memberOf": [
            {
                "@type": "Organization",
                "name": "Södra Sveriges Enskilda Bank",
                "startDate": "1901-01-01",
                "position": "Employee"
            },
            {
                "@type": "Organization",
                "name": "Hudiksvall branch",
                "startDate": "1921-01-01",
                "position": "Deputy Managing Director"
            },
            {
                "@type": "Organization",
                "name": "Child Welfare Committee",
                "position": "Chairman"
            },
            {
                "@type": "Organization",
                "name": "County Film Board",
                "position": "Member"
            },
            {
                "@type": "Organization",
                "name": "Social Welfare Committee",
                "position": "Member"
            },
            {
                "@type": "Organization",
                "name": "Finance Committee",
                "position": "Member"
            },
            {
                "@type": "Organization",
                "name": "Preparatory Committee",
                "position": "Member"
            },
            {
                "@type": "Organization",
                "name": "City Audit Board",
                "position": "Former Chairman"
            },
            {
                "@type": "Organization",
                "name": "Sister AB",
                "position": "Board member"
            },
            {
                "@type": "Organization",
                "name": "Gävle County Child Welfare Association",
                "position": "Board member"
            },
            {
                "@type": "Organization",
                "name": "Gävle County Orchestra Association",
                "position": "Former board member"
            },
            {
                "@type": "Organization",
                "name": "Hudiksvall Singing Association",
                "position": "Conductor"
            },
            {
                "@type": "Organization",
                "name": "Gävle County Singing Association",
                "position": "2nd conductor"
            }
        ],
        "spouse": {
            "@type": "Person",
            "name": "Berta Högbom"
        },
        "parents": [
            {
                "@type": "Person",
                "name": "G L 0 Karin Jonsson",
                "occupation": "Merchant"
            }
        ],
        "children": [],
        "awards": [
            {
                "@type": "Order",
                "name": "Royal Order of Vasa"
            }
        ],
        "hasOccupation": {
            "@type": "Role",
            "name": "Bank Director"
        },
        "about": "Hobbies include singing and music"
    },
    "occupations": {
        "career": [
            {
                "occupational_title": "Bank Director",
                "workplace": "Södra Sveriges Enskilda Bank",
                "industry": "Banking",
                "start_date": "1901"
            },
            {
                "occupational_title": "Deputy Managing Director",
                "workplace": "Hudiksvall branch",
                "industry": "Banking",
                "start_date": "1921"
            }
        ]
    }
}