{
    "original": "OTTMAR, Harry Oskar Ludvig, Kamrer, Oskarström, f Kristianstad 27/12 01 av ma-skinmäst A O Andersson o Lydia Jansson, gm Blenda Malmlöf. Studex 21, Schartaus 22, Possehlstip f Tyskl.stud 38. Anst Larsson &amp; Pehrsson AB Krst 23, AB Skånska Yllefabr 24, Hvilans Mek Verkst AB 25—28, Skand Jute-Spinneri- &amp; Väfveri AB (Oskarströms Lin-nefabr) sed. 28, kamr där. Rev.suppl Slätt-åkra s :n, kyrkoflm. Rev Sv Jutefabr Centr.-kont Halmstad, ordf Oskarströms tjm.klb o orkesterfrn, sekr ds högerfrn, styr.led ds körsällsk, led Hall hushålln.sällsk. Resor: Tyskl 38. Av trycket: Ref av reseberätt i Sv Tidskr f Textilind o Mercuribladet. Hobbies: Fiske, musik.",
    "translated": "OTTMAR, Harry Oskar Ludvig, Treasurer, Oskarström, born in Kristianstad on December 27, 1901, to furrier A O Andersson and Lydia Jansson, married to Blenda Malmlöf. Studied at Studex until 1921, Schartaus until 1922, and received a scholarship for German studies in 1938. Employed at Larsson & Pehrsson AB in Kristianstad from 1923, AB Skånska Yllefabr in 1924, Hvilans Mek Verkst AB from 1925 to 1928, and Skand Jute-Spinneri- & Väfveri AB (Oskarströms Lin-nefabr) since 1928, where he serves as a treasurer. Additionally, he is a supervisor for Slätt-åkra parish, a church official. He is also a board member for the Swedish Jute Factory Central Office in Halmstad. He is the chairman of the Oskarström Employee Club and the local orchestra, as well as the secretary for the right-wing party. He is a member of the board for the local choir society and the Hall household society. He has traveled to Germany in 1938. Published works include a travel report in the Swedish Journal of Textile Industry and Mercuri newsletter. Hobbies: Fishing, music.",
    "structured": {
        "name": "Harry Oskar Ludvig Ottmar",
        "jobTitle": "Treasurer",
        "birth": {
            "date": "1901-12-27",
            "place": "Kristianstad"
        },
        "parents": [
            {
                "name": "A O Andersson",
                "jobTitle": "Furrier"
            },
            {
                "name": "Lydia Jansson"
            }
        ],
        "spouse": "Blenda Malmlöf",
        "education": [
            {
                "institution": "Studex",
                "endDate": "1921"
            },
            {
                "institution": "Schartaus",
                "endDate": "1922"
            },
            {
                "institution": "Possehlstip",
                "description": "German Studies",
                "endDate": "1938"
            }
        ],
        "employmentHistory": [
            {
                "employer": "Larsson & Pehrsson AB",
                "startDate": "1923",
                "endDate": "1924",
                "location": "Kristianstad"
            },
            {
                "employer": "AB Skånska Yllefabr",
                "startDate": "1924",
                "endDate": "1925",
                "location": "Kristianstad"
            },
            {
                "employer": "Hvilans Mek Verkst AB",
                "startDate": "1925",
                "endDate": "1928"
            },
            {
                "employer": "Skand Jute-Spinneri & Väfveri AB",
                "startDate": "1928",
                "description": "Oskarströms Lin-nefabr",
                "title": "Treasurer"
            }
        ],
        "otherOccupations": [
            {
                "employer": "Slätt-åkra parish",
                "description": "Supervisor"
            },
            {
                "employer": "Sv Jutefabr Centr.-kont Halmstad",
                "description": "Board member"
            },
            {
                "employer": "Oskarströms tjm.klb",
                "description": "Chairman"
            },
            {
                "employer": "Local orchestra",
                "description": "Chairman"
            },
            {
                "employer": "right-wing party",
                "description": "Secretary"
            },
            {
                "employer": "ds körsällsk",
                "description": "Board member"
            },
            {
                "employer": "Hall hushålln.sällsk",
                "description": "Board member"
            }
        ],
        "travelHistory": [
            {
                "destination": "Germany",
                "date": "1938"
            }
        ],
        "publications": [
            "Ref av reseberätt i Sv Tidskr f Textilind",
            "Mercuribladet"
        ],
        "hobbies": [
            "Fishing",
            "Music"
        ]
    },
    "occupations": {
        "career": [
            {
                "occupational_title": "Treasurer",
                "workplace": "Skand Jute-Spinneri- & Väfveri AB",
                "industry": "Textiles",
                "start_date": "1928"
            },
            {
                "occupational_title": "Supervisor",
                "workplace": "Slätt-åkra parish",
                "industry": "Church",
                "start_date": "N/A"
            },
            {
                "occupational_title": "Board Member",
                "workplace": "Swedish Jute Factory Central Office",
                "industry": "Textiles",
                "start_date": "N/A"
            },
            {
                "occupational_title": "Chairman",
                "workplace": "Oskarström Employee Club",
                "industry": "N/A",
                "start_date": "N/A"
            },
            {
                "occupational_title": "Chairman",
                "workplace": "Local orchestra",
                "industry": "Music",
                "start_date": "N/A"
            },
            {
                "occupational_title": "Secretary",
                "workplace": "Right-wing party",
                "industry": "Politics",
                "start_date": "N/A"
            },
            {
                "occupational_title": "Board Member",
                "workplace": "Local choir society",
                "industry": "Music",
                "start_date": "N/A"
            },
            {
                "occupational_title": "Board Member",
                "workplace": "Hall household society",
                "industry": "N/A",
                "start_date": "N/A"
            }
        ]
    }
}