{
    "original": "KJELLMAN, Walter, överingenjör, Stockholm, f Hälsingborg 29/11 05 av disp W K o Asta Larsson, gm Ruth Lindeman. KTH 28, spec.stud i Erdbaumech v Techn Hoohsch Wien 31—32. Ing v Obras Publicas, Malaga, 30, AB vat.b.byrån 30—36 (bl a v vat.kr.vk i Ryssl), 1:e byråing V o V-styr 36—43. övering o chef f Statens gentekniska inst sed. 44. Geotekn utredn åt många statl o komm myndigh, industrier mfl. FI geotekn o mil patent. Av trycket: Jordarters deformationsegensk (Tekn Tidsk 36), Säkerhetsprobl ur teor o princ synp (IVA handl 40), Hållfasthetsbestämn direkt i marken (IVA handl 43) mfl. 1. pris Polhemspristävl 35, IVA pristävl om utredn av Säkerhetsprobl 39. Hobbies: Tennis, segling.",
    "translated": "Kjellman, Walter, chief engineer, Stockholm, born in Hälsingborg on November 29, 1905, son of disp[Walter Kristoffer Kjellman] and Asta Larsson, married Ruth Lindeman. Studied at KTH (Royal Institute of Technology) until 1928, with special studies in Earth Construction Engineering at the Technical University of Vienna from 1931 to 1932. Worked as an engineer at Obras Publicas in Malaga in 1930 and at AB vat.b.byrån from 1930 to 1936 (including work as a water engineering consultant in Russia). Became a senior engineer at V and V-styr from 1936 to 1943. Appointed chief engineer and director of the State Genetic Engineering Institute in 1944. Conducted geological and technical investigations for various government agencies, municipalities, industries, etc. Holds geological and environmental patents. Published works include \"Deformation properties of soil\" (Tekniska Tidskrift, 1936), \"Security problems from theoretical and practical perspectives\" (Royal Swedish Academy of Engineering Sciences Proceedings, 1940), \"Direct determination of soil strength\" (Royal Swedish Academy of Engineering Sciences Proceedings, 1943), etc. Awarded first prize in the Polhems prize competition in 1935 and participated in the Royal Swedish Academy of Engineering Sciences competition on security issues investigation in 1939. Hobbies: Tennis, sailing.",
    "structured": {
        "@context": "http://schema.org",
        "@type": "Person",
        "name": "Walter Kjellman",
        "birthDate": "1905-11-29",
        "birthPlace": "Hälsingborg, Sweden",
        "description": "Chief Engineer",
        "spouse": {
            "@type": "Person",
            "name": "Ruth Lindeman"
        },
        "parents": [
            {
                "@type": "Person",
                "name": "Walter Kristoffer Kjellman"
            },
            {
                "@type": "Person",
                "name": "Asta Larsson"
            }
        ],
        "education": {
            "@type": "CollegeOrUniversity",
            "name": "Royal Institute of Technology"
        },
        "alumniOf": {
            "@type": "CollegeOrUniversity",
            "name": "Technical University of Vienna"
        },
        "employmentHistory": [
            {
                "@type": "JobPosting",
                "title": "Engineer",
                "startDate": "1930",
                "endDate": "1930",
                "location": "Malaga, Spain",
                "employer": {
                    "@type": "Organization",
                    "name": "Obras Publicas"
                }
            },
            {
                "@type": "JobPosting",
                "title": "Engineer",
                "startDate": "1930",
                "endDate": "1936",
                "employer": {
                    "@type": "Organization",
                    "name": "AB vat.b.byrån"
                }
            },
            {
                "@type": "JobPosting",
                "title": "Senior Engineer",
                "startDate": "1936",
                "endDate": "1943",
                "employer": {
                    "@type": "Organization",
                    "name": "V and V-styr"
                }
            },
            {
                "@type": "JobPosting",
                "title": "Chief Engineer and Director",
                "startDate": "1944",
                "employer": {
                    "@type": "Organization",
                    "name": "State Genetic Engineering Institute"
                }
            }
        ],
        "worksFor": {
            "@type": "Organization",
            "name": "State Genetic Engineering Institute"
        },
        "awards": [
            {
                "@type": "Prize",
                "name": "Polhemspristävl",
                "awardDate": "1935"
            },
            {
                "@type": "Competition",
                "name": "Royal Swedish Academy of Engineering Sciences competition",
                "awardDate": "1939"
            }
        ],
        "memberOf": {
            "@type": "Organization",
            "name": "Royal Swedish Academy of Engineering Sciences"
        },
        "hobbies": [
            "Tennis",
            "Sailing"
        ]
    },
    "occupations": {
        "career": [
            {
                "occupational_title": "Chief Engineer",
                "workplace": "Stockholm",
                "industry": "",
                "start_date": ""
            },
            {
                "occupational_title": "Engineer",
                "workplace": "Obras Publicas",
                "industry": "",
                "start_date": "1930"
            },
            {
                "occupational_title": "Engineer",
                "workplace": "AB vat.b.byrån",
                "industry": "",
                "start_date": "1930"
            },
            {
                "occupational_title": "Water Engineering Consultant",
                "workplace": "AB vat.b.byrån",
                "industry": "Water Engineering",
                "start_date": ""
            },
            {
                "occupational_title": "Senior Engineer",
                "workplace": "V and V-styr",
                "industry": "",
                "start_date": "1936"
            },
            {
                "occupational_title": "Chief Engineer and Director",
                "workplace": "State Genetic Engineering Institute",
                "industry": "Genetic Engineering",
                "start_date": "1944"
            }
        ]
    }
}