{
    "original": "ODEJLBEBG, Axel Samuel Wilhelm, Civilingenjör, Djursholm, f Gustavsb, Sthlms l, 16/4 73 av bruksäg W O o Hilma Godenius, gm Maud Beavis. Ex KTH (kem tekn) 95. Ing v Gustavsb porsl.fabr 95, vkst dir o styr.ordf AB Gustavsb fabr intressenter 24—37, led kommun.flm 19, ordf Värmdö skeppslags väg-hålln.distr 21—37, styr.led Sv väginst 23—34, KAK 25—36, Sthlm l S vägdistr 36—37, Sv mässan, utst i S:t Petersb 08, Malmö 14, Paris 25, New York 27, Sthlm 30, London 31, Paris 37, styr.led Sv slöjdfrn 27—38, hed.led 38, styr.led Sv ind.frb 31—38, i Sv kem ind.kont :s styr o arb.utsk 29—38. Resor: USA 08 o 27. Av trycket: Gustavsb ett ind- o jordbr.föret (Sv ind.frb 17), art i keram forsk, konstind, ind. o vägfråg i in- o utl facktidskr, i föredr. LIVA, LLA, Hon Member of The British Ce-ramic Soc o The Amer Ceramic Soc, dir.led Sthlmförorternas regionsplanefrb. KVO2kl, RNO, RFrHL, RRS :tAO3kl, KAK ftjGM, Clar v RosenSM. Hobby: Foto.",
    "translated": "ODEJLBEBG, Axel Samuel Wilhelm, Civil Engineer, Djursholm, son of Gustavsb, Stockholm County, born on April 16th, 1873, to mill owner W O and Hilma Godenius, married to Maud Beavis. Former student at the Royal Institute of Technology (chemical engineering) in 1895. Employed at Gustavsberg porcelain factory in 1895, promoted to deputy director and member of the board of AB Gustavsberg factory shareholders from 1924 to 1937. Served as a member of the local council from 1919, chairman of the Värmdö ship district road maintenance district from 1921 to 1937, board member of the Swedish Road Institute from 1923 to 1934, member of the Royal Automobile Club from 1925 to 1936, board member of the Stockholm County South Road District from 1936 to 1937. Exhibited at the Swedish Exhibition in St. Petersburg in 1908, Malmö in 1914, Paris in 1925, New York in 1927, Stockholm in 1930, London in 1931, and Paris in 1937. Member of the board of the Swedish Handicraft Association from 1927 to 1938, honorary member from 1938, board member of the Swedish Industrial Federation from 1931 to 1938, on the board and working committee of the Swedish Chemical Industry Association. Travelled to the USA in 1908 and 1927. Published articles in ceramics research, industrial and road issues in national and international trade journals, and gave lectures at various conferences. Honorary Member of The British Ceramic Society and The American Ceramic Society, board member of the Stockholm Suburbs Regional Planning Association. Knight of the Royal Order of Vasa, Officer of the Royal Order of the North Star, Knight of the Order of the Polar Star, Knight of the Order of the Sword, Member of the Royal Academy of Engineering Sciences, Member of the Royal Swedish Academy of Letters, History and Antiquities. Hobby: Photography.",
    "structured": {
        "@context": "https://schema.org",
        "@type": "Person",
        "name": "Axel Samuel Wilhelm ODEJLBEBG",
        "birthDate": "1873-04-16",
        "jobTitle": "Civil Engineer",
        "address": {
            "@type": "PostalAddress",
            "addressLocality": "Djursholm",
            "addressRegion": "Stockholm County"
        },
        "parents": [
            {
                "@type": "Person",
                "name": "W O ODEJLBEBG",
                "jobTitle": "Mill owner"
            },
            {
                "@type": "Person",
                "name": "Hilma Godenius"
            }
        ],
        "spouse": {
            "@type": "Person",
            "name": "Maud Beavis"
        },
        "education": {
            "@type": "EducationalOccupationalCredential",
            "credentialCategory": "chemical engineering",
            "educationalLevel": "Bachelor's degree",
            "alumniOf": "Royal Institute of Technology",
            "startDate": "1895"
        },
        "employmentHistory": [
            {
                "@type": "OrganizationRole",
                "startDate": "1895",
                "endDate": "1937",
                "roleName": "Deputy Director",
                "organization": {
                    "@type": "Organization",
                    "name": "Gustavsberg porcelain factory"
                }
            },
            {
                "@type": "OrganizationRole",
                "startDate": "1924",
                "endDate": "1937",
                "roleName": "Member of the board",
                "organization": {
                    "@type": "Organization",
                    "name": "AB Gustavsberg factory shareholders"
                }
            }
        ],
        "memberships": [
            {
                "@type": "Organization",
                "name": "Local council"
            },
            {
                "@type": "Organization",
                "name": "Värmdö ship district road maintenance district",
                "startDate": "1921",
                "endDate": "1937"
            },
            {
                "@type": "Organization",
                "name": "Swedish Road Institute",
                "startDate": "1923",
                "endDate": "1934"
            },
            {
                "@type": "Organization",
                "name": "Royal Automobile Club",
                "startDate": "1925",
                "endDate": "1936"
            },
            {
                "@type": "Organization",
                "name": "Stockholm County South Road District",
                "startDate": "1936",
                "endDate": "1937"
            },
            {
                "@type": "Organization",
                "name": "Swedish Handicraft Association",
                "startDate": "1927",
                "endDate": "1938"
            },
            {
                "@type": "Organization",
                "name": "Swedish Industrial Federation",
                "startDate": "1931",
                "endDate": "1938"
            },
            {
                "@type": "Organization",
                "name": "Swedish Chemical Industry Association",
                "startDate": "1929",
                "endDate": "1938",
                "roleName": "Board member"
            },
            {
                "@type": "Organization",
                "name": "Swedish Chemical Industry Association",
                "roleName": "Board and working committee member"
            }
        ],
        "exhibitions": [
            {
                "@type": "ExhibitionEvent",
                "name": "Swedish Exhibition",
                "location": "St. Petersburg",
                "startDate": "1908"
            },
            {
                "@type": "ExhibitionEvent",
                "name": "Malmö Exhibition",
                "location": "Malmö",
                "startDate": "1914"
            },
            {
                "@type": "ExhibitionEvent",
                "name": "Paris Exhibition",
                "location": "Paris",
                "startDate": "1925"
            },
            {
                "@type": "ExhibitionEvent",
                "name": "New York Exhibition",
                "location": "New York",
                "startDate": "1927"
            },
            {
                "@type": "ExhibitionEvent",
                "name": "Stockholm Exhibition",
                "location": "Stockholm",
                "startDate": "1930"
            },
            {
                "@type": "ExhibitionEvent",
                "name": "London Exhibition",
                "location": "London",
                "startDate": "1931"
            },
            {
                "@type": "ExhibitionEvent",
                "name": "Paris Exhibition",
                "location": "Paris",
                "startDate": "1937"
            }
        ],
        "honors": [
            {
                "@type": "Order",
                "name": "Knight of the Royal Order of Vasa",
                "awardDate": "unknown"
            },
            {
                "@type": "Order",
                "name": "Officer of the Royal Order of the North Star",
                "awardDate": "unknown"
            },
            {
                "@type": "Order",
                "name": "Knight of the Order of the Polar Star",
                "awardDate": "unknown"
            },
            {
                "@type": "Order",
                "name": "Knight of the Order of the Sword",
                "awardDate": "unknown"
            },
            {
                "@type": "Organization",
                "name": "Royal Academy of Engineering Sciences"
            },
            {
                "@type": "Organization",
                "name": "Royal Swedish Academy of Letters, History and Antiquities"
            },
            {
                "@type": "Organization",
                "name": "The British Ceramic Society",
                "honorificSuffix": "Honorary Member"
            },
            {
                "@type": "Organization",
                "name": "The American Ceramic Society",
                "honorificSuffix": "Honorary Member"
            }
        ],
        "hobbies": [
            "Photography"
        ]
    },
    "occupations": {
        "career": [
            {
                "occupational_title": "Civil Engineer",
                "workplace": "Gustavsberg porcelain factory",
                "industry": "Ceramics",
                "start_date": "1895"
            },
            {
                "occupational_title": "Deputy Director and Board Member",
                "workplace": "AB Gustavsberg factory shareholders",
                "industry": "Ceramics",
                "start_date": "1924"
            },
            {
                "occupational_title": "Member of the Local Council",
                "workplace": "N/A",
                "industry": "Local Government",
                "start_date": "1919"
            },
            {
                "occupational_title": "Chairman",
                "workplace": "Värmdö ship district road maintenance district",
                "industry": "Road Infrastructure",
                "start_date": "1921"
            },
            {
                "occupational_title": "Board Member",
                "workplace": "Swedish Road Institute",
                "industry": "Road Infrastructure",
                "start_date": "1923"
            },
            {
                "occupational_title": "Member",
                "workplace": "Royal Automobile Club",
                "industry": "Automotive",
                "start_date": "1925"
            },
            {
                "occupational_title": "Board Member",
                "workplace": "Stockholm County South Road District",
                "industry": "Road Infrastructure",
                "start_date": "1936"
            },
            {
                "occupational_title": "Board Member",
                "workplace": "Swedish Handicraft Association",
                "industry": "Handicrafts",
                "start_date": "1927"
            },
            {
                "occupational_title": "Honorary Member",
                "workplace": "Swedish Handicraft Association",
                "industry": "Handicrafts",
                "start_date": "1938"
            },
            {
                "occupational_title": "Board Member",
                "workplace": "Swedish Industrial Federation",
                "industry": "Industry",
                "start_date": "1931"
            },
            {
                "occupational_title": "Board and Working Committee Member",
                "workplace": "Swedish Chemical Industry Association",
                "industry": "Chemical Industry",
                "start_date": "1929"
            }
        ]
    }
}