{
    "original": "BJÖRKMAN, Erik Ivan Andreas, överstelöjtnant, Byggnadschef, Karlstad, f Gbg 7/8 81 av civ.ing I M B o Emilia Elieson, gm Olga Knutzén. Studex Kalmar 99, civingex KTH (V o V) 04. Löjtn VVK 11, kapt 18, major 32, öv.löjtn 42. Bitr ing Karlst hamnbyggn 04—05, arb.ch där 06—08, ing v Vattenb.byrån Sthlm 08—10, ch f vattenvkt samt hämning Karlst 10—12, ch f gasvkt där fr 10, stadsing 12—17, Karlst stds byggn.ch sed. 18. Såsom konsult ing uppgj förslag t broar, kajer o husbyggn, vattenledn nim 10—43, kontr Karlst Mek Verkst :s nybygg 13—15, AB Mölnbacka-Trysils pappersbr.bygg 13—14, byggn.tekn rådg o kontr Uddeholms AB :s nybygg f elektrokem fabr, sulfit- o sulfatfabr samt kajbygg Skoghall 15—17. Styr.led i Karlstads sparbk. Led byggn.nmdn fr 15, ordf i kommiss f Värml.utställn Karlst 29, Styr.led Sv Kommunal tekn frn 29—38. Led Sv Tekn.frn o Värml Ing.frn. Resor: Tyskl, Frankr, Schweiz, Ital, Belg. RNO, RVO; Rotary, KAK, KSAK.",
    "translated": "BJÖRKMAN, Erik Ivan Andreas, Lieutenant Colonel, Construction Manager, Karlstad, b. Gothenburg 7/8 1881, son of Civil Engineer I.M.B and Emilia Elieson, m. Olga Knutzén. Graduated from Kalmar in 1899, Civil Engineer degree from KTH (Royal Institute of Technology) in 1904. Second Lieutenant in the Royal Värmland Regiment in 1911, Captain in 1918, Major in 1932, Lieutenant Colonel in 1942. Assistant Engineer at Karlstad Port Construction 1904-1905, worked there as an engineer from 1906 to 1908, engineer at the Swedish Water Bureau in Stockholm 1908-1910, Chief of Water Works and Damming in Karlstad 1910-1912, Chief of Gas Works from 1910, City Engineer from 1912 to 1917, and City Building Chief in Karlstad from 1918. Consulted on bridge, pier, and building construction, water pipelines from 1910 to 1943, managed contracts for Karlstad Mechanical Workshop's new buildings from 1913 to 1915, AB Mölnbacka-Trysils paper mill construction from 1913 to 1914, and provided building technical advice and contracts for Uddeholm AB's new electrochemical factory, sulfite and sulfate factories, and quay construction in Skoghall from 1915 to 1917. Board member of Karlstad Savings Bank. Member of the Building Committee from 1915, Chairman of the commission for Värmland Exhibition in Karlstad in 1929, Board member of the Swedish Municipal Engineering Association from 1929 to 1938. Member of the Swedish Technical Association and Värmland Engineering Association. Traveled to Germany, France, Switzerland, Italy, and Belgium. Awarded with the Royal Order of the North Star (RNO), Royal Order of Vasa (RVO), Member of Rotary International, the Royal Automobile Club, and the Swedish Aeronautical Society.",
    "structured": {
        "@context": "https://schema.org/",
        "@type": "Person",
        "name": "Erik Ivan Andreas Björkman",
        "birthDate": "1881-08-07",
        "birthPlace": "Gothenburg",
        "deathDate": null,
        "nationality": "Swedish",
        "jobTitle": [
            "Lieutenant Colonel",
            "Construction Manager"
        ],
        "memberOf": [
            {
                "@type": "Organization",
                "name": "Rotary International"
            },
            {
                "@type": "Organization",
                "name": "Royal Automobile Club"
            },
            {
                "@type": "Organization",
                "name": "Swedish Aeronautical Society"
            }
        ],
        "spouse": {
            "@type": "Person",
            "name": "Olga Knutzén"
        },
        "parents": [
            {
                "@type": "Person",
                "name": "I.M.B. Björkman",
                "jobTitle": "Civil Engineer"
            },
            {
                "@type": "Person",
                "name": "Emilia Elieson"
            }
        ],
        "education": [
            {
                "@type": "EducationalOrganization",
                "name": "Kalmar",
                "endDate": "1899"
            },
            {
                "@type": "EducationalOrganization",
                "name": "Royal Institute of Technology",
                "endDate": "1904"
            }
        ],
        "work": [
            {
                "@type": "OrganizationRole",
                "organization": {
                    "@type": "Organization",
                    "name": "Karlstad Port Construction"
                },
                "startDate": "1904",
                "endDate": "1905",
                "roleName": "Assistant Engineer"
            },
            {
                "@type": "OrganizationRole",
                "organization": {
                    "@type": "Organization",
                    "name": "Karlstad Port Construction"
                },
                "startDate": "1906",
                "endDate": "1908",
                "roleName": "Engineer"
            },
            {
                "@type": "OrganizationRole",
                "organization": {
                    "@type": "Organization",
                    "name": "Swedish Water Bureau"
                },
                "startDate": "1908",
                "endDate": "1910",
                "roleName": "Engineer"
            },
            {
                "@type": "OrganizationRole",
                "organization": {
                    "@type": "Organization",
                    "name": "Karlstad"
                },
                "startDate": "1910",
                "endDate": "1912",
                "roleName": "Chief of Water Works and Damming"
            },
            {
                "@type": "OrganizationRole",
                "organization": {
                    "@type": "Organization",
                    "name": "Karlstad"
                },
                "startDate": "1910",
                "endDate": null,
                "roleName": "Chief of Gas Works"
            },
            {
                "@type": "OrganizationRole",
                "organization": {
                    "@type": "Organization",
                    "name": "Karlstad"
                },
                "startDate": "1912",
                "endDate": "1917",
                "roleName": "City Engineer"
            },
            {
                "@type": "OrganizationRole",
                "organization": {
                    "@type": "Organization",
                    "name": "Karlstad"
                },
                "startDate": "1918",
                "endDate": null,
                "roleName": "City Building Chief"
            }
        ],
        "sameAs": [
            "https://en.wikipedia.org/wiki/Erik_Björkman"
        ]
    },
    "occupations": {
        "career": [
            {
                "occupational_title": "Assistant Engineer",
                "workplace": "Karlstad Port Construction",
                "industry": "Civil Engineering",
                "start_date": "1904-1905"
            },
            {
                "occupational_title": "Engineer",
                "workplace": "Karlstad Port Construction",
                "industry": "Civil Engineering",
                "start_date": "1906-1908"
            },
            {
                "occupational_title": "Engineer",
                "workplace": "Swedish Water Bureau",
                "industry": "Civil Engineering",
                "start_date": "1908-1910"
            },
            {
                "occupational_title": "Chief of Water Works and Damming",
                "workplace": "Karlstad",
                "industry": "Civil Engineering",
                "start_date": "1910-1912"
            },
            {
                "occupational_title": "Chief of Gas Works",
                "workplace": "Karlstad",
                "industry": "Utilities",
                "start_date": "1910"
            },
            {
                "occupational_title": "City Engineer",
                "workplace": "Karlstad",
                "industry": "Civil Engineering",
                "start_date": "1912-1917"
            },
            {
                "occupational_title": "City Building Chief",
                "workplace": "Karlstad",
                "industry": "Civil Engineering",
                "start_date": "1918"
            },
            {
                "occupational_title": "Consultant Engineer",
                "workplace": "Various",
                "industry": "Civil Engineering",
                "start_date": "1910-1943"
            },
            {
                "occupational_title": "Contract Manager",
                "workplace": "Karlstad Mechanical Workshop",
                "industry": "Construction",
                "start_date": "1913-1915"
            },
            {
                "occupational_title": "Contract Manager",
                "workplace": "AB Mölnbacka-Trysils paper mill",
                "industry": "Paper Manufacturing",
                "start_date": "1913-1914"
            },
            {
                "occupational_title": "Building Technical Advisor & Contract Manager",
                "workplace": "Uddeholm AB",
                "industry": "Electrochemical & Paper Manufacturing",
                "start_date": "1915-1917"
            }
        ]
    }
}