{
    "original": "KÖRDES, Einar Reinhold, Direktör, Smedslätten, f Filipst 28/3 03 av hdsskriv F Svensson o Eva K, gm Stina Pehrsson. Studex Karlst 22, jur kand Sthlm 27, DHS 28. Tingstjg Karlst 28—31, aman hdlsdep 31—37, sekr clear.nmdn 34—37, stat reservförrådsnmd 37, Gbgs hdlskamm sed. 38, dir stat hdlskommisa 39—43, vkst dir Sv grossistförbundet sed. 43. Sekr Gbgs handels- o sjöfartsnämnd sed. 38’. ordf Gbgs krist.styr 39, styr.led Gbgs HHS o Holmquist hdlsinst sed. 39. Resor: Tyskl 22, 23, 25, 36—38. Engl 23, 25, Frankr 25, 35, Ital 36, 37. RNO, OffltKrO, RBKrO, RFinl-VROlkl.",
    "translated": "KÖRDES, Einar Reinhold, Director, Smedslätten, born in Filipst on March 28, 1903, son of civil servant F Svensson and Eva K, married to Stina Pehrsson. He graduated from Karlstad in 1922, received a law degree from Stockholm in 1927, and a Diploma in Higher Studies in 1928. He served as a judicial clerk in Karlstad from 1928 to 1931, assistant at the Ministry of Commerce from 1931 to 1937, secretary of the Clearing House Association from 1934 to 1937, member of the State Reserve Stock Committee in 1937, member of the Gothenburg Chamber of Commerce since 1938, director of the State Commerce Commission from 1939 to 1943, and director of the Swedish Wholesale Association since 1943. He was secretary of the Gothenburg Trade and Shipping Board since 1938, chairman of the Gothenburg Christian Board since 1939, and board member of the Gothenburg School of Economics and Holmquist Commerce Institute since 1939. He traveled to Germany in 1922, 1923, 1925, and 1936-1938, England in 1923 and 1925, France in 1925 and 1935, and Italy in 1936 and 1937. He was awarded the Royal Norwegian Order, Order of Officer of the Finnish Lion, and the Order of the Cross of Liberty.",
    "structured": {
        "@context": "https://schema.org",
        "@type": "Person",
        "name": "Einar Reinhold Kördes",
        "birthDate": "1903-03-28",
        "birthPlace": "Filipst",
        "father": {
            "@type": "Person",
            "name": "F Svensson"
        },
        "mother": {
            "@type": "Person",
            "name": "Eva K"
        },
        "spouse": {
            "@type": "Person",
            "name": "Stina Pehrsson"
        },
        "education": [
            {
                "@type": "EducationalOccupationalCredential",
                "name": "Graduated from Karlstad",
                "endDate": "1922"
            },
            {
                "@type": "EducationalOccupationalCredential",
                "name": "Received law degree from Stockholm",
                "endDate": "1927"
            },
            {
                "@type": "EducationalOccupationalCredential",
                "name": "Diploma in Higher Studies",
                "endDate": "1928"
            }
        ],
        "employmentHistory": [
            {
                "@type": "GovernmentOrganization",
                "name": "Karlstad Judicial Clerk",
                "startDate": "1928",
                "endDate": "1931"
            },
            {
                "@type": "GovernmentOrganization",
                "name": "Assistant at the Ministry of Commerce",
                "startDate": "1931",
                "endDate": "1937"
            },
            {
                "@type": "Organization",
                "name": "Clearing House Association",
                "roleName": "Secretary",
                "startDate": "1934",
                "endDate": "1937"
            },
            {
                "@type": "GovernmentOrganization",
                "name": "State Reserve Stock Committee",
                "startDate": "1937"
            },
            {
                "@type": "Organization",
                "name": "Gothenburg Chamber of Commerce",
                "startDate": "1938"
            },
            {
                "@type": "GovernmentOrganization",
                "name": "State Commerce Commission",
                "roleName": "Director",
                "startDate": "1939",
                "endDate": "1943"
            },
            {
                "@type": "Organization",
                "name": "Swedish Wholesale Association",
                "roleName": "Director",
                "startDate": "1943"
            },
            {
                "@type": "Organization",
                "name": "Gothenburg Trade and Shipping Board",
                "roleName": "Secretary",
                "startDate": "1938"
            },
            {
                "@type": "Organization",
                "name": "Gothenburg Christian Board",
                "roleName": "Chairman",
                "startDate": "1939"
            },
            {
                "@type": "Organization",
                "name": "Gothenburg School of Economics and Holmquist Commerce Institute",
                "roleName": "Board Member",
                "startDate": "1939"
            }
        ],
        "travelHistory": [
            {
                "@type": "Country",
                "name": "Germany"
            },
            {
                "@type": "Country",
                "name": "England"
            },
            {
                "@type": "Country",
                "name": "France"
            },
            {
                "@type": "Country",
                "name": "Italy"
            }
        ],
        "awards": [
            {
                "@type": "Order",
                "name": "Royal Norwegian Order"
            },
            {
                "@type": "Order",
                "name": "Order of Officer of the Finnish Lion"
            },
            {
                "@type": "Order",
                "name": "Order of the Cross of Liberty"
            }
        ]
    },
    "occupations": {
        "career": [
            {
                "occupational_title": "Judicial Clerk",
                "workplace": "Karlstad",
                "industry": "Judiciary",
                "start_date": "1928"
            },
            {
                "occupational_title": "Assistant",
                "workplace": "Ministry of Commerce",
                "industry": "Government",
                "start_date": "1931"
            },
            {
                "occupational_title": "Secretary",
                "workplace": "Clearing House Association",
                "industry": "Finance",
                "start_date": "1934"
            },
            {
                "occupational_title": "Member",
                "workplace": "State Reserve Stock Committee",
                "industry": "Government",
                "start_date": "1937"
            },
            {
                "occupational_title": "Member",
                "workplace": "Gothenburg Chamber of Commerce",
                "industry": "Commerce",
                "start_date": "1938"
            },
            {
                "occupational_title": "Director",
                "workplace": "State Commerce Commission",
                "industry": "Government",
                "start_date": "1939"
            },
            {
                "occupational_title": "Director",
                "workplace": "Swedish Wholesale Association",
                "industry": "Commerce",
                "start_date": "1943"
            },
            {
                "occupational_title": "Secretary",
                "workplace": "Gothenburg Trade and Shipping Board",
                "industry": "Commerce",
                "start_date": "1938"
            }
        ]
    }
}