{
    "original": "ESKHL.SON, Sven Merus, Disponent, Landskrona, f Marieholm, Malmöh l, 21/3 92 av fabr Anders E o Anna Svensson, gm Margit Granzow. Realex 08, Hbg högre hldsinst 10, resoffex 15, kapt flygets res. Anst: Ass förs.-avd AB Enoch Thulins Aeroplanfabrik 17, förs.ch AB Thulinverken 19, disp där sed. 23. Stdsflm sed. 32, ordf trafiknämnden, v. ordf dräts.kamm o brandstyr, led socialvårds-komm, landst revisor i länslas Lkrona, ordf stdflm högergrupp. Styr.led AB Thulinverken o Lkrona fastigh AB, v. ordf Lkrona högerfrn o Hbg flygklubb; styr.led KAK skåneavd, ordf dess tekn komm; styr.led Lkrona hdlsfrn o luftförsvarsfrn.",
    "translated": "ESKHL.SON, Sven Merus, Manager, Landskrona, born in Marieholm, Malmöhus län, on March 21st, 1892, son of factory worker Anders E. and Anna Svensson. Married to Margit Granzow. Completed elementary school in 1908, higher commercial school in Helsingborg in 1910, Officer's Training School in 1915, Captain in the Aviation Corps. Employment history: Assistant in the Insurance Department of AB Enoch Thulin's Aeroplane Factory in 1917, insurance manager at AB Thulinverken in 1919, and manager there since 1923. Member of the City Council since 1932, Chairman of the Traffic Committee, Vice Chairman of the Finance Committee and Fire Brigade Board, member of the Social Welfare Committee and County Auditor in the County Council of Landskrona, Chairman of the City Council's conservative group. Board member of AB Thulinverken and Landskrona Fastighets AB, Vice Chairman of the Landskrona Conservative Association and Helsingborg Flying Club; Board member of the Royal Automobile Club, Skåne District Technology Committee Chairman; Board member of the Landskrona Commerce Association and Air Defense Association.",
    "structured": {
        "@context": "https://schema.org",
        "@type": "Person",
        "name": "Sven Merus Eskhl.son",
        "jobTitle": "Manager",
        "birthPlace": "Marieholm, Malmöhus län",
        "birthDate": "1892-03-21",
        "familyName": "Eskhl.son",
        "givenName": "Sven Merus",
        "parent": [
            {
                "@type": "Person",
                "name": "Anders E.",
                "jobTitle": "Factory Worker",
                "givenName": "Anders",
                "familyName": "E."
            },
            {
                "@type": "Person",
                "name": "Anna Svensson",
                "givenName": "Anna",
                "familyName": "Svensson"
            }
        ],
        "spouse": {
            "@type": "Person",
            "name": "Margit Granzow"
        },
        "educationalCredentialAwarded": [
            {
                "@type": "EducationalOccupationalCredential",
                "name": "Realex",
                "startDate": "1908"
            },
            {
                "@type": "EducationalOccupationalCredential",
                "name": "Hbg högre hldsinst",
                "startDate": "1910"
            },
            {
                "@type": "EducationalOccupationalCredential",
                "name": "resoffex",
                "startDate": "1915"
            }
        ],
        "worksFor": [
            {
                "@type": "Organization",
                "name": "AB Enoch Thulin's Aeroplane Factory",
                "department": [
                    {
                        "@type": "Organization",
                        "name": "Insurance Department"
                    }
                ],
                "startDate": "1917"
            },
            {
                "@type": "Organization",
                "name": "AB Thulinverken",
                "department": [
                    {
                        "@type": "Organization",
                        "name": "Insurance"
                    }
                ],
                "startDate": "1919"
            }
        ],
        "memberOf": [
            {
                "@type": "Organization",
                "name": "City Council",
                "startDate": "1932"
            },
            {
                "@type": "Organization",
                "name": "Traffic Committee",
                "position": "Chairman"
            },
            {
                "@type": "Organization",
                "name": "Finance Committee",
                "position": "Vice Chairman"
            },
            {
                "@type": "Organization",
                "name": "Fire Brigade Board",
                "position": "Vice Chairman"
            },
            {
                "@type": "Organization",
                "name": "Social Welfare Committee",
                "position": "Member"
            },
            {
                "@type": "Organization",
                "name": "County Council of Landskrona",
                "position": "County Auditor"
            },
            {
                "@type": "Organization",
                "name": "City Council's conservative group",
                "position": "Chairman"
            },
            {
                "@type": "Organization",
                "name": "AB Thulinverken",
                "position": "Board Member"
            },
            {
                "@type": "Organization",
                "name": "Landskrona Fastighets AB",
                "position": "Board Member"
            },
            {
                "@type": "Organization",
                "name": "Landskrona Conservative Association",
                "position": "Vice Chairman"
            },
            {
                "@type": "Organization",
                "name": "Helsingborg Flying Club",
                "position": "Vice Chairman"
            },
            {
                "@type": "Organization",
                "name": "Royal Automobile Club",
                "position": "Board Member"
            },
            {
                "@type": "Organization",
                "name": "Landskrona Commerce Association",
                "position": "Board Member"
            },
            {
                "@type": "Organization",
                "name": "Air Defense Association",
                "position": "Board Member"
            }
        ]
    },
    "occupations": {
        "career": [
            {
                "occupational_title": "Assistant",
                "workplace": "AB Enoch Thulin's Aeroplane Factory",
                "industry": "Aviation",
                "start_date": "1917"
            },
            {
                "occupational_title": "Insurance Manager",
                "workplace": "AB Thulinverken",
                "industry": "Insurance",
                "start_date": "1919"
            },
            {
                "occupational_title": "Manager",
                "workplace": "AB Thulinverken",
                "industry": "Manufacturing",
                "start_date": "1923"
            }
        ]
    }
}