{
    "original": "JOHNSON, Henning, v. Konsul, Karlstad, f Fryksände, Värml, 19/9 91 av lantbr J J o Gertrud Olson, gm Karin Borgström. Hdls-lärov. Bokh Bröd Löfbergs AB 13, kamr 19, kont.ch 24, dir.ass 27, vkst dir 29 samt num även deläg o styr.led. Stdsflm, beredn.utsk, budgetberedn mm. Finsk v.kons. Styr.led riksbkns avd.kont, AB Sv kolonialgrossister, förlagsAB ASK, Värml-Dalsl hdlskamm, V Sv sockerengrosfrn, Värml-Dalsl engrosfrn, ordf Värml.-Dalsl kol.varusekt mm. Frimurare (VIII), ProPstGM.",
    "translated": "JOHNSON, Henning, Honorary Consul, Karlstad, born in Fryksände, Värmland, on September 19, 1891, son of farmer J J and Gertrud Olson, married to Karin Borgström. Commercial education. Accountant at Bröd Löfbergs AB in 1913, assistant cashier in 1919, head of department in 1924, director's assistant in 1927, director in 1929, and also co-owner and board member. Member of various committees, such as the film advisory committee, the budget committee, etc. Finnish honorary consul. Board member of the central bank's department office, AB Sv kolonialgrossister, förlagsAB ASK, Värmland-Dalsland business chamber, Västsvenska sockerengrosförningen, Värmland-Dalsland engrosförningen, chairman of Värmland-Dalsland wholesale trade in groceries, etc. Freemason (VIII), Pro Provincial Grand Master. Note: The abbreviation 'm.' followed by the partner's name indicates that the person married in the year 19xx.",
    "structured": {
        "@context": "https://schema.org",
        "@type": "Person",
        "name": "Henning Johnson",
        "givenName": "Henning",
        "familyName": "Johnson",
        "honorificSuffix": "Honorary Consul",
        "birthDate": "1891-09-19",
        "birthPlace": "Fryksände, Värmland",
        "parent": [
            {
                "@type": "Person",
                "name": "J J",
                "jobTitle": "Farmer"
            },
            {
                "@type": "Person",
                "name": "Gertrud Olson",
                "jobTitle": "Unknown"
            }
        ],
        "spouse": {
            "@type": "Person",
            "name": "Karin Borgström"
        },
        "education": {
            "@type": "EducationalOccupationalCredential",
            "credentialCategory": "Commercial education"
        },
        "memberOf": [
            {
                "@type": "Organization",
                "name": "Bröd Löfbergs AB",
                "jobTitle": "Accountant",
                "startDate": "1913"
            },
            {
                "@type": "Organization",
                "name": "Bröd Löfbergs AB",
                "jobTitle": "Assistant Cashier",
                "startDate": "1919"
            },
            {
                "@type": "Organization",
                "name": "Bröd Löfbergs AB",
                "jobTitle": "Head of Department",
                "startDate": "1924"
            },
            {
                "@type": "Organization",
                "name": "Bröd Löfbergs AB",
                "jobTitle": "Director's Assistant",
                "startDate": "1927"
            },
            {
                "@type": "Organization",
                "name": "Bröd Löfbergs AB",
                "jobTitle": "Director",
                "startDate": "1929"
            },
            {
                "@type": "Organization",
                "name": "AB Sv kolonialgrossister"
            },
            {
                "@type": "Organization",
                "name": "FörlagsAB ASK"
            },
            {
                "@type": "Organization",
                "name": "Värmland-Dalsland business chamber"
            },
            {
                "@type": "Organization",
                "name": "Västsvenska sockerengrosförningen"
            },
            {
                "@type": "Organization",
                "name": "Värmland-Dalsland engrosförningen"
            },
            {
                "@type": "Organization",
                "name": "Värmland-Dalsland wholesale trade in groceries",
                "jobTitle": "Chairman"
            }
        ],
        "relatedTo": [
            {
                "@type": "Organization",
                "name": "Central Bank's department office"
            }
        ],
        "additionalName": [
            "deläg o styr.led",
            "beredn.utsk",
            "budgetberedn mm"
        ],
        "nationality": "Swedish",
        "sameAs": [
            "Frimurare (VIII)",
            "Pro Provincial Grand Master"
        ]
    },
    "occupations": {
        "career": [
            {
                "occupational_title": "Accountant",
                "workplace": "Bröd Löfbergs AB",
                "industry": "Bakery",
                "start_date": "1913"
            },
            {
                "occupational_title": "Assistant Cashier",
                "workplace": "Bröd Löfbergs AB",
                "industry": "Bakery",
                "start_date": "1919"
            },
            {
                "occupational_title": "Head of Department",
                "workplace": "Bröd Löfbergs AB",
                "industry": "Bakery",
                "start_date": "1924"
            },
            {
                "occupational_title": "Director's Assistant",
                "workplace": "Bröd Löfbergs AB",
                "industry": "Bakery",
                "start_date": "1927"
            },
            {
                "occupational_title": "Director",
                "workplace": "Bröd Löfbergs AB",
                "industry": "Bakery",
                "start_date": "1929"
            }
        ]
    }
}