{
    "original": "FURUSKOG, Olof (Olle) Antonius, Direktör, Stockholm, f Borgsjö, V.norrl län, 77, gm Gertrud Bergman. Fhsk. Eg skogs- o sågv.-rör Gustafshamn 09—15, ch o vkst dir Ankarsviks o Myrnäs AB 16—23, grund Sundsvalls träv.AB 23, ch, vkst dir, styr.led o ordf. Styr.led o ordf Ankarsviks o Myrnäs AB samt styr.led Svls virkesmätn.frn 16—23, styr.led o ordf AB Emil Bredenberg sed. 23. Resor i de fi europ länd. Frimurare, Odd Fellow, W6, Tekn frn i Svl mfl. Hobbies: Fiske, skogs- o fjällfärder.",
    "translated": "FURUSKOG, Olof (Olle) Antonius, Director, Stockholm, b. Borgsjö, Västernorrland County, 77, m. Gertrud Bergman. Secondary school education. Former forest and sawmill manager at Gustafshamn 1909-1915, managing and cultivating director of Ankarsviks and Myrnäs AB 1916-1923, founder of Sundsvalls trävaru AB in 1923, chairman, managing director, board member, and chairman of the board of Ankarsviks and Myrnäs AB, as well as board member of Svls virkesmätningsfrn 1916-1923, board member and chairman of AB Emil Bredenberg since 1923. Traveled in several European countries. Freemason, Odd Fellow, W6, member of the Swedish Technical Association. Hobbies: fishing, forest and mountain excursions.",
    "structured": {
        "@context": "https://schema.org",
        "@type": "Person",
        "name": "Olof Antonius Furuskog",
        "givenName": "Olof",
        "additionalName": "Olle",
        "familyName": "Furuskog",
        "jobTitle": "Director",
        "birthPlace": "Borgsjö, Västernorrland County",
        "birthDate": "YYYY-MM-DD",
        "age": "77",
        "spouse": {
            "@type": "Person",
            "name": "Gertrud Bergman"
        },
        "education": "Secondary school education",
        "worksFor": {
            "@type": "Organization",
            "name": "Stockholm"
        },
        "occupation": {
            "@type": "OrganizationRole",
            "startDate": "1909",
            "endDate": "1915",
            "roleName": "Forest and Sawmill Manager",
            "namedPosition": "Gustafshamn"
        },
        "memberOf": [
            {
                "@type": "Organization",
                "name": "Freemasons"
            },
            {
                "@type": "Organization",
                "name": "Odd Fellow"
            },
            {
                "@type": "Organization",
                "name": "W6"
            },
            {
                "@type": "Organization",
                "name": "Swedish Technical Association"
            }
        ],
        "travelledTo": [
            "European countries"
        ],
        "hobbies": [
            "Fishing",
            "Forest and mountain excursions"
        ]
    },
    "occupations": {
        "career": [
            {
                "occupational_title": "Forest and Sawmill Manager",
                "workplace": "Gustafshamn",
                "industry": "Skogs- och sågverksbranschen",
                "start_date": "1909"
            },
            {
                "occupational_title": "Managing and Cultivating Director",
                "workplace": "Ankarsviks och Myrnäs AB",
                "industry": "Skogs- och sågverksbranschen",
                "start_date": "1916"
            },
            {
                "occupational_title": "Founder",
                "workplace": "Sundsvalls trävaru AB",
                "industry": "Trävarubranschen",
                "start_date": "1923"
            },
            {
                "occupational_title": "Chairman, Managing Director, Board member",
                "workplace": "Ankarsviks och Myrnäs AB",
                "industry": "Skogs- och sågverksbranschen",
                "start_date": "1923"
            },
            {
                "occupational_title": "Board member",
                "workplace": "Svls virkesmätningsfrn",
                "industry": "Skogsbranschen",
                "start_date": "1916"
            },
            {
                "occupational_title": "Board member and Chairman",
                "workplace": "AB Emil Bredenberg",
                "industry": "Unknown",
                "start_date": "1923"
            }
        ]
    }
}