{
    "original": "BERGENSTRÅHLE, Karl Ivar Ludvig, Ci-vilingrenjör, Stockholm, f Sala 15/10 96 av magistr.sekr K J H R B o Eva von Knorring, gm Ingegerd Leffler. Studex Upps 16, KTH 17—21, avg.ex där sistn år. Konstr o prov-rumsing v Elektr AB AEG, Sthlm, 21—22, rit v Gen Electric Co, Schenectady, NY, USA, 23 —24, rit v New York Edison Co, New York, USA, 24—25, konsult i elektr frågor v Dept of Techn Education, Ministry of Education, Cairo, Egypt, samt förel v School of Engi-neering, Giza, Egypt, 25—27, patenting v Oscar Grahns Patentbyrå, Sthlm, 27—34, inneh egen patentbyrå under fma Ivar Bergenstråhles Patentbyrå, Sthlm, sed. 34, i kompanjonskap m civ.ing Ivar Lindvall sed. 39. Led Sv Tekn.frn sed. 21 o Sv Patentombudsfrn sed. 37.",
    "translated": "BERGENSTRÅHLE, Karl Ivar Ludvig, Civil engineer, Stockholm, born in Sala on October 15, 1896, to magistrate secretary K J H R B and Eva von Knorring. Studied at Uppsala University until 1916, then at the Royal Institute of Technology from 1917 to 1921, with final exams completed in the latter year. Constructive and testing engineer at Elektr AB AEG, Stockholm, from 1921 to 1922, draughtsman at General Electric Co, Schenectady, NY, USA, from 1923 to 1924, draughtsman at New York Edison Co, New York, USA, from 1924 to 1925. Consultant in electrical matters at the Department of Technical Education, Ministry of Education, Cairo, Egypt, and lecturer at the School of Engineering, Giza, Egypt, from 1925 to 1927. Engaged in patenting at Oscar Grahns Patent Agency, Stockholm, from 1927 to 1934. Owned own patent agency under the name Ivar Bergenstråhle's Patent Agency, Stockholm, since 1934, in partnership with civil engineer Ivar Lindvall since 1939. Member of the Swedish Society of Engineers since 1921 and the Swedish Patent Attorneys Association since 1937.",
    "structured": {
        "@context": "https://schema.org",
        "@type": "Person",
        "name": "Karl Ivar Ludvig Bergenstråhle",
        "birthDate": "1896-10-15",
        "birthPlace": "Sala, Sweden",
        "description": "Civil engineer",
        "memberOf": [
            {
                "@type": "Organization",
                "name": "Swedish Society of Engineers",
                "startDate": "1921"
            },
            {
                "@type": "Organization",
                "name": "Swedish Patent Attorneys Association",
                "startDate": "1937"
            }
        ],
        "spouse": "Ingegerd Leffler",
        "education": [
            {
                "@type": "EducationalOrganization",
                "name": "Uppsala University",
                "attendanceDate": {
                    "@type": "Date",
                    "startDate": "1916",
                    "endDate": "1916"
                }
            },
            {
                "@type": "EducationalOrganization",
                "name": "Royal Institute of Technology",
                "attendanceDate": {
                    "@type": "Date",
                    "startDate": "1917",
                    "endDate": "1921"
                }
            }
        ],
        "work": [
            {
                "@type": "Organization",
                "name": "Elektr AB AEG",
                "position": "Constructive and testing engineer",
                "startDate": "1921",
                "endDate": "1922"
            },
            {
                "@type": "Organization",
                "name": "General Electric Co",
                "position": "Draughtsman",
                "startDate": "1923",
                "endDate": "1924"
            },
            {
                "@type": "Organization",
                "name": "New York Edison Co",
                "position": "Draughtsman",
                "startDate": "1924",
                "endDate": "1925"
            },
            {
                "@type": "Organization",
                "name": "Department of Technical Education, Ministry of Education",
                "position": "Consultant in electrical matters",
                "location": "Cairo, Egypt",
                "startDate": "1925",
                "endDate": "1927"
            },
            {
                "@type": "Organization",
                "name": "School of Engineering, Giza",
                "position": "Lecturer",
                "location": "Giza, Egypt",
                "startDate": "1925",
                "endDate": "1927"
            },
            {
                "@type": "Organization",
                "name": "Oscar Grahns Patent Agency",
                "position": "Engaged in patenting",
                "startDate": "1927",
                "endDate": "1934"
            },
            {
                "@type": "Organization",
                "name": "Ivar Bergenstråhle's Patent Agency",
                "position": "Patent agency owner",
                "startDate": "1934"
            }
        ],
        "colleague": {
            "@type": "Person",
            "name": "Ivar Lindvall",
            "description": "Civil engineer",
            "startDate": "1939"
        }
    },
    "occupations": {
        "career": [
            {
                "occupational_title": "Civil engineer",
                "workplace": "Elektr AB AEG",
                "industry": "Electrical engineering",
                "start_date": "1921-01-01"
            },
            {
                "occupational_title": "Draughtsman",
                "workplace": "General Electric Co",
                "industry": "Electrical engineering",
                "start_date": "1923-01-01"
            },
            {
                "occupational_title": "Draughtsman",
                "workplace": "New York Edison Co",
                "industry": "Electrical engineering",
                "start_date": "1924-01-01"
            },
            {
                "occupational_title": "Consultant in electrical matters",
                "workplace": "Department of Technical Education, Ministry of Education",
                "industry": "Education",
                "start_date": "1925-01-01"
            },
            {
                "occupational_title": "Lecturer",
                "workplace": "School of Engineering, Giza",
                "industry": "Education",
                "start_date": "1925-01-01"
            },
            {
                "occupational_title": "Patenting",
                "workplace": "Oscar Grahns Patent Agency",
                "industry": "Legal services",
                "start_date": "1927-01-01"
            },
            {
                "occupational_title": "Owner of patent agency",
                "workplace": "Ivar Bergenstråhle's Patent Agency",
                "industry": "Legal services",
                "start_date": "1934-01-01"
            }
        ]
    }
}