{
    "original": "LUNDBERG, Åke Melcher Johan, överingenjör, Stockholm, f Sthlm 29/9 04 av öv.löjtn K A L o Signe Ekströmer, gm Allis Blumer. Studex Sthlm 23, KTH (bergsvetensk) 24—29, studieres t Tyskl 25, 31, 33, 39, 41, Engl 32, 33, 39, Schweiz 39, stud v Carnegie Inst of Techn USA 32. Ing v Jernkont :s forskn.inst 29—30, martining v AB Bofors 30—32, ing f valsverk, smedja o pressverk där 33—40, övering o tekn chef h AB Sv Metallvkn, V.ås, 40—42, övering o tekn led h OY Vuoksenniska AB Hfors sed. 42. Av trycket: Om malmfärskn i sur martinugn (tills m Tryggve Holm i Värml Bergs-mannafrns ann 29), Smidd lättmetall (Tekn Tidskr 35), Lättmetaller i ind:s tjänst (Falu Ing,klbs årsskr 36), Modernt smide (Värml Bergsm.frns Annaler 39).",
    "translated": "LUNDBERG, Åke Melcher Johan, senior engineer, Stockholm, born in Sthlm (Stockholm) on 29/9 1904 to Lieutenant K.A.L. and Signe Ekströmer. Married Allis Blumer. Graduated from Sthlm (Stockholm) in 1923, KTH (Royal Institute of Technology) 1924-1929 (mining engineering), studied in Germany in 1925, 1931, 1933, 1939, 1941, in England in 1932, 1933, 1939, in Switzerland in 1939, studied at Carnegie Institute of Technology, USA in 1932. Worked at Jernkont :s research institute from 1929-1930, held a managerial position at AB Bofors from 1930-1932, worked as an engineer at rolling mills, forges, and press shops from 1933-1940, was a senior engineer and technical manager at AB Sv Metallvkn in Västerås from 1940-1942, and held a senior engineering and technical leadership position at OY Vuoksenniska AB Hfors since 1942. Published works include: \"On ore preparation in acid open-hearth furnaces\" (co-authored with Tryggve Holm in Värml Bergs-mannafrns yearbook in 1929), \"Forged light metals\" (published in Tekn Tidskr in 1935), \"Light metals in industrial use\" (published in Falu Ing,klbs yearbook in 1936), \"Modern forging\" (published in Värml Bergsm.frns Annaler in 1939).",
    "structured": {
        "@context": "https://schema.org/",
        "@type": "Person",
        "name": "Åke Melcher Johan Lundberg",
        "jobTitle": "Senior Engineer",
        "birthDate": "1904-09-29",
        "birthPlace": "Stockholm",
        "parent": [
            {
                "@type": "Person",
                "name": "K.A.L. Lundberg",
                "jobTitle": "Lieutenant"
            },
            {
                "@type": "Person",
                "name": "Signe Ekströmer"
            }
        ],
        "spouse": {
            "@type": "Person",
            "name": "Allis Blumer"
        },
        "education": [
            {
                "@type": "EducationalOccupationalCredential",
                "educationalLevel": "Bachelor's Degree",
                "alumniOf": "Stockholm",
                "endDate": "1923"
            },
            {
                "@type": "EducationalOccupationalCredential",
                "educationalLevel": "Master's Degree",
                "alumniOf": "KTH (Royal Institute of Technology)",
                "endDate": "1929",
                "studyProgram": "Mining Engineering"
            },
            {
                "@type": "EducationalOccupationalCredential",
                "alumniOf": "Carnegie Institute of Technology",
                "endDate": "1932",
                "studyProgram": "Unknown"
            }
        ],
        "work": [
            {
                "@type": "OrganizationRole",
                "startDate": "1929",
                "endDate": "1930",
                "roleName": "Engineer",
                "organization": {
                    "@type": "Organization",
                    "name": "Jernkont"
                }
            },
            {
                "@type": "OrganizationRole",
                "startDate": "1930",
                "endDate": "1932",
                "roleName": "Manager",
                "organization": {
                    "@type": "Organization",
                    "name": "AB Bofors"
                }
            },
            {
                "@type": "OrganizationRole",
                "startDate": "1933",
                "endDate": "1940",
                "roleName": "Engineer",
                "organization": {
                    "@type": "Organization",
                    "name": "Rolling Mills, Forges, and Press Shops"
                }
            },
            {
                "@type": "OrganizationRole",
                "startDate": "1940",
                "endDate": "1942",
                "roleName": "Senior Engineer and Technical Manager",
                "organization": {
                    "@type": "Organization",
                    "name": "AB Sv Metallvkn"
                }
            },
            {
                "@type": "OrganizationRole",
                "startDate": "1942",
                "roleName": "Senior Engineering and Technical Leader",
                "organization": {
                    "@type": "Organization",
                    "name": "OY Vuoksenniska AB Hfors"
                }
            }
        ],
        "publication": [
            {
                "@type": "Article",
                "name": "On ore preparation in acid open-hearth furnaces",
                "coAuthor": "Tryggve Holm",
                "publicationDate": "1929",
                "publisher": "Värml Bergs-mannafrns yearbook"
            },
            {
                "@type": "Article",
                "name": "Forged light metals",
                "publicationDate": "1935",
                "publisher": "Tekn Tidskr"
            },
            {
                "@type": "Article",
                "name": "Light metals in industrial use",
                "publicationDate": "1936",
                "publisher": "Falu Ing,klbs yearbook"
            },
            {
                "@type": "Article",
                "name": "Modern forging",
                "publicationDate": "1939",
                "publisher": "Värml Bergsm.frns Annaler"
            }
        ]
    },
    "occupations": {
        "career": [
            {
                "occupational_title": "Senior Engineer",
                "workplace": "Stockholm",
                "industry": "Engineering",
                "start_date": null
            },
            {
                "occupational_title": "Researcher",
                "workplace": "Jernkont :s research institute",
                "industry": "Metallurgy",
                "start_date": "1929"
            },
            {
                "occupational_title": "Manager",
                "workplace": "AB Bofors",
                "industry": "Manufacturing",
                "start_date": "1930"
            },
            {
                "occupational_title": "Engineer",
                "workplace": "Rolling mills, forges, and press shops",
                "industry": "Metallurgy",
                "start_date": "1933"
            },
            {
                "occupational_title": "Senior Engineer",
                "workplace": "AB Sv Metallvkn",
                "industry": "Metallurgy",
                "start_date": "1940"
            },
            {
                "occupational_title": "Senior Engineer and Technical Leader",
                "workplace": "OY Vuoksenniska AB Hfors",
                "industry": "Metallurgy",
                "start_date": "1942"
            }
        ]
    }
}