{
    "original": "LAGERLÖF, Gari, Försäkringsdirektör, Stockholm, f Tåby, Ögl, 5/4 78 av tullförv, v hhövd Joh L o Clara de Broen, gm Ninni Rubenson. Stud Sthlm. Anst hdlskont Sthlm o Hamburg 98, tjm brandförs.AB Fenix 99, kamr 08, v. vkst dir sed. 27. Försäkr.stud Zurich o Strassburg 02, London 06. RVO, Brandförsäkr.AB Fenix’ GM. °LAGERLÖF, Hans, Affärsman, New York, USA, f Tåby, Ögl, 29/3 80 av tullförv o v. hhövd J L o Clara de Broen, gm Clara Lenz. Stat hdlsstip f USA 03. Bild Scand Axner Trading Co 07, en av inkorporatörerna i Sv hdlskamm i New York 07, start fma Lager-loef Trading Co Inc New York 18. Donat t postmus i Sthlm. •LAGERLÖW, Carl-Hilmer, Civilingenjör, Stockholm, f Gbg 1/4 77 av bokbind C E L o Hilma Quick, gm Ilse Hofmann. Mog.ex Högre reallärov Gbg 97, ex CTL (mask o bergs) 00. Anst AB Eminent Gbg 00—02, G E Berggrens Mek Verkst Helsingfors 02—05, Carl Hansson Gbg 06, Värmeledn AB Celsius Gbg 06—08, förest värmetekn avd AB Ahlsell &amp; Ahrens Sthlm 08—13, eg värmetekn agent.fma 14—17, ch värmetekn avd AB Ahlsell &amp; Bernström Sthlm sed. 18. Styr.led AB Sv Strebel-vkn sed. 33. Led Sv Tekn.frn. L har patent på bl a de s.k. nischradiatorerna o introduc i Sv o tillv prof Junkers varmluftsapparater.",
    "translated": "LAGERLÖF, Gari, Insurance Director, Stockholm, born in Tåby, Ögl, on 5/4 1878, son of customs officer, late Lieutenant Colonel Joh L and Clara de Broen, married to Ninni Rubenson. Studied in Stockholm. Employed at commercial offices in Stockholm and Hamburg in 1898, assistant at fire insurance company AB Fenix in 1899, clerk in 1908, vice managing director since 1927. Studied insurance in Zurich and Strasbourg in 1902, London in 1906. Received the Royal Victorian Order. General Manager of AB Fenix. \n\nLAGERLÖF, Hans, Businessman, New York, USA, born in Tåby, Ögl, on 29/3 1880, son of customs officer and retired Lieutenant Colonel J L and Clara de Broen, married to Clara Lenz. Received a business scholarship in the United States in 1903. Established Scand Axner Trading Co in 1907, one of the incorporators in the Swedish Chamber of Commerce in New York in 1907, started the company Lagerloef Trading Co Inc New York in 1918. Donated to the Postal Museum in Stockholm. \n\nLAGERLÖW, Carl-Hilmer, Civil Engineer, Stockholm, born in Gothenburg on 1/4 1877, son of bookbinder C E L and Hilma Quick, married to Ilse Hofmann. Graduated from Higher Real Gymnasium in Gothenburg in 1897, graduated in Mechanical and Mining Engineering in 1900. Employed at AB Eminent in Gothenburg from 1900 to 1902, G E Berggrens Mechanical Workshop in Helsinki from 1902 to 1905, Carl Hansson in Gothenburg in 1906, Värmeledn AB Celsius in Gothenburg from 1906 to 1908, head of heating technology department at AB Ahlsell & Ahrens in Stockholm from 1908 to 1913, owner of a heating technology agency from 1914 to 1917, chief of heating technology department at AB Ahlsell & Bernström in Stockholm since 1918. Member of the board of AB Sv Strebel-vkn since 1933. Member of the Swedish Technical Association. Lagerlöw holds patents on, among other things, the so-called niche radiators and introduced Junkers hot air heaters in Sweden.",
    "structured": {
        "@context": "https://schema.org",
        "@type": "Person",
        "name": "Gari Lagerlöf",
        "birthDate": "1877-04-01",
        "birthPlace": "Gothenburg",
        "description": "Civil Engineer in Stockholm",
        "parents": [
            {
                "@type": "Person",
                "givenName": "C E L",
                "familyName": "Lagerlöw",
                "occupation": "Bookbinder"
            },
            {
                "@type": "Person",
                "givenName": "Hilma",
                "familyName": "Quick"
            }
        ],
        "spouse": {
            "@type": "Person",
            "givenName": "Ilse",
            "familyName": "Hofmann"
        },
        "education": [
            {
                "@type": "EducationalOccupationalCredential",
                "educationLevel": "Mog.ex",
                "educationalCredentialAwarded": "Högre reallärov, Gothenburg"
            },
            {
                "@type": "EducationalOccupationalCredential",
                "educationLevel": "ex",
                "educationalCredentialAwarded": "CTL (mask o bergs)"
            }
        ],
        "employmentHistory": [
            {
                "@type": "Organization",
                "name": "AB Eminent",
                "location": "Gothenburg",
                "startDate": "1900",
                "endDate": "1902"
            },
            {
                "@type": "Organization",
                "name": "G E Berggrens Mek Verkst",
                "location": "Helsinki",
                "startDate": "1902",
                "endDate": "1905"
            },
            {
                "@type": "Organization",
                "name": "Carl Hansson",
                "location": "Gothenburg",
                "startDate": "1906"
            },
            {
                "@type": "Organization",
                "name": "Värmeledn AB Celsius",
                "location": "Gothenburg",
                "startDate": "1906",
                "endDate": "1908"
            },
            {
                "@type": "Organization",
                "name": "AB Ahlsell & Ahrens",
                "location": "Stockholm",
                "startDate": "1908",
                "endDate": "1913",
                "jobTitle": "Head of Heating Technology Department"
            },
            {
                "@type": "Organization",
                "name": "Heating Technology Agency",
                "startDate": "1914",
                "endDate": "1917",
                "jobTitle": "Owner"
            },
            {
                "@type": "Organization",
                "name": "AB Ahlsell & Bernström",
                "location": "Stockholm",
                "startDate": "1918",
                "jobTitle": "Chief of Heating Technology Department"
            }
        ],
        "additionalName": "Carl-Hilmer",
        "nationality": "USA",
        "donation": {
            "@type": "Organization",
            "name": "Postal Museum, Stockholm"
        },
        "affiliation": [
            {
                "@type": "Organization",
                "name": "AB Sv Strebel-vkn",
                "jobTitle": "Board Member"
            },
            {
                "@type": "Organization",
                "name": "Swedish Technical Association"
            }
        ],
        "patent": [
            {
                "@type": "IntellectualProperty",
                "name": "Nischradiatorerna"
            },
            {
                "@type": "IntellectualProperty",
                "name": "Junkers varmluftsapparater"
            }
        ]
    },
    "occupations": {
        "career": [
            {
                "occupational_title": "Insurance Director",
                "workplace": "Stockholm",
                "industry": "Insurance",
                "start_date": "1898"
            },
            {
                "occupational_title": "Assistant",
                "workplace": "AB Fenix",
                "industry": "Fire insurance",
                "start_date": "1899"
            },
            {
                "occupational_title": "Clerk",
                "workplace": "AB Fenix",
                "industry": "Fire insurance",
                "start_date": "1908"
            },
            {
                "occupational_title": "Vice Managing Director",
                "workplace": "AB Fenix",
                "industry": "Fire insurance",
                "start_date": "1927"
            },
            {
                "occupational_title": "Businessman",
                "workplace": "New York, USA",
                "industry": "Trading",
                "start_date": "1907"
            },
            {
                "occupational_title": "Founder",
                "workplace": "Lagerloef Trading Co Inc",
                "industry": "Trading",
                "start_date": "1918"
            },
            {
                "occupational_title": "Civil Engineer",
                "workplace": "Stockholm",
                "industry": "Engineering",
                "start_date": "1900"
            },
            {
                "occupational_title": "Mechanical and Mining Engineer",
                "workplace": "Helsinki",
                "industry": "Engineering",
                "start_date": "1902"
            },
            {
                "occupational_title": "Head of Heating Technology Department",
                "workplace": "AB Ahlsell & Ahrens",
                "industry": "Heating technology",
                "start_date": "1908"
            },
            {
                "occupational_title": "Owner",
                "workplace": "Heating technology agency",
                "industry": "Heating technology",
                "start_date": "1914"
            },
            {
                "occupational_title": "Chief of Heating Technology Department",
                "workplace": "AB Ahlsell & Bernström",
                "industry": "Heating technology",
                "start_date": "1918"
            }
        ]
    }
}