{
    "original": "BÄCKMAN, Nils Josef Fredrik, Sparbanks-kamrer, Lund, f Alseda, Jkpgs län, 12/3 88 av red A Bäckman o Augusta Isaksson, gm Bertha Johanson. Studex 07, resoffex 09. Anst bkAB S Sv (sen. Sv hdlsbkn) 09, 1. kass Lund 18, vkst styr.led o kont.förest Sävsjö 21 —25, huvudkamrer sparbkn i Lund sed. 25. °B7SCIOIANJ Oscar Hugo, Grosshandlare, Stockholm, f Sthlm 31/10 82, gm Ruth Zetterström. Etabl eg trikåvarufma 05, omb denna t AB 38. Styr.ordf Sthlms Manuf.handl.frn 30 –41; styr.led Sundsv Ensk Bk sed. 32. Flm Sthlms hdlskamm. Led av 36 års när.org.sakk. 2:a kamm (Fp) 38—40. RVO.",
    "translated": "BÄCKMAN, Nils Josef Fredrik, Savings Bank Clerk, Lund, born in Alseda, Jönköping county, on March 12, 1888, son of A. Bäckman and Augusta Isaksson, married to Bertha Johanson. Studex (graduate) 1907, reserve officer graduate 1909. Employed at bkAB S Sv (later Sv hdlsbkn) since 1909, 1st cashier in Lund from 1918, member of the executive board and head of the department at Sävsjö from 1921 to 1925, chief clerk of the savings bank in Lund since 1925. °B7SCIOIANJ Oscar Hugo, Merchant, Stockholm, born in Stockholm on October 31, 1882, married to Ruth Zetterström. Established a knitwear company in 1905, appointed as representative of this company in AB (a company) in 1938. Chairman of the board of Sthlms Manuf.handl.frn (Stockholm Wholesale Retailers) from 1930 to 1941; member of the executive board of Sundsv Ensk Bk (Sundsvall Private Bank) since 1932. Member of Stockholm Chamber of Commerce since 1936. Member of various expert commissions for 36 years. Member of the second chamber (Folkpartiet) from 1938 to 1940. Holder of the Order of Vasa.",
    "structured": {
        "@context": "https://schema.org",
        "@type": "Person",
        "name": "Nils Josef Fredrik Bäckman",
        "birthDate": "1888-03-12",
        "birthPlace": {
            "@type": "Place",
            "name": "Alseda, Jönköping county"
        },
        "father": {
            "@type": "Person",
            "name": "A. Bäckman"
        },
        "mother": {
            "@type": "Person",
            "name": "Augusta Isaksson"
        },
        "spouse": {
            "@type": "Person",
            "name": "Bertha Johanson"
        },
        "occupation": [
            {
                "@type": "Person",
                "name": "Savings Bank Clerk"
            },
            {
                "@type": "Person",
                "name": "Merchant"
            }
        ],
        "education": [
            {
                "@type": "EducationalOccupationalCredential",
                "name": "Studex, 1907"
            },
            {
                "@type": "EducationalOccupationalCredential",
                "name": "Reserve officer graduate, 1909"
            }
        ],
        "worksFor": [
            {
                "@type": "Organization",
                "name": "bkAB S Sv",
                "startDate": "1909"
            },
            {
                "@type": "Organization",
                "name": "Sv hdlsbkn",
                "startDate": "1909"
            },
            {
                "@type": "Organization",
                "name": "Sävsjö",
                "startDate": "1921",
                "endDate": "1925"
            },
            {
                "@type": "Organization",
                "name": "savings bank in Lund",
                "startDate": "1925"
            },
            {
                "@type": "Organization",
                "name": "AB",
                "startDate": "1938"
            },
            {
                "@type": "Organization",
                "name": "Stthlms Manuf.handl.frn",
                "startDate": "1930",
                "endDate": "1941"
            },
            {
                "@type": "Organization",
                "name": "Sundsv Ensk Bk",
                "startDate": "1932"
            },
            {
                "@type": "Organization",
                "name": "Stockholm Chamber of Commerce",
                "startDate": "1936"
            }
        ],
        "memberOf": [
            {
                "@type": "Organization",
                "name": "Stockholm Chamber of Commerce",
                "startDate": "1936"
            }
        ],
        "politicalAffiliation": {
            "@type": "Organization",
            "name": "Folkpartiet",
            "startDate": "1938",
            "endDate": "1940"
        },
        "awards": {
            "@type": "Order",
            "name": "Order of Vasa"
        }
    },
    "occupations": {
        "career": [
            {
                "occupational_title": "Savings Bank Clerk",
                "workplace": "Lund",
                "industry": "Banking",
                "start_date": "1909"
            },
            {
                "occupational_title": "1st Cashier",
                "workplace": "Lund",
                "industry": "Banking",
                "start_date": "1918"
            },
            {
                "occupational_title": "Executive Board Member and Department Head",
                "workplace": "Sävsjö",
                "industry": "Banking",
                "start_date": "1921"
            },
            {
                "occupational_title": "Chief Clerk",
                "workplace": "Lund",
                "industry": "Banking",
                "start_date": "1925"
            },
            {
                "occupational_title": "Merchant",
                "workplace": "Stockholm",
                "industry": "Retail",
                "start_date": "1905"
            },
            {
                "occupational_title": "Representative",
                "workplace": "Stockholm",
                "industry": "Retail",
                "start_date": "1938"
            }
        ]
    }
}