{
    "original": "GÖRANSSON, Karl Anders Fredrik, Bruksdisponent, Sandviken, f Sandv 12/6 79 av brukspatr A H G o Emma Sebardt, gm Solveig Spörck. Realstudex Gävle 97, allm tekn stud univ Lausanne 97—98, prakt Tyskl o Engl 98—00, Master of Arts m ämn metallurgi, nat.ekon o el väx.ström v Columbia Uuniv, New York, 01. Anst Sandv JvksAB 01, styr.-suppl 00, styr.led 10, vkst dir 20, styr.ordf 29. Ordf fattv.styr 11—15, styr f Sandv br sjukv.-stift o sjukh, led skolråd 06—21, kyrkoråd 10, komm.flm 19—42, kyrkoflm sed. 32, stdsflm sed. 42, ordf vägstämm 36—42, flm Gävle hdlskamm sed. 07, led av dess arb.utsk sed. 12, v. ordf sed. 34, led hdlskamm.möt komm sed. 36, styr.led Gästr brandst.bol 10—29, Lifränte- 0 kap.försäkr.anst i Gävleb län sed. 11, led direkt f centr.las i Gävle 11—20, inskr.rev 16—38, ldst o dess hälsov.utsk sed. 35, styr f Liibecks stiftelse, vägomb Gästr vägdistr 36, flm Jernkont sed. 28, deleg arb.konf i Sthlm 28, led SPP övertsyr sed. 30, Ådalskommiss 31, Jvgsrådet sed. 31, dess arb.utsk sed. 32, Metallogr inst. styr sed. 36, flm Sv tekn-ind skiljed.inst 3&amp;—40 mm. Styr.led Krylbo—Norbergs jvgsAB 10—22 o 30—32 samt dess vkst dir 10—16, styr.led Lanforsens kraftAB sed. 26, led Sv hdlsbkns centr.styr sed. 32 o ordf 1 dess Gävlecentr, styr.led Sv ind.frb sed. 34, ordf. 39^-42, styr.led Sv allm exp.frn sed. 38, fi gruvföretag samt fi av Sandvikens dtrbol i in- o utl. GV:sJmt, KVOlkl, RNO, RDDO, RFrHL, RFinlVROlkl, Illis quor 12. storl, Jernkont stGM, LIVA, LVS.",
    "translated": "GÖRANSSON, Karl Anders Fredrik, Mill Manager, Sandviken, born in Sandviken on December 6th, 1879 as the son of industrialist A H G Göransson and Emma Sebardt. Married to Solveig Spörck. Completed secondary education in Gävle in 1897, studied general technology at the University of Lausanne from 1897 to 1898, practical training in Germany and England from 1898 to 1900, obtained a Master of Arts degree in metallurgy, natural economics, and electrical power transmission at Columbia University, New York in 1901. Employed at Sandvik JvksAB from 1901, appointed as a deputy board member in 1900, board member in 1910, Director of Growth in 1920, and Chairman of the Board in 1929. Chairman of the Board of the Water Supply Company from 1911 to 1915, board member of Sandviken's hospital foundation and hospital, member of the school council from 1906 to 1921, church council member in 1910, municipal council member from 1919 to 1942, church council member since 1932, municipal board member since 1942, chairman of the road meeting from 1936 to 1942, member of the Gävle Chamber of Commerce from 1907, member of its working committee from 1912, vice chairman from 1934, member of the Chamber of Commerce meeting from 1936, board member of Gästrands Fire Insurance Company from 1910 to 1929, member of the Life Annuity and Capital Insurance Company in Gävle County since 1911, director of the Central Savings Bank in Gävle from 1911 to 1920, registered real estate agent from 1916 to 1938, member and chairman of the health committee since 1935, board member of the Lübeck Foundation, road representative of Gäströms Road District since 1936, member of the Jernkontoret from 1928, delegate at the working conference in Stockholm in 1928, member of the Swedish Pension Fund Supervisory Board since 1930, member of the Ådal Commission in 1931, member of the Railway Council since 1931, member of its working committee since 1932, board member of the Metallographic Institute since 1936, member of the Swedish Technical-Industrial Arbitration Institute from 1938 to 1940. Board member of Krylbo-Norberg Railway AB from 1910 to 1922 and from 1930 to 1932, and director of growth from 1910 to 1916. Board member of Lanforsen Power AB since 1926, member of the Swedish Trade Union Central Board since 1932, and chairman of the Gävle Central Division. Board member of the Swedish Industrial Association since 1934, chairman from 1939 to 1942, board member of the Swedish Public Trading Company since 1938, member of several mining companies and subsidiaries of Sandvik in Sweden and abroad. Knight of the Royal Order of Vasa, Knight of the Order of the Polar Star, Knight of the Red Cross of Finland, Knight of the Order of the Red Cross, Knight of the Finnish Order of the Lion, Illis quor 12, recipient of the Large Jernkontoret Gold Medal, member of the Royal Swedish Academy of Sciences, member of the Royal Swedish Society of Naval Sciences. \n\nNote: For the years of marriage (19xx), specific information is missing in the original text.",
    "structured": {
        "@context": "https://schema.org/",
        "@type": "Person",
        "name": "Karl Anders Fredrik GÖRANSSON",
        "birthDate": "1879-12-06",
        "birthPlace": "Sandviken, Sweden",
        "parent": [
            {
                "@type": "Person",
                "name": "A H G GÖRANSSON",
                "jobTitle": "Industrialist"
            },
            {
                "@type": "Person",
                "name": "Emma SEBARDT"
            }
        ],
        "spouse": {
            "@type": "Person",
            "name": "Solveig SPÖRCK"
        },
        "education": {
            "@type": "EducationalOccupationalCredential",
            "credentialCategory": "Master of Arts",
            "educationalLevel": [
                "Metallurgy",
                "Natural Economics",
                "Electrical Power Transmission"
            ],
            "awardDate": "1901",
            "awardingInstitution": {
                "@type": "CollegeOrUniversity",
                "name": "Columbia University",
                "location": "New York, USA"
            }
        },
        "jobTitle": "Mill Manager",
        "worksFor": {
            "@type": "Organization",
            "name": "Sandvik JvksAB"
        },
        "employmentHistory": [
            {
                "@type": "OrganizationRole",
                "memberOf": "Sandvik JvksAB",
                "startDate": "1901"
            }
        ],
        "boardMemberships": [
            {
                "@type": "OrganizationRole",
                "memberOf": "Sandvik JvksAB",
                "startDate": "1910",
                "endDate": "1929",
                "roleName": "Board Member",
                "description": "Chairman of the Board"
            },
            {
                "@type": "OrganizationRole",
                "memberOf": "Water Supply Company",
                "startDate": "1911",
                "endDate": "1915",
                "roleName": "Chairman of the Board"
            },
            {
                "@type": "OrganizationRole",
                "memberOf": "Gästlands Hospital Foundation",
                "startDate": "Unknown",
                "endDate": "Unknown",
                "roleName": "Board Member"
            },
            {
                "@type": "OrganizationRole",
                "memberOf": "Sandviken's Hospital",
                "startDate": "Unknown",
                "endDate": "Unknown",
                "roleName": "Board Member"
            },
            {
                "@type": "OrganizationRole",
                "memberOf": "Lanforsen Power AB",
                "startDate": "1926",
                "roleName": "Board Member"
            },
            {
                "@type": "OrganizationRole",
                "memberOf": "Swedish Trade Union Central Board",
                "startDate": "1932",
                "roleName": "Board Member",
                "description": "Chairman of the Gävle Central Division"
            },
            {
                "@type": "OrganizationRole",
                "memberOf": "Swedish Industrial Association",
                "startDate": "1934",
                "endDate": "1942",
                "roleName": "Board Member",
                "description": "Chairman"
            },
            {
                "@type": "OrganizationRole",
                "memberOf": "Swedish Public Trading Company",
                "startDate": "1938",
                "roleName": "Board Member"
            },
            {
                "@type": "OrganizationRole",
                "memberOf": "Swedish Technical-Industrial Arbitration Institute",
                "startDate": "1938",
                "endDate": "1940",
                "roleName": "Board Member"
            },
            {
                "@type": "OrganizationRole",
                "memberOf": "Krylbo-Norberg Railway AB",
                "startDate": "1910",
                "endDate": "1922",
                "roleName": "Board Member"
            },
            {
                "@type": "OrganizationRole",
                "memberOf": "Krylbo-Norberg Railway AB",
                "startDate": "1930",
                "endDate": "1932",
                "roleName": "Board Member",
                "description": "Director of Growth"
            }
        ],
        "communityMemberships": [
            {
                "@type": "OrganizationRole",
                "memberOf": "Gävle Municipal Council",
                "startDate": "1919",
                "endDate": "1942",
                "roleName": "Municipal Council Member"
            },
            {
                "@type": "OrganizationRole",
                "memberOf": "Church Council",
                "startDate": "1932",
                "roleName": "Church Council Member"
            }
        ],
        "honors": [
            "Knight of the Royal Order of Vasa",
            "Knight of the Order of the Polar Star",
            "Knight of the Red Cross of Finland",
            "Knight of the Order of the Red Cross",
            "Knight of the Finnish Order of the Lion",
            "Illis quor 12",
            "Large Jernkontoret Gold Medal"
        ],
        "memberships": [
            {
                "@type": "OrganizationRole",
                "memberOf": "Gästrands Fire Insurance Company",
                "startDate": "1910",
                "endDate": "1929",
                "roleName": "Board Member"
            },
            {
                "@type": "OrganizationRole",
                "memberOf": "Life Annuity and Capital Insurance Company",
                "startDate": "1911",
                "roleName": "Board Member"
            },
            {
                "@type": "OrganizationRole",
                "memberOf": "Central Savings Bank",
                "startDate": "1911",
                "endDate": "1920",
                "roleName": "Director"
            },
            {
                "@type": "OrganizationRole",
                "memberOf": "Jernkontoret",
                "startDate": "1928",
                "roleName": "Member"
            },
            {
                "@type": "OrganizationRole",
                "memberOf": "Swedish Pension Fund Supervisory Board",
                "startDate": "1930",
                "roleName": "Member"
            },
            {
                "@type": "OrganizationRole",
                "memberOf": "Ådal Commission",
                "startDate": "1931",
                "roleName": "Member"
            },
            {
                "@type": "OrganizationRole",
                "memberOf": "Railway Council",
                "startDate": "1931",
                "roleName": "Member"
            },
            {
                "@type": "OrganizationRole",
                "memberOf": "Metallographic Institute",
                "startDate": "1936",
                "roleName": "Board Member"
            },
            {
                "@type": "OrganizationRole",
                "memberOf": "Swedish Technical-Industrial Arbitration Institute",
                "startDate": "1938",
                "endDate": "1940",
                "roleName": "Member"
            },
            {
                "@type": "OrganizationRole",
                "memberOf": "Swedish Society of Naval Sciences",
                "startDate": "Unknown",
                "endDate": "Unknown",
                "roleName": "Member"
            }
        ]
    },
    "occupations": {
        "career": [
            {
                "occupational_title": "Mill Manager",
                "workplace": "Sandviken",
                "industry": "Iron industry",
                "start_date": "1901"
            },
            {
                "occupational_title": "Deputy Board Member",
                "workplace": "Sandvik JvksAB",
                "industry": "Iron industry",
                "start_date": "1900"
            },
            {
                "occupational_title": "Board Member",
                "workplace": "Sandvik JvksAB",
                "industry": "Iron industry",
                "start_date": "1910"
            },
            {
                "occupational_title": "Director of Growth",
                "workplace": "Sandvik JvksAB",
                "industry": "Iron industry",
                "start_date": "1920"
            },
            {
                "occupational_title": "Chairman of the Board",
                "workplace": "Sandvik JvksAB",
                "industry": "Iron industry",
                "start_date": "1929"
            },
            {
                "occupational_title": "Chairman of the Board",
                "workplace": "Water Supply Company",
                "industry": "Utility",
                "start_date": "1911"
            },
            {
                "occupational_title": "Board Member",
                "workplace": "Sandviken's hospital foundation and hospital",
                "industry": "Healthcare",
                "start_date": "Unknown"
            },
            {
                "occupational_title": "Member of the School Council",
                "workplace": "Unknown",
                "industry": "Education",
                "start_date": "1906"
            },
            {
                "occupational_title": "Municipal Council Member",
                "workplace": "Unknown",
                "industry": "Government",
                "start_date": "1919"
            },
            {
                "occupational_title": "Member of the Church Council",
                "workplace": "Unknown",
                "industry": "Religion",
                "start_date": "1910"
            },
            {
                "occupational_title": "Chairman of the Road Meeting",
                "workplace": "Unknown",
                "industry": "Infrastructure",
                "start_date": "1936"
            },
            {
                "occupational_title": "Member of the Chamber of Commerce",
                "workplace": "Gävle Chamber of Commerce",
                "industry": "Business",
                "start_date": "1907"
            },
            {
                "occupational_title": "Board Member",
                "workplace": "Gästrands Fire Insurance Company",
                "industry": "Insurance",
                "start_date": "1910"
            },
            {
                "occupational_title": "Member of the Life Annuity and Capital Insurance Company",
                "workplace": "Gävle County",
                "industry": "Insurance",
                "start_date": "1911"
            },
            {
                "occupational_title": "Director",
                "workplace": "Central Savings Bank in Gävle",
                "industry": "Banking",
                "start_date": "1911"
            },
            {
                "occupational_title": "Registered Real Estate Agent",
                "workplace": "Unknown",
                "industry": "Real Estate",
                "start_date": "1916"
            },
            {
                "occupational_title": "Member and Chairman of the Health Committee",
                "workplace": "Unknown",
                "industry": "Healthcare",
                "start_date": "1935"
            },
            {
                "occupational_title": "Board Member",
                "workplace": "Lübeck Foundation",
                "industry": "Charity",
                "start_date": "Unknown"
            },
            {
                "occupational_title": "Road Representative",
                "workplace": "Gäströms Road District",
                "industry": "Infrastructure",
                "start_date": "1936"
            },
            {
                "occupational_title": "Member of the Jernkontoret",
                "workplace": "Unknown",
                "industry": "Mining",
                "start_date": "1928"
            },
            {
                "occupational_title": "Delegate at the Working Conference",
                "workplace": "Unknown",
                "industry": "Unknown",
                "start_date": "1928"
            },
            {
                "occupational_title": "Member of the Swedish Pension Fund Supervisory Board",
                "workplace": "Unknown",
                "industry": "Pension Fund",
                "start_date": "1930"
            },
            {
                "occupational_title": "Member of the Ådal Commission",
                "workplace": "Unknown",
                "industry": "Unknown",
                "start_date": "1931"
            },
            {
                "occupational_title": "Member of the Railway Council",
                "workplace": "Unknown",
                "industry": "Railway",
                "start_date": "1931"
            },
            {
                "occupational_title": "Board Member of the Metallographic Institute",
                "workplace": "Unknown",
                "industry": "Research",
                "start_date": "1936"
            },
            {
                "occupational_title": "Board Member",
                "workplace": "Krylbo-Norberg Railway AB",
                "industry": "Railway",
                "start_date": "1910"
            },
            {
                "occupational_title": "Director of Growth",
                "workplace": "Krylbo-Norberg Railway AB",
                "industry": "Railway",
                "start_date": "1910"
            },
            {
                "occupational_title": "Board Member",
                "workplace": "Lanforsen Power AB",
                "industry": "Power",
                "start_date": "1926"
            },
            {
                "occupational_title": "Member of the Swedish Trade Union Central Board",
                "workplace": "Unknown",
                "industry": "Trade Union",
                "start_date": "1932"
            },
            {
                "occupational_title": "Chairman",
                "workplace": "Gävle Central Division of the Swedish Industrial Association",
                "industry": "Business",
                "start_date": "Unknown"
            },
            {
                "occupational_title": "Board Member",
                "workplace": "Swedish Industrial Association",
                "industry": "Business",
                "start_date": "1934"
            },
            {
                "occupational_title": "Chairman",
                "workplace": "Swedish Industrial Association",
                "industry": "Business",
                "start_date": "1939"
            },
            {
                "occupational_title": "Board Member",
                "workplace": "Swedish Public Trading Company",
                "industry": "Business",
                "start_date": "1938"
            },
            {
                "occupational_title": "Member of Multiple Mining Companies",
                "workplace": "Various",
                "industry": "Mining",
                "start_date": "Unknown"
            }
        ]
    }
}