{
    "original": "EKSTRAND, Thorsten Johan Emil, Disponent, Garphyttan, f Gbg 30/6 89 av lekt fil dr o civ.ing C R E o Augusta Pierrouth, gm (1) Dagmar Ekstrand (d 17), (2) Elisabeth Allard. Mog.ex GbgReal 08, KTH (Bergshögsk, högre kursen) 10—14, avg.ex 15. Resoffex 10, löjtn Jönkps reg:s res 16, avsked 21, över-ing.assist v Jernkontoret 15—19, tf övering 19, avd.chef h Ekman &amp; Co, Gbg, 20—25, chef f Ekstrand &amp; Tholand, Gbg o New York, 26—27, vkst dir o disp AB Garphytte Bruk sed. 27. Sakk v de Skand varuutbyteskonferenserna 18—19. Komm.flm i Tysslinge 31—42. Led av dir f Örebro läns tbc-sjukh 41, v. ordf där sed. 44. Led av styr f AB Garphytte Bruk sed. 27 o av styr f AB Nordströms Linbanor sed. 36. Deput Jernk sed. 28. Styr.ordf Garph skyttefrn sed. 40. Resor: Tyskl, Frankr, Span, Ital, Engl, USA uppr ggr. RDDO, RVO. Hobbies: Allt friluftsliv, spec ridn o skidåkn.",
    "translated": "EKSTRAND, Thorsten Johan Emil, Manager, Garphyttan, b Goteborg 30/6 89, son of lecturer and doctor of philosophy C R E and Augusta Pierrouth. Married (1) Dagmar Ekstrand (died 17), (2) Elisabeth Allard. Graduated from Goteborg Realgymnasium in 1908, KTH (Bergshögsk, higher course) 10—14, passed examination in 1915. Reserve officer since 1910, lieutenant in Jönköpings regiment reserves in 1916, discharged in 1921, deputy chief engineer at Jernkontoret 15—19, acting chief engineer in 1919, department manager at Ekman & Co, Goteborg, 20—25, CEO of Ekstrand & Tholand, Goteborg and New York, 26—27, director and manager of AB Garphytte Bruk since 1927. Expert in the Scandinavian commodity exchange conferences 18—19. Municipal commissioner in Tysslinge from 31—42. Board member of Örebro County TB Hospital in 1941, vice chairman since 1944. Board member of AB Garphytte Bruk since 1927 and AB Nordströms Linbanor since 1936. Delegate of Jernkontoret since 1928. Chairman of Garph shooting association since 1940. Travelled to Germany, France, Spain, Italy, England, and the USA several times. Recipient of RDDO, RVO. Hobbies: All outdoor activities, especially horse riding and skiing.",
    "structured": {
        "@context": "https://schema.org",
        "@type": "Person",
        "name": "Thorsten Johan Emil Ekstrand",
        "birthDate": "1889-06-30",
        "birthPlace": "Goteborg",
        "parent": [
            {
                "@type": "Person",
                "name": "C R E",
                "jobTitle": "Lecturer and Doctor of Philosophy"
            },
            {
                "@type": "Person",
                "name": "Augusta Pierrouth"
            }
        ],
        "spouse": [
            {
                "@type": "Person",
                "name": "Dagmar Ekstrand",
                "deathDate": "1917"
            },
            {
                "@type": "Person",
                "name": "Elisabeth Allard"
            }
        ],
        "education": [
            {
                "@type": "EducationalOrganization",
                "name": "Goteborg Realgymnasium",
                "endDate": "1908"
            },
            {
                "@type": "EducationalOrganization",
                "name": "KTH (Bergshögsk, higher course)",
                "startDate": "1910",
                "endDate": "1914"
            }
        ],
        "residence": {
            "@type": "Organization",
            "name": "Garphyttan"
        },
        "occupation": "Manager",
        "employmentHistory": [
            {
                "@type": "Organization",
                "name": "Jernkontoret",
                "startDate": "1915",
                "endDate": "1919",
                "jobTitle": "Deputy Chief Engineer"
            },
            {
                "@type": "Organization",
                "name": "Jernkontoret",
                "startDate": "1919",
                "jobTitle": "Acting Chief Engineer"
            },
            {
                "@type": "Organization",
                "name": "Ekman & Co",
                "startDate": "1920",
                "endDate": "1925",
                "jobTitle": "Department Manager"
            },
            {
                "@type": "Organization",
                "name": "Ekstrand & Tholand",
                "startDate": "1926",
                "endDate": "1927",
                "jobTitle": "CEO"
            },
            {
                "@type": "Organization",
                "name": "AB Garphytte Bruk",
                "startDate": "1927",
                "jobTitle": "Director and Manager"
            }
        ],
        "membership": [
            {
                "@type": "Organization",
                "name": "Scandinavian Commodity Exchange Conferences",
                "startDate": "1918",
                "endDate": "1919",
                "jobTitle": "Expert"
            },
            {
                "@type": "Organization",
                "name": "Tysslinge Municipal Council",
                "startDate": "1931",
                "endDate": "1942",
                "jobTitle": "Municipal Commissioner"
            },
            {
                "@type": "Organization",
                "name": "Örebro County TB Hospital",
                "startDate": "1941",
                "jobTitle": "Board Member"
            },
            {
                "@type": "Organization",
                "name": "AB Nordströms Linbanor",
                "startDate": "1936",
                "jobTitle": "Board Member"
            },
            {
                "@type": "Organization",
                "name": "Jernkontoret",
                "startDate": "1928",
                "jobTitle": "Delegate"
            },
            {
                "@type": "Organization",
                "name": "Garph Shooting Association",
                "startDate": "1940",
                "jobTitle": "Chairman"
            }
        ],
        "travelHistory": [
            "Germany",
            "France",
            "Spain",
            "Italy",
            "England",
            "USA"
        ],
        "awards": [
            "RDDO",
            "RVO"
        ],
        "interests": [
            "Outdoor activities",
            "Horse riding",
            "Skiing"
        ]
    },
    "occupations": {
        "career": [
            {
                "occupational_title": "Assistant Engineer",
                "workplace": "Jernkontoret",
                "industry": "Engineering",
                "start_date": "1915"
            },
            {
                "occupational_title": "Acting Chief Engineer",
                "workplace": "Jernkontoret",
                "industry": "Engineering",
                "start_date": "1919"
            },
            {
                "occupational_title": "Department Manager",
                "workplace": "Ekman & Co",
                "industry": "Trade",
                "start_date": "1920"
            },
            {
                "occupational_title": "CEO",
                "workplace": "Ekstrand & Tholand",
                "industry": "Trade",
                "start_date": "1926"
            },
            {
                "occupational_title": "Director and Manager",
                "workplace": "AB Garphytte Bruk",
                "industry": "Manufacturing",
                "start_date": "1927"
            }
        ]
    }
}