{
    "original": "HESSELMAN, Knut Jonas Elias, Direktör, Civilingenjör, Stockholm, f Sthlm 9/4 77 av fabrikör B A H o Marie Louise Åberg, gm Anna Strandell (d). Ex KTH 99. Rit v AB Diesels Motorer 00, konstr.ch o l:e ing 01— 11, övering 12—17, start eg konstr- o experi-mentverkst 18, bild Hesselmans Patent AB 25, vkst dir där. Styr.led i sistn bol sed. start, i AB Hema 30—41, i Hesselman Motor Corp 31—41. Konstr dieselmotorer f öl ändamål 01 —17, utexperimenterat syst f dir insprutn av bränsle i dieselmotorer 18—22, oljemotorer m låg kompression o elektr tändn 26—29 (Hesselmans lågtrycksmotor), inneh ett 100-tal pat betr motorer. RVO, LIVA (dess st GM), LVA, K AK: s gplak.",
    "translated": "HESSELMAN, Knut Jonas Elias, Director, Civil Engineer, Stockholm, b. Stockholm 9/4 1877, son of manufacturer B A H and Marie Louise Åberg, m. Anna Strandell (deceased). Former student at KTH (Royal Institute of Technology) 1899. Draftsman at AB Diesels Motorer 1900, design engineer and first engineer 1901-1911, chief engineer 1912-1917, started own design and experimental workshop in 1918, established Hesselmans Patent AB in 1925, served as managing director there. Board member of the company since its establishment. Also board member in AB Hema 1930-1941 and Hesselman Motor Corp 1931-1941. Designed diesel engines for various purposes 1901-1917, conducted experiments on direct fuel injection in diesel engines 1918-1922, worked on low compression oil engines and electric ignition 1926-1929 (Hesselmans low-pressure engine), held around 100 patents related to engines. Knight of the Royal Order of Vasa (RVO), Member of the Swedish Inventors Association (LIVA, its grand master), Member of the Swedish Engineers Association (LVA), Member of the Royal Swedish Academy of Sciences (K AK).",
    "structured": {
        "@context": "http://schema.org",
        "@type": "Person",
        "name": "Knut Jonas Elias Hesselman",
        "jobTitle": "Director",
        "birthPlace": "Stockholm",
        "birthDate": "1877-04-09",
        "parent": [
            {
                "@type": "Person",
                "name": "B A H"
            },
            {
                "@type": "Person",
                "name": "Marie Louise Åberg"
            }
        ],
        "spouse": {
            "@type": "Person",
            "name": "Anna Strandell",
            "deathDate": "<date-of-death>"
        },
        "alumniOf": {
            "@type": "EducationalOrganization",
            "name": "Royal Institute of Technology"
        },
        "worksFor": [
            {
                "@type": "Organization",
                "name": "AB Diesels Motorer",
                "startDate": "1900",
                "endDate": "1917",
                "jobTitle": "Draftsman"
            },
            {
                "@type": "Organization",
                "name": "Hesselmans Patent AB",
                "startDate": "1925",
                "jobTitle": "Managing Director"
            },
            {
                "@type": "Organization",
                "name": "AB Hema",
                "startDate": "1930",
                "endDate": "1941",
                "jobTitle": "Board Member"
            },
            {
                "@type": "Organization",
                "name": "Hesselman Motor Corp",
                "startDate": "1931",
                "endDate": "1941",
                "jobTitle": "Board Member"
            }
        ],
        "description": "Director and Civil Engineer",
        "memberOf": [
            {
                "@type": "Organization",
                "name": "Royal Order of Vasa",
                "startDate": "<knighthood-date>"
            },
            {
                "@type": "Organization",
                "name": "Swedish Inventors Association",
                "startDate": "<membership-start-date>",
                "endDate": "<membership-end-date>",
                "jobTitle": "Grand Master"
            },
            {
                "@type": "Organization",
                "name": "Swedish Engineers Association",
                "startDate": "<membership-start-date>"
            },
            {
                "@type": "Organization",
                "name": "Royal Swedish Academy of Sciences",
                "startDate": "<membership-start-date>"
            }
        ],
        "relatedTo": {
            "@type": "Person",
            "name": "<relative-name>"
        }
    },
    "occupations": {
        "career": [
            {
                "occupational_title": "Draftsman",
                "workplace": "AB Diesels Motorer",
                "industry": "Diesel engines",
                "start_date": "1900"
            },
            {
                "occupational_title": "Design Engineer",
                "workplace": "AB Diesels Motorer",
                "industry": "Diesel engines",
                "start_date": "1901"
            },
            {
                "occupational_title": "First Engineer",
                "workplace": "AB Diesels Motorer",
                "industry": "Diesel engines",
                "start_date": "1901"
            },
            {
                "occupational_title": "Chief Engineer",
                "workplace": "AB Diesels Motorer",
                "industry": "Diesel engines",
                "start_date": "1912"
            },
            {
                "occupational_title": "Design and Experimental Workshop Owner",
                "workplace": "Own workshop",
                "industry": "Engineering",
                "start_date": "1918"
            },
            {
                "occupational_title": "Managing Director",
                "workplace": "Hesselmans Patent AB",
                "industry": "Engineering",
                "start_date": "1925"
            }
        ]
    }
}