{
    "original": "HEMBERG, Sven Emil, Direktör, Stockholm, f Finja 8/8 73 av B Hemberg o Christina Svensdotter, gm Elin Jakobsson (d. 39). Bokhåll.sk Lund, mejeristud på öl pl i Skåne 0 Danm. Mej Strövelstorps andelsmej 94—98, mej.förest v Per Bondessons Lantbr AB Svalöv 98—07, förest Sthlms Mjölkförsäljn AB:s mej.avd 08—11, vkst dir o styrled AB Ost Sthlm 12—19 uppfinn av konstgrädde »Gräddin» samt tillv därav m pat i sju Idr, vkst dir o styr.led AB Kräddin Sthlm o Örebro sed. 26. Styr.led Fruktind.AB Pomo öbr sed. 40. Stift av Svalövs kristl ungd.frn, ordf 03—08, en av stift av Missionssällsk B V, styr.led där sed. 16, en av stift av Roseniusfrn i Sthlm, ordf sed. 10. Resor: Lettl, Estl 19— 21, Finl 21—22, uppsatt konstgräddefabriker 1 Finl 28, Danm 29, Tyskl 29, 30, Belg 31, Engl 36.",
    "translated": "HEMBERG, Sven Emil, Director, Stockholm, born in Finja on August 8, 1873, son of B Hemberg and Christina Svensdotter, married to Elin Jakobsson (deceased in 1939). Worked as an accountant in Lund, studied dairy farming in Skåne and Denmark. Worked at Strövelstorp's cooperative dairy from 1894 to 1898, as dairy manager at Per Bondesson's Agriculture Ltd. in Svalöv from 1898 to 1907, as manager of Stockholm Milk Sales Ltd.'s dairy department from 1908 to 1911, and as managing director and board member of AB Ost Stockholm from 1912 to 1919. Invented artificial cream \"Gräddin\" and produced it with partners in seven locations, as well as serving as managing director and board member of AB Kräddin in Stockholm and Örebro since 1926. Also served as a board member of Fruit Industry Ltd. Pomo since 1940. Founder of Svalöv's Christian Youth Association, chairman from 1903 to 1908, board member of the Bible Mission Society since 1916, board member of Roseniusfrun in Stockholm, chairman since 1910. Travelled to Latvia and Estonia from 1919 to 1921, Finland from 1921 to 1922, established artificial cream factories in Finland in 1928, Denmark in 1929, Germany in 1929 and 1930, Belgium in 1931, and England in 1936.",
    "structured": {
        "@context": "https://schema.org",
        "@type": "Person",
        "name": "Sven Emil HEMBERG",
        "jobTitle": "Director",
        "address": {
            "@type": "PostalAddress",
            "addressLocality": "Stockholm"
        },
        "birthDate": "1873-08-08",
        "birthPlace": "Finja",
        "parents": [
            {
                "@type": "Person",
                "name": "B Hemberg"
            },
            {
                "@type": "Person",
                "name": "Christina Svensdotter"
            }
        ],
        "spouse": [
            {
                "@type": "Person",
                "name": "Elin Jakobsson",
                "deathDate": "1939"
            }
        ],
        "work": [
            {
                "@type": "Organization",
                "name": "Lund Bookkeeping School"
            },
            {
                "@type": "Organization",
                "name": "Strövelstorp Cooperative Dairy",
                "startDate": "1894",
                "endDate": "1898"
            },
            {
                "@type": "Organization",
                "name": "Per Bondesson's Agriculture Ltd.",
                "startDate": "1898",
                "endDate": "1907"
            },
            {
                "@type": "Organization",
                "name": "Stockholm Milk Sales Ltd.",
                "startDate": "1908",
                "endDate": "1911"
            },
            {
                "@type": "Organization",
                "name": "AB Ost Stockholm",
                "startDate": "1912",
                "endDate": "1919",
                "jobTitle": "Managing Director"
            },
            {
                "@type": "Organization",
                "name": "AB Kräddin",
                "startDate": "1926",
                "jobTitle": "Managing Director"
            },
            {
                "@type": "Organization",
                "name": "Fruit Industry Ltd. Pomo",
                "startDate": "1940"
            }
        ],
        "founderOf": [
            {
                "@type": "Organization",
                "name": "Svalöv's Christian Youth Association",
                "startDate": "1903",
                "endDate": "1908",
                "jobTitle": "Chairman"
            }
        ],
        "memberOf": [
            {
                "@type": "Organization",
                "name": "Bible Mission Society",
                "startDate": "1916"
            },
            {
                "@type": "Organization",
                "name": "Roseniusfrun in Stockholm",
                "startDate": "1910",
                "jobTitle": "Chairman"
            }
        ],
        "travelledTo": [
            {
                "@type": "Place",
                "name": "Latvia"
            },
            {
                "@type": "Place",
                "name": "Estonia"
            },
            {
                "@type": "Place",
                "name": "Finland",
                "startDate": "1919",
                "endDate": "1921"
            },
            {
                "@type": "Place",
                "name": "Denmark",
                "startDate": "1929"
            },
            {
                "@type": "Place",
                "name": "Germany",
                "startDate": "1929",
                "endDate": "1930"
            },
            {
                "@type": "Place",
                "name": "Belgium",
                "startDate": "1931"
            },
            {
                "@type": "Place",
                "name": "England",
                "startDate": "1936"
            }
        ],
        "invented": "Gräddin - artificial cream"
    },
    "occupations": {
        "career": [
            {
                "occupational_title": "Accountant",
                "workplace": "Lund",
                "industry": "Bookkeeping",
                "start_date": "Unknown"
            },
            {
                "occupational_title": "Dairy Manager",
                "workplace": "Strövelstorp's Cooperative Dairy",
                "industry": "Dairy",
                "start_date": "1894"
            },
            {
                "occupational_title": "Dairy Manager",
                "workplace": "Per Bondesson's Agriculture Ltd.",
                "industry": "Dairy",
                "start_date": "1898"
            },
            {
                "occupational_title": "Manager, Dairy Department",
                "workplace": "Stockholm Milk Sales Ltd.",
                "industry": "Dairy",
                "start_date": "1908"
            },
            {
                "occupational_title": "Managing Director",
                "workplace": "AB Ost Stockholm",
                "industry": "Dairy",
                "start_date": "1912"
            },
            {
                "occupational_title": "Inventor",
                "workplace": "Artificial Cream Manufacturing (Gräddin)",
                "industry": "Food",
                "start_date": "Unknown"
            },
            {
                "occupational_title": "Managing Director",
                "workplace": "AB Kräddin",
                "industry": "Food",
                "start_date": "1926"
            },
            {
                "occupational_title": "Board Member",
                "workplace": "Fruit Industry Ltd. Pomo",
                "industry": "Food",
                "start_date": "1940"
            }
        ]
    }
}