{
    "original": "DJURBERG, Gösta Stensson, Disponent, Karlstad, f Lovö, Sthlms län, 11/7 97 av öv.-löjtn Sten D o Selma Thimgren, gm Lilly Boman. Studex, SKHS (forstm). Anst Sv järnbr träkolsfrn 26—28, Billeruds AB 2&amp;—38, sed. 38 h Wermländska Inmätn.frn (gr 09, opart org f mätn av västsv skogsprodukt), länsskogsbrandch Värml län, led kristidsstyr bränsledeleg, sekr Virkesmätn.rådet. Av trycket : Tabeller f volymberäkn av träkol (1. uppl 26, 2. uppl 41), upps i facktidskr. Rotary.",
    "translated": "DJURBERG, Gösta Stensson, Manager, Karlstad, b. Lovö, Stockholm County, 11/7 1897, son of Lieutenant Sten D and Selma Thimgren, m. Lilly Boman. Graduated from SKHS (Forestry). Employed at Swedish iron and charcoal company from 1926-1928, Billeruds AB from 1928-1938, and currently working at Wermländska Inmätningsföreningen (founded in 1909, non-partisan organization for forest product measurement in western Sweden). Also served in the County Forest Fire Brigade of Värmland County, and was a member of the fuel allocation emergency force. Secretary of the Timber Measurement Council. Publications include: Tables for volume calculation of charcoal (1st edition published in 1926, 2nd edition in 1941), published in professional journals. Member of Rotary.",
    "structured": {
        "@context": "https://schema.org",
        "@type": "Person",
        "name": "Gösta Stensson Djurberg",
        "givenName": "Gösta Stensson",
        "familyName": "Djurberg",
        "birthDate": "1897-07-11",
        "birthPlace": {
            "@type": "Place",
            "name": "Lovö, Sthlms län"
        },
        "parents": [
            {
                "@type": "Person",
                "name": "Sten D"
            },
            {
                "@type": "Person",
                "name": "Selma Thimgren"
            }
        ],
        "spouse": {
            "@type": "Person",
            "name": "Lilly Boman"
        },
        "memberOf": [
            {
                "@type": "Organization",
                "name": "SKHS",
                "additionalType": "Forestry",
                "endDate": "1926"
            },
            {
                "@type": "Organization",
                "name": "Swedish iron and charcoal company",
                "startDate": "1926",
                "endDate": "1928"
            },
            {
                "@type": "Organization",
                "name": "Billeruds AB",
                "startDate": "1928",
                "endDate": "1938"
            },
            {
                "@type": "Organization",
                "name": "Wermländska Inmätningsföreningen",
                "foundingDate": "1909",
                "nonprofitStatus": "Nonprofit",
                "description": "Non-partisan organization for forest product measurement in western Sweden"
            },
            {
                "@type": "Organization",
                "name": "County Forest Fire Brigade of Värmland County"
            },
            {
                "@type": "Organization",
                "name": "Timber Measurement Council",
                "roleName": "Secretary"
            },
            {
                "@type": "Organization",
                "name": "Rotary"
            }
        ],
        "publications": [
            {
                "@type": "PublicationIssue",
                "name": "Tables for volume calculation of charcoal",
                "issueNumber": "1",
                "datePublished": "1926"
            },
            {
                "@type": "PublicationIssue",
                "name": "Tables for volume calculation of charcoal",
                "issueNumber": "2",
                "datePublished": "1941"
            }
        ]
    },
    "occupations": {
        "career": [
            {
                "occupational_title": "Manager",
                "workplace": "Karlstad",
                "industry": null,
                "start_date": null
            },
            {
                "occupational_title": "Employee",
                "workplace": "Swedish iron and charcoal company",
                "industry": "Iron and charcoal production",
                "start_date": "1926"
            },
            {
                "occupational_title": "Employee",
                "workplace": "Billeruds AB",
                "industry": "Wood and paper industry",
                "start_date": "1928"
            },
            {
                "occupational_title": "Employee",
                "workplace": "Wermländska Inmätningsföreningen",
                "industry": "Forest product measurement",
                "start_date": "1938"
            }
        ]
    }
}