{
    "original": "BECKMAN, Gunnar Bernhard Gustaf, Civilingenjör, Stockholm, f Sthlm 16/5 98 av byrå-ch K A B o Ruth Hammarstedt, gm Sally Staaf. Studex Lundsb sk 16, civ.ingex KTH 21. Anst Tekn Inst 21—24. En av grund av Sthlms Tekn Inst 24 o förest f dess vkst-tekn.facksk sed. nmnda år. Vkst dir sed. 28 i fma Vinkelcentrifug Sthlm (gr nmda år f expl av konstr gjorda av B, fmn ombild t AB 33 m B som ag av aktiemaj). Vkst dir Fastgh-AB Kejsarkronan sed. 23. Resor: Engl 16, USA 21, Tyskl, Österr 36—37, Frankr 36—37, 39, Ital 38, Holl, Belg 39. Av trycket: »Våra maskiner» i ser Lä sn f folksk. Hållfasthetslära, Mekanik, Hydromekanik (Sthlms Tekn Inst förl). Sv Teknol.frn, KAK, Sv Kryss.kl. Hobby: Segling.",
    "translated": "BECKMAN, Gunnar Bernhard Gustaf, Civil Engineer, Stockholm, b. Stockholm 16/5 98, son of office manager K A B and Ruth Hammarstedt, married to Sally Staaf. Graduated from Lund's school at the age of 16, civil engineering degree from KTH in 1921. Employed at the Technical Institute from 1921 to 1924. One of the founders of Stockholm's Technical Institute in 1924 and served as its head of development technical department until mentioned year. Head of development since 1928 at the company Vinkelcentrifug in Stockholm (which became a limited company in 1933 with B as majority shareholder). Head of development at Fastgh-AB Kejsarkronan since 1923. Travelled to England in 1916, USA in 1921, Germany and Austria from 1936-1937, France in 1936-1937 and 1939, Italy in 1938, and the Netherlands and Belgium in 1939. Publications: \"Våra maskiner\" in the series \"Läsningsbok för folkskolan\". Author of books on Strength of Materials, Mechanics, and Hydromechanics (published by Stockholm's Technical Institute). Member of Swedish Technological Association, Royal Automobile Club, and Swedish Cruising Club. Hobby: Sailing.",
    "structured": {
        "@context": "https://schema.org",
        "@type": "Person",
        "name": "Gunnar Bernhard Gustaf Beckman",
        "birthDate": "1898-05-16",
        "birthPlace": "Stockholm, Sweden",
        "parents": [
            {
                "@type": "Person",
                "name": "K A B",
                "jobTitle": "Office Manager"
            },
            {
                "@type": "Person",
                "name": "Ruth Hammarstedt"
            }
        ],
        "spouse": {
            "@type": "Person",
            "name": "Sally Staaf"
        },
        "education": [
            {
                "@type": "EducationalOrganization",
                "name": "Lund's School",
                "location": "Lund, Sweden",
                "endDate": "1914"
            },
            {
                "@type": "EducationalOrganization",
                "name": "Royal Institute of Technology",
                "location": "Stockholm, Sweden",
                "startDate": "1914",
                "endDate": "1921"
            }
        ],
        "work": [
            {
                "@type": "Organization",
                "name": "Technical Institute",
                "location": "Stockholm, Sweden",
                "startDate": "1921",
                "endDate": "1924",
                "position": "Employee"
            },
            {
                "@type": "Organization",
                "name": "Stockholm's Technical Institute",
                "location": "Stockholm, Sweden",
                "startDate": "1924",
                "position": "Co-founder"
            },
            {
                "@type": "Organization",
                "name": "Vinkelcentrifug",
                "location": "Stockholm, Sweden",
                "startDate": "1928",
                "position": "Head of Development"
            },
            {
                "@type": "Organization",
                "name": "Fastgh-AB Kejsarkronan",
                "location": "Stockholm, Sweden",
                "startDate": "1923",
                "position": "Head of Development"
            }
        ],
        "publication": [
            {
                "@type": "PublicationIssue",
                "name": "Våra maskiner",
                "isPartOf": {
                    "@type": "CreativeWork",
                    "name": "Läsningsbok för folkskolan"
                }
            },
            {
                "@type": "PublicationVolume",
                "name": "Strength of Materials"
            },
            {
                "@type": "PublicationVolume",
                "name": "Mechanics"
            },
            {
                "@type": "PublicationVolume",
                "name": "Hydromechanics"
            }
        ],
        "memberOf": [
            {
                "@type": "Organization",
                "name": "Swedish Technological Association"
            },
            {
                "@type": "Organization",
                "name": "Royal Automobile Club"
            },
            {
                "@type": "Organization",
                "name": "Swedish Cruising Club"
            }
        ],
        "hobby": "Sailing",
        "travelHistory": [
            {
                "@type": "Place",
                "name": "England",
                "startDate": "1916"
            },
            {
                "@type": "Place",
                "name": "United States",
                "startDate": "1921"
            },
            {
                "@type": "Place",
                "name": "Germany",
                "startDate": "1936",
                "endDate": "1937"
            },
            {
                "@type": "Place",
                "name": "Austria",
                "startDate": "1936",
                "endDate": "1937"
            },
            {
                "@type": "Place",
                "name": "France",
                "startDate": "1936",
                "endDate": "1939"
            },
            {
                "@type": "Place",
                "name": "Italy",
                "startDate": "1938"
            },
            {
                "@type": "Place",
                "name": "Netherlands"
            },
            {
                "@type": "Place",
                "name": "Belgium"
            }
        ]
    },
    "occupations": {
        "career": [
            {
                "occupational_title": "Civil Engineer",
                "workplace": "Technical Institute",
                "industry": "Engineering",
                "start_date": "1921"
            },
            {
                "occupational_title": "Head of Development",
                "workplace": "Vinkelcentrifug Stockholm",
                "industry": "Engineering",
                "start_date": "1928"
            },
            {
                "occupational_title": "Head of Development",
                "workplace": "Fastgh-AB Kejsarkronan",
                "industry": "Engineering",
                "start_date": "1923"
            }
        ]
    }
}