{
    "original": "BÖRJESON, Björn Birger, Vägdirektör, Karlskrona, f Skillingmark, Värml l, 27/10 04 av hemm.äg B B B o Böret Tholsson, gm Gerd Persson. Studex Karlst 23, civ.ing KTH 29. Anst v Ribbing» ing.byrå Falun o Sthlm 29—31, Stat Arb.lösh.kommiss 32, väging.ass mm i Värml l 32—36, bitr arb.ch AB Vägförbättringar Karlst 36—43, varav arb.ch f be-läggn.arb i Iran 38—39. Vägdir i Blek 43. Led Sv Tekn.frn.",
    "translated": "BÖRJESON, Björn Birger, Road Director, Karlskrona, born in Skillingmark, Värmland County, on the 27th of October 1904 to home-owner B B B and Böret Tholsson, married to Gerd Persson. Graduated from Karlstad in 1923, civil engineer from the Royal Institute of Technology in 1929. Employed at Ribbing Engineering Bureau in Falun and Stockholm from 1929 to 1931, State Employment Commissioner for Road Construction in 1932, Assistant Road Engineer, and others, in Värmland County from 1932 to 1936, deputy worker at AB Vägförbättringar in Karlstad from 1936 to 1943, including working on the construction of roads in Iran from 1938 to 1939. Road Director in Blekinge County from 1943. Member of the Swedish Technical Society.",
    "structured": {
        "@context": "https://schema.org",
        "@type": "Person",
        "name": "Björn Birger Börjeson",
        "birthDate": "1904-10-27",
        "birthPlace": "Skillingmark, Värmland County",
        "nationality": "Swedish",
        "jobTitle": "Road Director",
        "worksFor": {
            "@type": "Organization",
            "name": "Karlskrona"
        },
        "parent": {
            "@type": "Person",
            "name": "B B B and Böret Tholsson"
        },
        "spouse": {
            "@type": "Person",
            "name": "Gerd Persson"
        },
        "education": [
            {
                "@type": "EducationalOrganization",
                "name": "Karlstad",
                "endDate": "1923"
            },
            {
                "@type": "EducationalOrganization",
                "name": "Royal Institute of Technology",
                "endDate": "1929",
                "degree": {
                    "@type": "EducationalDegree",
                    "name": "Civil Engineering"
                }
            }
        ],
        "works": [
            {
                "@type": "Organization",
                "name": "Ribbing Engineering Bureau",
                "startDate": "1929",
                "endDate": "1931"
            },
            {
                "@type": "GovernmentOrganization",
                "name": "State Employment Commissioner for Road Construction",
                "startDate": "1932"
            },
            {
                "@type": "GovernmentOrganization",
                "name": "Värmland County",
                "position": "Assistant Road Engineer",
                "startDate": "1932",
                "endDate": "1936"
            },
            {
                "@type": "Organization",
                "name": "AB Vägförbättringar",
                "position": "Deputy Worker",
                "startDate": "1936",
                "endDate": "1943"
            }
        ],
        "memberOf": {
            "@type": "Organization",
            "name": "Swedish Technical Society"
        }
    },
    "occupations": {
        "career": [
            {
                "occupational_title": "Road Director",
                "workplace": "Karlskrona",
                "industry": "Road Construction",
                "start_date": "1943"
            },
            {
                "occupational_title": "Deputy Worker",
                "workplace": "AB Vägförbättringar Karlstad",
                "industry": "Road Construction",
                "start_date": "1936"
            },
            {
                "occupational_title": "Assistant Road Engineer",
                "workplace": "Värmland County",
                "industry": "Road Construction",
                "start_date": "1932"
            },
            {
                "occupational_title": "State Employment Commissioner for Road Construction",
                "workplace": "Värmland County",
                "industry": "Road Construction",
                "start_date": "1932"
            },
            {
                "occupational_title": "Employed at Ribbing Engineering Bureau",
                "workplace": "Falun and Stockholm",
                "industry": "Engineering",
                "start_date": "1929"
            }
        ]
    }
}