{
    "original": "EKSTRÖM, Alfred, Fil Dr, Ahlby säteri, Fittja, f Viksta, Upps l, 4/11 73 av grhdl A H E o Anna Lovisa Holm, gm Signe Melin. Fil kand Upps 95, fil lic 96, fil dr 97, Poly-technicums i Zurich högsta årsk i el.tekn 97. Ass i el.tekn där 98, d :o i fysik v Kiels univ 99, ing AB Telef.fabr i Sthlm 99, disp där 00— 01, ing AB L M Ericsson &amp; Co 01—06, init.tag 0 vkst dir Hemsjö KraftAB, Mörrumsströms KraftAB 06—20, AB A H Ekström 06—23, disp Djupafors Fabr.AB 08—20, vkst dir AB Kraftintressenter 20—28, d :o fma Crompton &amp; Ekström London 28—32. Byggt Sikfors KraftAB 08, uppf telef, sy st f centralbatteri (anläggn i Ryssl, Holl, Mex mfl länd), banbryt betr sv landsbygd:s elektrifier, init.tag t o sekr i Mäl.provis El Länsfrn 23—28, sekr Riksfrn f Landsbygd:s Elektrifier 23—28, init.tag t IVA:s frn Rationell Textiltvätt, plan o tills m R B Matthews gnmfört Engl :s första större landsb.elektrifier 27—32, led Elektrifier.komm 16—22. Av trycket: Modern telef.tekn (tills m O Harder o S Lübeck 03), Landsbygd:s elektrifier (tills m fl andra förf 16), El.tekn i lantbr:s tj (22), Rural Electrification tills ni V Ekström London (29) ett flert broschyrer o föredr. RVO, LLA, HedLIVA.",
    "translated": "EKSTRÖM, Alfred, PhD, Ahlby Manor, Fittja, born in Viksta, Uppsala county, on November 4th, 1873, son of farmer A.H.E. and Anna Lovisa Holm, married to Signe Melin. Bachelor of Arts, Uppsala 1895, Licentiate of Philosophy 1896, Doctor of Philosophy 1897. Highest annual rank in Electrical Engineering at the Polytechnic Institute in Zurich in 1897. Assistant in Electrical Engineering there in 1898, assistant in Physics at Kiel University in 1899, engineer at AB Telef.fabr in Stockholm in 1899, manager there from 1900 to 1901, engineer at AB L.M. Ericsson & Co from 1901 to 1906. Started as managing director at Hemsjö Kraft AB and Mörrumsströms Kraft AB from 1906 to 1920. Established AB A.H. Ekström in 1906 and managed that company until 1923. Manager at Djupafors Fabr AB from 1908 to 1920. Managing director at AB Kraftintressenter from 1920 to 1928, and then as managing partner at Crompton & Ekström London from 1928 to 1932. Built Sikfors Kraft AB in 1908, constructed telephone systems and central battery stations in various countries such as Russia, Holland, Mexico, and others. Pioneer in rural electrification. Played a key role as secretary in the Board of Directors for the Mälaren Province Electric Power Company from 1923 to 1928, and as secretary for the National Rural Electrification Association from 1923 to 1928. Initiated the collaboration with R.B. Matthews to implement England's first significant rural electrification project from 1927 to 1932. Member of the Electrification Committee from 1916 to 1922. Published works include \"Modern Telecommunication Technology\" (co-authored with O. Harder and S. Lübeck, 1903), \"Rural Electrification\" (co-authored with other authors, 1916), \"Electrical Technology in Agriculture\" (1922), \"Rural Electrification\" (with V. Ekström, London, 1929), and several brochures and lectures. Awarded the Royal Order of Vasa, the Order of Léopold, and the Liva Medal for advancements in the field.",
    "structured": {
        "@context": "http://schema.org",
        "@type": "Person",
        "name": "Alfred Ekström",
        "birthDate": "1873-11-04",
        "birthPlace": "Viksta, Uppsala County, Sweden",
        "deathDate": "Unknown",
        "description": "PhD in Electrical Engineering",
        "nationality": "Swedish",
        "spouse": "Signe Melin",
        "parent": [
            {
                "@type": "Person",
                "name": "A.H.E.",
                "description": "Father"
            },
            {
                "@type": "Person",
                "name": "Anna Lovisa Holm",
                "description": "Mother"
            }
        ],
        "education": [
            {
                "@type": "EducationalOccupationalCredential",
                "credentialCategory": "Bachelor's degree",
                "educationalLevel": "Bachelor of Arts",
                "educationalProgram": "Uppsala University",
                "endDate": "1895"
            },
            {
                "@type": "EducationalOccupationalCredential",
                "credentialCategory": "Licentiate's degree",
                "educationalLevel": "Licentiate of Philosophy",
                "educationalProgram": "Uppsala University",
                "endDate": "1896"
            },
            {
                "@type": "EducationalOccupationalCredential",
                "credentialCategory": "Doctoral degree",
                "educationalLevel": "Doctor of Philosophy",
                "educationalProgram": "Uppsala University",
                "endDate": "1897"
            },
            {
                "@type": "EducationalOccupationalCredential",
                "credentialCategory": "Engineering degree",
                "educationalLevel": "Polytechnic Institute Zurich",
                "educationalProgram": "Electrical Engineering",
                "endDate": "1897"
            }
        ],
        "worksFor": [
            {
                "@type": "Organization",
                "name": "AB Telef.fabr"
            },
            {
                "@type": "Organization",
                "name": "AB L.M. Ericsson & Co",
                "startDate": "1901",
                "endDate": "1906"
            },
            {
                "@type": "Organization",
                "name": "Hemsjö Kraft AB",
                "startDate": "1906",
                "endDate": "1920"
            },
            {
                "@type": "Organization",
                "name": "Mörrumsströms Kraft AB",
                "startDate": "1906",
                "endDate": "1920"
            },
            {
                "@type": "Organization",
                "name": "AB A.H. Ekström",
                "startDate": "1906",
                "endDate": "1923"
            },
            {
                "@type": "Organization",
                "name": "Djupafors Fabr AB",
                "startDate": "1908",
                "endDate": "1920"
            },
            {
                "@type": "Organization",
                "name": "AB Kraftintressenter",
                "startDate": "1920",
                "endDate": "1928"
            },
            {
                "@type": "Organization",
                "name": "Crompton & Ekström London",
                "startDate": "1928",
                "endDate": "1932"
            },
            {
                "@type": "Organization",
                "name": "Sikfors Kraft AB",
                "startDate": "1908"
            }
        ],
        "memberOf": [
            {
                "@type": "Organization",
                "name": "Mälaren Province Electric Power Company",
                "roleName": "Secretary",
                "startDate": "1923",
                "endDate": "1928"
            },
            {
                "@type": "Organization",
                "name": "National Rural Electrification Association",
                "roleName": "Secretary",
                "startDate": "1923",
                "endDate": "1928"
            },
            {
                "@type": "Organization",
                "name": "Electrification Committee",
                "roleName": "Member",
                "startDate": "1916",
                "endDate": "1922"
            }
        ],
        "awards": [
            {
                "@type": "Order",
                "name": "Royal Order of Vasa"
            },
            {
                "@type": "Order",
                "name": "Order of Léopold"
            },
            {
                "@type": "Order",
                "name": "Liva Medal"
            }
        ],
        "publication": [
            {
                "@type": "PublicationEvent",
                "name": "Modern Telecommunication Technology",
                "startDate": "1903",
                "coAuthor": [
                    {
                        "@type": "Person",
                        "name": "O. Harder"
                    },
                    {
                        "@type": "Person",
                        "name": "S. Lübeck"
                    }
                ]
            },
            {
                "@type": "PublicationEvent",
                "name": "Rural Electrification",
                "startDate": "1916",
                "coAuthor": []
            },
            {
                "@type": "PublicationEvent",
                "name": "Electrical Technology in Agriculture",
                "startDate": "1922",
                "coAuthor": []
            },
            {
                "@type": "PublicationEvent",
                "name": "Rural Electrification",
                "startDate": "1929",
                "coAuthor": [
                    {
                        "@type": "Person",
                        "name": "V. Ekström",
                        "locationCreated": "London"
                    }
                ]
            }
        ]
    },
    "occupations": {
        "career": [
            {
                "occupational_title": "Assistant in Electrical Engineering",
                "workplace": "Poly-technicums in Zurich",
                "industry": "Education",
                "start_date": "1898"
            },
            {
                "occupational_title": "Assistant in Physics",
                "workplace": "Kiel University",
                "industry": "Education",
                "start_date": "1899"
            },
            {
                "occupational_title": "Engineer",
                "workplace": "AB Telef.fabr in Stockholm",
                "industry": "Telecommunications",
                "start_date": "1899"
            },
            {
                "occupational_title": "Manager",
                "workplace": "AB Telef.fabr",
                "industry": "Telecommunications",
                "start_date": "1900"
            },
            {
                "occupational_title": "Engineer",
                "workplace": "AB L M Ericsson & Co",
                "industry": "Telecommunications",
                "start_date": "1901"
            },
            {
                "occupational_title": "Managing Director",
                "workplace": "Hemsjö KraftAB",
                "industry": "Energy",
                "start_date": "1906"
            },
            {
                "occupational_title": "Managing Director",
                "workplace": "Mörrumsströms KraftAB",
                "industry": "Energy",
                "start_date": "1906"
            },
            {
                "occupational_title": "Managing Director",
                "workplace": "AB A H Ekström",
                "industry": "Engineering",
                "start_date": "1906"
            },
            {
                "occupational_title": "Manager",
                "workplace": "Djupafors Fabr.AB",
                "industry": "Manufacturing",
                "start_date": "1908"
            },
            {
                "occupational_title": "Managing Director",
                "workplace": "AB Kraftintressenter",
                "industry": "Energy",
                "start_date": "1920"
            },
            {
                "occupational_title": "Managing Partner",
                "workplace": "Crompton & Ekström London",
                "industry": "Engineering",
                "start_date": "1928"
            }
        ]
    }
}