{
    "original": "HENKE, Hans Agne Jerker, Direktör, Nockeby, f Malmö 1/5 02 av gen.kons Hans E H o Esther Forsberg, gm Gunnel Velander. Saltsjöbad samsk, HHS Berlin. Resoffex 24, fänr Livg t h res 24, uljt 27, ljt Livreg t h res 28, ryttm 39. Anst AB Elektraverken fr 29, AB Osram-Elektrav sed. 30, dir sed. 32. Lett v.kons 38. Styr.led AB Feiths kaféer o kond:er 24—28, Sv frn Ljuskultur 37—41, Gropptorps marmor AB Katrineh sed. 37, styr.suppl AB Osr-Elektrav sed. 32, FERA sed. 37, ordf Frn 02 års män sed. 41, Osr-Elektrav IF sed. 32, Sthlms S hemv.frn sed. 43 (v. ordf 40—42), klubbm o skattm Sv-Lett frn Sthlm sed. 32, sekr 32—33 o sed. 41, klubbm KMK sed. 36, ordf dess volont.avd sed. 36 o komm f klubbangeläg sed. 41, kårch Salts jo -bad scoutk 23—27. Resor: Engl, Tyskl, Schweiz, Österr, Belg, Frankr, 24—29, USA 28, 29, 39. RVO, NyaSvM, LettRKHt, Off LettSO, Sy scoutfrbs ftJM o vita Ht, Osr.Elektrav IF ftJM g, skyt.m g, milit idr.m g, pist.skyt.m g, skidl.m s, simmarm g mm. °HENNEL, Per, Köpman, Kristianstad, f Linneryd, Kronob l, 29/1 87, gm Stina Lindbladh. Växjö hal. Aff.bitr i fma P J Karlssons Söner Skruv 05—18, deläg dna 19—29. övert Axel Ljungbergs spec.aff Krst und fma Per Hennel 29, inneh dna. Styr.led Skruvs Nya Glasbr AB, gr 10.",
    "translated": "HENKE, Hans Agne Jerker, Director, Nockeby, born in Malmö on May 1, 1902, son of General Consul Hans E H and Esther Forsberg, married to Gunnel Velander. Saltsjöbaden com. school, HHS Berlin. Reserve Officer 1924, Second Lieutenant in the Life Grenadier Regiment 1924, Lieutenant 1927, Lieutenant in the Life Regiment of Horse 1928, Captain 1939. Employed at AB Elektraverken since 1929, AB Osram-Elektrav since 1930, director since 1932. Consul of Latvia in 1938. Board member of AB Feith's coffeehouses and confectioneries 1924-1928, Swedish Association for Lighting Culture 1937-1941, Gropptorp's Marble AB in Katrineholm since 1937, board deputy of AB Osram-Elektrav since 1932, FERA since 1937, chairman of the 1902 Men's Association since 1941, Osram-Elektrav Sports Club since 1932, Stockholm Home Guard from 1943 (vice chairman 1940-1942), club member and treasurer of Swedish-Latvian Association from Stockholm since 1932, secretary 1932-1933 and since 1941, club member of the Royal Motorboat Club since 1936, chairman of its volunteer department since 1936 and local committee member for club matters since 1941, scout leader in Saltsjöbaden 1923-1927. Travel: England, Germany, Switzerland, Austria, Belgium, France 1924-1929, USA 1928, 1929, 1939. Recipient of the Royal Order of Vasa, Swedish-Norwegian Motor Association, Latvian Knight's Cross of the Order of the Cross of Terra Mariana, Officer of the Latvian Order of the Three Stars, Swedish Scout Federation's Silver Medal and White Star, Osram-Elektrav Sports Club's Gold Medal, shooting medal, military sports medal, pistol shooting medal, skiing medal, swimming medal, etc.\n\nHENNEL, Per, Merchant, Kristianstad, born in Linneryd, Kronoberg County on January 29, 1887, married to Stina Lindbladh. Shop assistant at P J Karlsson's Sons in Skruv 1905-1918, co-owner since 1919-1929. Took over Axel Ljungberg's specialty store in Kristianstad and became co-owner with Per Hennel in 1929. Board member of Skruvs Nya Glasbruk AB, founded in 1910.",
    "structured": {
        "@context": "https://schema.org",
        "@type": "Person",
        "name": "Hans Agne Jerker Henke",
        "birthDate": "1902-05-01",
        "birthPlace": "Malmö",
        "nationality": "Swedish",
        "parents": [
            {
                "@type": "Person",
                "name": "Hans E H Henke",
                "sameAs": "#father"
            },
            {
                "@type": "Person",
                "name": "Esther Forsberg",
                "sameAs": "#mother"
            }
        ],
        "spouse": {
            "@type": "Person",
            "name": "Gunnel Velander"
        },
        "education": {
            "@type": "EducationalOccupationalCredential",
            "credentialCategory": "diploma",
            "educationalLevel": "SecondaryEducation",
            "schoolName": "Saltsjöbaden Community School"
        },
        "additionalName": "Jerker",
        "worksFor": [
            {
                "@type": "Organization",
                "name": "AB Elektraverken",
                "startDate": "1929"
            },
            {
                "@type": "Organization",
                "name": "AB Osram-Elektrav",
                "startDate": "1930"
            }
        ],
        "occupation": "Director",
        "affiliations": [
            {
                "@type": "Organization",
                "name": "AB Feith's Coffeehouses and Confectioneries",
                "startDate": "1924",
                "endDate": "1928"
            },
            {
                "@type": "Organization",
                "name": "Swedish Association for Lighting Culture",
                "startDate": "1937",
                "endDate": "1941"
            },
            {
                "@type": "Organization",
                "name": "Gropptorp's Marble AB",
                "startDate": "1937"
            },
            {
                "@type": "Organization",
                "name": "AB Osram-Elektrav",
                "startDate": "1932",
                "roleName": "Board Deputy"
            },
            {
                "@type": "Organization",
                "name": "FERA",
                "startDate": "1937"
            },
            {
                "@type": "Organization",
                "name": "1902 Men's Association",
                "startDate": "1941",
                "roleName": "Chairman"
            },
            {
                "@type": "Organization",
                "name": "Osram-Elektrav Sports Club",
                "startDate": "1932",
                "roleName": "Chairman"
            },
            {
                "@type": "Organization",
                "name": "Stockholm Home Guard",
                "startDate": "1943",
                "endDate": "present",
                "roleName": "Vice Chairman"
            },
            {
                "@type": "Organization",
                "name": "Swedish-Latvian Association from Stockholm",
                "startDate": "1932",
                "roleName": "Club Member and Treasurer"
            },
            {
                "@type": "Organization",
                "name": "Royal Motorboat Club",
                "startDate": "1936",
                "roleName": "Club Member"
            }
        ],
        "description": "Hans Agne Jerker Henke was a Swedish Director. He was born on May 1, 1902, in Malmö. His parents were Hans E H Henke and Esther Forsberg. He was married to Gunnel Velander. Hans Agne Jerker Henke attended Saltsjöbaden Community School for his secondary education. He worked as a Director for AB Elektraverken starting in 1929 and for AB Osram-Elektrav starting in 1930. Throughout his career, he was affiliated with various organizations, including AB Feith's Coffeehouses and Confectioneries (1924-1928), Swedish Association for Lighting Culture (1937-1941), Gropptorp's Marble AB (1937-present), AB Osram-Elektrav (1932-present), FERA (1937-present), 1902 Men's Association (1941-present), Osram-Elektrav Sports Club (1932-present), Stockholm Home Guard (1943-present), Swedish-Latvian Association from Stockholm (1932-present), and Royal Motorboat Club (1936-present).",
        "awards": [
            {
                "@type": "Order",
                "name": "Royal Order of Vasa",
                "year": "Unknown"
            },
            {
                "@type": "Order",
                "name": "Swedish-Norwegian Motor Association",
                "year": "Unknown"
            },
            {
                "@type": "Order",
                "name": "Latvian Knight's Cross of the Order of the Cross of Terra Mariana",
                "year": "Unknown"
            },
            {
                "@type": "Order",
                "name": "Officer of the Latvian Order of the Three Stars",
                "year": "Unknown"
            },
            {
                "@type": "Medal",
                "name": "Swedish Scout Federation's Silver Medal",
                "year": "Unknown"
            },
            {
                "@type": "Medal",
                "name": "White Star",
                "year": "Unknown"
            },
            {
                "@type": "Medal",
                "name": "Osram-Elektrav Sports Club's Gold Medal",
                "year": "Unknown"
            }
        ],
        "memberOf": [
            {
                "@type": "SportsTeam",
                "name": "Saltsjöbaden Scout Group",
                "startDate": "1923",
                "endDate": "1927"
            }
        ],
        "additionalProperty": [
            {
                "@type": "Property",
                "name": "Reserve Officer",
                "value": "1924"
            },
            {
                "@type": "Property",
                "name": "Second Lieutenant",
                "value": "1924"
            },
            {
                "@type": "Property",
                "name": "Lieutenant",
                "value": "1927"
            },
            {
                "@type": "Property",
                "name": "Captain",
                "value": "1939"
            }
        ]
    },
    "occupations": {
        "career": [
            {
                "occupational_title": "Director",
                "workplace": "AB Elektraverken",
                "industry": "Electrical",
                "start_date": "1929"
            },
            {
                "occupational_title": "Director",
                "workplace": "AB Osram-Elektrav",
                "industry": "Electrical",
                "start_date": "1932"
            },
            {
                "occupational_title": "Consul",
                "workplace": "Latvia",
                "industry": "Diplomacy",
                "start_date": "1938"
            },
            {
                "occupational_title": "Board member",
                "workplace": "AB Feith's coffeehouses and confectioneries",
                "industry": "Hospitality",
                "start_date": "1924"
            },
            {
                "occupational_title": "Board member",
                "workplace": "Swedish Association for Lighting Culture",
                "industry": "Lighting",
                "start_date": "1937"
            },
            {
                "occupational_title": "Board member",
                "workplace": "Gropptorp's Marble AB",
                "industry": "Marble",
                "start_date": "1937"
            },
            {
                "occupational_title": "Board deputy",
                "workplace": "AB Osram-Elektrav",
                "industry": "Electrical",
                "start_date": "1932"
            },
            {
                "occupational_title": "Board deputy",
                "workplace": "FERA",
                "industry": "Unknown",
                "start_date": "1937"
            },
            {
                "occupational_title": "Chairman",
                "workplace": "1902 Men's Association",
                "industry": "Unknown",
                "start_date": "1941"
            },
            {
                "occupational_title": "Chairman",
                "workplace": "Osram-Elektrav Sports Club",
                "industry": "Sports",
                "start_date": "1932"
            },
            {
                "occupational_title": "Vice Chairman",
                "workplace": "Stockholm Home Guard",
                "industry": "Military",
                "start_date": "1940"
            },
            {
                "occupational_title": "Club member and treasurer",
                "workplace": "Swedish-Latvian Association",
                "industry": "Unknown",
                "start_date": "1932"
            },
            {
                "occupational_title": "Scout leader",
                "workplace": "Saltsjöbaden",
                "industry": "Scouting",
                "start_date": "1923"
            },
            {
                "occupational_title": "Shop assistant",
                "workplace": "P J Karlsson's Sons",
                "industry": "Retail",
                "start_date": "1905"
            },
            {
                "occupational_title": "Co-owner",
                "workplace": "Axel Ljungberg's specialty store",
                "industry": "Retail",
                "start_date": "1929"
            },
            {
                "occupational_title": "Co-owner",
                "workplace": "Per Hennel",
                "industry": "Retail",
                "start_date": "1929"
            },
            {
                "occupational_title": "Board member",
                "workplace": "Skruvs Nya Glasbruk AB",
                "industry": "Manufacturing",
                "start_date": "1910"
            }
        ]
    }
}