{
    "original": "HANSON, Karl Johan, Disponent, Karlshamn, f Gbg 13/8 83 av v.värden L H o Justina Hansson, gm Signe Åhström. 5 kl lärov. Anst öl el fmor 99—08, disp El AB Hj. Smith 09—25. Inneh eg el installat- o gross.fma, Karl Hanson El AB, Khn, sed. 25, vkst dir dta. Ag fastigh Kullavik, Hällaryd, Blek. V. ordf stdsflm o hamndir; ordf Khns hdlsfrn o högerfrn, v. ordf Blek luftsk.frb, ordf ds arb.utsk, ordf Khns scoutkårsråd, styr.led Tekn frn Kkrona, El-entrep.frns östra krets mfl. RVO; riksluftsk.frbs o Sv köpm.frbs ftjt g, Scoutfrbs Förbundslilja, Städ brand-stodsbol:s M f »Mod i fara o medborg nit», FinlM 39—40; Odd Fellow. Hobbies: Segling, fiske.",
    "translated": "HANSON, Karl Johan, Manager, Karlshamn, born in Gothenburg on August 13, 1883, son of a retired military officer, L H, and Justina Hansson, married to Signe Åhström. Completed 5 years of primary education. Employed at a brewery or distillery from 1899 to 1908, then worked as a manager at El AB Hj. Smith from 1909 to 1925. Became the owner of his own electrical installation and wholesale company, Karl Hanson El AB, in Karlshamn since 1925, and currently serves as the company's director of operations. Also involved in various positions such as vice chairman of the local film society and harbor director, chairman of the Karlshamn's Chamber of Commerce and the conservative party, vice chairman of the Blekinge Air Association, chairman of the local work committee, chairman of the Karlshamn scout corps council, and board member of the Technical Association in Karlskrona, the eastern district of the Electrical Contractor Association, and more. Awarded the Order of Vasa (RVO). Member of the national air force association and the Swedish Chamber of Commerce. Received the Scout Association's \"Förbundslilja\" (Federation Lily) and the City Fire Support Company's Medal of \"Mod i fara o medborg nit\" (\"Courage in Danger and Civic Zeal\"). Served as a Finnish military officer from 1939 to 1940. Also a member of the Odd Fellow society. Hobbies include sailing and fishing.",
    "structured": {
        "@context": "https://schema.org",
        "@type": "Person",
        "name": "Karl Johan Hanson",
        "jobTitle": "Manager",
        "birthPlace": "Gothenburg",
        "birthDate": "1883-08-13",
        "father": {
            "@type": "Person",
            "name": "L H Hanson",
            "jobTitle": "Retired Military Officer"
        },
        "mother": {
            "@type": "Person",
            "name": "Justina Hansson"
        },
        "spouse": {
            "@type": "Person",
            "name": "Signe Åhström"
        },
        "education": {
            "@type": "EducationalOccupationalCredential",
            "name": "5 years of primary education"
        },
        "employmentHistory": [
            {
                "@type": "Organization",
                "name": "Brewery or Distillery",
                "startDate": "1899",
                "endDate": "1908"
            },
            {
                "@type": "Organization",
                "name": "El AB Hj. Smith",
                "startDate": "1909",
                "endDate": "1925",
                "jobTitle": "Manager"
            },
            {
                "@type": "Organization",
                "name": "Karl Hanson El AB",
                "location": "Karlshamn",
                "startDate": "1925",
                "jobTitle": "Owner",
                "director": "Karl Johan Hanson"
            }
        ],
        "additionalProperty": [
            {
                "@type": "PropertyValue",
                "name": "Hobbies",
                "value": "Sailing, Fishing"
            }
        ],
        "memberOf": [
            {
                "@type": "Organization",
                "name": "Local Film Society",
                "position": "Vice Chairman"
            },
            {
                "@type": "Organization",
                "name": "Harbor",
                "position": "Director"
            },
            {
                "@type": "Organization",
                "name": "Karlshamn's Chamber of Commerce",
                "position": "Chairman"
            },
            {
                "@type": "Organization",
                "name": "Conservative Party",
                "position": "Chairman"
            },
            {
                "@type": "Organization",
                "name": "Blekinge Air Association",
                "position": "Vice Chairman"
            },
            {
                "@type": "Organization",
                "name": "Local Work Committee",
                "position": "Chairman"
            },
            {
                "@type": "Organization",
                "name": "Karlshamn Scout Corps Council",
                "position": "Chairman"
            },
            {
                "@type": "Organization",
                "name": "Technical Association in Karlskrona",
                "position": "Board Member"
            },
            {
                "@type": "Organization",
                "name": "Eastern District of the Electrical Contractor Association",
                "position": "Board Member"
            }
        ],
        "awards": [
            {
                "@type": "Order",
                "name": "Order of Vasa (RVO)"
            },
            {
                "@type": "Organization",
                "name": "National Air Force Association",
                "position": "Member"
            },
            {
                "@type": "Organization",
                "name": "Swedish Chamber of Commerce",
                "position": "Member"
            },
            {
                "@type": "Organization",
                "name": "Scout Association",
                "award": "Federation Lily"
            },
            {
                "@type": "Organization",
                "name": "City Fire Support Company",
                "award": "Medal of Courage in Danger and Civic Zeal"
            }
        ],
        "worksFor": "Karl Hanson El AB",
        "finnishMilitaryService": {
            "@type": "MilitaryService",
            "startDate": "1939",
            "endDate": "1940"
        },
        "societies": {
            "@type": "Organization",
            "name": "Odd Fellow",
            "position": "Member"
        }
    },
    "occupations": {
        "career": [
            {
                "occupational_title": "Employee",
                "workplace": "Brewery or Distillery",
                "industry": "Alcohol Industry",
                "start_date": "1899"
            },
            {
                "occupational_title": "Manager",
                "workplace": "El AB Hj. Smith",
                "industry": "Electrical Company",
                "start_date": "1909"
            },
            {
                "occupational_title": "Owner",
                "workplace": "Karl Hanson El AB",
                "industry": "Electrical Installation and Wholesale",
                "start_date": "1925"
            },
            {
                "occupational_title": "Director of Operations",
                "workplace": "Karl Hanson El AB",
                "industry": "Electrical Installation and Wholesale",
                "start_date": "N/A"
            }
        ]
    }
}