{
    "original": "ALMGREN, Arvid Gustaf-Adolf, Civilingenjör, Krångede, f Åtvid, Ögl, 6/11 02 av distr.-veter A K F A o Hilma Ehrling, gm Märta Unger. Studex Lund 21, CTI (V o V) 21—25. Anst h Kreuger &amp; Tolls Byggn.AB 25—32 (bl a ing v Hammarforsens kraftvksbyggn, Årsta-bron, Månsbo kraftvksbyggn o östrands sul-fatfabr:s pumpstnsbyggn), anst Slussbyggn.-ktén Sthlm 32—34, AB Fundament 34—36, (arb.ch v dammbyggn f Storavans regl), Sv Entreprenad AB 36—40 (avd.ing v Kegums kraftvksbyggn i Lettl), anst i Krångede AB sed. 44 ss arb.ch f Krångede o Gammelänge v kraftvksbyggn. Led Sv Tekn.frn. Resor: Polen, Tjeckoslov, Österr, Tyskl 38, Norge 39. Hobbies: Skytte, friluftsliv.",
    "translated": "ALMGREN, Arvid Gustaf-Adolf, Civil Engineer, Krångede, born in Åtvid, Ögl, on November 6th, 1902, son of the district veterinarian A K F A and Hilma Ehrling, married to Märta Unger. Studied at Lund University and graduated in 1921. CTI (V o V) from 1921 to 1925. Employed at Kreuger & Tolls Construction AB from 1925 to 1932, involved in various engineering projects such as the construction of the Hammarforsens power plant, Årsta Bridge, Månsbo power plant, and the pumping station of the Östrand sulfuric acid factory. Employed at Slussbyggnadsaktiebolaget in Stockholm from 1932 to 1934, then at AB Fundament from 1934 to 1936, where he worked on the construction of the Storavan reservoir dam. Employed at Svensk Entreprenad AB from 1936 to 1940, working as a department engineer on the construction of Kegums power plant in Latvia. Employed at Krångede AB since 1944, primarily working on the construction of Krångede and Gammelänge power plants. Member of the Swedish Technical Association. Traveled to Poland, Czechoslovakia, Austria, Germany in 1938, and Norway in 1939. Hobbies include shooting and outdoor activities.",
    "structured": {
        "@context": "https://schema.org",
        "@type": "Person",
        "name": "Arvid Gustaf-Adolf Almgren",
        "birthDate": "1902-11-06",
        "birthPlace": "Åtvid, Ögl",
        "description": "Civil Engineer",
        "parents": [
            {
                "@type": "Person",
                "name": "A K F A",
                "description": "District Veterinarian"
            },
            {
                "@type": "Person",
                "name": "Hilma Ehrling"
            }
        ],
        "spouse": {
            "@type": "Person",
            "name": "Märta Unger"
        },
        "education": {
            "@type": "EducationalOccupationalCredential",
            "credentialCategory": "degree",
            "educationalLevel": "Bachelor's Degree",
            "alumniOf": {
                "@type": "CollegeOrUniversity",
                "name": "Lund University"
            },
            "startDate": "1921",
            "endDate": "1921"
        },
        "work": [
            {
                "@type": "Organization",
                "name": "Kreuger & Tolls Byggn.AB",
                "startDate": "1925",
                "endDate": "1932",
                "jobTitle": "Civil Engineer",
                "description": "Involved in various engineering projects such as the construction of the Hammarforsens power plant, Årsta Bridge, Månsbo power plant, and the pumping station of the Östrand sulfuric acid factory."
            },
            {
                "@type": "Organization",
                "name": "Slussbyggn.-ktén Sthlm",
                "startDate": "1932",
                "endDate": "1934",
                "jobTitle": "Civil Engineer"
            },
            {
                "@type": "Organization",
                "name": "AB Fundament",
                "startDate": "1934",
                "endDate": "1936",
                "jobTitle": "Civil Engineer",
                "description": "Worked on the construction of the Storavan reservoir dam."
            },
            {
                "@type": "Organization",
                "name": "Sv Entreprenad AB",
                "startDate": "1936",
                "endDate": "1940",
                "jobTitle": "Department Engineer",
                "description": "Worked on the construction of Kegums power plant in Latvia."
            },
            {
                "@type": "Organization",
                "name": "Krångede AB",
                "startDate": "1944",
                "jobTitle": "Civil Engineer",
                "description": "Primarily worked on the construction of Krångede and Gammelänge power plants."
            }
        ],
        "memberOf": {
            "@type": "Organization",
            "name": "Swedish Technical Association"
        },
        "birthPlaceObj": {
            "@type": "Place",
            "address": {
                "@type": "PostalAddress",
                "addressLocality": "Åtvid",
                "addressRegion": "Ögl"
            }
        },
        "spouseObj": {
            "@type": "Person",
            "name": "Märta Unger"
        },
        "hobbies": [
            "Shooting",
            "Outdoor activities"
        ],
        "travelHistory": [
            {
                "@type": "Place",
                "address": {
                    "@type": "PostalAddress",
                    "addressCountry": "Poland"
                }
            },
            {
                "@type": "Place",
                "address": {
                    "@type": "PostalAddress",
                    "addressCountry": "Czechoslovakia"
                }
            },
            {
                "@type": "Place",
                "address": {
                    "@type": "PostalAddress",
                    "addressCountry": "Austria"
                }
            },
            {
                "@type": "Place",
                "address": {
                    "@type": "PostalAddress",
                    "addressCountry": "Germany"
                }
            },
            {
                "@type": "Place",
                "address": {
                    "@type": "PostalAddress",
                    "addressCountry": "Norway"
                }
            }
        ]
    },
    "occupations": {
        "career": [
            {
                "occupational_title": "Civil Engineer",
                "workplace": "Kreuger & Tolls Byggn.AB",
                "industry": "Construction",
                "start_date": "1925"
            },
            {
                "occupational_title": "Engineer",
                "workplace": "Slussbyggn.-ktén Sthlm",
                "industry": "Construction",
                "start_date": "1932"
            },
            {
                "occupational_title": "Engineer",
                "workplace": "AB Fundament",
                "industry": "Construction",
                "start_date": "1934"
            },
            {
                "occupational_title": "Department Engineer",
                "workplace": "Sv Entreprenad AB",
                "industry": "Construction",
                "start_date": "1936"
            },
            {
                "occupational_title": "Employee",
                "workplace": "Krångede AB",
                "industry": "Construction",
                "start_date": "1944"
            }
        ]
    }
}