{
    "original": "LAGERMAN, Carl Gösta, Revisor, Stockholm, f Lommaryd, Jönkp l, 19/9 07 av major K V L o Märta Ärnström, gm Gurli Roosval. Studex Whitlockska samsk, DHS, besparings-beredn kurs i kont.org 42. Anst Försäkr AB Fylgia 2(&gt;—27, sekr gen.kommiss f Sv utst Barcelona 29, korresp Rodamientos a Bolas SKF, S A, Barcelona 30, rev.ass h aukt revisorn, professor O Sillen, Sthlm, 30—40, av Sthlms handelskannn aukt rev sed. 33, led Frn Aukt Rev sed. 35, eg fma C G Lagermans Revisionsbyrå Sthlm sed. 40. Bitr v utarb av förslag t omorg av Sv Riksbk 41—42, kont.-org.uppdr f Sthlms stads sjukhusdirekt o Arméförvaltn tygdep 42, rev Djursholms etad sed. 35. Resor: Spanien 29—30, USA (stud rev ss Sv-Amer.stift El-Luxetip) 37, Turkiet 37. Av trycket: Kurs i rev.tekn f Hermods (33), enl uppdr av Frn Aukt Rev utarb kurs i rev.-tekn f ass h aukt rev 38—39 (ej tryckt). Skid-f ram j SM.",
    "translated": "LAGERMAN, Carl Gösta, Auditor, Stockholm, b. Lommaryd, Jönköping county, 19/9 1907, son of Major K V L and Märta Ärnström, m. Gurli Roosval. Graduated from Whitlock Samsk, DHS, savings committee course in accounting 1942. Employed at Försäkr AB Fylgia 1927-1927, secretary of the General Commission for Swedish exhibitions in Barcelona 1929, correspondent for Rodamientos a Bolas SKF, S A, Barcelona 1930, assistant to the auction auditor, Professor O Sillen, Stockholm, 1930-1940, member of the Stockholm Chamber of Commerce as an authorized auditor since 1933, member of From Authorized Auditors since 1935, owner of C G Lagerman's Audit Office in Stockholm since 1940. Assisted in the preparation of proposals for the Swedish central bank 1941-1942, accounting organization mission for the Stockholm city hospital director and Army administration clothing depot 1942, auditor for Djursholm etad since 1935. Travel: Spain 1929-1930, USA (study trip as part of the Swedish-American Foundation for Electric Lighting) 1937, Turkey 1937. Published: Course in audit technique for Hermods (1933), prepared a course in audit technique for the assistant to the auction auditor 1938-1939 (not published). Skiing champion in the Swedish Championship.",
    "structured": {
        "@context": "https://schema.org",
        "@type": "Person",
        "givenName": "Carl Gösta",
        "familyName": "Lagerman",
        "jobTitle": "Auditor",
        "address": {
            "@type": "PostalAddress",
            "addressLocality": "Stockholm"
        },
        "birthDate": "1907-09-19",
        "birthPlace": "Lommaryd, Jönköping county",
        "parents": [
            {
                "@type": "Person",
                "givenName": "K",
                "additionalName": "V",
                "familyName": "L"
            },
            {
                "@type": "Person",
                "givenName": "Märta",
                "familyName": "Ärnström"
            }
        ],
        "spouse": {
            "@type": "Person",
            "givenName": "Gurli",
            "familyName": "Roosval"
        },
        "education": [
            {
                "@type": "EducationalOccupationalCredential",
                "credentialCategory": "Graduate",
                "alumniOf": {
                    "@type": "Organization",
                    "name": "Whitlock Samsk"
                }
            },
            {
                "@type": "EducationalOccupationalCredential",
                "credentialCategory": "DiplomaDegree",
                "alumniOf": {
                    "@type": "Organization",
                    "name": "DHS"
                }
            },
            {
                "@type": "EducationalOccupationalCredential",
                "credentialCategory": "Certification",
                "description": "Savings committee course in accounting"
            }
        ],
        "worksFor": [
            {
                "@type": "Organization",
                "name": "Försäkr AB Fylgia",
                "startDate": "1927",
                "endDate": "1927"
            },
            {
                "@type": "Organization",
                "name": "General Commission for Swedish exhibitions in Barcelona",
                "startDate": "1929"
            },
            {
                "@type": "Organization",
                "name": "Rodamientos a Bolas SKF, S A",
                "startDate": "1930",
                "location": "Barcelona"
            },
            {
                "@type": "Organization",
                "name": "C G Lagerman's Audit Office",
                "startDate": "1940",
                "location": "Stockholm"
            }
        ],
        "partOf": [
            {
                "@type": "Organization",
                "name": "Stockholm Chamber of Commerce",
                "membershipStartDate": "1933",
                "roleName": "Authorized Auditor"
            },
            {
                "@type": "Organization",
                "name": "From Authorized Auditors",
                "membershipStartDate": "1935"
            }
        ],
        "assistantTo": [
            {
                "@type": "Person",
                "givenName": "O",
                "familyName": "Sillen",
                "jobTitle": "Professor",
                "worksFor": {
                    "@type": "Organization",
                    "name": "Stockholm"
                },
                "startDate": "1930",
                "endDate": "1940"
            }
        ],
        "event": [
            {
                "@type": "Event",
                "name": "Swedish Championship",
                "startDate": "unspecified"
            }
        ],
        "relatedTo": [
            {
                "@type": "Person",
                "givenName": "Gurli",
                "familyName": "Roosval"
            }
        ],
        "sameAs": [
            "https://example.com/carl-gosta-lagerman"
        ]
    },
    "occupations": {
        "career": [
            {
                "occupational_title": "Auditor",
                "workplace": "Försäkr AB Fylgia",
                "industry": "Insurance",
                "start_date": "1927"
            },
            {
                "occupational_title": "Secretary",
                "workplace": "General Commission for Swedish exhibitions",
                "industry": "Event organization",
                "start_date": "1929"
            },
            {
                "occupational_title": "Correspondent",
                "workplace": "Rodamientos a Bolas SKF, S A",
                "industry": "Manufacturing (Ball bearings)",
                "start_date": "1930"
            },
            {
                "occupational_title": "Assistant to the auction auditor",
                "workplace": "Professor O Sillen",
                "industry": "Education",
                "start_date": "1930"
            },
            {
                "occupational_title": "Authorized Auditor",
                "workplace": "Stockholm Chamber of Commerce",
                "industry": "Finance",
                "start_date": "1933"
            },
            {
                "occupational_title": "Member",
                "workplace": "From Authorized Auditors",
                "industry": "Finance",
                "start_date": "1935"
            },
            {
                "occupational_title": "Owner",
                "workplace": "C G Lagerman's Audit Office",
                "industry": "Finance",
                "start_date": "1940"
            },
            {
                "occupational_title": "Preparation Assistant",
                "workplace": "Swedish central bank",
                "industry": "Government",
                "start_date": "1941"
            },
            {
                "occupational_title": "Accounting Organization Mission",
                "workplace": "Stockholm city hospital director",
                "industry": "Healthcare",
                "start_date": "1942"
            },
            {
                "occupational_title": "Auditor",
                "workplace": "Djursholm etad",
                "industry": "Finance",
                "start_date": "1935"
            }
        ]
    }
}