{
    "original": "ENGBERG, Nils Fredrik, Direktör, Kristianstad, f 19/3 82 i Nrkp av grhdl A E o Albertina Jonsson, gm Maja Göransson. Tekn Elem.sk Nrkp, vävsk Werdau, Sachsen, prakt v textilfabr Tyskl. Vävmäst v Ströms AB Nrkp 03—04, dessinatör Asp Yllefabr Mta 05— 08, fabr.ch AB Skånska Yllefabr Krst 08—12, ch 0 vkst dir sed. 12. Led Priskontr.nämndens råd, sakk där o i Industrikomm textilavd, led Länsarb.nämnden; Styr.ordf Sv Yllefabr.-frn v. ordf Sv Textilind.frb överstyr, ordf dess S:a Krets, v. ordf Sv Ylleimp.frn o Ylleind.frn, styr.led Sv Ind.frb, AB Sk Yllefabr o AB Cellull Älvenäs, Grums, styr.suppl Sv Arb.giv.frn o AB Mårten Pehrsons Valsqvarn, medl Textilrådet. KVO2kl, FinlVRO; ordf Krst Golfklubb. Hobbies: Golf mfl",
    "translated": "ENGBERG, Nils Fredrik, Director, Kristianstad, b. 19/3 82 in Nrkp (Norrköping) to parents A E and Albertina Jonsson, m. (married) to Maja Göransson. Technical Elementary School in Nrkp, weaver in Werdau, Saxony, practical experience in textile factory in Germany. Master weaver at Ströms AB Nrkp from 03-04, designer at Asp Yllefabr Mta from 05-08, factory manager at AB Skånska Yllefabr Krst from 08-12, and managing director since 12. Member of the Prize Contract Committee, expert in the Textile Department of the Industrial Committee, member of the County Labor Committee; Chairman of the Board of Swedish Yllefabr.-frn, Vice Chairman of the Swedish Textile Industry Association, Chairman of its South District, Vice Chairman of the Swedish Wool Import Association and the Wool Industry Association, board member of the Swedish Industry Association, AB Sk Yllefabr, and AB Cellull Älvenäs, Grums, supervisory board member of the Swedish Employers' Association and AB Mårten Pehrsons Valsqvarn, and a member of the Textile Council. Knight of the Royal Order of the Second Class (KVO2kl), Order of the White Rose of Finland (FinlVRO); Chairman of Krst Golf Club. Hobbies: Golf and others.",
    "structured": {
        "@context": "https://schema.org",
        "@type": "Person",
        "name": "Nils Fredrik Engberg",
        "jobTitle": "Director",
        "birthDate": "1882-03-19",
        "birthPlace": "Norrköping",
        "parents": [
            {
                "@type": "Person",
                "name": "A E Engberg"
            },
            {
                "@type": "Person",
                "name": "Albertina Jonsson"
            }
        ],
        "spouse": {
            "@type": "Person",
            "name": "Maja Göransson"
        },
        "education": [
            {
                "@type": "EducationalOccupationalCredential",
                "credentialCategory": "Technical Elementary School"
            }
        ],
        "work": [
            {
                "@type": "JobPosting",
                "title": "Master weaver",
                "startDate": "1903-01-01",
                "endDate": "1904-12-31",
                "employer": "Ströms AB",
                "location": "Norrköping"
            },
            {
                "@type": "JobPosting",
                "title": "Designer",
                "startDate": "1905-01-01",
                "endDate": "1908-12-31",
                "employer": "Asp Yllefabr Mta",
                "location": "Unknown"
            },
            {
                "@type": "JobPosting",
                "title": "Factory Manager",
                "startDate": "1908-01-01",
                "endDate": "1912-12-31",
                "employer": "AB Skånska Yllefabr",
                "location": "Kristianstad"
            },
            {
                "@type": "JobPosting",
                "title": "Managing Director",
                "startDate": "1912-01-01",
                "employer": "AB Skånska Yllefabr",
                "location": "Kristianstad"
            }
        ],
        "memberOf": [
            {
                "@type": "Organization",
                "name": "Prize Contract Committee"
            },
            {
                "@type": "Organization",
                "name": "Industrial Committee",
                "department": "Textile Department"
            },
            {
                "@type": "Organization",
                "name": "County Labor Committee"
            },
            {
                "@type": "Organization",
                "name": "Swedish Yllefabr.-frn",
                "roleName": "Chairman of the Board"
            },
            {
                "@type": "Organization",
                "name": "Swedish Textile Industry Association",
                "roleName": "Vice Chairman"
            },
            {
                "@type": "Organization",
                "name": "Swedish Wool Import Association",
                "roleName": "Vice Chairman"
            },
            {
                "@type": "Organization",
                "name": "Wool Industry Association",
                "roleName": "Vice Chairman"
            },
            {
                "@type": "Organization",
                "name": "Swedish Industry Association",
                "roleName": "Board Member"
            },
            {
                "@type": "Organization",
                "name": "AB Sk Yllefabr",
                "roleName": "Board Member"
            },
            {
                "@type": "Organization",
                "name": "AB Cellull Älvenäs",
                "roleName": "Board Member"
            },
            {
                "@type": "Organization",
                "name": "Swedish Employers' Association",
                "roleName": "Supervisory Board Member"
            },
            {
                "@type": "Organization",
                "name": "AB Mårten Pehrsons Valsqvarn",
                "roleName": "Supervisory Board Member"
            },
            {
                "@type": "Organization",
                "name": "Textile Council",
                "roleName": "Member"
            }
        ],
        "honorificSuffix": "KVO2kl, FinlVRO",
        "memberOfKrstGolfClub": {
            "@type": "Organization",
            "name": "Krst Golf Club",
            "roleName": "Chairman"
        },
        "additionalName": "Fredrik",
        "hasOccupation": {
            "@type": "Occupation",
            "name": "Golfer"
        }
    },
    "occupations": {
        "career": [
            {
                "occupational_title": "Master weaver",
                "workplace": "Ströms AB Nrkp",
                "industry": "Textile",
                "start_date": "1903"
            },
            {
                "occupational_title": "Designer",
                "workplace": "Asp Yllefabr Mta",
                "industry": "Textile",
                "start_date": "1905"
            },
            {
                "occupational_title": "Factory manager",
                "workplace": "AB Skånska Yllefabr Krst",
                "industry": "Textile",
                "start_date": "1908"
            },
            {
                "occupational_title": "Managing director",
                "workplace": "AB Skånska Yllefabr Krst",
                "industry": "Textile",
                "start_date": "1912"
            }
        ]
    }
}