{
    "original": "GAVELIN, Axel Olof, överdirektör, Djursholm, f Vilhelmina, Västerb, 4/10 75 av lantbr Nils G o Kristina Forsbom, gm (2) Anna-Greta Högland. Studex Umeå 96, fil kand Upps 99, fil lic 03, fil dr 05. Bitr geol v Sv geol undersökn 02, statsgeol 03, tf ch 14, överdir 16—41. Sekr geol frn o red av dess förhandl 14—16, ordf 17—24 o sed. 41, led komm f de allm kartarb sed. 14, styr f stat meteor-hydrogr anst sed. 18, styr f skogs-högsk o stat skogsförsäkr.anst sed. 28, sv nät.komm f geodesi o geofys, fd ordf sv na-turskyddsfrn, styr.led sv sällsk f antrop o geogr, Vassijaure naturvet stn, Nobelstift sed. 34, medl 38 års utredn ang utnyttj av kronans malmfyndigh i Västerb. Res f veten-skapl el prakt utredn t Finl, Norge, Danm, Engl, Tyskl, Holl, Schweiz, Ital, Frankr uppr ggr, Span 26, Afr 29. Av trycket: Ett 100-t avhandl i geol, geogr o prakt fråg, spec malmfråg, tidskr- o tidn-upps mm. KNOlkl, KVOlkl, LVA, LLA, HedLIVA, LFS; Idun, PB, S:t örjans Gille mfl.",
    "translated": "GAVELIN, Axel Olof, Senior Director, Djursholm, born in Vilhelmina, Västerbotten, on October 4, 1875, son of farmer Nils G and Kristina Forsbom, married (2) Anna-Greta Högland. Graduated Umeå 1896, Bachelor of Arts Uppsala 1899, Licentiate in Philosophy 1903, Doctor of Philosophy 1905. Assistant Geologist at the Swedish Geological Survey 1902, State Geologist 1903, Acting Head 1914, Senior Director 1916-1941. Secretary of the Geological Society and editor of its proceedings 1914-1916, Chairman 1917-1924, and since 1941, member of the committee for general cartography since 1914, board member of the State Meteorological-Hydrographic Institution since 1918, board member of the Forestry University and State Forestry Insurance Institution since 1928, Swedish National Committee for Geodesy and Geophysics, former Chairman of the Swedish Nature Conservation Association, board member of the Swedish Society for Anthropology and Geography, Vassijaure Natural Science Station, Nobel Foundation since 1934, member of the 1938 investigation concerning the utilization of the Crown's mineral resources in Västerbotten. Conducted scientific and practical investigations in Finland, Norway, Denmark, England, Germany, the Netherlands, Switzerland, Italy, France, Spain in 1926 and Africa in 1929. Published around 100 papers on geology, geography, and practical issues, specifically regarding ore matters, in various journals and newspapers, etc. Knight of the Order of the North Star, Knight of the Order of Vasa, Member of the Royal Swedish Academy of Agriculture and Forestry, Member of the Royal Swedish Society of Naval Sciences, Member of the Gothenburg Geographical Society, among others. Please note that the abbreviations KNOlkl, KVOlkl, LVA, LLA, HedLIVA, LFS; Idun, PB, S:t örjans Gille mfl. refer to various memberships and honors.",
    "structured": {
        "@context": "https://schema.org",
        "@type": "Person",
        "name": "Axel Olof GAVELIN",
        "givenName": "Axel",
        "additionalName": "Olof",
        "familyName": "GAVELIN",
        "birthDate": "1875-10-04",
        "birthPlace": {
            "@type": "Place",
            "name": "Vilhelmina, Västerbotten"
        },
        "deathDate": "",
        "nationality": "Swedish",
        "description": "Senior Director",
        "father": {
            "@type": "Person",
            "name": "Nils GAVELIN",
            "occupation": "Farmer"
        },
        "mother": {
            "@type": "Person",
            "name": "Kristina Forsbom",
            "occupation": "Unknown"
        },
        "spouse": [
            {
                "@type": "Person",
                "name": "Anna-Greta Högland",
                "gender": "female",
                "marriageDate": ""
            }
        ],
        "education": [
            {
                "@type": "EducationalOccupationalCredential",
                "name": "Studex",
                "educationalLevel": "High School Diploma",
                "educationalCredentialAwarded": "Umeå 96"
            },
            {
                "@type": "EducationalOccupationalCredential",
                "name": "Bachelor of Arts",
                "educationalLevel": "Bachelor's Degree",
                "educationalCredentialAwarded": "Uppsala 99"
            },
            {
                "@type": "EducationalOccupationalCredential",
                "name": "Licentiate in Philosophy",
                "educationalLevel": "Master's Degree",
                "educationalCredentialAwarded": "1903"
            },
            {
                "@type": "EducationalOccupationalCredential",
                "name": "Doctor of Philosophy",
                "educationalLevel": "Doctorate",
                "educationalCredentialAwarded": "1905"
            }
        ],
        "employmentHistory": [
            {
                "@type": "OrganizationRole",
                "name": "Assistant Geologist",
                "startDate": "1902",
                "endDate": ""
            },
            {
                "@type": "OrganizationRole",
                "name": "State Geologist",
                "startDate": "1903",
                "endDate": ""
            },
            {
                "@type": "OrganizationRole",
                "name": "Acting Head",
                "startDate": "1914",
                "endDate": ""
            },
            {
                "@type": "OrganizationRole",
                "name": "Senior Director",
                "startDate": "1916",
                "endDate": "1941"
            }
        ],
        "memberOf": [
            {
                "@type": "Organization",
                "name": "Geological Society"
            },
            {
                "@type": "Organization",
                "name": "Swedish Nature Conservation Association",
                "position": "Former Chairman"
            },
            {
                "@type": "Organization",
                "name": "Swedish Society for Anthropology and Geography",
                "position": "Board Member"
            },
            {
                "@type": "Organization",
                "name": "Vassijaure Natural Science Station"
            },
            {
                "@type": "Organization",
                "name": "Nobel Foundation",
                "startDate": "1934"
            },
            {
                "@type": "Organization",
                "name": "Swedish National Committee for Geodesy and Geophysics"
            },
            {
                "@type": "Organization",
                "name": "State Meteorological-Hydrographic Institution",
                "startDate": "1918"
            },
            {
                "@type": "Organization",
                "name": "Forestry University"
            },
            {
                "@type": "Organization",
                "name": "State Forestry Insurance Institution",
                "startDate": "1928"
            },
            {
                "@type": "Organization",
                "name": "Gothenburg Geographical Society"
            }
        ],
        "publication": {
            "@type": "CreativeWork",
            "name": "Around 100 papers on geology, geography, and practical issues"
        },
        "awards": [
            {
                "@type": "Order",
                "name": "Knight of the Order of the North Star",
                "dateAwarded": ""
            },
            {
                "@type": "Order",
                "name": "Knight of the Order of Vasa",
                "dateAwarded": ""
            }
        ]
    },
    "occupations": {
        "career": [
            {
                "occupational_title": "Assistant Geologist",
                "workplace": "Swedish Geological Survey",
                "industry": "Geology",
                "start_date": "1902"
            },
            {
                "occupational_title": "State Geologist",
                "workplace": "Swedish Geological Survey",
                "industry": "Geology",
                "start_date": "1903"
            },
            {
                "occupational_title": "Acting Head",
                "workplace": "Swedish Geological Survey",
                "industry": "Geology",
                "start_date": "1914"
            },
            {
                "occupational_title": "Senior Director",
                "workplace": "Swedish Geological Survey",
                "industry": "Geology",
                "start_date": "1916"
            },
            {
                "occupational_title": "Secretary",
                "workplace": "Geological Society",
                "industry": "Geology",
                "start_date": "1914"
            },
            {
                "occupational_title": "Editor",
                "workplace": "Geological Society",
                "industry": "Geology",
                "start_date": "1914"
            },
            {
                "occupational_title": "Chairman",
                "workplace": "Geological Society",
                "industry": "Geology",
                "start_date": "1917"
            },
            {
                "occupational_title": "Member of the committee for general cartography",
                "workplace": "Unknown",
                "industry": "Geography",
                "start_date": "1914"
            },
            {
                "occupational_title": "Board member",
                "workplace": "State Meteorological-Hydrographic Institution",
                "industry": "Meteorology / Hydrography",
                "start_date": "1918"
            },
            {
                "occupational_title": "Board member",
                "workplace": "Forestry University",
                "industry": "Forestry",
                "start_date": "1928"
            },
            {
                "occupational_title": "Board member",
                "workplace": "State Forestry Insurance Institution",
                "industry": "Forestry",
                "start_date": "1928"
            },
            {
                "occupational_title": "Chairman",
                "workplace": "Swedish National Committee for Geodesy and Geophysics",
                "industry": "Geodesy / Geophysics",
                "start_date": "Unknown"
            },
            {
                "occupational_title": "Chairman",
                "workplace": "Swedish Nature Conservation Association",
                "industry": "Nature Conservation",
                "start_date": "Unknown"
            },
            {
                "occupational_title": "Board member",
                "workplace": "Swedish Society for Anthropology and Geography",
                "industry": "Anthropology / Geography",
                "start_date": "Unknown"
            },
            {
                "occupational_title": "Board member",
                "workplace": "Vassijaure Natural Science Station",
                "industry": "Natural Science",
                "start_date": "Unknown"
            },
            {
                "occupational_title": "Board member",
                "workplace": "Nobel Foundation",
                "industry": "Unknown",
                "start_date": "1934"
            },
            {
                "occupational_title": "Member of the investigation concerning the utilization of the Crown's mineral resources in Västerbotten",
                "workplace": "Unknown",
                "industry": "Mining",
                "start_date": "1938"
            }
        ]
    }
}