{
    "original": "KEULSTRÖM, Erik Gustaf Fredrik, Civilingenjör, Katrineholm, f Älskog, Gotl, 4/11 00 av kyrkoh Gust K o Lydia Budin, gm Ruth Ahlstedt. Studex Visby 19, civingex KTH (maskinbyggn o mek tekn) 25. Anst v AB Arctic i Motala 27—28, USA 28—34, v SKF sed. 34, varav ss planeringschef v Katrineholmsverken sed. 38. Inneh fi skytteutmärkelser. Hobby: Skytte.",
    "translated": "KEULSTRÖM, Erik Gustaf Fredrik, Civil Engineer, Katrineholm, born Älskog, Gotland, November 4th, 1900, son of parish minister Gust K and Lydia Budin, married to Ruth Ahlstedt. Passed high school exams in Visby in 1919, obtained a civil engineering degree from the Royal Institute of Technology (KTH) specializing in mechanical engineering and machine technology in 1925. Employed by AB Arctic in Motala from 1927 to 1928, worked in the United States from 1928 to 1934, and has been working at SKF since 1934, including the position of planning manager at Katrineholmsverken since 1938. Holds several shooting awards. Hobby: Shooting.",
    "structured": {
        "name": "Erik Gustaf Fredrik Keulström",
        "jobTitle": "Civil Engineer",
        "birthPlace": "Älskog, Gotland",
        "birthDate": "1900-11-04",
        "father": {
            "name": "Gust K",
            "jobTitle": "Parish Minister"
        },
        "mother": {
            "name": "Lydia Budin"
        },
        "spouse": {
            "name": "Ruth Ahlstedt"
        },
        "education": [
            {
                "institution": "Visby High School",
                "studyType": "High School Exams",
                "endDate": "1919"
            },
            {
                "institution": "Royal Institute of Technology (KTH)",
                "studyType": "Civil Engineering (Mechanical Engineering and Machine Technology)",
                "endDate": "1925"
            }
        ],
        "employmentHistory": [
            {
                "employer": "AB Arctic",
                "startDate": "1927",
                "endDate": "1928"
            },
            {
                "employer": "United States",
                "startDate": "1928",
                "endDate": "1934"
            },
            {
                "employer": "SKF",
                "startDate": "1934",
                "currentJob": true
            },
            {
                "employer": "Katrineholmsverken",
                "startDate": "1938",
                "position": "Planning Manager",
                "currentJob": true
            }
        ],
        "awards": [
            {
                "name": "Shooting Awards",
                "type": "Skytteutmärkelser"
            }
        ],
        "hobbies": [
            "Shooting"
        ]
    },
    "occupations": {
        "career": [
            {
                "occupational_title": "Civil Engineer",
                "workplace": "AB Arctic",
                "industry": "Engineering",
                "start_date": "1927"
            },
            {
                "occupational_title": "Civil Engineer",
                "workplace": "USA",
                "industry": "Engineering",
                "start_date": "1928"
            },
            {
                "occupational_title": "Civil Engineer",
                "workplace": "SKF",
                "industry": "Engineering",
                "start_date": "1934"
            },
            {
                "occupational_title": "Planning Manager",
                "workplace": "Katrineholmsverken",
                "industry": "Engineering",
                "start_date": "1938"
            }
        ]
    }
}