{
    "original": "ENSKOG, David, Professor, Ängby, f Västra Ämtervik, Värml, 22/4 84 av lantbr, pred N Olsson o Karolina Jonasdotter, gm Anna Jönsson. Studex Karlstad 03, fil kand Upps 07, fil lic 11, fil dr 17. E o lektor Skövde 13—18, lekt matern o fys Gävle 18—29, NLatin 29—30, prof matem o mek KTH 30; lär inatem o mek KSHS 33—39. Censor v studex sed. 31. Resor : Letterstedt-stip t Göttingen o Munchen f teor fys stud 22—23, m statsstip till tyska o a tekn högsk f stud av undervisn i matem o mek 31. Av trycket: Skrift oni integralekvat, kinetisk gas- o vätsketeori, radioaktivitet mm. RNO; LIVA; styr.led Sv Fysikersamf, medl Mat o Fys sällsk i Sthlm; Mitgl d deutsch Matemat Vereinigung; medl Ängby båtklb.",
    "translated": "ENSKOG, David, Professor, Ängby, born in Västra Ämtervik, Värmland, on April 22, 1884, son of farmer N Olsson and Karolina Jonasdotter, married to Anna Jönsson. Completed high school in Karlstad in 1903, Bachelor of Arts degree from Uppsala University in 1907, Master's degree in Philosophy in 1911, Doctoral degree in Philosophy in 1917. Became a lecturer in Skövde from 1913 to 1918, lecturer in Mathematics and Physics in Gävle from 1918 to 1929, Lecturer in Latin from 1929 to 1930, professor of Mathematics and Mechanics at the Royal Institute of Technology (KTH) from 1930. Taught Mathematics and Mechanics at the Royal College of Technology in Stockholm from 1933 to 1939. Served as censor for high school exams since 1931. Traveled on the Letterstedt scholarship to Göttingen and Munich for theoretical physics studies from 1922 to 1923, received a government scholarship to German and other technical universities for studies in mathematics and mechanics teaching methods in 1931. Published works on integral equations, kinetic gas and fluid theory, radioactivity, etc. Member of the Royal Swedish Academy of Sciences (RNO); Royal Swedish Academy of Letters, History and Antiquities (LIVA); board member of the Swedish Association of Physicists; member of the Mathematical and Physical Society in Stockholm; member of the German Mathematical Association; member of Ängby boat club.",
    "structured": {
        "@context": "https://schema.org",
        "@type": "Person",
        "name": "David Enskog",
        "givenName": "David",
        "familyName": "Enskog",
        "jobTitle": "Professor",
        "birthPlace": "Västra Ämtervik, Värmland",
        "birthDate": "1884-04-22",
        "parents": [
            {
                "@type": "Person",
                "name": "N Olsson"
            },
            {
                "@type": "Person",
                "name": "Karolina Jonasdotter"
            }
        ],
        "spouse": {
            "@type": "Person",
            "name": "Anna Jönsson"
        },
        "education": [
            {
                "@type": "EducationalOccupationalCredential",
                "name": "High School Diploma",
                "alumniOf": "Karlstad"
            },
            {
                "@type": "EducationalOccupationalCredential",
                "name": "Bachelor of Arts",
                "alumniOf": "Uppsala University",
                "startDate": "1903",
                "endDate": "1907"
            },
            {
                "@type": "EducationalOccupationalCredential",
                "name": "Master of Philosophy",
                "alumniOf": "Uppsala University",
                "startDate": "1907",
                "endDate": "1911"
            },
            {
                "@type": "EducationalOccupationalCredential",
                "name": "Doctor of Philosophy",
                "alumniOf": "Uppsala University",
                "startDate": "1911",
                "endDate": "1917"
            }
        ],
        "work": [
            {
                "@type": "JobPosting",
                "jobTitle": "Lecturer",
                "startDate": "1913",
                "endDate": "1918",
                "location": "Skövde"
            },
            {
                "@type": "JobPosting",
                "jobTitle": "Lecturer",
                "startDate": "1918",
                "endDate": "1929",
                "location": "Gävle",
                "occupationLocation": "Gävle"
            },
            {
                "@type": "JobPosting",
                "jobTitle": "Lecturer",
                "startDate": "1929",
                "endDate": "1930",
                "location": "Gävle",
                "occupationLocation": "Stockholm"
            },
            {
                "@type": "JobPosting",
                "jobTitle": "Professor",
                "startDate": "1930",
                "organization": {
                    "@type": "EducationalOrganization",
                    "name": "Royal Institute of Technology (KTH)"
                },
                "location": "Stockholm"
            },
            {
                "@type": "JobPosting",
                "jobTitle": "Teacher",
                "startDate": "1933",
                "endDate": "1939",
                "organization": {
                    "@type": "EducationalOrganization",
                    "name": "Royal College of Technology"
                },
                "location": "Stockholm"
            }
        ],
        "censorship": {
            "@type": "EventRole",
            "roleName": "Censor",
            "startDate": "1931",
            "endDate": "present",
            "event": {
                "@type": "EducationalOccupationalCredential",
                "name": "High School Exams"
            }
        },
        "awards": [
            {
                "@type": "EducationalOccupationalCredential",
                "name": "Letterstedt Scholarship",
                "startDate": "1922",
                "endDate": "1923",
                "description": "Theoretical physics studies in Göttingen and Munich"
            },
            {
                "@type": "EducationalOccupationalCredential",
                "name": "German Government Scholarship",
                "startDate": "1931",
                "description": "Studies in mathematics and mechanics teaching methods in German and other technical universities"
            }
        ],
        "publications": [
            "Skrift oni integralekvat",
            "kinetisk gas- o vätsketeori",
            "radioaktivitet mm"
        ],
        "memberOf": [
            {
                "@type": "Organization",
                "name": "Royal Swedish Academy of Sciences (RNO)"
            },
            {
                "@type": "Organization",
                "name": "Royal Swedish Academy of Letters, History and Antiquities (LIVA)"
            },
            {
                "@type": "Organization",
                "name": "Swedish Association of Physicists",
                "boardMember": true
            },
            {
                "@type": "Organization",
                "name": "Mathematical and Physical Society in Stockholm",
                "member": true
            },
            {
                "@type": "Organization",
                "name": "German Mathematical Association",
                "member": true
            },
            {
                "@type": "Organization",
                "name": "Ängby Boat Club",
                "member": true
            }
        ]
    },
    "occupations": {
        "career": [
            {
                "occupational_title": "Lecturer",
                "workplace": "Skövde",
                "industry": "Education",
                "start_date": "1913"
            },
            {
                "occupational_title": "Lecturer",
                "workplace": "Gävle",
                "industry": "Education",
                "start_date": "1918"
            },
            {
                "occupational_title": "Lecturer",
                "workplace": "Royal College of Technology (KTH)",
                "industry": "Education",
                "start_date": "1930"
            },
            {
                "occupational_title": "Professor",
                "workplace": "Royal College of Technology (KTH)",
                "industry": "Education",
                "start_date": "1930"
            },
            {
                "occupational_title": "Mathematics and Mechanics Teacher",
                "workplace": "Royal College of Technology in Stockholm",
                "industry": "Education",
                "start_date": "1933"
            }
        ]
    }
}