{
    "original": "BERGLIND, Carl Alfred, Direktör, Stockholm, f Sthlm 26/8 90 av C B o Klara Danielsdotter, gm Greta Erikson. Lärov, hdlssk. Tjm Sthlms Bomullsspinneri &amp; Väveri AB t 10, Sthlms Elvk 11—16, inköpschef AB Baltic Sthlm 16—22, vkst dir Trelleborgs Gummi-fabr För sälj n AB Sthlm sed. 22. Led div bol-o frn.styr. Odd Fellow, Neptuniorden, KAK, KSSS, Sthlms Sportfiskeklubb mfl. Hobbies: Segling, jakt, sportfiske.",
    "translated": "BERGLIND, Carl Alfred, Director, Stockholm, born in Stockholm on August 26, 1890, to C. B. and Klara Danielsdotter. Married to Greta Erikson. Educated at a commercial school. Worked as a maid at Stockholm Cotton Spinning & Weaving Company until 1910. Employed at Stockholm Electric Company from 1911 to 1916. Became the purchasing manager at Baltic AB in Stockholm from 1916 to 1922. Currently, the Deputy Managing Director at Trelleborg Rubber Factory since 1922. Holds positions on various boards of directors, including Odd Fellow, Neptuniorden, KAK, KSSS, Stockholm Sportfishing Club, among others. Hobbies include sailing, hunting, and sportfishing. Please note that the information '19xx m. partner's name' indicates that the person got married in that particular year.",
    "structured": {
        "@context": "https://schema.org",
        "@type": "Person",
        "name": "Carl Alfred Berglind",
        "birthDate": "1890-08-26",
        "birthPlace": "Stockholm",
        "father": {
            "@type": "Person",
            "name": "C. B. Berglind"
        },
        "mother": {
            "@type": "Person",
            "name": "Klara Danielsdotter"
        },
        "spouse": {
            "@type": "Person",
            "name": "Greta Erikson"
        },
        "education": {
            "@type": "EducationalOrganization",
            "name": "Commercial School"
        },
        "jobTitle": "Director",
        "worksFor": {
            "@type": "Organization",
            "name": "Trelleborg Rubber Factory"
        },
        "memberOf": [
            {
                "@type": "Organization",
                "name": "Odd Fellow"
            },
            {
                "@type": "Organization",
                "name": "Neptuniorden"
            },
            {
                "@type": "Organization",
                "name": "KAK"
            },
            {
                "@type": "Organization",
                "name": "KSSS"
            },
            {
                "@type": "Organization",
                "name": "Stockholm Sportfishing Club"
            }
        ],
        "workExperience": [
            {
                "@type": "Organization",
                "name": "Stockholm Cotton Spinning & Weaving Company",
                "startDate": "19xx",
                "endDate": "1910",
                "jobTitle": "Maid"
            },
            {
                "@type": "Organization",
                "name": "Stockholm Electric Company",
                "startDate": "1911",
                "endDate": "1916",
                "jobTitle": "Employee"
            },
            {
                "@type": "Organization",
                "name": "Baltic AB",
                "startDate": "1916",
                "endDate": "1922",
                "jobTitle": "Purchasing Manager"
            }
        ],
        "hobbies": [
            "Sailing",
            "Hunting",
            "Sportfishing"
        ]
    },
    "occupations": {
        "career": [
            {
                "occupational_title": "Maid",
                "workplace": "Stockholm Cotton Spinning & Weaving Company",
                "industry": "Textile Manufacturing",
                "start_date": "Until 1910"
            },
            {
                "occupational_title": "Employee",
                "workplace": "Stockholm Electric Company",
                "industry": "Energy",
                "start_date": "1911"
            },
            {
                "occupational_title": "Purchasing Manager",
                "workplace": "Baltic AB",
                "industry": "Various",
                "start_date": "1916"
            },
            {
                "occupational_title": "Deputy Managing Director",
                "workplace": "Trelleborg Rubber Factory",
                "industry": "Rubber",
                "start_date": "1922"
            }
        ]
    }
}