{
    "original": "HANSSON, Bror Olov Nikolaus, överingenjör, Stockholm, f Bollnäs 5/1 00 av bankdir N H o Sigrid Olsson, gm Gudrun Stanler.Studex 18, KTH (eltekn) 18—^2, Komm.koll o Sv-Am.stift:s stip f studier USA 28—29. Anst Sieverts Kabelverk 24—28, Common-wealth Edison Co Chicago 28—^29, Liljeholmens Kabelfabrik sed. 29, övering där sed. 30. Inneh ett 40-tal in- o utl patent på eltekn o mek uppf. Styr.led Sv Elektroing.frn sed. 41, styr.suppl AB Liljeh Kabelfabrik sed. 43. Resor: Sydamer 27, USA 28—29 o fi resor i Europa. Av trycket: Bidr t fråg om använd av kondens f kompens av reaktiv effekt (Tekn Tidskr 27), Starkströmskondens f vxl-strömsnät (Elektrotekn Tidskr 28), Stark-strömskabelinstall i USA (Tekn Tidskr 28), Kortslutn.skydd i Chicagos kraftsystem (Tekn Tidskr 29), På Inkafolkets stigar gm Colombia (NDA 28), Elektrifierade mönstergårdar (ERA, Electra 29), Static condensers for power circuits (ASEA:s Journal 35, ASEA:s Tidn 34), Sjökablar (ASEA:s Tidn o Driftbe-styreren, Norge, 37), The dielectric strength of impregnated paper under high pressure (ASEA:s Journal 39), The foil cooled pressure capacitor (ASEA:s Tidn 39), Förbättras ej de gummiisolerade ledningarna? (ERA 40), Syntetiskt gummi (Tekn Tidskr 38), En ny kondensator (Tekn Tidskr 39), Kontinuerlig kabeltillverkning samt Isolationsmaterialens jämnhet som mått på kvaliteten (ASEA:s Tidn",
    "translated": "HANSSON, Bror Olov Nikolaus, chief engineer, Stockholm, born in Bollnäs on January 5, 1900, son of bank director N.H. and Sigrid Olsson, married to Gudrun Stanler. Studied at the age of 18, attended the Royal Institute of Technology (majoring in electrical engineering) from 1918 to 1922. Received scholarships from the Swedish-American Foundation for studies in the USA from 1928 to 1929. Employed at Sieverts Cable Works from 1924 to 1928, Commonwealth Edison Company in Chicago from 1928 to 1929, Liljeholmens Cable Factory since 1929, and has been chief engineer there since 1930. Holds approximately 40 international and domestic patents in the field of electrical engineering and mechanical inventions. Board member of the Swedish Electrical Engineers Association since 1941, and board supervisor of AB Liljeh Kabelfabrik since 1943. Traveled to South America in 1927, the USA from 1928 to 1929, and made several trips in Europe. Published works include contributions on the use of condensers for compensating reactive power (Technical Journal, 1927), high voltage condensers for alternating current networks (Electrotechnical Journal, 1928), high-voltage cable installations in the USA (Technical Journal, 1928), short-circuit protection in Chicago's power system (Technical Journal, 1929), journey through Colombia on the Inca trails (New Daily News, 1928), electrified model farms (ERA, Electra, 1929), static condensers for power circuits (ASEA's Journal, 1935; ASEA's Magazine, 1934), submarine cables (ASEA's Magazine and Manager, Norway, 1937), the dielectric strength of impregnated paper under high pressure (ASEA's Journal, 1939), the foil-cooled pressure capacitor (ASEA's Magazine, 1939), are rubber insulated cables improving? (ERA, 1940), synthetic rubber (Technical Journal, 1938), a new capacitor (Technical Journal, 1939), continuous cable production and uniformity of insulation materials as a measure of quality (ASEA's Magazine).",
    "structured": {
        "@context": "https://schema.org",
        "@type": "Person",
        "name": "Bror Olov Nikolaus Hansson",
        "jobTitle": "Chief Engineer",
        "address": {
            "@type": "PostalAddress",
            "addressLocality": "Stockholm"
        },
        "birthDate": "1900-01-05",
        "parents": [
            {
                "@type": "Person",
                "name": "N.H.",
                "jobTitle": "Bank Director"
            },
            {
                "@type": "Person",
                "name": "Sigrid Olsson"
            }
        ],
        "spouse": {
            "@type": "Person",
            "name": "Gudrun Stanler"
        },
        "education": {
            "@type": "EducationalOccupationalCredential",
            "credentialCategory": "Bachelor's degree",
            "educationalLevel": "Undergraduate",
            "educationalProgram": "Electrical Engineering",
            "educationalInstitution": {
                "@type": "CollegeOrUniversity",
                "name": "Royal Institute of Technology"
            },
            "startDate": "1918",
            "endDate": "1922"
        },
        "scholarships": {
            "@type": "Scholarship",
            "name": "Swedish-American Foundation",
            "description": "Studied in the USA",
            "startDate": "1928",
            "endDate": "1929"
        },
        "employmentHistory": [
            {
                "@type": "OrganizationRole",
                "roleName": "Sieverts Cable Works",
                "startDate": "1924",
                "endDate": "1928"
            },
            {
                "@type": "OrganizationRole",
                "roleName": "Commonwealth Edison Company",
                "location": "Chicago",
                "startDate": "1928",
                "endDate": "1929"
            },
            {
                "@type": "OrganizationRole",
                "roleName": "Liljeholmens Cable Factory",
                "startDate": "1929"
            }
        ],
        "currentJob": {
            "@type": "OrganizationRole",
            "roleName": "Chief Engineer",
            "startDate": "1930"
        },
        "patents": {
            "@type": "CreativeWork",
            "name": "Patents in Electrical Engineering and Mechanical Inventions",
            "description": "Approximately 40 patents",
            "dateCreated": null
        },
        "organizationalMembership": [
            {
                "@type": "OrganizationRole",
                "roleName": "Swedish Electrical Engineers Association",
                "startDate": "1941"
            },
            {
                "@type": "OrganizationRole",
                "roleName": "AB Liljeh Kabelfabrik",
                "startDate": "1943"
            }
        ],
        "travels": [
            {
                "@type": "TouristTrip",
                "name": "South America",
                "startDate": "1927"
            },
            {
                "@type": "TouristTrip",
                "name": "USA",
                "startDate": "1928",
                "endDate": "1929"
            },
            {
                "@type": "TouristTrip",
                "name": "Europe"
            }
        ],
        "publications": [
            {
                "@type": "Article",
                "name": "Use of Condensers for Compensating Reactive Power",
                "journal": "Technical Journal",
                "datePublished": "1927"
            },
            {
                "@type": "Article",
                "name": "High Voltage Condensers for Alternating Current Networks",
                "journal": "Electrotechnical Journal",
                "datePublished": "1928"
            },
            {
                "@type": "Article",
                "name": "High-Voltage Cable Installations in the USA",
                "journal": "Technical Journal",
                "datePublished": "1928"
            },
            {
                "@type": "Article",
                "name": "Short-Circuit Protection in Chicago's Power System",
                "journal": "Technical Journal",
                "datePublished": "1929"
            },
            {
                "@type": "Article",
                "name": "Journey Through Colombia on the Inca Trails",
                "journal": "New Daily News",
                "datePublished": "1928"
            },
            {
                "@type": "Article",
                "name": "Electrified Model Farms",
                "journal": "ERA, Electra",
                "datePublished": "1929"
            },
            {
                "@type": "Article",
                "name": "Static Condensers for Power Circuits",
                "journal": "ASEA's Journal",
                "datePublished": "1935"
            },
            {
                "@type": "Article",
                "name": "Static Condensers for Power Circuits",
                "journal": "ASEA's Magazine",
                "datePublished": "1934"
            },
            {
                "@type": "Article",
                "name": "Submarine Cables",
                "journal": "ASEA's Magazine and Manager, Norway",
                "datePublished": "1937"
            },
            {
                "@type": "Article",
                "name": "The Dielectric Strength of Impregnated Paper Under High Pressure",
                "journal": "ASEA's Journal",
                "datePublished": "1939"
            },
            {
                "@type": "Article",
                "name": "The Foil-Cooled Pressure Capacitor",
                "journal": "ASEA's Magazine",
                "datePublished": "1939"
            },
            {
                "@type": "Article",
                "name": "Are Rubber Insulated Cables Improving?",
                "journal": "ERA",
                "datePublished": "1940"
            },
            {
                "@type": "Article",
                "name": "Synthetic Rubber",
                "journal": "Technical Journal",
                "datePublished": "1938"
            },
            {
                "@type": "Article",
                "name": "A New Capacitor",
                "journal": "Technical Journal",
                "datePublished": "1939"
            },
            {
                "@type": "Article",
                "name": "Continuous Cable Production and Uniformity of Insulation Materials as a Measure of Quality",
                "journal": "ASEA's Magazine"
            }
        ]
    },
    "occupations": {
        "career": [
            {
                "occupational_title": "Chief Engineer",
                "workplace": "Liljeholmens Kabelfabrik",
                "industry": "Electrical Engineering",
                "start_date": "1930"
            },
            {
                "occupational_title": "Engineer",
                "workplace": "Liljeholmens Kabelfabrik",
                "industry": "Electrical Engineering",
                "start_date": "1929"
            },
            {
                "occupational_title": "Engineer",
                "workplace": "Commonwealth Edison Co",
                "industry": "Electrical Engineering",
                "start_date": "1928"
            },
            {
                "occupational_title": "Engineer",
                "workplace": "Sieverts Kabelverk",
                "industry": "Electrical Engineering",
                "start_date": "1924"
            }
        ]
    }
}