{
    "original": "FERNSTRÖM, Erik Ferdinand, Direktör, Stockholm, f Kopparbergs landsförs 20/8 88 av K E Fernström o Sofia Westgren, gm Edith Neijber. Falu hal. Anst St Kopparb Bergsl AB 03—10, korresp v Rydö o Hylte pappers- o cellul.fabr 10—14, försäljn.ch 15— 19. Eg fma i London ss ombud f Fiskeby, Skärblacka o Ljusfors pappersfabr i United Kingdom 19, gr Fernström &amp; Co AB i Sthlm o Fernström Paper Co Newyork 20, gr o styr-, ordf Fernström Paper Mills Inc, Pomona, Kalif, 26, gr Protecto Products Co, Inc, Pomona, Kalif, 36, deläg Fernström Paper Co Pomona o San Francisco Kalif sed. 26, styr.-ordf o vkst dir Fernström &amp; Co AB. Led U S Bureau of Standards, Washington. Resor: Tyskl, Engl, Frankr, USA, Canada, Mexico, Brasil, Uruguay, Argent, Chile, Peru, Columbia mfl.",
    "translated": "FERNSTRÖM, Erik Ferdinand, Director, Stockholm, b. in the parish of Kopparbergs on August 20, 1888, to parents K E Fernström and Sofia Westgren, married to Edith Neijber. Formerly employed at St Kopparb Bergsl AB from 1903 to 1910, corresponding for Rydö and Hylte paper and cellulose factory from 1910 to 1914, sales representative from 1915 to 1919. Established own company in London as agent for Fiskeby, Skärblacka, and Ljusfors paper factories in the United Kingdom in 1919. Established Fernström & Co AB in Stockholm and Fernström Paper Co in New York in 1920. Founded and chaired Fernström Paper Mills Inc in Pomona, California, in 1926. Established Protecto Products Co, Inc in Pomona, California, in 1936. Partial owner of Fernström Paper Co in Pomona and San Francisco, California, since 1926. Board chairman and managing director of Fernström & Co AB. Member of the U.S. Bureau of Standards, Washington. Travels: Germany, England, France, USA, Canada, Mexico, Brazil, Uruguay, Argentina, Chile, Peru, Colombia, and others.",
    "structured": {
        "@context": "https://schema.org",
        "@type": "Person",
        "name": "Erik Ferdinand Fernström",
        "birthDate": "1888-08-20",
        "birthPlace": "Kopparbergs",
        "deathDate": null,
        "parent": [
            {
                "@type": "Person",
                "name": "K E Fernström"
            },
            {
                "@type": "Person",
                "name": "Sofia Westgren"
            }
        ],
        "spouse": [
            {
                "@type": "Person",
                "name": "Edith Neijber"
            }
        ],
        "jobTitle": "Director",
        "address": {
            "@type": "PostalAddress",
            "addressLocality": "Stockholm"
        },
        "worksFor": [
            {
                "@type": "Organization",
                "name": "St Kopparb Bergsl AB",
                "startDate": "1903",
                "endDate": "1910"
            },
            {
                "@type": "Organization",
                "name": "Rydö and Hylte paper and cellulose factory",
                "startDate": "1910",
                "endDate": "1914"
            },
            {
                "@type": "Organization",
                "name": "Own Company in London",
                "startDate": "1919"
            },
            {
                "@type": "Organization",
                "name": "Fernström & Co AB",
                "startDate": "1920"
            },
            {
                "@type": "Organization",
                "name": "Fernström Paper Co",
                "startDate": "1920"
            },
            {
                "@type": "Organization",
                "name": "Fernström Paper Mills Inc",
                "startDate": "1926"
            },
            {
                "@type": "Organization",
                "name": "Protecto Products Co, Inc",
                "startDate": "1936"
            },
            {
                "@type": "Organization",
                "name": "Fernström Paper Co Pomona",
                "startDate": "1926"
            },
            {
                "@type": "Organization",
                "name": "Fernström Paper Co San Francisco",
                "startDate": "1926"
            }
        ],
        "memberOf": {
            "@type": "Organization",
            "name": "U.S. Bureau of Standards"
        },
        "nationality": "Swedish",
        "description": "Director, Stockholm",
        "travel": [
            "Germany",
            "England",
            "France",
            "USA",
            "Canada",
            "Mexico",
            "Brazil",
            "Uruguay",
            "Argentina",
            "Chile",
            "Peru",
            "Colombia"
        ]
    },
    "occupations": {
        "career": [
            {
                "occupational_title": "Employee",
                "workplace": "St Kopparb Bergsl AB",
                "industry": "Mining",
                "start_date": "1903"
            },
            {
                "occupational_title": "Correspondent",
                "workplace": "Rydö and Hylte paper and cellulose factory",
                "industry": "Paper and cellulose",
                "start_date": "1910"
            },
            {
                "occupational_title": "Sales Representative",
                "workplace": "Unknown",
                "industry": "Unknown",
                "start_date": "1915"
            },
            {
                "occupational_title": "Agent",
                "workplace": "Fiskeby, Skärblacka, and Ljusfors paper factories",
                "industry": "Paper",
                "start_date": "1919"
            },
            {
                "occupational_title": "Founder & Chairman",
                "workplace": "Fernström Paper Mills Inc",
                "industry": "Paper",
                "start_date": "1926"
            },
            {
                "occupational_title": "Founder",
                "workplace": "Fernström & Co AB",
                "industry": "Paper",
                "start_date": "1920"
            },
            {
                "occupational_title": "Founder",
                "workplace": "Fernström Paper Co",
                "industry": "Paper",
                "start_date": "1920"
            },
            {
                "occupational_title": "Founder",
                "workplace": "Protecto Products Co, Inc",
                "industry": "Unknown",
                "start_date": "1936"
            }
        ]
    }
}