{
    "original": "EHRUN, John, Direktör, Värnamo, f Ockelbo 10/9 87 av lantbrukare J A Ehrlin o Kristina Hempel, gm Elin Johannesson. 5 kl h a l, bokf.- o hdlskurs Kristineh prakt sk. Arist Kopparfors AB 08—16, Siljans KolAB 16—20, Dalälv Fördeln.kont 20—23, omb.m Sydsv Vir-kesfrn 23, vkst dir där sed. 43. V. ordf stdfm, ordf Värnamoort luf tsk.f rn, N Finnv Pastorats Skogsfrb, led past.rådet. Styr.led o ordf AB Värnamo Nyt, styr.led Vernamo KraftAB, rev Rydaholnis Ind o KraftAB, Västbo. Kraftv.frn, Nissaåns Flottn.frn. Resor: Tyskl 37. RVO; Odd Fellow.",
    "translated": "EHRUN, John, Director, Värnamo, born in Ockelbo on September 10, 1887, son of farmer J A Ehrlin and Kristina Hempel, married to Elin Johannesson. Completed 5th grade, attended bookkeeping and commercial courses at Kristineh Practical School. Worked at Arist Kopparfors AB from 08 to 16, Siljans KolAB from 16 to 20, Dalälv Fördeln.kont from 20 to 23, and as a representative for Sydsvirkesfrn from 23, serving as a sales director there since 43. Vice-chairman of the board for the Studieförbund (Education Association), chairman of the Värnamoort Luftskärmförbund (Air Defense Association), member of the N Finnv Pastorats Skogsfrb (Forestry Association), and member of the parish council. Board member and chairman of AB Värnamo Nyt, board member of Vernamo KraftAB, auditor for Rydaholnis Ind and KraftAB, Västbo Kraftvärmeförening, and Nissåns Flottningsförening. Traveled to Germany in 1937. Received the Royal Order of Vasa (RVO) and was a member of the Odd Fellow Society.",
    "structured": {
        "@context": "https://schema.org",
        "@type": "Person",
        "name": "John EHRUN",
        "jobTitle": "Director",
        "birthDate": "1887-09-10",
        "birthPlace": "Ockelbo",
        "description": "John EHRUN was born on September 10, 1887 in Ockelbo. He worked as a Director in Värnamo. He was the son of J A Ehrlin and Kristina Hempel. He married Elin Johannesson.",
        "spouse": {
            "@type": "Person",
            "name": "Elin Johannesson"
        },
        "education": [
            {
                "@type": "EducationalOccupationalCredential",
                "credentialCategory": "5th grade"
            },
            {
                "@type": "EducationalOccupationalCredential",
                "credentialCategory": "Bookkeeping and commercial courses",
                "educationalLevel": "VocationalSchool",
                "educationalProgram": "Kristineh Practical School"
            }
        ],
        "employmentHistory": [
            {
                "@type": "OrganizationRole",
                "startDate": "1908",
                "endDate": "1916",
                "roleName": "Arist Kopparfors AB"
            },
            {
                "@type": "OrganizationRole",
                "startDate": "1916",
                "endDate": "1920",
                "roleName": "Siljans KolAB"
            },
            {
                "@type": "OrganizationRole",
                "startDate": "1920",
                "endDate": "1923",
                "roleName": "Dalälv Fördeln.kont"
            },
            {
                "@type": "OrganizationRole",
                "startDate": "1923",
                "roleName": "Representative for Sydsvirkesfrn",
                "description": "Sales Director since 1943"
            }
        ],
        "memberOf": [
            {
                "@type": "Organization",
                "name": "Värnamo Education Association",
                "roleName": "Vice-chairman of the board"
            },
            {
                "@type": "Organization",
                "name": "Värnamoort Air Defense Association",
                "roleName": "Chairman"
            },
            {
                "@type": "Organization",
                "name": "N Finnv Pastorats Skogsfrb",
                "roleName": "Member"
            },
            {
                "@type": "Organization",
                "name": "Parish Council",
                "roleName": "Member"
            },
            {
                "@type": "Organization",
                "name": "AB Värnamo Nyt",
                "roleName": "Board member and chairman"
            },
            {
                "@type": "Organization",
                "name": "Vernamo KraftAB",
                "roleName": "Board member"
            },
            {
                "@type": "Organization",
                "name": "Rydaholnis Ind and KraftAB",
                "roleName": "Auditor"
            },
            {
                "@type": "Organization",
                "name": "Västbo Kraftvärmeförening",
                "roleName": "Auditor"
            },
            {
                "@type": "Organization",
                "name": "Nissåns Flottningsförening",
                "roleName": "Auditor"
            }
        ],
        "award": {
            "@type": "Order",
            "name": "Royal Order of Vasa (RVO)"
        },
        "affiliation": {
            "@type": "Organization",
            "name": "Odd Fellow Society"
        },
        "travelHistory": [
            {
                "@type": "Trip",
                "name": "Traveled to Germany",
                "startDate": "1937"
            }
        ]
    },
    "occupations": {
        "career": [
            {
                "occupational_title": "Director",
                "workplace": "Arist Kopparfors AB",
                "industry": "Unknown",
                "start_date": "1908"
            },
            {
                "occupational_title": "Director",
                "workplace": "Siljans KolAB",
                "industry": "Unknown",
                "start_date": "1916"
            },
            {
                "occupational_title": "Director",
                "workplace": "Dalälv Fördeln.kont",
                "industry": "Unknown",
                "start_date": "1920"
            },
            {
                "occupational_title": "Sales Director",
                "workplace": "Sydsvirkesfrn",
                "industry": "Unknown",
                "start_date": "1923"
            }
        ]
    }
}