{
    "original": "ALRUTZ, Otto Reinhold, Advokat, Stockholm, f Sthlm 2/5 72 av byggn.ch A O A o Anna Benckert, gm Malla Jansson. Studex NLatin 90, jur utr kand Upps 97, tingstjg Mellansysslets doms 98—00, tjg i domst o äm-betsv. Anst å G Abenius, adv.byrå 01—09, eg adv.byrå sed. 09; sekr h Nya Trollh kanalbol 01—05, h Sthlm byggm.frn 02—08, ombudsm Sthlm-Nynäs jvg 03—06, aman h Sthlms städs ombudsm 03—06, ombudsm Sthlms stads brandförsäkr.kont 06—37, sekr o ombudsm Dalälvens regl.frn o vattenregl.föret 16—42, jur o styr.led Indalsälvens regl.frn o vattenregl.föret fr bild 20 resp 36 t 42 samt h Sv vattenkraftfrn. Ag villafastgh i Djursh. Resor: Skand länd, Tyskl, Engl, Holl, Belg. Frankr, Ital. Av trycket: Upps i vattenrättsl f rå g. KVO2kl, RNO, Sthlms stads brandför-säkr.kont:s st o mindre GM; led Sv adv.samf, Juristfrn, Sällsk Idun, SHT.",
    "translated": "ALRUTZ, Otto Reinhold, Lawyer, Stockholm, born in Stockholm on May 2nd, 1872, son of building contractor A.O.A and Anna Benckert, married Malla Jansson. Graduated from Latin School in 1890, completed law studies at Uppsala University in 1897. Served as a court clerk in the Mellansysslet District Court from 1898 to 1900, worked in various court and government positions. Employed at G. Abenius law firm from 1901 to 1909, established own law firm in 1909. Secretary at Nya Trollh Canal Company from 1901 to 1905, Stockholm Construction Company from 1902 to 1908, representative for Stockholm-Nynäs Railway from 1903 to 1906, assistant to the Stockholm City Cleaning Authority from 1903 to 1906, representative for Stockholm City Fire Insurance Company from 1906 to 1937, secretary and representative for Dalälven Regulation Company and Water Regulation Association from 1916 to 1942, legal advisor and board member for Indalsälven Regulation Company and Water Regulation Association since establishment in 1920 and 1936 respectively, and member of the Swedish Hydroelectric Power Company. Owned villa property in Djursholm. Traveled to Scandinavian countries, Germany, England, the Netherlands, Belgium, France, and Italy. Published work on water rights in Uppsala. Holder of the Royal Order of Vasa, Knight 2nd Class, the Royal Norwegian Order, and recognized for service at Stockholm City Fire Insurance Company. Member of the Swedish Bar Association, Juridical Society, Society Idun, and the Swedish Historical Society.",
    "structured": {
        "@context": "https://schema.org",
        "@type": "Person",
        "name": "ALRUTZ, Otto Reinhold",
        "birthDate": "1872-05-02",
        "gender": "Male",
        "nationality": "Swedish",
        "jobTitle": "Lawyer",
        "alumniOf": {
            "@type": "EducationalOrganization",
            "name": "Uppsala University"
        },
        "father": {
            "@type": "Person",
            "name": "A.O.A"
        },
        "mother": {
            "@type": "Person",
            "name": "Anna Benckert"
        },
        "spouse": {
            "@type": "Person",
            "name": "Malla Jansson"
        },
        "worksFor": {
            "@type": "Organization",
            "name": "G Abenius"
        },
        "memberOf": [
            {
                "@type": "Organization",
                "name": "Swedish Bar Association"
            },
            {
                "@type": "Organization",
                "name": "Juridical Society"
            },
            {
                "@type": "Organization",
                "name": "Society Idun"
            },
            {
                "@type": "Organization",
                "name": "Swedish Historical Society"
            }
        ],
        "owns": {
            "@type": "Place",
            "name": "Villa property in Djursholm"
        },
        "awards": [
            {
                "@type": "Order",
                "name": "Royal Order of Vasa",
                "description": "Knight 2nd Class"
            },
            {
                "@type": "Order",
                "name": "Royal Norwegian Order"
            }
        ],
        "traveled": [
            "Scandinavian countries",
            "Germany",
            "England",
            "the Netherlands",
            "Belgium",
            "France",
            "Italy"
        ],
        "publications": [
            {
                "@type": "CreativeWork",
                "name": "Upps i vattenrättsl f rå g"
            }
        ],
        "employmentHistory": [
            {
                "@type": "Organization",
                "name": "Stockholm Construction Company",
                "startDate": "1902",
                "endDate": "1908"
            },
            {
                "@type": "Organization",
                "name": "Stockholm-Nynäs Railway",
                "startDate": "1903",
                "endDate": "1906"
            },
            {
                "@type": "Organization",
                "name": "Stockholm City Cleaning Authority",
                "startDate": "1903",
                "endDate": "1906"
            },
            {
                "@type": "Organization",
                "name": "Stockholm City Fire Insurance Company",
                "startDate": "1906",
                "endDate": "1937"
            },
            {
                "@type": "Organization",
                "name": "Dalälven Regulation Company and Water Regulation Association",
                "startDate": "1916",
                "endDate": "1942"
            },
            {
                "@type": "Organization",
                "name": "Indalsälven Regulation Company",
                "startDate": "1920"
            },
            {
                "@type": "Organization",
                "name": "Water Regulation Association",
                "startDate": "1936",
                "endDate": "1942"
            },
            {
                "@type": "Organization",
                "name": "Swedish Hydroelectric Power Company"
            }
        ]
    },
    "occupations": {
        "career": [
            {
                "occupational_title": "Lawyer",
                "workplace": "G. Abenius law firm",
                "industry": "Law",
                "start_date": "1901-01-01"
            },
            {
                "occupational_title": "Own law firm",
                "workplace": "Eg adv.byrå",
                "industry": "Law",
                "start_date": "1909-01-01"
            },
            {
                "occupational_title": "Secretary",
                "workplace": "Nya Trollh Canal Company",
                "industry": "Canal Construction",
                "start_date": "1901-01-01"
            },
            {
                "occupational_title": "Secretary",
                "workplace": "Stockholm Construction Company",
                "industry": "Construction",
                "start_date": "1902-01-01"
            },
            {
                "occupational_title": "Representative",
                "workplace": "Stockholm-Nynäs Railway",
                "industry": "Railway",
                "start_date": "1903-01-01"
            },
            {
                "occupational_title": "Assistant",
                "workplace": "Stockholm City Cleaning Authority",
                "industry": "Municipal Services",
                "start_date": "1903-01-01"
            },
            {
                "occupational_title": "Representative",
                "workplace": "Stockholm City Fire Insurance Company",
                "industry": "Insurance",
                "start_date": "1906-01-01"
            },
            {
                "occupational_title": "Secretary",
                "workplace": "Dalälven Regulation Company and Water Regulation Association",
                "industry": "Water Regulation",
                "start_date": "1916-01-01"
            },
            {
                "occupational_title": "Legal advisor and board member",
                "workplace": "Indalsälven Regulation Company and Water Regulation Association",
                "industry": "Water Regulation",
                "start_date": "1920-01-01"
            },
            {
                "occupational_title": "Legal advisor and board member",
                "workplace": "Indalsälven Regulation Company and Water Regulation Association",
                "industry": "Water Regulation",
                "start_date": "1936-01-01"
            }
        ]
    }
}