{
    "original": "EHRENBORG, Rickard Lars Casper, Direktör, Stockholm, f Long, Skarab l, 26/4 90 av kapt C E o h h, f Börjesson, gm Marianne Jenner Borg. Efter avsl skolstudier verks å fädernegården, Kråks säteri, Västergötl, till 09, inneh St Röå gård 09—18, inneh 7 drosk-rättigheter i fma Casper Ehrenborg, Sthlm, sed. 18, dir i Bilägarnas Inköpscentral 26—34 o ordf i dess styr 27—34, dir i AB Bilägarnas Oljeraffinaderier o ordf i dess styr 38— 42. Studerat i utl drosk- o bensinbranschen samt »Altölregenerierung». Av trycket: Ett flert art o upps i trafik- o bensinfrågor i facktidskr o dagspress samt broschyrer bl a »Ett ord i bensinfrågan», »Staten och bensinfrågan» mfl. Styr.led i Sthlms Droskägarefrn.",
    "translated": "EHRENBORG, Rickard Lars Casper, Director, Stockholm, born in Skaraborg county, 26/4 1890, son of Captain C E and H H, born Börjesson, married to Marianne Jenner Borg. After completing school studies, worked at the ancestral estate, Kråks säteri, in Västergötland, until 1909. Became owner of St Röå estate from 1909 to 1918, and owned 7 carriage rights in the company Casper Ehrenborg, Stockholm, since 1918. Director of Bilägarnas Inköpscentral from 1926 to 1934, and chairman of its board from 1927 to 1934. Director of AB Bilägarnas Oljeraffinaderier and chairman of its board from 1938 to 1942. Studied the carriage and gasoline industry abroad, as well as \"Alt beer regeneration\". Published multiple articles and essays on traffic and gasoline issues in specialized magazines, daily press, and brochures, including \"A word on gasoline issues\", \"The state and gasoline issues\", and others. Board member of Sthlms Droskägarefrn.",
    "structured": {
        "@context": "https://schema.org",
        "@type": "Person",
        "name": "Rickard Lars Casper Ehrenborg",
        "birthDate": "1890-04-26",
        "birthPlace": "Skaraborg county",
        "nationality": "Swedish",
        "father": {
            "@type": "Person",
            "name": "Captain C E"
        },
        "mother": {
            "@type": "Person",
            "name": "H H",
            "birthName": "Börjesson"
        },
        "spouse": {
            "@type": "Person",
            "name": "Marianne Jenner Borg"
        },
        "occupation": "Director",
        "workLocation": "Stockholm",
        "education": {
            "@type": "EducationalOrganization",
            "name": "School"
        },
        "work": [
            {
                "@type": "Organization",
                "name": "Kråks säteri",
                "location": "Västergötland",
                "startDate": "1909",
                "endDate": "1909"
            },
            {
                "@type": "Organization",
                "name": "St Röå estate",
                "location": "Unknown",
                "startDate": "1909",
                "endDate": "1918"
            },
            {
                "@type": "Organization",
                "name": "Casper Ehrenborg",
                "location": "Stockholm",
                "startDate": "1918",
                "endDate": "Unknown"
            },
            {
                "@type": "Organization",
                "name": "Bilägarnas Inköpscentral",
                "location": "Stockholm",
                "startDate": "1926",
                "endDate": "1934",
                "roleName": "Director",
                "boardRole": "Chairman"
            },
            {
                "@type": "Organization",
                "name": "AB Bilägarnas Oljeraffinaderier",
                "location": "Unknown",
                "startDate": "1938",
                "endDate": "1942",
                "roleName": "Director",
                "boardRole": "Chairman"
            }
        ],
        "studyProgram": [
            {
                "@type": "Course",
                "name": "Carriage and gasoline industry",
                "studyLocation": "Unknown"
            },
            {
                "@type": "Course",
                "name": "Alt beer regeneration",
                "studyLocation": "Unknown"
            }
        ],
        "publication": [
            "A word on gasoline issues",
            "The state and gasoline issues",
            "Others"
        ],
        "membership": [
            {
                "@type": "Organization",
                "name": "Sthlms Droskägarefrn",
                "roleName": "Board member"
            }
        ]
    },
    "occupations": {
        "career": [
            {
                "occupational_title": "Director",
                "workplace": "Stockholm",
                "industry": "Unknown",
                "start_date": "N/A"
            },
            {
                "occupational_title": "Owner",
                "workplace": "St Röå estate",
                "industry": "Agriculture",
                "start_date": "1909"
            },
            {
                "occupational_title": "Owner",
                "workplace": "Casper Ehrenborg company",
                "industry": "Carriage",
                "start_date": "1918"
            },
            {
                "occupational_title": "Director",
                "workplace": "Bilägarnas Inköpscentral",
                "industry": "Unknown",
                "start_date": "1926"
            },
            {
                "occupational_title": "Chairman",
                "workplace": "Bilägarnas Inköpscentral",
                "industry": "Unknown",
                "start_date": "1927"
            },
            {
                "occupational_title": "Director",
                "workplace": "AB Bilägarnas Oljeraffinaderier",
                "industry": "Oil refining",
                "start_date": "1938"
            },
            {
                "occupational_title": "Chairman",
                "workplace": "AB Bilägarnas Oljeraffinaderier",
                "industry": "Oil refining",
                "start_date": "1938"
            }
        ]
    }
}