{
    "original": "HOBWITZ, Sten Philip, Grosshandlare, Stockholm, f Sthlm 13/10 99 av grossh G H o Karin Svahn, gm Harriet Hjorth. Studex Nya Elem.sk Sthlm 18. Volont Finsp Metallverks AB 19, tjm Industri-Emissions AB 20—22 o fma Gustaf Horwitz Sthlm 22—31, inneh sistnmda fma sed. 31. Ordf Sthlms Rekl.frn sed. 42, led av Sv Rekl.frbs styr. o arb.utsk, led av Sv Rekl.frbs opinionsnmd. H :s fma etabl av hans farbr M Horwitz 80 o övertogs 21 av H:s fader.",
    "translated": "HOBWITZ, Sten Philip, Merchant, Stockholm, born in Stockholm on October 13, 1899, son of wholesale merchant G H and Karin Svahn, married to Harriet Hjorth. Obtained a diploma from Nya Elementarskolan in Stockholm in 1918. Volunteered at Finspång Metallverks AB in 1919. Worked at Industri-Emissions AB from 1920 to 1922 and then at Gustaf Horwitz Stockholm from 1922 to 1931, eventually becoming the owner of the latter. Chairman of Stockholm Advertising Association since 1942, member of the board and working committee of the Swedish Advertising Association, member of the opinion committee of the Swedish Advertising Association. The company he currently owns was established by his uncle M Horwitz in 1880 and taken over by Sten's father in 1921.",
    "structured": {
        "@context": "https://schema.org",
        "@type": "Person",
        "name": "Sten Philip Hobwitz",
        "birthDate": "1899-10-13",
        "birthPlace": "Stockholm, Sweden",
        "parent": [
            {
                "@type": "Person",
                "name": "G H Hobwitz",
                "description": "Father"
            },
            {
                "@type": "Person",
                "name": "Karin Svahn",
                "description": "Mother"
            }
        ],
        "spouse": {
            "@type": "Person",
            "name": "Harriet Hjorth"
        },
        "education": {
            "@type": "EducationalOrganization",
            "name": "Nya Elementarskolan",
            "location": "Stockholm, Sweden",
            "endDate": "1918"
        },
        "employment": [
            {
                "@type": "Organization",
                "name": "Finspång Metallverks AB",
                "startDate": "1919",
                "endDate": "1919"
            },
            {
                "@type": "Organization",
                "name": "Industri-Emissions AB",
                "startDate": "1920",
                "endDate": "1922"
            },
            {
                "@type": "Organization",
                "name": "Gustaf Horwitz Stockholm",
                "startDate": "1922",
                "endDate": "1931"
            }
        ],
        "owns": {
            "@type": "Organization",
            "name": "Gustaf Horwitz Stockholm",
            "startDate": "1931"
        },
        "positions": [
            {
                "@type": "OrganizationRole",
                "roleName": "Chairman",
                "startDate": "1942",
                "endDate": null,
                "organization": {
                    "@type": "Organization",
                    "name": "Stockholm Advertising Association"
                }
            },
            {
                "@type": "OrganizationRole",
                "roleName": "Member",
                "startDate": null,
                "endDate": null,
                "organization": {
                    "@type": "Organization",
                    "name": "Swedish Advertising Association",
                    "subOrganization": {
                        "@type": "Organization",
                        "name": "Swedish Advertising Association Opinion Committee"
                    }
                }
            }
        ],
        "familyBusiness": {
            "@type": "Organization",
            "name": "Gustaf Horwitz Stockholm",
            "startDate": "1880",
            "endDate": null,
            "establishedBy": {
                "@type": "Person",
                "name": "M Horwitz",
                "description": "Uncle"
            },
            "takenOverBy": {
                "@type": "Person",
                "name": "G H Hobwitz",
                "description": "Father"
            }
        }
    },
    "occupations": {
        "career": [
            {
                "occupational_title": "Merchant",
                "workplace": "Stockholm",
                "industry": "Wholesale",
                "start_date": "1922-1931"
            },
            {
                "occupational_title": "Chairman",
                "workplace": "Stockholm Advertising Association",
                "industry": "Advertising",
                "start_date": "1942"
            }
        ]
    }
}