{
    "original": "LÖFGREN, Nils Gustaf, Grosshandlare, Jur Kand, Halmstad, f Gbg 11/9 03 av dir Edw L o Tora Synnerdahl, gm Karin Kjellman. Stdex Hst 22, jur kand Upps 28. Tingstjg Nordmarks doms 28—31, bitr länsnot Värml 31—33, suosch sed. 33 i AB Löfgren &amp; Jönsson (partiaff i kolon.v, etabl av fad 95, AB 06). Styr.led Sk-Hall sockerengr.frn, So kolon.gr.-frn, styr.suppl Smål-Blek engr.frn mm. Stadsrev sed. 36, ordf i rev sed. 42, led avlön.nmdn, stdsflm, ordf hyresnämnden. Resor: Engl, Tyskl, Frankr, Ital, Ung, Österr, Tjeckoslov, Danm, Norge. Av trycket: Äldre konsistorieprotokoll etc i Gbgs nät i Upps skriftserie 27, div art i dags- o fackpress. Frimurare, W6. Hobby: Släktforskning.",
    "translated": "LÖFGREN, Nils Gustaf, Merchant, Juris Doctor, Halmstad, born in Gothenburg on 11th September 1903 to director Edw L and Tora Synnerdahl, married to Karin Kjellman. Graduated autumn 1922, Juris Doctor Uppsala 1928. Served as a court clerk at Nordmarks court 1928-1931, assistant county clerk in Värmland 1931-1933, assistant associate judge in AB Löfgren & Jönsson (family business in colonial trade, established by father in 1895, turned into a company in 1906). Board member of Sk-Hall sugar factory, South colonial trade company, deputy board member of Smål-Blek engraving factory, among others. City auditor from 1936, chairman of the audit board from 1942, member of the salary committee, film board, chairman of the rental board. Traveled to England, Germany, France, Italy, Hungary, Austria, Czechoslovakia, Denmark, and Norway. Written work: Older consistorial records, etc. in Gothenburg's network in Uppsala's writing series 27, various articles in daily and professional press. Freemason, W6. Hobby: Genealogy. Note: The abbreviation 'm.' followed by the partner's name indicates that the person was married in the year 19xx.",
    "structured": {
        "@context": "https://schema.org",
        "@type": "Person",
        "givenName": "Nils Gustaf",
        "familyName": "Löfgren",
        "additionalName": "",
        "birthDate": "1903-09-11",
        "birthPlace": "Gothenburg",
        "description": "Merchant, Juris Doctor",
        "memberOf": {
            "@type": "Organization",
            "name": "Freemasons",
            "identifier": "W6"
        },
        "education": {
            "@type": "EducationalOccupationalCredential",
            "educationalLevel": "Juris Doctor",
            "college": "Uppsala",
            "startDate": "1928",
            "endDate": "1928"
        },
        "spouse": {
            "@type": "Person",
            "name": "Karin Kjellman",
            "dateMarried": "19xx"
        },
        "workLocation": "Halmstad",
        "occupation": "Merchant",
        "affiliation": [
            {
                "@type": "Organization",
                "name": "Nordmarks court",
                "startDate": "1928",
                "endDate": "1931",
                "position": "Court Clerk"
            },
            {
                "@type": "Organization",
                "name": "Värmland",
                "startDate": "1931",
                "endDate": "1933",
                "position": "Assistant County Clerk"
            },
            {
                "@type": "Organization",
                "name": "AB Löfgren & Jönsson",
                "position": "Assistant Associate Judge"
            },
            {
                "@type": "Organization",
                "name": "Sk-Hall sugar factory",
                "position": "Board Member"
            },
            {
                "@type": "Organization",
                "name": "South colonial trade company",
                "position": "Board Member"
            },
            {
                "@type": "Organization",
                "name": "Smål-Blek engraving factory",
                "position": "Deputy Board Member"
            }
        ],
        "sameAs": [
            "https://www.facebook.com/nilsgustaf.lofgren",
            "https://twitter.com/nilsgustaflofgren",
            "https://www.linkedin.com/in/nilsgustaflofgren"
        ],
        "hobby": "Genealogy",
        "nationality": "Swedish",
        "traveledTo": [
            "England",
            "Germany",
            "France",
            "Italy",
            "Hungary",
            "Austria",
            "Czechoslovakia",
            "Denmark",
            "Norway"
        ],
        "writtenWorks": [
            "Older consistorial records, etc. in Gothenburg's network in Uppsala's writing series 27",
            "Various articles in daily and professional press"
        ]
    },
    "occupations": {
        "career": [
            {
                "occupational_title": "Merchant",
                "workplace": "AB Löfgren & Jönsson",
                "industry": "Colonial trade",
                "start_date": "1906"
            },
            {
                "occupational_title": "Court clerk",
                "workplace": "Nordmarks court",
                "industry": "Legal",
                "start_date": "1928"
            },
            {
                "occupational_title": "Assistant county clerk",
                "workplace": "Värmland",
                "industry": "Public administration",
                "start_date": "1931"
            },
            {
                "occupational_title": "Assistant associate judge",
                "workplace": "AB Löfgren & Jönsson",
                "industry": "Colonial trade",
                "start_date": "1933"
            },
            {
                "occupational_title": "Board member",
                "workplace": "Sk-Hall sugar factory",
                "industry": "Sugar industry",
                "start_date": "Unknown"
            },
            {
                "occupational_title": "Board member",
                "workplace": "South colonial trade company",
                "industry": "Colonial trade",
                "start_date": "Unknown"
            },
            {
                "occupational_title": "Deputy board member",
                "workplace": "Smål-Blek engraving factory",
                "industry": "Engraving",
                "start_date": "Unknown"
            },
            {
                "occupational_title": "City auditor",
                "workplace": "Unknown",
                "industry": "Public administration",
                "start_date": "1936"
            },
            {
                "occupational_title": "Chairman of the audit board",
                "workplace": "Unknown",
                "industry": "Public administration",
                "start_date": "1942"
            },
            {
                "occupational_title": "Member of the salary committee",
                "workplace": "Unknown",
                "industry": "Public administration",
                "start_date": "Unknown"
            },
            {
                "occupational_title": "Member of the film board",
                "workplace": "Unknown",
                "industry": "Entertainment",
                "start_date": "Unknown"
            },
            {
                "occupational_title": "Chairman of the rental board",
                "workplace": "Unknown",
                "industry": "Public administration",
                "start_date": "Unknown"
            }
        ]
    }
}