{
    "original": "ANDERSON, Oscar, Kontorschef. Strömstad, f Bengtsfors, Älvsb l, 21/9 93 av handl P o Ida A, gm Torborg Lundberg. Realex 09. Anst Gbgs bk, B.fors 10, kont.ch Mustad-fors 15, Bäckefors 17, Strömst 24. Led dräts.kamm. Styr.led Strst Packirig Co AB, styr.ordf Strst tennisbanefrn, skyt.frn o skyt.-krets, styr.led Gbgs o Bohusl skyt.frb. Resor: Tyskl 36. Gbgs o Bohusl skyt.frbs ftJM g. Hobbies: Jakt, Skytte, tennis.",
    "translated": "ANDERSON, Oscar, Office Manager. Strömstad, born in Bengtsfors, Älvsborg County, on September 21, 1893, to merchant P and Ida A. Married to Torborg Lundberg. Completed Realex (lower secondary school) in 1909. Employed at Gbgs (Gothenburg) bank in 1910, B.fors (Bäckefors) in 1915, Mustad-fors (Mustad Falls) as office manager in 1915, Bäckefors in 1917, and Strömstad in 1924. Member of the local council. Board member of Strömstad Packaging Co. Chairman of the board of Strömstad Tennis Club. Member of the shooting range and district shooting range association in Gothenburg and Bohuslän. Board member of Gothenburg and Bohuslän shooting association. Traveled to Germany in 1936. Participated in Gothenburg and Bohuslän shooting association's championship. Hobbies: Hunting, shooting, tennis.",
    "structured": {
        "givenName": "Oscar",
        "familyName": "Anderson",
        "jobTitle": "Office Manager",
        "birthPlace": "Bengtsfors, Älvsborg County",
        "birthDate": "1893-09-21",
        "parents": [
            {
                "givenName": "P"
            },
            {
                "givenName": "Ida",
                "familyName": "A"
            }
        ],
        "spouse": "Torborg Lundberg",
        "education": [
            {
                "schoolName": "Realex",
                "dateCompleted": "1909"
            }
        ],
        "employmentHistory": [
            {
                "employer": "Gbgs bank",
                "startDate": "1910"
            },
            {
                "employer": "B.fors",
                "startDate": "1915",
                "endDate": "1917"
            },
            {
                "employer": "Mustad-fors",
                "jobTitle": "Office Manager",
                "startDate": "1915"
            },
            {
                "employer": "Bäckefors",
                "startDate": "1917"
            },
            {
                "employer": "Strömstad",
                "startDate": "1924"
            }
        ],
        "organizations": [
            {
                "organizationName": "Strömstad Packaging Co",
                "role": "Board Member"
            },
            {
                "organizationName": "Strömstad Tennis Club",
                "role": "Chairman of the Board"
            },
            {
                "organizationName": "Gothenburg and Bohuslän Shooting Association",
                "role": "Board Member"
            }
        ],
        "memberships": [
            {
                "organizationName": "Local Council"
            },
            {
                "organizationName": "Gothenburg and Bohuslän Shooting Range Association"
            },
            {
                "organizationName": "Gothenburg and Bohuslän District Shooting Range Association"
            }
        ],
        "travels": [
            {
                "destination": "Germany",
                "date": "1936"
            }
        ],
        "sportInterests": [
            {
                "sport": "Hunting"
            },
            {
                "sport": "Shooting"
            },
            {
                "sport": "Tennis"
            }
        ]
    },
    "occupations": {
        "career": [
            {
                "occupational_title": "Office Manager",
                "workplace": "Gbgs bank",
                "industry": "Banking",
                "start_date": "1910"
            },
            {
                "occupational_title": "Office Manager",
                "workplace": "B.fors",
                "industry": "Unknown",
                "start_date": "1915"
            },
            {
                "occupational_title": "Office Manager",
                "workplace": "Mustad-fors",
                "industry": "Unknown",
                "start_date": "1915"
            },
            {
                "occupational_title": "Office Manager",
                "workplace": "Bäckefors",
                "industry": "Unknown",
                "start_date": "1917"
            },
            {
                "occupational_title": "Office Manager",
                "workplace": "Strömstad",
                "industry": "Unknown",
                "start_date": "1924"
            }
        ]
    }
}