{
    "original": "AB, Sv tidskr.förl.AB, styr.suppl AB Sthlms brygg, styr.led Sv tidn.utg.frn 26—35, ordf i dess östg.kr 21—28, ordf Sv nät ungd.frb 31— 32, led allm valm.frbs överstyr o vkst utsk, ordf sv högerpress frn 32—40. Polit o ekon studieres Engl 14, 20, 22, 35, Holl 15, Frankr 24, 35, Tyskl, Schweiz, Finl mfl länd. Av trycket: Oppositionen o ministeransvarighe-ten, pari strömn i sv polit 1809—40 (17), Sv ind.probl i krigstid (39), tidskr.upps mm. Utg Sv tidskr 31—32. RNO, RVO. °ANDERSON, Johan, Grosshandlare, Borås, f Varnum 16/9 67. Gr 92 tills m brod Bröd Andersons Herrkläder AB Borås, AB 30, vkst dir där. Fd led dräts.kamm o tax.nmd.",
    "translated": "AB - Limited company\nSv tidskr.förl.AB - Publishing company AB\nstyr.suppl AB Sthlms brygg - Board member substitute at AB Stockholm Brewery\nstyr.led Sv tidn.utg.frn 26—35 - Board member of Swedish Newspaper Publishing from 1926 to 1935\nordf i dess östg.kr 21—28 - Chairman of its East Department from 1921 to 1928\nordf Sv nät ungd.frb 31—32 - Chairman of the Swedish Youth Network from 1931 to 1932\nled allm valm.frbs överstyr o vkst utsk - Member of the Public Election Committee's Oversight and Growth Committee\nordf sv högerpress frn 32—40 - Chairman of the Swedish Right Press from 1932 to 1940\nPolit o ekon studieres Engl 14, 20, 22, 35, Holl 15, Frankr 24, 35, Tyskl, Schweiz, Finl mfl länd - Studied politics and economics in England in 1914, 1920, 1922, and 1935, in Holland in 1915, in France in 1924 and 1935, in Germany, Switzerland, Finland, and other countries\nAv trycket - Published works: Oppositionen o ministeransvarighet-en, pari strömn i sv polit 1809—40 (17), Sv ind.probl i krigstid (39), tidskr.upps mm - Published articles: Opposition and ministerial responsibility, the parallel streams in Swedish politics 1809—1940 (17), Swedish industrial problems during wartime (39), miscellaneous journal essays\nUtg Sv tidskr 31—32 - Published in the Swedish Journal from 1931 to 1932\nRNO, RVO - Royal Order of the North Star, Royal Order of Vasa\n°ANDERSON, Johan, Grosshandlare, Borås, f Varnum 16/9 67 - Johan Anderson, Merchant, Borås, born in Varnum on September 16, 1867\nGr 92 tills m brod Bröd Andersons Herrkläder AB Borås, AB 30, vkst dir där - Partnered in 1892 with his brother at Bröd Andersons Herrkläder AB Borås, became director there in 1930\nFd led dräts.kamm o tax.nmd - Former member of the finance committee and tax board",
    "structured": {
        "@context": "https://schema.org",
        "@type": "Person",
        "name": "Johan Anderson",
        "jobTitle": "Grosshandlare",
        "birthDate": "1867-09-16",
        "birthPlace": "Varnum, Sweden",
        "nationality": "Swedish",
        "memberOf": [
            {
                "@type": "Organization",
                "name": "AB - Limited company",
                "startDate": "1892"
            },
            {
                "@type": "Organization",
                "name": "Sv tidskr.förl.AB - Publishing company AB"
            },
            {
                "@type": "Organization",
                "name": "AB Sthlms brygg - Stockholm Brewery AB",
                "position": "Board member substitute"
            },
            {
                "@type": "Organization",
                "name": "Sv tidn.utg - Swedish Newspaper Publishing",
                "position": "Board member",
                "startDate": "1926",
                "endDate": "1935"
            },
            {
                "@type": "Organization",
                "name": "Sv nät ungd.frb - Swedish Youth Network",
                "position": "Chairman",
                "startDate": "1931",
                "endDate": "1932"
            },
            {
                "@type": "Organization",
                "name": "Public Election Committee",
                "position": "Committee member"
            },
            {
                "@type": "Organization",
                "name": "Swedish Right Press",
                "position": "Chairman",
                "startDate": "1932",
                "endDate": "1940"
            }
        ],
        "education": [
            {
                "@type": "EducationalOrganization",
                "name": "England",
                "startDate": "1914",
                "endDate": "1914"
            },
            {
                "@type": "EducationalOrganization",
                "name": "England",
                "startDate": "1920",
                "endDate": "1920"
            },
            {
                "@type": "EducationalOrganization",
                "name": "England",
                "startDate": "1922",
                "endDate": "1922"
            },
            {
                "@type": "EducationalOrganization",
                "name": "England",
                "startDate": "1935",
                "endDate": "1935"
            },
            {
                "@type": "EducationalOrganization",
                "name": "Holland",
                "startDate": "1915",
                "endDate": "1915"
            },
            {
                "@type": "EducationalOrganization",
                "name": "France",
                "startDate": "1924",
                "endDate": "1924"
            },
            {
                "@type": "EducationalOrganization",
                "name": "France",
                "startDate": "1935",
                "endDate": "1935"
            },
            {
                "@type": "EducationalOrganization",
                "name": "Germany"
            },
            {
                "@type": "EducationalOrganization",
                "name": "Switzerland"
            },
            {
                "@type": "EducationalOrganization",
                "name": "Finland"
            }
        ],
        "worksFor": {
            "@type": "Organization",
            "name": "Bröd Andersons Herrkläder AB",
            "location": "Borås, Sweden",
            "startDate": "1892",
            "endDate": "1930",
            "position": "Director"
        },
        "hasOccupation": [
            {
                "@type": "Organization",
                "name": "dräts.kamm - Finance Committee"
            },
            {
                "@type": "Organization",
                "name": "tax.nmd - Tax Board"
            }
        ],
        "hasAward": [
            {
                "@type": "Order",
                "name": "RNO - Royal Order of the North Star"
            },
            {
                "@type": "Order",
                "name": "RVO - Royal Order of Vasa"
            }
        ],
        "publishedWorks": [
            "Oppositionen o ministeransvarighet-en",
            "pari strömn i sv polit 1809—40 (17)",
            "Sv ind.probl i krigstid (39)",
            "tidskr.upps mm"
        ],
        "hasJournal": {
            "@type": "Periodical",
            "name": "Sv tidskr - Swedish Journal",
            "startDate": "1931",
            "endDate": "1932"
        }
    },
    "occupations": {
        "career": [
            {
                "occupational_title": "Board member substitute",
                "workplace": "AB Stockholm Brewery",
                "industry": "Beverage manufacturing",
                "start_date": "Unknown"
            },
            {
                "occupational_title": "Board member",
                "workplace": "Swedish Newspaper Publishing",
                "industry": "Media and publishing",
                "start_date": "1926"
            },
            {
                "occupational_title": "Chairman",
                "workplace": "East Department, Swedish Newspaper Publishing",
                "industry": "Media and publishing",
                "start_date": "1921"
            },
            {
                "occupational_title": "Chairman",
                "workplace": "Swedish Youth Network",
                "industry": "Youth organization",
                "start_date": "1931"
            },
            {
                "occupational_title": "Member",
                "workplace": "Public Election Committee's Oversight and Growth Committee",
                "industry": "Government",
                "start_date": "Unknown"
            },
            {
                "occupational_title": "Chairman",
                "workplace": "Swedish Right Press",
                "industry": "Media and publishing",
                "start_date": "1932"
            },
            {
                "occupational_title": "Merchant",
                "workplace": "Bröd Andersons Herrkläder AB Borås",
                "industry": "Retail",
                "start_date": "1892"
            }
        ]
    }
}