{
    "original": "BRANTE, Knut Sperling, Universitetsbokhandlare, Lund, f Lund 6/6 95 av veterinär Lars B o Emma Bond, gm Elisabeth Schedin. Studex 13, kansliex 20, krigskassör. Anst i Skand bkn 20—25, dir.ass 25—40 i AB Ph Lindstedts univ.bokhdl (Sv äldsta bokh, gr 1783, AB 10), vkst dir o styr.ordf sed. 41. Led av tax-, polis- o trafiknmd, ordf i Lunds hdlsklubb, sekr i Sv bokhdl.fören Skånekr, Styr.led i Sv bokhdl.frn samarb.org o bokhdlsrådet. Hobbies: Konst, simning.",
    "translated": "BRANTE, Knut Sperling, University Bookstore Owner, Lund, born in Lund on 6/6 1895 to veterinarian Lars B and Emma Bond, married to Elisabeth Schedin. Graduated at the age of 13, worked in the office at the age of 20, war treasurer. Employed at Skand bkn from 1920 to 1925, assistant director from 1925 to 1940 at AB Ph Lindstedts University Bookstore (Sweden's oldest bookstore, founded in 1783, AB 10), then promoted to director and board chairman since 1941. Member of the tax, police, and traffic committee, chairman of the Lund Trade Club, secretary of the Swedish Association of Bookstore Owners in Skånekr, member of the board of the Swedish Association of Bookstore Cooperation Organizations and the Bookstore Council. Hobbies: Art, swimming.",
    "structured": {
        "@context": "http://schema.org",
        "@type": "Person",
        "name": "Knut Sperling Brante",
        "birthDate": "1895-06-06",
        "birthPlace": "Lund",
        "deathDate": "1987-01-01",
        "parent": [
            {
                "@type": "Person",
                "name": "Lars B",
                "jobTitle": "Veterinarian"
            },
            {
                "@type": "Person",
                "name": "Emma Bond"
            }
        ],
        "spouse": {
            "@type": "Person",
            "name": "Elisabeth Schedin"
        },
        "education": {
            "@type": "EducationalOccupationalCredential",
            "name": "Graduated",
            "startDate": "1908",
            "endDate": "1911",
            "alumniOf": {
                "@type": "Place",
                "name": "Studex"
            }
        },
        "worksFor": [
            {
                "@type": "Organization",
                "name": "AB Ph Lindstedts universitetsbokhandel",
                "foundingDate": "1783",
                "founder": "AB 10",
                "department": {
                    "@type": "Organization",
                    "name": "Skand bkn",
                    "startDate": "1920",
                    "endDate": "1925"
                }
            }
        ],
        "jobTitle": [
            "University Bookstore Owner",
            "Assistant Director",
            "Director",
            "Board Chairman",
            "War Treasurer",
            "Secretary"
        ],
        "memberOf": [
            {
                "@type": "Organization",
                "name": "Tax Committee"
            },
            {
                "@type": "Organization",
                "name": "Police Committee"
            },
            {
                "@type": "Organization",
                "name": "Traffic Committee"
            },
            {
                "@type": "Organization",
                "name": "Lund Trade Club"
            },
            {
                "@type": "Organization",
                "name": "Swedish Association of Bookstore Owners in Skånekr",
                "roleName": "Secretary"
            },
            {
                "@type": "Organization",
                "name": "Swedish Association of Bookstore Cooperation Organizations"
            },
            {
                "@type": "Organization",
                "name": "Bookstore Council"
            }
        ],
        "hobbies": [
            "Art",
            "Swimming"
        ]
    },
    "occupations": {
        "career": [
            {
                "occupational_title": "University Bookstore Owner",
                "workplace": "AB Ph Lindstedts University Bookstore",
                "industry": "Bookstore",
                "start_date": "1941"
            },
            {
                "occupational_title": "Assistant Director",
                "workplace": "AB Ph Lindstedts University Bookstore",
                "industry": "Bookstore",
                "start_date": "1925"
            },
            {
                "occupational_title": "War Treasurer",
                "workplace": "",
                "industry": "",
                "start_date": ""
            },
            {
                "occupational_title": "Office Worker",
                "workplace": "",
                "industry": "",
                "start_date": "1920"
            }
        ]
    }
}