{
    "original": "ODQVIST, Karl Torsten Lennart, Civilingenjör, Eskilstuna, f Sthlm 6/10 11 av reg.- läk K A O o Inez Wahlén, gm Ann Marie Edlind. Studex Sthlm 29, KTH (maskinbyggn 0 mek tekn, spec.stud v avd f bergsvetenskap) 30—35. Anst v AB Nomy i Ulvsunda 35 m plac bl a vid Nomy Bearings Ltd i London, SKF i Gbg 37—38, v AB Bolinder-Munktell i Eskilstuna sed. 38, ss chef f maskinlab sed. 42. Resor: Medelhavsländerna, Tyskl, Frankr, Tjeckoslov o Engl v öl tillf. Av trycket: Upps 1 facktidskr.",
    "translated": "ODQVIST, Karl Torsten Lennart, Civil Engineer, Eskilstuna, born in Stockholm on October 6th, 1911, son of Regimental Doctor K.A.O. and Inez Wahlén, married to Ann Marie Edlind. Completed his high school education in Stockholm in 1929, and studied at the Royal Institute of Technology (specializing in mechanical engineering, with additional studies in the mining sciences department) from 1930 to 1935. Employed by AB Nomy in Ulvsunda from 1935, with various assignments including Nomy Bearings Ltd in London, SKF in Gothenburg from 1937 to 1938, and with AB Bolinder-Munktell in Eskilstuna since 1938, serving as the head of the machine laboratory since 1942. Traveled to Mediterranean countries, Germany, France, Czechoslovakia, and England for professional purposes. Published one article in a professional journal.",
    "structured": {
        "name": "Karl Torsten Lennart Odqvist",
        "birthDate": "1911-10-06",
        "birthPlace": "Stockholm",
        "occupation": "Civil Engineer",
        "address": "Eskilstuna",
        "parents": [
            {
                "name": "K.A.O. Odqvist",
                "occupation": "Regimental Doctor"
            },
            {
                "name": "Inez Wahlén"
            }
        ],
        "spouse": {
            "name": "Ann Marie Edlind"
        },
        "education": [
            {
                "institution": "Stockholm High School",
                "dateCompleted": "1929"
            },
            {
                "institution": "Royal Institute of Technology",
                "specialization": "Mechanical Engineering",
                "additionalStudies": "Mining Sciences",
                "dateCompleted": "1935"
            }
        ],
        "employmentHistory": [
            {
                "employer": "AB Nomy",
                "location": "Ulvsunda",
                "startDate": "1935",
                "endDate": "1938",
                "positions": [
                    {
                        "title": "Engineer",
                        "assignments": [
                            "Nomy Bearings Ltd, London"
                        ]
                    },
                    {
                        "title": "Engineer",
                        "employer": "SKF",
                        "location": "Gothenburg",
                        "startDate": "1937",
                        "endDate": "1938"
                    },
                    {
                        "title": "Chief of Machine Laboratory",
                        "employer": "AB Bolinder-Munktell",
                        "location": "Eskilstuna",
                        "startDate": "1938"
                    }
                ]
            }
        ],
        "travels": [
            "Mediterranean countries",
            "Germany",
            "France",
            "Czechoslovakia",
            "England"
        ],
        "publications": [
            {
                "title": "Upps 1 facktidskr"
            }
        ]
    },
    "occupations": {
        "career": [
            {
                "occupational_title": "Civil Engineer",
                "workplace": "AB Nomy",
                "industry": "Engineering",
                "start_date": "1935"
            },
            {
                "occupational_title": "Engineer",
                "workplace": "Nomy Bearings Ltd",
                "industry": "Engineering",
                "start_date": "Unknown"
            },
            {
                "occupational_title": "Engineer",
                "workplace": "SKF",
                "industry": "Engineering",
                "start_date": "1937"
            },
            {
                "occupational_title": "Engineer",
                "workplace": "AB Bolinder-Munktell",
                "industry": "Engineering",
                "start_date": "1938"
            },
            {
                "occupational_title": "Head of Machine Laboratory",
                "workplace": "AB Bolinder-Munktell",
                "industry": "Engineering",
                "start_date": "1942"
            }
        ]
    }
}