{
    "original": "BLOMBERG, Dag Arvidsson, Gatuinspektör hos Väg- o Vattenb.styr, Saltsjöbaden, f Motala 30/5 99 av överstelöjtn J A B o Gerda Westrell, gm Gullan Dufwa (d). Studex Malmö 18, KTH (V o V) 20—24. Bitr ing å väg- o vattendistr 24—30, extra byråing Väg-o Vattenb.styr 30—34, byråing där 34, sekt.ch h Stat Arb.markn.kommiss 40—43. Led 32 års^ utredn betr beredsk.arb, sakk betr beredsk.-arb 36, led av skärgårdsutredn 38, expert h Investeringsutredningen 43.",
    "translated": "BLOMBERG, Dag Arvidsson, Street Inspector at the Road and Water Authority, Saltsjöbaden, born in Motala on May 30, 1899, son of Lieutenant Colonel J A B and Gerda Westrell, married to Gullan Dufwa (deceased). Graduated from Malmö School 1918, Royal Institute of Technology (Road and Water) 1920-1924. Assistant Engineer at the Road and Water District 1924-1930, Extra Clerk at the Road and Water Authority 1930-1934, Clerk there in 1934, Section Chief at the State Labor Market Commission 1940-1943. Led investigations for 32 years regarding emergency work, expert in emergency work in 1936, member of the Archipelago Investigation in 1938, expert in the Investment Investigation in 1943.",
    "structured": {
        "@context": "https://schema.org",
        "@type": "Person",
        "name": "Dag Arvidsson Blomberg",
        "birthDate": "1899-05-30",
        "birthPlace": "Motala",
        "deathDate": null,
        "parents": [
            {
                "name": "J A B",
                "relationship": "father"
            },
            {
                "name": "Gerda Westrell",
                "relationship": "mother"
            }
        ],
        "spouse": [
            {
                "name": "Gullan Dufwa",
                "deathDate": "unknown"
            }
        ],
        "jobTitle": [
            "Street Inspector",
            "Assistant Engineer",
            "Extra Clerk",
            "Clerk",
            "Section Chief",
            "Investigation Expert"
        ],
        "worksFor": [
            {
                "name": "Road and Water Authority",
                "startDate": "unknown",
                "endDate": "unknown"
            },
            {
                "name": "State Labor Market Commission",
                "startDate": "1940",
                "endDate": "1943"
            }
        ],
        "education": [
            {
                "institution": "Malmö School",
                "startDate": "1918",
                "endDate": "unknown"
            },
            {
                "institution": "Royal Institute of Technology",
                "startDate": "1920",
                "endDate": "1924"
            }
        ],
        "memberOf": [
            {
                "name": "Archipelago Investigation",
                "startDate": "1938",
                "endDate": "unknown"
            },
            {
                "name": "Investment Investigation",
                "startDate": "1943",
                "endDate": "unknown"
            }
        ],
        "description": "Street Inspector at the Road and Water Authority, Saltsjöbaden. Graduated from Malmö School and Royal Institute of Technology. Worked as an Assistant Engineer, Extra Clerk, Clerk, and Section Chief. Led investigations on emergency work and served as an expert in emergency work."
    },
    "occupations": {
        "career": [
            {
                "occupational_title": "Street Inspector",
                "workplace": "Road and Water Authority",
                "industry": "Government",
                "start_date": "Unknown"
            },
            {
                "occupational_title": "Assistant Engineer",
                "workplace": "Road and Water District",
                "industry": "Government",
                "start_date": "1924"
            },
            {
                "occupational_title": "Extra Clerk",
                "workplace": "Road and Water Authority",
                "industry": "Government",
                "start_date": "1930"
            },
            {
                "occupational_title": "Clerk",
                "workplace": "Road and Water Authority",
                "industry": "Government",
                "start_date": "1934"
            },
            {
                "occupational_title": "Section Chief",
                "workplace": "State Labor Market Commission",
                "industry": "Government",
                "start_date": "1940"
            }
        ]
    }
}