{
    "original": "FANT, Gösta, Ingenjör, Ålsten, f 5/8 84 av stins C G F o Lydia Lénström, gm Vicky Myrberg. Sala allm lärov, ex Tekn sk Sthlm (maskin) 04, stud Tyskl 04—06. Ing Fören El AB Sthlm o Ludvika 06—14, därav fil.ch i Sydam 09—11, ch f Graham Brothers el avd Sthlm 13—34, komm. repres. f Mather Platt Ltd, London, sed. 34, aut sprinkleranläggn. Ag villa i Ålsten. Styr.led AB Kristian Sthlm. Resor: Tyskl 04—06, Frankr, Engl, Sydam 09—11, Danm, Norge, Finl. Av trycket: Div upps i fackpress om radiosänd o centralradio-anläggn, aut eldsläckn m sprinkler, släckn av oljebränd m Mulsifyre-syst. Sv Tekn.frn, Sthlms Sportfiskeklubb. Hobbies: Jakt, fiske, orientering, blomsterodling, litteratur.",
    "translated": "FANT, Gösta, Engineer, Ålsten, b. 5/8 84 to stationmaster C G F and Lydia Lénström, m. Vicky Myrberg. Graduate of Sala General School, Technical School Stockholm (mechanical) 04, studied German 04-06. Engineer at El AB Stockholm and Ludvika 06-14, including a degree in South America 09-11, head of Graham Brothers electrical department Stockholm 13-34, commissioned representative of Mather Platt Ltd, London, since 34, author of sprinkler systems at Ag Villa in Ålsten. Board member of AB Kristian Stockholm. Travels: German 04-06, France, England, South America 09-11, Denmark, Norway, Finland. Publications: Various articles in trade press on radio transmitting and central radio systems, automatic sprinkler fire extinguishing, and extinguishing oil fires with the Mulsifyre system. Member of the Swedish Society of Technology, Stockholm Sports Fishing Club. Hobbies: Hunting, fishing, orienteering, gardening, literature.\n\nNote: The abbreviation '\\d\\d m. partners name' indicates the person got married in the year 19xx.",
    "structured": {
        "@context": "https://schema.org",
        "@type": "Person",
        "givenName": "Gösta",
        "familyName": "Fant",
        "jobTitle": "Engineer",
        "address": {
            "@type": "PostalAddress",
            "addressLocality": "Ålsten"
        },
        "birthDate": "1884-08-05",
        "parents": [
            {
                "@type": "Person",
                "givenName": "C G F",
                "familyName": "Lénström",
                "jobTitle": "Stationmaster"
            },
            {
                "@type": "Person",
                "givenName": "Lydia",
                "familyName": "Lénström"
            }
        ],
        "spouse": {
            "@type": "Person",
            "givenName": "Vicky",
            "familyName": "Myrberg"
        },
        "education": [
            {
                "@type": "EducationalOccupationalCredential",
                "credentialCategory": "Graduate",
                "alumniOf": {
                    "@type": "EducationalOrganization",
                    "name": "Sala General School"
                }
            },
            {
                "@type": "EducationalOccupationalCredential",
                "credentialCategory": "Degree",
                "alumniOf": {
                    "@type": "EducationalOrganization",
                    "name": "Technical School Stockholm (mechanical)"
                },
                "endDate": "1904"
            },
            {
                "@type": "EducationalOccupationalCredential",
                "credentialCategory": "Course",
                "alumniOf": {
                    "@type": "EducationalOrganization",
                    "name": "German Language Course"
                },
                "startDate": "1904",
                "endDate": "1906"
            }
        ],
        "worksFor": [
            {
                "@type": "Organization",
                "name": "El AB"
            },
            {
                "@type": "Organization",
                "name": "Graham Brothers"
            },
            {
                "@type": "Organization",
                "name": "Mather Platt Ltd"
            },
            {
                "@type": "Organization",
                "name": "AB Kristian Stockholm"
            }
        ],
        "memberOf": [
            {
                "@type": "Organization",
                "name": "Swedish Society of Technology"
            },
            {
                "@type": "Organization",
                "name": "Stockholm Sports Fishing Club"
            }
        ],
        "additionalName": [
            "Ingenjör"
        ],
        "description": "Author, Engineer, Sprinkler Systems Specialist",
        "deathDate": "unknown",
        "marriedTo": {
            "@type": "Event",
            "startDate": "19xx"
        },
        "hobbies": [
            "Hunting",
            "Fishing",
            "Orienteering",
            "Gardening",
            "Literature"
        ],
        "travels": [
            {
                "@type": "Place",
                "name": "Germany"
            },
            {
                "@type": "Place",
                "name": "France"
            },
            {
                "@type": "Place",
                "name": "England"
            },
            {
                "@type": "Place",
                "name": "South America"
            },
            {
                "@type": "Place",
                "name": "Denmark"
            },
            {
                "@type": "Place",
                "name": "Norway"
            },
            {
                "@type": "Place",
                "name": "Finland"
            }
        ],
        "publications": [
            "Various articles in trade press on radio transmitting and central radio systems",
            "Automatic sprinkler fire extinguishing",
            "Extinguishing oil fires with the Mulsifyre system"
        ]
    },
    "occupations": {
        "career": [
            {
                "occupational_title": "Engineer",
                "workplace": "El AB Sthlm o Ludvika",
                "industry": "Electrical",
                "start_date": "1906"
            },
            {
                "occupational_title": "Chief of Graham Brothers electrical department",
                "workplace": "Sthlm",
                "industry": "Electrical",
                "start_date": "1913"
            },
            {
                "occupational_title": "Commissioned representative",
                "workplace": "Mather Platt Ltd, London",
                "industry": "Engineering",
                "start_date": "1934"
            }
        ]
    }
}