{
    "original": "KIHLBOM, Nils Elias Tommy, Kapten, Assuransdirektör, Malmö, f Mariestad 2/7 86 av kapt J N K o Maria Forsman, gm Eva Rabe. Allm lärov Mariest, däreft studier i Engl o Tyskl, t sjöss 03, styrm o sjökapt.ex Gbg 07. Resoff 08. Anst: Styrm o bef.ha\\ å segel- o ångfartyg 10—15, besiktn.man o haverichef f Sjöförs.AB Öresund 16, vkst dir där 27. Ordf i dir Malmö nav.sk o stift »42 års studielånefond» där, v.ordf hdls- o sjöf-nmd Malmö, led hamndir o 41 års isbryt.-utredn, flm Skånes hdlskamm. Styr.led Sjö-försäkr AB Öresund o AB Aequitas, v. ordf Försäkr AB Iris. Ordf Sv Krigsförsäkr Poolen o Nord Krigsförsäkr Poolens arb.utsk. Led Sv Krigsförsäkr Poolens Skaderegl.utsk o Sjöassuradörernas Frn :s Gemens Cover-kté, ktén f det mindre kaskot mfl. Ordf i Malmö Sjöfartsfrn, Malmö Sjöfartsmuseum» Sydsv Navigationsstiftelsen, Ringsjöns Villaäg.frn, Frn f odling av laxfiskar. Vkst led i styr f Malmöhus l Rusthåll, sekr i S :a Sv Sportfiskeklubb, Styr.led Sv Sportfiskarfrb. RVO, FinlVRO, Emmerymedaljen. Hobbies: Fiske o jakt, litteratur.",
    "translated": "KIHLBOM, Nils Elias Tommy, Captain, Insurance Director, Malmö, born in Mariestad on July 2, 1886, son of Captain J.N.K. and Maria Forsman, married to Eva Rabe. General education in Mariestad, followed by studies in English and German, at sea in 1903, navigation officer and ship captain's exam in Gothenburg in 1907. Reserve officer in 1908. Employment: Navigation officer and commander on sailing and steam vessels from 1910 to 1915, inspector and chief of accidents for Sjöförsäkrings AB Öresund from 1916, deputy managing director there from 1927. Chairman of the board of Malmö navigation school and the \"42 years study loan fund,\" vice chairman of Malmö commerce and shipping board, member of the port board and the \"41 years icebreaker investigation,\" film Skåne commerce chamber. Board member of Sjöförsäkrings AB Öresund and AB Aequitas, vice chairman of Försäkrings AB Iris. Chairman of the Swedish war insurance pool and the Nordic war insurance pool's working committee. Member of the Swedish war insurance pool's damage regulation committee and the Swedish insurers' Joint Cover Committee, among others. Chairman of the Malmö maritime association, \"Malmö maritime museum,\" South Sweden navigation foundation, Ringsjön villa owners' association, association for cultivation of salmon fish. Active member in the board of Malmöhus l Rusthåll, secretary of the Swedish Sports Fishing Club, board member of the Swedish Sports Fishermen's Association. Received the Royal Norwegian Order of Merit, Emmery medal. Hobbies: Fishing, hunting, literature.",
    "structured": {
        "@context": "https://schema.org",
        "@type": "Person",
        "name": "Nils Elias Tommy Kihlbom",
        "birthDate": "1886-07-02",
        "birthPlace": "Mariestad",
        "deathDate": "",
        "description": "Captain, Insurance Director",
        "spouse": {
            "@type": "Person",
            "name": "Eva Rabe"
        },
        "parents": [
            {
                "@type": "Person",
                "name": "Captain J.N.K."
            },
            {
                "@type": "Person",
                "name": "Maria Forsman"
            }
        ],
        "education": [
            {
                "@type": "EducationalOrganization",
                "name": "Mariestad General Education"
            },
            {
                "@type": "EducationalOrganization",
                "name": "Studies in English and German"
            }
        ],
        "occupation": [
            {
                "@type": "OrganizationRole",
                "name": "Navigation Officer",
                "startDate": "1910",
                "endDate": "1915"
            },
            {
                "@type": "OrganizationRole",
                "name": "Inspector and Chief of Accidents",
                "startDate": "1916",
                "organization": {
                    "@type": "Organization",
                    "name": "Sjöförsäkrings AB Öresund"
                }
            },
            {
                "@type": "OrganizationRole",
                "name": "Deputy Managing Director",
                "startDate": "1927",
                "organization": {
                    "@type": "Organization",
                    "name": "Sjöförsäkrings AB Öresund"
                }
            }
        ],
        "memberOf": [
            {
                "@type": "Organization",
                "name": "Malmö Navigation School"
            },
            {
                "@type": "Organization",
                "name": "Malmö Commerce and Shipping Board"
            },
            {
                "@type": "Organization",
                "name": "Port Board"
            },
            {
                "@type": "Organization",
                "name": "Skåne Commerce Chamber"
            },
            {
                "@type": "Organization",
                "name": "Malmö Maritime Association"
            },
            {
                "@type": "Organization",
                "name": "Malmö Maritime Museum"
            },
            {
                "@type": "Organization",
                "name": "South Sweden Navigation Foundation"
            },
            {
                "@type": "Organization",
                "name": "Ringsjön Villa Owners' Association"
            },
            {
                "@type": "Organization",
                "name": "Association for Cultivation of Salmon Fish"
            },
            {
                "@type": "Organization",
                "name": "Malmöhus l Rusthåll"
            },
            {
                "@type": "Organization",
                "name": "Swedish Sports Fishing Club"
            },
            {
                "@type": "Organization",
                "name": "Swedish Sports Fishermen's Association"
            }
        ],
        "honorificSuffix": "RVO",
        "awards": [
            {
                "@type": "Order",
                "name": "Royal Norwegian Order of Merit"
            },
            {
                "@type": "Medal",
                "name": "Emmery Medal"
            }
        ],
        "hasOccupation": [
            {
                "@type": "OrganizationRole",
                "name": "Chairman",
                "startDate": "unknown",
                "organization": {
                    "@type": "Organization",
                    "name": "Sv Krigsförsäkr Poolen"
                }
            },
            {
                "@type": "OrganizationRole",
                "name": "Chairman",
                "startDate": "unknown",
                "organization": {
                    "@type": "Organization",
                    "name": "Nord Krigsförsäkr Poolens arb.utsk"
                }
            },
            {
                "@type": "OrganizationRole",
                "name": "Member",
                "startDate": "unknown",
                "organization": {
                    "@type": "Organization",
                    "name": "Sv Krigsförsäkr Poolens Skaderegl.utsk"
                }
            },
            {
                "@type": "OrganizationRole",
                "name": "Member",
                "startDate": "unknown",
                "organization": {
                    "@type": "Organization",
                    "name": "Sjöassuradörernas Frn :s Gemens Cover-kté"
                }
            }
        ],
        "hobbies": "Fishing, hunting, literature"
    },
    "occupations": {
        "career": [
            {
                "occupational_title": "Captain",
                "workplace": "At sea",
                "industry": "Maritime",
                "start_date": "1903"
            },
            {
                "occupational_title": "Navigation officer and commander",
                "workplace": "Sailing and steam vessels",
                "industry": "Maritime",
                "start_date": "1910"
            },
            {
                "occupational_title": "Inspector and Chief of Accidents",
                "workplace": "Sjöförsäkrings AB Öresund",
                "industry": "Insurance",
                "start_date": "1916"
            },
            {
                "occupational_title": "Deputy Managing Director",
                "workplace": "Sjöförsäkrings AB Öresund",
                "industry": "Insurance",
                "start_date": "1927"
            },
            {
                "occupational_title": "Chairman of the Board",
                "workplace": "Malmö Navigation School",
                "industry": "Education",
                "start_date": "Unknown"
            },
            {
                "occupational_title": "Chairman of the Board",
                "workplace": "Malmö commerce and shipping board",
                "industry": "Business",
                "start_date": "Unknown"
            },
            {
                "occupational_title": "Member of the Port Board",
                "workplace": "Unknown",
                "industry": "Maritime",
                "start_date": "Unknown"
            },
            {
                "occupational_title": "Chairman of the Swedish War Insurance Pool",
                "workplace": "Unknown",
                "industry": "Insurance",
                "start_date": "Unknown"
            },
            {
                "occupational_title": "Vice Chairman of the Swedish Insurers' Joint Cover Committee",
                "workplace": "Unknown",
                "industry": "Insurance",
                "start_date": "Unknown"
            },
            {
                "occupational_title": "Chairman of the Malmö Maritime Association",
                "workplace": "Unknown",
                "industry": "Maritime",
                "start_date": "Unknown"
            }
        ]
    }
}