{
    "original": "MALMFORS, Gustaf, Kraftverksdirektör, Umeå, f Norberg, Västml, 30/7 90 av järnhand! J Pettersson o Matilda Andersson, gm Anna Mollen. Ex KTH (eltekn) 14, uljt 14, ljt 17, kapt I 13 res 29. Ing Graham Brothers 15, verkstadsing Sv ackumulator AB Jungner 16— 18, chefsass Motala kraftvk 18—23, bitr distr.-ing 23—28, distr.ing Trollhätte kraftv 28—39, kraftvksdir öv Norrl kraftvk sed. 39. V. ordf Västerb tekn frn. RVO; Bohus l Istfrb SM.",
    "translated": "MALMFORS, Gustaf, Power Plant Director, Umeå, b. Norberg, Västmanland, July 30th, 1890, the son of J Pettersson and Matilda Andersson, married to Anna Mollen. Former student at KTH (Royal Institute of Technology), specializing in electrical engineering in 1914, advanced studies in 1914, promoted to lieutenant in 1917, and captain in 1913 to 1929. Started working at Graham Brothers in 1915, then worked as an engineering engineer at Sv Accummulator AB Jungner from 1916 to 1918. Served as Chief Assistant at Motala Power Plant from 1918 to 1923, then as Deputy District Engineer from 1923 to 1928. Worked as District Engineer at Trollhätte Power Plant from 1928 to 1939. Became a Power Plant Director in the Northern Power Plant since 1939. Vice Chairman of Västerbotten Technical Association, received the Royal Order of Vasa (RVO) and represented Bohus l Istfrb at the Swedish Mastership.",
    "structured": {
        "@context": "https://schema.org",
        "@type": "Person",
        "name": "Gustaf Malmfors",
        "jobTitle": "Power Plant Director",
        "birthDate": "1890-07-30",
        "birthPlace": "Norberg, Västmanland",
        "parent": [
            {
                "@type": "Person",
                "name": "J Pettersson"
            },
            {
                "@type": "Person",
                "name": "Matilda Andersson"
            }
        ],
        "spouse": {
            "@type": "Person",
            "name": "Anna Mollen"
        },
        "education": {
            "@type": "EducationalOccupationalCredential",
            "educationalLevel": "Bachelor's degree",
            "degreeName": "Electrical Engineering",
            "educationalCredentialAwarded": "KTH (Royal Institute of Technology)"
        },
        "alumniOf": "KTH (Royal Institute of Technology)",
        "employmentHistory": [
            {
                "@type": "OrganizationRole",
                "startDate": "1915",
                "endDate": "1915",
                "roleName": "Graham Brothers",
                "description": "Engineering position"
            },
            {
                "@type": "OrganizationRole",
                "startDate": "1916",
                "endDate": "1918",
                "roleName": "Sv Accummulator AB Jungner",
                "description": "Engineering Engineer"
            },
            {
                "@type": "OrganizationRole",
                "startDate": "1918",
                "endDate": "1923",
                "roleName": "Motala Power Plant",
                "description": "Chief Assistant"
            },
            {
                "@type": "OrganizationRole",
                "startDate": "1923",
                "endDate": "1928",
                "roleName": "Trollhätte Power Plant",
                "description": "Deputy District Engineer"
            },
            {
                "@type": "OrganizationRole",
                "startDate": "1928",
                "endDate": "1939",
                "roleName": "Trollhätte Power Plant",
                "description": "District Engineer"
            },
            {
                "@type": "OrganizationRole",
                "startDate": "1939",
                "roleName": "Northern Power Plant",
                "description": "Power Plant Director"
            }
        ],
        "memberOf": {
            "@type": "Organization",
            "name": "Västerbotten Technical Association",
            "roleName": "Vice Chairman"
        },
        "award": {
            "@type": "Order",
            "name": "Royal Order of Vasa (RVO)"
        },
        "representativeOf": {
            "@type": "Organization",
            "name": "Bohus l Istfrb",
            "description": "Representative at the Swedish Mastership"
        }
    },
    "occupations": {
        "career": [
            {
                "occupational_title": "Power Plant Director",
                "workplace": "Umeå",
                "industry": "Power Plant",
                "start_date": "1939"
            },
            {
                "occupational_title": "Chief Assistant",
                "workplace": "Motala Power Plant",
                "industry": "Power Plant",
                "start_date": "1918"
            },
            {
                "occupational_title": "Deputy District Engineer",
                "workplace": "Trollhätte Power Plant",
                "industry": "Power Plant",
                "start_date": "1923"
            },
            {
                "occupational_title": "District Engineer",
                "workplace": "Trollhätte Power Plant",
                "industry": "Power Plant",
                "start_date": "1928"
            },
            {
                "occupational_title": "Engineering Engineer",
                "workplace": "Sv Accummulator AB Jungner",
                "industry": "Electrical Engineering",
                "start_date": "1916"
            }
        ]
    }
}