{
    "original": "RYDBECK, Patrik Samuel, Bergsingenjör, Göteborg, f Krst 13/3 83 av fabr P R o Hedvig Widerström, gm Elsa Tauvon. Studex 02, KTH 06. Ing AB Pålen &amp; Rydbeck Nättraby 09—13, konstr SKF 14—16, övering o ritkont.ch där 16—18 o fabr.ch sed. 18. Styr.led Gr Hotell Haglund AB, Wedevågs br AB, Ind.AB Sv automatvapen (SÄV), led överstyr f Sv verkst.frn, v. ordf dess v:a krets, flm Sv arb.giv.frn, styr.led CTH, div kommun uppdr i Gbg, ordf öl frn. KVO2kl, RNO, LIVA, IVA mindre GM.",
    "translated": "RYDBECK, Patrik Samuel, Mining Engineer, Gothenburg, born March 13th, 1883, son of factory owner P.R. and Hedvig Widerström, married to Elsa Tauvon. Graduated 1902, Royal Institute of Technology (KTH) 1906. Engineer at AB Pålen & Rydbeck Nättraby 1909-1913, construction at SKF 1914-1916, head engineer and drawing office manager since 1916 and factory manager since 1918. Board member of Gr Hotell Haglund AB, Wedevågs br AB, Ind.AB Sv automatvapen (SÄV), and chairman of the board of Swedish Machinery Manufacturers Association (Sv verkst.frn). Vice chairman of its western district, member of the Swedish Employers' Confederation (Sv arb.giv.frn). Board member of the Chalmers University of Technology (CTH), various municipal assignments in Gothenburg, chairman of the Öl brewing company. Knight of the Royal Order of Vasa (KVO2kl), Commander of the Order of the Sword (RNO), Knight of the Order of the Polar Star (LIVA), member of the Royal Swedish Academy of Engineering Sciences (IVA), recipient of lesser orders and medals.",
    "structured": {
        "@context": "http://schema.org",
        "@type": "Person",
        "name": "Patrik Samuel Rydbeck",
        "birthDate": "1883-03-13",
        "birthPlace": "Gothenburg",
        "parents": {
            "@type": "Person",
            "father": "P.R.",
            "mother": "Hedvig Widerström"
        },
        "spouse": {
            "@type": "Person",
            "name": "Elsa Tauvon"
        },
        "jobTitle": "Mining Engineer",
        "affiliation": [
            {
                "@type": "Organization",
                "name": "AB Pålen & Rydbeck Nättraby",
                "startDate": "1909",
                "endDate": "1913",
                "role": "Engineer"
            },
            {
                "@type": "Organization",
                "name": "SKF",
                "startDate": "1914",
                "endDate": "1916",
                "role": "Construction Engineer"
            },
            {
                "@type": "Organization",
                "name": "SKF",
                "startDate": "1916",
                "endDate": "1918",
                "role": "Head Engineer and Drawing Office Manager"
            },
            {
                "@type": "Organization",
                "name": "SKF",
                "startDate": "1918",
                "role": "Factory Manager"
            },
            {
                "@type": "Organization",
                "name": "Gr Hotell Haglund AB",
                "role": "Board Member"
            },
            {
                "@type": "Organization",
                "name": "Wedevågs br AB",
                "role": "Board Member"
            },
            {
                "@type": "Organization",
                "name": "Ind.AB Sv automatvapen (SÄV)",
                "role": "Board Member"
            },
            {
                "@type": "Organization",
                "name": "Swedish Machinery Manufacturers Association (Sv verkst.frn)",
                "role": "Chairman of the Board"
            },
            {
                "@type": "Organization",
                "name": "Swedish Employers' Confederation (Sv arb.giv.frn)",
                "role": "Member"
            },
            {
                "@type": "Organization",
                "name": "Chalmers University of Technology (CTH)",
                "role": "Board Member"
            },
            {
                "@type": "Organization",
                "name": "Gothenburg Municipality",
                "role": "Various Municipal Assignments"
            },
            {
                "@type": "Organization",
                "name": "Öl Brewing Company",
                "role": "Chairman"
            }
        ],
        "awards": [
            {
                "@type": "Order",
                "name": "Royal Order of Vasa",
                "awardDate": "Unknown",
                "awardLevel": "Knight Second Class"
            },
            {
                "@type": "Order",
                "name": "Order of the Sword",
                "awardDate": "Unknown",
                "awardLevel": "Commander"
            },
            {
                "@type": "Order",
                "name": "Order of the Polar Star",
                "awardDate": "Unknown",
                "awardLevel": "Knight"
            }
        ],
        "memberships": [
            {
                "@type": "Organization",
                "name": "Royal Swedish Academy of Engineering Sciences (IVA)",
                "membershipStartDate": "Unknown"
            }
        ]
    },
    "occupations": {
        "career": [
            {
                "occupational_title": "Mining Engineer",
                "workplace": "AB Pålen & Rydbeck Nättraby",
                "industry": "Mining",
                "start_date": "1909"
            },
            {
                "occupational_title": "Construction Engineer",
                "workplace": "SKF",
                "industry": "Manufacturing",
                "start_date": "1914"
            },
            {
                "occupational_title": "Head Engineer and Drawing Office Manager",
                "workplace": "SKF",
                "industry": "Manufacturing",
                "start_date": "1916"
            },
            {
                "occupational_title": "Factory Manager",
                "workplace": "SKF",
                "industry": "Manufacturing",
                "start_date": "1918"
            }
        ]
    }
}