{
    "original": "FRISTEDT, Knut Albrekt (Alle), Konsul, Norrköping, f Linköping 12/4 72 av kr.läns-man Aug Fristedt o Anna Crona, gm Karin Ekstam. Studex Linkp. Anst fma Axel Andersén &amp; Co Nrkp 91, delas sed. 00, vkst dir clta AB:s Eftr sed. 10. Tjeckoslov kons sed. 24. Kyrkovärd, kyrkoråd. Led lokal- o centralstyr f östgötabkn, styr.led J Fristedts AB, Ögl ind- o hdlskamm, Tjeckoslov hdlskamm Sthlm, led Gustavianska stift f ungdomsvård, Reuterskiöldska Barnhusinrättn mfl. Resor 1 de fi eur länd. RVO, TjslVLO. Hobbies: Lantbruk, filateli.",
    "translated": "FRISTEDT, Knut Albrekt (Alle), Consul, Norrköping, born in Linköping on April 12, 1872, son of county officer Aug Fristedt and Anna Crona, married to Karin Ekstam. Graduated from Linköping High School. Employee at Axel Andersén & Co in Norrköping in 1891, later became a managing director and partner in the company. Appointed Consul of Czechoslovakia in 1924. Churchwarden, member of the church council. Member of the local and central boards of Östgöta Bank, board member of J Fristedts AB, Öglind Industrial and Trade Chamber, Czechoslovak Trade Chamber in Stockholm, and the Gustavianska Foundation for Youth Welfare, Reuterskiöld's Children's Institution, among others. Traveled extensively throughout Europe. Recipient of the Order of the Polar Star (RVO) and the Swedish Medal for Distinguished Service (TjslVLO). Hobbies: Agriculture, philately.",
    "structured": {
        "@context": "https://schema.org",
        "@type": "Person",
        "name": "Knut Albrekt Fristedt",
        "birthDate": "1872-04-12",
        "birthPlace": "Linköping",
        "description": "Consul in Norrköping",
        "parent": [
            {
                "@type": "Person",
                "name": "Aug Fristedt",
                "jobTitle": "County Officer"
            },
            {
                "@type": "Person",
                "name": "Anna Crona"
            }
        ],
        "spouse": {
            "@type": "Person",
            "name": "Karin Ekstam"
        },
        "education": {
            "@type": "EducationalOccupationalCredential",
            "credentialCategory": "link:Studex",
            "educationalLevel": "link:Linkoping High School"
        },
        "work": [
            {
                "@type": "OrganizationRole",
                "roleName": "Employee",
                "startDate": "1891",
                "endDate": "1900",
                "organization": {
                    "@type": "Organization",
                    "name": "Axel Andersén & Co"
                }
            },
            {
                "@type": "OrganizationRole",
                "roleName": "Managing Director",
                "startDate": "1910",
                "endDate": "present",
                "organization": {
                    "@type": "Organization",
                    "name": "AB's Eftr"
                }
            },
            {
                "@type": "OrganizationRole",
                "roleName": "Consul",
                "startDate": "1924",
                "organization": {
                    "@type": "Organization",
                    "name": "Czechoslovakia"
                }
            }
        ],
        "memberOf": [
            {
                "@type": "Organization",
                "name": "Östgöta Bank",
                "memberOf": {
                    "@type": "Organization",
                    "name": "East Central Bank Directors"
                }
            },
            {
                "@type": "Organization",
                "name": "J Fristedts AB"
            },
            {
                "@type": "Organization",
                "name": "Öglind Industrial and Trade Chamber"
            },
            {
                "@type": "Organization",
                "name": "Czechoslovak Trade Chamber in Stockholm"
            },
            {
                "@type": "Organization",
                "name": "Gustavianska Foundation for Youth Welfare"
            },
            {
                "@type": "Organization",
                "name": "Reuterskiöld's Children's Institution"
            }
        ],
        "travelHistory": "Traveled extensively throughout Europe",
        "award": [
            {
                "@type": "Order",
                "name": "Order of the Polar Star",
                "awardDate": "unknown",
                "identifier": "RVO"
            },
            {
                "@type": "Medal",
                "name": "Swedish Medal for Distinguished Service",
                "awardDate": "unknown",
                "identifier": "TjslVLO"
            }
        ],
        "hasOccupation": [
            {
                "@type": "Occupation",
                "name": "Agriculture"
            },
            {
                "@type": "Occupation",
                "name": "Philately"
            }
        ]
    },
    "occupations": {
        "career": [
            {
                "occupational_title": "Employee",
                "workplace": "Axel Andersén & Co",
                "industry": "Unknown",
                "start_date": "1891"
            },
            {
                "occupational_title": "Managing Director",
                "workplace": "Unknown",
                "industry": "Unknown",
                "start_date": "1900"
            },
            {
                "occupational_title": "Consul of Czechoslovakia",
                "workplace": "Unknown",
                "industry": "Diplomatic",
                "start_date": "1924"
            }
        ]
    }
}