{
    "original": "LUNDQVIST, Sten Magnus Zachau, Civilingenjör, Göteborg, f Uddev 4/7 96 av dir M L o Clara Zachau, gm Elin Arnell. Studex 15, språkstud i Oxford, stud v KSS, Thulins flygsk samt CTH, diploming (mek) v tekn högsk i Zurich. Anst SKF 18, Götaverken 24 —33, fartygsinspektör f ett ant sv rederier, kontr f ett flert in- o utl fartygsbygg, maskin-exp i Gbgs distr f Germ Lloyds klassn.sällsk, lär i termodynamik o oljemotorer v GTI sed. 31, eg konsult ing.fma f fartyg o maskiner sed. 33. Vkst dir-o styr.led AB Marine Service, styr.led Red.AB C Å Blidberg. Magistr.-besiktningsm i Gbg. Resor: Engl 14, vist i Schweiz 19—24, USA 24, Tyskl, Holl, Norge, Danm, Ital, Polen, Frankr o Engl uppr ggr 1 samb m öl uppdr. Medl The Royal Bachelor’s Club, Tekn Saml Hobby: Motorsport (bilism, sportflyg). °LUNDSTEDT, Arvid Nestor, Fabrikör, Vadstena, f Vadstena 26/2 71 av gelbgjutare Aug L o Mathilda Pettersson, gm Jenny Johansson. Inneh tills m ing Ivar Lundstedt fma Lund-stedts Bil AB i Vadstena. Stdsflm, led av drätselk 27—31, tillh beredn.utsk.",
    "translated": "LUNDQVIST, Sten Magnus Zachau, Civil Engineer, Gothenburg, born in Uddevalla on April 7, 1896, son of director M L and Clara Zachau, married to Elin Arnell. Studied at Oxford, specializing in languages, studied at KSS, Thulins Aviation School, and CTH, obtained a diploma (mechanics) from the Zurich Technical University. Employed at SKF from 1918, at Götaverken from 1924 to 1933, served as a ship inspector for several shipping companies, managed contracts for both domestic and foreign shipbuilding, worked as a mechanical expert for Germ Lloyd's Classification Society in the Gothenburg district, taught thermodynamics and oil engines at GTI since 1931, and worked as an independent consultant for ships and machinery since 1933. Vice Director and Member of the Board of AB Marine Service, Member of the Board of Red AB C Å Blidberg. Magistrate's Inspector in Gothenburg. Traveled to England in 1914, stayed in Switzerland from 1919 to 1924, visited the USA in 1924, and also traveled to Germany, the Netherlands, Norway, Denmark, Italy, Poland, France, and England on several occasions in connection with assignments. Member of The Royal Bachelor's Club, Technical Society. Hobby: Motorsport (car racing, sport aviation). °LUNDSTEDT, Arvid Nestor, Manufacturer, Vadstena, born in Vadstena on February 26, 1871, son of brass founder Aug L and Mathilda Pettersson, married to Jenny Johansson. Owner together with Ivar Lundstedt of Lundstedts Bil AB in Vadstena. City film inspector, member of the local council from 1927 to 1931, served on the preparatory committee.",
    "structured": {
        "@context": "https://schema.org",
        "@type": "Person",
        "name": "Sten Magnus Zachau Lundqvist",
        "birthDate": "1896-04-07",
        "birthPlace": "Uddevalla",
        "description": "Civil Engineer",
        "parent": [
            {
                "@type": "Person",
                "name": "M L Zachau",
                "jobTitle": "Director"
            },
            {
                "@type": "Person",
                "name": "Clara Zachau"
            }
        ],
        "spouse": {
            "@type": "Person",
            "name": "Elin Arnell"
        },
        "education": [
            {
                "@type": "EducationalOrganization",
                "name": "Oxford University",
                "description": "Studied languages"
            },
            {
                "@type": "EducationalOrganization",
                "name": "KSS"
            },
            {
                "@type": "EducationalOrganization",
                "name": "Thulins Aviation School"
            },
            {
                "@type": "EducationalOrganization",
                "name": "CTH",
                "description": "Diploma in Mechanics from Zurich Technical University"
            }
        ],
        "employmentHistory": [
            {
                "@type": "Organization",
                "name": "SKF",
                "startDate": "1918"
            },
            {
                "@type": "Organization",
                "name": "Götaverken",
                "startDate": "1924",
                "endDate": "1933"
            }
        ],
        "workLocation": [
            "Gothenburg"
        ],
        "memberOf": [
            {
                "@type": "Organization",
                "name": "The Royal Bachelor's Club"
            },
            {
                "@type": "Organization",
                "name": "Technical Society"
            }
        ],
        "hobbies": [
            "Motorsport (car racing, sport aviation)"
        ],
        "travelHistory": [
            {
                "@type": "Place",
                "name": "England",
                "startDate": "1914"
            },
            {
                "@type": "Place",
                "name": "Switzerland",
                "startDate": "1919",
                "endDate": "1924"
            },
            {
                "@type": "Place",
                "name": "USA",
                "startDate": "1924"
            },
            {
                "@type": "Place",
                "name": "Germany"
            },
            {
                "@type": "Place",
                "name": "Netherlands"
            },
            {
                "@type": "Place",
                "name": "Norway"
            },
            {
                "@type": "Place",
                "name": "Denmark"
            },
            {
                "@type": "Place",
                "name": "Italy"
            },
            {
                "@type": "Place",
                "name": "Poland"
            },
            {
                "@type": "Place",
                "name": "France"
            }
        ]
    },
    "occupations": {
        "career": [
            {
                "occupational_title": "Civil Engineer",
                "workplace": "SKF",
                "industry": "Engineering",
                "start_date": "1918"
            },
            {
                "occupational_title": "Ship Inspector",
                "workplace": "Various Shipping Companies",
                "industry": "Maritime",
                "start_date": "1924"
            },
            {
                "occupational_title": "Mechanical Expert",
                "workplace": "Germ Lloyd's Classification Society",
                "industry": "Maritime",
                "start_date": "1931"
            },
            {
                "occupational_title": "Independent Consultant",
                "workplace": "Own Consulting Firm",
                "industry": "Maritime and Engineering",
                "start_date": "1933"
            },
            {
                "occupational_title": "Vice Director",
                "workplace": "AB Marine Service",
                "industry": "Maritime",
                "start_date": "N/A"
            },
            {
                "occupational_title": "Board Member",
                "workplace": "Red AB C Å Blidberg",
                "industry": "Maritime",
                "start_date": "N/A"
            },
            {
                "occupational_title": "Magistrate's Inspector",
                "workplace": "Gothenburg",
                "industry": "Government",
                "start_date": "N/A"
            }
        ]
    }
}