{
    "original": "LUND, Karl-Gustaf, Ingenjör, Varberg, f Hilleviks br, Gävleb l, 22/7 93 av brukstjm G L o Anne Maria Andersson, gm Sigrid Johansson. Ex bergssk i Filipst, spec.elev KTH (bergsvtensk) 3. o 4. årsk, stud StHS o Me-tallogr inst 21—22. Kem Strömsnäs jvk 18— 20, metallurg o kem Westinghouse El &amp; Manuf Co, East Pittsb Pennsylv USA, 23—26 o 28— 29, ch.metallurg Laclede Steel Co, Alton 111 USA, 27, hyttstålvksing Iggesunds br 29—31, platsch Gunnebo br AB, Varb.vkt, sed. 31. Led dräts.kamm, v. ordf ekon.avd, styr.suppl elvkt, huv.m sparbkn, arb.giv repr i länsarb.-nmdns kretsråd, styr.led Varb luftsk.frn, sekr Varb högerfrn, ordf järnvkts sjukkassa. Flantsällsk Småfågl Vann. Resor: Tyskl 21, 22, 23, 30, 36, Danm, Tjeckoslov 21, 22, 23, Österr 21, USA 23—29. Av trycket: Some fundamental factors for obtainiiig Sharp ther-mal curves (Träns Amer Soc f Steel Treating, tills m C Benedicks o W H Dearden 25), Nutida fabr av sågblad, sågklingor o maskin-knivar (Träv.ind 26). Frimurare (VI), skattm Varb Gille. Hobbies: Jakt, fiske.",
    "translated": "LUND, Karl-Gustaf, Engineer, Varberg, son of Johan Gustaf Lund and Anne Maria Andersson, married to Sigrid Johansson. Former mining school student in Filipstad, specialized student at KTH (mining engineering) in the 3rd and 4th year, studied at StHS (Stockholm High School) and Metallurgical Institute from 1921 to 1922. Worked at Strömsnäs mine from 1918 to 1920, and as a metallurgist and chemist at Westinghouse Electric & Manufacturing Co, East Pittsburgh, Pennsylvania, USA from 1923 to 1926 and 1928 to 1929, and as a chief metallurgist at Laclede Steel Co, Alton, Illinois, USA in 1927. Worked as a blast furnace steelworker at Iggesund mill from 1929 to 1931, and currently holds a position at Gunnebo mill AB, Varberg. Member of the municipal council, deputy chairman of the economic department, member of the board of electricity supply, chief board of savings bank, employer representative in the county labor committee, board member of Varberg air squadrons, secretary of Varberg conservative party, chairman of the railway guild's sick fund. Member of the Small Birds Association. Travels: Germany in 1921, 1922, 1923, 1930, 1936, Denmark, Czechoslovakia in 1921, 1922, 1923, Austria in 1921, USA from 1923 to 1929. Published works: Some fundamental factors for obtaining sharp thermal curves (Transactions of the American Society for Steel Treating, co-authored with C. Benedicks and W.H. Dearden, 1925), Modern manufacturing of saw blades, saw edges, and machine knives (Wood Industry, 1926). Freemason (VI), treasurer of Varberg Lodge. Hobbies: Hunting, fishing.",
    "structured": {
        "@context": "https://schema.org",
        "@type": "Person",
        "name": "Karl-Gustaf Lund",
        "jobTitle": "Engineer",
        "birthPlace": "Varberg, Sweden",
        "birthDate": "1893-07-22",
        "parent": {
            "@type": "Person",
            "name": "Anne Maria Andersson"
        },
        "spouse": {
            "@type": "Person",
            "name": "Sigrid Johansson"
        },
        "education": [
            {
                "@type": "EducationalOrganization",
                "name": "Filipstad Mining School"
            },
            {
                "@type": "EducationalOrganization",
                "name": "KTH Royal Institute of Technology"
            },
            {
                "@type": "EducationalOrganization",
                "name": "Stockholm High School"
            },
            {
                "@type": "EducationalOrganization",
                "name": "Metallurgical Institute"
            }
        ],
        "workExperience": [
            {
                "@type": "Organization",
                "name": "Strömsnäs Mine",
                "startDate": "1918",
                "endDate": "1920",
                "jobTitle": "Chemist"
            },
            {
                "@type": "Organization",
                "name": "Westinghouse Electric & Manufacturing Co",
                "address": {
                    "@type": "PostalAddress",
                    "addressLocality": "East Pittsburgh",
                    "addressRegion": "Pennsylvania",
                    "addressCountry": "USA"
                },
                "startDate": "1923",
                "endDate": "1926",
                "jobTitle": "Metallurgist and Chemist"
            },
            {
                "@type": "Organization",
                "name": "Laclede Steel Co",
                "address": {
                    "@type": "PostalAddress",
                    "addressLocality": "Alton",
                    "addressRegion": "Illinois",
                    "addressCountry": "USA"
                },
                "startDate": "1927",
                "jobTitle": "Chief Metallurgist"
            },
            {
                "@type": "Organization",
                "name": "Iggesund Mill",
                "startDate": "1929",
                "endDate": "1931",
                "jobTitle": "Blast Furnace Steelworker"
            },
            {
                "@type": "Organization",
                "name": "Gunnebo Mill AB",
                "jobTitle": "Employee",
                "startDate": "1931"
            }
        ],
        "affiliation": [
            {
                "@type": "Organization",
                "name": "Varberg Municipal Council",
                "roleName": "Member"
            },
            {
                "@type": "Organization",
                "name": "Varberg Economic Department",
                "roleName": "Deputy Chairman"
            },
            {
                "@type": "Organization",
                "name": "Electricity Supply",
                "roleName": "Board Member"
            },
            {
                "@type": "Organization",
                "name": "Savings Bank",
                "roleName": "Chief Board Member"
            },
            {
                "@type": "Organization",
                "name": "County Labor Committee",
                "roleName": "Employer Representative"
            },
            {
                "@type": "Organization",
                "name": "Varberg Air Squadrons",
                "roleName": "Board Member"
            },
            {
                "@type": "Organization",
                "name": "Varberg Conservative Party",
                "roleName": "Secretary"
            },
            {
                "@type": "Organization",
                "name": "Railway Guild's Sick Fund",
                "roleName": "Chairman"
            }
        ],
        "memberOf": [
            {
                "@type": "Organization",
                "name": "Small Birds Association"
            },
            {
                "@type": "Organization",
                "name": "Frimurare",
                "roleName": "Treasurer"
            },
            {
                "@type": "Organization",
                "name": "Varberg Lodge",
                "roleName": "Treasurer"
            }
        ],
        "travelHistory": [
            {
                "@type": "Place",
                "name": "Germany"
            },
            {
                "@type": "Place",
                "name": "Denmark"
            },
            {
                "@type": "Place",
                "name": "Czechoslovakia"
            },
            {
                "@type": "Place",
                "name": "Austria"
            },
            {
                "@type": "Place",
                "name": "USA"
            }
        ],
        "publication": [
            {
                "@type": "Article",
                "name": "Some fundamental factors for obtaining sharp thermal curves",
                "publicationDate": "1925",
                "coAuthors": [
                    {
                        "@type": "Person",
                        "name": "C. Benedicks"
                    },
                    {
                        "@type": "Person",
                        "name": "W.H. Dearden"
                    }
                ]
            },
            {
                "@type": "Article",
                "name": "Modern manufacturing of saw blades, saw edges, and machine knives",
                "publicationDate": "1926",
                "publisher": {
                    "@type": "Organization",
                    "name": "Wood Industry"
                }
            }
        ],
        "hobbies": [
            "Hunting",
            "Fishing"
        ]
    },
    "occupations": {
        "career": [
            {
                "occupational_title": "Engineer",
                "workplace": "Strömsnäs mine",
                "industry": "Mining",
                "start_date": "1918"
            },
            {
                "occupational_title": "Metallurgist and Chemist",
                "workplace": "Westinghouse Electric & Manufacturing Co",
                "industry": "Electrical equipment manufacturing",
                "start_date": "1923"
            },
            {
                "occupational_title": "Chief Metallurgist",
                "workplace": "Laclede Steel Co",
                "industry": "Steel",
                "start_date": "1927"
            },
            {
                "occupational_title": "Blast Furnace Steelworker",
                "workplace": "Iggesund mill",
                "industry": "Steel",
                "start_date": "1929"
            },
            {
                "occupational_title": "Unknown",
                "workplace": "Gunnebo mill AB",
                "industry": "Unknown",
                "start_date": "Unknown"
            }
        ]
    }
}