{
    "original": "DYMLING, Carl Anders Fil. !Lic., Stockholm, f Gbg 26/3 98 av avd.ch Ch D o Martha Levgren, gm Greta Westberg. Studex 16, fil kand 21, fil lic 25. Aman Gbg Stadsbibl 23—27, progr.ch Radiotj Gbg 26—30, avd.ch Radiotj Sthlm 30, ch f radioteatern 31—35, riksprogr.-ch o vkst dir Radiotj 36, vkst dir Sv Filmind 42. Led Stat Inf.styr 40—42, led Filmutredn 41—42. Resor: I de fi europ länd samt USA 36, Egypt, Palestina o Syrien 38. Av trycket: Litt.hist upps, litt.krit art o rec i tidn o tidskr, medarb Sv biogr lexikon o Sv uppslagsbok mm, utg Radiotjänst, en bok om programmet o lyssnarna (tills m J Rabe 29), Röster om Radio 34. RVO, RFinlVRO, RNO, TjeckVLO, RDDO, medl Rotary. °DYMI,ING, Olof Richard, Direktör, Stockholm, f Härnösand 25/5 98, gm Erna Fähn-rich-Frandsen. Studex Djursholm 17, resoffex 19, studier i Frankr, Engl o USA 20—24. Del-äg i Fma Jacob Versteegh, Hsand o Sthlm, sed. 28.",
    "translated": "DYMLING, Carl Anders, Son of Ch D and Martha Levgren, born in Gothenburg on 26th March 1898. Married to Greta Westberg. Graduated in 1916, Bachelor of Arts in 1921, Licentiate in 1925. Employed at Gothenburg City Library from 1923 to 1927, Programme Chief at Gothenburg Radio from 1926 to 1930, Department Chief at Stockholm Radio from 1930, Director of Radio Theatre from 1931 to 1935, Director of Programme Development and Growth at Radio from 1936, Director of Growth at Swedish Film Industry from 1942. Member of the State Information Board from 1940 to 1942, Member of the Film Investigation Board from 1941 to 1942. Travelled to various European countries and the USA in 1936, Egypt, Palestine, and Syria in 1938. Published in historical research, literary criticism articles, and reviews in newspapers and magazines, contributor to Swedish Biography Lexicon and Swedish Encyclopedia, among others. Published a book about the program and listenership of Radio (with J Rabe in 1929), Voices about Radio in 1934. Received the Royal Order of Vasa, the Finnish Order of the White Rose, the Norwegian Order of St. Olav, the Czech Order of the White Lion, and the Danish Order of the Dannebrog. Member of the Rotary Club.\n\nDYMLING, Olof Richard, Director, born in Härnösand on 25th May 1898, married to Erna Fähnrich-Frandsen. Graduated from Djursholm in 1917, Reserve Officer's exam in 1919, studied in France, England, and the USA from 1920 to 1924. Co-owner of Fma Jacob Versteegh, Härnösand, and Stockholm since 1928.",
    "structured": {
        "@context": "https://schema.org",
        "@type": "Person",
        "name": "Carl Anders Dymling",
        "birthDate": "1898-03-26",
        "birthPlace": "Gothenburg",
        "parents": [
            {
                "@type": "Person",
                "name": "Ch D"
            },
            {
                "@type": "Person",
                "name": "Martha Levgren"
            }
        ],
        "spouse": {
            "@type": "Person",
            "name": "Greta Westberg"
        },
        "education": [
            {
                "@type": "EducationalOccupationalCredential",
                "name": "Licentiate",
                "description": "Received Licentiate degree in 1925"
            },
            {
                "@type": "EducationalOccupationalCredential",
                "name": "Bachelor of Arts",
                "description": "Received Bachelor of Arts degree in 1921"
            },
            {
                "@type": "EducationalOccupationalCredential",
                "name": "Studex",
                "description": "Graduated in 1916"
            }
        ],
        "workExperience": [
            {
                "@type": "OrganizationRole",
                "startDate": "1923",
                "endDate": "1927",
                "roleName": "Employee",
                "organization": {
                    "@type": "Organization",
                    "name": "Gothenburg City Library"
                }
            },
            {
                "@type": "OrganizationRole",
                "startDate": "1926",
                "endDate": "1930",
                "roleName": "Programme Chief",
                "organization": {
                    "@type": "Organization",
                    "name": "Gothenburg Radio"
                }
            },
            {
                "@type": "OrganizationRole",
                "startDate": "1930",
                "roleName": "Department Chief",
                "organization": {
                    "@type": "Organization",
                    "name": "Stockholm Radio"
                }
            },
            {
                "@type": "OrganizationRole",
                "startDate": "1931",
                "endDate": "1935",
                "roleName": "Director of Radio Theatre",
                "organization": {
                    "@type": "Organization",
                    "name": "Radio"
                }
            },
            {
                "@type": "OrganizationRole",
                "startDate": "1936",
                "roleName": "Director of Programme Development and Growth",
                "organization": {
                    "@type": "Organization",
                    "name": "Radio"
                }
            },
            {
                "@type": "OrganizationRole",
                "startDate": "1942",
                "roleName": "Director of Growth",
                "organization": {
                    "@type": "Organization",
                    "name": "Swedish Film Industry"
                }
            }
        ],
        "memberOf": [
            {
                "@type": "Organization",
                "name": "State Information Board",
                "startDate": "1940",
                "endDate": "1942"
            },
            {
                "@type": "Organization",
                "name": "Film Investigation Board",
                "startDate": "1941",
                "endDate": "1942"
            },
            {
                "@type": "Organization",
                "name": "Rotary Club"
            }
        ],
        "nationality": "Swedish",
        "sameAs": [
            "https://www.wikidata.org/wiki/Q93003151"
        ],
        "jobTitle": [
            "Director"
        ],
        "description": [
            "Published in historical research, literary criticism articles, and reviews in newspapers and magazines."
        ],
        "awards": [
            {
                "@type": "Order",
                "name": "Royal Order of Vasa"
            },
            {
                "@type": "Order",
                "name": "Finnish Order of the White Rose"
            },
            {
                "@type": "Order",
                "name": "Norwegian Order of St. Olav"
            },
            {
                "@type": "Order",
                "name": "Czech Order of the White Lion"
            },
            {
                "@type": "Order",
                "name": "Danish Order of the Dannebrog"
            }
        ],
        "travelHistory": [
            {
                "@type": "Trip",
                "name": "European Countries and USA",
                "startDate": "1936"
            },
            {
                "@type": "Trip",
                "name": "Egypt, Palestine, and Syria",
                "startDate": "1938"
            }
        ],
        "worksPublished": [
            {
                "@type": "Book",
                "name": "A book about the program and listenership of Radio",
                "authors": [
                    {
                        "@type": "Person",
                        "name": "J Rabe"
                    }
                ],
                "publicationYear": "1929"
            },
            {
                "@type": "Article",
                "name": "Voices about Radio",
                "publicationYear": "1934"
            }
        ]
    },
    "occupations": {
        "career": [
            {
                "occupational_title": "Amanuensis",
                "workplace": "Gothenburg City Library",
                "industry": "Library",
                "start_date": "1923"
            },
            {
                "occupational_title": "Programme Chief",
                "workplace": "Gothenburg Radio",
                "industry": "Radio",
                "start_date": "1926"
            },
            {
                "occupational_title": "Department Chief",
                "workplace": "Stockholm Radio",
                "industry": "Radio",
                "start_date": "1930"
            },
            {
                "occupational_title": "Director of Radio Theatre",
                "workplace": "Radioteatern",
                "industry": "Radio",
                "start_date": "1931"
            },
            {
                "occupational_title": "Director of Programme Development and Growth",
                "workplace": "Radiotjänst",
                "industry": "Radio",
                "start_date": "1936"
            },
            {
                "occupational_title": "Director of Growth",
                "workplace": "Swedish Film Industry",
                "industry": "Film",
                "start_date": "1942"
            }
        ]
    }
}