{
    "original": "MÅNSSON, Gustaf Birger, Konsul, Norrköping, f Nrkp 20/4 86 av avd.ch G M o lär:an Augusta Jonson, gm Gurli Janzon. Tjm Nrkp sjöm.h 05—14, tf sjöm.h.omb.m 14—17, anst sed. 05 i sped-, befraktn- o skeppsmäkl.fma Aug V Svenson (etabl 89), vkst dir sed. 14 o num av inneh, edsv skeppsmäkl 20, auktor skeppsklarer 34, vkst dir AB Nrkp godsbil-central. Norsk kons Nrkp, Ögl o Sörml 36. Styr.led hamnstyr, ordf bilvärd.nmdn, komm.-.koll rev f Nrkp sjöm.h, flm o ordf Nrkp ’köpmfrn o Nrkp hdlsfrn, ordf Ögl Fabr &amp; Grossistfrb, Nrkpsavd av Sv Statens försvarslån, Nrkp auto- &amp; flygklubb, Nrkp SS, Frn Sv Flottas lokalavd, Cykelfrämj Nrkpavd, Sv segl.sk :s lokalkomm, Kopparbo vägfrn, styr.led Sv skeppsklarer- o skeppsmäkl.frn, KSAK, KAK Idsfrn, Sv Norgehj :s Nrkpkomm, org.-komm f insaml t Nrkp försvar. Rest i flert europ länd. RNO, RVO, FinlVRO, FinlKrg-MM, ProPGM, idrm g, Nrkp SS GM, Nrkp Auto- &amp; Flygklb ftjt g o gplak, KAK Idsfrns gplak. Hobbies: Idrott, gymn, sport, segling, flygning, schack, tennis.",
    "translated": "MÅNSSON, Gustaf Birger, Consul, Norrköping, born in Norrköping on April 20th, 1886, son of division chief G M and teacher Augusta Jonson, married to Gurli Janzon. Employed at Norrköping shipping company from 1905 to 1914, acting shipping company manager from 1914 to 1917, employed since 1905 in forwarding, chartering, and shipbroking firm Aug V Svenson (established 1889), appointed managing director in 1914 and became a partner in 1920, authorized ship agent in 1934, managing director of AB Norrköping Goods Transport Center. Norwegian Consul in Norrköping, Östergötland, and Södermanland in 1936. Board member of the harbor board, chairman of the vehicle registration committee, member of the naval control board in Norrköping, member and chairman of Norrköping merchants association and Norrköping Chamber of Commerce, chairman of Östergötland Manufacturers and Wholesalers Association, Norrköping division of the Swedish State Defense Loan, Norrköping automobile and aviation club, Norrköping Social Democrats, Local division of the Swedish Navy Association, Norrköping division of the Bicycle Promotion Society, local committee of the Swedish Sailing Association, board member of the Swedish ship agents and shipbrokers association, Royal Swedish Aero Club, Royal Automobile Club, and Swedish Norway Aid Committee in Norrköping, organizing committee for fundraising for the defense of Norrköping. Traveled extensively in several European countries. Recipient of the Order of the Northern Star, Order of Vasa, Order of the White Rose of Finland, Finnish War memorial medal, Pro Patria Gold Medal, honorary member of Norrköping Social Democrats, Norrköping Automobile and Aviation Club gold diploma, Royal Automobile Club's honorary diploma. Hobbies: sports, gymnastics, sailing, flying, chess, tennis.",
    "structured": {
        "@context": "https://schema.org",
        "@type": "Person",
        "name": "Gustaf Birger MÅNSSON",
        "birthDate": "1886-04-20",
        "birthPlace": "Norrköping",
        "nationality": "Swedish",
        "description": "Consul",
        "spouse": "Gurli Janzon",
        "parents": [
            {
                "@type": "Person",
                "name": "GM MÅNSSON",
                "jobTitle": "Division Chief"
            },
            {
                "@type": "Person",
                "name": "Augusta Jonson",
                "jobTitle": "Teacher"
            }
        ],
        "employment": [
            {
                "@type": "Organization",
                "name": "Norrköping Shipping Company",
                "startDate": "1905-01-01",
                "endDate": "1914-12-31",
                "jobTitle": "Employee"
            },
            {
                "@type": "Organization",
                "name": "Forwarding, Chartering, and Shipbroking Firm Aug V Svenson",
                "startDate": "1905-01-01",
                "endDate": "1920-12-31",
                "jobTitle": "Employee"
            },
            {
                "@type": "Organization",
                "name": "AB Norrköping Goods Transport Center",
                "startDate": "1920-01-01",
                "jobTitle": "Managing Director"
            }
        ],
        "honors": [
            {
                "@type": "Order",
                "name": "Order of the Northern Star"
            },
            {
                "@type": "Order",
                "name": "Order of Vasa"
            },
            {
                "@type": "Order",
                "name": "Order of the White Rose of Finland"
            },
            {
                "@type": "Medal",
                "name": "Finnish War memorial medal"
            },
            {
                "@type": "Medal",
                "name": "Pro Patria Gold Medal"
            },
            {
                "@type": "Organization",
                "name": "Norrköping Social Democrats",
                "honorary": true
            },
            {
                "@type": "Organization",
                "name": "Norrköping Automobile and Aviation Club",
                "honorary": true,
                "award": "Gold diploma"
            },
            {
                "@type": "Organization",
                "name": "Royal Automobile Club",
                "honorary": true,
                "award": "Honorary diploma"
            }
        ],
        "hobbies": [
            "Sports",
            "Gymnastics",
            "Sailing",
            "Flying",
            "Chess",
            "Tennis"
        ]
    },
    "occupations": {
        "career": [
            {
                "occupational_title": "Marine Trainee",
                "workplace": "Norrköping Shipping Company",
                "industry": "Shipping",
                "start_date": "1905"
            },
            {
                "occupational_title": "Acting Shipping Company Manager",
                "workplace": "Norrköping Shipping Company",
                "industry": "Shipping",
                "start_date": "1914"
            },
            {
                "occupational_title": "Managing Director",
                "workplace": "Aug V Svenson (established 1889)",
                "industry": "Forwarding, Chartering, and Shipbroking",
                "start_date": "1914"
            },
            {
                "occupational_title": "Partner",
                "workplace": "Aug V Svenson (established 1889)",
                "industry": "Forwarding, Chartering, and Shipbroking",
                "start_date": "1920"
            },
            {
                "occupational_title": "Authorized Ship Agent",
                "workplace": "Aug V Svenson (established 1889)",
                "industry": "Forwarding, Chartering, and Shipbroking",
                "start_date": "1934"
            },
            {
                "occupational_title": "Managing Director",
                "workplace": "AB Norrköping Goods Transport Center",
                "industry": "Transportation",
                "start_date": "unknown"
            },
            {
                "occupational_title": "Norwegian Consul",
                "workplace": "Norrköping",
                "industry": "Diplomacy",
                "start_date": "unknown"
            }
        ]
    }
}