{
    "original": "HÄGGLUND, Erik Karl Mauritz, Professor, Stockholm, f Hässjö, Medelp, 15/6 87 av landsfiskal E Hägglund o Margreta öhlén, gm Aina Forsberg. Mog.ex Sundsvall 06, StHS 06—11, fil mag 09, fil lic 11, fil dr 14. Aman v StHS 08—11, kem v Bergviks sulfitfabr o sulfit-spritfabr 11—15, e.o. lekt i Eksjö 15—16, kem o avd.ch i Th Goldschmidt AG i Essen o Mannheim 16—20, prof i skogsprodukternas kemi o kem teknol v Åbo akad 20—30, prof i cellulosatekn o träkemi KTH fr 30, förest f cellulosaind :s centrallab fr 36. Led av Sv tekn vetensk.akad i Finl 24. Hed.dr i Heidelberg 39. LIVA 34. Styr.led Sv Tekn.frn 34—36. Norblad-Ekstrand-priset, GM 23. MitschM 38. Av trycket bl. a.: Die hydrolyse der Zellulose und des Holzes (15), Die Sulfitablauge und ihre Verar-beitung auf Alkohol (21), Nya vägar f träförsockring (24), Holschemie (3. uppl, 43), Un-tersuchungen iiber die Chemie der Sulfitzell-stoffkochung, 40 Medd (24—43), Natronzellstoff (26). RNO, KFinlVRO2kl.",
    "translated": "HÄGGLUND, Erik Karl Mauritz, Professor, Stockholm, born in Hässjö, Medelp, 15/6 1887, son of district prosecutor E Hägglund and Margreta Öhlén, married to Aina Forsberg. Graduated from Sundsvall in 1906, studied at Stockholm University 1906-1911, obtained a Bachelor's degree in 1909, a Master's degree in 1911, and a Doctorate in Philosophy in 1914. Was an assistant teacher at Stockholm University 1908-1911, worked as a chemist at Bergvik Sulphite Factory and Sulphite Alcohol Factory 1911-1915, served as a temporary lecturer in Eksjö 1915-1916, chemist and department head at Th Goldschmidt AG in Essen and Mannheim 1916-1920, professor of chemistry of forest products and chemical technology at Åbo Academy 1920-1930, professor of cellulose technology and wood chemistry at KTH from 1930, and director of the central laboratory at the Cellulose Industry from 1936. Elected member of the Finnish Academy of Technical Sciences in 1924. Honorary doctorate from Heidelberg in 1939. Member of the Royal Swedish Academy of Engineering Sciences since 1934. Chair of the Swedish Technical Research Council from 1934-1936. Recipient of the Norblad-Ekstrand Prize in 1923. Member of the Mitscherlich Society in 1938. Published works include: \"The Hydrolysis of Cellulose and Wood\" (1915), \"The Sulphite Solution and its Processing into Alcohol\" (1921), \"New Ways of Sugaring Wood\" (1924), \"Wood Chemistry\" (3rd edition, 1943), \"Investigations on the Chemistry of Sulphite Pulp Cooking\" (1924-1943), \"Soda Pulp\" (1926). Received the Order of the North Star (RNO) and the Knight's 2nd Class of the Order of the White Rose of Finland (KFinlVRO2kl).",
    "structured": {
        "@context": "http://schema.org",
        "@type": "Person",
        "name": "Erik Karl Mauritz Hägglund",
        "birthDate": "1887-06-15",
        "birthPlace": "Hässjö, Medelp",
        "description": "Professor, Stockholm",
        "parent": [
            {
                "@type": "Person",
                "name": "E Hägglund",
                "description": "Father"
            },
            {
                "@type": "Person",
                "name": "Margreta Öhlén",
                "description": "Mother"
            }
        ],
        "spouse": {
            "@type": "Person",
            "name": "Aina Forsberg"
        },
        "education": [
            {
                "@type": "EducationalOccupationalCredential",
                "educationalLevel": "Bachelor's degree",
                "educationalCredentialAwarded": "1909",
                "awardingInstitution": {
                    "@type": "EducationalOrganization",
                    "name": "Sundsvall"
                }
            },
            {
                "@type": "EducationalOccupationalCredential",
                "educationalLevel": "Master's degree",
                "educationalCredentialAwarded": "1911",
                "awardingInstitution": {
                    "@type": "EducationalOrganization",
                    "name": "Stockholm University"
                }
            },
            {
                "@type": "EducationalOccupationalCredential",
                "educationalLevel": "Doctorate in Philosophy",
                "educationalCredentialAwarded": "1914",
                "awardingInstitution": {
                    "@type": "EducationalOrganization",
                    "name": "Stockholm University"
                }
            }
        ],
        "jobTitle": "Professor",
        "worksFor": "Stockholm",
        "affiliation": [
            {
                "@type": "Organization",
                "name": "Bergvik Sulphite Factory"
            },
            {
                "@type": "Organization",
                "name": "Sulphite Alcohol Factory"
            },
            {
                "@type": "Organization",
                "name": "Th Goldschmidt AG",
                "location": [
                    {
                        "@type": "Place",
                        "name": "Essen"
                    },
                    {
                        "@type": "Place",
                        "name": "Mannheim"
                    }
                ]
            },
            {
                "@type": "Organization",
                "name": "Åbo Academy"
            },
            {
                "@type": "Organization",
                "name": "KTH"
            },
            {
                "@type": "Organization",
                "name": "Cellulose Industry"
            }
        ],
        "memberOf": [
            {
                "@type": "Organization",
                "name": "Finnish Academy of Technical Sciences",
                "foundingDate": "1924"
            },
            {
                "@type": "Organization",
                "name": "Royal Swedish Academy of Engineering Sciences",
                "foundingDate": "1934"
            }
        ],
        "awards": [
            {
                "@type": "Award",
                "name": "Norblad-Ekstrand Prize",
                "awardDate": "1923"
            },
            {
                "@type": "Award",
                "name": "Mitscherlich Society",
                "awardDate": "1938"
            }
        ],
        "honoraryDoctorate": {
            "@type": "EducationalOccupationalCredential",
            "educationalLevel": "Doctorate",
            "educationalCredentialAwarded": "1939",
            "awardingInstitution": {
                "@type": "EducationalOrganization",
                "name": "Heidelberg"
            }
        },
        "nationality": "Swedish",
        "identifier": [
            {
                "@type": "PropertyValue",
                "name": "Order of the North Star",
                "value": "RNO"
            },
            {
                "@type": "PropertyValue",
                "name": "Order of the White Rose of Finland",
                "value": "Knight's 2nd Class (KFinlVRO2kl)"
            }
        ],
        "publications": [
            {
                "@type": "Article",
                "name": "The Hydrolysis of Cellulose and Wood",
                "datePublished": "1915"
            },
            {
                "@type": "Article",
                "name": "The Sulphite Solution and its Processing into Alcohol",
                "datePublished": "1921"
            },
            {
                "@type": "Article",
                "name": "New Ways of Sugaring Wood",
                "datePublished": "1924"
            },
            {
                "@type": "Article",
                "name": "Wood Chemistry",
                "datePublished": "1943"
            },
            {
                "@type": "Article",
                "name": "Investigations on the Chemistry of Sulphite Pulp Cooking",
                "datePublished": "1924-1943"
            },
            {
                "@type": "Article",
                "name": "Soda Pulp",
                "datePublished": "1926"
            }
        ]
    },
    "occupations": {
        "career": [
            {
                "occupational_title": "Assistant Teacher",
                "workplace": "Stockholm University",
                "industry": "Academia",
                "start_date": "1908"
            },
            {
                "occupational_title": "Chemist",
                "workplace": "Bergvik Sulphite Factory and Sulphite Alcohol Factory",
                "industry": "Chemical",
                "start_date": "1911"
            },
            {
                "occupational_title": "Temporary Lecturer",
                "workplace": "Eksjö",
                "industry": "Academia",
                "start_date": "1915"
            },
            {
                "occupational_title": "Chemist and Department Head",
                "workplace": "Th Goldschmidt AG in Essen and Mannheim",
                "industry": "Chemical",
                "start_date": "1916"
            },
            {
                "occupational_title": "Professor of Chemistry of Forest Products and Chemical Technology",
                "workplace": "Åbo Academy",
                "industry": "Academia",
                "start_date": "1920"
            },
            {
                "occupational_title": "Professor of Cellulose Technology and Wood Chemistry",
                "workplace": "KTH (Royal Institute of Technology)",
                "industry": "Academia",
                "start_date": "1930"
            },
            {
                "occupational_title": "Director of Central Laboratory",
                "workplace": "Cellulose Industry",
                "industry": "Forestry",
                "start_date": "1936"
            }
        ]
    }
}