{
    "original": "JACOBSON, Jacob Thobias Eusebius, Disponent, Norrköping, f Linderås, Jkp l, 14/8 96 av godsäg J J o Ida Gustafsson, gm Elsa Nilsson. Olssons hdlssk Jkp, Osby lantm.sk, forts.kurs Vilan o Alnarp. Anst Ögl l hush.-sällsk 20—23, avd.ch fma Hylander &amp; Co Gbg 23, disp Nrkpkont 24—29, kol.varufma Rob Johnsson &amp; Co Nrkp 30—32, Alb Anderssons slakt.AB sed. 33, inneh detta AB samt Svärtinge vat.vAB, fastigh.AB Strömmen o egend Leverstad, samtl i Nrkp. Styr.ordf i sistn tre AB. Resor i de Skand länd. Frimurare, Odd Fellow, Nrkp autom- o flygklubb mfl frn :ar o sammanslutn. Hobby: Lantbruk.",
    "translated": "JACOBSON, Jacob Thobias Eusebius, Manager, Norrköping, born in Linderås, Jönköping county, on August 14, 1896, to the estate owner J.J. and Ida Gustafsson. Married to Elsa Nilsson. Completed his education at Olssons Handelsskola in Jönköping, Osby Agricultural School, and further courses at Vilan and Alnarp. Employed at Ögl's household company from 1920 to 1923, department chief at Hylander & Co in Gothenburg in 1923, manager at the Norrköping office from 1924 to 1929, employed at the coal and goods company Rob Johnsson & Co in Norrköping from 1930 to 1932, and worked at Alb Anderssons slaughterhouse AB from 1933. Currently, he is the owner of this company as well as of Svärtinge water supply AB, Strömmen real estate AB, and the property Leverstad, all located in Norrköping. He holds the position of chairman in the last three mentioned companies. Has traveled within the Scandinavian countries. Member of the Freemasons, Odd Fellows, Norrköping Automobile and Flying Club, and other associations and organizations. His hobby is farming.",
    "structured": {
        "@context": "https://schema.org",
        "@type": "Person",
        "name": "Jacob Thobias Eusebius Jacobson",
        "jobTitle": "Manager",
        "birthDate": "1896-08-14",
        "birthPlace": "Linderås, Jönköping, Sweden",
        "nationality": "Swedish",
        "spouse": "Elsa Nilsson",
        "education": [
            {
                "@type": "EducationalOrganization",
                "name": "Olssons Handelsskola",
                "location": "Jönköping, Sweden"
            },
            {
                "@type": "EducationalOrganization",
                "name": "Osby Agricultural School",
                "location": "Osby, Sweden"
            },
            {
                "@type": "EducationalOrganization",
                "name": "Vilan",
                "location": "Sweden"
            },
            {
                "@type": "EducationalOrganization",
                "name": "Alnarp",
                "location": "Sweden"
            }
        ],
        "alumniOf": [
            "Olssons Handelsskola",
            "Osby Agricultural School",
            "Vilan",
            "Alnarp"
        ],
        "work": [
            {
                "@type": "Organization",
                "name": "Ögl's Household Company",
                "startDate": "1920",
                "endDate": "1923",
                "location": "Sweden"
            },
            {
                "@type": "Organization",
                "name": "Hylander & Co",
                "department": "Household Division",
                "startDate": "1923",
                "endDate": "1924",
                "location": "Gothenburg, Sweden"
            },
            {
                "@type": "Organization",
                "name": "Norrköping Office",
                "startDate": "1924",
                "endDate": "1929",
                "location": "Norrköping, Sweden"
            },
            {
                "@type": "Organization",
                "name": "Rob Johnsson & Co",
                "department": "Coal and Goods Company",
                "startDate": "1930",
                "endDate": "1932",
                "location": "Norrköping, Sweden"
            },
            {
                "@type": "Organization",
                "name": "Alb Anderssons Slaughterhouse AB",
                "startDate": "1933",
                "location": "Norrköping, Sweden"
            }
        ],
        "owns": [
            {
                "@type": "Organization",
                "name": "Alb Anderssons Slaughterhouse AB",
                "location": "Norrköping, Sweden"
            },
            {
                "@type": "Organization",
                "name": "Svärtinge Water Supply AB",
                "location": "Norrköping, Sweden"
            },
            {
                "@type": "Organization",
                "name": "Strömmen Real Estate AB",
                "location": "Norrköping, Sweden"
            },
            {
                "@type": "Place",
                "name": "Leverstad",
                "location": "Norrköping, Sweden"
            }
        ],
        "affiliation": [
            {
                "@type": "Organization",
                "name": "Freemasons"
            },
            {
                "@type": "Organization",
                "name": "Odd Fellows"
            },
            {
                "@type": "Organization",
                "name": "Norrköping Automobile and Flying Club"
            }
        ],
        "hobby": "Farming"
    },
    "occupations": {
        "career": [
            {
                "occupational_title": "Disponent",
                "workplace": "Norrköping",
                "industry": "Unknown",
                "start_date": "1924"
            },
            {
                "occupational_title": "Department Chief",
                "workplace": "Hylander & Co",
                "industry": "Unknown",
                "start_date": "1923"
            },
            {
                "occupational_title": "Manager",
                "workplace": "Rob Johnsson & Co",
                "industry": "Coal and Goods",
                "start_date": "1930"
            },
            {
                "occupational_title": "Manager",
                "workplace": "Alb Anderssons slaughterhouse AB",
                "industry": "Slaughterhouse",
                "start_date": "1933"
            }
        ]
    }
}