{
    "original": "EKMAN, Gustaf, Bankdirektör, östafors, f Torrskog, Älvsb l, 21/12 72 av bruksäg J W E o Julia Wallroth, gm Hedvig Larson. Mo-genh.ex Gbg 91, CTL 91—92. Ing v Lesjöfors 93—95, Hallstahammar 95—97, Finspång 97— 99, övering Lesjöfors 99—00, vkst dir Mor-gårdshammars Mek Verkst AB 00—12, Lesjöfors AB 07—11, Storfors Bruks AB 11—19 o AB Gbgs Bk 22—34, vkst dir o Styr.ordf östafors AB sed. 23. Styr.led Morgårdsham-mars Mek Verkst AB sed. 00 (ordf sed. 11), Uddeholms AB sed. 13, Halmst Jvks AB sed. 22, Blombacka AB sed. 30, Degerfors Jvks AB sed. 39. Ldstm Värml l 09, ordf Kroppa s :ns kom.stämma 16—18, d:o Färnebo hds vägstyr 17—19. Led av The Iron and Steel Inst London sed. 04. Led av Sv Tekn.frn. Resor: USA 99, 21 o 23; europ länder uppr ggr. Avtrycket: »Ur Storforsverkcns historia» samt UDDS i tekn o ekon frågor. KVO2kl, KNO; Sv Luftfartfrbs GM, PatrGM. Hobby: Lösande av mek problem.",
    "translated": "EKMAN, Gustaf, Bank director, Östafors, born Torrskog, Älvsborg County, on 21/12 1872, son of industrialist J W E and Julia Wallroth, married to Hedvig Larson. Mother deceased. Education: Gothenburg 1891, Agricultural College in Alnarp, 1891-1892. Started working at Lesjöfors, 1893-1895, Hallstahammar, 1895-1897, Finspång, 1897-1899. Became manager at Lesjöfors, 1899-1900, then growth director at Morgårdshammars Mek Verkst AB, 1900-1912, Lesjöfors AB, 1907-1911, Storfors Bruks AB, 1911-1919, and AB Gbgs Bk, 1922-1934, growth director and chairman of the board of Östafors AB since 1923. Board member of Morgårdshammars Mek Verkst AB since 1900 (chairman since 1911), Uddeholms AB since 1913, Halmstad Jvks AB since 1922, Blombacka AB since 1930, Degerfors Jvks AB since 1939. Oldest member of Värmland County Council, 1909, chairman of Kroppa municipal meeting, 1916-1918, chairman of Färnebo rural road authority, 1917-1919. Member of The Iron and Steel Institute in London since 1904. Member of the Swedish Technological Association. Travels: USA in 1899, 1921, and 1923; several European countries. Publications: \"From the History of Storfors Works\" and contributions on technical and economic issues. Awarded with Commander of the Royal Order of the Polar Star (KVO2kl), Knight of the Order of the North Star (KNO), Honorary Member of the Swedish Aviation Association (GM), Honorary Member of the Scout Association (PatrGM). Hobby: Solving mechanical problems.",
    "structured": {
        "@context": "http://schema.org",
        "@type": "Person",
        "name": "Gustaf Ekman",
        "birthDate": "1872-12-21",
        "birthPlace": "Torrskog, Älvsborg County",
        "spouse": "Hedvig Larson",
        "education": [
            {
                "startDate": "1891",
                "endDate": "1892",
                "institution": "Gothenburg, Agricultural College in Alnarp"
            }
        ],
        "work": [
            {
                "startDate": "1893",
                "endDate": "1895",
                "position": "Lesjöfors"
            },
            {
                "startDate": "1895",
                "endDate": "1897",
                "position": "Hallstahammar"
            },
            {
                "startDate": "1897",
                "endDate": "1899",
                "position": "Finspång"
            },
            {
                "startDate": "1899",
                "endDate": "1900",
                "position": "Lesjöfors (Manager)"
            },
            {
                "startDate": "1900",
                "endDate": "1912",
                "position": "Morgårdshammars Mek Verkst AB (Growth Director)"
            },
            {
                "startDate": "1907",
                "endDate": "1911",
                "position": "Lesjöfors AB (Board Member)"
            },
            {
                "startDate": "1911",
                "endDate": "1919",
                "position": "Storfors Bruks AB (Board Member)"
            },
            {
                "startDate": "1922",
                "endDate": "1934",
                "position": "AB Gbgs Bk (Growth Director, Chairman of the Board)"
            },
            {
                "startDate": "1923",
                "position": "Östafors AB (Chairman of the Board)"
            },
            {
                "startDate": "1900",
                "position": "Morgårdshammars Mek Verkst AB (Board Member, Chairman since 1911)"
            },
            {
                "startDate": "1913",
                "position": "Uddeholms AB (Board Member)"
            },
            {
                "startDate": "1922",
                "position": "Halmstad Jvks AB (Board Member)"
            },
            {
                "startDate": "1930",
                "position": "Blombacka AB (Board Member)"
            },
            {
                "startDate": "1939",
                "position": "Degerfors Jvks AB (Board Member)"
            }
        ],
        "membership": [
            {
                "organization": "Värmland County Council",
                "position": "Oldest Member",
                "startDate": "1909"
            },
            {
                "organization": "Kroppa municipal meeting",
                "position": "Chairman",
                "startDate": "1916",
                "endDate": "1918"
            },
            {
                "organization": "Färnebo rural road authority",
                "position": "Chairman",
                "startDate": "1917",
                "endDate": "1919"
            },
            {
                "organization": "The Iron and Steel Institute",
                "position": "Member",
                "startDate": "1904"
            },
            {
                "organization": "Swedish Technological Association",
                "position": "Member"
            }
        ],
        "travel": [
            {
                "destination": "USA",
                "year": [
                    "1899",
                    "1921",
                    "1923"
                ]
            },
            {
                "destination": "Various European Countries"
            }
        ],
        "publications": [
            "From the History of Storfors Works",
            "Contributions on technical and economic issues"
        ],
        "awards": [
            "Commander of the Royal Order of the Polar Star (KVO2kl)",
            "Knight of the Order of the North Star (KNO)",
            "Honorary Member of the Swedish Aviation Association (GM)",
            "Honorary Member of the Scout Association (PatrGM)"
        ],
        "hobby": "Solving mechanical problems"
    },
    "occupations": {
        "career": [
            {
                "occupational_title": "Bank Director",
                "workplace": "Östafors",
                "industry": "Banking",
                "start_date": "1923"
            },
            {
                "occupational_title": "Manager",
                "workplace": "Lesjöfors",
                "industry": "Unknown",
                "start_date": "1899"
            },
            {
                "occupational_title": "Growth Director",
                "workplace": "Morgårdshammars Mek Verkst AB",
                "industry": "Machinery Manufacturing",
                "start_date": "1900"
            },
            {
                "occupational_title": "Growth Director",
                "workplace": "Lesjöfors AB",
                "industry": "Unknown",
                "start_date": "1907"
            },
            {
                "occupational_title": "Growth Director",
                "workplace": "Storfors Bruks AB",
                "industry": "Unknown",
                "start_date": "1911"
            },
            {
                "occupational_title": "Growth Director",
                "workplace": "AB Gbgs Bk",
                "industry": "Banking",
                "start_date": "1922"
            }
        ]
    }
}