{
    "original": "FRENNESEN, Torsten Rye, Civilingenjör, Borås, f Malmkp, Sörml l, 20/5 85 av länsveterinär N O R F o Gerda Berg, gm Elsa Jonzon. Halmst hal, CTI (E) 05, ex Poly-technicum Zurich 08. Linjeing v Kraftuber-tragungswerke Rheinfelden Baden 08—09, montageing ASEA 09—11, ch f John M Sum-ner &amp; Co:s elektr avd Mexico 12—13, anst ASEA:s exp.avd 13—14, ch ASEA:s Norrköpingsfil 14—19, inköpsch v ASEA 19— 22, försäljn.ch v Standard Varnish Works Sthlm 22—24, v Sv Elektromek Ind AB Hbg 24—26, anst h gen.konsul T Kreuger o STAB ss ch f Litauiska tändsticksAB 26—30, div uppdr i Sthlm 30—33, distr.ch f Livförsäkr.-AB Victorias sparursavd Borås 33, ombud f Städernas Försäkr.bol, Sjöförsäkr.AB Gaut-hiod mfl sed. 36. Fd löjtn i Göta art.reg:s res. Ag Eningsnäs i Seglora s:n. Resor: Finl, Norge, Danm, Tyskl, Schweiz, Ital, Belg, Engl, Frankr, Span, Lit, Lettl, Kuba, USA, Kanada, Mexico. Led Sv Tekn.frn. Frimurare. Rotary mm.",
    "translated": "FRENNESEN, Torsten Rye, Civil Engineer, Borås, born in Malmköping, Sörmland county, on May 20th, 1885, son of county veterinarian N.O.R.F and Gerda Berg, married to Elsa Jonzon. Completed Halmstad Technical Institute (Electrical) in 1905, former student of the Polytechnic University of Zurich in 1908. Worked at the power transmission company Kraftübertragungswerke Rheinfelden in Baden from 1908 to 1909, as a mounting engineer at ASEA from 1909 to 1911, chief engineer at John M. Sumner & Co.'s electrical department in Mexico from 1912 to 1913, employee of ASEA's export department from 1913 to 1914, chief of ASEA's Norrköping branch from 1914 to 1919, purchasing manager at ASEA from 1919 to 1922, sales manager at Standard Varnish Works in Stockholm from 1922 to 1924, at Swedish Electromechanical Industries in Helsingborg from 1924 to 1926, employed by General Consul T. Kreuger and STAB as chief engineer of the Lithuanian Match AB from 1926 to 1930, various assignments in Stockholm from 1930 to 1933, district manager of the Savings Clocks Department at Livförsäkrings AB Victoria in Borås in 1933, representative for Städernas Försäkringsbolag, Sjöförsäkringsbolag Gaut-hiod, and others since 1936. Former Lieutenant in the Göta Artillery Regiment's reserve. Travels: Finland, Norway, Denmark, Germany, Switzerland, Italy, Belgium, England, France, Spain, Lithuania, Latvia, Cuba, USA, Canada, Mexico. Member of the Swedish Technical Association, Freemason, Rotary, etc.",
    "structured": {
        "@context": "https://schema.org",
        "@type": "Person",
        "name": "Torsten Rye Frennesen",
        "jobTitle": [
            "Mounting Engineer",
            "Chief Engineer",
            "Purchasing Manager",
            "Sales Manager",
            "Chief Engineer",
            "District Manager",
            "Representative"
        ],
        "address": {
            "@type": "PostalAddress",
            "addressLocality": "Borås"
        },
        "birthPlace": {
            "@type": "City",
            "name": "Malmköping"
        },
        "birthDate": "1885-05-20",
        "parents": [
            {
                "@type": "Person",
                "name": "N.O.R.F"
            },
            {
                "@type": "Person",
                "name": "Gerda Berg"
            }
        ],
        "spouse": {
            "@type": "Person",
            "name": "Elsa Jonzon"
        },
        "education": {
            "@type": "EducationalOccupationalCredential",
            "credentialCategory": "Electrical Engineering",
            "credentialSubject": "Halmstad Technical Institute",
            "completionDate": "1905"
        },
        "alumniOf": {
            "@type": "CollegeOrUniversity",
            "name": "Polytechnic University of Zurich",
            "endDate": "1908"
        },
        "worksFor": [
            {
                "@type": "Organization",
                "name": "Kraftübertragungswerke Rheinfelden"
            },
            {
                "@type": "Organization",
                "name": "ASEA"
            },
            {
                "@type": "Organization",
                "name": "John M. Sumner & Co."
            },
            {
                "@type": "Organization",
                "name": "Swedish Electromechanical Industries"
            },
            {
                "@type": "Organization",
                "name": "Standard Varnish Works"
            },
            {
                "@type": "Organization",
                "name": "Lituanian Match AB"
            },
            {
                "@type": "Organization",
                "name": "Livförsäkrings AB Victoria"
            },
            {
                "@type": "Organization",
                "name": "Städernas Försäkringsbolag"
            },
            {
                "@type": "Organization",
                "name": "Sjöförsäkringsbolag Gaut-hiod"
            }
        ],
        "memberOf": {
            "@type": "Organization",
            "name": "Swedish Technical Association"
        },
        "affiliation": [
            {
                "@type": "Organization",
                "name": "Freemasons"
            },
            {
                "@type": "Organization",
                "name": "Rotary"
            }
        ],
        "militaryService": {
            "@type": "Organization",
            "name": "Göta Artillery Regiment"
        },
        "residence": {
            "@type": "Place",
            "name": "Seglora"
        },
        "travel": {
            "@type": "ItemList",
            "numberOfItems": 17,
            "itemListElement": [
                "Finland",
                "Norway",
                "Denmark",
                "Germany",
                "Switzerland",
                "Italy",
                "Belgium",
                "England",
                "France",
                "Spain",
                "Lithuania",
                "Latvia",
                "Cuba",
                "USA",
                "Canada",
                "Mexico"
            ]
        }
    },
    "occupations": {
        "career": [
            {
                "occupational_title": "Civil Engineer",
                "workplace": "Borås",
                "industry": "Engineering",
                "start_date": null
            },
            {
                "occupational_title": "Mounting Engineer",
                "workplace": "Kraftübertragungswerke Rheinfelden, Baden",
                "industry": "Power transmission",
                "start_date": "1908"
            },
            {
                "occupational_title": "Montage Engineer",
                "workplace": "ASEA",
                "industry": "Engineering",
                "start_date": "1909"
            },
            {
                "occupational_title": "Chief Engineer",
                "workplace": "John M. Sumner & Co.'s Electrical Department",
                "industry": "Electrical",
                "start_date": "1912"
            },
            {
                "occupational_title": "Employee",
                "workplace": "ASEA Export Department",
                "industry": "Export",
                "start_date": "1913"
            },
            {
                "occupational_title": "Chief",
                "workplace": "ASEA Norrköping Branch",
                "industry": "Engineering",
                "start_date": "1914"
            },
            {
                "occupational_title": "Purchasing Manager",
                "workplace": "ASEA",
                "industry": "Engineering",
                "start_date": "1919"
            },
            {
                "occupational_title": "Sales Manager",
                "workplace": "Standard Varnish Works",
                "industry": "Manufacturing",
                "start_date": "1922"
            },
            {
                "occupational_title": "Employee",
                "workplace": "Swedish Electromechanical Industries",
                "industry": "Engineering",
                "start_date": "1924"
            },
            {
                "occupational_title": "Chief Engineer",
                "workplace": "Lithuanian Match AB",
                "industry": "Matchstick",
                "start_date": "1926"
            },
            {
                "occupational_title": "District Manager",
                "workplace": "Livförsäkrings AB Victoria",
                "industry": "Insurance",
                "start_date": "1933"
            },
            {
                "occupational_title": "Representative",
                "workplace": "Städernas Försäkringsbolag, Sjöförsäkringsbolag Gaut-hiod, and others",
                "industry": "Insurance",
                "start_date": "1936"
            }
        ]
    }
}