{
    "original": "CARLSON, Olof Birger, Civilingenjör, Filip-stad, f Väne-Åsaka, Älvsb l, 18/3 91 av lantbr J C o Alma Ohlsson, gm Edith Eriksson, Studex Vänersb:s h a l 09, KTH 13. Rit v Morgårdshammar Mek Verkst AB 13—14, konstr h Knut Eriksson &amp; Co Hosjö 15—16, ord lär v Bergsk Filipst sed. 16. Led av stdsflm 29—42, av dräts.kamm 24—36, ordf i brandstyr 24—34, i elverksstyr sed. 37, led av byggn.nmdii sed. 23, styr.led i Filipst Sparbk sed. 34. Resor: Tyskl, Engl, Frankr, Ital, Ung mfl. Av trycket: Avsnitt av lärob 1 mek teknol, korresp.kurs i mek mtrlprovn. RVO; Frimurare, Odd Fellow. Hobby: Fiske.",
    "translated": "CARLSON, Olof Birger, Civil Engineer, Filipstad, born in Väne-Åsaka, Älvsborg län, on March 18, 1891, son of farmer J C and Alma Ohlsson. Married to Edith Eriksson. Completed studies at Vänersborg Technical School in 1909 and at the Royal Institute of Technology (KTH) in 1913. Worked as a draftsman at Morgårdshammar Mechanical Works AB from 1913 to 1914, and as a designer at Knut Eriksson & Co in Hosjö from 1915 to 1916. Became a mining teacher in Filipstad in 1916. Served as a member of the county film board from 1929 to 1942, and on the municipal finance committee from 1924 to 1936. Was chairman of the fire brigade from 1924 to 1934, and of the power company from 1937 onwards. Served on the building committee since 1923 and as a board member of the Filipstad Savings Bank since 1934. Traveled to Germany, England, France, Italy, Hungary, and other places. Publications include sections of a textbook on mechanical technology and a correspondence course in mechanical material testing. Received the Royal Order of Vasa. Member of the Freemasons and the Odd Fellows. Hobby: Fishing.",
    "structured": {
        "@context": "https://schema.org",
        "@type": "Person",
        "name": "Olof Birger Carlson",
        "jobTitle": "Civil Engineer",
        "birthDate": "1891-03-18",
        "birthPlace": "Väne-Åsaka, Älvsborg län",
        "parent": [
            {
                "@type": "Person",
                "name": "J C Carlson",
                "jobTitle": "Farmer"
            },
            {
                "@type": "Person",
                "name": "Alma Ohlsson",
                "jobTitle": "Farmer"
            }
        ],
        "spouse": {
            "@type": "Person",
            "name": "Edith Eriksson"
        },
        "education": [
            {
                "@type": "EducationalOrganization",
                "name": "Vänersborg Technical School",
                "startDate": "1909",
                "endDate": "1909"
            },
            {
                "@type": "EducationalOrganization",
                "name": "Royal Institute of Technology (KTH)",
                "startDate": "1913",
                "endDate": "1913"
            }
        ],
        "worksFor": [
            {
                "@type": "Organization",
                "name": "Morgårdshammar Mechanical Works AB",
                "startDate": "1913",
                "endDate": "1914",
                "jobTitle": "Draftsman"
            },
            {
                "@type": "Organization",
                "name": "Knut Eriksson & Co",
                "startDate": "1915",
                "endDate": "1916",
                "jobTitle": "Designer"
            },
            {
                "@type": "Organization",
                "name": "Filipstad Mining School",
                "startDate": "1916",
                "jobTitle": "Mining Teacher"
            }
        ],
        "memberOf": [
            {
                "@type": "Organization",
                "name": "County Film Board",
                "startDate": "1929",
                "endDate": "1942",
                "position": "Member"
            },
            {
                "@type": "Organization",
                "name": "Municipal Finance Committee",
                "startDate": "1924",
                "endDate": "1936",
                "position": "Member"
            },
            {
                "@type": "Organization",
                "name": "Fire Brigade",
                "startDate": "1924",
                "endDate": "1934",
                "position": "Chairman"
            },
            {
                "@type": "Organization",
                "name": "Power Company",
                "startDate": "1937",
                "position": "Chairman"
            },
            {
                "@type": "Organization",
                "name": "Building Committee",
                "startDate": "1923",
                "position": "Member"
            },
            {
                "@type": "Organization",
                "name": "Filipstad Savings Bank",
                "startDate": "1934",
                "position": "Board Member"
            },
            {
                "@type": "Organization",
                "name": "Freemasons"
            },
            {
                "@type": "Organization",
                "name": "Odd Fellows"
            }
        ],
        "nationality": "Swedish",
        "hobbies": "Fishing",
        "publication": [
            {
                "@type": "PublicationEvent",
                "name": "Sections of a Textbook on Mechanical Technology"
            },
            {
                "@type": "PublicationEvent",
                "name": "Correspondence Course in Mechanical Material Testing"
            }
        ],
        "award": {
            "@type": "Order",
            "name": "Royal Order of Vasa"
        },
        "memberOfCountries": [
            "Germany",
            "England",
            "France",
            "Italy",
            "Hungary"
        ]
    },
    "occupations": {
        "career": [
            {
                "occupational_title": "Civil Engineer",
                "workplace": "Filipstad",
                "industry": "Engineering",
                "start_date": "1913"
            },
            {
                "occupational_title": "Draftsman",
                "workplace": "Morgårdshammar Mechanical Works AB",
                "industry": "Mechanical Engineering",
                "start_date": "1913"
            },
            {
                "occupational_title": "Designer",
                "workplace": "Knut Eriksson & Co",
                "industry": "Mechanical Engineering",
                "start_date": "1915"
            },
            {
                "occupational_title": "Mining Teacher",
                "workplace": "Filipstad",
                "industry": "Education",
                "start_date": "1916"
            }
        ]
    }
}