{
    "original": "ABELSON, Birger Leonard, Fabrikör, Nybro, f Kosta 17/3 90 av Johannes Abel Pettersson o Johanna Ljungberg, gm Elin Melcher. Glasslip Kosta glasbr 00—06, anst. Sth glasslip. &amp; speg.fabr 07, Göta livg 08—10, åter Kosta glasbr 11—16, Trondheims glasslip. &amp; speg.fabr 17—19, Orrefors glasbr 20—30, etbl fma Abelssons glas- &amp; kristallsliperi 31. Ordf dräts.kamm, stdflm, styr.led Nybro brunn &amp; badanst, sparbk o koop hdlsfrn. Resor: Norge 17—19, Danm 36.",
    "translated": "ABELSON, Birger Leonard, Manufacturer, Nybro, born in Kosta on March 17, 1890, to Johannes Abel Pettersson and Johanna Ljungberg, married to Elin Melcher. Worked at Kosta Glassworks as a glassblower from 1900 to 1906, employed at a glassworks in Stockholm for mirrors from 1907, served in the Göta Life Guard Regiment from 1908 to 1910, returned to Kosta Glassworks from 1911 to 1916, worked at a glassworks in Trondheim for mirrors from 1917 to 1919, worked at Orrefors Glassworks from 1920 to 1930, established Abelsson's Glass and Crystal Grinding Workshop in 1931. Served as chairman of the financial committee, city council, board member of Nybro spa and bathing facility, savings bank, and cooperative trade association. Traveled to Norway from 1917 to 1919, Denmark in 1936.",
    "structured": {
        "@context": "https://schema.org",
        "@type": "Person",
        "name": "Birger Leonard Abelson",
        "birthDate": "1890-03-17",
        "birthPlace": "Kosta, Sweden",
        "parents": [
            {
                "@type": "Person",
                "name": "Johannes Abel Pettersson"
            },
            {
                "@type": "Person",
                "name": "Johanna Ljungberg"
            }
        ],
        "spouse": {
            "@type": "Person",
            "name": "Elin Melcher"
        },
        "occupation": "Manufacturer",
        "description": "Birger Leonard Abelson was a Swedish manufacturer.",
        "memberOf": [
            {
                "@type": "Place",
                "name": "Norway",
                "startDate": "1917",
                "endDate": "1919"
            },
            {
                "@type": "Place",
                "name": "Denmark",
                "startDate": "1936"
            }
        ]
    },
    "occupations": {
        "career": [
            {
                "occupational_title": "Glassblower",
                "workplace": "Kosta Glassworks",
                "industry": "Glass manufacturing",
                "start_date": "1900"
            },
            {
                "occupational_title": "Mirrors employee",
                "workplace": "Stockholm glassworks",
                "industry": "Glass manufacturing",
                "start_date": "1907"
            },
            {
                "occupational_title": "Göta Life Guard Regiment soldier",
                "workplace": "Göta Life Guard Regiment",
                "industry": "Military",
                "start_date": "1908"
            },
            {
                "occupational_title": "Glassblower",
                "workplace": "Kosta Glassworks",
                "industry": "Glass manufacturing",
                "start_date": "1911"
            },
            {
                "occupational_title": "Mirrors employee",
                "workplace": "Trondheim glassworks",
                "industry": "Glass manufacturing",
                "start_date": "1917"
            },
            {
                "occupational_title": "Glassblower",
                "workplace": "Orrefors Glassworks",
                "industry": "Glass manufacturing",
                "start_date": "1920"
            },
            {
                "occupational_title": "Founder",
                "workplace": "Abelsson's Glass and Crystal Grinding Workshop",
                "industry": "Glass and crystal grinding",
                "start_date": "1931"
            }
        ]
    }
}