{
    "original": "OHLIN, Bertil Gotthard, Professor, Stockholm, f Gråmanstorp, Krst l, 23/4 99 av landsfiskal E W O o Ingeborg Sandberg, gm Evy Kruse. Fil kand Lund 17, DHS 19, fil lic Sthlm 22, A. M. Harvard 23, fil dr Sthlm 24, doc små år. T f prof StHS 24, prof i statsvetenskap Köpenh univ 24—29, prof i nat.ek HHS sed. 29, anst Nät Frb 31 ss led av under-sökn rör världsekon depressionen, prof Univ of Calif 37, riksdagsm l:a kamm (fp) sed. 38, ordf 42 års järnv.kostn.utredn, led 42 års jordbr.komm. Stud.res Tyskl 20, Frankr 21, Engl, USA 22—23. Av trycket: Bl a »Inter-regional and Internat Trade» (33), »Utrikes-hdl o hdlspolit» 3. uppl (43), »Fri eller dirigerad ekonomi» (34), »Staterna o världsekonomin» (37). RNS:tOO, IFO, RDDO. Hobbies: Skidåkning, fjällvandring.",
    "translated": "OHLIN, Bertil Gotthard, Professor, Stockholm, born in Gråmanstorp, christened on the 1st of April, 1899, son of district prosecutor E.W.O. and Ingeborg Sandberg, married to Evy Kruse. Bachelor of Arts, Lund, 1917, Doctor of Humanities and Social Sciences, Stockholm, 1919, licentiate, Stockholm, 1922, A.M. Harvard, 1923, Ph.D., Stockholm, 1924, visiting professor, Stockholm School of Social Sciences, 1924, professor of political science, University of Copenhagen, 1924-1929, professor of national economics, Stockholm School of Economics, since 1929, employed by the National Federation of Cooperative Societies since 1931 as part of the investigation regarding the global economic depression, professor, University of California, 1937, member of the Parliament, First Chamber (Liberal Party), since 1938, chairman of the 1942 Railway Costs Investigation Committee, member of the 1942 Agricultural Committee. Study trips to Germany, 1920, France, 1921, England, USA, 1922-1923. Published works include, among others: \"Inter-regional and International Trade\" (1933), \"Foreign Trade and Trade Policy\" 3rd edition (1943), \"Free or Directed Economy\" (1934), \"The Nations and the Global Economy\" (1937). Royal Swedish Academy of Sciences: member since 1900, member of the Institute for International Economic Research, member of the Royal Swedish Academy of Engineering Sciences. Hobbies: skiing, hiking in the mountains.",
    "structured": {
        "@context": "https://schema.org",
        "@type": "Person",
        "name": "Bertil Gotthard Ohlin",
        "jobTitle": "Professor",
        "address": {
            "@type": "PostalAddress",
            "addressLocality": "Stockholm"
        },
        "birthPlace": {
            "@type": "Place",
            "name": "Gråmanstorp"
        },
        "birthDate": "1899-04-01",
        "father": {
            "@type": "Person",
            "name": "E.W.O. Ohlin"
        },
        "mother": {
            "@type": "Person",
            "name": "Ingeborg Sandberg"
        },
        "spouse": {
            "@type": "Person",
            "name": "Evy Kruse"
        },
        "education": [
            {
                "@type": "EducationalOccupationalCredential",
                "credentialCategory": "Bachelor of Arts",
                "educationalLevel": "Bachelor's Degree",
                "awardingInstitution": "Lund University",
                "dateAwarded": "1917"
            },
            {
                "@type": "EducationalOccupationalCredential",
                "credentialCategory": "Doctor of Humanities and Social Sciences",
                "educationalLevel": "Doctoral Degree",
                "awardingInstitution": "Stockholm University",
                "dateAwarded": "1919"
            },
            {
                "@type": "EducationalOccupationalCredential",
                "credentialCategory": "Licentiate",
                "educationalLevel": "Licentiate Degree",
                "awardingInstitution": "Stockholm University",
                "dateAwarded": "1922"
            },
            {
                "@type": "EducationalOccupationalCredential",
                "credentialCategory": "Master of Arts",
                "educationalLevel": "Master's Degree",
                "awardingInstitution": "Harvard University",
                "dateAwarded": "1923"
            },
            {
                "@type": "EducationalOccupationalCredential",
                "credentialCategory": "Ph.D.",
                "educationalLevel": "Doctoral Degree",
                "awardingInstitution": "Stockholm University",
                "dateAwarded": "1924"
            }
        ],
        "memberOf": [
            {
                "@type": "Organization",
                "name": "Stockholm School of Social Sciences",
                "startDate": "1924",
                "endDate": "1929",
                "jobTitle": "Visiting Professor"
            },
            {
                "@type": "Organization",
                "name": "University of Copenhagen",
                "startDate": "1924",
                "endDate": "1929",
                "jobTitle": "Professor of Political Science"
            },
            {
                "@type": "Organization",
                "name": "Stockholm School of Economics",
                "startDate": "1929",
                "jobTitle": "Professor of National Economics"
            },
            {
                "@type": "Organization",
                "name": "National Federation of Cooperative Societies",
                "startDate": "1931",
                "jobTitle": "Employee"
            },
            {
                "@type": "Organization",
                "name": "University of California",
                "startDate": "1937",
                "jobTitle": "Professor"
            },
            {
                "@type": "Organization",
                "name": "Swedish Parliament",
                "startDate": "1938",
                "jobTitle": "Member (First Chamber)"
            },
            {
                "@type": "Organization",
                "name": "Royal Swedish Academy of Sciences",
                "startDate": "1900",
                "jobTitle": "Member"
            },
            {
                "@type": "Organization",
                "name": "Institute for International Economic Research",
                "jobTitle": "Member"
            },
            {
                "@type": "Organization",
                "name": "Royal Swedish Academy of Engineering Sciences",
                "jobTitle": "Member"
            }
        ],
        "studyTrip": [
            {
                "@type": "Trip",
                "name": "Germany",
                "startDate": "1920"
            },
            {
                "@type": "Trip",
                "name": "France",
                "startDate": "1921"
            },
            {
                "@type": "Trip",
                "name": "England",
                "startDate": "1922"
            },
            {
                "@type": "Trip",
                "name": "USA",
                "startDate": "1922",
                "endDate": "1923"
            }
        ],
        "publications": [
            {
                "@type": "PublicationIssue",
                "name": "Inter-regional and International Trade",
                "datePublished": "1933"
            },
            {
                "@type": "PublicationIssue",
                "name": "Foreign Trade and Trade Policy",
                "datePublished": "1943",
                "edition": "3rd edition"
            },
            {
                "@type": "PublicationIssue",
                "name": "Free or Directed Economy",
                "datePublished": "1934"
            },
            {
                "@type": "PublicationIssue",
                "name": "The Nations and the Global Economy",
                "datePublished": "1937"
            }
        ],
        "hobbies": [
            "Skiing",
            "Hiking in the mountains"
        ]
    },
    "occupations": {
        "career": [
            {
                "occupational_title": "Professor",
                "workplace": "Stockholm",
                "industry": "Higher Education",
                "start_date": null
            },
            {
                "occupational_title": "Visiting Professor",
                "workplace": "Stockholm School of Social Sciences",
                "industry": "Higher Education",
                "start_date": "1924"
            },
            {
                "occupational_title": "Professor of Political Science",
                "workplace": "University of Copenhagen",
                "industry": "Higher Education",
                "start_date": "1924"
            },
            {
                "occupational_title": "Professor of National Economics",
                "workplace": "Stockholm School of Economics",
                "industry": "Higher Education",
                "start_date": "1929"
            },
            {
                "occupational_title": "Professor",
                "workplace": "University of California",
                "industry": "Higher Education",
                "start_date": "1937"
            }
        ]
    }
}