{
    "original": "ERICSSON, Johan Elof, Disponent, förutv Statsråd, Åtvidaberg, f Trankil, Värml län, 25/8 87. Disp o vkst dir f AB Åtvidabergs Ind. Tidigare anst Lennartsfors AB, Sv Litograf Tryckerier o Sv Möbelfabr. Led utredn om folkförsörjn o arb.fred 35, statsråd o ch f hdlsdep 36, bestyr.ordf New York-utställn 38— 39, ordf Stat Trptkommiss 39—40, ordf hjälp-komm f Finl invalider, led 2:a kamm, muni-cip.flm. Ordf Sv Träind.frb, styr.led Åtvida-bgskonc olika föret. Sk bkn, Försäkr.bol Sk, Sv Ind.frb, Sv Allm Exp.frn, Sv hdlskamm i New York, Sv Gymn- o Idr.frn riksfrb överstyr, ordf Sv Fotb.frb. RNO, KVOlkl, KFinl-VROlkl, KFFrK, KBLeopOlkl, Riksidr.frb ftjt g, Fotb.frb d:o Hirn. Hobby: Fotboll.",
    "translated": "ERICSSON, Johan Elof, Manager, former Minister, Åtvidaberg, born in Trankil, Värmland county, 25/8 1887. Manager and Deputy Managing Director of AB Åtvidabergs Industry. Formerly employed by Lennartsfors AB, Swedish Lithographic Printers, and Swedish Furniture Factory. Led investigations on national supply and labor peace in 1935, served as Minister and Chief of the Trade Department in 1936, Chairman of the Board of the New York Exhibition from 1938 to 1939, Chairman of the State Traffic Committee from 1939 to 1940, Chairman of the Aid Committee for Finnish invalids and member of the 2nd Chamber and Municipal Council, among others. Chairman of the Swedish Wood Industry Association and board member of various companies in Åtvidaberg. Member of the Swedish Bank, Insurance Company Sk, Swedish Industry Association, Swedish General Export Association, Swedish Chamber of Commerce in New York, Swedish Gymnastics and Sports Association, and President of the Swedish Football Association. Received Order of the North Star, Order of Vasa, Order of the Lion of Finland, Order of the Finnish White Rose, Order of the Belgian Crown, and the Swedish Sports Confederation's Merit Badge in gold, as well as the Football Association's Medal of Honor. Hobby: Football.",
    "structured": {
        "@context": "https://schema.org",
        "@type": "Person",
        "name": "Johan Elof Ericsson",
        "birthDate": "1887-08-25",
        "birthPlace": {
            "@type": "Place",
            "address": {
                "@type": "PostalAddress",
                "addressLocality": "Trankil",
                "addressRegion": "Värmland",
                "addressCountry": "Sweden"
            }
        },
        "description": "Manager, former Minister",
        "jobTitle": "Manager",
        "nationality": "Swedish",
        "memberOf": [
            {
                "@type": "Organization",
                "name": "AB Åtvidabergs Industry"
            },
            {
                "@type": "Organization",
                "name": "Lennartsfors AB"
            },
            {
                "@type": "Organization",
                "name": "Swedish Lithographic Printers"
            },
            {
                "@type": "Organization",
                "name": "Swedish Furniture Factory"
            },
            {
                "@type": "Organization",
                "name": "New York Exhibition",
                "startDate": "1938-01-01",
                "endDate": "1939-12-31"
            },
            {
                "@type": "Organization",
                "name": "State Traffic Committee",
                "startDate": "1939-01-01",
                "endDate": "1940-12-31"
            },
            {
                "@type": "Organization",
                "name": "Aid Committee for Finnish invalids"
            },
            {
                "@type": "Organization",
                "name": "Swedish Wood Industry Association"
            },
            {
                "@type": "Organization",
                "name": "Swedish Bank"
            },
            {
                "@type": "Organization",
                "name": "Insurance Company Sk"
            },
            {
                "@type": "Organization",
                "name": "Swedish Industry Association"
            },
            {
                "@type": "Organization",
                "name": "Swedish General Export Association"
            },
            {
                "@type": "Organization",
                "name": "Swedish Chamber of Commerce in New York"
            },
            {
                "@type": "Organization",
                "name": "Swedish Gymnastics and Sports Association",
                "memberOf": {
                    "@type": "Organization",
                    "name": "Swedish Sports Confederation",
                    "memberOf": {
                        "@type": "Organization",
                        "name": "International Federation of Sports Medicine"
                    }
                }
            },
            {
                "@type": "Organization",
                "name": "Swedish Football Association"
            }
        ],
        "awards": [
            {
                "@type": "Order",
                "name": "Order of the North Star",
                "awardDate": "UNKNOWN"
            },
            {
                "@type": "Order",
                "name": "Order of Vasa",
                "awardDate": "UNKNOWN"
            },
            {
                "@type": "Order",
                "name": "Order of the Lion of Finland",
                "awardDate": "UNKNOWN"
            },
            {
                "@type": "Order",
                "name": "Order of the Finnish White Rose",
                "awardDate": "UNKNOWN"
            },
            {
                "@type": "Order",
                "name": "Order of the Belgian Crown",
                "awardDate": "UNKNOWN"
            },
            {
                "@type": "Medal",
                "name": "Swedish Sports Confederation's Merit Badge in gold",
                "awardDate": "UNKNOWN"
            },
            {
                "@type": "Medal",
                "name": "Football Association's Medal of Honor",
                "awardDate": "UNKNOWN"
            }
        ],
        "sameAs": {
            "@type": "URL",
            "url": "UNKNOWN"
        },
        "hobby": "Football"
    },
    "occupations": {
        "career": [
            {
                "occupational_title": "Disponent",
                "workplace": "Åtvidaberg",
                "industry": "AB Åtvidabergs Ind",
                "start_date": "Unknown"
            },
            {
                "occupational_title": "Statsråd",
                "workplace": "Hdlsdep",
                "industry": "Trade Department",
                "start_date": "1936"
            },
            {
                "occupational_title": "Ordf",
                "workplace": "New York-utställn",
                "industry": "New York Exhibition",
                "start_date": "1938"
            },
            {
                "occupational_title": "Ordf",
                "workplace": "Stat Trptkommiss",
                "industry": "State Traffic Committee",
                "start_date": "1939"
            },
            {
                "occupational_title": "Ordf",
                "workplace": "hjälp-komm f Finl invalider",
                "industry": "Aid Committee for Finnish invalids",
                "start_date": "Unknown"
            },
            {
                "occupational_title": "Led",
                "workplace": "2:a kamm, muni-cip.flm",
                "industry": "2nd Chamber and Municipal Council",
                "start_date": "Unknown"
            },
            {
                "occupational_title": "Ordf",
                "workplace": "Sv Träind.frb",
                "industry": "Swedish Wood Industry Association",
                "start_date": "Unknown"
            }
        ]
    }
}