{
    "original": "ELIASSON, Karl Georg, Civilingenjör, Göteborg, f Halmstad 14/7 84 av byggm Jöns E o Kristina Andersson, gm Solveig Margareta Wahlström. Hmst hal 99, CTH (el) 06, Techn Hochsch Karlsruhe 06—07, Anst Luth &amp; Rosén 07, ass eltekn lab CTH 07—16, prof Fredrik H Lamms eltekn byrå 07—11, El Prövn. anst Gbg 11—12. Eg kons eltekn ing-byrå o eltekn lab sed. 12. Ag fastigh Gbg. Kons ing v elvkn i Varberg, Lysekil, Kungälv, Kungsbacka o Älvsb municipsmh. Styr.led Sv Kons Ing frn, ordf Sv Besiktn.man.frn sekt f eltekn. Resor: Tyskl, Schweiz, Ital, Österr, Frankr, Engl, Danm, Norge, Finl 12—39. Av trycket spec.art i div tekn tidskr o dagl tidn. RVO, ProPstGM, PatrstGM; Odd Fellow, PB, Bachelors’ Club. Hobbies: Pistolskytte, smalfilmning.",
    "translated": "ELIASSON, Karl Georg, Civil Engineer, Gothenburg, b. Halmstad 14/7 84 to builder Jöns E and Kristina Andersson, m. Solveig Margareta Wahlström. Moved to Halmstad in 1899, studied at Chalmers University of Technology (electrical engineering) from 1906 to 1907 and at the Technical University of Karlsruhe from 1906 to 1907. Worked at the Luth & Rosén Institution in 1907, assistant at the electrical engineering laboratory at Chalmers University of Technology from 1907 to 1916, professor at Fredrik H Lamm's electrical engineering firm from 1907 to 1911, and at the Electrical Testing Institute in Gothenburg from 1911 to 1912. Owns an electrical engineering consultancy and laboratory since 1912. Also engaged in property businesses in Gothenburg. Consulting engineer for electricity in Varberg, Lysekil, Kungälv, Kungsbacka, and Älvsborg municipalities. Board member of the Swedish Consulting Engineers Association, chairman of the Swedish Inspection-Managers Association in the electrical engineering sector. Traveled to Germany, Switzerland, Italy, Austria, France, England, Denmark, Norway, and Finland from 1912 to 1939. Published articles in various technical journals and newspapers. Awards: Royal Order of Vasa, Knight of the Order of the Polar Star, Knight of the Order of St. Olav; member of Odd Fellow, PB (Bachelors' Club). Hobbies: Shooting with pistols, amateur filmmaking.",
    "structured": {
        "@context": "https://schema.org",
        "@type": "Person",
        "name": "Karl Georg Eliasson",
        "birthDate": "1884-07-14",
        "birthPlace": "Halmstad",
        "description": "Civil Engineer",
        "nationality": "Swedish",
        "father": {
            "@type": "Person",
            "name": "Jöns E",
            "occupation": "Builder"
        },
        "mother": {
            "@type": "Person",
            "name": "Kristina Andersson"
        },
        "spouse": {
            "@type": "Person",
            "name": "Solveig Margareta Wahlström"
        },
        "address": {
            "@type": "PostalAddress",
            "addressLocality": "Gothenburg"
        },
        "education": [
            {
                "@type": "EducationalOccupationalCredential",
                "credentialCategory": "engineering degree",
                "educationalLevel": "Civilingenjör",
                "educationalCredentialAwarded": "Chalmers University of Technology"
            },
            {
                "@type": "EducationalOccupationalCredential",
                "credentialCategory": "engineering degree",
                "educationalLevel": "Civilingenjör",
                "educationalCredentialAwarded": "Technical University of Karlsruhe"
            }
        ],
        "employment": [
            {
                "@type": "OrganizationRole",
                "startDate": "1907",
                "endDate": "1916",
                "roleName": "Assistant",
                "organization": {
                    "@type": "EducationalOrganization",
                    "name": "Chalmers University of Technology",
                    "department": "Electrical Engineering Laboratory"
                }
            },
            {
                "@type": "OrganizationRole",
                "startDate": "1907",
                "endDate": "1911",
                "roleName": "Professor",
                "organization": {
                    "@type": "Organization",
                    "name": "Fredrik H Lamm's Electrical Engineering Firm"
                }
            },
            {
                "@type": "OrganizationRole",
                "startDate": "1911",
                "endDate": "1912",
                "roleName": "Professor",
                "organization": {
                    "@type": "Organization",
                    "name": "Electrical Testing Institute in Gothenburg"
                }
            }
        ],
        "owns": {
            "@type": "Organization",
            "name": "Electrical Engineering Consultancy"
        },
        "business": [
            {
                "@type": "Organization",
                "name": "Property Business in Gothenburg"
            },
            {
                "@type": "Organization",
                "name": "Consulting Engineer for Electricity in Varberg"
            },
            {
                "@type": "Organization",
                "name": "Consulting Engineer for Electricity in Lysekil"
            },
            {
                "@type": "Organization",
                "name": "Consulting Engineer for Electricity in Kungälv"
            },
            {
                "@type": "Organization",
                "name": "Consulting Engineer for Electricity in Kungsbacka"
            },
            {
                "@type": "Organization",
                "name": "Consulting Engineer for Electricity in Älvsborg"
            }
        ],
        "membership": [
            {
                "@type": "Organization",
                "name": "Swedish Consulting Engineers Association",
                "roleName": "Board Member"
            },
            {
                "@type": "Organization",
                "name": "Swedish Inspection-Managers Association",
                "roleName": "Chairman",
                "sector": "Electrical Engineering"
            },
            {
                "@type": "Organization",
                "name": "Odd Fellow"
            },
            {
                "@type": "Organization",
                "name": "PB (Bachelors' Club)"
            }
        ],
        "awards": [
            {
                "@type": "Order",
                "name": "Royal Order of Vasa",
                "awardDate": "unknown"
            },
            {
                "@type": "Order",
                "name": "Order of the Polar Star",
                "awardDate": "unknown"
            },
            {
                "@type": "Order",
                "name": "Order of St. Olav",
                "awardDate": "unknown"
            }
        ],
        "hobbies": [
            "Shooting with pistols",
            "Amateur filmmaking"
        ],
        "travels": [
            "Germany",
            "Switzerland",
            "Italy",
            "Austria",
            "France",
            "England",
            "Denmark",
            "Norway",
            "Finland"
        ],
        "publications": [
            "Various articles in technical journals and newspapers"
        ]
    },
    "occupations": {
        "career": [
            {
                "occupational_title": "Civil Engineer",
                "workplace": "Gothenburg",
                "industry": "",
                "start_date": ""
            },
            {
                "occupational_title": "Assistant at Electrical Engineering Laboratory",
                "workplace": "Chalmers University of Technology",
                "industry": "Education",
                "start_date": "1907"
            },
            {
                "occupational_title": "Professor",
                "workplace": "Fredrik H Lamm's Electrical Engineering Firm",
                "industry": "",
                "start_date": "1907"
            },
            {
                "occupational_title": "Employee at Electrical Testing Institute",
                "workplace": "Gothenburg",
                "industry": "Electrical Engineering",
                "start_date": "1911"
            },
            {
                "occupational_title": "Owner of Electrical Engineering Consultancy and Laboratory",
                "workplace": "",
                "industry": "Consulting",
                "start_date": "1912"
            },
            {
                "occupational_title": "Consulting Engineer for Electricity",
                "workplace": "Varberg, Lysekil, Kungälv, Kungsbacka, and Älvsborg Municipalities",
                "industry": "Government",
                "start_date": ""
            }
        ]
    }
}