{
    "original": "LIND, Sven Gustaf, Direktör, Södertälje, f Sthlm 18/2 01 av ing C G L o Jenny Scher-quist, gm Inga Grönwall. Studex S Latin 19, civ.ing KTH (kem) 25. Anst AB Elektrometall 27—28, driftch AB Arbit, Arb, 28—36, vkst dir 36—37, vkst dir o styr.led AB Arb mek verkst 37—43, vkst dir AB W Dan Bergman, Södt, fr 44. Stdflm sed. 34, v. ordf be-redn.utsk, styr.ordf Arb yrkessk, kommis Arb-utställn 35, ordf luftsk.nmdn, luftsk.frns vkst utsk samt hembygdsfrn Arb Minne. Styr.led AB Berglöfs verkstad, Kopparb, Mekanfrbs gjut.sekt, led öbr o Västml l hdlskamm :s vkst utsk. Resor: Koomm.koll stip Tyskl 27, Belg, Norge, Danm, Finl, Tyskl uppr ggr. Av trycket: Art i Tekn Tidskr. Odd Fellow, Sv tekn. -frn. Tekn frn mfl, ordf Ärter o fläsk-klubben Sthlm. Hobbies: Fiske, trädg.skötsel. Se även LINDH. °LINBAHL, Curt Axel Robert, Bankdirektör, Stockholm, f Kkrona 22/12 92 av bkdir I L o Elin Carlson. Studex 10, Upps univ 10—13. Anst Stat Hdlskomm 16, Sv Lantmännens Bk 18, Jordbr.bkn sed. 23, vkst dir där sed. 36. Styr.led AB Lånekassan af 1914, Fastigh.AB Agraria, Fastigh.AB Villahem. RNO.",
    "translated": "LIND, Sven Gustaf, Director, Södertälje, b. Stockholm 18/2 01, son of engineer C G L and Jenny Scherquist, m. Inga Grönwall. Graduated from S Latin School in 1919, graduated as a civil engineer from the Royal Institute of Technology (chemistry) in 1925. Employed at AB Elektrometall from 1927 to 1928, then at AB Arbit as a department manager from 1928 to 1936, promoted to vice director from 1936 to 1937, and vice director and board member at AB Arb Mek Verkstad from 1937 to 1943. Vice director at AB W Dan Bergman in Södertälje since 1944. Member of the Stockholm city council since 1934, vice chairman of the preparatory committee, chairman of the board of Arbetsyrkesskolan, committee member of the Labor Exhibition in 1935, chairman of the aviation school committee, member of the aviation school expansion committee, and chairman of the local heritage association Arb Minne. Board member of AB Berglöfs Verkstad, Kopparberg, the Mechanical Industry Trade Association Casting Section, and a member of the Örebro and Västmanland Chamber of Commerce's growth committee. Travelled to Germany on the Commerce Inspectorate scholarship in 1927, visited Belgium, Norway, Denmark, Finland, and Germany several times. Published articles in Teknisk Tidskrift. Member of the Odd Fellow lodge, Swedish Technological Association, Technological Association for Women, chairman of the Pea and Pork Club in Stockholm. Hobbies: Fishing, gardening. See also LINDH.\n\nLINBAHL, Curt Axel Robert, Bank Director, Stockholm, b. Karlskrona 22/12 92, son of bank director I L and Elin Carlson. Graduated in 1910, attended Uppsala University from 1910 to 1913. Employed at the Commercial Inspectorate in 1916, Swedish Farmers' Bank in 1918, and the Agricultural Bank from 1923, promoted to vice director in 1936. Board member of AB Lånekassan af 1914, Fastighets AB Agraria, Fastighets AB Villahem. RNO...",
    "structured": {
        "@context": "https://schema.org/",
        "@type": "Person",
        "name": "Sven Gustaf Lind",
        "jobTitle": "Director",
        "address": {
            "@type": "PostalAddress",
            "addressLocality": "Södertälje"
        },
        "birthDate": "1901-02-18",
        "parent": [
            {
                "@type": "Person",
                "name": "C G L Lind",
                "jobTitle": "Engineer"
            },
            {
                "@type": "Person",
                "name": "Jenny Scherquist"
            }
        ],
        "spouse": "Inga Grönwall",
        "education": [
            {
                "@type": "EducationalOrganization",
                "name": "S Latin School",
                "location": "Stockholm",
                "startDate": "1919",
                "endDate": "1925"
            },
            {
                "@type": "EducationalOrganization",
                "name": "Royal Institute of Technology (KTH)",
                "location": "Stockholm",
                "startDate": "1925",
                "endDate": "1925",
                "alumniOf": "chemistry"
            }
        ],
        "memberOf": [
            {
                "@type": "Organization",
                "name": "AB Elektrometall",
                "startDate": "1927",
                "endDate": "1928",
                "jobTitle": "Employee"
            },
            {
                "@type": "Organization",
                "name": "AB Arbit",
                "startDate": "1928",
                "endDate": "1936",
                "jobTitle": "Department Manager"
            },
            {
                "@type": "Organization",
                "name": "AB Arb Mek Verkstad",
                "startDate": "1937",
                "endDate": "1943",
                "jobTitle": "Vice Director and Board Member"
            },
            {
                "@type": "Organization",
                "name": "AB W Dan Bergman",
                "startDate": "1944",
                "jobTitle": "Vice Director"
            },
            {
                "@type": "Organization",
                "name": "Stockholm City Council",
                "startDate": "1934",
                "jobTitle": "Member"
            },
            {
                "@type": "Organization",
                "name": "Arbetsyrkesskolan",
                "jobTitle": "Chairman of the Board"
            },
            {
                "@type": "Organization",
                "name": "Aviation School",
                "jobTitle": "Chairman of the Committee"
            },
            {
                "@type": "Organization",
                "name": "Labor Exhibition",
                "startDate": "1935",
                "jobTitle": "Committee Member"
            },
            {
                "@type": "Organization",
                "name": "Aviation School Expansion Committee"
            },
            {
                "@type": "Organization",
                "name": "Arb Minne",
                "jobTitle": "Chairman"
            },
            {
                "@type": "Organization",
                "name": "AB Berglöfs Verkstad",
                "location": "Kopparberg",
                "jobTitle": "Board Member"
            },
            {
                "@type": "Organization",
                "name": "Mechanical Industry Trade Association Casting Section",
                "jobTitle": "Board Member"
            },
            {
                "@type": "Organization",
                "name": "Örebro and Västmanland Chamber of Commerce",
                "jobTitle": "Member of the Growth Committee"
            },
            {
                "@type": "Organization",
                "name": "Odd Fellow Lodge",
                "jobTitle": "Member"
            },
            {
                "@type": "Organization",
                "name": "Swedish Technological Association",
                "jobTitle": "Member"
            },
            {
                "@type": "Organization",
                "name": "Technological Association for Women",
                "jobTitle": "Member"
            },
            {
                "@type": "Organization",
                "name": "Pea and Pork Club",
                "location": "Stockholm",
                "jobTitle": "Chairman"
            }
        ],
        "hobbies": [
            "Fishing",
            "Gardening"
        ]
    },
    "occupations": {
        "career": [
            {
                "occupational_title": "Director",
                "workplace": "AB Elektrometall",
                "industry": "Electrometallurgical industry",
                "start_date": "1927"
            },
            {
                "occupational_title": "Department Manager",
                "workplace": "AB Arbit",
                "industry": "Unknown",
                "start_date": "1928"
            },
            {
                "occupational_title": "Vice Director",
                "workplace": "AB Arbit",
                "industry": "Unknown",
                "start_date": "1936"
            },
            {
                "occupational_title": "Vice Director",
                "workplace": "AB Arb Mek Verkstad",
                "industry": "Mechanical workshop",
                "start_date": "1937"
            },
            {
                "occupational_title": "Vice Director",
                "workplace": "AB W Dan Bergman",
                "industry": "Unknown",
                "start_date": "1944"
            },
            {
                "occupational_title": "Member of the Stockholm City Council",
                "workplace": "Stockholm City Council",
                "industry": "Government",
                "start_date": "1934"
            }
        ]
    }
}