{
    "original": "LINDEROTH, Paul Oscar Filip, Bokhandlare, Vingåker, f Skarbjörke, Skedevi s :n, Ögl, 1/5 92 av fabr J O L o Vilhelmina Claesson, gm Rigmor Hansen. Anst fad pappershdl o tryckeri (gr 98) 06, ag dsa 18, då utvidg m bokhdl. Ag fastigh Oskarsborg, Vingåker, vkst dir dta fastigh AB. Resor: Engl, Frankr, Holl, Belg 24, Tjeckoslov, Ital 28, Tyskl, Österr, Ung, Danm, Norge upprep ggr. Sport- o skyt-tegm; Odd Fellow, KAK, Sv Filat.frn, HedL Pojkklb U.D. Hobbies: Sport, friluftsliv, Skytte, filateli, antikviteter, resor, musik o sång, konst, böcker.",
    "translated": "LINDEROTH, Paul Oscar Filip, Bookseller, Vingåker, born in Skarbjörke, Skedevi parish, Ögl, on May 1, 1892, son of the factory worker J O L and Vilhelmina Claesson, married to Rigmor Hansen. Employed at his father's paper trading and printing business (since 1898) until 1906, then expanded into book selling. Owns the property Oskarsborg in Vingåker, and also serves as the managing director of a real estate company. Has made multiple trips to England, France, the Netherlands, Belgium (in 1924), Czechoslovakia, Italy (in 1928), Germany, Austria, Hungary, Denmark, and Norway. Member of sports and shooting clubs, Odd Fellow, KAK, Swedish Philatelic Association, HedL Boys' Club, and the U.D. Hobbies: sports, outdoor activities, shooting, philately, antiques, traveling, music and singing, art, books.",
    "structured": {
        "@context": "https://schema.org",
        "@type": "Person",
        "name": "Paul Oscar Filip Linderoth",
        "jobTitle": "Bookseller",
        "address": {
            "@type": "PostalAddress",
            "addressLocality": "Vingåker"
        },
        "birthDate": "1892-05-01",
        "birthPlace": "Skarbjörke, Skedevi parish, Ögl",
        "father": {
            "@type": "Person",
            "name": "J O L"
        },
        "mother": {
            "@type": "Person",
            "name": "Vilhelmina Claesson"
        },
        "spouse": {
            "@type": "Person",
            "name": "Rigmor Hansen"
        },
        "employment": {
            "@type": "Organization",
            "name": "Father's paper trading and printing business",
            "startDate": "1898",
            "endDate": "1906"
        },
        "property": "Oskarsborg, Vingåker",
        "realEstateCompany": {
            "@type": "Organization",
            "name": "Managing director of a real estate company"
        },
        "trips": [
            "England",
            "France",
            "Netherlands",
            "Belgium",
            "Czechoslovakia",
            "Italy",
            "Germany",
            "Austria",
            "Hungary",
            "Denmark",
            "Norway"
        ],
        "memberships": [
            "Sports and shooting clubs",
            "Odd Fellow",
            "KAK",
            "Swedish Philatelic Association",
            "HedL Boys' Club",
            "U.D."
        ],
        "hobbies": [
            "Sports",
            "Outdoor activities",
            "Shooting",
            "Philately",
            "Antiques",
            "Traveling",
            "Music and singing",
            "Art",
            "Books"
        ]
    },
    "occupations": {
        "career": [
            {
                "occupational_title": "Factory Worker",
                "workplace": "Father's paper trading and printing business",
                "industry": "Paper Trading and Printing",
                "start_date": "1898"
            },
            {
                "occupational_title": "Bookseller",
                "workplace": "Own bookshop in Vingåker",
                "industry": "Bookselling",
                "start_date": "1906"
            },
            {
                "occupational_title": "Managing Director",
                "workplace": "Real estate company",
                "industry": "Real Estate",
                "start_date": "N/A"
            }
        ]
    }
}