{
    "original": "MOSSBERG, Karl Wilhelm Robert, Civilingenjör, Direktör, Norrköping, f Gävle 12/10 94 av brandch R M o Esther Bengtsson, gm Ann Mari Klaening. Studex 13, KTH (v öv) 17. Anst AB Vatt.byggn.byrån 18—19, 1. ass KTH:s byggn.stat avd 19—26, e. ing Sthlm stads byggn.nmd 20—26, byggm.rättigheter 25, egen konsult verksamhet Sthlm 26—33, h Nrkp stadshyp.frn sed. 34, Nrkp bostadskred.frn sed. 37, vik lekt v Nrkp tekn elem.sk, 26, lär v flera byggmästarekurser, sakk v olika utredn åt riksd rev. Stdflm Sthlm 27—31, led kyrkoråd o kyrkonmd samt fi komm nmdr o styr i Sthlm 25—33. Styr.led Nrkp bostads-kred.frn, Ögl ö Istfrb, Nrkp luftv.frn, Nrkp luftsk.frn samt fi idr sam.slutn. Studieres Tyskl, öster, Schweiz o Holl 22, 25, 30. Av trycket: Ett 30-t upps i tekn fråg samt om skidbacksbyggn. Frimurare, Coldin; Landst-SM, Sthlm, Kronob o Ögl ö Istfrbs, Lstoff-sällsk fiksförbs samt Skidfrämj :s SM :er, Riksidrfrbs ftjt g, Sv skidfrbs ftjplak s, idr-o skyt.m g, fi idr.dipl. Hobby: Friluftsliv.",
    "translated": "MOSSBERG, Karl Wilhelm Robert, Civil Engineer, Director, Norrköping, born Gävle 12/10 94, son of fire chief R M and Esther Bengtsson, married to Ann Mari Klaening. Graduated 1913, Royal Institute of Technology (KTH), studies abroad 1917. Employed at AB Vatt.byggn.byrån 1918-1919, 1st assistant at KTH's building statistics department 1919-1926, engineer at Stockholm City Building Committee 1920-1926, obtained building rights in 1925, started own consulting business in Stockholm 1926-1933, became head of Norrköping City Housing Cooperative since 1934, Norrköping Housing Credit Cooperative since 1937, acting lecturer at Norrköping Technical Elementary School 1926, teacher at several master builder courses, expert in various investigations for the parliamentary audit committee, Stockholm 1925-1933, member of church council and church board, as well as municipal committees and boards in Stockholm 1925-1933. Board member of Norrköping Housing Credit Cooperative, Öglö Intensive Forestry Company, Norrköping Air Conditioning Company, Norrköping Air Transport Company, and various sports associations. Studied in Germany, Austria, Switzerland, and the Netherlands in 1922, 1925, and 1930. Published around 30 articles on technical matters and ski slope construction. Freemason, member of Coldin; participated in county championships in cross-country skiing, Stockholm, Kronoberg, and Öglö Intensive Forestry Company, member of Lstoff Society Professional Association and Ski Promotion Association, Swedish Ski Federation Gold Medal, Sports and Shooting Medals, and Sports Diploma. Hobby: Outdoor activities.",
    "structured": {
        "@context": "http://schema.org",
        "@type": "Person",
        "name": "Karl Wilhelm Robert Mossberg",
        "jobTitle": "Civil Engineer, Director",
        "birthDate": "1894-10-12",
        "birthPlace": "Gävle, Sweden",
        "parent": [
            {
                "@type": "Person",
                "name": "R M Mossberg"
            },
            {
                "@type": "Person",
                "name": "Esther Bengtsson"
            }
        ],
        "spouse": {
            "@type": "Person",
            "name": "Ann Mari Klaening"
        },
        "education": {
            "@type": "EducationalOrganization",
            "name": "Royal Institute of Technology (KTH)",
            "location": "Stockholm, Sweden",
            "alumniOf": "KTH",
            "startDate": "1913",
            "endDate": "1917"
        },
        "employment": [
            {
                "@type": "Organization",
                "name": "AB Vatt.byggn.byrån",
                "startDate": "1918",
                "endDate": "1919"
            },
            {
                "@type": "Organization",
                "name": "KTH's Building Statistics Department",
                "startDate": "1919",
                "endDate": "1926",
                "jobTitle": "1st Assistant"
            },
            {
                "@type": "Organization",
                "name": "Stockholm City Building Committee",
                "startDate": "1920",
                "endDate": "1926",
                "jobTitle": "Engineer"
            },
            {
                "@type": "Organization",
                "name": "Own Consulting Business",
                "location": "Stockholm, Sweden",
                "startDate": "1926",
                "endDate": "1933",
                "jobTitle": "Owner"
            },
            {
                "@type": "Organization",
                "name": "Norrköping City Housing Cooperative",
                "location": "Norrköping, Sweden",
                "startDate": "1934"
            },
            {
                "@type": "Organization",
                "name": "Norrköping Housing Credit Cooperative",
                "location": "Norrköping, Sweden",
                "startDate": "1937"
            },
            {
                "@type": "Organization",
                "name": "Norrköping Technical Elementary School",
                "location": "Norrköping, Sweden",
                "startDate": "1926",
                "endDate": "ongoing",
                "jobTitle": "Acting Lecturer"
            }
        ],
        "teaching": {
            "@type": "Organization",
            "name": "Master Builder Courses"
        },
        "expertise": [
            {
                "@type": "Organization",
                "name": "Parliamentary Audit Committee",
                "location": "Stockholm, Sweden",
                "startDate": "1925",
                "endDate": "1933",
                "jobTitle": "Expert Investigator"
            }
        ],
        "membership": [
            {
                "@type": "Organization",
                "name": "Frimurare"
            },
            {
                "@type": "Organization",
                "name": "Coldin"
            },
            {
                "@type": "Organization",
                "name": "Lstoff Society Professional Association"
            },
            {
                "@type": "Organization",
                "name": "Ski Promotion Association"
            },
            {
                "@type": "Organization",
                "name": "Swedish Ski Federation"
            }
        ],
        "awards": [
            {
                "@type": "Medal",
                "name": "County Championships in Cross-Country Skiing"
            },
            {
                "@type": "Medal",
                "name": "Stockholm Medal"
            },
            {
                "@type": "Medal",
                "name": "Kronoberg Medal"
            },
            {
                "@type": "Medal",
                "name": "Öglö Intensive Forestry Company Medal"
            },
            {
                "@type": "Medal",
                "name": "Sports and Shooting Medals"
            },
            {
                "@type": "Diploma",
                "name": "Sports Diploma"
            }
        ],
        "hobbies": [
            "Outdoor activities"
        ]
    },
    "occupations": {
        "career": [
            {
                "occupational_title": "Civil Engineer",
                "workplace": "AB Vatt.byggn.byrån",
                "industry": "Engineering/Construction",
                "start_date": "1918"
            },
            {
                "occupational_title": "1st Assistant",
                "workplace": "KTH's Building Statistics Department",
                "industry": "Education/Research",
                "start_date": "1919"
            },
            {
                "occupational_title": "Engineer",
                "workplace": "Stockholm City Building Committee",
                "industry": "Government/Construction",
                "start_date": "1920"
            },
            {
                "occupational_title": "Owner/Consultant",
                "workplace": "Own consulting business",
                "industry": "Engineering/Construction",
                "start_date": "1926"
            },
            {
                "occupational_title": "Head",
                "workplace": "Norrköping City Housing Cooperative",
                "industry": "Housing",
                "start_date": "1934"
            },
            {
                "occupational_title": "Head",
                "workplace": "Norrköping Housing Credit Cooperative",
                "industry": "Finance/Housing",
                "start_date": "1937"
            },
            {
                "occupational_title": "Acting Lecturer",
                "workplace": "Norrköping Technical Elementary School",
                "industry": "Education",
                "start_date": "1926"
            },
            {
                "occupational_title": "Teacher",
                "workplace": "Several master builder courses",
                "industry": "Education/Construction",
                "start_date": "Unknown"
            }
        ]
    }
}