{
    "original": "HELLSTRÖM, Kristian, Direktör. Stockholm, f Sthlm 24/7 80 av fabr J E H o Anna Stenman, gm Brita Jansson. N LRtin, kommers utb Sthlm. Hamb o Berlin 03—05, London 06—09, Paris 10. Gen.sekr 12 års olymp sp Sthlm. exp.ch Paragonkonc huv.kont Lon d 14, dir dtrbol:s avd,kont Petrogr 15—17, eg imp.fma Sthlm sed. 19, mest eng agrurer. Styr.led i fl idr.org. Resor: Tyskl 03—05, Engl 06—09 o 14. Frankr 10, Ryssl 15—17. Idr.korresp fr Tyskl 04—05. Engl 06—09 RVO, RPrRöO. RFinlVTROIkl, GV:sOlM. Linjr.TubM, SvgifrfbGM, SvcfiGM, Sv idr.frbs Ht (St Grabb), Sv brottn.frbs SM, Sv bandyfrbs st brplak. Sv Finl idr.frbs ftjt, Kristiania idr.-frns Ht mm. Hobbies: Friluftsliv o sportfiske.",
    "translated": "HELLSTRÖM, Kristian, Director. Stockholm, b. Stockholm on July 24, 1880, son of J E H and Anna Stenman, married to Brita Jansson. No higher education in Stockholm. Hamburg and Berlin 1903-1905, London 1906-1909, Paris 1910. General Secretary for 12 years in Olympic Games Stockholm. Export manager at Paragon Concert Hall's main office in London in 1914, director at daughter company's department, Petrograd 1915-1917, owner of own import company in Stockholm since 1919, mainly dealing with English agriculture. Board member in several sports organizations. Travels: Germany 1903-1905, England 1906-1909 and 1914. France 1910, Russia 1915-1917. Correspondent for sports in Germany 1904-1905. England 1906-1909 RVO (Royal Victorian Order), RPrRöO (Royal Prussian Red Eagle Order). RFinlVTROIkl (Order of the White Rose of Finland Commander), GV'sOlM (Gustaf V's Order of Merit Commander). Member of the Swedish Masonry Lodge, Swedish Freight Railway Company's General Manager, Swedish Sports Fishing Guild Master, Swedish Sports Federation for Hunting (Grand Cross), Swedish Wrestling Federation's Swedish Championship, Swedish Bandy Federation's Gold Plaque. Member of the Swedish-Finnish Sports Federation, Kristiania Sports and Recreation Society, etc. Hobbies: Outdoor life and sport fishing.",
    "structured": {
        "@context": "https://schema.org/",
        "@type": "Person",
        "name": "Kristian Hellström",
        "givenName": "Kristian",
        "familyName": "Hellström",
        "birthDate": "1880-07-24",
        "birthPlace": {
            "@type": "Place",
            "address": {
                "@type": "PostalAddress",
                "addressLocality": "Stockholm"
            }
        },
        "parents": [
            {
                "@type": "Person",
                "name": "J E H",
                "familyName": "H"
            },
            {
                "@type": "Person",
                "name": "Anna Stenman"
            }
        ],
        "spouse": {
            "@type": "Person",
            "name": "Brita Jansson"
        },
        "jobTitle": "Director",
        "memberOf": [
            {
                "@type": "Organization",
                "name": "Olympic Games Stockholm",
                "startDate": "1912",
                "endDate": "1924"
            },
            {
                "@type": "Organization",
                "name": "Paragon Concert Hall",
                "jobTitle": "Export Manager",
                "startDate": "1914",
                "location": {
                    "@type": "Place",
                    "address": {
                        "@type": "PostalAddress",
                        "addressLocality": "London"
                    }
                }
            },
            {
                "@type": "Organization",
                "name": "Petrograd"
            },
            {
                "@type": "Organization",
                "name": "Own Import Company",
                "location": {
                    "@type": "Place",
                    "address": {
                        "@type": "PostalAddress",
                        "addressLocality": "Stockholm"
                    }
                },
                "startDate": "1919"
            },
            {
                "@type": "Organization",
                "name": "Swedish Freight Railway Company",
                "jobTitle": "General Manager"
            },
            {
                "@type": "Organization",
                "name": "Swedish Sports Federation for Hunting"
            },
            {
                "@type": "Organization",
                "name": "Swedish Wrestling Federation",
                "jobTitle": "Swedish Championship"
            },
            {
                "@type": "Organization",
                "name": "Swedish Bandy Federation",
                "jobTitle": "Gold Plaque"
            },
            {
                "@type": "Organization",
                "name": "Swedish-Finnish Sports Federation"
            },
            {
                "@type": "Organization",
                "name": "Kristiania Sports and Recreation Society"
            }
        ],
        "education": {
            "@type": "Qualification",
            "location": {
                "@type": "Place",
                "address": {
                    "@type": "PostalAddress",
                    "addressLocality": "Stockholm"
                }
            }
        },
        "hobbies": [
            "Outdoor life",
            "Sport fishing"
        ],
        "hasOccupation": {
            "@type": "Occupation",
            "name": "Director"
        },
        "award": [
            "RVO (Royal Victorian Order)",
            "RPrRöO (Royal Prussian Red Eagle Order)",
            "RFinlVTROIkl (Order of the White Rose of Finland Commander)",
            "GV'sOlM (Gustaf V's Order of Merit Commander)"
        ],
        "traveler": [
            {
                "@type": "Country",
                "name": "Germany",
                "startDate": "1903",
                "endDate": "1905"
            },
            {
                "@type": "Country",
                "name": "England",
                "startDate": "1906",
                "endDate": "1909"
            },
            {
                "@type": "Country",
                "name": "England",
                "startDate": "1914"
            },
            {
                "@type": "Country",
                "name": "France",
                "startDate": "1910"
            },
            {
                "@type": "Country",
                "name": "Russia",
                "startDate": "1915",
                "endDate": "1917"
            }
        ],
        "correspondent": [
            {
                "@type": "Country",
                "name": "Germany",
                "startDate": "1904",
                "endDate": "1905"
            },
            {
                "@type": "Country",
                "name": "England",
                "startDate": "1906",
                "endDate": "1909"
            }
        ]
    },
    "occupations": {
        "career": [
            {
                "occupational_title": "General Secretary",
                "workplace": "Olympic Games Stockholm",
                "industry": "Sports",
                "start_date": "1912"
            },
            {
                "occupational_title": "Export Manager",
                "workplace": "Paragon Concert Hall",
                "industry": "Entertainment",
                "start_date": "1914"
            },
            {
                "occupational_title": "Director",
                "workplace": "Daughter company's department",
                "industry": "Import/Export",
                "start_date": "Unknown"
            },
            {
                "occupational_title": "Owner",
                "workplace": "Own import company",
                "industry": "Import/Export (focus on English agriculture)",
                "start_date": "1919"
            }
        ]
    }
}