{
    "original": "LUNDBERG, Carl Johan Tage, Major, Direktör, Stockholm, f Sthlm 19/5 84 av rekt Carl L o Sophie Follin, gm (2) Ingeborg Sellén. Studex N Latin 03. Offex o uljt Al 05, AIHS 08, RS 10, ljt Sk hus.reg 11, SS 19 mfl sk, ryttm 20, v Livreg drag 21, adjut h kronpr 13, lär v kav stud.skvadr 17, lär o kadettoff KS 19, tjg h hert av Västerb 20—27, ch kav stud.skvadr 25, på övgst 28, major i armén 37. Ass Sthlmsutst 1930 31—32, dir.-ass STAB 31—32, anst Int Bus Mach Corp 34—35, vkst dir dess sv dtrbol sed. 35, hdlsex USA 35, styr.led Sthlms Rotary o Sv-Amer Sällsk, ordf STAB skyt- o idr.frn 31—32, sekr o master Uppl-Västml fältrittkl 18. Resor: Frankr 06, Engl, Frankr årl 20—24 o 27, USA 34—35 o 39, Schweiz, Tyskl, Ital. Red o med-arb Hälsa o friluftsliv 35 mfl sport- o frilufts-tidskr mm. GVisJmt, RSO, RNO, RVO, KSE-O2kl, OffNedONOmsv, arm skytM, idrm g, skytm g, medl Sällsk i Sthlm. Hobbies: Jakt, sportfiske, golf, släktforskn.",
    "translated": "LUNDBERG, Carl Johan Tage, Major, Director, Stockholm, born in Stockholm on May 19, 1884, son of rector Carl L and Sophie Follin, married (2) Ingeborg Sellén. Completed Latin studies in 1903. Officer and lieutenant in the Royal Aland Regiment from 1905, graduated from the Royal Military Academy in 1908, Royal Swedish Army Staff College in 1910, lieutenant in the Swedish House Regiment in 1911, served in the Swedish Signal Corps from 1919, cavalry officer from 1920, served in the Livregimentet till Häst (Life Regiment Horse) from 1921, adjutant to the Crown Prince in 1913, teacher at the Cavalry Training Squadron in 1917, teacher and cadet officer at the Royal Military Academy from 1919, served in the household of the Duke of Västerbotten from 1920 to 1927, cavalry officer at the Cavalry Training Squadron in 1925, on leave of absence in 1928, promoted to Major in the Army in 1937. Assistant at the Stockholm Exhibition in 1930, Director's assistant at STAB from 1931 to 1932, employed by International Business Machines Corporation from 1934 to 1935, appointed Vice Director of its Swedish subsidiary in 1935, also engaged in trade with the United States in 1935. Board member of Stockholm Rotary and the Swedish-American Association, Chairman of STAB shooting and sports clubs from 1931 to 1932, secretary and master of Uppland and Västmanland field riding club in 1918. Traveled to France in 1906, annual visits to England and France between 1920 and 1924 and in 1927, visited the United States in 1934, 1935, and 1939, also traveled to Switzerland, Germany, and Italy. Editor and collaborator of \"Hälsa o friluftsliv\" (Health and Outdoor Life) from 1935 and various sports and outdoor magazines. Member of the Royal Swedish Academy of War Sciences, Royal Order of the Polar Star, King's Medal, Royal Order of Vasa, Knight of the Order of the North Star, Officer of the Royal Norwegian Order of St. Olav, Shooting Medal of the Army, Sports Medal, Shooting Medal, and member of various societies in Stockholm. Hobbies: hunting, sport fishing, golf, genealogy.",
    "structured": {
        "@context": "https://schema.org/",
        "@type": "Person",
        "name": "Carl Johan Tage Lundberg",
        "birthDate": "1884-05-19",
        "birthPlace": "Stockholm",
        "deathDate": null,
        "nationality": "Swedish",
        "jobTitle": [
            "Major",
            "Director"
        ],
        "worksFor": "Stockholm",
        "parents": [
            {
                "@type": "Person",
                "name": "Carl L Lundberg"
            },
            {
                "@type": "Person",
                "name": "Sophie Follin"
            }
        ],
        "spouse": {
            "@type": "Person",
            "name": "Ingeborg Sellén"
        },
        "education": [
            {
                "@type": "EducationalOccupationalCredential",
                "credentialCategory": "Latin studies",
                "dateAwarded": "1903"
            }
        ],
        "affiliation": [
            {
                "@type": "Organization",
                "name": "Royal Aland Regiment",
                "position": "Officer and Lieutenant",
                "startDate": "1905"
            },
            {
                "@type": "Organization",
                "name": "Royal Military Academy",
                "position": "Graduate",
                "startDate": "1908"
            },
            {
                "@type": "Organization",
                "name": "Royal Swedish Army Staff College",
                "position": "Graduate",
                "startDate": "1910"
            },
            {
                "@type": "Organization",
                "name": "Swedish House Regiment",
                "position": "Lieutenant",
                "startDate": "1911"
            },
            {
                "@type": "Organization",
                "name": "Swedish Signal Corps",
                "position": "Lieutenant",
                "startDate": "1919"
            },
            {
                "@type": "Organization",
                "name": "Livregimentet till Häst (Life Regiment Horse)",
                "position": "Lieutenant",
                "startDate": "1921"
            },
            {
                "@type": "Organization",
                "name": "Cavalry Training Squadron",
                "position": "Teacher",
                "startDate": "1917"
            },
            {
                "@type": "Organization",
                "name": "Royal Military Academy",
                "position": "Teacher and Cadet Officer",
                "startDate": "1919"
            },
            {
                "@type": "Organization",
                "name": "Duke of Västerbotten household",
                "position": "Member of staff",
                "startDate": "1920",
                "endDate": "1927"
            },
            {
                "@type": "Organization",
                "name": "Cavalry Training Squadron",
                "position": "Cavalry Officer",
                "startDate": "1925"
            },
            {
                "@type": "Organization",
                "name": "Swedish Army",
                "position": "Major",
                "startDate": "1937"
            },
            {
                "@type": "Organization",
                "name": "Stockholm Exhibition",
                "position": "Assistant",
                "startDate": "1930"
            },
            {
                "@type": "Organization",
                "name": "STAB",
                "position": "Director's Assistant",
                "startDate": "1931",
                "endDate": "1932"
            },
            {
                "@type": "Organization",
                "name": "International Business Machines Corporation",
                "position": "Employee",
                "startDate": "1934",
                "endDate": "1935"
            },
            {
                "@type": "Organization",
                "name": "IBM Swedish subsidiary",
                "position": "Vice Director",
                "startDate": "1935"
            },
            {
                "@type": "Organization",
                "name": "Stockholm Rotary",
                "position": "Board Member"
            },
            {
                "@type": "Organization",
                "name": "Swedish-American Association",
                "position": "Board Member"
            }
        ],
        "memberOf": [
            {
                "@type": "Organization",
                "name": "STAB shooting club",
                "position": "Chairman",
                "startDate": "1931",
                "endDate": "1932"
            },
            {
                "@type": "Organization",
                "name": "STAB sports club",
                "position": "Chairman",
                "startDate": "1931",
                "endDate": "1932"
            },
            {
                "@type": "Organization",
                "name": "Uppland and Västmanland field riding club",
                "position": "Secretary and Master",
                "startDate": "1918"
            }
        ],
        "travelHistory": [
            "France (1906)",
            "England (1920-1924, 1927)",
            "United States (1934, 1935, 1939)",
            "Switzerland",
            "Germany",
            "Italy"
        ],
        "publications": [
            {
                "@type": "PublicationIssue",
                "name": "Hälsa o friluftsliv",
                "startDate": "1935"
            }
        ],
        "awards": [
            "GVisJmt",
            "RSO",
            "RNO",
            "RVO",
            "KSE-O2kl",
            "OffNedONOmsv",
            "arm skytM",
            "idrm g",
            "skytm g"
        ],
        "hobbies": [
            "Hunting",
            "Sport fishing",
            "Golf",
            "Genealogy"
        ]
    },
    "occupations": {
        "career": [
            {
                "occupational_title": "Officer",
                "workplace": "Royal Aland Regiment",
                "industry": "",
                "start_date": "1905"
            },
            {
                "occupational_title": "Lieutenant",
                "workplace": "Royal Aland Regiment",
                "industry": "",
                "start_date": "1905"
            },
            {
                "occupational_title": "Officer",
                "workplace": "Royal Swedish Army Staff College",
                "industry": "",
                "start_date": "1908"
            },
            {
                "occupational_title": "Lieutenant",
                "workplace": "Swedish House Regiment",
                "industry": "",
                "start_date": "1911"
            },
            {
                "occupational_title": "Signal Corps Officer",
                "workplace": "Swedish Signal Corps",
                "industry": "",
                "start_date": "1919"
            },
            {
                "occupational_title": "Cavalry Officer",
                "workplace": "Livregimentet till Häst (Life Regiment Horse)",
                "industry": "",
                "start_date": "1921"
            },
            {
                "occupational_title": "Adjutant",
                "workplace": "Household of the Crown Prince",
                "industry": "",
                "start_date": "1913"
            },
            {
                "occupational_title": "Teacher",
                "workplace": "Cavalry Training Squadron",
                "industry": "",
                "start_date": "1917"
            },
            {
                "occupational_title": "Teacher",
                "workplace": "Royal Military Academy",
                "industry": "",
                "start_date": "1919"
            },
            {
                "occupational_title": "Cadet Officer",
                "workplace": "Royal Military Academy",
                "industry": "",
                "start_date": "1919"
            },
            {
                "occupational_title": "Household Officer",
                "workplace": "Household of the Duke of Västerbotten",
                "industry": "",
                "start_date": "1920"
            },
            {
                "occupational_title": "Cavalry Officer",
                "workplace": "Cavalry Training Squadron",
                "industry": "",
                "start_date": "1925"
            },
            {
                "occupational_title": "Assistant",
                "workplace": "Stockholm Exhibition",
                "industry": "",
                "start_date": "1930"
            },
            {
                "occupational_title": "Director's Assistant",
                "workplace": "STAB",
                "industry": "",
                "start_date": "1931"
            },
            {
                "occupational_title": "Employee",
                "workplace": "International Business Machines Corporation",
                "industry": "",
                "start_date": "1934"
            },
            {
                "occupational_title": "Vice Director",
                "workplace": "International Business Machines Corporation (Swedish subsidiary)",
                "industry": "",
                "start_date": "1935"
            }
        ]
    }
}