{
    "original": "GIDLUND, Tycko Alexander, Direktör, Örnsköldsvik, f By viken, Gideå, 11/1 97 av hem.-ägare P O G o Augusta Edlund. Bilförsälj fma Johan Norberg, övik, 24—26 AB öviks Bilcentral 26, deläg o v. dir 32, eg fma AB Gidlunds Bilaffär, övik, sed. 39, vkst dir där. Fman inköpte 39 G :s fastigh Järnvägsgat 6. Ordf M. H. F:s lokalavd övik, styr.led Å. M. K, Sollefteå, öviks Motorklb. Resor: Genom Danm 29, Norge 35, 36, 38. Medl Skyttefrn, Skidfrämj, Konstfrn, RK, Motormännens Riks-frb mfl. Hobby: Jakt, spec harjakt.",
    "translated": "GIDLUND, Tycko Alexander, Director, Örnsköldsvik, b. By viken, Gideå, 11/1 1897, son of home owner P O G and Augusta Edlund. Car salesman for Johan Norberg, Örnsköldsvik, 1924-1926, Örnsköldsvik Car Central AB from 1926, co-owner and vice director from 1932, sole proprietor of AB Gidlunds Car Dealership, Örnsköldsvik, since 1939, currently serving as managing director there. The company purchased the Gidlund property at Järnvägsgatan 6 in 1939. Chairman of the Swedish Sea Rescue Society's local branch in Örnsköldsvik and board member of Ångermanland Motor Club, Sollefteå, and Örnsköldsvik's Motor Club. Travels: Through Denmark in 1929, Norway in 1935, 1936, and 1938. Member of the Shooting Society, Ski Promotion Society, Art Society, Royal Club, National Association for Motorists, and others. Hobbies: Hunting, especially hare hunting.",
    "structured": {
        "@context": "https://schema.org",
        "@type": "Person",
        "name": "Tycko Alexander Gidlund",
        "jobTitle": "Director",
        "birthDate": "1897-01-11",
        "birthPlace": {
            "@type": "Place",
            "name": "By viken, Gideå"
        },
        "parents": [
            {
                "@type": "Person",
                "name": "P O G Edlund",
                "jobTitle": "Home Owner"
            },
            {
                "@type": "Person",
                "name": "Augusta Edlund"
            }
        ],
        "worksFor": [
            {
                "@type": "Organization",
                "name": "Johan Norberg"
            },
            {
                "@type": "Organization",
                "name": "Örnsköldsvik Car Central AB",
                "startDate": "1926",
                "endDate": "1939"
            },
            {
                "@type": "Organization",
                "name": "AB Gidlunds Car Dealership",
                "startDate": "1939"
            }
        ],
        "memberOf": [
            {
                "@type": "Organization",
                "name": "Swedish Sea Rescue Society"
            },
            {
                "@type": "Organization",
                "name": "Ångermanland Motor Club",
                "location": "Sollefteå"
            },
            {
                "@type": "Organization",
                "name": "Örnsköldsvik's Motor Club"
            },
            {
                "@type": "Organization",
                "name": "Shooting Society"
            },
            {
                "@type": "Organization",
                "name": "Ski Promotion Society"
            },
            {
                "@type": "Organization",
                "name": "Art Society"
            },
            {
                "@type": "Organization",
                "name": "Royal Club"
            },
            {
                "@type": "Organization",
                "name": "National Association for Motorists"
            }
        ],
        "hobbies": "Hunting, especially hare hunting",
        "travels": [
            {
                "@type": "Place",
                "name": "Denmark"
            },
            {
                "@type": "Place",
                "name": "Norway",
                "startDate": "1935",
                "endDate": "1936"
            },
            {
                "@type": "Place",
                "name": "Norway",
                "startDate": "1938"
            }
        ]
    },
    "occupations": {
        "career": [
            {
                "occupational_title": "Car Salesman",
                "workplace": "Johan Norberg",
                "industry": "Automobile Sales",
                "start_date": "1924"
            },
            {
                "occupational_title": "Co-owner and Vice Director",
                "workplace": "AB Örnsköldsviks Bilcentral",
                "industry": "Automobile Sales",
                "start_date": "1932"
            },
            {
                "occupational_title": "Sole Proprietor",
                "workplace": "AB Gidlunds Bilaffär",
                "industry": "Automobile Sales",
                "start_date": "1939"
            },
            {
                "occupational_title": "Managing Director",
                "workplace": "AB Gidlunds Bilaffär",
                "industry": "Automobile Sales",
                "start_date": "1939"
            }
        ]
    }
}