{
    "original": "CHRISTOFFERSON, Nils Harald, Fabrikör, Vingåker, f Vingåker 4/11 04 av dir V H C o Edith Cederström, gm Elsa Adler. Norrköpings hal, Påhlmans. Tj.m h AB L &amp; P Widengren Vingåker 24—33; deläg Bröd Christofferson Herrklädersfabr, gr 33. Ag fastigh Trollegat 14 o Byhle östergård, Skedevi s:n. V. styr.ordf Vingåkers fastigh.äg.frn, medl municip.flm. Resor: Tyskl, Ital, Finl, Estl, Danm. Odd Fellow. Hobbies: Jakt, fiske, jordbruk.",
    "translated": "CHRISTOFFERSON, Nils Harald, Industrialist, Vingåker, born in Vingåker on November 4, 1904, son of director V.H.C and Edith Cederström, married to Elsa Adler. Educated at Norrköping's Hal, Påhlmans. Worked at AB L&P Widengren in Vingåker from 1924 to 1933; became a partner at Bröd Christofferson Men's Clothing Factory in 1933. Involved in real estate at Trollegatan 14 and Byhle Östergård in Skedevi parish. Chairman of the board of Vingåker's real estate owners' association, and a member of the municipality board. Traveled to Germany, Italy, Finland, Estonia, and Denmark. Member of the Odd Fellow society. Hobbies include hunting, fishing, and farming.",
    "structured": {
        "@context": "https://schema.org",
        "@type": "Person",
        "name": "Nils Harald Christofferson",
        "birthDate": "1904-11-04",
        "birthPlace": "Vingåker",
        "description": "Industrialist",
        "parents": [
            {
                "@type": "Person",
                "name": "V.H.C"
            },
            {
                "@type": "Person",
                "name": "Edith Cederström"
            }
        ],
        "spouse": {
            "@type": "Person",
            "name": "Elsa Adler"
        },
        "education": {
            "@type": "EducationalOrganization",
            "name": "Norrköping's Hal, Påhlmans"
        },
        "worksFor": [
            {
                "@type": "Organization",
                "name": "AB L&P Widengren",
                "startDate": "1924",
                "endDate": "1933"
            },
            {
                "@type": "Organization",
                "name": "Bröd Christofferson Men's Clothing Factory",
                "startDate": "1933"
            }
        ],
        "owns": [
            {
                "@type": "LandmarksOrHistoricalBuildings",
                "name": "Trollegat 14"
            },
            {
                "@type": "LandmarksOrHistoricalBuildings",
                "name": "Byhle östergård"
            }
        ],
        "memberOf": [
            {
                "@type": "Organization",
                "name": "Vingåkers fastighetsägareförening",
                "position": "Chairman of the board"
            },
            {
                "@type": "Organization",
                "name": "Municipality board"
            }
        ],
        "travel": [
            "Germany",
            "Italy",
            "Finland",
            "Estonia",
            "Denmark"
        ],
        "hasOccupation": {
            "@type": "Occupation",
            "name": "Industrialist"
        },
        "hasInterest": [
            "Hunting",
            "Fishing",
            "Farming"
        ]
    },
    "occupations": {
        "career": [
            {
                "occupational_title": "Industrialist",
                "workplace": "AB L&P Widengren",
                "industry": "Textile manufacturing",
                "start_date": "1924"
            },
            {
                "occupational_title": "Partner",
                "workplace": "Bröd Christofferson Men's Clothing Factory",
                "industry": "Textile manufacturing",
                "start_date": "1933"
            }
        ]
    }
}