{
    "original": "NORBERG, Pehr-Gösta, Redaktör, Stockholm, f Gbg 19/11 80 av bankoflm R N o Elvira Svensson, gm Gertrud Binney. Studex Krist 98, stud i Upps, Freiburg, Paris, London o Gbg, fil kand 04. Anst P A Norstedt &amp; Söner Sthlm 09—13, 15—17, hvdred f Gamla o Nya Hemlandet, Chicago, 13—14, förest Sv Hdlsbkns publ.avd 19, red f samma bks publ Index sed. 26 o ch f Sv Hdlsbkns ekon sekrriat Sthlm sed. 37. Styr.led Sv-Amer Nyhetsbyrån, skattm Sv res Förf.frn. Resor: USA 6 ggr 04—35, Västind, Venezuela 04, Madeira, Alger 13, Guatemala, Panama 19, Canada 23. Av trycket: (förf.sign Peter Norden) En brygga över havet (09), Adelie (15), Mina bankaffärer (22) mm. Medl Orfei Drängar, Sv:es Förf.frn, Publ. klubben, Utl Pressfrn, Travel -lers Club mm. Hobbies: Skärgården, musik, folkvisestudium.",
    "translated": "NORBERG, Pehr-Gösta, Editor, Stockholm, born in Gothenburg on November 19, 1880, son of bank official R N and Elvira Svensson, married to Gertrud Binney. Graduated from Kristianstad School in 1898, studied in Uppsala, Freiburg, Paris, London, and Gothenburg, and obtained a Bachelor of Arts degree in 1904. Employed at P A Norstedt & Sons in Stockholm from 1909 to 1913, and again from 1915 to 1917, served as head of the publishing departments of the newspapers Gamla and Nya Hemlandet in Chicago from 1913 to 1914, became the director of the publishing division of the Swedish Trade Bank in 1919, and served as editor of the same bank's publication Index since 1926 and secretary of the bank's economic secretariat in Stockholm since 1937. Member of the board of the Swedish-American News Agency, treasurer of the Swedish Authors' Association, member of the Publishing Club, International Press Association, and the Travelers' Club, among others. Travelled to the USA 6 times from 1904 to 1935, visited the West Indies, Venezuela in 1904, Madeira, Algeria in 1913, Guatemala, Panama in 1919, and Canada in 1923. Published works include: \"En brygga över havet\" (09) [A Bridge Across the Sea], \"Adelie\" (15), \"Mina bankaffärer\" (22) [My Banking Affairs], and more. Member of the Orfei Drängar choir, the Swedish Authors' Association, the Publishing Club, the International Press Association, and the Travelers' Club, among others. Hobbies include the archipelago, music, and studying traditional folk songs.",
    "structured": {
        "@context": "https://schema.org",
        "@type": "Person",
        "name": "Pehr-Gösta Norberg",
        "jobTitle": [
            {
                "@type": "Role",
                "name": "Head of Publishing Department",
                "startDate": "1913",
                "endDate": "1914",
                "memberOf": {
                    "@type": "Organization",
                    "name": "Gamla and Nya Hemlandet"
                }
            },
            {
                "@type": "Role",
                "name": "Director of Publishing Division",
                "startDate": "1919",
                "memberOf": {
                    "@type": "Organization",
                    "name": "Swedish Trade Bank"
                }
            },
            {
                "@type": "Role",
                "name": "Editor",
                "startDate": "1926",
                "memberOf": {
                    "@type": "Organization",
                    "name": "Swedish Trade Bank"
                }
            },
            {
                "@type": "Role",
                "name": "Secretary of Economic Secretariat",
                "startDate": "1937",
                "memberOf": {
                    "@type": "Organization",
                    "name": "Swedish Trade Bank"
                }
            }
        ],
        "birthDate": "1880-11-19",
        "birthPlace": "Gothenburg",
        "parent": {
            "@type": "Person",
            "name": "R N Norberg",
            "jobTitle": "Bank Official"
        },
        "parent2": {
            "@type": "Person",
            "name": "Elvira Svensson"
        },
        "spouse": {
            "@type": "Person",
            "name": "Gertrud Binney"
        },
        "education": {
            "@type": "EducationalOccupationalCredential",
            "degreeName": "Bachelor of Arts",
            "alumniOf": [
                {
                    "@type": "HighSchool",
                    "name": "Kristianstad School",
                    "endDate": "1898"
                },
                {
                    "@type": "CollegeOrUniversity",
                    "name": "Uppsala University"
                },
                {
                    "@type": "CollegeOrUniversity",
                    "name": "University of Freiburg"
                },
                {
                    "@type": "CollegeOrUniversity",
                    "name": "University of Paris"
                },
                {
                    "@type": "CollegeOrUniversity",
                    "name": "University of London"
                },
                {
                    "@type": "CollegeOrUniversity",
                    "name": "University of Gothenburg"
                }
            ],
            "startDate": "1898",
            "endDate": "1904"
        },
        "worksFor": [
            {
                "@type": "Organization",
                "name": "P A Norstedt & Sons",
                "startDate": "1909",
                "endDate": "1913"
            },
            {
                "@type": "Organization",
                "name": "P A Norstedt & Sons",
                "startDate": "1915",
                "endDate": "1917"
            },
            {
                "@type": "Organization",
                "name": "Swedish Trade Bank",
                "startDate": "1919"
            }
        ],
        "memberOf": [
            {
                "@type": "Organization",
                "name": "Swedish-American News Agency",
                "roleName": "Board Member"
            },
            {
                "@type": "Organization",
                "name": "Swedish Authors' Association",
                "roleName": "Treasurer"
            },
            {
                "@type": "Organization",
                "name": "Publishing Club"
            },
            {
                "@type": "Organization",
                "name": "International Press Association"
            },
            {
                "@type": "Organization",
                "name": "Travelers' Club"
            }
        ],
        "hobbies": [
            "Archipelago",
            "Music",
            "Traditional Folk Song Study"
        ],
        "hasOccupation": [
            "Editor",
            "Author"
        ],
        "nationality": "Swedish",
        "address": {
            "@type": "PostalAddress",
            "addressLocality": "Stockholm"
        },
        "travel": [
            {
                "countryName": "USA",
                "startDate": "1904",
                "endDate": "1935",
                "numberOfTravels": 6
            },
            {
                "countryName": "West Indies"
            },
            {
                "countryName": "Venezuela",
                "startDate": "1904"
            },
            {
                "countryName": "Madeira",
                "startDate": "1913"
            },
            {
                "countryName": "Algeria",
                "startDate": "1913"
            },
            {
                "countryName": "Guatemala",
                "startDate": "1919"
            },
            {
                "countryName": "Panama",
                "startDate": "1919"
            },
            {
                "countryName": "Canada",
                "startDate": "1923"
            }
        ],
        "publications": [
            {
                "@type": "Book",
                "name": "En brygga över havet",
                "publicationDate": "1909"
            },
            {
                "@type": "Book",
                "name": "Adelie",
                "publicationDate": "1915"
            },
            {
                "@type": "Book",
                "name": "Mina bankaffärer",
                "publicationDate": "1922"
            }
        ]
    },
    "occupations": {
        "career": [
            {
                "occupational_title": "Editor",
                "workplace": "P A Norstedt & Sons",
                "industry": "Publishing",
                "start_date": "1909"
            },
            {
                "occupational_title": "Head of Publishing",
                "workplace": "Gamla and Nya Hemlandet newspapers",
                "industry": "Publishing",
                "start_date": "1913"
            },
            {
                "occupational_title": "Director of Publishing",
                "workplace": "Swedish Trade Bank",
                "industry": "Banking",
                "start_date": "1919"
            },
            {
                "occupational_title": "Editor",
                "workplace": "Swedish Trade Bank - Publication Index",
                "industry": "Banking",
                "start_date": "1926"
            },
            {
                "occupational_title": "Secretary",
                "workplace": "Swedish Trade Bank - Economic Secretariat",
                "industry": "Banking",
                "start_date": "1937"
            }
        ]
    }
}