{
    "original": "BJÖRNBERG, Tor Karl Emanuel, Bankdirektör, Oskarshamn, f Misterhult, Kalm län, 17/4 92 av Carl Gustaf Björnberg o Charlotta K Olsson, gm Karin Lundin. Realex, bk-kurs. Anst Smal ensk bk 09, kass 17, kamrer 24, ch avd.kont Oskarsh 25, vkst dir Oskarsh sparbk sed. 30, v. styr.ordf sed. 38. Land-st.m, ordf polisnmdn, v .ordf stdfm o dräts.kamm, kyrkofm, överförmynd mm, v. styr.ordf Oskarsh.-Tidn, Smal o Ölands sparbks-frn, styr.led Sv sparbk garantikassa, styr.-suppl Sv spafbksfrn, vkst dir Kalm l:s naell brandstodsbol. Av trycket: Kalm läns mell brandstodsbol 1889—1939.",
    "translated": "BJÖRNBERG, Tor Karl Emanuel, Bank Director, Oskarshamn, formerly of Misterhult, Kalmar County, born on April 17, 1892 to Carl Gustaf Björnberg and Charlotta K Olsson. Married to Karin Lundin. Completed his education at a business school. Employed at Smal Enskilda Bank in 1909, served as cashier in 1917, became treasurer in 1924, head of department at Oskarshamn in 1925, appointed deputy managing director of Oskarshamn Savings Bank since 1930, and vice chairman since 1938. Also served as a member of the County Council, chairman of the Police Authority, vice chairman of the Tax Board and Finance Committee, church treasurer, guardian of minors, and vice chairman of the boards of Oskarshamns-Tidningen, Smålands and Ölands Savings Bank Association. Member of the board of directors of the Swedish Savings Bank Guarantee Fund and a board substitute for the Swedish Savings Bank Association. Also holds the position of deputy managing director at Kalmar County Fire Insurance Company. Published a book printing company: Kalmar County Fire Insurance Company 1889-1939.",
    "structured": {
        "@context": "https://schema.org",
        "@type": "Person",
        "name": "Tor Karl Emanuel Björnberg",
        "birthDate": "1892-04-17",
        "birthPlace": "Misterhult, Kalmar County, Sweden",
        "deathDate": "unknown",
        "description": "Bank Director",
        "spouse": {
            "@type": "Person",
            "name": "Karin Lundin"
        },
        "parent": [
            {
                "@type": "Person",
                "name": "Carl Gustaf Björnberg",
                "gender": "male"
            },
            {
                "@type": "Person",
                "name": "Charlotta K Olsson",
                "gender": "female"
            }
        ],
        "education": {
            "@type": "EducationalOccupationalCredential",
            "credentialCategory": "business",
            "degreeName": "Realex"
        },
        "employment": [
            {
                "@type": "Organization",
                "name": "Smal Enskilda Bank",
                "startDate": "1909",
                "endDate": "unknown",
                "title": "Cashier"
            },
            {
                "@type": "Organization",
                "name": "Smal Enskilda Bank",
                "startDate": "1917",
                "endDate": "unknown",
                "title": "Treasurer"
            },
            {
                "@type": "Organization",
                "name": "Oskarshamn",
                "startDate": "1925",
                "endDate": "unknown",
                "title": "Head of Department"
            },
            {
                "@type": "Organization",
                "name": "Oskarshamn Savings Bank",
                "startDate": "1930",
                "endDate": "unknown",
                "title": "Deputy Managing Director"
            },
            {
                "@type": "Organization",
                "name": "Oskarshamn Savings Bank",
                "startDate": "1938",
                "endDate": "unknown",
                "title": "Vice Chairman"
            }
        ],
        "memberOf": [
            {
                "@type": "Organization",
                "name": "County Council"
            },
            {
                "@type": "Organization",
                "name": "Police Authority",
                "title": "Chairman"
            },
            {
                "@type": "Organization",
                "name": "Tax Board and Finance Committee",
                "title": "Vice Chairman"
            },
            {
                "@type": "Organization",
                "name": "Church",
                "title": "Treasurer"
            },
            {
                "@type": "Organization",
                "name": "Guardian of Minors"
            },
            {
                "@type": "Organization",
                "name": "Oskarshamns-Tidningen",
                "title": "Board Vice Chairman"
            },
            {
                "@type": "Organization",
                "name": "Smålands and Ölands Savings Bank Association",
                "title": "Board Vice Chairman"
            },
            {
                "@type": "Organization",
                "name": "Swedish Savings Bank Guarantee Fund",
                "title": "Board member"
            },
            {
                "@type": "Organization",
                "name": "Swedish Savings Bank Association",
                "title": "Board Substitute"
            }
        ],
        "worksFor": {
            "@type": "Organization",
            "name": "Kalmar County Fire Insurance Company",
            "startDate": "unknown",
            "endDate": "unknown",
            "title": "Deputy Managing Director"
        },
        "publication": {
            "@type": "Book",
            "name": "Kalmar County Fire Insurance Company 1889-1939",
            "publisher": "unknown",
            "datePublished": "unknown"
        }
    },
    "occupations": {
        "career": [
            {
                "occupational_title": "Cashier",
                "workplace": "Smal Enskilda Bank",
                "industry": "Banking",
                "start_date": "1917"
            },
            {
                "occupational_title": "Treasurer",
                "workplace": "Smal Enskilda Bank",
                "industry": "Banking",
                "start_date": "1924"
            },
            {
                "occupational_title": "Head of Department",
                "workplace": "Oskarshamn",
                "industry": "Banking",
                "start_date": "1925"
            },
            {
                "occupational_title": "Deputy Managing Director",
                "workplace": "Oskarshamn Savings Bank",
                "industry": "Banking",
                "start_date": "1930"
            },
            {
                "occupational_title": "Vice Chairman",
                "workplace": "Oskarshamn Savings Bank",
                "industry": "Banking",
                "start_date": "1938"
            }
        ]
    }
}