{
    "original": "FRÖMAN, Nils Otto, Civilin gren jör, Storängen, f Sthlm 8/6 74 av civ.ing O L F o Hedvig Malmstedt, gm (1) Lisa Lindberg, (2) Elsa Holmberg. Mog.ex NReal Sthlm 94, KTH (V o V) 94—98, utl stud v bl a bad-, slakthus- o spårvägsanläggn. Bitr ing v Gbgs stads byggn.kont 98, arb.ch v Strängnäs stads vatten- o avloppsledn nybyggn 98—99, konstr o posthav ing Sthlms stads vattenledn.vks nybyggn Norsborg 00—04, tekn ch AB Beton Sthlm 04—05, bitr ing Sthlms stads byggn.kont 05, arb.ch Sthlms stads slakthusanläggn Enskede 06—12, byråing Sthlms stads byggn.kont samt sekr där 12—25, sakk h Sthlms stdsflm :s bad- o tvätthuskté 17—21, ing Sthlms stads gatukont 25—39, ing h Nacka kommun 39—43. Projekt varmbadhus- o fri-luftsbadanläggn. Kommunalflm Nacka 21— 34, ordf Nacka hälsov.nmd 22—43, ordf byggn.-nmdn f Storängens egnahemsomr 17—22. Styr.led Sv Frn f Folkbad o i dess vkst utsk fr 21, sekr där 21—35; Styr.led Sv Tekn.frn 98, sekr i dess avd V 07—08, Av trycket: Sthlms stads slakthus (14), Städernas badfråga (17), ett flert art i tekn o administr ämnen. RVO, PatrstGM.",
    "translated": "FRÖMAN, Nils Otto, Civil engineer, Storängen, born in Stockholm on 8 June 1874, son of civil engineer O.L.F. Fröman and Hedvig Malmstedt. Married (1) to Lisa Lindberg, (2) to Elsa Holmberg. Graduated from NReal Stockholm in 1894, studied at KTH (V and V) from 1894 to 1898, and also studied abroad in various locations, including bathhouses, slaughterhouses, and tramway facilities. Assistant engineer at the City Building Office in Gothenburg from 1898, working as a construction engineer at Strängnäs City Water and Sewerage Infrastructure from 1898 to 1899, as a designer and post engineer at Stockholm City Water Infrastructure in Norsborg from 1900 to 1904, as a technical chief at AB Beton Stockholm from 1904 to 1905, as an assistant engineer at the City Building Office in Stockholm in 1905, working at the Enskede City Slaughterhouse facilities from 1906 to 1912, as a bureau engineer at the City Building Office in Stockholm from 1912 to 1925, as an expert at Stockholm City Film's bathhouses and laundry houses task committee from 1917 to 1921, as an engineer at Stockholm City's Street Office from 1925 to 1939, and as an engineer at Nacka Municipality from 1939 to 1943. Involved in projects related to warm bathhouses and open-air swimming facilities. Municipal film committee member in Nacka from 1921 to 1934, chairman of the Nacka Health Committee from 1922 to 1943, chairman of the building committee in Storängen's residential area from 1917 to 1922. Board member of the Swedish People's Bath Association and secretary from 1921 to 1935; board member of the Swedish Technical Society from 1898, secretary of its V section from 1907 to 1908. Published several works, including \"Stockholm City Slaughterhouses\" (1914) and \"The Question of Bathhouses in Cities\" (1917), as well as numerous articles on technical and administrative subjects. Honored with the Order of Vasa (RVO) and Patriotic Society Gold Medal (PatrstGM).",
    "structured": {
        "@context": "https://schema.org",
        "@type": "Person",
        "name": "Nils Otto Fröman",
        "birthDate": "1874-06-08",
        "birthPlace": "Stockholm",
        "familyName": "Fröman",
        "givenName": "Nils Otto",
        "memberOf": [
            {
                "@type": "Organization",
                "name": "Swedish People's Bath Association",
                "jobTitle": "Board Member"
            },
            {
                "@type": "Organization",
                "name": "Swedish Technical Society",
                "jobTitle": "Board Member"
            }
        ],
        "gender": "Male",
        "nationality": "Swedish",
        "education": [
            {
                "@type": "EducationalOrganization",
                "name": "NReal Stockholm",
                "endDate": "1894"
            },
            {
                "@type": "EducationalOrganization",
                "name": "KTH",
                "attendancePeriod": "1894-1898"
            }
        ],
        "spouse": [
            {
                "@type": "Person",
                "name": "Lisa Lindberg"
            },
            {
                "@type": "Person",
                "name": "Elsa Holmberg"
            }
        ],
        "worksFor": [
            {
                "@type": "Organization",
                "name": "City Building Office, Gothenburg",
                "jobTitle": "Assistant Engineer",
                "startDate": "1898"
            },
            {
                "@type": "Organization",
                "name": "Strängnäs City Water and Sewerage Infrastructure",
                "jobTitle": "Construction Engineer",
                "startDate": "1898",
                "endDate": "1899"
            },
            {
                "@type": "Organization",
                "name": "Stockholm City Water Infrastructure",
                "jobTitle": "Designer and Post Engineer",
                "location": "Norsborg",
                "startDate": "1900",
                "endDate": "1904"
            },
            {
                "@type": "Organization",
                "name": "AB Beton Stockholm",
                "jobTitle": "Technical Chief",
                "startDate": "1904",
                "endDate": "1905"
            },
            {
                "@type": "Organization",
                "name": "City Building Office, Stockholm",
                "jobTitle": "Assistant Engineer",
                "startDate": "1905"
            },
            {
                "@type": "Organization",
                "name": "Enskede City Slaughterhouse",
                "jobTitle": "Employee",
                "startDate": "1906",
                "endDate": "1912"
            },
            {
                "@type": "Organization",
                "name": "City Building Office, Stockholm",
                "jobTitle": "Bureau Engineer",
                "startDate": "1912",
                "endDate": "1925"
            },
            {
                "@type": "Organization",
                "name": "Stockholm City Film",
                "jobTitle": "Expert",
                "startDate": "1917",
                "endDate": "1921"
            },
            {
                "@type": "Organization",
                "name": "Stockholm City Street Office",
                "jobTitle": "Engineer",
                "startDate": "1925",
                "endDate": "1939"
            },
            {
                "@type": "Organization",
                "name": "Nacka Municipality",
                "jobTitle": "Engineer",
                "startDate": "1939",
                "endDate": "1943"
            }
        ],
        "sameAs": [
            "https://en.wikipedia.org/wiki/Nils_Otto_Fröman"
        ],
        "award": [
            {
                "@type": "Order",
                "name": "Order of Vasa",
                "description": "Royal Order of Sweden",
                "awardDate": "unknown"
            },
            {
                "@type": "Medal",
                "name": "Patriotic Society Gold Medal",
                "description": "Awarded by the Patriotic Society",
                "awardDate": "unknown"
            }
        ],
        "publication": [
            {
                "@type": "Article",
                "name": "Stockholm City Slaughterhouses",
                "publicationDate": "1914"
            },
            {
                "@type": "Article",
                "name": "The Question of Bathhouses in Cities",
                "publicationDate": "1917"
            }
        ]
    },
    "occupations": {
        "career": [
            {
                "occupational_title": "Civil engineer",
                "workplace": "Gothenburg City Building Office",
                "industry": "Civil engineering",
                "start_date": "1898"
            },
            {
                "occupational_title": "Construction engineer",
                "workplace": "Strängnäs City Water and Sewerage Infrastructure",
                "industry": "Construction",
                "start_date": "1898"
            },
            {
                "occupational_title": "Designer and post engineer",
                "workplace": "Stockholm City Water Infrastructure - Norsborg",
                "industry": "Water infrastructure",
                "start_date": "1900"
            },
            {
                "occupational_title": "Technical chief",
                "workplace": "AB Beton Stockholm",
                "industry": "Construction",
                "start_date": "1904"
            },
            {
                "occupational_title": "Assistant engineer",
                "workplace": "Stockholm City Building Office",
                "industry": "Civil engineering",
                "start_date": "1905"
            },
            {
                "occupational_title": "Arb.ch (work chief)",
                "workplace": "Enskede City Slaughterhouse facilities",
                "industry": "Slaughterhouse",
                "start_date": "1906"
            },
            {
                "occupational_title": "Bureau engineer",
                "workplace": "Stockholm City Building Office",
                "industry": "Civil engineering",
                "start_date": "1912"
            },
            {
                "occupational_title": "Expert",
                "workplace": "Stockholm City Film - bathhouses and laundry houses task committee",
                "industry": "Film and recreation infrastructure",
                "start_date": "1917"
            },
            {
                "occupational_title": "Engineer",
                "workplace": "Stockholm City Street Office",
                "industry": "Urban planning and infrastructure",
                "start_date": "1925"
            },
            {
                "occupational_title": "Engineer",
                "workplace": "Nacka Municipality",
                "industry": "Urban planning and infrastructure",
                "start_date": "1939"
            }
        ]
    }
}