{
    "original": "LAGERMAN, Torsten, Direktör, Stockholm, f 18/9 00 av major K V L o Märta Ärnström, gm Märta Claréus. Studex NReal 19, HHS 21, fil kand StHS 23, kansliex 24. Anst AB Åtvidab ind 24—35, vkst dir AB Facit 31—35, v. dir AB Volvo 35—39, vkst dlr AB Rosengren» kassask.fabr Gbg 41—42, start spec.fma i stål-inredn o kassaskåp Sthlm 42. Styr.led AB Result Sthlm. Kommun.flm Åtvidab 33—35. Resor: Samtl europ länd, USA, Central- o Sydamer 24—38. Hobbies: Flygning (certif 37), golf.",
    "translated": "LAGERMAN, Torsten, Director, Stockholm, b. September 18, 1900, son of Major K V L and Märta Ärnström, m. Märta Claréus. Graduated from NReal in 1919, HHS in 1921, obtained a Bachelor of Arts degree from StHS in 1923, and completed the kansliex in 1924. Employed at AB Åtvidab industries from 1924 to 1935, vice director at AB Facit from 1931 to 1935, vice director at AB Volvo from 1935 to 1939, vice director at AB Rosengren safe factory in Gothenburg from 1941 to 1942, and started a specialized company for steel interior fittings and safes in Stockholm in 1942. Board member of AB Result in Stockholm. Municipal film commissioner for Åtvidab from 1933 to 1935. Travelled extensively through European countries, the United States, and Central and South America from 1924 to 1938. Hobbies include flying (certified in 1937) and golf.",
    "structured": {
        "@context": "https://schema.org",
        "@type": "Person",
        "name": "Torsten Lagerman",
        "jobTitle": "Director",
        "birthDate": "1900-09-18",
        "father": {
            "@type": "Person",
            "name": "Major K V L"
        },
        "mother": {
            "@type": "Person",
            "name": "Märta Ärnström"
        },
        "spouse": {
            "@type": "Person",
            "name": "Märta Claréus"
        },
        "education": [
            {
                "@type": "EducationalOrganization",
                "name": "NReal",
                "startDate": "1919"
            },
            {
                "@type": "EducationalOrganization",
                "name": "HHS",
                "startDate": "1921"
            },
            {
                "@type": "EducationalOrganization",
                "name": "StHS",
                "degree": "Bachelor of Arts",
                "startDate": "1923"
            }
        ],
        "employmentHistory": [
            {
                "@type": "Organization",
                "name": "AB Åtvidab industries",
                "startDate": "1924",
                "endDate": "1935"
            },
            {
                "@type": "Organization",
                "name": "AB Facit",
                "startDate": "1931",
                "endDate": "1935",
                "jobTitle": "Vice Director"
            },
            {
                "@type": "Organization",
                "name": "AB Volvo",
                "startDate": "1935",
                "endDate": "1939",
                "jobTitle": "Vice Director"
            },
            {
                "@type": "Organization",
                "name": "AB Rosengren safe factory",
                "location": "Gothenburg",
                "startDate": "1941",
                "endDate": "1942",
                "jobTitle": "Vice Director"
            },
            {
                "@type": "Organization",
                "name": "Specialized Steel Interior Fittings and Safes Company",
                "location": "Stockholm",
                "startDate": "1942",
                "jobTitle": "Founder"
            },
            {
                "@type": "Organization",
                "name": "AB Result",
                "location": "Stockholm",
                "jobTitle": "Board Member"
            }
        ],
        "activities": {
            "@type": "Person",
            "name": "Torsten Lagerman",
            "memberOf": {
                "@type": "Organization",
                "name": "Åtvidab Municipal Film Commission"
            },
            "hobbies": [
                "Flying (certified in 1937)",
                "Golf"
            ]
        },
        "travelHistory": {
            "countriesVisited": [
                "European countries",
                "United States",
                "Central America",
                "South America"
            ],
            "startDate": "1924",
            "endDate": "1938"
        }
    },
    "occupations": {
        "career": {
            "occupational_title": [
                "Director",
                "Employed",
                "Vice Director",
                "Vice Director",
                "Vice Director",
                "Started a specialized company"
            ],
            "workplace": [
                "Stockholm",
                "AB Åtvidab industries",
                "AB Facit",
                "AB Volvo",
                "AB Rosengren safe factory",
                "Stockholm"
            ],
            "industry": [
                "Unknown",
                "Industrial",
                "Industrial",
                "Automotive",
                "Safe manufacturing",
                "Steel interior fittings and safes"
            ],
            "start_date": [
                "Unknown",
                "1924",
                "1931",
                "1935",
                "1941",
                "1942"
            ]
        }
    }
}