{
    "original": "EKLUND, Gösta Walter, Direktör, Malmö, f Gbg 31/5 03 av chark.fabr A E o Augusta Andersson, gm Ragnhild Malmström. Realex Gbg 19, ex Gbgs hdlsinst 21, Istljt 43. Kamr h österberg &amp; Bernson ing.byrå Gbg 21—24, repr o förs.ch h D Gestetner AB Sthlm 24—27, deläg sed. 27 i fma N Åberg (kaffeimp o rosteri, grund 1836), ens inneh sed. 33. Ordf Skånefrn 03 års män. Resor: USA 21, Afr, Span 35, Norge 36, Tyskl, Holl, Belg, Frankr 37. Frimurare, PB, Paltgillet i Malmö, Bellevue tenniskl, Skidfrämj, Ind.frn; skyt.m g, pist.skyt.m g, skidl.m. Hobbies: Tennis, ridn, skidor, jakt, Skytte, bridge.",
    "translated": "EKLUND, Gösta Walter, Director, Malmö, b. Gothenburg May 31, 1903, son of butcher factory owner A E and Augusta Andersson, m. Ragnhild Malmström. Attended Gothenburg Real School until 1919, graduated Gothenburg Commercial Institute 1921, Lieutenant 1943. Worked for Österberg &amp; Bernson Engineering Firm in Gothenburg 1921-1924, representative and sales manager for D. Gestetner AB in Stockholm 1924-1927, became co-owner in 1927 of N Åberg (coffee importer and roaster, founded 1836), sole proprietor since 1933. Chairman of the Skåne County Association of the 1903 birth cohort. Traveled to USA in 1921, Africa and Spain in 1935, Norway in 1936, Germany, the Netherlands, Belgium, and France in 1937. Freemason, member of the Police Association, Palt Guild in Malmö, Bellevue Tennis Club, Ski Promoter, Industrial Association; marksman with rifle, pistol marksman, cross-country skier. Hobbies: Tennis, horseback riding, skiing, hunting, marksmanship, bridge.",
    "structured": {
        "@context": "https://schema.org",
        "@type": "Person",
        "name": "Gösta Walter Eklund",
        "jobTitle": "Director",
        "birthPlace": "Gothenburg",
        "birthDate": "1903-05-31",
        "parents": [
            {
                "@type": "Person",
                "name": "A E",
                "jobTitle": "Butcher Factory Owner"
            },
            {
                "@type": "Person",
                "name": "Augusta Andersson"
            }
        ],
        "spouse": {
            "@type": "Person",
            "name": "Ragnhild Malmström"
        },
        "education": [
            {
                "@type": "EducationalOccupationalCredential",
                "credentialCategory": "Realex",
                "credentialSubject": "Gothenburg Real School",
                "alumniOf": "Gothenburg",
                "endDate": "1919"
            },
            {
                "@type": "EducationalOccupationalCredential",
                "credentialSubject": "Gothenburg Commercial Institute",
                "alumniOf": "Gothenburg",
                "endDate": "1921"
            },
            {
                "@type": "EducationalOccupationalCredential",
                "credentialCategory": "Lieutenant",
                "endDate": "1943"
            }
        ],
        "work": [
            {
                "@type": "OrganizationRole",
                "roleName": "Österberg & Bernson Engineering Firm",
                "startDate": "1921",
                "endDate": "1924"
            },
            {
                "@type": "OrganizationRole",
                "roleName": "Representative and Sales Manager",
                "startDate": "1924",
                "endDate": "1927",
                "organization": {
                    "@type": "Organization",
                    "name": "D. Gestetner AB",
                    "location": "Stockholm"
                }
            },
            {
                "@type": "OrganizationRole",
                "roleName": "Co-owner",
                "startDate": "1927",
                "organization": {
                    "@type": "Organization",
                    "name": "N Åberg",
                    "description": "Coffee Importer and Roaster",
                    "foundingDate": "1836"
                }
            },
            {
                "@type": "OrganizationRole",
                "roleName": "Sole Proprietor",
                "startDate": "1933"
            }
        ],
        "memberOf": [
            {
                "@type": "Organization",
                "name": "Skåne County Association of the 1903 Birth Cohort",
                "description": "Chairman"
            },
            {
                "@type": "Organization",
                "name": "Freemasons"
            },
            {
                "@type": "Organization",
                "name": "Police Association"
            },
            {
                "@type": "Organization",
                "name": "Palt Guild in Malmö"
            },
            {
                "@type": "Organization",
                "name": "Bellevue Tennis Club"
            },
            {
                "@type": "Organization",
                "name": "Ski Promoter"
            },
            {
                "@type": "Organization",
                "name": "Industrial Association"
            }
        ],
        "hasOccupation": [
            {
                "@type": "Occupation",
                "name": "Marksman",
                "skill": "Rifle"
            },
            {
                "@type": "Occupation",
                "name": "Marksman",
                "skill": "Pistol"
            },
            {
                "@type": "Occupation",
                "name": "Cross-country Skier"
            }
        ],
        "hasInterest": [
            "Tennis",
            "Horseback Riding",
            "Skiing",
            "Hunting",
            "Marksmanship",
            "Bridge"
        ],
        "sameAs": "https://example.com/goesta-walter-eklund"
    },
    "occupations": {
        "career": [
            {
                "occupational_title": "Director",
                "workplace": "Malmö",
                "industry": "Unknown",
                "start_date": "Unknown"
            },
            {
                "occupational_title": "Representative and Sales Manager",
                "workplace": "D. Gestetner AB",
                "industry": "Office Equipment",
                "start_date": "1924"
            },
            {
                "occupational_title": "Co-owner",
                "workplace": "N Åberg",
                "industry": "Coffee Import and Roasting",
                "start_date": "1927"
            }
        ]
    }
}