{
    "original": "RAPP, Johan David, Grosshandlare, Stockholm, f Uppsala 26/7 76 av skomak.mäst A R o Lydia Bothell, gm Eva Swartz. Upps hal» Löwenhielms hdlssk, priv studentbetyg i ty o eng språken. Anst imp.fma Carl Em. Dahl Sthlm 95, ag.fma Nicolai Johannsen Sthlm 98, etabl ag.fma David Rapp Sthlm 02, fil Gbg 05, New York 06, Köpenhamn 15 (imp av kol.-varor, exp av pappersmassa o tändstickor, omb f utl försäkr.bol o banker). Mångår ordf Saltsjöbadens idr.frn, styr.led Nord Livför-säkr AB Sthlm 20, v. ordf Sthlms Borgargille 23, styr.suppl frn 76 års män 43. Besökt de fi av Kontinentens länder. RVO; SIF :s GM, KMK:s 25-årsm, Borgargill ftjm; livstidsledl Sv hdlskamr London o New York, KSSS, KMK,. KSAK, Nationalmusei vänner, Sv Linnésällsk,,,Frn Sv Flotta, Smålands gille, 76 års män, KFUM, Sthlms Grosshdlssocietet. Hobbies: Konst, idrott.",
    "translated": "RAPP, Johan David, Merchant, Stockholm, b. Uppsala 26/7 1876, son of shoemaker master A R and Lydia Bothell, m. Eva Swartz. Uppsala's commercial school, private student certificates in German and English. Employed by Carl Em. Dahl in Stockholm in 1895, Nicolai Johannsen in Stockholm in 1898, established his own business in Stockholm in 1902, moved to Gothenburg in 1905, New York in 1906, and Copenhagen in 1915 (import of colonial goods, export of pulp and matches, foreign sales agent for insurance companies and banks). Long-time chairman of Saltsjöbaden's sports club, board member of Nord Life Insurance AB in Stockholm since 1920, vice chairman of Stockholm's Citizens' Guild since 1923, board substitute for the 76 men of the year 1943. Has visited several countries on the continent. Decorated with the Royal Order of Vasa; Swedish Industrial Alliance's Gold Medal, Royal Swedish Automobile Club's 25-year medal, Citizens' Guild's honorary emblem; lifetime member of the Swedish Chamber of Commerce in London and New York, Royal Swedish Yacht Club, Royal Motorboat Club, Royal Swedish Aero Club, Friends of the National Museum, Swedish Linnaeus Society, Swedish Navy's Flotilla, Småland's Guild, 76 Men of the Year, YMCA, Stockholm's Merchants Association. Hobbies: Art, sports.",
    "structured": {
        "@context": "https://schema.org",
        "@type": "Person",
        "name": "Johan David Rapp",
        "givenName": "Johan David",
        "familyName": "Rapp",
        "birthDate": "1876-07-26",
        "birthPlace": "Uppsala, Sweden",
        "description": "Merchant",
        "spouse": {
            "@type": "Person",
            "name": "Eva Swartz"
        },
        "education": {
            "@type": "EducationalOrganization",
            "name": "Uppsala's Commercial School"
        },
        "employment": [
            {
                "@type": "OrganizationRole",
                "startDate": "1895",
                "endDate": "1898",
                "roleName": "Employee",
                "namedPosition": "Carl Em. Dahl",
                "memberOf": {
                    "@type": "Organization",
                    "name": "Stockholm"
                }
            },
            {
                "@type": "OrganizationRole",
                "startDate": "1898",
                "endDate": "1902",
                "roleName": "Employee",
                "namedPosition": "Nicolai Johannsen",
                "memberOf": {
                    "@type": "Organization",
                    "name": "Stockholm"
                }
            },
            {
                "@type": "OrganizationRole",
                "startDate": "1902",
                "endDate": "1905",
                "roleName": "Owner",
                "namedPosition": "David Rapp",
                "memberOf": {
                    "@type": "Organization",
                    "name": "Stockholm"
                }
            },
            {
                "@type": "OrganizationRole",
                "startDate": "1905",
                "endDate": "1906",
                "roleName": "Owner",
                "namedPosition": "David Rapp",
                "memberOf": {
                    "@type": "Organization",
                    "name": "Gothenburg"
                }
            },
            {
                "@type": "OrganizationRole",
                "startDate": "1906",
                "endDate": "1915",
                "roleName": "Owner",
                "namedPosition": "David Rapp",
                "memberOf": {
                    "@type": "Organization",
                    "name": "New York"
                }
            },
            {
                "@type": "OrganizationRole",
                "startDate": "1915",
                "endDate": null,
                "roleName": "Owner",
                "namedPosition": "David Rapp",
                "memberOf": {
                    "@type": "Organization",
                    "name": "Copenhagen"
                }
            }
        ],
        "memberOf": [
            {
                "@type": "Organization",
                "name": "Saltsjöbaden's Sports Club",
                "roleName": "Chairman"
            },
            {
                "@type": "Organization",
                "name": "Nord Life Insurance AB",
                "roleName": "Board Member",
                "startDate": "1920"
            },
            {
                "@type": "Organization",
                "name": "Stockholm's Citizens' Guild",
                "roleName": "Vice Chairman",
                "startDate": "1923"
            },
            {
                "@type": "Organization",
                "name": "76 Men of the Year",
                "roleName": "Board Substitute",
                "startDate": "1943"
            }
        ],
        "nationality": "Swedish",
        "award": {
            "@type": "Badge",
            "name": "Citizens' Guild's Honorary Emblem"
        },
        "honorificSuffix": [
            "Lifetime Member of the Swedish Chamber of Commerce in London and New York",
            "Royal Swedish Yacht Club",
            "Royal Motorboat Club",
            "Royal Swedish Aero Club",
            "Friends of the National Museum",
            "Swedish Linnaeus Society",
            "Swedish Navy's Flotilla",
            "Småland's Guild",
            "76 Men of the Year",
            "YMCA",
            "Stockholm's Merchants Association"
        ],
        "knowsAbout": [
            "Art",
            "Sports"
        ]
    },
    "occupations": {
        "career": [
            {
                "occupational_title": "Employed",
                "workplace": "Carl Em. Dahl",
                "industry": "Import/Export",
                "start_date": "1895"
            },
            {
                "occupational_title": "Employed",
                "workplace": "Nicolai Johannsen",
                "industry": "Import/Export",
                "start_date": "1898"
            },
            {
                "occupational_title": "Established own business",
                "workplace": "David Rapp",
                "industry": "Import/Export",
                "start_date": "1902"
            },
            {
                "occupational_title": "Established own business",
                "workplace": "David Rapp",
                "industry": "Import/Export",
                "start_date": "1905"
            },
            {
                "occupational_title": "Established own business",
                "workplace": "David Rapp",
                "industry": "Import/Export",
                "start_date": "1906"
            },
            {
                "occupational_title": "Established own business",
                "workplace": "David Rapp",
                "industry": "Import/Export",
                "start_date": "1915"
            }
        ]
    }
}