{
    "original": "HALL, Gösta Arvid, Civilingenjör, Direktör, Stockholm, f Sundsvall 15/3 99 av fond-mäkl S A H o Laura Carlson, gm Elsa Olin. Studex Sthlm 17, KTH (kemi) 17—21, studieresa t USA 25 o Frankr 30. Anst v Scandi-navian Pulp Agency Inc i Sthlm 23, utförde spec.undersökn betr cellulosa o papper v Stat Provn.anst f sv statens o sv finpappersbrukens räkning 24—25, ch.kemist v Albemarle Paper Mfg Co i Richmond Va USA 26—27, ing v Korsnäs Sågverks AB :s cellulosafabriker 28—30, övering o tekn rådgiv inom Sv Cellulosa AB:s försäljn.org 30—32, led f den sv o finska sulfatcellulosaind:s propagandalab f Europa i Paris 34—37, tekn rådgivare v Sv Cellulosa AB:s försäljningsavdelning i Sthlm sed. 37. Ordf i kommittén f standardisering av cellulosaprovningsmetoder 28^^—32. Ledamot av Sv ind.deleg t USA 44. Styr.led i Sv Ing.sällsk i Frankr 35. Led Sv Tekn.frn. Av trycket: Permance of paper (26), Några erfa-renh betr fiberkaraktärens o målningens inflytande på hållfasthetsegenskaperna h papper (28), Identification and evaluation of un-bleached chemical wood pulps (29), Quelques innovations techniques importantes dans 1’in-dustrie suédoise de cellulose (30), The Swe-dish Pulp Companys new sulphate pulp mill ät östrand (32), Tiber dje Erzeugung von schweren Kraftpapieren fiir Wellpappkisten (34), Un apergu de la fabrication du papier kraft (35) samt upps i in o utl fackpress.",
    "translated": "HALL, Gösta Arvid, Civil Engineer, Director, Stockholm, b. Sundsvall 15/3 99, son of fund broker S A H and Laura Carlson, m. Elsa Olin. Completed studies in Stockholm in 1917, KTH (chemistry) 17-21, study trips to the USA in 1925 and France in 1930. Employed at Scandinavian Pulp Agency Inc in Stockholm from 1923, conducted special investigations on cellulose and paper for the state testing institute for Swedish state and Swedish fine paper factories from 1924-1925, chief chemist at Albemarle Paper Mfg Co in Richmond, VA, USA from 1926-1927, engineer at Korsnäs Sawmills AB's pulp mills from 1928-1930, then head engineer and technical adviser in the sales organization of Sv Cellulosa AB from 1930-1932, member and leader of the Swedish and Finnish sulfate cellulose industry's propaganda laboratory in Europe in Paris from 1934-1937, technical adviser in the sales department of Sv Cellulosa AB in Stockholm since 1937. Chairman of the committee for standardization of cellulose testing methods from 1928-1932. Member of the Swedish industry delegation to the USA in 1944. Board member of the Swedish Engineering Society in France in 1935. Member of the Swedish Technical Association. Published works include: Permance of paper (1926), Some observations on the influence of fiber characteristics and sizing on strength properties of paper (1928), Identification and evaluation of unbleached chemical wood pulps (1929), Some important technical innovations in the Swedish cellulose industry (1930), The Swedish Pulp Company's new sulfate pulp mill at Östrand (1932), Production of heavy kraft papers for corrugated boxes (1934), A glimpse of kraft paper production (1935), as well as articles in domestic and foreign trade press.",
    "structured": {
        "@context": "https://schema.org/",
        "@type": "Person",
        "name": "Gösta Arvid Hall",
        "birthDate": "1899-03-15",
        "birthPlace": "Sundsvall",
        "description": "Civil Engineer, Director",
        "spouse": {
            "@type": "Person",
            "name": "Elsa Olin"
        },
        "parents": [
            {
                "@type": "Person",
                "name": "S A H",
                "jobTitle": "Fund Broker"
            },
            {
                "@type": "Person",
                "name": "Laura Carlson"
            }
        ],
        "education": [
            {
                "@type": "EducationalOrganization",
                "name": "Stockholm",
                "startDate": "1917"
            },
            {
                "@type": "EducationalOrganization",
                "name": "KTH",
                "studyType": "Chemistry",
                "startDate": "1917",
                "endDate": "1921"
            },
            {
                "@type": "Place",
                "name": "USA",
                "startDate": "1925"
            },
            {
                "@type": "Place",
                "name": "France",
                "startDate": "1930"
            }
        ],
        "employmentHistory": [
            {
                "@type": "Organization",
                "name": "Scandinavian Pulp Agency Inc",
                "startDate": "1923",
                "location": "Stockholm"
            },
            {
                "@type": "Organization",
                "name": "State Testing Institute",
                "startDate": "1924",
                "endDate": "1925",
                "description": "Special investigations on cellulose and paper"
            },
            {
                "@type": "Organization",
                "name": "Albemarle Paper Mfg Co",
                "startDate": "1926",
                "endDate": "1927",
                "location": "Richmond, VA, USA",
                "jobTitle": "Chief Chemist"
            },
            {
                "@type": "Organization",
                "name": "Korsnäs Sawmills AB",
                "startDate": "1928",
                "endDate": "1930",
                "jobTitle": "Engineer"
            },
            {
                "@type": "Organization",
                "name": "Sv Cellulosa AB",
                "startDate": "1930",
                "endDate": "1932",
                "jobTitle": "Head Engineer, Technical Adviser"
            },
            {
                "@type": "Organization",
                "name": "Swedish and Finnish sulfate cellulose industry's propaganda laboratory",
                "startDate": "1934",
                "endDate": "1937",
                "description": "Leader"
            },
            {
                "@type": "Organization",
                "name": "Sv Cellulosa AB",
                "startDate": "1937",
                "jobTitle": "Technical Adviser"
            }
        ],
        "memberships": [
            {
                "@type": "Organization",
                "name": "Committee for Standardization of Cellulose Testing Methods",
                "startDate": "1928",
                "endDate": "1932",
                "description": "Chairman"
            },
            {
                "@type": "Organization",
                "name": "Swedish Industry Delegation to the USA",
                "startDate": "1944"
            },
            {
                "@type": "Organization",
                "name": "Swedish Engineering Society in France",
                "startDate": "1935",
                "roleName": "Board Member"
            },
            {
                "@type": "Organization",
                "name": "Swedish Technical Association",
                "roleName": "Member"
            }
        ],
        "publications": [
            {
                "@type": "PublicationEvent",
                "startDate": "1926",
                "location": "Stockholm",
                "workFeatured": {
                    "@type": "CreativeWork",
                    "name": "Permance of Paper"
                }
            },
            {
                "@type": "PublicationEvent",
                "startDate": "1928",
                "location": "Stockholm",
                "workFeatured": {
                    "@type": "CreativeWork",
                    "name": "Some Observations on the Influence of Fiber Characteristics and Sizing on Strength Properties of Paper"
                }
            },
            {
                "@type": "PublicationEvent",
                "startDate": "1929",
                "location": "Stockholm",
                "workFeatured": {
                    "@type": "CreativeWork",
                    "name": "Identification and Evaluation of Unbleached Chemical Wood Pulps"
                }
            },
            {
                "@type": "PublicationEvent",
                "startDate": "1930",
                "location": "Stockholm",
                "workFeatured": {
                    "@type": "CreativeWork",
                    "name": "Some Important Technical Innovations in the Swedish Cellulose Industry"
                }
            },
            {
                "@type": "PublicationEvent",
                "startDate": "1932",
                "location": "Stockholm",
                "workFeatured": {
                    "@type": "CreativeWork",
                    "name": "The Swedish Pulp Company's New Sulfate Pulp Mill at Östrand"
                }
            },
            {
                "@type": "PublicationEvent",
                "startDate": "1934",
                "location": "Stockholm",
                "workFeatured": {
                    "@type": "CreativeWork",
                    "name": "Production of Heavy Kraft Papers for Corrugated Boxes"
                }
            },
            {
                "@type": "PublicationEvent",
                "startDate": "1935",
                "location": "Stockholm",
                "workFeatured": {
                    "@type": "CreativeWork",
                    "name": "A Glimpse of Kraft Paper Production"
                }
            }
        ]
    },
    "occupations": {
        "career": [
            {
                "occupational_title": "Civil Engineer",
                "workplace": "Scandinavian Pulp Agency Inc",
                "industry": "Pulp and Paper",
                "start_date": "1923"
            },
            {
                "occupational_title": "Chief Chemist",
                "workplace": "Albemarle Paper Mfg Co",
                "industry": "Pulp and Paper",
                "start_date": "1926"
            },
            {
                "occupational_title": "Engineer",
                "workplace": "Korsnäs Sawmills AB",
                "industry": "Pulp and Paper",
                "start_date": "1928"
            },
            {
                "occupational_title": "Head Engineer and Technical Adviser",
                "workplace": "Sv Cellulosa AB",
                "industry": "Pulp and Paper",
                "start_date": "1930"
            },
            {
                "occupational_title": "Leader of Propaganda Laboratory",
                "workplace": "Swedish and Finnish Sulfate Cellulose Industry",
                "industry": "Pulp and Paper",
                "start_date": "1934"
            },
            {
                "occupational_title": "Technical Adviser",
                "workplace": "Sv Cellulosa AB",
                "industry": "Pulp and Paper",
                "start_date": "1937"
            }
        ]
    }
}