{
    "original": "LANGE, Axel Mauritz, Direktör, Uddevalla, f Udd 11/12 82 av dir E G L o Hedvig Kafle, gm Elsa Lange. Hal, CTI lägre avd. Med-arb sed. 02 o vkst dir sed. 25 i E G Lange AB (grund 67, fam.AB 19); vkst dir Sv hdls-bkns avd.kont 20—24. Förest Gbgs o Bohusl vedbyrå 15, ch bränslekommiss :s byrå i Gbgs o Bohus l 16—18, ch dess förvaltn i V Sv und avveckl, led hdls- o sjöf.nmdn 17—38, hamnstyr 21—39 (ordf 33—39), stdsflm 27—34, dess beredn.utsk 29—34, hälsov.nmdn 28—38, nuförest krist.styr:s bränslekont i Udd, v. ordf Värml, Dalsl o Bohusl hdlskamm o ordf dess lokalrepr, v. ordf dir f sjöm.h, Frn Udd semesterhem, ordf Udd trafikAB, Udd caféAB, styr.led o huv.m sparbkn, fd v. ordf Udd köp-mfrn fd ordf Bohus sjöass.frn, fd ordf o sekr segelsällsk Viken. RVO, Bohusl Istfrns SM, Sv Istfrbs SJet, Försäkr.AB Norrl :s ftJM, Finl-MannerhM; medl Odd Fellow (ExöM). Hobbies: Motorsport, jakt, segling, fiske.",
    "translated": "LANGE, Axel Mauritz, Director, Uddevalla, b. Udd 11/12 82, son of dir E G L and Hedvig Kafle, m. Elsa Lange. Studied at CTI lower division. Started working as an assistant in 1902 and became a director in 1925 at E G Lange AB (established in 1867, family-owned since 1919); also worked as a director at the Swedish Trade Bank department office from 1920 to 1924. Served as manager of the Gothenburg and Bohus County forestry office in 1915, and the Fuel Commission's office in Gothenburg and Bohus County from 1916 to 1918, as well as its administration in West Sweden until dissolution, member of the Trade and Shipping Committee from 1917 to 1938, Harbor Board from 1921 to 1939 (chairman from 1933 to 1939), City Council from 1927 to 1934, its preparation committee from 1929 to 1934, Health Committee from 1928 to 1938, currently acting as chairman of the Fuel Commission in Udd, vice chairman of the Chamber of Commerce for Värmland, Dalsland, and Bohuslän, and chairman of its local representation, vice chairman of the board of the Maritime School, from Udd vacation home, chairman of Udd Traffic AB, Udd Café AB, board member and main shareholder of the savings bank, former vice chairman of Udd wholesale and retail trade association, former chairman of the Bohus Sea Rescue Association, and former chairman and secretary of the sailing club Viken. Awarded with RVO (Royal Order of Vasa), participated in Bohuslän Ice Skating Championships, Swedish Ice Yachting Championships, and worked for Norrland Insurance Company. Member of the Odd Fellow (Exalted Order Member). Hobbies: Motorsports, hunting, sailing, fishing.",
    "structured": {
        "@context": "https://schema.org",
        "@type": "Person",
        "name": "Axel Mauritz Lange",
        "birthDate": "1882-12-11",
        "birthPlace": "Uddevalla",
        "spouse": "Elsa Lange",
        "parent": [
            {
                "@type": "Person",
                "name": "E G L"
            },
            {
                "@type": "Person",
                "name": "Hedvig Kafle"
            }
        ],
        "occupation": "Director",
        "memberOf": [
            {
                "@type": "Organization",
                "name": "E G Lange AB",
                "foundingDate": "1867",
                "ownershipFundingInfo": "Family-owned since 1919"
            },
            {
                "@type": "Organization",
                "name": "Swedish Trade Bank",
                "department": "Office",
                "startDate": "1920",
                "endDate": "1924"
            },
            {
                "@type": "Organization",
                "name": "Gothenburg and Bohus County Forestry",
                "position": "Manager",
                "startDate": "1915"
            },
            {
                "@type": "Organization",
                "name": "Fuel Commission",
                "position": "Office",
                "startDate": "1916",
                "endDate": "1918"
            },
            {
                "@type": "Organization",
                "name": "Trade and Shipping Committee",
                "startDate": "1917",
                "endDate": "1938"
            },
            {
                "@type": "Organization",
                "name": "Harbor Board",
                "startDate": "1921",
                "endDate": "1939",
                "position": "Chairman"
            },
            {
                "@type": "Organization",
                "name": "City Council",
                "startDate": "1927",
                "endDate": "1934"
            },
            {
                "@type": "Organization",
                "name": "Health Committee",
                "startDate": "1928",
                "endDate": "1938"
            },
            {
                "@type": "Organization",
                "name": "Chamber of Commerce",
                "position": "Vice Chairman",
                "startDate": "Present",
                "memberOf": [
                    {
                        "@type": "Organization",
                        "name": "Chamber of Commerce for Värmland, Dalsland, and Bohuslän",
                        "localRepresentation": true
                    }
                ]
            },
            {
                "@type": "Organization",
                "name": "Maritime School",
                "position": "Board Member"
            },
            {
                "@type": "Organization",
                "name": "Udd Traffic AB",
                "position": "Chairman"
            },
            {
                "@type": "Organization",
                "name": "Udd Café AB"
            },
            {
                "@type": "Organization",
                "name": "Savings Bank",
                "position": "Board Member",
                "mainShareholder": true
            },
            {
                "@type": "Organization",
                "name": "Udd Wholesale and Retail Trade Association",
                "formerPosition": "Vice Chairman"
            },
            {
                "@type": "Organization",
                "name": "Bohus Sea Rescue Association",
                "formerPosition": "Chairman"
            },
            {
                "@type": "Organization",
                "name": "Sailing Club Viken",
                "formerPosition": "Secretary"
            },
            {
                "@type": "Organization",
                "name": "Odd Fellow",
                "position": "Exalted Order Member"
            },
            {
                "@type": "Organization",
                "name": "Norrland Insurance Company",
                "position": "Employee"
            }
        ],
        "awards": [
            {
                "@type": "Order",
                "name": "Royal Order of Vasa"
            },
            {
                "@type": "Championship",
                "name": "Bohuslän Ice Skating Championships"
            },
            {
                "@type": "Championship",
                "name": "Swedish Ice Yachting Championships"
            }
        ],
        "hobbies": [
            "Motorsports",
            "Hunting",
            "Sailing",
            "Fishing"
        ]
    },
    "occupations": {
        "career": [
            {
                "occupational_title": "Assistant",
                "workplace": "E G Lange AB",
                "industry": "Unknown",
                "start_date": "1902"
            },
            {
                "occupational_title": "Director",
                "workplace": "E G Lange AB",
                "industry": "Unknown",
                "start_date": "1925"
            },
            {
                "occupational_title": "Director",
                "workplace": "Swedish Trade Bank",
                "industry": "Financial Services",
                "start_date": "1920"
            },
            {
                "occupational_title": "Manager",
                "workplace": "Gothenburg and Bohus County Forestry Office",
                "industry": "Forestry",
                "start_date": "1915"
            },
            {
                "occupational_title": "Manager",
                "workplace": "Fuel Commission's Office, Gothenburg and Bohus County",
                "industry": "Energy",
                "start_date": "1916"
            },
            {
                "occupational_title": "Administrator",
                "workplace": "Fuel Commission's Office, Gothenburg and Bohus County",
                "industry": "Energy",
                "start_date": "1918"
            },
            {
                "occupational_title": "Member",
                "workplace": "Trade and Shipping Committee",
                "industry": "Government",
                "start_date": "1917"
            },
            {
                "occupational_title": "Member",
                "workplace": "Harbor Board",
                "industry": "Transportation",
                "start_date": "1921"
            },
            {
                "occupational_title": "Member",
                "workplace": "City Council",
                "industry": "Government",
                "start_date": "1927"
            },
            {
                "occupational_title": "Chairman",
                "workplace": "Harbor Board",
                "industry": "Transportation",
                "start_date": "1933"
            },
            {
                "occupational_title": "Chairman",
                "workplace": "City Council",
                "industry": "Government",
                "start_date": "1927"
            },
            {
                "occupational_title": "Chairman",
                "workplace": "Fuel Commission in Udd",
                "industry": "Energy",
                "start_date": "Unknown"
            }
        ]
    }
}