{
    "original": "HELLSTRÖM, Erik Gustaf (Pedro), Civilingenjör, Kapten, Stockholm, f Kkrona 8/8 96 av pastor K G H o Agnes Carlsson, gm Karin Svedberg. Studex NReal Sthlm 16, KTH (V o V) 18—23. Resoffex 18, fänr i Fortif :s res 18, ulöjtn 21, löjtn 26, löjtn VVK 27, kapt 34. Anst v AB Väg- &amp; Husbyggnader Sthlm 24—26, lär v tekn sk Hässleholm 27—28, konstr o försäljning v AB Vägmaskiner Sthlm 28—31, ch f vägtjäreavd v Gas- o Koksverkens Ekon Frn Sthlm 31—35, ch f Sthlmsavd av AB Bergendahl &amp; Höckert Vägbeläggningar sed. 35. Projekt vattenkraftanläggn f staden Neiva i Colombia Sydamer 23—24. Styr.led i AB Krita, Gbg. Led Sv Tekn.frn, styr.led där 38— 40, i avd V 2(5—28, 33—35, 37—39 o fr 44. Av trycket: Vägtjära o tjärbeläggningar (32), Rationella metoder f utför av indränkning o ytbehandl i samb m ombyggn el nybyggn av väg (32), Bidrag t frågan om damm- o korrugeringsfri beläggn på våra grusvägar (33, ny uppl 34), Tjära f vägändamål (Sv Tekn.frns skr Nr 10). Resor: Utom ovanst av Norge, Danm, Holl, Belg, Frankr o Tyskl v öl tillf.",
    "translated": "HELLSTRÖM, Erik Gustaf (Pedro), Civil Engineer, Captain, Stockholm, b. Karlskrona 8/8 1896, son of pastor K G H and Agnes Carlsson, m. Karin Svedberg. Graduated Real Sthlm 1916, KTH (V o V) 1918-1923. Reserve Officer 1918, Second Lieutenant in the Fortification Corps 1918, Lieutenant 1921, Lieutenant VVK 1927, Captain 1934. Employed at AB Väg- & House Construction Sthlm 1924-1926, teacher at technical school Hässleholm 1927-1928, construction and sales at AB Vägmaskiner Sthlm 1928-1931, head of the road tar department at the Gas and Coke Works Economic Association Sthlm 1931-1935, head of the Stockholm department of AB Bergendahl & Höckert Vägbeläggningar since 1935. Project for a hydropower plant in the city of Neiva in Colombia South America 1923-1924. Board member of AB Krita, Gothenburg. Member of the Swedish Technical Association, board member there 1938-1940, in section V 2 (1925-1928, 1933-1935, 1937-1939, and from 1944). Publications: Vägtjära o tjärbeläggningar (1932), Rationella metoder f utför av indränkning o ytbehandl i samb m ombyggn el nybyggn av väg (1932), Bidrag t frågan om damm- o korrugeringsfri beläggning på våra grusvägar (1933, new edition 1934), Tjära f vägändamål (Sv Tekn.frns skr Nr 10). Travels: Besides the mentioned countries, also Norway, Denmark, the Netherlands, Belgium, France, and Germany on different occasions.",
    "structured": {
        "@context": "https://schema.org/",
        "@type": "Person",
        "name": "Erik Gustaf Hellström",
        "alternateName": "Pedro",
        "jobTitle": "Civil Engineer",
        "birthPlace": "Karlskrona, Sweden",
        "birthDate": "1896-08-08",
        "parents": [
            {
                "@type": "Person",
                "name": "K G H",
                "jobTitle": "Pastor"
            },
            {
                "@type": "Person",
                "name": "Agnes Carlsson"
            }
        ],
        "spouse": {
            "@type": "Person",
            "name": "Karin Svedberg"
        },
        "education": [
            {
                "@type": "EducationalOrganization",
                "name": "Real Sthlm",
                "startDate": "1916",
                "endDate": "1916"
            },
            {
                "@type": "EducationalOrganization",
                "name": "KTH",
                "startDate": "1918",
                "endDate": "1923"
            }
        ],
        "worksFor": [
            {
                "@type": "OrganizationRole",
                "roleName": "AB Väg- & House Construction Sthlm",
                "startDate": "1924",
                "endDate": "1926"
            },
            {
                "@type": "OrganizationRole",
                "roleName": "Technical School Hässleholm",
                "startDate": "1927",
                "endDate": "1928"
            },
            {
                "@type": "OrganizationRole",
                "roleName": "AB Vägmaskiner Sthlm",
                "startDate": "1928",
                "endDate": "1931"
            },
            {
                "@type": "OrganizationRole",
                "roleName": "Gas and Coke Works Economic Association Sthlm",
                "startDate": "1931",
                "endDate": "1935"
            },
            {
                "@type": "OrganizationRole",
                "roleName": "AB Bergendahl & Höckert Vägbeläggningar",
                "startDate": "1935"
            }
        ],
        "memberOf": [
            {
                "@type": "Organization",
                "name": "AB Krita",
                "location": "Gothenburg"
            },
            {
                "@type": "Organization",
                "name": "Swedish Technical Association"
            }
        ],
        "familyName": "Hellström",
        "givenName": "Erik Gustaf",
        "gender": "Male",
        "nationality": "Swedish",
        "description": "Captain, Author",
        "hasOccupation": {
            "@type": "Occupation",
            "name": "Captain"
        },
        "hasCredential": [
            {
                "@type": "Credential",
                "name": "Studex"
            },
            {
                "@type": "Credential",
                "name": "Resoffex"
            },
            {
                "@type": "Credential",
                "name": "Fänr",
                "awarder": "Fortification Corps"
            },
            {
                "@type": "Credential",
                "name": "Ulöjtn"
            },
            {
                "@type": "Credential",
                "name": "Löjtn"
            },
            {
                "@type": "Credential",
                "name": "Löjtn VVK"
            },
            {
                "@type": "Credential",
                "name": "Kapt"
            }
        ],
        "hasPublication": [
            {
                "@type": "PublicationEvent",
                "name": "Vägtjära o tjärbeläggningar",
                "startDate": "1932"
            },
            {
                "@type": "PublicationEvent",
                "name": "Rationella metoder f utför av indränkning o ytbehandl i samb m ombyggn el nybyggn av väg",
                "startDate": "1932"
            },
            {
                "@type": "PublicationEvent",
                "name": "Bidrag t frågan om damm- o korrugeringsfri beläggning på våra grusvägar",
                "startDate": "1933",
                "endDate": "1934"
            },
            {
                "@type": "PublicationEvent",
                "name": "Tjära f vägändamål",
                "startDate": "Unknown",
                "location": "Sv Tekn.frns skr Nr 10"
            }
        ],
        "hasTravelExperience": [
            "Norway",
            "Denmark",
            "Netherlands",
            "Belgium",
            "France",
            "Germany"
        ]
    },
    "occupations": {
        "career": [
            {
                "occupational_title": "Civil Engineer",
                "workplace": "AB Väg- & House Construction",
                "industry": "Construction",
                "start_date": "1924"
            },
            {
                "occupational_title": "Teacher",
                "workplace": "Technical School Hässleholm",
                "industry": "Education",
                "start_date": "1927"
            },
            {
                "occupational_title": "Construction and Sales",
                "workplace": "AB Vägmaskiner Sthlm",
                "industry": "Construction",
                "start_date": "1928"
            },
            {
                "occupational_title": "Head of Road Tar Department",
                "workplace": "Gas and Coke Works Economic Association Sthlm",
                "industry": "Energy",
                "start_date": "1931"
            },
            {
                "occupational_title": "Head of Stockholm Department",
                "workplace": "AB Bergendahl & Höckert Vägbeläggningar",
                "industry": "Construction",
                "start_date": "1935"
            }
        ]
    }
}