{
    "original": "MOLIX, Erik Gunnar Nikolaus, överingenjör, Stockholm, f Alnö, Vnorrl l, 30/7 83 av disp A M o Martha Sundström, gm (2) Ingrid Tingström. Ex KTH (kemi) 06. Ing Höga-näs-Billesh AB 06—08, lab.förest AB Saltsjö-ctvarn 08—19, tekn ch fr 19,, v. vkst dir sed. S3. Styr.led AB Saltsjöqv, AB Gefle Valsqv, AB Nykps Storhusqv, Sv kem ind.kont, Frn £3-års män. RVO, Nord cerealkem.frns Ht, LIVA, LLA. °MOr,IN, Carl Erik Olof, Civilingenjör, Hofors, f Björksta, Västml l, 6/5 00 av lantbr JK E A M o Olivia Andersson, gm Marta &amp;andeborg. Studex NReal Sthlm 19, KTH (maskinbyggri o mek tekn) 22—26. Anst v AB Oerh Arehns Mek Verkst i Sthlm 26—27, drifts-ing v STAB i Sv, Belg, Engl, Argentina o Mexico 27—32, spec.stud i organisation o rev.-tekn v HHS 32—33, värderingssakk av utl iföretag v AB Kreuger &amp; Tolls konkursför-valtn 33—34, utexperimenterat, patenterat o exploaterat fabrikationsmetoder f ensk konsortiums räkn 34—35, driftsing h SKF v Hofors Bruk sed. 35. °MOMN, Otto, Grosshandlare, Kristianstad, f Anderslöv 16/4 92. Eft slut skolgång anst Eskilstunaboden Malmö, h Yngve Andrén ’Tomelilla, förest ds Krstfil 18, inneh dna sed. 26 und fma Otto Molin, Järnv, cyklar mm i parti, Krst. Styr.ordf Skåne-Blek stång-järnshandl.frn, styr.led Sv hdlsres.frb :s Hbgs-sekt o Frn Lillöhus, 2 :e v. ordf Frn 92 års män, kass Konstfm Krst. Hobby: Konst.",
    "translated": "MOLIX, Erik Gunnar Nikolaus, chief engineer, Stockholm, born in Alnö, Västernorrland county, on July 30th, 1883, son of assistant pastor A M and Martha Sundström, married (2) Ingrid Tingström. Graduate of the Royal Institute of Technology (chemical engineering) in 1906. Engineer at Höga-näs-Billesh AB from 1906 to 1908, laboratory supervisor at AB Saltsjö-ctvarn from 1908 to 1919, technical director from 1919, vice managing director since 1933. Board member of AB Saltsjöqv, AB Gefle Valsqv, AB Nykps Storhusqv, Swedish chemical industry council. Royal Order of Vasa (RVO), Northern Society for Cereal Chemistry, LIVA (Royal Swedish Academy of Agriculture and Forestry), LLA (Royal Swedish Academy of Letters, History and Antiquities). \nFather: MOR,IN, Carl Erik Olof, civil engineer, Hofors, born in Björksta, Västmanland county, on May 6th, 1900, son of farmer JK E A M and Olivia Andersson, married to Marta Valandeborg. Graduated from NReal Sthlm in 1919, KTH (mechanical engineering and mechanical technology) from 1922 to 1926. Employed by AB Oerh Arehns Mek Verkst in Stockholm from 1926 to 1927, chief engineer at STAB in Sweden, Belgium, England, Argentina, and Mexico from 1927 to 1932, specialized studies in organization and audit techniques at HHS from 1932 to 1933, valuation expert for foreign companies at AB Kreuger & Tolls bankruptcy administration from 1933 to 1934, experimented, patented, and exploited manufacturing methods for Swedish consortium from 1934 to 1935, chief engineer at SKF in Hofors works since 1935. \nMother: MOMN, Otto, merchant, Kristianstad, born in Anderslöv on April 16th, 1892. After completing his education, employed by Eskilstunaboden Malmö, managed by Yngve Andrén in Tomelilla, served as director of Krstfil from 1918, owned since 1926 in partnership with Otto Molin, dealing in iron, bicycles, etc., in Kristianstad. Chairman of Skåne-Blek stång-järnshandl.frn, board member of the Swedish Trade Association's Helsingborg branch and the Frn Lillöhus organization, vice chairman of the Frn 92 year men's association, treasurer of the Krst Art Society. Hobby: Art.",
    "structured": {
        "@context": "http://schema.org",
        "@type": "Person",
        "name": "Erik Gunnar Nikolaus Molix",
        "jobTitle": "Chief Engineer",
        "birthDate": "1883-07-30",
        "birthPlace": {
            "@type": "City",
            "name": "Alnö"
        },
        "nationality": "Swedish",
        "address": {
            "@type": "PostalAddress",
            "addressLocality": "Stockholm"
        },
        "parent": [
            {
                "@type": "Person",
                "name": "A M Molix",
                "jobTitle": "Assistant Pastor"
            },
            {
                "@type": "Person",
                "name": "Martha Sundström"
            }
        ],
        "spouse": [
            {
                "@type": "Person",
                "name": "Ingrid Tingström"
            }
        ],
        "education": {
            "@type": "EducationalOccupationalCredential",
            "credentialCategory": "Chemical Engineering",
            "educationalLevel": "Graduate",
            "educationalProgram": [
                {
                    "@type": "EducationalOccupationalProgram",
                    "name": "Royal Institute of Technology",
                    "startDate": "1906",
                    "endDate": "1906"
                }
            ]
        },
        "work": [
            {
                "@type": "Organization",
                "name": "Höga-näs-Billesh AB",
                "jobTitle": "Engineer",
                "startDate": "1906",
                "endDate": "1908"
            },
            {
                "@type": "Organization",
                "name": "AB Saltsjö-ctvarn",
                "jobTitle": "Laboratory Supervisor",
                "startDate": "1908",
                "endDate": "1919"
            },
            {
                "@type": "Organization",
                "name": "AB Saltsjö-ctvarn",
                "jobTitle": "Technical Director",
                "startDate": "1919"
            },
            {
                "@type": "Organization",
                "name": "SKF",
                "jobTitle": "Chief Engineer",
                "startDate": "1935"
            }
        ],
        "memberOf": [
            {
                "@type": "Organization",
                "name": "AB Saltsjöqv"
            },
            {
                "@type": "Organization",
                "name": "AB Gefle Valsqv"
            },
            {
                "@type": "Organization",
                "name": "AB Nykps Storhusqv"
            },
            {
                "@type": "Organization",
                "name": "Swedish chemical industry council"
            }
        ],
        "awards": [
            {
                "@type": "Order",
                "name": "Royal Order of Vasa (RVO)"
            },
            {
                "@type": "Organization",
                "name": "Northern Society for Cereal Chemistry"
            },
            {
                "@type": "Organization",
                "name": "LIVA (Royal Swedish Academy of Agriculture and Forestry)"
            },
            {
                "@type": "Organization",
                "name": "LLA (Royal Swedish Academy of Letters, History and Antiquities)"
            }
        ],
        "father": {
            "@type": "Person",
            "name": "Carl Erik Olof MOR,IN",
            "jobTitle": "Civil Engineer",
            "birthDate": "1900-05-06",
            "birthPlace": {
                "@type": "City",
                "name": "Björksta"
            },
            "parent": [
                {
                    "@type": "Person",
                    "name": "JK E A M MOR,IN",
                    "jobTitle": "Farmer"
                },
                {
                    "@type": "Person",
                    "name": "Olivia Andersson"
                }
            ],
            "spouse": {
                "@type": "Person",
                "name": "Marta Valandeborg"
            },
            "education": {
                "@type": "EducationalOccupationalCredential",
                "credentialCategory": "Mechanical Engineering",
                "educationalLevel": "Graduate",
                "educationalProgram": [
                    {
                        "@type": "EducationalOccupationalProgram",
                        "name": "NReal Sthlm",
                        "startDate": "1919",
                        "endDate": "1919"
                    },
                    {
                        "@type": "EducationalOccupationalProgram",
                        "name": "KTH",
                        "startDate": "1922",
                        "endDate": "1926"
                    }
                ]
            },
            "work": [
                {
                    "@type": "Organization",
                    "name": "AB Oerh Arehns Mek Verkst",
                    "jobTitle": "Engineer",
                    "startDate": "1926",
                    "endDate": "1927"
                },
                {
                    "@type": "Organization",
                    "name": "STAB",
                    "jobTitle": "Chief Engineer",
                    "startDate": "1927",
                    "endDate": "1932"
                },
                {
                    "@type": "Organization",
                    "name": "HHS",
                    "jobTitle": "Specialized Studies",
                    "startDate": "1932",
                    "endDate": "1933"
                },
                {
                    "@type": "Organization",
                    "name": "AB Kreuger & Tolls",
                    "jobTitle": "Valuation Expert",
                    "startDate": "1933",
                    "endDate": "1934"
                },
                {
                    "@type": "Organization",
                    "name": "Swedish Consortium",
                    "jobTitle": "Chief Engineer",
                    "startDate": "1934",
                    "endDate": "1935"
                },
                {
                    "@type": "Organization",
                    "name": "SKF",
                    "jobTitle": "Chief Engineer",
                    "startDate": "1935"
                }
            ]
        },
        "mother": {
            "@type": "Person",
            "name": "Otto MOMN",
            "jobTitle": "Merchant",
            "birthDate": "1892-04-16",
            "birthPlace": {
                "@type": "City",
                "name": "Anderslöv"
            },
            "education": {
                "@type": "EducationalOccupationalCredential",
                "credentialCategory": "Merchant",
                "educationalLevel": "Graduate"
            },
            "work": [
                {
                    "@type": "Organization",
                    "name": "Eskilstunaboden Malmö"
                },
                {
                    "@type": "Organization",
                    "name": "Krstfil",
                    "jobTitle": "Director",
                    "startDate": "1918"
                },
                {
                    "@type": "Organization",
                    "name": "otto Molin",
                    "jobTitle": "Owner",
                    "startDate": "1926"
                }
            ],
            "memberOf": [
                {
                    "@type": "Organization",
                    "name": "Skåne-Blek stång-järnshandl.frn"
                },
                {
                    "@type": "Organization",
                    "name": "Swedish Trade Association's Helsingborg branch"
                },
                {
                    "@type": "Organization",
                    "name": "Frn Lillöhus"
                },
                {
                    "@type": "Organization",
                    "name": "Frn 92 year men's association"
                },
                {
                    "@type": "Organization",
                    "name": "Krst Art Society"
                }
            ],
            "hobby": "Art"
        }
    },
    "occupations": {
        "career": [
            {
                "occupational_title": "Chief Engineer",
                "workplace": "Höga-näs-Billesh AB",
                "industry": "Engineering",
                "start_date": "1906"
            },
            {
                "occupational_title": "Laboratory Supervisor",
                "workplace": "AB Saltsjö-ctvarn",
                "industry": "Chemical industry",
                "start_date": "1908"
            },
            {
                "occupational_title": "Technical Director",
                "workplace": "AB Saltsjö-ctvarn",
                "industry": "Chemical industry",
                "start_date": "1919"
            },
            {
                "occupational_title": "Vice Managing Director",
                "workplace": "AB Saltsjö-ctvarn",
                "industry": "Chemical industry",
                "start_date": "1933"
            },
            {
                "occupational_title": "Engineer",
                "workplace": "SKF Hofors Bruk",
                "industry": "Engineering",
                "start_date": "1935"
            },
            {
                "occupational_title": "Chief Engineer",
                "workplace": "SKF Hofors Bruk",
                "industry": "Engineering",
                "start_date": "1935"
            },
            {
                "occupational_title": "Merchant",
                "workplace": "Eskilstunaboden Malmö",
                "industry": "Retail",
                "start_date": "1926"
            },
            {
                "occupational_title": "Director",
                "workplace": "Krstfil",
                "industry": "Entertainment",
                "start_date": "1918"
            }
        ]
    }
}