{
    "original": "MALMFORS, Sam Karl, Kraftverks direktör, Falun, f Norberg, Västml l, 20/11 88 av järn-handl J Pettersson o Matilda Andersson, gm Xenia Ohlsson. Studex N Latin 08, civilingex KTH (eltekn) 12. Resoffex 12, uljt 13, ljt 18, avsk 20. Ass KTH o Graham Brothers Sthlm 13—16, ch ry fman Grah Broth, Petrograd, 17, distr.ing Älvkarleby kraftvk 18—20, ing Torpshammars AB 20—22, 1. byråing Vat.f.styr 22— 24, förest dess Norrl.avd 24—29, kraftvksdir o ch Norrl kraftvkn 29—32, dir St Kopparb bergsl kraftvk sed. 32. Ch stat ind.kommiss :s bränsle- o kraftavd 40. Styr.led Sv el.ing.frn, Sv elvksfrn, Sv vat.kr.frn, Dalälvens regl.-föret, Västerdalälvens kraftAB. Resor: Ryssl 17, Frankr, Ital, Schweiz 29, Tyskl 36. Av trycket: Utredn betr planmäss elektrifier av Norrb:s landsbygd (24), fi skrifter rör el kraftdistribution. RVO; Frimurare, S :t ör-jens Gille, Kraftvksklubben. Hobbies: Musik, litteratur.",
    "translated": "MALMFORS, Sam Karl, Power Plant Director, Falun, born in Norberg, Västmanland county, on November 20, 1888, to iron merchant J Pettersson and Matilda Andersson, married to Xenia Ohlsson. Completed secondary school at Latin School in 1908, graduated from the Royal Institute of Technology (KTH) with a degree in electrical engineering in 1912. Commissioned officer in 1912, promoted to second lieutenant in 1913, and lieutenant in 1918. Discharged in 1920. Assistant at KTH and Graham Brothers in Stockholm from 1913 to 1916, chief engineer at Grah Brothers in Petrograd in 1917, district engineer at Älvkarleby power plant from 1918 to 1920, engineer at Torpshammars AB from 1920 to 1922, first engineer at the Water Works Authority from 1922 to 1924, head of the Northern department from 1924 to 1929, power plant director and chief of Northern Power Plants from 1929 to 1932, director of Stora Kopparbergs Bergslagens power plant since 1932. Chairman of the state industrial commissioners fuel and power department in 1940. Board member of the Swedish Association of Electrical Engineers, Swedish Power Plants Association, Swedish Water Authorities, Dalälven Regulation Company, and Västerdalälvens Power AB. Travelled to Russia in 1917, France, Italy, and Switzerland in 1929, and Germany in 1936. Published investigations on systematic electrification of rural areas in Norrbotten (1924) and writings on electric power distribution. Received the Royal Order of Vasa (RVO) and is a member of Freemasons, St. Erik's Guild, and the Power Plant Club. Hobbies include music and literature.",
    "structured": {
        "@context": "https://schema.org",
        "@type": "Person",
        "name": "Sam Karl Malmfors",
        "jobTitle": "Power Plant Director",
        "birthPlace": "Norberg, Västmanland County, Sweden",
        "birthDate": "1888-11-20",
        "spouse": "Xenia Ohlsson",
        "parents": [
            {
                "@type": "Person",
                "name": "J. Pettersson"
            },
            {
                "@type": "Person",
                "name": "Matilda Andersson"
            }
        ],
        "education": [
            {
                "@type": "EducationalOccupationalCredential",
                "credentialCategory": "secondary",
                "alumniOf": {
                    "@type": "EducationalOrganization",
                    "name": "Latin School"
                },
                "endDate": "1908"
            },
            {
                "@type": "EducationalOccupationalCredential",
                "credentialCategory": "degree",
                "alumniOf": {
                    "@type": "EducationalOrganization",
                    "name": "Royal Institute of Technology (KTH)"
                },
                "startDate": "1908",
                "endDate": "1912",
                "course": [
                    {
                        "@type": "Course",
                        "name": "Electrical Engineering",
                        "provider": {
                            "@type": "EducationalOrganization",
                            "name": "Royal Institute of Technology (KTH)"
                        }
                    }
                ]
            }
        ],
        "worksFor": [
            {
                "@type": "Organization",
                "name": "Graham Brothers"
            },
            {
                "@type": "Organization",
                "name": "Älvkarleby Power Plant",
                "startDate": "1918",
                "endDate": "1920"
            },
            {
                "@type": "Organization",
                "name": "Torpshammars AB",
                "startDate": "1920",
                "endDate": "1922"
            },
            {
                "@type": "Organization",
                "name": "Water Works Authority",
                "startDate": "1922",
                "endDate": "1924"
            },
            {
                "@type": "Organization",
                "name": "Stora Kopparbergs Bergslagens Power Plant",
                "startDate": "1932"
            }
        ],
        "memberOf": [
            "Swedish Association of Electrical Engineers",
            "Swedish Power Plants Association",
            "Swedish Water Authorities",
            "Dalälven Regulation Company",
            "Västerdalälvens Power AB",
            "Freemasons",
            "St. Erik's Guild",
            "Power Plant Club"
        ],
        "affiliation": "Stora Kopparbergs Bergslagens Power Plant",
        "awards": "Royal Order of Vasa (RVO)",
        "nationality": "Swedish",
        "description": "Sam Karl Malmfors was a Swedish Power Plant Director, born on November 20, 1888, in Norberg, Västmanland County. He was married to Xenia Ohlsson. Malmfors completed his secondary education at Latin School in 1908 and graduated from the Royal Institute of Technology (KTH) with a degree in Electrical Engineering in 1912. He held various positions including Assistant at KTH and Graham Brothers in Stockholm, Chief Engineer at Grah Brothers in Petrograd, and District Engineer at Älvkarleby Power Plant. Malmfors also worked as an engineer at Torpshammars AB and the Water Works Authority before becoming the Power Plant Director and Chief of Northern Power Plants in 1929. Since 1932, he served as the Director of Stora Kopparbergs Bergslagens Power Plant. Malmfors was actively involved in several organizations such as the Swedish Association of Electrical Engineers, Swedish Power Plants Association, Swedish Water Authorities, Dalälven Regulation Company, Västerdalälvens Power AB, Freemasons, St. Erik's Guild, and the Power Plant Club. He received the Royal Order of Vasa (RVO) for his contributions in the field. Malmfors had a strong interest in music and literature."
    },
    "occupations": {
        "career": [
            {
                "occupational_title": "Assistant",
                "workplace": "KTH",
                "industry": "Higher Education",
                "start_date": "1913"
            },
            {
                "occupational_title": "Assistant",
                "workplace": "Graham Brothers",
                "industry": "Engineering",
                "start_date": "1913"
            },
            {
                "occupational_title": "Chief Engineer",
                "workplace": "Graham Brothers",
                "industry": "Engineering",
                "start_date": "1917"
            },
            {
                "occupational_title": "District Engineer",
                "workplace": "Älvkarleby Power Plant",
                "industry": "Power and Energy",
                "start_date": "1918"
            },
            {
                "occupational_title": "Engineer",
                "workplace": "Torpshammars AB",
                "industry": "Engineering",
                "start_date": "1920"
            },
            {
                "occupational_title": "First Engineer",
                "workplace": "Water Works Authority",
                "industry": "Public Utilities",
                "start_date": "1922"
            },
            {
                "occupational_title": "Head of Northern Department",
                "workplace": "Water Works Authority",
                "industry": "Public Utilities",
                "start_date": "1924"
            },
            {
                "occupational_title": "Power Plant Director",
                "workplace": "Northern Power Plants",
                "industry": "Power and Energy",
                "start_date": "1929"
            },
            {
                "occupational_title": "Director",
                "workplace": "Stora Kopparbergs Bergslagens Power Plant",
                "industry": "Power and Energy",
                "start_date": "1932"
            },
            {
                "occupational_title": "Chairman",
                "workplace": "State Industrial Commissioners",
                "industry": "Government",
                "start_date": "1940"
            }
        ]
    }
}