{
    "original": "JOHANSSON, Artur Gösta, Civilingenjör, Norrköping, f Lyse 28/5 11 av byggm A J o Agda Matson, gm Gunhild Ericsson. Realex Lysekil 28, studex Gbg 31, CTH 35. Anst v Sv Radio AB 36, h Tel.AB L M Ericsson 37, v Arméförvaltn tygdepartem 41, lab- o avd.ch v Nrkps Elektrotekn Fabr AB (NEFA) sed. 42. Resor : Norge, Danm, Tyskl 28—35. Av trycket: »Radiomätteknik» (NKI), ett stort ant radio-tekn art i facktidskr. Led Sv Tekn.frn, Sthlms Radioklb mfl. Hobbies: Filateli, fotografi, sport.",
    "translated": "JOHANSSON, Artur Gösta, MSc, Norrköping, b. Lyse 28/5 11 to builder Mr. A J and Agda Matson. m. Gunhild Ericsson. Graduated from Lysekil School 1928, studied at Gothenburg University 1931, graduated from Chalmers University of Technology 1935. Employed by Swedish Radio AB 1936, then at Tel.AB L M Ericsson 1937, transferred to the Army Central Administration's Department of Textiles 1941, worked as a laboratory and department head at Norrköping Elektrotekniska Fabriks AB (NEFA) from 1942 onwards. Traveled: Norway, Denmark, Germany 1928-1935. Publications: \"Radio Measurement Techniques\" (NKI), numerous radio-technology articles in professional journals. Member of the Swedish Technical Association, Stockholm Radio Club, among others. Hobbies: Philately, photography, sports.",
    "structured": {
        "@context": "https://schema.org",
        "@type": "Person",
        "name": "Artur Gösta Johansson",
        "givenName": "Artur Gösta",
        "familyName": "Johansson",
        "gender": "Male",
        "birthDate": "1911-05-28",
        "birthPlace": "Lyse",
        "description": "MSc, Civilingenjör",
        "nationality": "Swedish",
        "sameAs": "",
        "memberOf": [
            {
                "@type": "Organization",
                "name": "Swedish Technical Association"
            },
            {
                "@type": "Organization",
                "name": "Stockholm Radio Club"
            }
        ],
        "alumniOf": [
            {
                "@type": "EducationalOrganization",
                "name": "Lysekil School",
                "endDate": "1928"
            },
            {
                "@type": "EducationalOrganization",
                "name": "Gothenburg University",
                "startDate": "1931"
            },
            {
                "@type": "EducationalOrganization",
                "name": "Chalmers University of Technology",
                "startDate": "1935"
            }
        ],
        "worksFor": [
            {
                "@type": "Organization",
                "name": "Swedish Radio AB",
                "startDate": "1936",
                "endDate": "1937"
            },
            {
                "@type": "Organization",
                "name": "Tel.AB L M Ericsson",
                "startDate": "1937",
                "endDate": "1941"
            },
            {
                "@type": "Organization",
                "name": "Army Central Administration's Department of Textiles",
                "startDate": "1941"
            },
            {
                "@type": "Organization",
                "name": "Norrköping Elektrotekniska Fabriks AB (NEFA)",
                "startDate": "1942"
            }
        ],
        "spouse": {
            "@type": "Person",
            "name": "Gunhild Ericsson"
        },
        "publication": [
            {
                "@type": "PublicationEvent",
                "name": "Radiomätteknik",
                "startDate": "NKI"
            }
        ],
        "hobbies": [
            "Philately",
            "Photography",
            "Sports"
        ],
        "travelHistory": [
            {
                "@type": "Place",
                "name": "Norway",
                "startDate": "1928",
                "endDate": "1935"
            },
            {
                "@type": "Place",
                "name": "Denmark",
                "startDate": "1928",
                "endDate": "1935"
            },
            {
                "@type": "Place",
                "name": "Germany",
                "startDate": "1928",
                "endDate": "1935"
            }
        ]
    },
    "occupations": {
        "career": [
            {
                "occupational_title": "Civilingenjör",
                "workplace": "Swedish Radio AB",
                "industry": "Radio",
                "start_date": "1936"
            },
            {
                "occupational_title": "v Arméförvaltn tygdepartem",
                "workplace": "Army Central Administration's Department of Textiles",
                "industry": "Textiles",
                "start_date": "1941"
            },
            {
                "occupational_title": "lab- o avd.ch v Nrkps Elektrotekn Fabr AB (NEFA)",
                "workplace": "Norrköping Elektrotekniska Fabriks AB (NEFA)",
                "industry": "Electrotechnology",
                "start_date": "1942"
            }
        ]
    }
}