{
    "original": "ESBJÖRNSSON, Åke, Ingenjör, Bromölla, f Löddeköpinge, Malmöh l, 21/5 83 av ombudsman H E o Elna Åkesdtr, gm Sigrid Andersén. Ex tekn elem.sk Malmö 03, ex Techn Hoch-schule Darmstadt 06. Rit v Skånska Cement AB:s Limhamnförvaltn 06—07 o 08—10, ritkont.ch Sthlms Superfosf.fabr AB Månsbo 10 —15, konstr o fabr.ch v Jungners Kali-Cement Norrkp 15—17, ritkont.ch o tf övering Sthlms Superfosf.fabr AB Ljungaverk 17—21, ing o avd.ch AB Iföverken Bromölla sed. 21. Resor: Tyskl 17, USA 07 o 20, Norge, Danm o Finl 21—40. Av trycket: Upps i Tekn Tidskr o i Uppf Bok. Led Sv Tekn.frn.",
    "translated": "ESBJÖRNSSON, Åke, Engineer, Bromölla, b. Löddeköpinge, Malmöh l, May 21st, 1883, son of trade unionist H E and Elna Åkesdtr, married to Sigrid Andersén. Former student of Technical Elementary School in Malmö 1903, former student of Technical University Darmstadt 1906. Worked as a draftsman at Skånska Cement AB's Limhamn office from 1906 to 1907 and 1908 to 1910. Worked as a drafting clerk at Stockholm Superphosphate Factory AB Månsbo from 1910 to 1915. Engaged in design and fabrication at Jungner's Kali-Cement in Norrköping from 1915 to 1917. Worked as a drafting clerk and temporary supervisor at Stockholm Superphosphate Factory AB Ljungaverk from 1917 to 1921. Engineer and department head at AB Iföverken Bromölla since 1921. Traveled to Germany in 1917, USA in 1907 and 1920, Norway, Denmark, and Finland from 1921 to 1940. Published in Technical Journal and Construction Book. Member of the Swedish Society of Engineers.",
    "structured": {
        "@context": "https://schema.org",
        "@type": "Person",
        "name": "Åke Esbjörnsson",
        "jobTitle": "Engineer",
        "birthDate": "1883-05-21",
        "birthPlace": "Löddeköpinge, Malmöh l",
        "parent": [
            {
                "@type": "Person",
                "name": "H E",
                "jobTitle": "Trade Unionist"
            },
            {
                "@type": "Person",
                "name": "Elna Åkesdtr"
            }
        ],
        "spouse": {
            "@type": "Person",
            "name": "Sigrid Andersén"
        },
        "education": [
            {
                "@type": "EducationalOrganization",
                "name": "Technical Elementary School, Malmö",
                "startDate": "1903"
            },
            {
                "@type": "EducationalOrganization",
                "name": "Technical University Darmstadt",
                "startDate": "1906",
                "endDate": "1906"
            }
        ],
        "work": [
            {
                "@type": "Organization",
                "name": "Skånska Cement AB's Limhamn Office",
                "jobTitle": "Draftsman",
                "startDate": "1906",
                "endDate": "1907"
            },
            {
                "@type": "Organization",
                "name": "Skånska Cement AB's Limhamn Office",
                "jobTitle": "Draftsman",
                "startDate": "1908",
                "endDate": "1910"
            },
            {
                "@type": "Organization",
                "name": "Stockholm Superphosphate Factory AB Månsbo",
                "jobTitle": "Drafting Clerk",
                "startDate": "1910",
                "endDate": "1915"
            },
            {
                "@type": "Organization",
                "name": "Jungner's Kali-Cement, Norrköping",
                "jobTitle": "Design and Fabrication",
                "startDate": "1915",
                "endDate": "1917"
            },
            {
                "@type": "Organization",
                "name": "Stockholm Superphosphate Factory AB Ljungaverk",
                "jobTitle": "Drafting Clerk and Temporary Supervisor",
                "startDate": "1917",
                "endDate": "1921"
            },
            {
                "@type": "Organization",
                "name": "AB Iföverken, Bromölla",
                "jobTitle": "Engineer and Department Head",
                "startDate": "1921"
            }
        ],
        "nationality": "Swedish",
        "memberOf": {
            "@type": "Organization",
            "name": "Swedish Society of Engineers"
        },
        "travelHistory": [
            "Germany (1917)",
            "USA (1907, 1920)",
            "Norway, Denmark, Finland (1921-1940)"
        ],
        "publication": [
            {
                "@type": "Article",
                "name": "Technical Journal"
            },
            {
                "@type": "Article",
                "name": "Construction Book"
            }
        ]
    },
    "occupations": {
        "career": [
            {
                "occupational_title": "Engineer",
                "workplace": "Skånska Cement AB's Limhamn office",
                "industry": "Construction",
                "start_date": "1906"
            },
            {
                "occupational_title": "Draftsman",
                "workplace": "Stockholm Superphosphate Factory AB Månsbo",
                "industry": "Chemical",
                "start_date": "1910"
            },
            {
                "occupational_title": "Design and Fabrication",
                "workplace": "Jungner's Kali-Cement",
                "industry": "Construction",
                "start_date": "1915"
            },
            {
                "occupational_title": "Drafting Clerk",
                "workplace": "Stockholm Superphosphate Factory AB Ljungaverk",
                "industry": "Chemical",
                "start_date": "1917"
            },
            {
                "occupational_title": "Engineer",
                "workplace": "AB Iföverken",
                "industry": "Manufacturing",
                "start_date": "1921"
            }
        ]
    }
}