{
    "original": "BERG, Ernst Daniel, Fabrikör, Hönön, &gt;f Gesäter, Älvsb l, 2/6 92 av soldat O F B o Inga Sofia Tall, gm Gerda Nilsson. Folksk o fortsattn.sk. Anst v varv i Källö-Knipplan 10 —12, v varv i Smögen 12—13, v Skandiaverken i Lysekil 14 o v Bergs Varv i Hälsö 15—25, start Firman Berg &amp; Johansson Slip, Varv &amp; Mek Verkst i Hönö 25, vkst dir eft fmans ombild t AB 44. Led av municipalflm, ordf i byggn.kté, v brandch, v. ordf i arb.lösh.komm. Hobbies: Hemvärn, Skytte.",
    "translated": "BERG, Ernst Daniel, Industrialist, Hönö, born in Gesäter, Älvsborg län, on February 6, 1892, son of soldier O.F.B and Inga Sofia Tall, married to Gerda Nilsson. Attended primary school and continued education. Employed at shipyard in Källö-Knipplan from 1910 to 1912, shipyard in Smögen from 1912 to 1913, Skandiaverken in Lysekil in 1914 and Bergs Varv in Hälsö from 1915 to 1925. Started the company Berg & Johansson Slip, Varv & Mek Verkst in Hönö in 1925, became managing director after the company transformed into a limited company in 1944. Member of the municipal board, chairman of the building committee, the fire brigade, and deputy chairman of the unemployment committee. Hobbies: Home Guard, Shooting.",
    "structured": {
        "@context": "https://schema.org/",
        "@type": "Person",
        "name": "Ernst Daniel Berg",
        "birthDate": "1892-02-06",
        "birthPlace": "Gesäter, Älvsborg län",
        "father": {
            "name": "O.F.B"
        },
        "mother": {
            "name": "Inga Sofia Tall"
        },
        "spouse": {
            "name": "Gerda Nilsson"
        },
        "education": {
            "@type": "EducationalOrganization",
            "name": "Primary School"
        },
        "occupation": "Industrialist",
        "employer": [
            {
                "@type": "Organization",
                "name": "Shipyard in Källö-Knipplan",
                "startDate": "1910",
                "endDate": "1912"
            },
            {
                "@type": "Organization",
                "name": "Shipyard in Smögen",
                "startDate": "1912",
                "endDate": "1913"
            },
            {
                "@type": "Organization",
                "name": "Skandiaverken",
                "location": "Lysekil",
                "startDate": "1914"
            },
            {
                "@type": "Organization",
                "name": "Bergs Varv",
                "location": "Hälsö",
                "startDate": "1915",
                "endDate": "1925"
            },
            {
                "@type": "Organization",
                "name": "Berg & Johansson Slip, Varv & Mek Verkst",
                "location": "Hönö",
                "startDate": "1925"
            }
        ],
        "memberOf": [
            {
                "@type": "Organization",
                "name": "Municipal board"
            },
            {
                "@type": "Organization",
                "name": "Building committee",
                "position": "Chairman"
            },
            {
                "@type": "Organization",
                "name": "Fire brigade",
                "position": "Chairman"
            },
            {
                "@type": "Organization",
                "name": "Unemployment committee",
                "position": "Deputy Chairman"
            }
        ],
        "hobbies": [
            "Home Guard",
            "Shooting"
        ]
    },
    "occupations": {
        "career": [
            {
                "occupational_title": "Employee",
                "workplace": "Shipyard in Källö-Knipplan",
                "industry": "Shipbuilding",
                "start_date": "1910"
            },
            {
                "occupational_title": "Employee",
                "workplace": "Shipyard in Smögen",
                "industry": "Shipbuilding",
                "start_date": "1912"
            },
            {
                "occupational_title": "Employee",
                "workplace": "Skandiaverken in Lysekil",
                "industry": "Engineering/Manufacturing",
                "start_date": "1914"
            },
            {
                "occupational_title": "Employee",
                "workplace": "Bergs Varv in Hälsö",
                "industry": "Shipbuilding",
                "start_date": "1915"
            },
            {
                "occupational_title": "Founder/Owner/Managing Director",
                "workplace": "Berg & Johansson Slip, Varv & Mek Verkst",
                "industry": "Shipbuilding/Engineering",
                "start_date": "1925"
            }
        ]
    }
}