{
    "original": "LUNDQVIST, Karl Hjalmar, Direktör, Tullinge, f Säby, Jönkps l, 6/4 81 av stationsförest C A L o Charlotta Rylander, gm Edith Carlsson. Mog.ex Södermalms h a l 01, ex KTH (maskinbyggn o mek tekn) 05. Under-ing v SJ:s maskinavd i Malmö 05—10, ma-skining v Kkrona—Växjö Jvg i Kkrona 11— 14, ban- o maskining v Nora Bergsl Jvg i Nora 14—17, ing v Sv Jvg:s Arb.giv.frn 18— 32, trafikch o vkst dir v Kalmar Jvg i Kalmar 32—38, v. vkst dir i Sv Jvgsfrn o Sv Jvg :s Arb.giv.frn 38—39, vkst dir i samma föreningar sed. 40. Resor: Tyskl, Österr, Ung, Schweiz, Ital, Frankr, Engl o Belg. KVO2kl, RNO.",
    "translated": "LUNDQVIST, Karl Hjalmar, Director, Tullinge, born in Säby, Jönköping county, on 6/4 1881, son of station master C A L and Charlotta Rylander, married to Edith Carlsson. Graduated from Södermalms higher school in 1901, and from Royal Institute of Technology (mechanical engineering and technical mechanics) in 1905. Worked as an assistant engineer at SJ's (Swedish State Railways) machinery department in Malmö from 1905 to 1910, as a mechanical engineer at Kkrona-Växjö Railway in Kkrona from 1911 to 1914, as an engineer for construction and machinery at Nora Bergslag Railway in Nora from 1914 to 1917. Employed as an engineer at Swedish Railways' employee association from 1918 to 1932, as a traffic chief and development director at Kalmar Railway in Kalmar from 1932 to 1938, as a deputy development director at Swedish Railways' employee association and Swedish Railways from 1938 to 1939, and as a development director in the same associations since 1940. Traveled to Germany, Austria, Hungary, Switzerland, Italy, France, England, and Belgium. Awarded with the Order of Vasa, Knight 2nd Class, and the Royal Norwegian Order of Merit.",
    "structured": {
        "@context": "https://schema.org",
        "@type": "Person",
        "name": "Karl Hjalmar Lundqvist",
        "jobTitle": "Director",
        "birthPlace": "Säby, Jönköping county",
        "birthDate": "1881-04-06",
        "parents": [
            {
                "@type": "Person",
                "name": "C A L Lundqvist",
                "jobTitle": "Station Master"
            },
            {
                "@type": "Person",
                "name": "Charlotta Rylander"
            }
        ],
        "spouse": {
            "@type": "Person",
            "name": "Edith Carlsson"
        },
        "education": [
            {
                "@type": "EducationalOrganization",
                "name": "Södermalms högre allmänna läroverk",
                "endDate": "1901"
            },
            {
                "@type": "EducationalOrganization",
                "name": "Royal Institute of Technology",
                "areaOfStudy": "Mechanical Engineering and Technical Mechanics",
                "endDate": "1905"
            }
        ],
        "work": [
            {
                "@type": "Organization",
                "name": "SJ's (Swedish State Railways) machinery department",
                "jobTitle": "Assistant Engineer",
                "location": "Malmö",
                "startDate": "1905",
                "endDate": "1910"
            },
            {
                "@type": "Organization",
                "name": "Kkrona-Växjö Railway",
                "jobTitle": "Mechanical Engineer",
                "location": "Kkrona",
                "startDate": "1911",
                "endDate": "1914"
            },
            {
                "@type": "Organization",
                "name": "Nora Bergslag Railway",
                "jobTitle": "Engineer for Construction and Machinery",
                "location": "Nora",
                "startDate": "1914",
                "endDate": "1917"
            },
            {
                "@type": "Organization",
                "name": "Swedish Railways' Employee Association",
                "jobTitle": "Engineer",
                "location": "Sweden",
                "startDate": "1918",
                "endDate": "1932"
            },
            {
                "@type": "Organization",
                "name": "Kalmar Railway",
                "jobTitle": "Traffic Chief and Development Director",
                "location": "Kalmar",
                "startDate": "1932",
                "endDate": "1938"
            },
            {
                "@type": "Organization",
                "name": "Swedish Railways",
                "jobTitle": "Deputy Development Director",
                "location": "Sweden",
                "startDate": "1938",
                "endDate": "1939"
            },
            {
                "@type": "Organization",
                "name": "Swedish Railways' Employee Association",
                "jobTitle": "Development Director",
                "location": "Sweden",
                "startDate": "1940"
            }
        ],
        "nationality": "Swedish",
        "memberOf": [
            {
                "@type": "Organization",
                "name": "Order of Vasa",
                "award": "Knight 2nd Class"
            },
            {
                "@type": "Organization",
                "name": "Royal Norwegian Order of Merit"
            }
        ],
        "travelledTo": [
            "Germany",
            "Austria",
            "Hungary",
            "Switzerland",
            "Italy",
            "France",
            "England",
            "Belgium"
        ]
    },
    "occupations": {
        "career": [
            {
                "occupational_title": "Assistant Engineer",
                "workplace": "SJ's Machinery Department",
                "industry": "Swedish State Railways",
                "start_date": "1905"
            },
            {
                "occupational_title": "Mechanical Engineer",
                "workplace": "Kkrona-Växjö Railway",
                "industry": "Railway",
                "start_date": "1911"
            },
            {
                "occupational_title": "Engineer for Construction and Machinery",
                "workplace": "Nora Bergslag Railway",
                "industry": "Railway",
                "start_date": "1914"
            },
            {
                "occupational_title": "Engineer",
                "workplace": "Swedish Railways' Employee Association",
                "industry": "Railway",
                "start_date": "1918"
            },
            {
                "occupational_title": "Traffic Chief and Development Director",
                "workplace": "Kalmar Railway",
                "industry": "Railway",
                "start_date": "1932"
            },
            {
                "occupational_title": "Deputy Development Director",
                "workplace": "Swedish Railways' Employee Association and Swedish Railways",
                "industry": "Railway",
                "start_date": "1938"
            },
            {
                "occupational_title": "Development Director",
                "workplace": "Swedish Railways' Employee Association and Swedish Railways",
                "industry": "Railway",
                "start_date": "1940"
            }
        ]
    }
}