{
    "original": "FALKMAN, Erik Johan Wilhelm, Civilingenjör, Uppsala, f Sireköpinge, Malmöh l, 29/7 07 av agronom S J F o Elisabeth Ganslandt, gm Gully Geier. Studex Malmö 25, KTH (V o V) 26—30. Priv.assist h prof C Heuman 31, anst h konsult in %. f ma Messrs Crompton &amp; Ekström (fil i Sthlm) 32, v Stat provn.anst 32 —35, assist i allm byggn.lära m vägtekn KTH 33—35, Väg- o Vatteribyggn.styr:s platskontr v brobyggn Skorped o Örnsköldsvik 35-^-36 samt i Gävleb län 37—38, väging.assist i Gävleborgs län 37—38, byggn.insp h Gävle Stads Byggn.nmd 38—44, nu byggn.insp h Upps Stads Byggn.nmd.",
    "translated": "FALKMAN, Erik Johan Wilhelm, Civil Engineer, Uppsala, born in Sireköpinge, Malmö County, on July 29, 1907, son of agronomist S.J.F. and Elisabeth Ganslandt, married to Gully Geier. Graduated in Malmö in 1925, and studied at the Royal Institute of Technology (VT) from 1926 to 1930. Worked as a private assistant to Professor C. Heuman in 1931, and employed as a consultant at % of the firm Messrs Crompton & Ekström (located in Stockholm) in 1932. Joined the State Inspection Authority from 1932 to 1935, and served as an assistant in general building and road construction at the Royal Institute of Technology from 1933 to 1935. Held contract positions for the Road and Water Construction Board, overseeing bridge construction in Skorped and Örnsköldsvik from 1935 to 1936, as well as in Gävleborg County from 1937 to 1938. Additionally, worked as a road engineer assistant in Gävleborg County from 1937 to 1938 and as a building inspector for Gävle City Building Board from 1938 to 1944. Currently working as a building inspector for Uppsala City Building Board.",
    "structured": {
        "@context": "https://schema.org",
        "@type": "Person",
        "name": "Erik Johan Wilhelm Falkman",
        "jobTitle": "Civil Engineer",
        "birthPlace": "Sireköpinge, Malmö County",
        "birthDate": "1907-07-29",
        "parents": [
            {
                "@type": "Person",
                "name": "S.J.F."
            },
            {
                "@type": "Person",
                "name": "Elisabeth Ganslandt"
            }
        ],
        "spouse": {
            "@type": "Person",
            "name": "Gully Geier"
        },
        "education": [
            {
                "@type": "EducationalOccupationalCredential",
                "name": "Graduated in Malmö",
                "endDate": "1925"
            },
            {
                "@type": "EducationalOccupationalCredential",
                "name": "Studied at Royal Institute of Technology",
                "startDate": "1926",
                "endDate": "1930"
            }
        ],
        "work": [
            {
                "@type": "EmploymentOrganization",
                "name": "Private assistant to Professor C. Heuman",
                "startDate": "1931"
            },
            {
                "@type": "EmploymentOrganization",
                "name": "Consultant at Messrs Crompton & Ekström",
                "startDate": "1932"
            },
            {
                "@type": "EmploymentOrganization",
                "name": "State Inspection Authority",
                "startDate": "1932",
                "endDate": "1935"
            },
            {
                "@type": "EmploymentOrganization",
                "name": "Assistant at Royal Institute of Technology",
                "startDate": "1933",
                "endDate": "1935"
            },
            {
                "@type": "EmploymentOrganization",
                "name": "Road and Water Construction Board",
                "startDate": "1935",
                "endDate": "1936",
                "jobTitle": "Contract Positions",
                "serviceArea": [
                    {
                        "@type": "City",
                        "name": "Skorped"
                    },
                    {
                        "@type": "City",
                        "name": "Örnsköldsvik"
                    }
                ]
            },
            {
                "@type": "EmploymentOrganization",
                "name": "Gävleborg County",
                "startDate": "1937",
                "endDate": "1938",
                "jobTitle": "Contract Positions"
            },
            {
                "@type": "EmploymentOrganization",
                "name": "Gävleborg County",
                "startDate": "1937",
                "endDate": "1938",
                "jobTitle": "Road Engineer Assistant"
            },
            {
                "@type": "EmploymentOrganization",
                "name": "Gävle City Building Board",
                "startDate": "1938",
                "endDate": "1944",
                "jobTitle": "Building Inspector"
            },
            {
                "@type": "EmploymentOrganization",
                "name": "Uppsala City Building Board",
                "jobTitle": "Building Inspector"
            }
        ]
    },
    "occupations": {
        "career": [
            {
                "occupational_title": "Private Assistant",
                "workplace": "Professor C. Heuman",
                "industry": "Education",
                "start_date": "1931"
            },
            {
                "occupational_title": "Consultant",
                "workplace": "Messrs Crompton & Ekström",
                "industry": "Engineering",
                "start_date": "1932"
            },
            {
                "occupational_title": "Assistant in General Building and Road Construction",
                "workplace": "Royal Institute of Technology",
                "industry": "Education/Engineering",
                "start_date": "1933"
            },
            {
                "occupational_title": "Contract Position",
                "workplace": "Road and Water Construction Board",
                "industry": "Construction",
                "start_date": "1935"
            },
            {
                "occupational_title": "Contract Position",
                "workplace": "Road and Water Construction Board",
                "industry": "Construction",
                "start_date": "1937"
            },
            {
                "occupational_title": "Road Engineer Assistant",
                "workplace": "Gävleborg County",
                "industry": "Construction",
                "start_date": "1937"
            },
            {
                "occupational_title": "Building Inspector",
                "workplace": "Gävle City Building Board",
                "industry": "Construction",
                "start_date": "1938"
            },
            {
                "occupational_title": "Building Inspector",
                "workplace": "Uppsala City Building Board",
                "industry": "Construction",
                "start_date": "Unknown"
            }
        ]
    }
}