{
    "original": "HYTTENBERG, Carl Eugen Waldemar, Bergsingenjör, Stockholm, f Sthlm 23/4 88 av kammarvaktm J Carlson o Hedvig Peterson, gm Gundborg Sjöberg. Mog.ex NReal Sthlm 06, KTH 06—09 o 12—13. Resoffex o ulöjtn v Norrl art.reg :s res 08, löjtn 14, kapt 28. Anst v The Midvale Steel Co i Philadelphia o v The Carnegie Steel Co i Pittsburgh USA 13—14, avd.chef v Stat Provn.anst 15—17, anst v AB Frank Hirschs Maskiner i Sthlm o v AB Sv Maskinverken i Södertälje 17—18, v SKF i Gbg 18—20, försäljn.ing v AB Atlas-Diesel i Sthlm 20—21, vkst dir f AB Auto-compressor i Sthlm 21—27, f Bergsing.fma Hyttenberg AB i Sthlm 28. HuTTNER, Julius, Generalkonsul, Göteborg, f Gbg 1/4 81 av dir B S H o Hanna H, gm Bertha Salm. Hal, hdlsinst. Vkst dlr i B S Huttners AB (grund av fad ss ensk bol 72). Rev vanföreanst i Gbg, d:o SvRK 6. distr, init.tag t SvRK julklappsadr, kassaförv Mosaiska förs:s i Gbg fattigv, förest f Hjälpkomm i Gbg mm. Resor: Flert europ länd o USA. RNO, RVO, SvRKftjSM 8storl. HuTTNER, Ruben, Grosshandlare, Stockholm, f Sthlm 25/4 10 av grhdl M S H o Signe Ruben, gm Lilli Emanuel. Studex 28, DHS 32. Anst h aukt rev Fritiof Dahlgren 33—34. Ag fma Max Huttner o Sv Optiska Engros-Affären. Resor: Tyskl, Österr, Schweiz, Frankr mfl. Hobby: Konst.",
    "translated": "HYTTENBERG, Carl Eugen Waldemar, Mining Engineer, Stockholm, b Stockholm 23/4 1888, son of chamber custodian J Carlson and Hedvig Peterson, married to Gundborg Sjöberg. Graduated Real school Stockholm 1906, Royal Institute of Technology 1906-1909 and 1912-1913. Reserve Officer and Second Lieutenant in the Northern Artillery Regiment: reserve 1908, lieutenant 1914, captain 1928. Employed at The Midvale Steel Co in Philadelphia and The Carnegie Steel Co in Pittsburgh, USA 1913-1914, department chief at State Test Institute 1915-1917, employed at AB Frank Hirsch's Machinery in Stockholm and AB Swedish Machine Works in Södertälje 1917-1918, at SKF in Gothenburg 1918-1920, sales manager at AB Atlas-Diesel in Stockholm 1920-1921, Managing Director of AB Auto-compressor in Stockholm 1921-1927, founded Hyttenberg Mining Company AB in Stockholm in 1928.\n\nHUTTNER, Julius, Consul General, Gothenburg, b Gothenburg 1/4 1881, son of director B S H and Hanna H, married to Bertha Salm. Trade College. Managing Director of B S Huttners AB (founded by father as sole proprietorship in 1872). Reviewer of disabled institutions in Gothenburg, also Swedish Red Cross 6th district, initiated Swedish Red Cross Christmas address registry, treasurer of the Jewish congregation's charity in Gothenburg, chairman of the Aid Committee in Gothenburg, and more. Travels: Several European countries and the USA. RNO (Order of the North Star), RVO (Order of Vasa), Swedish Red Cross silver medal, 8th (large) size.\n\nHUTTNER, Ruben, Wholesaler, Stockholm, b Stockholm 25/4 1910, son of wholesaler M S H and Signe Ruben, married to Lilli Emanuel. Graduated 1928, studied at the Royal Dutch Colonial Institute 1932. Employed at the authorized auditor Fritiof Dahlgren 1933-1934. Agent at the company Max Huttner and AB Swedish Optics Wholesale Store. Travels: Germany, Austria, Switzerland, France, and others. Hobby: Art.",
    "structured": {
        "@context": "http://schema.org",
        "name": "Carl Eugen Waldemar Hyttenberg",
        "alternateName": "C. E. W. Hyttenberg",
        "birthDate": "1888-04-23",
        "birthPlace": "Stockholm, Sweden",
        "description": "Mining Engineer",
        "spouse": "Gundborg Sjöberg",
        "education": {
            "@type": "EducationalOccupationalCredential",
            "credentialCategory": "Degree",
            "educationalLevel": "High School Diploma",
            "alumniOf": "Real school Stockholm",
            "endDate": "1906"
        },
        "alumniOf": [
            {
                "@type": "CollegeOrUniversity",
                "name": "Royal Institute of Technology",
                "location": "Stockholm, Sweden",
                "startDate": "1906",
                "endDate": "1909"
            },
            {
                "@type": "CollegeOrUniversity",
                "name": "Royal Institute of Technology",
                "location": "Stockholm, Sweden",
                "startDate": "1912",
                "endDate": "1913"
            }
        ],
        "memberOf": [
            {
                "@type": "Organization",
                "name": "The Midvale Steel Co",
                "location": "Philadelphia, USA",
                "startDate": "1913",
                "endDate": "1914",
                "jobTitle": "Employee"
            },
            {
                "@type": "Organization",
                "name": "The Carnegie Steel Co",
                "location": "Pittsburgh, USA",
                "startDate": "1913",
                "endDate": "1914",
                "jobTitle": "Employee"
            },
            {
                "@type": "Organization",
                "name": "State Test Institute",
                "location": "Sweden",
                "startDate": "1915",
                "endDate": "1917",
                "jobTitle": "Department Chief"
            },
            {
                "@type": "Organization",
                "name": "AB Frank Hirsch's Machinery",
                "location": "Stockholm, Sweden",
                "startDate": "1917",
                "endDate": "1918",
                "jobTitle": "Employee"
            },
            {
                "@type": "Organization",
                "name": "AB Swedish Machine Works",
                "location": "Södertälje, Sweden",
                "startDate": "1917",
                "endDate": "1918",
                "jobTitle": "Employee"
            },
            {
                "@type": "Organization",
                "name": "SKF",
                "location": "Gothenburg, Sweden",
                "startDate": "1918",
                "endDate": "1920",
                "jobTitle": "Employee"
            },
            {
                "@type": "Organization",
                "name": "AB Atlas-Diesel",
                "location": "Stockholm, Sweden",
                "startDate": "1920",
                "endDate": "1921",
                "jobTitle": "Sales Manager"
            },
            {
                "@type": "Organization",
                "name": "AB Auto-compressor",
                "location": "Stockholm, Sweden",
                "startDate": "1921",
                "endDate": "1927",
                "jobTitle": "Vice President"
            },
            {
                "@type": "Organization",
                "name": "Hyttenberg Mining Company AB",
                "location": "Stockholm, Sweden",
                "startDate": "1928",
                "jobTitle": "Founder, CEO"
            }
        ],
        "honorificPrefix": "Bergsingenjör",
        "hasOccupation": {
            "@type": "Occupation",
            "name": "Mining Engineer"
        },
        "relatedTo": {
            "@type": "Person",
            "name": "Julius Huttner",
            "description": "Consul General",
            "birthDate": "1881-04-01",
            "birthPlace": "Gothenburg, Sweden",
            "spouse": "Bertha Salm",
            "memberOf": [
                {
                    "@type": "Organization",
                    "name": "B S Huttners AB",
                    "location": "Gothenburg, Sweden",
                    "jobTitle": "Managing Director"
                }
            ],
            "award": [
                {
                    "@type": "Order",
                    "name": "Order of the North Star",
                    "description": "Recipient",
                    "honorificSuffix": "RNO"
                },
                {
                    "@type": "Order",
                    "name": "Order of Vasa",
                    "description": "Recipient",
                    "honorificSuffix": "RVO"
                },
                {
                    "@type": "Medal",
                    "name": "Swedish Red Cross silver medal",
                    "description": "Recipient",
                    "honorificSuffix": "SvRKftjSM 8storl"
                }
            ],
            "travels": [
                "Multiple European countries",
                "USA"
            ],
            "relatedTo": {
                "@type": "Person",
                "name": "Ruben Huttner",
                "description": "Wholesaler",
                "birthDate": "1910-04-25",
                "birthPlace": "Stockholm, Sweden",
                "spouse": "Lilli Emanuel",
                "memberOf": [
                    {
                        "@type": "Organization",
                        "name": "Max Huttner",
                        "jobTitle": "Agent"
                    },
                    {
                        "@type": "Organization",
                        "name": "AB Swedish Optics Wholesale Store",
                        "jobTitle": "Agent"
                    }
                ],
                "education": {
                    "@type": "EducationalOccupationalCredential",
                    "credentialCategory": "Degree",
                    "educationalLevel": "High School Diploma",
                    "alumniOf": "Royal Dutch Colonial Institute",
                    "endDate": "1932"
                },
                "employs": {
                    "@type": "OrganizationRole",
                    "employee": {
                        "@type": "Person",
                        "name": "Fritiof Dahlgren",
                        "description": "Authorized Auditor"
                    },
                    "startDate": "1933",
                    "endDate": "1934"
                },
                "hobby": "Art",
                "travels": [
                    "Germany",
                    "Austria",
                    "Switzerland",
                    "France"
                ]
            }
        }
    },
    "occupations": {
        "career": [
            {
                "occupational_title": "Mining Engineer",
                "workplace": "The Midvale Steel Co",
                "industry": "Steel",
                "start_date": "1913"
            },
            {
                "occupational_title": "Mining Engineer",
                "workplace": "The Carnegie Steel Co",
                "industry": "Steel",
                "start_date": "1913"
            },
            {
                "occupational_title": "Department Chief",
                "workplace": "State Test Institute",
                "industry": "Government",
                "start_date": "1915"
            },
            {
                "occupational_title": "Employee",
                "workplace": "AB Frank Hirsch's Machinery",
                "industry": "Machinery",
                "start_date": "1917"
            },
            {
                "occupational_title": "Employee",
                "workplace": "AB Swedish Machine Works",
                "industry": "Machinery",
                "start_date": "1917"
            },
            {
                "occupational_title": "Employee",
                "workplace": "SKF",
                "industry": "Manufacturing",
                "start_date": "1918"
            },
            {
                "occupational_title": "Sales Manager",
                "workplace": "AB Atlas-Diesel",
                "industry": "Diesel Engines",
                "start_date": "1920"
            },
            {
                "occupational_title": "Managing Director",
                "workplace": "AB Auto-compressor",
                "industry": "Automotive",
                "start_date": "1921"
            },
            {
                "occupational_title": "Founder",
                "workplace": "Hyttenberg Mining Company AB",
                "industry": "Mining",
                "start_date": "1928"
            }
        ]
    }
}