{
    "original": "BORG, Otto Wilhelm, Direktör, Lund, f Lund 18/5 78 av dir P W B o Hilma Lundgren, gm Else Friedrich. Lunds katedralsk,Gbgs hdlsinst, Königl Preuss Weberschule, Aachen, o Mockels Weberschule, Vaals, Holl. Vol v textilfabr i Lambrecht o på kont h Armand Linck, Vervier, 98. Elev h Borgs Söners Fabriker, Lund, 99—03. Anst å garn-engroslager i New York 04 o däreft h AB C O Borgs Söners Fabriker, Lund, först på kont sed. som led f detaljaffären. V. vkst dir i dna fma 13, vkst dir o styr.ordf där sed. 29. Fman gr 1739 har gått fr far t äldste son i sex genitioner. (Litt: »Borgs i Lund».) Stadsrev i Lund und två år, led taxer.nmdn sed. 43, tidigare suppl där. Styr.led AB Skånska bkn sed. 36, Lunds Hdls &amp; Ind.frn sed. 29. V. ordf Lunds Manuf.hdlrfrn 18—36, ordf där 36—39, v. ordf Skånes Manuf.hdlfrn 36— 37, tidigare styr.led där. Styr.led o kass RST 38—39. Handhaft redov f Stecksénska jordarna i Lund f Upps Akad 28—40. Resor: USA, Canada, Tyskl, Belg, Holl, Österr, Frankr, Ital, Schweiz, Danm, Norge. RVO, Kgl Patr Sällsk GM l:sta storl, Knutsgillets 25-års Silverduva. Hobby: Filateli.",
    "translated": "BORG, Otto Wilhelm, Director, Lund, b Lund 18/5 78, son of dir P W B and Hilma Lundgren, married to Else Friedrich. Education at Lunds katedralsk, Gbgs hdlsinst, Königl Preuss Weberschule in Aachen, and Mockels Weberschule in Vaals, Holland. Worked at a textile factory in Lambrecht and at the office of Armand Linck in Verviers, Belgium, from 1898. Apprentice at Borgs Söners Fabriker, Lund, from 1899 to 1903. Employed at a wholesale yarn warehouse in New York in 1904, and afterwards at AB C O Borgs Söners Fabriker, Lund, first in the office and later as a retail store manager. Became vice managing director in 1913, and then managing director and chairman of the board from 1929. The company, founded in 1739, has been passed down from father to eldest son for six generations. (Reference: \"Borgs i Lund\"). Served as city auditor in Lund for two years, member of the tax assessment committee from 1943, previously a substitute member. Board member of AB Skånska bkn since 1936, Lunds Hdls & Ind.from 1929. Vice chairman of Lunds Manuf.hdlr from 1918 to 1936, chairman from 1936 to 1939, vice chairman of Skånes Manuf.hdlfr from 1936 to 1937, previously a board member. Board member and treasurer of RST from 1938 to 1939. Responsible for the administration of the Stecksén farms in Lund belonging to Uppsala University from 1928 to 1940. Travelled to the USA, Canada, Germany, Belgium, Holland, Austria, France, Italy, Switzerland, Denmark, and Norway. Awarded with the Royal Order of Vasa, Royal Patriotic Society's Gold Medal (1st class), and Knutsgillets 25-year Silver Dove. Hobby: Philately.",
    "structured": {
        "@context": "http://schema.org",
        "@type": "Person",
        "name": "Otto Wilhelm Borg",
        "birthDate": "1878-05-18",
        "birthPlace": "Lund, Sweden",
        "parents": [
            {
                "@type": "Person",
                "name": "P W Borg"
            },
            {
                "@type": "Person",
                "name": "Hilma Lundgren"
            }
        ],
        "spouse": {
            "@type": "Person",
            "name": "Else Friedrich"
        },
        "education": [
            {
                "@type": "Organization",
                "name": "Lunds katedralsk"
            },
            {
                "@type": "Organization",
                "name": "Gbgs hdlsinst"
            },
            {
                "@type": "Organization",
                "name": "Königl Preuss Weberschule",
                "location": "Aachen, Germany"
            },
            {
                "@type": "Organization",
                "name": "Mockels Weberschule",
                "location": "Vaals, Holland"
            }
        ],
        "work": [
            {
                "@type": "Organization",
                "name": "Textilfabr in Lambrecht",
                "startDate": "1898"
            },
            {
                "@type": "Organization",
                "name": "Armand Linck",
                "location": "Verviers, Belgium",
                "startDate": "1898"
            },
            {
                "@type": "Organization",
                "name": "Borgs Söners Fabriker",
                "location": "Lund, Sweden",
                "startDate": "1899",
                "endDate": "1903"
            },
            {
                "@type": "Organization",
                "name": "AB C O Borgs Söners Fabriker",
                "location": "Lund, Sweden",
                "startDate": "1904"
            },
            {
                "@type": "Organization",
                "name": "Wholesale yarn warehouse",
                "location": "New York",
                "startDate": "1904"
            }
        ],
        "positions": [
            {
                "@type": "Role",
                "name": "Vice Managing Director",
                "startDate": "1913",
                "endDate": "1929",
                "memberOf": {
                    "@type": "Organization",
                    "name": "DNA Fma"
                }
            },
            {
                "@type": "Role",
                "name": "Managing Director and Chairman",
                "startDate": "1929",
                "memberOf": {
                    "@type": "Organization",
                    "name": "DNA Fma"
                }
            }
        ],
        "generation": [
            {
                "@type": "Organization",
                "name": "Borgs i Lund",
                "foundingYear": "1739",
                "inheritanceType": "Eldest son"
            }
        ],
        "activities": [
            {
                "@type": "Role",
                "name": "City Auditor",
                "startDate": "unknown",
                "endDate": "unknown",
                "memberOf": {
                    "@type": "Organization",
                    "name": "Lund Municipality"
                }
            },
            {
                "@type": "Role",
                "name": "Member of Tax Assessment Committee",
                "startDate": "1943",
                "memberOf": {
                    "@type": "Organization",
                    "name": "Lund Municipality"
                }
            },
            {
                "@type": "Role",
                "name": "Board Member",
                "organization": "AB Skånska bkn",
                "startDate": "1936"
            },
            {
                "@type": "Role",
                "name": "Board Member",
                "organization": "Lunds Hdls & Ind.",
                "startDate": "1929"
            },
            {
                "@type": "Role",
                "name": "Vice Chairman",
                "organization": "Lunds Manuf.hdlr",
                "startDate": "1918",
                "endDate": "1936"
            },
            {
                "@type": "Role",
                "name": "Chairman",
                "organization": "Lunds Manuf.hdlr",
                "startDate": "1936",
                "endDate": "1939"
            },
            {
                "@type": "Role",
                "name": "Vice Chairman",
                "organization": "Skånes Manuf.hdlfr",
                "startDate": "1936",
                "endDate": "1937"
            },
            {
                "@type": "Role",
                "name": "Board Member",
                "organization": "RST",
                "startDate": "1938",
                "endDate": "1939"
            },
            {
                "@type": "Role",
                "name": "Administrator",
                "organization": "Stecksénska farms",
                "location": "Lund, Sweden",
                "startDate": "1928",
                "endDate": "1940"
            }
        ],
        "hobbies": [
            "Philately"
        ],
        "travels": [
            "USA",
            "Canada",
            "Germany",
            "Belgium",
            "Holland",
            "Austria",
            "France",
            "Italy",
            "Switzerland",
            "Denmark",
            "Norway"
        ],
        "awards": [
            {
                "@type": "Order",
                "name": "Royal Order of Vasa"
            },
            {
                "@type": "Medal",
                "name": "Royal Patriotic Society's Gold Medal (1st class)"
            },
            {
                "@type": "Medal",
                "name": "Knutsgillets 25-year Silver Dove"
            }
        ]
    },
    "occupations": {
        "career": [
            {
                "occupational_title": "Director",
                "workplace": "ÅB C O Borgs Söners Fabriker",
                "industry": "Textile",
                "start_date": "1929"
            },
            {
                "occupational_title": "Vice Managing Director",
                "workplace": "ÅB C O Borgs Söners Fabriker",
                "industry": "Textile",
                "start_date": "1913"
            },
            {
                "occupational_title": "Retail Store Manager",
                "workplace": "ÅB C O Borgs Söners Fabriker",
                "industry": "Textile",
                "start_date": "unknown"
            },
            {
                "occupational_title": "Apprentice",
                "workplace": "Borgs Söners Fabriker",
                "industry": "Textile",
                "start_date": "1899"
            },
            {
                "occupational_title": "Employee",
                "workplace": "Armand Linck",
                "industry": "Textile",
                "start_date": "1898"
            },
            {
                "occupational_title": "Employee",
                "workplace": "Textile Factory in Lambrecht",
                "industry": "Textile",
                "start_date": "unknown"
            },
            {
                "occupational_title": "Employee",
                "workplace": "Wholesale yarn warehouse in New York",
                "industry": "Textile",
                "start_date": "1904"
            }
        ]
    }
}