{
    "original": "LINDBLAD, Axel Rudolf, Fil Dr, Djursholm, f Vånga, Ögl, 23/4 74 av lantbr Ad L o Margareta Andersson, gm 1) Ester Bergman (d 30), 2) Sigrid Fridén f Pehrsson. Ex Norrkps tekn elem.sk. Anst olika firmor 01— 06, en av led f de av bl a Jernkont understödda grundlägg exper betr elektr tackj- o stål-framställn; uppf fi metoder f elektr fram-ställn av metaller o met.legrar; init.tag t malmletn.arb i Västerb 18 (varund bl a Bolidens gruvfält upptäcktes); förbättr o uppf\" malmletn.metoder, bl a en f malmletn spec lämpad gravimeter; ss tekn led f Rönnskärs smältverk uppf fi metoder f Boliden-malmen»Ibearb, metoder f svavelframst ur smältverks -gaserna eller direkt ur svavelkis mm. Fd stdsflm o Idstm, led krigsmtrlkomm 17—23, socialiser.nmdn 20—25, rikskommiss f ekon försv.beredsk 29—38, v. ordf Sv kem ind.kont 32—42, ordf Försv.väs:s kem anstis vetensk råd 37—41. Fil hed.dr Upps 17. KNOlkl, KVOlkl, Iqml 12 :e storl, LVA, LVA i Oslo,",
    "translated": "LINDBLAD, Axel Rudolf, PhD, Djursholm, b. Vånga, Ögl, April 23, 1874, to Ad L. and Margareta Andersson, married 1) Ester Bergman (deceased 1930), 2) Sigrid Fridén, neé Pehrsson. Former student at Norrkp's technical elementary school. Employed by various companies from 1901 to 1906, holding a leading position in several foundations subsidized by Jernkont in the field of electrical welding and steel production; developed methods for the electric production of metals and metal alloys; initiated ore prospecting work in Västerbotten in 1918 (where, among other things, Boliden's mining field was discovered); improved and developed ore prospecting methods, including a gravimeter suitable for ore prospecting; served as technical director at Rönnskärs smelter, where he developed methods for processing Boliden ore, extracting sulfur from smelter gases, and directly from pyrite, and more. Former member of the city council and the county council, member of the military material committee from 1917 to 1923, member of the nationalization committee from 1920 to 1925, commissioner of economic defense preparedness from 1929 to 1938, deputy chairman of the Swedish Chemical Industry Control Board from 1932 to 1942, chairman of the Defense Technical Research Council from 1937 to 1941. Honorary Doctor of Philosophy from Uppsala University in 1917. Knight of the Order of the North Star, Knight of the Order of Vasa, 12th class of the Swedish Academy, Member of the Royal Swedish Academy of Sciences, and the Norwegian Academy of Sciences.",
    "structured": {
        "name": "Axel Rudolf Lindblad",
        "givenName": "Axel Rudolf",
        "familyName": "Lindblad",
        "birthDate": "1874-04-23",
        "birthPlace": "Vånga, Ögl",
        "deathDate": null,
        "address": {
            "addressLocality": "Djursholm"
        },
        "father": {
            "name": "Ad L."
        },
        "mother": {
            "name": "Margareta Andersson"
        },
        "spouse": [
            {
                "name": "Ester Bergman",
                "deathDate": "1930"
            },
            {
                "name": "Sigrid Fridén",
                "birthFamilyName": "Pehrsson"
            }
        ],
        "education": [
            {
                "institution": "Norrkp's technical elementary school",
                "endDate": null
            },
            {
                "honoraryDegree": "PhD",
                "awardingInstitution": "Uppsala University",
                "awardDate": "1917-01-01"
            }
        ],
        "employment": [
            {
                "name": "Rönnskärs smelter",
                "position": "Technical Director",
                "startDate": null,
                "endDate": null
            },
            {
                "name": "Various Companies",
                "position": "Employee",
                "startDate": "1901-01-01",
                "endDate": "1906-01-01"
            }
        ],
        "memberships": [
            {
                "organization": "Jernkont",
                "role": "Leading Position"
            },
            {
                "organization": "Swedish Chemical Industry Control Board",
                "role": "Deputy Chairman",
                "startDate": "1932-01-01",
                "endDate": "1942-01-01"
            },
            {
                "organization": "Defense Technical Research Council",
                "role": "Chairman",
                "startDate": "1937-01-01",
                "endDate": "1941-01-01"
            }
        ],
        "activities": [
            {
                "name": "Ore Prospect",
                "description": "Initiated ore prospecting work in Västerbotten in 1918, contributing to the discovery of Boliden's mining field."
            },
            {
                "name": "Ore Prospecting Methods",
                "description": "Improved and developed ore prospecting methods, including the design of a gravimeter suitable for ore prospecting."
            },
            {
                "name": "Electrical Welding and Steel Production",
                "description": "Developed methods for electric production of metals and metal alloys in foundations subsidized by Jernkont."
            },
            {
                "name": "Sulfur Extraction",
                "description": "Developed methods for extracting sulfur from smelter gases and directly from pyrite."
            }
        ],
        "honors": [
            {
                "name": "Knight of the Order of the North Star"
            },
            {
                "name": "Knight of the Order of Vasa"
            },
            {
                "name": "Swedish Academy, 12th class"
            },
            {
                "name": "Royal Swedish Academy of Sciences"
            },
            {
                "name": "Norwegian Academy of Sciences"
            }
        ]
    },
    "occupations": {
        "career": [
            {
                "occupational_title": "Former student",
                "workplace": "Norrkp's technical elementary school",
                "industry": "Education",
                "start_date": "Unknown"
            },
            {
                "occupational_title": "Employee",
                "workplace": "Various companies",
                "industry": "Unknown",
                "start_date": "1901"
            },
            {
                "occupational_title": "Leading position",
                "workplace": "Foundations subsidized by Jernkont",
                "industry": "Electrical welding and steel production",
                "start_date": "Unknown"
            },
            {
                "occupational_title": "Ore prospector",
                "workplace": "Västerbotten",
                "industry": "Mining",
                "start_date": "1918"
            },
            {
                "occupational_title": "Technical director",
                "workplace": "Rönnskärs smelter",
                "industry": "Metallurgy",
                "start_date": "Unknown"
            },
            {
                "occupational_title": "Commissioner of economic defense preparedness",
                "workplace": "Unknown",
                "industry": "Military",
                "start_date": "1929"
            },
            {
                "occupational_title": "Deputy chairman",
                "workplace": "Swedish Chemical Industry Control Board",
                "industry": "Chemical",
                "start_date": "1932"
            },
            {
                "occupational_title": "Chairman",
                "workplace": "Defense Technical Research Council",
                "industry": "Military research",
                "start_date": "1937"
            }
        ]
    }
}