{
    "original": "KABLBEBG, Bobert, Civilingenjör, Hallstavik, f Vimmerby 26/11 92 av garverifabr C E G K o Ida Sundin, gm Margareta Hansson. Studex Lund 11, fil kand 15, tillf stud KTH 15—16, ord stud 16—17 (kemi). Anst v Sthlms Superfosfatfabr AB i Ljungaverk 17, Holmens Bruks &amp; Fabr AB i Norrkp 17—28, v samma bol:s pappersbr i Hallstavik fr-28, ing f sul-fitfabr o ch.kemist, tillika vkst dir o styr.led i Kemiska Kontrollbyrån o Vimmerby Läder-fabr AB (grund av fadern i början av 90-talet und namn Lindekulla Garveri v Vimmerby, överlåt på barnen o ombild t fam.bol 18). Sekr i Sv Pappersbruksfrns kté f industriellt avloppsvatten. Fd besiktn.man f motorfordon h Sv Automobiltariff-frn. Led av kommunal-flm, kyrkoflm, folksk.styr mm i Häverö. Styr.led i hemv.kretsnmd o Hallstaviks Luftsk.frn, luftskyddsled v Hallstaviks pappersbruk. Ordf i N Roslags Skyttekrets, styr.suppl i Sthlms Läns Skyttefrb, v. ordf i Hallstaviks Skytte-frn. Fd ordf i Sv Motorklubbens östgötaavd o styr.led i klubbens centralstyr. Resor: Tyskl 20 26 o 32, Frankr 20 o 26, Engl, USA o Canada 23 o 31, Ryssl 30, Ital 32, Norge, Danm o Finl uppr ggr. Av trycket: Luftfuktighetens inverkan v fuktighetsbestämn å papper (25), Om pH-kontroll v pappersbruk (29), Slemavsättningar i cellulosa- o pappers-fabriker samt deras bekämp m klor eller klor-amin mm (34), Om frisyratorn o likn anordn v sulfitsyraberedningen (42). Frimurare. Riks-luftsk.frbs ftjt. Hobby: Skytte.",
    "translated": "KABLBEBG, Bobert, Civil Engineer, Hallstavik, b. Vimmerby 26/11 92, son of tannery factory owners C E G K and Ida Sundin, married to Margareta Hansson. Graduated from Lund University in 1911 with a Bachelor's degree in Philosophy. Temporary studies at KTH (Royal Institute of Technology) in 1915-1916, regular studies in 1916-1917 (Chemistry). Employed at Stockholm Superphosphate Works AB in Ljungaverk in 1917, Holmens Bruks & Fabr AB in Norrköping in 1917-1928, and at the paper mill of the same company in Hallstavik from 1928 onwards, as an engineer in the sulfite factory and a chemist, also serving as the deputy director and board member. Additionally, he served as secretary at the Swedish Pulp and Paper Industry Association for industrial wastewater. Former inspector of motor vehicles for the Swedish Automobile Tariff Association. Member of the municipal film committee, church film committee, and the public school board in Häverö. Board member of the local civil defense council and Hallstavik Air Defense Association, air defense leader at the Hallstavik paper mill. Chairman of the Northern Roslagen Shooting District, board substitute in the Stockholm County Shooting Federation, vice chairman of the Hallstavik Shooting Association. Former chairman of the Swedish Motor Club's Östergötland branch and board member of the club's central board. Travel: Germany in 1920, 1926, and 1932, France in 1920 and 1926, England, USA, and Canada in 1923 and 1931, Russia in 1930, Italy in 1932, multiple trips to Norway, Denmark, and Finland. Publications: The effect of humidity on paper moisture determination (1925), pH control in paper mills (1929), slime deposition in cellulose and paper factories and their control using chlorine or chloramine, etc. (1934), hairdryer and similar devices for sulfite acid preparation (1942). Freemason. National air defense medal. Hobby: Shooting.",
    "structured": {
        "@context": "https://schema.org",
        "@type": "Person",
        "name": "Bobert Kablbebg",
        "jobTitle": "Civil Engineer",
        "birthPlace": "Vimmerby",
        "birthDate": "1892-11-26",
        "parents": [
            {
                "@type": "Person",
                "name": "C E G K"
            },
            {
                "@type": "Person",
                "name": "Ida Sundin"
            }
        ],
        "spouse": {
            "@type": "Person",
            "name": "Margareta Hansson"
        },
        "education": [
            {
                "@type": "EducationalOccupationalCredential",
                "credentialCategory": "Bachelor's degree",
                "educationalLevel": "Bachelor's Degree",
                "educationalProgram": "Philosophy",
                "educationalInstitution": {
                    "@type": "CollegeOrUniversity",
                    "name": "Lund University"
                },
                "startDate": "1911",
                "endDate": "1915"
            },
            {
                "@type": "EducationalOccupationalCredential",
                "educationalLevel": "Temporary Studies",
                "educationalProgram": "Chemistry",
                "educationalInstitution": {
                    "@type": "CollegeOrUniversity",
                    "name": "Royal Institute of Technology (KTH)"
                },
                "startDate": "1915",
                "endDate": "1916"
            },
            {
                "@type": "EducationalOccupationalCredential",
                "educationalLevel": "Regular Studies",
                "educationalProgram": "Chemistry",
                "educationalInstitution": {
                    "@type": "CollegeOrUniversity",
                    "name": "Royal Institute of Technology (KTH)"
                },
                "startDate": "1916",
                "endDate": "1917"
            }
        ],
        "employment": [
            {
                "@type": "Organization",
                "name": "Stockholm Superphosphate Works AB",
                "startDate": "1917",
                "endDate": "1928",
                "location": "Ljungaverk"
            },
            {
                "@type": "Organization",
                "name": "Holmens Bruks & Fabr AB",
                "startDate": "1917",
                "endDate": "1928",
                "location": "Norrköping"
            },
            {
                "@type": "Organization",
                "name": "Holmens Bruks & Fabr AB",
                "startDate": "1928",
                "location": "Hallstavik",
                "description": "Paper Mill"
            }
        ],
        "profession": [
            "Engineer",
            "Chemist"
        ],
        "memberOf": [
            {
                "@type": "Organization",
                "name": "Swedish Pulp and Paper Industry Association",
                "position": "Secretary"
            },
            {
                "@type": "Organization",
                "name": "Swedish Automobile Tariff Association",
                "position": "Former Inspector of Motor Vehicles"
            },
            {
                "@type": "Organization",
                "name": "Municipal Film Committee of Häverö"
            },
            {
                "@type": "Organization",
                "name": "Church Film Committee of Häverö"
            },
            {
                "@type": "Organization",
                "name": "Public School Board of Häverö"
            },
            {
                "@type": "Organization",
                "name": "Local Civil Defense Council"
            },
            {
                "@type": "Organization",
                "name": "Hallstavik Air Defense Association",
                "position": "Board Member"
            },
            {
                "@type": "Organization",
                "name": "Northern Roslagen Shooting District",
                "position": "Chairman"
            },
            {
                "@type": "Organization",
                "name": "Stockholm County Shooting Federation",
                "position": "Board Substitute"
            },
            {
                "@type": "Organization",
                "name": "Hallstavik Shooting Association",
                "position": "Vice Chairman"
            },
            {
                "@type": "Organization",
                "name": "Swedish Motor Club's Östergötland Branch",
                "position": "Former Chairman"
            },
            {
                "@type": "Organization",
                "name": "Swedish Motor Club",
                "position": "Board Member"
            }
        ],
        "travels": [
            {
                "@type": "Place",
                "name": "Germany",
                "timespan": "1920, 1926, 1932"
            },
            {
                "@type": "Place",
                "name": "France",
                "timespan": "1920, 1926"
            },
            {
                "@type": "Place",
                "name": "England"
            },
            {
                "@type": "Place",
                "name": "USA"
            },
            {
                "@type": "Place",
                "name": "Canada"
            },
            {
                "@type": "Place",
                "name": "Russia",
                "timespan": "1930"
            },
            {
                "@type": "Place",
                "name": "Italy",
                "timespan": "1932"
            },
            {
                "@type": "Place",
                "name": "Norway"
            },
            {
                "@type": "Place",
                "name": "Denmark"
            },
            {
                "@type": "Place",
                "name": "Finland"
            }
        ],
        "publications": [
            {
                "@type": "PublicationIssue",
                "name": "Luftfuktighetens inverkan v fuktighetsbestämn å papper (25)",
                "datePublished": "1925"
            },
            {
                "@type": "PublicationIssue",
                "name": "Om pH-kontroll v pappersbruk (29)",
                "datePublished": "1929"
            },
            {
                "@type": "PublicationIssue",
                "name": "Slemavsättningar i cellulosa- o pappers-fabriker samt deras bekämp m klor eller klor-amin mm (34)",
                "datePublished": "1934"
            },
            {
                "@type": "PublicationIssue",
                "name": "Om frisyratorn o likn anordn v sulfitsyraberedningen (42)",
                "datePublished": "1942"
            }
        ],
        "hobbies": [
            {
                "@type": "Thing",
                "name": "Shooting"
            }
        ],
        "religions": [
            {
                "@type": "Organization",
                "name": "Freemasons"
            }
        ],
        "medals": [
            {
                "@type": "Thing",
                "name": "National Air Defense Medal"
            }
        ]
    },
    "occupations": {
        "career": [
            {
                "occupational_title": "Civil Engineer",
                "workplace": "Stockholm Superphosphate Works AB",
                "industry": "Chemical Manufacturing",
                "start_date": "1917-01-01"
            },
            {
                "occupational_title": "Engineer",
                "workplace": "Holmens Bruks & Fabr AB",
                "industry": "Paper Manufacturing",
                "start_date": "1917-01-01"
            },
            {
                "occupational_title": "Engineer",
                "workplace": "Hallstavik Paper Mill",
                "industry": "Paper Manufacturing",
                "start_date": "1928-01-01"
            }
        ]
    }
}