{
    "original": "CARLSTEDT, Ragnar, Direktör, Stockholm, f Stjärnfors, Ljusnarsberg, Örebro l, 26/4 79 av folkskoll J P C o Ida Lindholm, gni Tina Lundström. Arb.prakt v Morgårdshammar Bruk, ASEA, LUX, New York Standard Watch Co, Norsk Electrisk AS mfl; start AB Elek-trotid 06, tekn led o styr.led där 06—09, etabl fma R Carlstedt &amp; Co f tillv av elektr precisions- o driftsinstrument 08, ombild t AB Elektrometer 10, tekn led f detta bolag 10—11; konstr h AB LUX 12—17; grund på egna uppf AB Area Regulatorer 18, styr.led o tekn led där fr 18 o vkst dir sed. 25; medstift o styr.led i AB Sv Pressgjuteriet 19—22; ag o driver Ing.fman Ragnar Carlstedt (tillverkn av regleringsinstrument) sed. 34. Första pris o GM f elektr ur v Norrkpsutställn 06, SM v ut-ställn i Lund 07, IVA:s mindre GM.",
    "translated": "CARLSTEDT, Ragnar, Director, Stockholm, born in Stjärnfors, Ljusnarsberg, Örebro county, April 26, 1879. Son of J.P.C. and Ida Lindholm, formerly Tina Lundström. Worked as an apprentice at Morgårdshammar Bruk, ASEA, LUX, New York Standard Watch Co, Norsk Electrisk AS, among others. Founded AB Elek-trotid in 1906 and served as the technical and managing director until 1909. Established R. Carlstedt & Co for the production of electrical precision and control instruments in 1908, which was later transformed into AB Elektrometer in 1910. Served as the technical director of AB Elektrometer from 1910 to 1911. Involved in the design of AB LUX from 1912 to 1917. Founded his own company, AB Area Regulatorer, in 1918 and served as the managing and technical director from 1918 until 1925, when he became the managing director. Co-founder and board member of AB Sv Pressgjuteriet from 1919 to 1922. Currently operates as the owner and manager of the engineering firm Ragnar Carlstedt (manufacturers of regulating instruments) since 1934. Awarded the first prize and gold medal for electrical clocks at the Norrköping Exhibition in 1906, and received a silver medal at the exhibition in Lund in 1907. Received the Royal Swedish Academy of Engineering Sciences' minor gold medal.",
    "structured": {
        "@context": "https://schema.org",
        "@type": "Person",
        "name": "Ragnar Carlstedt",
        "birthDate": "1879-04-26",
        "birthPlace": {
            "@type": "Place",
            "address": {
                "@type": "PostalAddress",
                "addressLocality": "Stjärnfors",
                "addressRegion": "Ljusnarsberg",
                "addressCountry": "Sweden"
            }
        },
        "deathDate": "",
        "nationality": "Swedish",
        "parent": [
            {
                "@type": "Person",
                "name": "J.P.C. Carlstedt"
            },
            {
                "@type": "Person",
                "name": "Ida Lindholm",
                "alternateName": "Tina Lundström"
            }
        ],
        "jobTitle": "Director",
        "worksFor": {
            "@type": "Organization",
            "name": "AB Area Regulatorer",
            "foundingDate": "1918",
            "founders": [
                "Ragnar Carlstedt"
            ],
            "address": {
                "@type": "PostalAddress",
                "addressLocality": "Stockholm",
                "addressCountry": "Sweden"
            }
        },
        "worksIn": {
            "@type": "Organization",
            "name": "R. Carlstedt & Co",
            "startDate": "1908",
            "endDate": "1910",
            "address": {
                "@type": "PostalAddress",
                "addressLocality": "Stockholm",
                "addressCountry": "Sweden"
            }
        },
        "owns": [
            {
                "@type": "Organization",
                "name": "Ragnar Carlstedt",
                "additionalName": "Ing.fman",
                "description": "Manufacturers of regulating instruments",
                "foundingDate": "1934",
                "address": {
                    "@type": "PostalAddress",
                    "addressLocality": "Stockholm",
                    "addressCountry": "Sweden"
                }
            }
        ],
        "education": [
            {
                "@type": "Organization",
                "name": "Morgårdshammar Bruk"
            },
            {
                "@type": "Organization",
                "name": "ASEA"
            },
            {
                "@type": "Organization",
                "name": "LUX"
            },
            {
                "@type": "Organization",
                "name": "New York Standard Watch Co"
            },
            {
                "@type": "Organization",
                "name": "Norsk Electrisk AS"
            }
        ],
        "award": [
            {
                "@type": "Achievement",
                "name": "First Prize and Gold Medal for Electrical Clocks",
                "description": "Norrköping Exhibition (1906)"
            },
            {
                "@type": "Achievement",
                "name": "Silver Medal",
                "description": "Exhibition in Lund (1907)"
            },
            {
                "@type": "Achievement",
                "name": "Minor Gold Medal",
                "issuer": {
                    "@type": "Organization",
                    "name": "Royal Swedish Academy of Engineering Sciences"
                }
            }
        ]
    },
    "occupations": {
        "career": [
            {
                "occupational_title": "Apprentice",
                "workplace": "Morgårdshammar Bruk",
                "industry": "Ironworks",
                "start_date": "Unknown"
            },
            {
                "occupational_title": "Apprentice",
                "workplace": "ASEA",
                "industry": "Electrical engineering",
                "start_date": "Unknown"
            },
            {
                "occupational_title": "Apprentice",
                "workplace": "LUX",
                "industry": "Electrical engineering",
                "start_date": "Unknown"
            },
            {
                "occupational_title": "Apprentice",
                "workplace": "New York Standard Watch Co",
                "industry": "Watchmaking",
                "start_date": "Unknown"
            },
            {
                "occupational_title": "Apprentice",
                "workplace": "Norsk Electrisk AS",
                "industry": "Electrical engineering",
                "start_date": "Unknown"
            },
            {
                "occupational_title": "Technical and Managing Director",
                "workplace": "AB Elek-trotid",
                "industry": "Electrical precision and control instrument manufacturing",
                "start_date": "1906"
            },
            {
                "occupational_title": "Technical Director",
                "workplace": "AB Elektrometer",
                "industry": "Electrical precision and control instrument manufacturing",
                "start_date": "1910"
            },
            {
                "occupational_title": "Design Engineer",
                "workplace": "AB LUX",
                "industry": "Lighting",
                "start_date": "1912"
            },
            {
                "occupational_title": "Managing and Technical Director",
                "workplace": "AB Area Regulatorer",
                "industry": "Regulator instrument manufacturing",
                "start_date": "1918"
            },
            {
                "occupational_title": "Managing Director",
                "workplace": "AB Area Regulatorer",
                "industry": "Regulator instrument manufacturing",
                "start_date": "1925"
            },
            {
                "occupational_title": "Owner and Manager",
                "workplace": "Ragnar Carlstedt (Ing.fman)",
                "industry": "Regulator instrument manufacturing",
                "start_date": "1934"
            }
        ]
    }
}