{
    "original": "BOLMSTEDT, Johan Edvard Albin, Redaktör, Malmö, f Eslöv 20/7 82 av pappershandl C E B o Anna Hallgren, gm Signe Lindberg. Eslövs elem.lärov 92—96. Medarb i Skåningen Eslövs Tidn 97—02, i Sv Telegrambyråns Malmöfilial 02—06, red.sekr i Kristianstads Läns Tidn 06—20, red o utg- av Krstds Läns Veckoblad 10—20, med.red i Sv Hantv.tidn några år, red av Skånes Köpmannablad 20— 36, då han start eg tidn Handelsbladet, alltjämt dess red o utgivare. Ombudsman, sekr o kassa-förvalt i So Sv Möbelhandl.f sed. 39, v. ordf i Publ.klubbens södra krets, ordf i Sydsv Tidn.-männens sjukkassa. Av trycket: FI minnesskrifter o skr av genealogiskt o historiskt innehåll. Resor: Danm, Tyskl, Österr 12 (Hier-tastip), Engl o Holl 23 (Sv Journalistfrn stip), Frankr, Ital, Span 30, dessutom andra utl studieresor. Hobby: Konst.",
    "translated": "BOLMSTEDT, Johan Edvard Albin, Editor, Malmö, born in Eslöv on July 20, 1882, to paper merchant C E B and Anna Hallgren, married to Signe Lindberg. Attended Eslöv elementary school from 1892 to 1896. Worked for Skåningen and Eslövs Tidning from 1897 to 1902, then at the Malmö branch of the Swedish Telegraph Agency from 1902 to 1906. Became the editor and secretary of Kristianstads Läns Tidning from 1906 to 1920, also editor and publisher of Krstds Läns Veckoblad from 1910 to 1920. Worked as an editor for a few years at the Swedish Hantverkstidning, followed by being the editor of Skånes Köpmannablad from 1920 to 1936. Started his own newspaper, Handelsbladet, in 1936, and continues to be its editor and publisher. Additionally, served as an agent, secretary, and cash manager at the South Swedish Furniture Dealers' Association since 1939, vice chairman of the Southern District of the Public Club, and chairman of the South Swedish Newspapermen's Sick Fund. Published several memoirs and writings on genealogical and historical topics. Traveled to Denmark, Germany, Austria in 1912 (Hierta stipend), England and the Netherlands in 1923 (Swedish Journalists' Association stipend), and France, Italy, and Spain in 1930, as well as other international study trips. Hobby: Art.",
    "structured": {
        "@context": "https://schema.org",
        "@type": "Person",
        "name": "Johan Edvard Albin Bolmstedt",
        "jobTitle": "Editor",
        "birthDate": "1882-07-20",
        "birthPlace": "Eslöv, Sweden",
        "parents": [
            {
                "@type": "Person",
                "name": "C E B"
            },
            {
                "@type": "Person",
                "name": "Anna Hallgren"
            }
        ],
        "spouse": {
            "@type": "Person",
            "name": "Signe Lindberg"
        },
        "education": [
            {
                "@type": "EducationalOrganization",
                "name": "Eslövs Elementary School",
                "startDate": "1892",
                "endDate": "1896"
            }
        ],
        "worksFor": [
            {
                "@type": "Organization",
                "name": "Skåningen"
            },
            {
                "@type": "Organization",
                "name": "Eslövs Tidning",
                "startDate": "1897",
                "endDate": "1902"
            },
            {
                "@type": "Organization",
                "name": "Swedish Telegraph Agency",
                "department": "Malmö Branch",
                "startDate": "1902",
                "endDate": "1906"
            },
            {
                "@type": "Organization",
                "name": "Kristianstads Läns Tidning",
                "position": "Editor and Secretary",
                "startDate": "1906",
                "endDate": "1920"
            },
            {
                "@type": "Organization",
                "name": "Kristianstads Läns Veckoblad",
                "position": "Editor and Publisher",
                "startDate": "1910",
                "endDate": "1920"
            },
            {
                "@type": "Organization",
                "name": "Swedish Hantverkstidning",
                "position": "Editor",
                "startDate": "...",
                "endDate": "..."
            },
            {
                "@type": "Organization",
                "name": "Skånes Köpmannablad",
                "position": "Editor",
                "startDate": "1920",
                "endDate": "1936"
            },
            {
                "@type": "Organization",
                "name": "Handelsbladet",
                "position": "Editor and Publisher",
                "startDate": "1936"
            },
            {
                "@type": "Organization",
                "name": "South Swedish Furniture Dealers' Association",
                "position": [
                    "Agent",
                    "Secretary",
                    "Cash Manager"
                ],
                "startDate": "1939"
            }
        ],
        "memberOf": [
            {
                "@type": "Organization",
                "name": "Public Club",
                "position": "Vice Chairman",
                "region": "Southern District"
            },
            {
                "@type": "Organization",
                "name": "South Swedish Newspapermen's Sick Fund",
                "position": "Chairman"
            }
        ],
        "publication": [
            "Memoirs",
            "Writings on genealogical and historical topics"
        ],
        "travel": [
            {
                "@type": "Trip",
                "name": "Denmark",
                "startDate": "1912"
            },
            {
                "@type": "Trip",
                "name": "Germany",
                "startDate": "1912"
            },
            {
                "@type": "Trip",
                "name": "Austria",
                "startDate": "1912"
            },
            {
                "@type": "Trip",
                "name": "England",
                "startDate": "1923"
            },
            {
                "@type": "Trip",
                "name": "Netherlands",
                "startDate": "1923"
            },
            {
                "@type": "Trip",
                "name": "France",
                "startDate": "1930"
            },
            {
                "@type": "Trip",
                "name": "Italy",
                "startDate": "1930"
            },
            {
                "@type": "Trip",
                "name": "Spain",
                "startDate": "1930"
            }
        ],
        "hobby": "Art"
    },
    "occupations": {
        "career": [
            {
                "occupational_title": "Editor",
                "workplace": "Skåningen, Eslövs Tidning",
                "industry": "Media",
                "start_date": "1897/1897"
            },
            {
                "occupational_title": "Editor",
                "workplace": "Swedish Telegraph Agency (Malmö branch)",
                "industry": "Media",
                "start_date": "1902/1902"
            },
            {
                "occupational_title": "Editor, Secretary",
                "workplace": "Kristianstads Läns Tidning",
                "industry": "Media",
                "start_date": "1906/1906"
            },
            {
                "occupational_title": "Editor, Publisher",
                "workplace": "Krstds Läns Veckoblad",
                "industry": "Media",
                "start_date": "1910/1910"
            },
            {
                "occupational_title": "Editor",
                "workplace": "Swedish Hantverkstidning",
                "industry": "Media",
                "start_date": "Unknown"
            },
            {
                "occupational_title": "Editor",
                "workplace": "Skånes Köpmannablad",
                "industry": "Media",
                "start_date": "1920/1920"
            },
            {
                "occupational_title": "Editor, Publisher",
                "workplace": "Handelsbladet",
                "industry": "Media",
                "start_date": "1936/1936"
            },
            {
                "occupational_title": "Agent, Secretary, Cash Manager",
                "workplace": "South Swedish Furniture Dealers' Association",
                "industry": "Trade",
                "start_date": "1939/1939"
            }
        ]
    }
}