{
    "original": "DAHLIN, Sven Peder Anton, Bankdirektör, Karlstad, f 14/4 86 av folksk.lär Sven D o Hanna Ohlsson, gm Elna Wennerstrand. Studex 05, kansliex 07. Anst å kont i Sthlm 05, e.o. bokh AB Sthlms hdlsbk 06, Sk hdlsbkn 07—18, led o ass i bkinsp 07—19, byråinsp i bk- o fondinsp 20, led o 1. byråinsp där 21, sparbksinsp o ch f sparbksinsp 29—34, vkst dir f Wermlands ensk bk AB sed. 34, bitr i utredn ang vissa sparbks inställda betaln 29. Ordf i Karlst stdsflm, landst.m i Värml län. Styr.led Sv Bankfrn, AB Karlst mek werkst, Munksjö AB, Lagamilis AB, Åmotfors Pappersbruks AB, Bäckhammars AB, AB Rottneros Bruk mfl. RNO, KVO2kl.",
    "translated": "DAHLIN, Sven Peder Anton, Bank Director, Karlstad, b. 14/4 1886, son of elementary school teacher Sven D and Hanna Ohlsson, married to Elna Wennerstrand. Completed secondary school in 1905, completed clerkship in 1907. Employed at a bank in Stockholm from 1905, temporary accountant at AB Stockholm's commercial court in 1906, commercial court clerk from 1907-1918, member and assistant at the bank inspection from 1907-1919, bureau inspector at the banking and stock inspection from 1920, member and first bureau inspector there from 1921, savings bank inspector and chief savings bank inspector from 1929-1934, deputy director of Wermlands Enskilda Bank AB since 1934, assistant in investigations regarding certain savings bank suspended payments in 1929. Chairman of the Karlstad City Film Board, county commissioner of Värmland county. Board member of Swedish Bankfrn, AB Karlstad Mechanical Workshop, Munksjö AB, Lagamilis AB, Åmotfors Pulp Mill AB, Bäckhammars AB, AB Rottneros Bruk, among others. Awarded Royal Order of the North Star, 2nd class, and the Order of Vasa, 2nd class.",
    "structured": {
        "@context": "https://schema.org",
        "@type": "Person",
        "name": "Sven Peder Anton Dahlin",
        "birthDate": "1886-04-14",
        "birthPlace": "Karlstad, Sweden",
        "father": {
            "@type": "Person",
            "name": "Sven D"
        },
        "mother": {
            "@type": "Person",
            "name": "Hanna Ohlsson"
        },
        "spouse": {
            "@type": "Person",
            "name": "Elna Wennerstrand"
        },
        "education": {
            "@type": "EducationalOccupationalCredential",
            "credentialCategory": "SecondarySchool",
            "startDate": "1905",
            "endDate": "1905"
        },
        "occupation": [
            {
                "@type": "OrganizationRole",
                "title": "Bank Director",
                "namedPosition": "Bankdirektör",
                "startDate": "1905",
                "endDate": "1934",
                "description": "Employed at a bank in Stockholm from 1905, temporary accountant at AB Stockholm's commercial court in 1906, commercial court clerk from 1907-1918, member and assistant at the bank inspection from 1907-1919, bureau inspector at the banking and stock inspection from 1920, member and 1st bureau inspector there from 1921, savings bank inspector and chief savings bank inspector from 1929-1934, deputy director of Wermlands Enskilda Bank AB since 1934"
            }
        ],
        "organization": [
            {
                "@type": "Organization",
                "name": "Wermlands Enskilda Bank AB"
            },
            {
                "@type": "Organization",
                "name": "AB Stockholm's Commercial Court"
            },
            {
                "@type": "Organization",
                "name": "Sv Bankfrn"
            },
            {
                "@type": "Organization",
                "name": "AB Karlstad Mechanical Workshop"
            },
            {
                "@type": "Organization",
                "name": "Munksjö AB"
            },
            {
                "@type": "Organization",
                "name": "Lagamilis AB"
            },
            {
                "@type": "Organization",
                "name": "Åmotfors Pulp Mill AB"
            },
            {
                "@type": "Organization",
                "name": "Bäckhammars AB"
            },
            {
                "@type": "Organization",
                "name": "AB Rottneros Bruk"
            }
        ],
        "memberOf": [
            {
                "@type": "Organization",
                "name": "Karlstad City Film Board"
            },
            {
                "@type": "Organization",
                "name": "Värmland County"
            }
        ],
        "awards": [
            {
                "@type": "Order",
                "name": "Royal Order of the North Star",
                "category": "RNO",
                "awardDate": "UNKNOWN"
            },
            {
                "@type": "Order",
                "name": "Order of Vasa",
                "category": "KVO2kl",
                "awardDate": "UNKNOWN"
            }
        ]
    },
    "occupations": {
        "career": [
            {
                "occupational_title": "Temporary Accountant",
                "workplace": "AB Stockholm's Commercial Court",
                "industry": "Banking",
                "start_date": "1906"
            },
            {
                "occupational_title": "Commercial Court Clerk",
                "workplace": "AB Stockholm's Commercial Court",
                "industry": "Banking",
                "start_date": "1907"
            },
            {
                "occupational_title": "Member and Assistant at Bank Inspection",
                "workplace": "Unknown",
                "industry": "Banking",
                "start_date": "1907"
            },
            {
                "occupational_title": "Bureau Inspector at Banking and Stock Inspection",
                "workplace": "Unknown",
                "industry": "Banking",
                "start_date": "1920"
            },
            {
                "occupational_title": "Member and First Bureau Inspector at Banking and Stock Inspection",
                "workplace": "Unknown",
                "industry": "Banking",
                "start_date": "1921"
            },
            {
                "occupational_title": "Savings Bank Inspector and Chief Savings Bank Inspector",
                "workplace": "Unknown",
                "industry": "Banking",
                "start_date": "1929"
            },
            {
                "occupational_title": "Deputy Director",
                "workplace": "Wermlands Enskilda Bank AB",
                "industry": "Banking",
                "start_date": "1934"
            }
        ]
    }
}