{
    "original": "EKLUND, Johannes L:son (Johan Jonas), Direktör, Stockholm, f Eslöv 2/12 78 av rust-håll L Andersson o h h, gm Sigrid Hammarstrand. Hdls- o språkstud Engl, Frankr o Tyskl, Gbgs hdlsinst :s forts.kurs. Vkst dir AB Silvanders sed. 12. Ordf Drottninggatans Frn sed. 29, Sthlms Herrekip.frb 32—37, Sthlms Detaljistfrb sed. 36, flm Sthlms Hdlskamm sed. 36, dess repr i Inst f bekämp av mutor p bestickn sed. 38, led Hdlns arb.giv.org :s öv.styr sed. 36, av Centr krigskonj.skattenmcln sed. 40, av hdlsdeleg t Engl 39, styr.led Brand-försäkr.AB Tor o Frn Sthlms Landstorms-kamr. RNO, RVO, OffFrd’A.",
    "translated": "EKLUND, Johannes L:son (Johan Jonas), Director, Stockholm, b. Eslöv on December 2, 1878, son of farmer L Andersson and his wife. Married to Sigrid Hammarstrand. Studied commerce and languages in England, France, and Germany, followed by a further course at Gothenburg Commercial Institute. Deputy director of AB Silvanders since 1912. Chairman of Drottninggatan's Association since 1929, Stockholm's Gentlemen's Tailoring Association from 1932 to 1937, Stockholm's Retailers Association since 1936, and Stockholm's Chamber of Commerce from 1936. Representative of the Institute for Combating Bribery and Corruption since 1938. Member of the Employers' Organization's executive board since 1936, the Central War Economic Tax Council since 1940, and the trade delegation to England in 1939. Board member of the Fire Insurance Company AB Tor and the Stockholm Landstorm Association. Awarded Royal Order of the North Star, Royal Order of Vasa, and Officer of the French Order of Agricultural Merit.",
    "structured": {
        "@context": "https://schema.org",
        "@type": "Person",
        "givenName": "Johannes",
        "additionalName": "L:son",
        "familyName": "Eklund",
        "name": "Johannes L:son Eklund",
        "description": "Director, Stockholm",
        "birthDate": "1878-12-02",
        "birthPlace": "Eslöv",
        "nationality": "Swedish",
        "spouse": {
            "@type": "Person",
            "name": "Sigrid Hammarstrand"
        },
        "education": {
            "@type": "EducationalOrganization",
            "name": "Gothenburg Commercial Institute"
        },
        "jobTitle": [
            "Deputy Director of AB Silvanders",
            "Chairman of Drottninggatan's Association",
            "Chairman of Stockholm's Gentlemen's Tailoring Association",
            "Chairman of Stockholm's Retailers Association",
            "Representative of the Institute for Combating Bribery and Corruption",
            "Member of the Employers' Organization's Executive Board",
            "Member of the Central War Economic Tax Council",
            "Board Member of the Fire Insurance Company AB Tor",
            "Board Member of the Stockholm Landstorm Association"
        ],
        "memberOf": [
            {
                "@type": "Organization",
                "name": "Stockholm's Chamber of Commerce"
            },
            {
                "@type": "Organization",
                "name": "Institute for Combating Bribery and Corruption"
            }
        ],
        "award": [
            {
                "@type": "Order",
                "name": "Royal Order of the North Star"
            },
            {
                "@type": "Order",
                "name": "Royal Order of Vasa"
            },
            {
                "@type": "Order",
                "name": "French Order of Agricultural Merit",
                "description": "Officer"
            }
        ]
    },
    "occupations": {
        "career": [
            {
                "occupational_title": "Deputy Director",
                "workplace": "AB Silvanders",
                "industry": "Unknown",
                "start_date": "1912"
            },
            {
                "occupational_title": "Chairman",
                "workplace": "Drottninggatan's Association",
                "industry": "Unknown",
                "start_date": "1929"
            },
            {
                "occupational_title": "Chairman",
                "workplace": "Stockholm's Gentlemen's Tailoring Association",
                "industry": "Unknown",
                "start_date": "1932"
            },
            {
                "occupational_title": "Chairman",
                "workplace": "Stockholm's Retailers Association",
                "industry": "Unknown",
                "start_date": "1936"
            },
            {
                "occupational_title": "Representative",
                "workplace": "Institute for Combating Bribery and Corruption",
                "industry": "Unknown",
                "start_date": "1938"
            },
            {
                "occupational_title": "Member",
                "workplace": "Employers' Organization's Executive Board",
                "industry": "Unknown",
                "start_date": "1936"
            },
            {
                "occupational_title": "Member",
                "workplace": "Central War Economic Tax Council",
                "industry": "Unknown",
                "start_date": "1940"
            },
            {
                "occupational_title": "Member",
                "workplace": "Trade Delegation to England",
                "industry": "Unknown",
                "start_date": "1939"
            },
            {
                "occupational_title": "Board Member",
                "workplace": "Fire Insurance Company AB Tor",
                "industry": "Unknown",
                "start_date": "Unknown"
            },
            {
                "occupational_title": "Board Member",
                "workplace": "Stockholm Landstorm Association",
                "industry": "Unknown",
                "start_date": "Unknown"
            }
        ]
    }
}