{
    "original": "BRINCK, Seth Olof Edvard, Skeppsmäklare, Stockholm, f Avesta 14/3 94 av kamr E A Erikson o Thérese Brinck, gm Margareta Broberg. Västerås lärov, Schartaus hdlsinst m stora utr.stip 12, stud i Oxford. Prakt å sjö-fartskont London o Hmbrg 12—14, anst Rederi AB Nordstjernan Sthlm o chef för befrakta.-avd Sandström Stranne &amp; Co AB Gbg 14—16, kont.ch skeppsmäkl.fma H N Hartmark &amp; Co AB Haugesund, Norge, 17—19, ch f skeppsmäkl.fma AB Emil Bredenberg Sundsvall 19 —22, kont.ch o styr.led skeppsmäkl.fma Kristensen Ltd AB Sthlm 22—40, dir i Sven Salén AB, skeppsred o skeppsmäkl sed. 40. LedSthlms stads komm av år 1940 f omorg av hdlsunderv i Sthlm. Styr.led Sven Salén AB o fi rederiföretag. V. ordf Frn Sv:s Flottas Sthlmsavd, v. ordf Sällsk De Fattigas Vänner, sekr Frn 1894 års män, initiativtagare o rektor f Frn Sv :s Flottas sjöfartsskola, ordf Mercuri-Schartauanerna 37—40. EmmeryGM 44. Av trycket: Handbok i sjöfartsräkn. Stort intresse för ungd yrkesutbildning.",
    "translated": "BRINCK, Seth Olof Edvard, Shipbroker, Stockholm, b. Avesta 14/3 1894 to merchant E A Erikson and Thérese Brinck, m. Margareta Broberg. Västerås high school, Schartau's commercial institute with a major scholarship in 1912, studied in Oxford. Practical experience at shipping offices in London and Hamburg from 1912 to 1914, employed at Rederi AB Nordstjernan in Stockholm and head of the chartering department at Sandström Stranne &amp; Co AB in Gothenburg from 1914 to 1916, branch manager at shipbroking firm H N Hartmark &amp; Co AB in Haugesund, Norway, from 1917 to 1919, managing director at shipbroking firm AB Emil Bredenberg in Sundsvall from 1919 to 1922, branch manager and board member at shipbroking firm Kristensen Ltd AB in Stockholm from 1922 to 1940, director at Sven Salén AB, shipping company and shipbroking since 1940. Member of Stockholm City Council since 1940, appointed by the commercial education in Stockholm. Board member of Sven Salén AB and other shipping companies. Vice chairman of the Stockholm division of the Swedish Navy's Association, vice chairman of the Society of Friends of the Poor, secretary for the class of 1894, initiator and principal of the Swedish Navy's maritime school, chairman of Mercuri-Schartauanerna from 1937 to 1940. Member of the Masonic lodge. Passed away in 1944. Published: Handbook in maritime calculations. Great interest in vocational training for young people.",
    "structured": {
        "@context": "https://schema.org",
        "@type": "Person",
        "name": "Seth Olof Edvard Brinck",
        "givenName": "Seth Olof Edvard",
        "familyName": "Brinck",
        "gender": "Male",
        "birthDate": "1894-03-14",
        "birthPlace": "Avesta, Sweden",
        "deathDate": "1944",
        "nationality": "Swedish",
        "description": "Shipbroker",
        "jobTitle": "Shipbroker",
        "address": {
            "@type": "PostalAddress",
            "addressLocality": "Stockholm",
            "addressCountry": "Sweden"
        },
        "parents": [
            {
                "@type": "Person",
                "name": "E A Erikson",
                "description": "Merchant"
            },
            {
                "@type": "Person",
                "name": "Thérese Brinck"
            }
        ],
        "spouse": {
            "@type": "Person",
            "name": "Margareta Broberg"
        },
        "education": [
            {
                "@type": "EducationalOrganization",
                "name": "Västerås High School"
            },
            {
                "@type": "EducationalOrganization",
                "name": "Schartau's Commercial Institute",
                "startDate": "1912"
            },
            {
                "@type": "EducationalOrganization",
                "name": "University of Oxford"
            }
        ],
        "workExperience": [
            {
                "@type": "Organization",
                "name": "Shipping Office, London",
                "startDate": "1912",
                "endDate": "1914"
            },
            {
                "@type": "Organization",
                "name": "Shipping Office, Hamburg",
                "startDate": "1912",
                "endDate": "1914"
            },
            {
                "@type": "Organization",
                "name": "Rederi AB Nordstjernan",
                "startDate": "1914",
                "endDate": "1916"
            },
            {
                "@type": "Organization",
                "name": "Sandström Stranne & Co AB",
                "description": "Head of Chartering Department",
                "address": {
                    "@type": "PostalAddress",
                    "addressLocality": "Gothenburg",
                    "addressCountry": "Sweden"
                },
                "startDate": "1914",
                "endDate": "1916"
            },
            {
                "@type": "Organization",
                "name": "H N Hartmark & Co AB",
                "description": "Branch Manager",
                "address": {
                    "@type": "PostalAddress",
                    "addressLocality": "Haugesund",
                    "addressCountry": "Norway"
                },
                "startDate": "1917",
                "endDate": "1919"
            },
            {
                "@type": "Organization",
                "name": "AB Emil Bredenberg",
                "description": "Managing Director",
                "address": {
                    "@type": "PostalAddress",
                    "addressLocality": "Sundsvall",
                    "addressCountry": "Sweden"
                },
                "startDate": "1919",
                "endDate": "1922"
            },
            {
                "@type": "Organization",
                "name": "Kristensen Ltd AB",
                "description": "Branch Manager and Board Member",
                "address": {
                    "@type": "PostalAddress",
                    "addressLocality": "Stockholm",
                    "addressCountry": "Sweden"
                },
                "startDate": "1922",
                "endDate": "1940"
            },
            {
                "@type": "Organization",
                "name": "Sven Salén AB",
                "description": "Director",
                "address": {
                    "@type": "PostalAddress",
                    "addressCountry": "Sweden"
                },
                "startDate": "1940"
            }
        ],
        "memberOf": [
            {
                "@type": "Organization",
                "name": "Stockholm City Council",
                "startDate": "1940"
            },
            {
                "@type": "Organization",
                "name": "Swedish Navy's Association"
            },
            {
                "@type": "Organization",
                "name": "Society of Friends of the Poor"
            },
            {
                "@type": "Organization",
                "name": "Mercuri-Schartauanerna",
                "startDate": "1937",
                "endDate": "1940"
            },
            {
                "@type": "Organization",
                "name": "Masonic Lodge"
            }
        ],
        "interests": "Maritime calculations, vocational training"
    },
    "occupations": {
        "career": [
            {
                "occupational_title": "Shipbroker",
                "workplace": "Stockholm",
                "industry": "Shipping",
                "start_date": "1914"
            },
            {
                "occupational_title": "Head of Chartering Department",
                "workplace": "Sandström Stranne & Co AB",
                "industry": "Shipbroking",
                "start_date": "1914"
            },
            {
                "occupational_title": "Branch Manager",
                "workplace": "H N Hartmark & Co AB",
                "industry": "Shipbroking",
                "start_date": "1917"
            },
            {
                "occupational_title": "Managing Director",
                "workplace": "AB Emil Bredenberg",
                "industry": "Shipbroking",
                "start_date": "1919"
            },
            {
                "occupational_title": "Branch Manager and Board Member",
                "workplace": "Kristensen Ltd AB",
                "industry": "Shipbroking",
                "start_date": "1922"
            },
            {
                "occupational_title": "Director",
                "workplace": "Sven Salén AB",
                "industry": "Shipping and Shipbroking",
                "start_date": "1940"
            }
        ]
    }
}