{
    "original": "BIRKE, Håkan Daniel, Civilingenjör, Stockholm, f örkelljunga, Kristianst l, 24/4 04 av nämndem A Danielsson o Ida Nilsson, gm Ulla Ordell. Ex CTI (V o V) 27. Konstr v Allm Betongbyggn.byrån Sthlm 28—29, stud v Polytechn Inst of Brooklyn NY USA 29— 31, konstr v Gibbs &amp; Hill Consulting Engi-neers New York 29—30, v Ambursen Dam Co New York 30—32, bitr ing v Varbergs stads-ing.kont 32—33, v Jönkps byggn.kont 33—34, konstr v Tolls Byggn AB Sthlm sed. 34, ch.-konstr sed. 37. Av trycket: Economical design of waterbearing members of articulated Buttress dams (Proc Am Soc Civ Engrs 33). Led Sv Tekn.frn. Hobbies: Frilufstliv o tennis.",
    "translated": "BIRKE, Håkan Daniel, Civil Engineer, Stockholm, formerly Örkelljunga, Kristianstad County, born on April 24, 1904, son of juryman A Danielsson and Ida Nilsson, married to Ulla Ordell. Former employee of CTI (V and V) from 1927. Worked as a construction engineer at the General Concrete Construction Office in Stockholm from 1928 to 1929, studied at the Polytechnic Institute of Brooklyn, NY, USA from 1929 to 1931, served as a construction engineer at Gibbs & Hill Consulting Engineers in New York from 1929 to 1930, worked for Ambursen Dam Co in New York from 1930 to 1932. Assisted at the engineering office of Varberg city from 1932 to 1933, worked at the building office in Jönköping from 1933 to 1934, employed as a construction engineer at Tolls Construction AB in Stockholm since 1934, promoted to chief construction engineer in 1937. Published: \"Economical design of waterbearing members of articulated Buttress dams\" (Proceedings of the American Society of Civil Engineers, 1933). Member of the Swedish Engineering Society. Hobbies: Outdoor activities and tennis.",
    "structured": {
        "@context": "https://schema.org",
        "@type": "Person",
        "name": "Håkan Daniel Birke",
        "birthDate": "1904-04-24",
        "birthPlace": "Örkelljunga, Kristianstad County",
        "father": {
            "@type": "Person",
            "name": "A Danielsson"
        },
        "mother": {
            "@type": "Person",
            "name": "Ida Nilsson"
        },
        "spouse": {
            "@type": "Person",
            "name": "Ulla Ordell"
        },
        "jobTitle": "Civil Engineer",
        "address": {
            "@type": "PostalAddress",
            "addressLocality": "Stockholm"
        },
        "formerEmployeeOf": {
            "@type": "Organization",
            "name": "CTI"
        },
        "employmentHistory": [
            {
                "@type": "Organization",
                "name": "General Concrete Construction Office",
                "jobTitle": "Construction Engineer",
                "startDate": "1928",
                "endDate": "1929"
            },
            {
                "@type": "Organization",
                "name": "Polytechnic Institute of Brooklyn",
                "jobTitle": "Student",
                "startDate": "1929",
                "endDate": "1931"
            },
            {
                "@type": "Organization",
                "name": "Gibbs & Hill Consulting Engineers",
                "jobTitle": "Construction Engineer",
                "startDate": "1929",
                "endDate": "1930"
            },
            {
                "@type": "Organization",
                "name": "Ambursen Dam Co",
                "jobTitle": "Construction Engineer",
                "startDate": "1930",
                "endDate": "1932"
            },
            {
                "@type": "Organization",
                "name": "Varberg City",
                "jobTitle": "Engineering Office Assistant",
                "startDate": "1932",
                "endDate": "1933"
            },
            {
                "@type": "Organization",
                "name": "Jönköping Building Office",
                "jobTitle": "Employee",
                "startDate": "1933",
                "endDate": "1934"
            },
            {
                "@type": "Organization",
                "name": "Tolls Construction AB",
                "jobTitle": "Construction Engineer",
                "startDate": "1934"
            }
        ],
        "publication": {
            "@type": "Article",
            "name": "Economical design of waterbearing members of articulated Buttress dams",
            "publicationDate": "1933",
            "publisher": {
                "@type": "Organization",
                "name": "American Society of Civil Engineers"
            }
        },
        "memberOf": {
            "@type": "Organization",
            "name": "Swedish Engineering Society"
        },
        "hobbies": [
            "Outdoor activities",
            "Tennis"
        ]
    },
    "occupations": {
        "career": [
            {
                "occupational_title": "Civil Engineer",
                "workplace": "CTI (V and V)",
                "industry": "Engineering",
                "start_date": "1927"
            },
            {
                "occupational_title": "Construction Engineer",
                "workplace": "General Concrete Construction Office",
                "industry": "Construction",
                "start_date": "1928"
            },
            {
                "occupational_title": "Student",
                "workplace": "Polytechnic Institute of Brooklyn",
                "industry": "Education",
                "start_date": "1929"
            },
            {
                "occupational_title": "Construction Engineer",
                "workplace": "Gibbs & Hill Consulting Engineers",
                "industry": "Engineering",
                "start_date": "1929"
            },
            {
                "occupational_title": "Construction Engineer",
                "workplace": "Ambursen Dam Co",
                "industry": "Construction",
                "start_date": "1930"
            },
            {
                "occupational_title": "Assistant Engineer",
                "workplace": "Varberg City Engineering Office",
                "industry": "Engineering",
                "start_date": "1932"
            },
            {
                "occupational_title": "Construction Engineer",
                "workplace": "Jönköping Building Office",
                "industry": "Construction",
                "start_date": "1933"
            },
            {
                "occupational_title": "Construction Engineer",
                "workplace": "Tolls Construction AB",
                "industry": "Construction",
                "start_date": "1934"
            },
            {
                "occupational_title": "Chief Construction Engineer",
                "workplace": "Tolls Construction AB",
                "industry": "Construction",
                "start_date": "1937"
            }
        ]
    }
}