{
    "original": "KRANTZ, Carl Teodor, Grosshandlare, Äppelviken, f Rogberga, Jönkps l, 25/10 76 av dist.korpral G K o Matilda Freijd, gm Ester Kjellin. Livg t häst uoffsk, hdls-, språk- o tekn sk. Anst Livg t häst 95—99, Zacco, Bruhn &amp; Co o AB Zacco &amp; Co 99—11,’ eg fma Zacco &amp; Co Eftr, maskinaff, sed. 11. Kyrko-flm, kyrkoråd, rev, styr.led Mälargårdens o Ribbingebäeks alkoholistanst, styr.led Skär-viks, Tallåsens, Högas o Solåkers statsunderst hem f flick, styr.led Boxtorps pojkhem o Elsa Borgs-hemmen. Styr.led KFUM, Lutherska miss.frn i Sthlm, Sthlms Stadsmission, Hemmet Vård o Arbete mfl. Borgare. Aff.res Sv, Norge, Danm, Tyskl. RVO. Hobbies: Hästar, skidor, arbetet. Zacco &amp; Co Eftr gr 70 und fma Zacco Bruhn &amp; Co, ombild sen t AB Zacco &amp; Co, övert 11 av K.",
    "translated": "KRANTZ, Carl Teodor, Merchant, Äppelviken, b. Rogberga, Jönköping, 25/10 1876, son of district corporal G K and Matilda Freijd, married to Ester Kjellin. Formerly serving as a cavalry officer, he has received training in commerce, languages, and technology. Employed by the Royal Cavalry Regiment from 1895 to 1899, Zacco, Bruhn & Co and AB Zacco & Co from 1899 to 1911, and has since worked as the sole proprietor of Zacco & Co Eftr, specializing in machinery sales. Participated in church activities, served on the church council, and has been on boards of directors for Mälargården and Ribbingebäeks alcohol rehabilitation centers, as well as for Skärviks, Tallåsens, Högas, and Solåkers state-funded homes for girls. Also served on the board of directors for Boxtorps boys' home and Elsa Borg's homes. Active on the boards of directors for KFUM, Lutheran Mission in Stockholm, Stockholm City Mission, and Home Care and Employment, among others. Honorary Citizen. Has traveled on business to Sweden, Norway, Denmark, and Germany. Received the Royal Order of Vasa. Hobbies include horses, skiing, and work. Zacco & Co Eftr was established in 1870 under the name Zacco Bruhn & Co, and later reorganized as AB Zacco & Co in 1911, which he took over in the same year.",
    "structured": {
        "@context": "http://schema.org",
        "@type": "Person",
        "name": "Carl Teodor Krantz",
        "birthDate": "1876-10-25",
        "birthPlace": "Rogberga, Jönköping",
        "nationality": "Swedish",
        "occupation": "Merchant",
        "address": {
            "@type": "PostalAddress",
            "addressLocality": "Äppelviken"
        },
        "parents": [
            {
                "@type": "Person",
                "name": "G K",
                "roleName": "Father",
                "jobTitle": "District corporal"
            },
            {
                "@type": "Person",
                "name": "Matilda Freijd",
                "roleName": "Mother"
            }
        ],
        "spouse": [
            {
                "@type": "Person",
                "name": "Ester Kjellin"
            }
        ],
        "memberOf": [
            {
                "@type": "Organization",
                "name": "Royal Cavalry Regiment",
                "startDate": "1895-01-01",
                "endDate": "1899-12-31",
                "jobTitle": "Cavalry officer"
            },
            {
                "@type": "Organization",
                "name": "Zacco, Bruhn & Co",
                "startDate": "1899-01-01",
                "endDate": "1911-12-31",
                "jobTitle": "Employee"
            },
            {
                "@type": "Organization",
                "name": "AB Zacco & Co",
                "startDate": "1899-01-01",
                "endDate": "1911-12-31",
                "jobTitle": "Employee"
            },
            {
                "@type": "Organization",
                "name": "Zacco & Co Eftr",
                "startDate": "1911-01-01",
                "jobTitle": "Sole proprietor"
            },
            {
                "@type": "Organization",
                "name": "Mälargården",
                "roleName": "Board of directors"
            },
            {
                "@type": "Organization",
                "name": "Ribbingebäeks",
                "roleName": "Board of directors"
            },
            {
                "@type": "Organization",
                "name": "Skärviks",
                "roleName": "Board of directors"
            },
            {
                "@type": "Organization",
                "name": "Tallåsens",
                "roleName": "Board of directors"
            },
            {
                "@type": "Organization",
                "name": "Högas",
                "roleName": "Board of directors"
            },
            {
                "@type": "Organization",
                "name": "Solåkers",
                "roleName": "Board of directors"
            },
            {
                "@type": "Organization",
                "name": "Boxtorps",
                "roleName": "Board of directors"
            },
            {
                "@type": "Organization",
                "name": "Elsa Borg's",
                "roleName": "Board of directors"
            },
            {
                "@type": "Organization",
                "name": "KFUM",
                "roleName": "Board of directors"
            },
            {
                "@type": "Organization",
                "name": "Lutheran Mission in Stockholm",
                "roleName": "Board of directors"
            },
            {
                "@type": "Organization",
                "name": "Stockholm City Mission",
                "roleName": "Board of directors"
            },
            {
                "@type": "Organization",
                "name": "Home Care and Employment",
                "roleName": "Board of directors"
            }
        ],
        "honoraryTitles": "Honorary Citizen",
        "hasOccupation": {
            "@type": "Occupation",
            "name": "Merchant"
        },
        "hasCredential": {
            "@type": "Role",
            "name": "Royal Order of Vasa"
        },
        "hasSkill": [
            {
                "@type": "Skill",
                "name": "Horses"
            },
            {
                "@type": "Skill",
                "name": "Skiing"
            },
            {
                "@type": "Skill",
                "name": "Work"
            }
        ],
        "hasEducation": [
            {
                "@type": "EducationEvent",
                "name": "Commerce"
            },
            {
                "@type": "EducationEvent",
                "name": "Languages"
            },
            {
                "@type": "EducationEvent",
                "name": "Technology"
            }
        ],
        "hasTravelled": [
            {
                "@type": "Country",
                "name": "Sweden"
            },
            {
                "@type": "Country",
                "name": "Norway"
            },
            {
                "@type": "Country",
                "name": "Denmark"
            },
            {
                "@type": "Country",
                "name": "Germany"
            }
        ]
    },
    "occupations": {
        "career": [
            {
                "occupational_title": "District Corporal",
                "workplace": "Royal Cavalry Regiment",
                "industry": "Military",
                "start_date": "1895"
            },
            {
                "occupational_title": "Merchant",
                "workplace": "Zacco, Bruhn & Co",
                "industry": "Commerce",
                "start_date": "1899"
            },
            {
                "occupational_title": "Merchant",
                "workplace": "AB Zacco & Co",
                "industry": "Commerce",
                "start_date": "1899"
            },
            {
                "occupational_title": "Merchant",
                "workplace": "Zacco & Co Eftr",
                "industry": "Machinery Sales",
                "start_date": "1911"
            }
        ]
    }
}