{
    "original": "LILJEBLAD, Karl Ragnar, Civilingenjör, Teknisk direktör, Västerås, f Nrkp 25/9 85 av kass F L o Tekla Svanström, gm Gurli Bartholdi. KTH 07. Ing Graham Brothers Sthlm 08—10 o 13—14, anst Syd- o Nordamer 11—12, verkst.ch Nya foren el AB Ludvika 14—18, ch ASEA tillverkn.avd sed. 18. Stdsflm 27—38. Av trycket: Ett 50-t avhandl o upps av tekn, fysikal o ekon inneh samt tidskr.art i relig, filos, rashyg mfl ämn. KVO, RNO, LVA,",
    "translated": "LILJEBLAD, Karl Ragnar, Civil Engineer, Technical Director, Västerås, born on September 25th, 1885 to father F L and mother Tekla Svanström, married to Gurli Bartholdi. Graduated from KTH in 1907. Worked at Graham Brothers Stockholm from 1908 to 1910 and 1913 to 1914, employed in South and North America from 1911 to 1912. Became the chief engineer at Nya Foren AB Ludvika from 1914 to 1918, and then joined ASEA manufacturing department. Resided in Stockholm from 1927 to 1938. Has published around 50 dissertations and papers on technical, physical, and economic subjects, as well as articles in various fields including religion, philosophy, and racial hygiene. Member of the Royal Swedish Academy of Engineering Sciences (KVO), The Royal Society of Sciences in Uppsala (RNO), The Royal Society of Sciences in Letterkenny (LVA).",
    "structured": {
        "@context": "https://schema.org",
        "@type": "Person",
        "name": "Karl Ragnar Liljeblad",
        "birthDate": "1885-09-25",
        "birthPlace": "Västerås",
        "nationality": "Swedish",
        "father": {
            "@type": "Person",
            "name": "F L Liljeblad"
        },
        "mother": {
            "@type": "Person",
            "name": "Tekla Svanström"
        },
        "spouse": {
            "@type": "Person",
            "name": "Gurli Bartholdi"
        },
        "education": {
            "@type": "EducationalOccupationalCredential",
            "credentialCategory": "Civil Engineering",
            "educationalLevel": "Bachelor's Degree",
            "educationalRole": "Civil Engineer",
            "awardingInstitution": {
                "@type": "Organization",
                "name": "Royal Institute of Technology (KTH)"
            },
            "startDate": "1907",
            "endDate": "1907"
        },
        "worksFor": {
            "@type": "Organization",
            "name": "ASEA"
        },
        "jobTitle": "Technical Director",
        "workLocation": "Västerås",
        "hasOccupation": {
            "@type": "Occupation",
            "name": "Civil Engineer"
        },
        "hasMembership": [
            {
                "@type": "Organization",
                "name": "Royal Swedish Academy of Engineering Sciences (KVO)"
            },
            {
                "@type": "Organization",
                "name": "The Royal Society of Sciences in Uppsala (RNO)"
            },
            {
                "@type": "Organization",
                "name": "The Royal Society of Sciences in Letterkenny (LVA)"
            }
        ],
        "publication": [
            {
                "@type": "PublicationEvent",
                "name": "Doctoral Dissertation",
                "location": "Stockholm",
                "startDate": "1927",
                "endDate": "1938"
            },
            {
                "@type": "PublicationEvent",
                "name": "Technical Papers",
                "location": "Stockholm",
                "startDate": "1927",
                "endDate": "1938"
            },
            {
                "@type": "PublicationEvent",
                "name": "Articles",
                "location": "Stockholm",
                "startDate": "1927",
                "endDate": "1938"
            }
        ]
    },
    "occupations": {
        "career": [
            {
                "occupational_title": "Civil Engineer",
                "workplace": "Graham Brothers",
                "industry": "Engineering",
                "start_date": "1908"
            },
            {
                "occupational_title": "Civil Engineer",
                "workplace": "Graham Brothers",
                "industry": "Engineering",
                "start_date": "1913"
            },
            {
                "occupational_title": "Employee",
                "workplace": "South and North America",
                "industry": "Various",
                "start_date": "1911"
            },
            {
                "occupational_title": "Chief Engineer",
                "workplace": "Nya Foren AB Ludvika",
                "industry": "Manufacturing",
                "start_date": "1914"
            },
            {
                "occupational_title": "Manufacturing Department",
                "workplace": "ASEA",
                "industry": "Manufacturing",
                "start_date": "1918"
            },
            {
                "occupational_title": "Technical Director",
                "workplace": "Västerås",
                "industry": "Unknown",
                "start_date": null
            },
            {
                "occupational_title": "Unknown",
                "workplace": "Stockholm",
                "industry": "Unknown",
                "start_date": "1927"
            }
        ]
    }
}