{
    "original": "DUHS, Sven Folke, Kamrer, Stockholm, f Molkom 29/6 14 av konstnär G W D o Karin Laurell, gm Birgit Lundin. Realex Krist 30, hdlskurs Bar-Lock-Inst 31, Sthlms borg.sk o Sthlms stds hdls- o yrkessk (eng, ty, fr, sp, ry språken) 32—43, kurser i bokf, skattelagar, självdekl o matem v Hermods 36. Anst AB B A Hjorth &amp; Co Sthlm sed. 31, först ss kont o korr, sederm ss bokf.ch o sed. 38 ss kamrer. Företagit semesterresor till grannländerna. Medl Sällsk W6. Hobbies: Fotografering o friluftsliv.",
    "translated": "DUHS, Sven Folke, Accountant, Stockholm, born in Molkom on June 29, 1914, to artist G.W.D and Karin Laurell. Married to Birgit Lundin. Graduated from Kristina Realskola in 1930, attended a commercial course at Bar-Lock Institute in 1931. Studied at Stockholm City Business School and Stockholm City Vocational School (English, German, French, Spanish, and Russian languages) from 1932 to 1943. Completed courses in bookkeeping, tax laws, self-assessment, and mathematics at Hermods in 1936. Employed by AB B.A. Hjorth & Co in Stockholm since 1931, initially as a clerk and correspondent, later as an accountant in 1938. Took vacations to neighboring countries. Member of Society W6. Hobbies include photography and outdoor activities.",
    "structured": {
        "@context": "https://schema.org",
        "@type": "Person",
        "name": "Sven Folke DUHS",
        "jobTitle": [
            "Clerk",
            "Correspondent",
            "Accountant"
        ],
        "birthPlace": "Molkom",
        "birthDate": "1914-06-29",
        "parents": {
            "@type": "Person",
            "father": "G.W.D",
            "mother": "Karin Laurell"
        },
        "spouse": "Birgit Lundin",
        "education": [
            {
                "@type": "EducationalOccupationalCredential",
                "educationLevel": "HighSchool",
                "educationalRole": "Graduated",
                "startDate": "1930",
                "endDate": "1930",
                "institution": "Kristina Realskola"
            },
            {
                "@type": "EducationalOccupationalCredential",
                "educationLevel": "Course",
                "educationalRole": "Attended",
                "startDate": "1931",
                "endDate": "1931",
                "institution": "Bar-Lock Institute",
                "description": "Commercial course"
            },
            {
                "@type": "EducationalOccupationalCredential",
                "educationLevel": "BusinessSchool",
                "educationalRole": "Attended",
                "startDate": "1932",
                "endDate": "1943",
                "institution": "Stockholm City Business School",
                "description": "Studied English, German, French, Spanish, and Russian languages"
            },
            {
                "@type": "EducationalOccupationalCredential",
                "educationLevel": "VocationalSchool",
                "educationalRole": "Attended",
                "startDate": "1932",
                "endDate": "1943",
                "institution": "Stockholm City Vocational School",
                "description": "Studied English, German, French, Spanish, and Russian languages"
            },
            {
                "@type": "EducationalOccupationalCredential",
                "educationLevel": "Course",
                "educationalRole": "Completed",
                "startDate": "1936",
                "endDate": "1936",
                "institution": "Hermods",
                "description": "Courses in bookkeeping, tax laws, self-assessment, and mathematics"
            }
        ],
        "worksFor": {
            "@type": "Organization",
            "name": "AB B.A. Hjorth & Co",
            "startDate": "1931"
        },
        "travelHistory": [
            "Neighboring countries"
        ],
        "memberOf": [
            {
                "@type": "Organization",
                "name": "Sällsk W6"
            }
        ],
        "hobbies": [
            "Photography",
            "Outdoor activities"
        ]
    },
    "occupations": {
        "career": [
            {
                "occupational_title": "Clerk",
                "workplace": "AB B.A. Hjorth & Co",
                "industry": "Unspecified",
                "start_date": "1931"
            },
            {
                "occupational_title": "Correspondent",
                "workplace": "AB B.A. Hjorth & Co",
                "industry": "Unspecified",
                "start_date": "1931"
            },
            {
                "occupational_title": "Accountant",
                "workplace": "AB B.A. Hjorth & Co",
                "industry": "Unspecified",
                "start_date": "1938"
            }
        ]
    }
}