{
    "original": "JONSSON, Sven Ejnar, Civilingenjör, Göteborg, f Hsand 27/3 14 av lärov.adj Ejnar J o Karin Hagelbäck. Studex Gbgs H Reallärov, civingex CTH. Anst v Mölnlycke Väfveri AB i Gbg 38—39, v Färg AB International i Gbg sed. 40. fabr.chef där sed. 43. Studieresor i Danm 36, Danm, Tyskl, Tjeckoslov, Ung o Österr 37. Led av Sv Tekn.frn o Tekn Samf i Gbg.",
    "translated": "JONSSON, Sven Ejnar, Civil Engineer, Gothenburg, born in Helsingborg on March 27, 1914, son of high school teacher Ejnar J and Karin Hagelbäck. Graduated from Gothenburg Higher Secondary School, obtained a civil engineering degree from Chalmers University of Technology. Employed at Mölnlycke Väfveri AB in Gothenburg from 1938 to 1939, then at International AB in Gothenburg from 1940. Became the factory manager there in 1943. Went on study trips to Denmark in 1936, Denmark, Germany, Czechoslovakia, Hungary, and Austria in 1937. Member of the Swedish Technical Association and the Technical Society in Gothenburg.",
    "structured": {
        "name": "Sven Ejnar Jonsson",
        "jobTitle": "Civil Engineer",
        "address": {
            "addressLocality": "Gothenburg"
        },
        "birthDate": "1914-03-27",
        "parents": [
            {
                "name": "Ejnar J",
                "jobTitle": "High School Teacher"
            },
            {
                "name": "Karin Hagelbäck"
            }
        ],
        "education": [
            {
                "institution": "Gothenburg Higher Secondary School",
                "degree": "Studex"
            },
            {
                "institution": "Chalmers University of Technology",
                "degree": "Civil Engineering"
            }
        ],
        "employmentHistory": [
            {
                "employer": "Mölnlycke Väfveri AB",
                "jobTitle": "Employee",
                "startDate": "1938-01-01",
                "endDate": "1939-12-31",
                "location": "Gothenburg"
            },
            {
                "employer": "International AB",
                "jobTitle": "Employee",
                "startDate": "1940-01-01",
                "location": "Gothenburg"
            },
            {
                "employer": "International AB",
                "jobTitle": "Factory Manager",
                "startDate": "1943-01-01",
                "location": "Gothenburg"
            }
        ],
        "studyTrips": [
            {
                "destination": "Denmark",
                "year": "1936"
            },
            {
                "destination": "Denmark, Germany, Czechoslovakia, Hungary, Austria",
                "year": "1937"
            }
        ],
        "memberships": [
            "Swedish Technical Association",
            "Technical Society in Gothenburg"
        ]
    },
    "occupations": {
        "career": [
            {
                "occupational_title": "Civil Engineer",
                "workplace": "Mölnlycke Väfveri AB",
                "industry": "Textile",
                "start_date": "1938"
            },
            {
                "occupational_title": "Civil Engineer",
                "workplace": "Färg AB International",
                "industry": "Chemicals",
                "start_date": "1940"
            },
            {
                "occupational_title": "Factory Manager",
                "workplace": "Färg AB International",
                "industry": "Chemicals",
                "start_date": "1943"
            }
        ]
    }
}