{
    "original": "HYLANDER, Hans, Civilingenjör, Stockholm, f Nrkpg 4/3 92 av överlär J H o Fredrika Wallberg, gm Hjördis Fosterud. Studex 11, ex KTH 14, resoffex 14, uljt Uppl inf.reg res 14. Ing AB Zander &amp; Ingeström Sthlm 15, styr.led o v. vkst dir 31, vkst dir sed. 40. Styr.led AB Arctic 23—24, Sv teknol.frn avd f mek 24—26, österskärs villaäg.frn sed. 39, I. 8 offklubb i Sthlm sed. 39. Patent inom värme- 0 kyltekii. Av trycket: Upps i fackpressen, medarb Bonniers konv.lex. PatrGM. HYLÉN, August, Direktör, Kristianstad, f Vedby, Krst l, 18/11 69, gm Bertha Dymling. Vkst dir i AB Aug Hylén, möbler o bosättn.-art mm, Krst o Sölvesborg, grund 96, AB 34. Fd stdsflm. V. styr.ordf i Frn Barnavård, fd ordf i S Sv Möbelhandl.frn, fd v. ordf i S Sv Linoleumhandl.frn. RVO. HYLÉN, Georg Andreas, Direktör, Malmö, f Malmö 19/2 91 av Alb Hylén o Ingrid Torsson. Malmö borgarsk. Anst AB Wilh Sonesson &amp; Co, Malmö, 06—08, Malmö armaturfabr 08—18, AB Torvförsäljn, Malmö, 18—21, ag f AB van Berkels Patent 21—27. Egna föret: Georg Hylén AB, Malmö, m fil i Gbg, Julius Sjögren spec.maskiner AB, Sthlm, m fil i Nrkpg, AB Tegil, Malmö, vkst dir o styr.ordf 1 dessa bol. Resor: Tyskl, Engl, Österr, Tjeckoslov, Holl, Belg, Frankr, Finl, Norge o Danm. Hobbies: Golf, motorsport. HYLÉN, Karl Gunnar August, Bankkamrer, Skänninge, f Forserum, Jkp län, 19/10 94 av handl J A L H o Anna Wetterholm, gm Gun Löfman. Realex 11. Bitr N Vedbo hds dom.-kansli, Tranås, 12—13, bokh AB Möbelind.-komp, T.ås 14, östgötabkn, T.ås 14—16, Motala 16—17, Linköp 17—18, kamr o styr.suppl Mjölby 1&amp;—29, kamr T.ås 29—31, lånekamr Mta 31—32, Skge 32—34, kamr, kont.ch o vkst styr.led där sed. 35. Siffergr o rev Mjölby stads räkensk 24—29, stdsflm Skge sed. 39, ordf pens.nmdn sed. 34, lönenmdn sed. 41, v. ordf brandstyr, kristidsnmdn o fam.bidr.-nmdn sed. 40, led beredn.utsk sed. 39, folksk.-styr sed. 40, ind.komm sed. 41, 2. v. luftsk.ch sed. 42. Kass Ögl högerfrb sed. 31, ordf Skge o N Göstrings högerfrn sed. 33, Skge luftsk.-frn sed. 39, omb Städ försäkr.bol sed. 37. Frimurare, Odd Fellow o dess veter.t. 0 HYLÉN, Senny Arvid Torsten, Arkitekt, Kristianstad, f Krst 14/11 06, gm Kerstin Thermsenius. Medarb i AB Aug Hylén Krst; dela g i S Hylén &amp; Co, Möblerings AB, Sthlm.HYMN, Zerold, Disponent, Kristianstad, f Krstd 2/1 00 av dir A H o Bertha Dymling, gm Lisbeth Sommerfeldt. Realex, Schartau. Anst Myrstedt &amp; Trowall, Sthlm, 19— 21, Aug Hylén 22, Herm Tietz, Hamb, 23, Linoleum Manufact Co, London, 24, åter Aug Hylén 25, disp o styr.led där, eg fma Autom.-verkst i Krstd 26—36. Styr.led S Sv möbel-hdl.frn. Resor: Tyskl 22, 23, Engl, Frankr 24. Frimurare. Hobbies: Tennis, jakt.",
    "translated": "HYLANDER, Hans, Civil Engineer, Stockholm, born in Nyköping on the 4th of March 1892 to Headmaster J.H. and Fredrika Wallberg, married to Hjördis Fosterud. High School Diploma in 1911, graduated from the Royal Institute of Technology in 1914, reserve officer in 1914, served in the Uppland Infantry Regiment from 1914. Joined AB Zander & Ingeström in Stockholm in 1915, served as a board member and vice managing director from 1931, promoted to managing director in 1940. Served as a board member of AB Arctic from 1923-1924, Swedish Technological Society, Mechanical Department from 1924-1926, East Skärs Villa Owners Association from 1939, member of the 8th Officer's Club in Stockholm from 1939. Holds patents in heating and cooling technology. Published in trade press, contributed to Bonnier's Encyclopedia. Member of the Patent Grand Master lodge.\n\nHYLÉN, August, Director, Kristianstad, born in Vedby on the 18th of November 1869, married to Bertha Dymling. Managing director of AB Aug Hylén, furniture and home decor, in Kristianstad and Sölvesborg founded in 1896, joined the board in 1934. Former chairman of the Swedish Child Care Association, former chairman of the Swedish Furniture Retailers Association, former vice chairman of the Swedish Linoleum Retailers Association. Holds the Royal Order of Vasa.\n\nHYLÉN, Georg Andreas, Director, Malmö, born in Malmö on the 19th of February 1891 to Alb Hylén and Ingrid Torsson. Educated in Malmö bourgeoisie. Employed at AB Wilh Sonesson & Co in Malmö from 1906-1908, Malmö Armature Factory from 1908-1918, AB Torvförsäljn in Malmö from 1918-1921, agent for AB van Berkel's Patent from 1921-1927. Own businesses: Georg Hylén AB in Malmö with branch in Gothenburg, Julius Sjögren Special Machinery AB in Stockholm with branch in Norrköping, AB Tegil in Malmö, serving as managing director and chairman of the board in these companies. Traveled to Germany, England, Austria, Czechoslovakia, Holland, Belgium, France, Finland, Norway, and Denmark. Hobbies include golf and motorsport.\n\nHYLÉN, Karl Gunnar August, Bank Official, Skänninge, born in Forserum, Jönköping county, on the 19th of October 1894 to merchant J.A.L.H. and Anna Wetterholm, married to Gun Löfman. Graduated from high school in 1911. Assistant at the district court office in Tranås from 1912-1913, bookkeeper at AB Möbelindustrikompaniet in Tranås in 1914, East Gothland Bank in Tranås from 1914-1916, Motala from 1916-1917, Linköping from 1917-1918, cashier and board deputy at East Gothland Bank in Mjölby from 1920-1929, cashier in Tranås from 1929-1931, loan cashier in Motala from 1931-1932, Skänninge from 1932-1934, cashier, head of accounts department, and board of directors member in Skänninge since 1935. Auditor and revenue inspector for Mjölby municipality from 1924-1929, chairman of the Skänninge Fire Brigade from 1939, chairman of the Pension Committee since 1934, salary committee since 1941, vice chairman of the Fire Brigade, wartime committee, and family support committee since 1940, member of the preparatory committee since 1939, school board since 1940, and industrial committee since 1941, 2nd vice air protection chief since 1942. Cashier of the right-wing Östergötland County Federation since 1931, chairman of the Skänninge and North Göstring County Right-Wing Association since 1933, Skänninge Air Protection Association since 1939, and representative of the Municipal Insurance Company since 1937. Freemason, Odd Fellow, and veteran of both organizations.\n\nHYLÉN, Senny Arvid Torsten, Architect, Kristianstad, born in Kristianstad on the 14th of November 1906, married to Kerstin Thermsenius. Employee at AB Aug Hylén in Kristianstad; co-owner of S Hylén & Co, Furniture AB, in Stockholm.\n\nHYMN, Zerold, Manager, Kristianstad, born in Kristianstad on the 2nd of January 1900 to director A.H. and Bertha Dymling, married to Lisbeth Sommerfeldt. Graduated Realex at Schartau. Employed at Myrstedt & Trowall in Stockholm from 1919-1921, Aug Hylén in 1922, Herm Tietz in Hamburg in 1923, Linoleum Manufact Co in London in 1924, returned to Aug Hylén in 1925, serving as manager and board member, owner of an automatic workshop in Kristianstad from 1926-1936. Board member of the Swedish Furniture Retailers Association. Traveled to Germany in 1922 and 1923, England and France in 1924. Freemason. Hobbies include tennis and hunting.",
    "structured": {
        "HYLANDER": {
            "givenName": "Hans",
            "familyName": "Hylander",
            "jobTitle": "Civil Engineer",
            "birthPlace": "Nyköping",
            "birthDate": "1892-03-04",
            "parents": {
                "father": {
                    "givenName": "J.H.",
                    "familyName": "Hylander"
                },
                "mother": {
                    "givenName": "Fredrika",
                    "familyName": "Wallberg"
                }
            },
            "spouse": {
                "givenName": "Hjördis",
                "familyName": "Fosterud"
            },
            "education": [
                {
                    "schoolName": "Royal Institute of Technology",
                    "degree": "High School Diploma",
                    "endDate": "1911"
                },
                {
                    "schoolName": "KTH",
                    "degree": "Civil Engineering",
                    "endDate": "1914"
                }
            ],
            "career": [
                {
                    "employer": "AB Zander & Ingeström",
                    "position": "Engineer",
                    "startDate": "1915",
                    "endDate": "1940"
                },
                {
                    "employer": "AB Arctic",
                    "position": "Board Member",
                    "startDate": "1923",
                    "endDate": "1924"
                }
            ],
            "patents": [
                {
                    "description": "Heating and cooling technology"
                }
            ],
            "publications": [
                {
                    "publicationName": "Upps i fackpressen"
                },
                {
                    "publicationName": "Bonniers konv.lex"
                }
            ],
            "memberships": [
                {
                    "organizationName": "Patent Grand Master lodge"
                }
            ]
        },
        "HYLÉN": {
            "givenName": "August",
            "familyName": "Hylén",
            "jobTitle": "Director",
            "birthPlace": "Vedby",
            "birthDate": "1869-11-18",
            "spouse": {
                "givenName": "Bertha",
                "familyName": "Dymling"
            },
            "career": [
                {
                    "employer": "AB Aug Hylén",
                    "domain": "Furniture and Home Decor",
                    "locations": [
                        "Kristianstad",
                        "Sölvesborg"
                    ],
                    "startDate": "1896"
                }
            ],
            "memberships": [
                {
                    "organizationName": "Swedish Child Care Association",
                    "positions": [
                        "Chairman"
                    ]
                },
                {
                    "organizationName": "Swedish Furniture Retailers Association",
                    "positions": [
                        "Chairman"
                    ]
                },
                {
                    "organizationName": "Swedish Linoleum Retailers Association",
                    "positions": [
                        "Vice Chairman"
                    ]
                },
                {
                    "organizationName": "Royal Order of Vasa"
                }
            ]
        },
        "HYLÉN_Georg_Andreas": {
            "givenName": "Georg Andreas",
            "familyName": "Hylén",
            "jobTitle": "Director",
            "birthPlace": "Malmö",
            "birthDate": "1891-02-19",
            "parents": {
                "father": {
                    "givenName": "Alb",
                    "familyName": "Hylén"
                },
                "mother": {
                    "givenName": "Ingrid",
                    "familyName": "Torsson"
                }
            },
            "education": [
                {
                    "schoolName": "Malmö Borgarskola"
                }
            ],
            "career": [
                {
                    "employer": "AB Wilh Sonesson & Co",
                    "startDate": "1906",
                    "endDate": "1908"
                },
                {
                    "employer": "Malmö Armature Factory",
                    "startDate": "1908",
                    "endDate": "1918"
                },
                {
                    "employer": "AB Torvförsäljn",
                    "startDate": "1918",
                    "endDate": "1921"
                },
                {
                    "employer": "AB van Berkel's Patent",
                    "startDate": "1921",
                    "endDate": "1927"
                },
                {
                    "employer": "Georg Hylén AB",
                    "locations": [
                        "Malmö",
                        "Gothenburg"
                    ]
                },
                {
                    "employer": "Julius Sjögren Special Machinery AB",
                    "locations": [
                        "Stockholm",
                        "Norrköping"
                    ]
                },
                {
                    "employer": "AB Tegil",
                    "location": "Malmö"
                }
            ],
            "travels": [
                "Germany",
                "England",
                "Austria",
                "Czechoslovakia",
                "Holland",
                "Belgium",
                "France",
                "Finland",
                "Norway",
                "Denmark"
            ],
            "hobbies": [
                "Golf",
                "Motorsport"
            ]
        },
        "HYLÉN_Karl_Gunnar_August": {
            "givenName": "Karl Gunnar August",
            "familyName": "Hylén",
            "jobTitle": "Bank Official",
            "birthPlace": "Forserum, Jönköping",
            "birthDate": "1894-10-19",
            "parents": {
                "father": {
                    "givenName": "J.A.L.H.",
                    "familyName": "Hylén"
                },
                "mother": {
                    "givenName": "Anna",
                    "familyName": "Wetterholm"
                }
            },
            "spouse": {
                "givenName": "Gun",
                "familyName": "Löfman"
            },
            "education": [
                {
                    "schoolName": "Realex"
                }
            ],
            "career": [
                {
                    "employer": "N Vedbo HS District Court Office",
                    "location": "Tranås",
                    "startDate": "1912",
                    "endDate": "1913"
                },
                {
                    "employer": "AB Möbelindustrikompaniet",
                    "location": "Tranås",
                    "startDate": "1914"
                },
                {
                    "employer": "East Gothland Bank",
                    "locations": [
                        "Tranås",
                        "Motala",
                        "Linköping"
                    ],
                    "startDate": "1914",
                    "endDate": "1918"
                },
                {
                    "employer": "Mjölby",
                    "positions": [
                        "Cashier",
                        "Board Deputy",
                        "Auditor",
                        "Revenue Inspector"
                    ],
                    "startDate": "1920",
                    "endDate": "1929"
                },
                {
                    "employer": "Motala",
                    "positions": [
                        "Loan Cashier"
                    ],
                    "startDate": "1931",
                    "endDate": "1932"
                },
                {
                    "employer": "Skänninge",
                    "positions": [
                        "Cashier",
                        "Accounting Head",
                        "Board Director"
                    ],
                    "startDate": "1932",
                    "endDate": "1934"
                },
                {
                    "employer": "Skänninge",
                    "positions": [
                        "Cashier",
                        "Head of Accounts Department",
                        "Board Member",
                        "2nd Vice Air Protection Chief"
                    ],
                    "startDate": "1935"
                }
            ],
            "memberships": [
                {
                    "organizationName": "Mjölby City Council",
                    "positions": [
                        "Auditor",
                        "Revenue Inspector"
                    ],
                    "startDate": "1924",
                    "endDate": "1929"
                },
                {
                    "organizationName": "Skänninge Fire Brigade",
                    "positions": [
                        "Chairman"
                    ],
                    "startDate": "1939"
                },
                {
                    "organizationName": "Pension Committee",
                    "positions": [
                        "Chairman"
                    ],
                    "startDate": "1934"
                },
                {
                    "organizationName": "Skänninge and North Göstring County Right-Wing Association",
                    "positions": [
                        "Chairman"
                    ],
                    "startDate": "1933"
                },
                {
                    "organizationName": "Skänninge Air Protection Association",
                    "positions": [
                        "Chairman"
                    ],
                    "startDate": "1939"
                }
            ],
            "hobbies": [
                "Member of Freemason",
                "Member of Odd Fellow"
            ]
        },
        "HYLÉN_Senny_Arvid_Torsten": {
            "givenName": "Senny Arvid Torsten",
            "familyName": "Hylén",
            "jobTitle": "Architect",
            "birthPlace": "Kristianstad",
            "birthDate": "1906-11-14",
            "spouse": {
                "givenName": "Kerstin",
                "familyName": "Thermsenius"
            },
            "career": [
                {
                    "employer": "AB Aug Hylén",
                    "location": "Kristianstad"
                },
                {
                    "employer": "S Hylén & Co, Furniture AB",
                    "location": "Stockholm"
                }
            ]
        },
        "HYMN_Zerold": {
            "givenName": "Zerold",
            "familyName": "Hymn",
            "jobTitle": "Manager",
            "birthPlace": "Kristianstad",
            "birthDate": "1900-01-02",
            "parents": {
                "father": {
                    "givenName": "A.H.",
                    "familyName": "Hymn"
                },
                "mother": {
                    "givenName": "Bertha",
                    "familyName": "Dymling"
                }
            },
            "education": [
                {
                    "schoolName": "Realex at Schartau"
                }
            ],
            "career": [
                {
                    "employer": "Myrstedt & Trowall",
                    "location": "Stockholm",
                    "startDate": "1919",
                    "endDate": "1921"
                },
                {
                    "employer": "Aug Hylén",
                    "startDate": "1922"
                },
                {
                    "employer": "Herm Tietz",
                    "location": "Hamburg",
                    "startDate": "1923"
                },
                {
                    "employer": "Linoleum Manufact Co",
                    "location": "London",
                    "startDate": "1924"
                },
                {
                    "employer": "Aug Hylén",
                    "startDate": "1925"
                },
                {
                    "employer": "Own Automatic Workshop",
                    "location": "Kristianstad",
                    "startDate": "1926",
                    "endDate": "1936"
                }
            ],
            "memberships": [
                {
                    "organizationName": "Swedish Furniture Retailers Association",
                    "positions": [
                        "Board Member"
                    ]
                }
            ],
            "travels": [
                "Germany",
                "England",
                "France"
            ],
            "hobbies": [
                "Tennis",
                "Hunting"
            ]
        }
    },
    "occupations": {
        "career": [
            {
                "occupational_title": "Civil Engineer",
                "workplace": "AB Zander & Ingeström",
                "industry": "Engineering",
                "start_date": "1915"
            },
            {
                "occupational_title": "Board Member and Vice Managing Director",
                "workplace": "AB Zander & Ingeström",
                "industry": "Engineering",
                "start_date": "1931"
            },
            {
                "occupational_title": "Managing Director",
                "workplace": "AB Zander & Ingeström",
                "industry": "Engineering",
                "start_date": "1940"
            },
            {
                "occupational_title": "Board Member",
                "workplace": "AB Arctic",
                "industry": "Unknown",
                "start_date": "1923"
            },
            {
                "occupational_title": "Board Member",
                "workplace": "Swedish Technological Society, Mechanical Department",
                "industry": "Technology",
                "start_date": "1924"
            },
            {
                "occupational_title": "Member of the 8th Officer's Club",
                "workplace": "Unknown",
                "industry": "Unknown",
                "start_date": "1939"
            },
            {
                "occupational_title": "Managing Director",
                "workplace": "AB Aug Hylén",
                "industry": "Furniture and Home Decor",
                "start_date": "1896"
            },
            {
                "occupational_title": "Chairman",
                "workplace": "Swedish Child Care Association",
                "industry": "Childcare",
                "start_date": "Unknown"
            },
            {
                "occupational_title": "Chairman",
                "workplace": "Swedish Furniture Retailers Association",
                "industry": "Furniture Retail",
                "start_date": "Unknown"
            },
            {
                "occupational_title": "Vice Chairman",
                "workplace": "Swedish Linoleum Retailers Association",
                "industry": "Linoleum Retail",
                "start_date": "Unknown"
            },
            {
                "occupational_title": "Managing Director",
                "workplace": "Georg Hylén AB",
                "industry": "Unknown",
                "start_date": "Unknown"
            },
            {
                "occupational_title": "Chairman of the Board",
                "workplace": "Georg Hylén AB",
                "industry": "Unknown",
                "start_date": "Unknown"
            },
            {
                "occupational_title": "Managing Director",
                "workplace": "Julius Sjögren Special Machinery AB",
                "industry": "Unknown",
                "start_date": "Unknown"
            },
            {
                "occupational_title": "Managing Director",
                "workplace": "AB Tegil",
                "industry": "Unknown",
                "start_date": "Unknown"
            },
            {
                "occupational_title": "Cashier",
                "workplace": "East Gothland Bank",
                "industry": "Banking",
                "start_date": "1914"
            },
            {
                "occupational_title": "Auditor",
                "workplace": "Mjölby Municipality",
                "industry": "Government",
                "start_date": "1924"
            },
            {
                "occupational_title": "Chairman",
                "workplace": "Skänninge Fire Brigade",
                "industry": "Emergency Services",
                "start_date": "1939"
            },
            {
                "occupational_title": "Chairman",
                "workplace": "Pension Committee",
                "industry": "Social Services",
                "start_date": "1934"
            },
            {
                "occupational_title": "Chairman",
                "workplace": "Skänninge and North Göstring County Right-Wing Association",
                "industry": "Politics",
                "start_date": "1933"
            },
            {
                "occupational_title": "Board Member",
                "workplace": "Swedish Furniture Retailers Association",
                "industry": "Furniture Retail",
                "start_date": "Unknown"
            },
            {
                "occupational_title": "Employee",
                "workplace": "AB Aug Hylén",
                "industry": "Furniture",
                "start_date": "Unknown"
            },
            {
                "occupational_title": "Manager",
                "workplace": "Aug Hylén",
                "industry": "Unknown",
                "start_date": "Unknown"
            }
        ]
    }
}