{
    "original": "CLAESON, Helge, Disponent, Uddebo, f Uddebo 13/3 92 av dir R C o Anna Bårström. Hal Borås, Gbgs hdlsinst, vävsk Chemnitz Tyskl, stud Tyskl o Engl. Anst fad fma Uddebo Möbeltygsväfveri, disp dna sed. 40, vkst dir Tostarps Träförädlings AB o Uddebo AB. Fd ordf komm.nmd; led dna o kyrkoflm samt kyrkoråd; ordf Uddebo friv brandkårsförening.",
    "translated": "CLAESON, Helge, Manager, Uddebo, b. Uddebo 13/3 92, to director R C and Anna Bårström. Raised in Borås, attended GBG Commercial Institute, studied German and English. Employed by father at Uddebo Möbeltygsväfveri (furniture fabric weaving factory), became manager after father's retirement. At age 40, became director of Tostarps Träförädlings AB (wood processing company) and Uddebo AB. Former chairman of the local council; member of the local DNA (not clear what this abbreviation stands for) and church filament (also not clear what this abbreviation stands for) as well as the church council; chairman of the Uddebo volunteer fire brigade association.",
    "structured": {
        "@context": "https://schema.org/",
        "@type": "Person",
        "givenName": "Helge",
        "familyName": "Claeson",
        "jobTitle": "Manager",
        "birthPlace": "Uddebo",
        "birthDate": "1892-03-13",
        "parents": [
            {
                "@type": "Person",
                "givenName": "R C",
                "familyName": "Claeson",
                "jobTitle": "Director"
            },
            {
                "@type": "Person",
                "givenName": "Anna",
                "familyName": "Bårström"
            }
        ],
        "memberOf": [
            {
                "@type": "Organization",
                "name": "Tostarps Träförädlings AB"
            },
            {
                "@type": "Organization",
                "name": "Uddebo AB"
            }
        ],
        "education": [
            {
                "@type": "EducationalOrganization",
                "name": "GBG Commercial Institute"
            },
            {
                "@type": "EducationalOrganization",
                "name": "Chemnitz German weavers school"
            }
        ],
        "worksFor": {
            "@type": "Organization",
            "name": "Uddebo Möbeltygsväfveri"
        },
        "formerChairmanOf": [
            {
                "@type": "Organization",
                "name": "Local Council"
            },
            {
                "@type": "Organization",
                "name": "Local DNA"
            },
            {
                "@type": "Organization",
                "name": "Church Filament"
            },
            {
                "@type": "Organization",
                "name": "Church Council"
            }
        ]
    },
    "occupations": {
        "career": [
            {
                "occupational_title": "Manager",
                "workplace": "Uddebo Möbeltygsväfveri",
                "industry": "Furniture Fabric Weaving",
                "start_date": "1922"
            },
            {
                "occupational_title": "Director",
                "workplace": "Tostarps Träförädlings AB",
                "industry": "Wood Processing",
                "start_date": "1932"
            },
            {
                "occupational_title": "Director",
                "workplace": "Uddebo AB",
                "industry": "Unknown",
                "start_date": "-"
            }
        ]
    }
}