{
    "original": "DUHS, Gustaf Hugo Reinhold, Generalkonsul, Djursholm, f Hagfors, Vrml, 16/6 78 av ing G D o Emilie Löfgren, gm Greta Hjorth. Studex, civ.ing. Anst AB Arehns Mek Verkst Sthlm 02—09, ^B B A Hjorth sed. 10. Gen.kons f Monaco sed. 14. Ordf i Corps Consulaire, dir.led i Wenner-Grenska institutet,’ Styr.ordf AB B A Hjorth &amp; Co, AB Primus, AB Enköpings Verkst, Inst f be-kämp av mutor o bestickn, Sällsk SBK mm. Resor: Sydam 23, Asien 24, 31, Afr 19, 24, 25, 27, 28, 29, 31, Tyskl, Holl, Belg. Frankr, Engl, Ital fi ggr. KVO2kl, KFinlVRO, KLettSO, KMonS :tCO, KTunNI, OffBKrO, OffFrllL, OffNedONO; KAK, KMK, KSSS, KSAK, Sthlms Isjaktklb, Sthlms Yachtklb, Sv Tekn.frn, Sthlms Köpm.klb, W6, Stadsbildskåren, Travellers club, ett f ler t frn f idrott, konst, kultur, internat samarb osv.",
    "translated": "DUHS, Gustaf Hugo Reinhold, Honorary Consul General, Djursholm, born in Hagfors, Värmland, on June 16, 1878, to parents Gustav David and Emilie Löfgren. Married to Greta Hjorth. Graduated, engineer. Employed at AB Arehns Mechanical Workshop in Stockholm from 1902 to 1909, and later at B. A. Hjorth & Co. Became Honorary Consul in Monaco in 1914. Chairman of the Corps Consulaire and board member of Wenner-Gren Institute. Chairman of AB B. A. Hjorth & Co., AB Primus, and AB Enköpings Mechanical Works. Member of the Institute for Combating Bribery and Corruption, Society of Business and Culture, and other organizations. Traveled extensively to South America (1923), Asia (1924, 1931), Africa (1919, 1924, 1925, 1927, 1928, 1929, 1931), Germany, Holland, Belgium, France, England, Italy, and others. Recipient of several decorations: Knight Second Class of the Royal Order of Vasa, Knight of the Order of the White Rose of Finland, Knight First Class of the Order of Three Stars of Latvia, Commander of the Order of St. Charles of Monaco, Knight of the Order of St. Olav of Norway, Officer of the Order of the Crown of Belgium, Officer of the Legion of Honour of France, Officer of the Order of Orange-Nassau of the Netherlands. Member of the Royal Academy of Fine Arts, the Royal Swedish Academy of Music, the Royal Society of Sea Rescue, the Stockholm Ice Yachting Club, the Stockholm Yacht Club, the Swedish Association of Engineers, the Stockholm Merchant Club, and others. Also involved in sports, arts, culture, and international cooperation.",
    "structured": {
        "@context": "https://schema.org",
        "@type": "Person",
        "name": "Gustaf Hugo Reinhold Duhs",
        "birthDate": "1878-06-16",
        "birthPlace": {
            "@type": "Place",
            "name": "Hagfors, Värmland, Sweden"
        },
        "parent": [
            {
                "@type": "Person",
                "name": "Gustav David Duhs"
            },
            {
                "@type": "Person",
                "name": "Emilie Löfgren"
            }
        ],
        "spouse": {
            "@type": "Person",
            "name": "Greta Hjorth"
        },
        "education": {
            "@type": "EducationalOccupationalCredential",
            "credentialCategory": "Studex, civ.ing"
        },
        "employment": [
            {
                "@type": "Organization",
                "name": "AB Arehns Mek Verkst",
                "startDate": "1902-01-01",
                "endDate": "1909-01-01"
            },
            {
                "@type": "Organization",
                "name": "B. A. Hjorth & Co.",
                "startDate": "1910-01-01"
            }
        ],
        "honoraryTitles": [
            {
                "@type": "OrganizationRole",
                "namedPosition": "Honorary Consul General",
                "startDate": "1914-01-01",
                "endDate": "present",
                "roleName": "Monaco"
            }
        ],
        "memberships": [
            {
                "@type": "OrganizationRole",
                "namedPosition": "Chairman",
                "roleName": "Corps Consulaire"
            },
            {
                "@type": "OrganizationRole",
                "namedPosition": "Board Member",
                "roleName": "Wenner-Gren Institute"
            },
            {
                "@type": "OrganizationRole",
                "namedPosition": "Chairman",
                "roleName": "AB B. A. Hjorth & Co."
            },
            {
                "@type": "OrganizationRole",
                "namedPosition": "Chairman",
                "roleName": "AB Primus"
            },
            {
                "@type": "OrganizationRole",
                "namedPosition": "Chairman",
                "roleName": "AB Enköpings Verkst"
            },
            {
                "@type": "OrganizationRole",
                "namedPosition": "Board Member",
                "roleName": "Institute for Combating Bribery and Corruption"
            }
        ],
        "travels": [
            "South America (1923)",
            "Asia (1924, 1931)",
            "Africa (1919, 1924, 1925, 1927, 1928, 1929, 1931)",
            "Germany",
            "Holland",
            "Belgium",
            "France",
            "England",
            "Italy"
        ],
        "decorations": [
            {
                "@type": "Order",
                "name": "Knight Second Class of the Royal Order of Vasa",
                "dateAwarded": "unknown"
            },
            {
                "@type": "Order",
                "name": "Knight of the Order of the White Rose of Finland",
                "dateAwarded": "unknown"
            },
            {
                "@type": "Order",
                "name": "Knight First Class of the Order of Three Stars of Latvia",
                "dateAwarded": "unknown"
            },
            {
                "@type": "Order",
                "name": "Commander of the Order of St. Charles of Monaco",
                "dateAwarded": "unknown"
            },
            {
                "@type": "Order",
                "name": "Knight of the Order of St. Olav of Norway",
                "dateAwarded": "unknown"
            },
            {
                "@type": "Order",
                "name": "Officer of the Order of the Crown of Belgium",
                "dateAwarded": "unknown"
            },
            {
                "@type": "Order",
                "name": "Officer of the Legion of Honour of France",
                "dateAwarded": "unknown"
            },
            {
                "@type": "Order",
                "name": "Officer of the Order of Orange-Nassau of the Netherlands",
                "dateAwarded": "unknown"
            }
        ],
        "memberOf": [
            {
                "@type": "Organization",
                "name": "Royal Academy of Fine Arts"
            },
            {
                "@type": "Organization",
                "name": "Royal Swedish Academy of Music"
            },
            {
                "@type": "Organization",
                "name": "Royal Society of Sea Rescue"
            },
            {
                "@type": "Organization",
                "name": "Stockholm Ice Yachting Club"
            },
            {
                "@type": "Organization",
                "name": "Stockholm Yacht Club"
            },
            {
                "@type": "Organization",
                "name": "Swedish Association of Engineers"
            },
            {
                "@type": "Organization",
                "name": "Stockholm Merchant Club"
            }
        ],
        "otherInterests": [
            "Sports",
            "Arts",
            "Culture",
            "International cooperation"
        ]
    },
    "occupations": {
        "career": [
            {
                "occupational_title": "Engineer",
                "workplace": "AB Arehns Mechanical Workshop",
                "industry": "Mechanical Engineering",
                "start_date": "1902"
            },
            {
                "occupational_title": "Honorary Consul",
                "workplace": "Monaco",
                "industry": "Diplomacy",
                "start_date": "1914"
            },
            {
                "occupational_title": "Chairman",
                "workplace": "AB B. A. Hjorth & Co.",
                "industry": "Business",
                "start_date": "Unknown"
            },
            {
                "occupational_title": "Chairman",
                "workplace": "AB Primus",
                "industry": "Business",
                "start_date": "Unknown"
            },
            {
                "occupational_title": "Chairman",
                "workplace": "AB Enköpings Mechanical Works",
                "industry": "Mechanical Engineering",
                "start_date": "Unknown"
            }
        ]
    }
}