{
    "original": "JONSSON, Oskar Birger, Direktör, Göteborg, f Uddev 82, gm Märta Kölner von Bet-zen. Uddev hal, hdlsstud Gbg. Kont J A Hertz &amp; Co 00—03, kont.ch AB Barth &amp; Dahlgren 03—19, dir AB Clase &amp; Wessman 1(3—19, ag AB Berlin &amp; Jonsson 19—25, kassadir Gbg rest.AB 25—35 (num Vara), vkst dir sed. 35. Kontr.styr:s rev i systembol 21—25, sakk i kontr.styr o stat priskontr.nmd. Styr.led VARA, AB Kronhusgat 21 Gbg, AB Mid-gård Falköp, Skövde hotellbyggn.AB, Falkbg hotell- &amp; rest.AB, Falkbg badhotell, HotellAB i Kkrona, v. ordf Rest :s arb.giv.frn, rev Gbgs Hdlsbk, styr.led Sv seglarfrb sed. 22, SS Aeo-lus 15—30, Aeolus Yacht Club sed. 16 (ordf 24 —42), v. ordf GKSS 42. Resor: Skand, Tyskl, Frankr, Engl, Ital o Holl 25—43. RNO, RVO, RFinlVRO, ordf o stormast ord.sällsk T-G. Hobby: Segling.",
    "translated": "JONSSON, Oskar Birger, Director, Gothenburg, born in Uddevalla in 1882, married Märta Kölner von Betzen. Uddevalla half, studied commerce in Gothenburg. Employed at J.A. Hertz &amp; Co 1900-1903, accountant at AB Barth &amp; Dahlgren 1903-1919, director at AB Clase &amp; Wessman 1913-1919, agent at AB Berlin &amp; Jonsson 1919-1925, cashier at Gotea rest.AB 1925-1935 (now Vara), vice director since 1935. Member of the board of directors in the systembol 1921-1925, expert in the board of directors and state price contract committee. Board member of VARA, AB Kronhusgat 21 Gothenburg, AB Midgård Falköping, Skövde hotel building AB, Falkenberg hotel and restaurant AB, Falkenberg beach hotel, Hotel AB in Krona, vice chairman of Rest's employer association, expert in Goteborgs Hdlsbk, board member of Swedish sailing club since 1922, SS Aeolus 1915-1930, Aeolus Yacht Club since 1916 (chairman 1924-1942), vice chairman of GKSS in 1942. Travelled to Scandinavia, Germany, France, England, Italy or the Netherlands in 1925-1943. Received Order of the North Star, Order of Vasa, Order of the Finnish Lion, chairman and grand master of the T-G. Hobby: Sailing.",
    "structured": {
        "@context": "https://schema.org/",
        "@type": "Person",
        "name": "Oskar Birger Jonsson",
        "birthDate": "1882-01-01",
        "birthPlace": "Uddevalla",
        "deathDate": null,
        "nationality": "Swedish",
        "jobTitle": "Director",
        "memberOf": "Gothenburg",
        "marriage": [
            {
                "@type": "Person",
                "name": "Märta Kölner von Betzen"
            }
        ],
        "education": [
            {
                "@type": "Organization",
                "name": "Gothenburg"
            }
        ],
        "work": [
            {
                "@type": "Organization",
                "name": "J.A. Hertz & Co",
                "startDate": "1900-01-01",
                "endDate": "1903-01-01"
            },
            {
                "@type": "Organization",
                "name": "AB Barth & Dahlgren",
                "startDate": "1903-01-01",
                "endDate": "1919-01-01",
                "position": "Accountant"
            },
            {
                "@type": "Organization",
                "name": "AB Clase & Wessman",
                "startDate": "1913-01-01",
                "endDate": "1919-01-01",
                "position": "Director"
            },
            {
                "@type": "Organization",
                "name": "AB Berlin & Jonsson",
                "startDate": "1919-01-01",
                "endDate": "1925-01-01",
                "position": "Agent"
            },
            {
                "@type": "Organization",
                "name": "Gotea rest.AB",
                "startDate": "1925-01-01",
                "endDate": "1935-01-01",
                "position": "Cashier"
            }
        ],
        "boardMember": [
            {
                "@type": "Organization",
                "name": "VARA"
            },
            {
                "@type": "Organization",
                "name": "AB Kronhusgat 21 Gothenburg"
            },
            {
                "@type": "Organization",
                "name": "AB Midgård Falköping"
            },
            {
                "@type": "Organization",
                "name": "Skövde hotel building AB"
            },
            {
                "@type": "Organization",
                "name": "Falkenberg hotel and restaurant AB"
            },
            {
                "@type": "Organization",
                "name": "Falkenberg beach hotel"
            },
            {
                "@type": "Organization",
                "name": "Hotel AB in Krona"
            },
            {
                "@type": "Organization",
                "name": "Rest's employer association",
                "position": "Vice Chairman"
            },
            {
                "@type": "Organization",
                "name": "Goteborgs Hdlsbk",
                "position": "Expert"
            },
            {
                "@type": "Organization",
                "name": "Swedish sailing club",
                "startDate": "1922-01-01",
                "position": "Board Member"
            },
            {
                "@type": "Organization",
                "name": "SS Aeolus",
                "startDate": "1915-01-01",
                "endDate": "1930-01-01",
                "position": "Board Member"
            },
            {
                "@type": "Organization",
                "name": "Aeolus Yacht Club",
                "startDate": "1916-01-01",
                "position": "Chairman"
            },
            {
                "@type": "Organization",
                "name": "GKSS",
                "startDate": "1942-01-01",
                "position": "Vice Chairman"
            }
        ],
        "travelledTo": [
            "Scandinavia",
            "Germany",
            "France",
            "England",
            "Italy",
            "Netherlands"
        ],
        "awards": [
            "Order of the North Star",
            "Order of Vasa",
            "Order of the Finnish Lion"
        ],
        "hobby": "Sailing"
    },
    "occupations": {
        "career": [
            {
                "occupational_title": "Accountant",
                "workplace": "AB Barth & Dahlgren",
                "industry": "Unknown",
                "start_date": "1903"
            },
            {
                "occupational_title": "Director",
                "workplace": "AB Clase & Wessman",
                "industry": "Unknown",
                "start_date": "1913"
            },
            {
                "occupational_title": "Agent",
                "workplace": "AB Berlin & Jonsson",
                "industry": "Unknown",
                "start_date": "1919"
            },
            {
                "occupational_title": "Cashier",
                "workplace": "Gotea rest.AB (now Vara)",
                "industry": "Unknown",
                "start_date": "1925"
            },
            {
                "occupational_title": "Vice Director",
                "workplace": "Unknown",
                "industry": "Unknown",
                "start_date": "1935"
            }
        ]
    }
}