{
    "original": "CAI/LANDER, Marcus, Revisor, Stockholm, f Motala 2/5 95 av kamr G. A. C o Alma Westerberg, gm Wivan Friberg. Hal o hdlsinst i Hbg. Anst SJ 19—23, kamrer i ind 23—27, eg rev.byrå sed. 27, ombild t Cal-lander &amp; Co AB Revisionsbyrå 38. Led av Sv rev.samf. Lstlöjtn 34. Medl Lstfrb, Klara Istfrn, Centralskyttefrn, Sthlms pistolskyt-tekl; Klara Istfrns SM, SkytteSM. Hobbies: Skytte, yrkeslitteratur.",
    "translated": "CAI/LANDER, Marcus, Auditor, Stockholm, born in Motala on 2/5 1895, son of G. A. C and Alma Westerberg, married to Wivan Friberg. Completed commercial and trade education in Helsingborg. Employed by the Swedish Railways 1919-1923, auditor in the industry 1923-1927, established his own auditing firm in 1927, transformed into Cal-lander & Co AB Auditing Firm in 1938. Member of the Swedish Auditing Society. Second Lieutenant in the Reserve from 1934. Member of the Auditing Association, Klara Rifle Association, Central Shooting Association, Stockholm Pistol Shooting Club; winner of Klara Rifle Association's Swedish Championship, Shooting Championship. Hobbies: Shooting, professional literature.",
    "structured": {
        "@context": "https://schema.org",
        "@type": "Person",
        "name": "Marcus Cai/Lander",
        "jobTitle": "Auditor",
        "birthDate": "1895-05-02",
        "birthPlace": "Motala",
        "spouse": "Wivan Friberg",
        "parent": [
            {
                "@type": "Person",
                "givenName": "G. A. C",
                "familyName": "Cai/Lander"
            },
            {
                "@type": "Person",
                "givenName": "Alma",
                "familyName": "Westerberg"
            }
        ],
        "education": [
            {
                "@type": "EducationalOrganization",
                "name": "Helsingborg-Commercial and Trade Education"
            }
        ],
        "worksFor": [
            {
                "@type": "Organization",
                "name": "Swedish Railways",
                "startDate": "1919",
                "endDate": "1923"
            },
            {
                "@type": "Organization",
                "name": "Auditing Firm",
                "startDate": "1927"
            }
        ],
        "memberOf": [
            {
                "@type": "Organization",
                "name": "Swedish Auditing Society"
            },
            {
                "@type": "Organization",
                "name": "Reserve"
            },
            {
                "@type": "Organization",
                "name": "Auditing Association"
            },
            {
                "@type": "Organization",
                "name": "Klara Rifle Association"
            },
            {
                "@type": "Organization",
                "name": "Central Shooting Association"
            },
            {
                "@type": "Organization",
                "name": "Stockholm Pistol Shooting Club"
            }
        ],
        "championship": [
            {
                "@type": "SportsEvent",
                "name": "Klara Rifle Association's Swedish Championship"
            },
            {
                "@type": "SportsEvent",
                "name": "Shooting Championship"
            }
        ],
        "hobbies": [
            "Shooting",
            "Professional literature"
        ]
    },
    "occupations": {
        "career": [
            {
                "occupational_title": "Auditor",
                "workplace": "Swedish Railways",
                "industry": "Transportation",
                "start_date": "1919"
            },
            {
                "occupational_title": "Auditor",
                "workplace": "Industry",
                "industry": "Unknown",
                "start_date": "1923"
            },
            {
                "occupational_title": "Auditor",
                "workplace": "Cal-lander & Co AB Auditing Firm",
                "industry": "Auditing",
                "start_date": "1927"
            }
        ]
    }
}