{
    "original": "BERGVAI/I,, Erik Gustaf, Direktör, Mjölby, f Hults bruk, Åby, 29/3 92 av fabr G F B o Emma Bonnevier, gm Elswig Carlsson. Ljungstedtska tekn yrk.sk Link, Ebersteins tekn sk o Tekn gymn Norrk. Disp Mjölby gjut o mek vkst 13—18, vkst dir där (Primoverken) sed. 18 Ag bost.fastgh Kyrkog 8, Mjölby. Styr.led o v. ordf österg ensk bk Mjbykont, insp Mjby stds sk f yrk.underv, ordf Sv gjutm.frbs rev.utsk o rev i dess Norr-k.-avd, rev Ålderd.frbs Mjbyavd, fullm Allm brandst.bol, kyrkofullm, led Mjby stds byggn.nmd, styr.led o skattm Mjby arb.frn, styr.led Mjby stds erk sjukk, led Mjby stds luftsk.nmd. Resor: Tyskl, Tj.-Slow, Ung, Schweiz, Ital, Danm, Norge uppr ggr, Odd Fellow (m dess Vet.tkn), FrimO. Sv Sång.-frbs GM, östg Sång.frbs GM, Månsk Sångar-br:nas GM. Hobbies: Sång o musik.",
    "translated": "BERGVAI/I,, Erik Gustaf, Director, Mjölby, born in Hults bruk, Åby, on March 29, 1892, son of factory owner G F B and Emma Bonnevier, married to Elswig Carlsson. Attended Ljungstedtska technical vocational school (Linköping), Ebersteins technical school, and Technical Gymnasium in Norrköping. Worked at Mjölby foundry and mechanical workshop from 1913 to 1918, then became director there (Primoverken) since 1918. Resides at Kyrkogatan 8, Mjölby. Holds positions as board member and vice chairman of Östergötland Savings Bank, inspector at Mjölby trade school for vocational education, chairman of the Swedish Foundry Association's review board and review board in its Northern region, reviewer at the Mjölby branch of the Pensioners' Association, member of the board of directors of Allmänna Brandstodsbolag, member of the church council, member of Mjölby's building committee, board member and treasurer of Mjölby workers' union, board member of Mjölby's recognized hospital, and member of Mjölby's recognized air school committee. Has traveled to Germany, Czechoslovakia, Hungary, Switzerland, Italy, Denmark, and Norway several times. Member of the Odd Fellow fraternity (including its Veterans' Technical Association) and Freemasonry. Awarded the Grand Master's medal by the Swedish Singing Society and the Östergötland Singing Society, as well as the Grand Master's medal by the Månsk Singing Society. Hobbies include singing and music.",
    "structured": {
        "@context": "https://schema.org",
        "@type": "Person",
        "name": "Erik Gustaf Bergvai",
        "birthDate": "1892-03-29",
        "birthPlace": "Hults bruk, Åby",
        "description": "Director, Mjölby",
        "spouse": "Elswig Carlsson",
        "address": {
            "@type": "PostalAddress",
            "streetAddress": "Kyrkogatan 8",
            "addressLocality": "Mjölby"
        },
        "education": [
            {
                "@type": "EducationalOrganization",
                "name": "Ljungstedtska technical vocational school",
                "location": "Linköping"
            },
            {
                "@type": "EducationalOrganization",
                "name": "Ebersteins technical school"
            },
            {
                "@type": "EducationalOrganization",
                "name": "Technical Gymnasium Norrköping"
            }
        ],
        "employmentHistory": [
            {
                "@type": "Organization",
                "name": "Mjölby foundry and mechanical workshop",
                "startDate": "1913-01-01",
                "endDate": "1918-12-31",
                "description": "Worked at Mjölby foundry and mechanical workshop from 1913 to 1918."
            },
            {
                "@type": "Organization",
                "name": "Primoverken",
                "startDate": "1918-01-01",
                "description": "Director at Primoverken since 1918."
            }
        ],
        "memberOf": [
            {
                "@type": "Organization",
                "name": "Östergötland Savings Bank",
                "roleName": "Board Member",
                "roleAffiliation": "Vice Chairman"
            },
            {
                "@type": "Organization",
                "name": "Swedish Foundry Association",
                "reviewer": [
                    "Chairman of the Review Board",
                    "Reviewer (Northern Region)"
                ]
            },
            {
                "@type": "Organization",
                "name": "Mjölby branch of the Pensioners' Association",
                "reviewer": "Reviewer"
            },
            {
                "@type": "Organization",
                "name": "Allmänna Brandstodsbolag"
            },
            {
                "@type": "Organization",
                "name": "Church Council"
            },
            {
                "@type": "Organization",
                "name": "Mjölby's building committee"
            },
            {
                "@type": "Organization",
                "name": "Mjölby workers' union",
                "roleName": "Board Member",
                "roleAffiliation": "Treasurer"
            },
            {
                "@type": "Organization",
                "name": "Mjölby's recognized hospital",
                "roleName": "Board Member"
            },
            {
                "@type": "Organization",
                "name": "Mjölby's recognized air school committee",
                "roleName": "Member"
            }
        ],
        "travelHistory": [
            "Germany",
            "Czechoslovakia",
            "Hungary",
            "Switzerland",
            "Italy",
            "Denmark",
            "Norway"
        ],
        "memberOfFraternity": [
            "Odd Fellow fraternity",
            "Freemasonry"
        ],
        "awards": [
            {
                "@type": "Award",
                "name": "Grand Master's medal",
                "presentedByName": "Swedish Singing Society"
            },
            {
                "@type": "Award",
                "name": "Grand Master's medal",
                "presentedByName": "Östergötland Singing Society"
            },
            {
                "@type": "Award",
                "name": "Grand Master's medal",
                "presentedByName": "Månsk Singing Society"
            }
        ],
        "hobbies": "Singing and music"
    },
    "occupations": {
        "career": [
            {
                "occupational_title": "Director",
                "workplace": "Mjölby",
                "industry": null,
                "start_date": null
            },
            {
                "occupational_title": "Factory Owner",
                "workplace": "Hults bruk, Åby",
                "industry": null,
                "start_date": null
            },
            {
                "occupational_title": "Inspector",
                "workplace": "Mjölby Trade School for Vocational Education",
                "industry": "Education",
                "start_date": null
            },
            {
                "occupational_title": "Chairman",
                "workplace": "Swedish Foundry Association's Review Board",
                "industry": "Manufacturing",
                "start_date": null
            },
            {
                "occupational_title": "Chairman",
                "workplace": "Review Board in Northern region of Swedish Foundry Association",
                "industry": "Manufacturing",
                "start_date": null
            },
            {
                "occupational_title": "Reviewer",
                "workplace": "Mjölby Branch of the Pensioners' Association",
                "industry": null,
                "start_date": null
            },
            {
                "occupational_title": "Board Member",
                "workplace": "Allmänna Brandstodsbolag",
                "industry": "Insurance",
                "start_date": null
            },
            {
                "occupational_title": "Board Member",
                "workplace": "Östergötland Savings Bank",
                "industry": "Finance",
                "start_date": null
            },
            {
                "occupational_title": "Vice Chairman",
                "workplace": "Östergötland Savings Bank",
                "industry": "Finance",
                "start_date": null
            },
            {
                "occupational_title": "Member",
                "workplace": "Church Council",
                "industry": "Religion",
                "start_date": null
            },
            {
                "occupational_title": "Member",
                "workplace": "Mjölby's Building Committee",
                "industry": "Government",
                "start_date": null
            },
            {
                "occupational_title": "Board Member",
                "workplace": "Mjölby Workers' Union",
                "industry": "Labor",
                "start_date": null
            },
            {
                "occupational_title": "Treasurer",
                "workplace": "Mjölby Workers' Union",
                "industry": "Labor",
                "start_date": null
            },
            {
                "occupational_title": "Member",
                "workplace": "Mjölby's Recognized Hospital",
                "industry": "Healthcare",
                "start_date": null
            },
            {
                "occupational_title": "Member",
                "workplace": "Mjölby's Recognized Air School Committee",
                "industry": "Education",
                "start_date": null
            }
        ]
    }
}