{
    "original": "BLOMQUIST, Nils Knutsson, Civilingenjör, Uppsala, f Västra Ny, Ögl, 13/2 10 av dir v stat uppfostr.anst å Bona K B o Beata Puke, gm Elsa Sandberg. Studex Motala 29, KTH (V o V) 35, bygg.mäst.rättigh i Sthlm 39; löjtn i VVK 42. Anst v Väg- o vattenbyggn.-styr 35, v Byggn AB Konstruktör Gävle 35—36, Sthlms stads fastigh.kont 36—37, AB Betongindustri Sthlm 37—41, v Tegelbr Centralfrb Sthlm 42—43, övering i Byggn.fman Anders Diös Upps sed. 44. Resor: Danm, Holl, Belg, Engl, Frankr 29, Danm, Engl, Frankr, Span, Egypt, Aden, Kenya, Tanganjika, Sydafr, Sierra Leone, Madeira 30—31, Danm, Tyskl 34, 38, 41. Av trycket: Div art i tidskr Tegel, red o ansv utg f dna 43; en tegelhandbok under utarb.",
    "translated": "BLOMQUIST, Nils Knutsson, Civil Engineer, Uppsala, born in Västra Ny, Ögl, on February 13th, 1910, son of director at the state education institution Bona K B and Beata Puke, married to Elsa Sandberg. High school graduate in Motala in 1929, studied at KTH (Royal Institute of Technology, both V and V indicate different programs) from 1935, obtained construction master's rights in Stockholm in 1939; lieutenant in the Volunteer Reserve Corps in 1942. Employed by the Road and Water Building Authority from 1935, worked as a Construction Engineer at Building AB in Gävle from 1935 to 1936, at Stockholm City's Property Office from 1936 to 1937, at AB Betongindustri Stockholm from 1937 to 1941, at Tegelbrick Central Union Stockholm from 1942 to 1943, and as Chief Engineer at Building Firm Anders Diös in Uppsala since 1944. Traveled to Denmark, the Netherlands, Belgium, England, and France in 1929, to Denmark, England, France, Spain, Egypt, Aden, Kenya, Tanganyika, South Africa, Sierra Leone, and Madeira in 1930-1931, to Denmark and Germany in 1934, 1938, and 1941. Published various articles in the Tegel magazine, served as editor and responsible publisher from 1943; currently working on a brick handbook.",
    "structured": {
        "@context": "https://schema.org/",
        "@type": "Person",
        "name": "Nils Knutsson Blomquist",
        "jobTitle": "Civil Engineer",
        "birthPlace": "Västra Ny, Ögl",
        "birthDate": "1910-02-13",
        "parents": [
            {
                "@type": "Person",
                "name": "Bona K B"
            },
            {
                "@type": "Person",
                "name": "Beata Puke"
            }
        ],
        "spouse": {
            "@type": "Person",
            "name": "Elsa Sandberg"
        },
        "education": {
            "@type": "EducationalOccupationalCredential",
            "credentialCategory": "High school graduate",
            "educationalLevel": "High school",
            "alumniOf": "Motala"
        },
        "alumniOf": [
            {
                "@type": "EducationalOrganization",
                "name": "KTH",
                "additionalType": "Royal Institute of Technology",
                "startDate": "1935"
            }
        ],
        "worksFor": [
            {
                "@type": "Organization",
                "name": "Road and Water Building Authority",
                "employeeStartDate": "1935",
                "employeeEndDate": "present"
            },
            {
                "@type": "Organization",
                "name": "Building AB",
                "employeeStartDate": "1935",
                "employeeEndDate": "1936",
                "location": "Gävle"
            },
            {
                "@type": "Organization",
                "name": "Stockholm City's Property Office",
                "employeeStartDate": "1936",
                "employeeEndDate": "1937"
            },
            {
                "@type": "Organization",
                "name": "AB Betongindustri Stockholm",
                "employeeStartDate": "1937",
                "employeeEndDate": "1941"
            },
            {
                "@type": "Organization",
                "name": "Tegelbrick Central Union Stockholm",
                "employeeStartDate": "1942",
                "employeeEndDate": "1943"
            },
            {
                "@type": "Organization",
                "name": "Building Firm Anders Diös",
                "employeeStartDate": "1944",
                "employeeEndDate": "present",
                "location": "Uppsala"
            }
        ],
        "militaryService": {
            "@type": "Organization",
            "name": "Volunteer Reserve Corps",
            "serviceType": "Lieutenant",
            "startDate": "1942"
        },
        "memberOf": [
            {
                "@type": "Organization",
                "name": "Tegel Magazine",
                "startDate": "1943",
                "editor": "Nils Knutsson Blomquist",
                "publisher": "Nils Knutsson Blomquist"
            }
        ],
        "travelHistory": [
            {
                "countriesVisited": [
                    "Denmark",
                    "Netherlands",
                    "Belgium",
                    "England",
                    "France"
                ],
                "yearVisited": "1929"
            },
            {
                "countriesVisited": [
                    "Denmark",
                    "England",
                    "France",
                    "Spain",
                    "Egypt",
                    "Aden",
                    "Kenya",
                    "Tanganyika",
                    "South Africa",
                    "Sierra Leone",
                    "Madeira"
                ],
                "yearVisited": "1930-1931"
            },
            {
                "countriesVisited": [
                    "Denmark",
                    "Germany"
                ],
                "yearVisited": "1934"
            },
            {
                "countriesVisited": [
                    "Denmark",
                    "Germany"
                ],
                "yearVisited": "1938"
            },
            {
                "countriesVisited": [
                    "Denmark",
                    "Germany"
                ],
                "yearVisited": "1941"
            }
        ],
        "additionalNote": "Currently working on a brick handbook."
    },
    "occupations": {
        "career": [
            {
                "occupational_title": "Civil Engineer",
                "workplace": "Uppsala",
                "industry": "Engineering",
                "start_date": "Unknown"
            },
            {
                "occupational_title": "Lieutenant",
                "workplace": "Volunteer Reserve Corps",
                "industry": "Military",
                "start_date": "1942"
            },
            {
                "occupational_title": "Construction Engineer",
                "workplace": "Building AB",
                "industry": "Construction",
                "start_date": "1935"
            },
            {
                "occupational_title": "Construction Engineer",
                "workplace": "Stockholm City's Property Office",
                "industry": "Construction",
                "start_date": "1936"
            },
            {
                "occupational_title": "Construction Engineer",
                "workplace": "AB Betongindustri Stockholm",
                "industry": "Construction",
                "start_date": "1937"
            },
            {
                "occupational_title": "Construction Engineer",
                "workplace": "Tegelbrick Central Union Stockholm",
                "industry": "Construction",
                "start_date": "1942"
            },
            {
                "occupational_title": "Chief Engineer",
                "workplace": "Building Firm Anders Diös",
                "industry": "Construction",
                "start_date": "1944"
            }
        ]
    }
}