{
    "original": "ALMQVIST, Ernst Olof Daniel, Civilingenjör, Göteborg, f Mta verkst 19/10 82 av dir S A o Agnes Norrman, gm Signe Berteisen. Studex Gbg 01, CTH (skeppsbyggn) 04, varvs- o verkst.prakt Sv, Danm, Tyskl o Engl 04—08. Verkst- o driftsing Götavkn 08—17, AB Bonthrons Gbgskont 18—21, dir Spec.maskiner i Gbg AB 22—33, styr.ordf sed. 34. Styr.led SSJE 10—15, GKSS 16—21, i Tekn samf :s nmd sed. 32. Studieres ss ovan samt i USA 15. Av trycket: Reseberätt i Tekn Tidskr.",
    "translated": "ALMQVIST, Ernst Olof Daniel, Civil Engineer, Gothenburg, born on October 19, 1882, son of S A and Agnes Norrman, married Signe Berteisen. Completed studies in Gothenburg in 1901 and at the Chalmers University of Technology (naval architecture) in 1904. Practical training in shipyards and engineering in Sweden, Denmark, Germany, and England from 1904 to 1908. Engineering and management positions at Götaverken from 1908 to 1917, AB Bonthrons Gothenburg branch office from 1918 to 1921, director of Spec.maskiner in Gothenburg AB from 1922 to 1933, serving as chairman of the board since 1934. Board member of the Swedish Society of Naval Engineers from 1910 to 1915, Royal Gothenburg Yacht Club from 1916 to 1921, and the Technical Society's board since 1932. Studied abroad in the United States in 1915. Published a travel narrative in the Technical Journal.",
    "structured": {
        "@context": "https://schema.org/",
        "@type": "Person",
        "name": "Ernst Olof Daniel Almqvist",
        "birthDate": "1882-10-19",
        "birthPlace": "Gothenburg",
        "spouse": {
            "@type": "Person",
            "name": "Signe Berteisen"
        },
        "parents": [
            {
                "@type": "Person",
                "name": "S A Norrman"
            },
            {
                "@type": "Person",
                "name": "Agnes Norrman"
            }
        ],
        "occupation": "Civil Engineer",
        "education": [
            {
                "@type": "EducationalOccupationalCredential",
                "credentialCategory": "studex",
                "educationalLevel": "Graduate",
                "educationCredentialAwarded": "Gbg 01"
            },
            {
                "@type": "EducationalOccupationalCredential",
                "credentialCategory": "CTH (skeppsbyggn)",
                "educationalLevel": "Bachelor",
                "educationCredentialAwarded": "04"
            }
        ],
        "employmentHistory": [
            {
                "@type": "Organization",
                "name": "Götaverken",
                "category": "Engineering",
                "startDate": "1908",
                "endDate": "1917"
            },
            {
                "@type": "Organization",
                "name": "AB Bonthrons Gothenburg branch office",
                "category": "Engineering",
                "startDate": "1918",
                "endDate": "1921"
            },
            {
                "@type": "Organization",
                "name": "Spec.maskiner in Gothenburg AB",
                "category": "Engineering",
                "position": "Director",
                "startDate": "1922",
                "endDate": "1933"
            },
            {
                "@type": "Organization",
                "name": "Spec.maskiner in Gothenburg AB",
                "category": "Engineering",
                "position": "Chairman of the Board",
                "startDate": "1934"
            }
        ],
        "boardMembership": [
            {
                "@type": "Organization",
                "name": "Swedish Society of Naval Engineers",
                "startDate": "1910",
                "endDate": "1915"
            },
            {
                "@type": "Organization",
                "name": "Royal Gothenburg Yacht Club",
                "startDate": "1916",
                "endDate": "1921"
            },
            {
                "@type": "Organization",
                "name": "Technical Society",
                "position": "Board Member",
                "startDate": "1932"
            }
        ],
        "travelHistory": [
            {
                "@type": "Organization",
                "name": "United States",
                "startDate": "1915"
            }
        ],
        "publications": [
            {
                "@type": "Article",
                "name": "Reseberätt i Tekn Tidskr."
            }
        ]
    },
    "occupations": {
        "career": [
            {
                "occupational_title": "Civil Engineer",
                "workplace": "Gothenburg",
                "industry": null,
                "start_date": null
            },
            {
                "occupational_title": "Practical training in shipyards and engineering",
                "workplace": "Sweden, Denmark, Germany, England",
                "industry": null,
                "start_date": "1904"
            },
            {
                "occupational_title": "Engineering and management positions",
                "workplace": "Götaverken",
                "industry": null,
                "start_date": "1908"
            },
            {
                "occupational_title": "Engineering and management positions",
                "workplace": "AB Bonthrons Gothenburg branch office",
                "industry": null,
                "start_date": "1918"
            },
            {
                "occupational_title": "Director",
                "workplace": "Spec.maskiner in Gothenburg AB",
                "industry": null,
                "start_date": "1922"
            }
        ]
    }
}