{
    "original": "KREUGER, Henrik, Professor emeritus, Stockholm, f Kalmar 24/6 82 av konsul O L K o Ebba Sparre, gm Greta Göransson. Studex Kmr, ex KTH (V o V) 04. Anst ing F Söder-bergh 04—08, ass KTH 05—09, eg konsult verksamh i byggn.fack fr 08, tf prof i väg- o brobyggnadskonst KTH 09—11, prof i byggn.-tekn KTH 14—23, prorektor 27—31, rektor 31—43. Suppl Sthlms stads byggn.nmd 19, byggn.styr:s sakk f byggn.tekn fråg, sakk v utarb av försl t statl normer f järnkonstrukt f byggn av betong o armerad bet, d:o f el linjebyggn, byggnflm i kommunikat.dep 21, broråd f SJ :s bro över Årsta holmar 23, prisdom v int tävl om Västerbron 30, led dir f stat väginst 38, 40 års utredn f tekn vet forskn ordnande, 40 års sakk f högre tekn undervisn ordn, styr.led stat provn.anst 41, ordf byggn.-forskn.ktén 42; stdsflm 23—37, styr.led Sthlms stadsbibliot 23. Av trycket en mängd art om byggn.mtrl o deras egensk, klimat påverkn på byggn, grundläggn för hus- o brobyggn, »Husbyggn.tekn» i De Tekn Vetensk, öl byggn.konstr :s värmeisoler.förinåga, akust probl mm. KNOlkl, KDDOlgr, S :t EriksM; fil hed.dr Upps 27, LIVA 20, LVA 32, LKrVA 37.",
    "translated": "KREUGER, Henrik, Professor Emeritus, Stockholm, b. Kalmar 24/6 82, son of consul O L K and Ebba Sparre, m. Greta Göransson. Graduated from Kmr, former student of KTH (V and V) in 1904. Employed at F Söderbergh from 1904 to 1908, assistant at KTH from 1905 to 1909, worked as a consultant in the construction field from 1908, temporary professor in road and bridge construction at KTH from 1909 to 1911, professor of building technology at KTH from 1914 to 1923, vice chancellor from 1927 to 1931, rector from 1931 to 1943. Supplementary member of Stockholm city's building committee in 1919, member of the building board's expert group on building technology issues, expert in the development of national standards for iron construction and construction of concrete and reinforced concrete structures, expert in electric power line construction, member of the building film committee in the Ministry of Communications in 1921, member of the bridge council for SJ's bridge over Årsta Holmar in 1923, judge in the international competition for Västerbron in 1930, director of the state road institute in 1938, member of the 40-year investigation on organizing technical and scientific research, member of the 40-year expert group on organizing higher technical education, chairman of the building research committee in 1942; member of the Board of Directors of Stockholm Film AB from 1923 to 1937, board member of Stockholm City Library in 1923. Published numerous articles on building materials and their properties, the impact of climate on buildings, foundation construction for houses and bridges, \"Husbyggn.tekn\" in De Tekn Vetensk, the thermal insulation properties of building structures, acoustic problems, etc. Decorated with KNOlkl, KDDOlgr, S :t EriksM; received an honorary doctorate from Uppsala University in 1927, member of LIVA in 1920, LVA in 1932, LKrVA in 1937.",
    "structured": {
        "@context": "https://schema.org",
        "@type": "Person",
        "name": "Henrik Kreuger",
        "jobTitle": "Professor Emeritus",
        "address": {
            "@type": "PostalAddress",
            "addressLocality": "Stockholm"
        },
        "birthDate": "1882-06-24",
        "birthPlace": "Kalmar",
        "parents": [
            {
                "@type": "Person",
                "name": "O L K Kreuger",
                "jobTitle": "Consul"
            },
            {
                "@type": "Person",
                "name": "Ebba Sparre"
            }
        ],
        "spouse": [
            {
                "@type": "Person",
                "name": "Greta Göransson"
            }
        ],
        "education": {
            "@type": "EducationalOccupationalCredential",
            "credentialCategory": "Graduation",
            "educationalLevel": "Studex Kmr"
        },
        "alumniOf": [
            {
                "@type": "CollegeOrUniversity",
                "name": "KTH",
                "location": "Stockholm",
                "startDate": "1904",
                "endDate": "1909"
            }
        ],
        "employmentHistory": [
            {
                "@type": "Organization",
                "name": "F Söderbergh",
                "startDate": "1904",
                "endDate": "1908",
                "jobTitle": "Employee"
            },
            {
                "@type": "Organization",
                "name": "KTH",
                "startDate": "1905",
                "endDate": "1909",
                "jobTitle": "Assistant"
            }
        ],
        "consultancy": {
            "@type": "OrganizationRole",
            "roleName": "Consultant",
            "startDate": "1908"
        },
        "academicPositions": [
            {
                "@type": "OrganizationRole",
                "roleName": "Temporary Professor",
                "startDate": "1909",
                "endDate": "1911",
                "affiliation": {
                    "@type": "CollegeOrUniversity",
                    "name": "KTH"
                },
                "field": "Road and Bridge Construction"
            },
            {
                "@type": "OrganizationRole",
                "roleName": "Professor of Building Technology",
                "startDate": "1914",
                "endDate": "1923",
                "affiliation": {
                    "@type": "CollegeOrUniversity",
                    "name": "KTH"
                }
            },
            {
                "@type": "OrganizationRole",
                "roleName": "Vice Chancellor",
                "startDate": "1927",
                "endDate": "1931"
            },
            {
                "@type": "OrganizationRole",
                "roleName": "Rector",
                "startDate": "1931",
                "endDate": "1943"
            }
        ],
        "committeeMemberships": [
            {
                "@type": "OrganizationRole",
                "roleName": "Member of 40-year Investigation",
                "startDate": "1938"
            },
            {
                "@type": "OrganizationRole",
                "roleName": "Member of 40-year Expert Group",
                "startDate": "1938"
            },
            {
                "@type": "OrganizationRole",
                "roleName": "Chairman of Building Research Committee",
                "startDate": "1942"
            }
        ],
        "expertise": [
            "Development of National Standards for Iron Construction",
            "Construction of Concrete and Reinforced Concrete Structures",
            "Electric Power Line Construction"
        ],
        "projects": [
            {
                "@type": "Project",
                "name": "SJ's Bridge over Årsta Holmar",
                "startDate": "1923",
                "endDate": "1923",
                "affiliation": {
                    "@type": "Organization",
                    "name": "SJ"
                }
            },
            {
                "@type": "Project",
                "name": "Västerbron International Competition",
                "startDate": "1930",
                "endDate": "1930"
            },
            {
                "@type": "Project",
                "name": "State Road Institute",
                "startDate": "1938",
                "endDate": "1938",
                "affiliation": {
                    "@type": "Organization",
                    "name": "State Road Institute"
                }
            }
        ],
        "publications": [
            {
                "@type": "Article",
                "name": "Building Materials and Their Properties"
            },
            {
                "@type": "Article",
                "name": "Impact of Climate on Buildings"
            },
            {
                "@type": "Article",
                "name": "Foundation Construction for Houses and Bridges"
            },
            {
                "@type": "Article",
                "name": "Husbyggn.tekn in De Tekn Vetensk"
            },
            {
                "@type": "Article",
                "name": "Thermal Insulation Properties of Building Structures"
            },
            {
                "@type": "Article",
                "name": "Acoustic Problems"
            }
        ],
        "awards": [
            {
                "@type": "Order",
                "name": "KNOlkl"
            },
            {
                "@type": "Order",
                "name": "KDDOlgr"
            },
            {
                "@type": "Order",
                "name": "S:t EriksM"
            }
        ],
        "honoraryDegrees": [
            {
                "@type": "EducationalOccupationalCredential",
                "name": "Doctor of Philosophy",
                "awardDate": "1927",
                "awardingInstitution": {
                    "@type": "CollegeOrUniversity",
                    "name": "Uppsala University"
                }
            }
        ],
        "memberships": [
            {
                "@type": "OrganizationRole",
                "roleName": "Member",
                "startDate": "1920",
                "affiliation": {
                    "@type": "Organization",
                    "name": "LIVA"
                }
            },
            {
                "@type": "OrganizationRole",
                "roleName": "Member",
                "startDate": "1932",
                "affiliation": {
                    "@type": "Organization",
                    "name": "LVA"
                }
            },
            {
                "@type": "OrganizationRole",
                "roleName": "Member",
                "startDate": "1937",
                "affiliation": {
                    "@type": "Organization",
                    "name": "LKrVA"
                }
            }
        ]
    },
    "occupations": {
        "career": [
            {
                "occupational_title": "Student",
                "workplace": "KTH (Royal Institute of Technology)",
                "industry": "Education",
                "start_date": "1904"
            },
            {
                "occupational_title": "Employee",
                "workplace": "F Söderbergh",
                "industry": "Construction",
                "start_date": "1904"
            },
            {
                "occupational_title": "Assistant",
                "workplace": "KTH (Royal Institute of Technology)",
                "industry": "Education",
                "start_date": "1905"
            },
            {
                "occupational_title": "Consultant",
                "workplace": "Building industry",
                "industry": "Construction",
                "start_date": "1908"
            },
            {
                "occupational_title": "Temporary Professor",
                "workplace": "KTH (Royal Institute of Technology)",
                "industry": "Education",
                "start_date": "1909"
            },
            {
                "occupational_title": "Professor",
                "workplace": "KTH (Royal Institute of Technology)",
                "industry": "Education",
                "start_date": "1914"
            },
            {
                "occupational_title": "Vice Chancellor",
                "workplace": "KTH (Royal Institute of Technology)",
                "industry": "Education",
                "start_date": "1927"
            },
            {
                "occupational_title": "Rector",
                "workplace": "KTH (Royal Institute of Technology)",
                "industry": "Education",
                "start_date": "1931"
            }
        ]
    }
}