{
    "original": "GELHAAR, Stefan Julius, Ingenjör, Ljungaverk, f O van s j ö, Gävleb l, 26/12 76 av skom o fältmusikanten E G o Anna Holmström, gm (2) Inez Rur. Arb v Hofors hästskofabr Ås-hammar 91, målarlärl o arb Hedesunda o Gävle 92—98, lab.bitr Sthlms Superfosf.fabr AB :s kloratfabr Månsbo 98, l :e ass v fabr.lab där 04, v exp.lab 07, förest detta 14, lab.förest o bibi v bol:s fil Ljungaverk sed. 28. Kom-munalflm Grytnäs 19—25 mm. Led Sv Tekn.frn samt Sv Uppfinnarefrn. Av trycket: Med-arb i Ullmans Encyklopedie der techn Chemie, upps i Tekn Tidskr. ProPstGM.",
    "translated": "GELHAAR, Stefan Julius, Engineer, Ljungaverk, born on the island of Van in the Gävleborg County, December 26, 1876, son of the shoemaker and field musician E G and Anna Holmström, married (2) Inez Rur. Worked at the Hofors horse shoe factory Åshammar from 1891, apprentice painter and worked in Hedesunda and Gävle from 1892 to 1898, laboratory assistant at Stockholm Superphosphate Factory AB's chlorate factory in Månsbo in 1898, promoted to first assistant in 1904, promoted to chief of experimentation in 1907, former head of department in 1914, laboratory supervisor and librarian at the company's headquarters in Ljungaverk since 1928. Municipal official in Grytnäs from 1919 to 1925, among other positions. Member of the Swedish Society of Technicians and the Swedish Inventors' Association. Contributed to Ullmans Encyclopedia of Chemical Technology, published in Technical Journal. ProPstGM.\n\nNote: The abbreviation \"ProPstGM\" is not clear and cannot be translated without further context.",
    "structured": {
        "@context": "https://schema.org",
        "@type": "Person",
        "name": "Stefan Julius Gelhaar",
        "birthDate": "1876-12-26",
        "birthPlace": {
            "@type": "Place",
            "name": "Gävleborg County, Sweden"
        },
        "deathDate": null,
        "jobTitle": "Engineer",
        "memberOf": [
            {
                "@type": "Organization",
                "name": "Swedish Society of Technicians"
            },
            {
                "@type": "Organization",
                "name": "Swedish Inventors' Association"
            }
        ],
        "spouse": [
            {
                "@type": "Person",
                "name": "Inez Rur",
                "familyName": "Rur"
            }
        ],
        "parents": [
            {
                "@type": "Person",
                "name": "E G Gelhaar",
                "familyName": "Gelhaar",
                "jobTitle": "Shoemaker and Field Musician"
            },
            {
                "@type": "Person",
                "name": "Anna Holmström",
                "familyName": "Holmström"
            }
        ],
        "worksFor": {
            "@type": "Organization",
            "name": "Stockholm Superphosphate Factory AB",
            "parentOrganization": {
                "@type": "Organization",
                "name": "Hofors Horse Shoe Factory"
            }
        },
        "occupation": {
            "@type": "OrganizationRole",
            "startDate": "1891",
            "endDate": null,
            "roleName": "Apprentice Painter",
            "namedPosition": "Hedesunda and Gävle"
        },
        "deathPlace": null
    },
    "occupations": {
        "career": [
            {
                "occupational_title": "Apprentice Painter",
                "workplace": "Hedesunda",
                "industry": "Painting",
                "start_date": "1892"
            },
            {
                "occupational_title": "Apprentice Painter",
                "workplace": "Gävle",
                "industry": "Painting",
                "start_date": "1892"
            },
            {
                "occupational_title": "Lab Assistant",
                "workplace": "Stockholm Superphosphate Factory AB - Månsbo",
                "industry": "Chemical manufacturing",
                "start_date": "1898"
            },
            {
                "occupational_title": "First Assistant",
                "workplace": "Stockholm Superphosphate Factory AB - Månsbo",
                "industry": "Chemical manufacturing",
                "start_date": "1904"
            },
            {
                "occupational_title": "Chief of Experimentation",
                "workplace": "Stockholm Superphosphate Factory AB - Månsbo",
                "industry": "Chemical manufacturing",
                "start_date": "1907"
            },
            {
                "occupational_title": "Head of Department",
                "workplace": "Stockholm Superphosphate Factory AB - Månsbo",
                "industry": "Chemical manufacturing",
                "start_date": "1914"
            },
            {
                "occupational_title": "Laboratory Supervisor and Librarian",
                "workplace": "Company's headquarters in Ljungaverk",
                "industry": "Chemical manufacturing",
                "start_date": "1928"
            }
        ]
    }
}