{
    "original": "DOL.FE, Gustav, Kapten, Direktör, Göteborg, f Nittorp, Älvsb l, 11/4 90 av dåv lantbr.insp, sedermera grhdl And D o Jenny Johansson, gm Asta Jansson. Studex Gbgs Real-lärov 10, inskr v CTH 11 o v GbHS 14. Resoff v Fortif 12, krigsmobil Bodens fästning 14 o 39, kapt i res v Ing.trupperna. Huvud-deläg i fma Dolfe &amp; Co i Gbg (smör, ost, ägg, margarin o honung samt smör- o äggexp; start 00), kgl hovlev 24, vkst dir i Dolfe &amp; CoAB sed. grund 33, inneh tillika Dolfes Smöraffär i Grästorp (grund 34). Ag fastigh i Gbg samt lantställe. Rev i Gbgs hdlskamm. Ordf i Kommunalföreningarnas Samorg i Gbg o i Fp:s lia valkrets där. Frimurare.",
    "translated": "DOL.FE, Gustav, Captain, Director, Gothenburg, born in Nittorp, Älvsborg county, on April 11th, 1890, son of the late agricultural inspector And D and Jenny Johansson. Married to Asta Jansson. Graduated from Gothenburg Real School in 1910, enrolled at Chalmers University of Technology in 1911 and Gothenburg Handelsskola in 1914. Reserve officer at Fortif from 1912, called to military service at Boden Fortress in 1914 and 1939, captain in the reserve infantry. Main owner of the company Dolfe & Co in Gothenburg (butter, cheese, eggs, margarine, and honey, as well as butter and egg exports; established in 1900), appointed royal court supplier in 1924, managing director of Dolfe & Co AB since its foundation in 1933, also owner of Dolfes Smöraffär in Grästorp (established in 1934). Owned properties in Gothenburg and a country estate. Member of the board of the Gothenburg Chamber of Commerce. Chairman of the Municipal Associations' Joint Organization in Gothenburg and the Liberal People's Party in the local constituency. Freemason.",
    "structured": {
        "@context": "https://schema.org",
        "@type": "Person",
        "name": "Gustav Dolfe",
        "birthDate": "1890-04-11",
        "birthPlace": "Nittorp, Älvsborg County",
        "deathDate": "",
        "deathPlace": "",
        "nationality": "Swedish",
        "occupation": [
            "Captain",
            "Director"
        ],
        "address": {
            "@type": "PostalAddress",
            "addressLocality": "Gothenburg"
        },
        "parents": [
            {
                "@type": "Person",
                "name": "And D"
            },
            {
                "@type": "Person",
                "name": "Jenny Johansson"
            }
        ],
        "spouse": "Asta Jansson",
        "education": [
            {
                "@type": "EducationalOrganization",
                "name": "Gothenburg Real School",
                "startDate": "1910"
            },
            {
                "@type": "EducationalOrganization",
                "name": "Chalmers University of Technology",
                "startDate": "1911"
            },
            {
                "@type": "EducationalOrganization",
                "name": "Gothenburg Handelsskola",
                "startDate": "1914"
            }
        ],
        "memberOf": [
            {
                "@type": "Organization",
                "name": "Fortif",
                "roleName": "Reserve Officer",
                "startDate": "1912"
            },
            {
                "@type": "Organization",
                "name": "Boden Fortress",
                "roleName": "Military Service",
                "startDate": "1914, 1939"
            },
            {
                "@type": "Organization",
                "name": "Dolfe & Co",
                "roleName": "Main Owner",
                "startDate": "1900"
            },
            {
                "@type": "Organization",
                "name": "Dolfe & Co AB",
                "roleName": "Managing Director",
                "startDate": "1933"
            },
            {
                "@type": "Organization",
                "name": "Dolfes Smöraffär",
                "roleName": "Owner",
                "startDate": "1934"
            },
            {
                "@type": "Organization",
                "name": "Gothenburg Chamber of Commerce",
                "roleName": "Board Member"
            },
            {
                "@type": "Organization",
                "name": "Municipal Associations' Joint Organization",
                "roleName": "Chairman",
                "location": "Gothenburg"
            },
            {
                "@type": "Organization",
                "name": "Liberal People's Party",
                "roleName": "Chairman",
                "location": "Local Constituency"
            },
            {
                "@type": "Organization",
                "name": "Frimurare"
            }
        ]
    },
    "occupations": {
        "career": [
            {
                "occupational_title": "Captain",
                "workplace": "Fortif",
                "industry": "Military",
                "start_date": "1912"
            },
            {
                "occupational_title": "Director",
                "workplace": "Dolfe & Co",
                "industry": "Food and Beverage",
                "start_date": "1900"
            },
            {
                "occupational_title": "Managing Director",
                "workplace": "Dolfe & Co AB",
                "industry": "Food and Beverage",
                "start_date": "1933"
            }
        ]
    }
}