{
    "original": "LUNDBERG, Hans Torkel Fredrik, Bergsingenjör, Toronto, Ontario, Canada, f Malmö, 22/7 93 av disp C T L o Emma Bong, gm Signe Sjöberg. Studex Sthlm 12, KTH (bergs) 17. Ass bergshögsk 18—19, ing AB Bergsbyrån 18—22, l:a ing AB El Malmletn 23—26, manager of fieldwork Swedish American Pro-specting Corp N. Y., USA, 24—26, manager o v. pres där 29—33, d:o Swed Amer Prosp Co of Canada Ltd, Toronto, konsult geofys 34, manager o pres Hans Lundberg Ltd Montreal Canada sed. 35. Uppf o utveckl fi prakt metod f uppsökn av malmer. Vidstr resor i Europ o Amer v malmletn.arb, geofys unders på Grönl maj—nov 42. Av trycket: Upps o avhandl om el o magn malmletn, publ av bl a Sv Geol unders, Canadian Inst of Min and Metallurg Engineers, Soc of Economical Geo-logists, Mining and Metallurg Soc of Amer, Amer Inst of and Metallurg Eng, N. Y. VA:s GM 25 f arb om el malmletn. Hobby: Frimärkssamling. Två söner i aktiv kanadensisk flygtjänst.",
    "translated": "LUNDBERG, Hans Torkel Fredrik, Mining Engineer, Toronto, Ontario, Canada, born in Malmö on July 22nd, 1893 to Karl Torkel Lundberg and Emma Bong, married to Signe Sjöberg. Graduated from Stockholm University in 1912, KTH (Royal Institute of Technology) in 1917. Assistant at the Geological Institute from 1918 to 1919, engineer at AB Bergsbyrån from 1918 to 1922, first engineer at AB El Malmletn from 1923 to 1926. Manager of fieldwork at the Swedish American Prospecting Corporation in New York, USA, from 1924 to 1926, and vice president from 1929 to 1933. Also manager and president of the Swed Amer Prosp Co of Canada Ltd in Toronto. Consultant in geophysics from 1934, manager and president of Hans Lundberg Ltd in Montreal, Canada since 1935. Developed practical methods for ore prospecting and conducted extensive travels in Europe, America, and Greenland for mining research and geophysical surveys from May to November 1942. Published works on electrical and magnetic ore prospecting, including publications by the Swedish Geological Survey, the Canadian Institute of Mining and Metallurgical Engineers, the Society of Economic Geologists, the Mining and Metallurgical Society of America, and the American Institute of Mining and Metallurgical Engineers. Received the GM 25 award from the Va Institute for his work on electrical ore prospecting. Hobby: Stamp collection. Two sons serving in the Canadian aviation service.",
    "structured": {
        "@context": "https://schema.org",
        "@type": "Person",
        "givenName": "Hans",
        "additionalName": "Torkel Fredrik",
        "familyName": "Lundberg",
        "birthDate": "1893-07-22",
        "birthPlace": "Malmö",
        "deathDate": null,
        "description": "Mining Engineer",
        "jobTitle": "Mining Engineer",
        "address": {
            "@type": "PostalAddress",
            "addressLocality": "Toronto",
            "addressRegion": "Ontario",
            "addressCountry": "Canada"
        },
        "parents": [
            {
                "@type": "Person",
                "name": "Karl Torkel Lundberg"
            },
            {
                "@type": "Person",
                "name": "Emma Bong"
            }
        ],
        "spouse": {
            "@type": "Person",
            "name": "Signe Sjöberg"
        },
        "alumniOf": [
            {
                "@type": "CollegeOrUniversity",
                "name": "Stockholm University",
                "startDate": "1912",
                "endDate": null
            },
            {
                "@type": "CollegeOrUniversity",
                "name": "KTH (Royal Institute of Technology)",
                "startDate": "1917",
                "endDate": null
            }
        ],
        "worksFor": [
            {
                "@type": "Organization",
                "name": "AB Bergsbyrån",
                "jobTitle": "Engineer",
                "startDate": "1918",
                "endDate": "1922"
            },
            {
                "@type": "Organization",
                "name": "AB El Malmletn",
                "jobTitle": "First Engineer",
                "startDate": "1923",
                "endDate": "1926"
            },
            {
                "@type": "Organization",
                "name": "Swedish American Prospecting Corporation",
                "jobTitle": "Fieldwork Manager",
                "startDate": "1924",
                "endDate": "1926"
            },
            {
                "@type": "Organization",
                "name": "Swed Amer Prosp Co of Canada Ltd",
                "jobTitle": "Manager and President",
                "address": {
                    "@type": "PostalAddress",
                    "addressLocality": "Toronto",
                    "addressCountry": "Canada"
                }
            },
            {
                "@type": "Organization",
                "name": "Hans Lundberg Ltd",
                "jobTitle": "Manager and President",
                "address": {
                    "@type": "PostalAddress",
                    "addressLocality": "Montreal",
                    "addressCountry": "Canada"
                },
                "startDate": "1935",
                "endDate": null
            }
        ],
        "memberOf": [
            {
                "@type": "Organization",
                "name": "Geological Institute",
                "jobTitle": "Assistant",
                "startDate": "1918",
                "endDate": "1919"
            }
        ],
        "award": {
            "@type": "MonetaryAmount",
            "name": "GM 25"
        },
        "sameAs": [
            "https://en.wikipedia.org/wiki/Hans_Torkel_Fredrik_Lundberg"
        ],
        "hasOccupation": {
            "@type": "Occupation",
            "name": "Mining Engineer"
        },
        "nationality": "Canadian",
        "hobbies": [
            "Stamp collection"
        ],
        "children": [
            {
                "@type": "Person",
                "name": "Son 1",
                "memberOf": [
                    {
                        "@type": "Organization",
                        "name": "Canadian aviation service"
                    }
                ]
            },
            {
                "@type": "Person",
                "name": "Son 2",
                "memberOf": [
                    {
                        "@type": "Organization",
                        "name": "Canadian aviation service"
                    }
                ]
            }
        ]
    },
    "occupations": {
        "career": [
            {
                "occupational_title": "Assistant",
                "workplace": "Geological Institute",
                "industry": "Geology",
                "start_date": "1918"
            },
            {
                "occupational_title": "Engineer",
                "workplace": "AB Bergsbyrån",
                "industry": "Mining",
                "start_date": "1918"
            },
            {
                "occupational_title": "Engineer",
                "workplace": "AB El Malmletn",
                "industry": "Mining",
                "start_date": "1923"
            },
            {
                "occupational_title": "Manager of fieldwork",
                "workplace": "Swedish American Prospecting Corporation",
                "industry": "Mining",
                "start_date": "1924"
            },
            {
                "occupational_title": "Vice President",
                "workplace": "Swedish American Prospecting Corporation",
                "industry": "Mining",
                "start_date": "1929"
            },
            {
                "occupational_title": "Manager and President",
                "workplace": "Swed Amer Prosp Co of Canada Ltd",
                "industry": "Mining",
                "start_date": "1935"
            },
            {
                "occupational_title": "Consultant in Geophysics",
                "workplace": "Self-employed",
                "industry": "Geophysics",
                "start_date": "1934"
            },
            {
                "occupational_title": "Manager and President",
                "workplace": "Hans Lundberg Ltd",
                "industry": "Mining",
                "start_date": "1935"
            }
        ]
    }
}