{
    "original": "BERGGREN, Gunnar Eberhard, Direktör, v. Konsul, Kalmar, f Kalmar 23/9 82 av gross-handl Carl Hj L B o Lydia M Sjögren, gm Margit Hofverberg. Studex Kalm 02, Schart hldsinst 02—03, språk- o merk stud. Anst i Kalm ensk bk o bkAB S. Sv, styr.led 08, led. i AB Bröderna Berggren (gr. 78), vkst dir sed. 10. Stdsflm 26—38 i belysn.styr 22—38, tax.-nmdn 18—36, högre folksk, bibl.styr, v. ordf o sekr i Kalm ind- o köpm.fören mfl off. uppdr. Styr.led i AB Kalm nya tapetfabr 24, i Smal ensk bks avd.kont 28, i Smal stadshyp.fören 41, ordf i Sv Röda K i Kalm 20, sekr i De blindas vänner 22, ordf i Kalm somm.stugor. Barnens dag mm. Resor: Tyskl o Estl. Av trycket: Fältprosten Johan Gabr Berggren o hans ättl mm. RVO, EVSO, Sv köpm.förb hed. t. g, Sv Röda K f ört j. t. s.",
    "translated": "BERGGREN, Gunnar Eberhard, Director, Vice Consul, Kalmar, b. Kalmar 23/9 1882 to merchant Carl Hj L B and Lydia M Sjögren, m. Margit Hofverberg. Studied at Kalm 02, Schart held position 02-03, language and culture studies. Employed at Kalm private bank and bkAB S. Sv, became board member in 1908, member of AB Bröderna Berggren (since 1878), promoted to managing director in 1910. Member of lighting committee 1922-1938, tax committee member 1918-1936, higher primary school, library board member, vice chair and secretary in Kalmar industrial and commercial association, among other official positions. Board member of AB Kalm new wallpaper factory in 1924, of Småland private bank's department office in 1928, of Småland city housing association in 1941, chair of Swedish Red Cross in Kalmar in 1920, secretary of Friends of the Blind in 1922, chair of Kalmar summer cottages. Children's day, etc. Travels: Germany and Estonia. Publications: Lieutenant Colonel Johan Gabr Berggren and his descendants, etc. Awarded with Royal Order of Vasa, Royal Order of the Sword, honorary member of Swedish merchants' association, Swedish Red Cross gold medal for exceptional service.",
    "structured": {
        "@context": "http://schema.org",
        "@type": "Person",
        "name": "Gunnar Eberhard Berggren",
        "birthDate": "1882-09-23",
        "birthPlace": "Kalmar, Sweden",
        "deathDate": null,
        "nationality": "Swedish",
        "description": "Director, Vice Consul",
        "alumniOf": {
            "@type": "EducationalOrganization",
            "name": "Kalm"
        },
        "parents": [
            {
                "@type": "Person",
                "name": "Carl Hj L Berggren",
                "description": "Merchant"
            },
            {
                "@type": "Person",
                "name": "Lydia M Sjögren",
                "description": "n/a"
            }
        ],
        "spouse": {
            "@type": "Person",
            "name": "Margit Hofverberg"
        },
        "worksFor": {
            "@type": "Organization",
            "name": "Kalmar Private Bank"
        },
        "memberOf": [
            {
                "@type": "Organization",
                "name": "AB Bröderna Berggren",
                "startDate": "1878"
            }
        ],
        "boardMemberIn": [
            {
                "@type": "Organization",
                "name": "AB Bröderna Berggren",
                "startDate": "1878",
                "endDate": "1910"
            },
            {
                "@type": "Organization",
                "name": "AB Kalm New Wallpaper Factory",
                "startDate": "1924",
                "endDate": null
            },
            {
                "@type": "Organization",
                "name": "Småland Private Bank - Department Office",
                "startDate": "1928",
                "endDate": null
            },
            {
                "@type": "Organization",
                "name": "Småland City Housing Association",
                "startDate": "1941",
                "endDate": null
            }
        ],
        "occupationalCategory": "Business",
        "boardMember": [
            {
                "@type": "Organization",
                "name": "AB Kalm New Wallpaper Factory",
                "startDate": "1924",
                "endDate": null
            },
            {
                "@type": "Organization",
                "name": "Småland Private Bank - Department Office",
                "startDate": "1928",
                "endDate": null
            }
        ],
        "deathPlace": null,
        "affiliations": [
            {
                "@type": "Organization",
                "name": "Kalmar Industrial and Commercial Association",
                "position": [
                    "Vice Chair",
                    "Secretary"
                ]
            }
        ],
        "publications": [
            {
                "@type": "Article",
                "name": "Fältprosten Johan Gabr Berggren o hans ättl mm"
            }
        ],
        "awards": [
            {
                "@type": "Order",
                "name": "Royal Order of Vasa"
            },
            {
                "@type": "Order",
                "name": "Royal Order of the Sword"
            }
        ]
    },
    "occupations": {
        "career": [
            {
                "occupational_title": "Director",
                "workplace": "Kalm private bank and bkAB S. Sv",
                "industry": "Banking",
                "start_date": "Unknown"
            },
            {
                "occupational_title": "Board member",
                "workplace": "AB Bröderna Berggren",
                "industry": "Unknown",
                "start_date": "Unknown"
            },
            {
                "occupational_title": "Managing Director",
                "workplace": "AB Bröderna Berggren",
                "industry": "Unknown",
                "start_date": "1910"
            },
            {
                "occupational_title": "Member of Lighting Committee",
                "workplace": "Unknown",
                "industry": "Unknown",
                "start_date": "1922"
            },
            {
                "occupational_title": "Member of Tax Committee",
                "workplace": "Unknown",
                "industry": "Unknown",
                "start_date": "1918"
            },
            {
                "occupational_title": "Board member",
                "workplace": "AB Kalm new wallpaper factory",
                "industry": "Wallpaper manufacturing",
                "start_date": "1924"
            },
            {
                "occupational_title": "Board member",
                "workplace": "Småland private bank's department office",
                "industry": "Banking",
                "start_date": "1928"
            },
            {
                "occupational_title": "Chair",
                "workplace": "Swedish Red Cross in Kalmar",
                "industry": "Non-profit organization",
                "start_date": "1920"
            },
            {
                "occupational_title": "Secretary",
                "workplace": "Friends of the Blind",
                "industry": "Non-profit organization",
                "start_date": "1922"
            },
            {
                "occupational_title": "Chair",
                "workplace": "Kalmar summer cottages",
                "industry": "Hospitality",
                "start_date": "Unknown"
            }
        ]
    }
}