{
    "original": "EDENHOLM, Ivar Henrik Verner, Professor, Stockholm, f Göteryd, Kronob l, 19/8 01 av disp E G Swensson o Hulda Edenholm, gm Anna-Greta Petrini. Studex Kristianst 18, KTH (maskinbygg o mek tekn) 19—24. i:e ass KTH:s ångtekn lab 24—27, rektors bitr v underyisn i ångtekn KTH 27—31, d:o i läran om värmemotorer ht 28, ing AB Ljungströms Ångturbin 28—31, ing IVA:s ångvärmeinst 31 —33, förest f detta 34—40, nu prof KTH. Av trycket: The flame radiation in watercooled boiler furnaces (tills m T Lindmark i IVA:s handl 27), Laboratory test results with diffe-rent types of heating elements for Ljungström^ air preheaters (tills m A Lysholm, Världskraftkonf i Tokyo 29), ett flert upps i facktidskr. IVA 34—38. Led Sv Tekn.frn.",
    "translated": "EDENHOLM, Ivar Henrik Verner, Professor, Stockholm, born in Göteryd, Kronoberg county, on August 19, 1901 to parents E. G. Swensson and Hulda Edenholm. Married to Anna-Greta Petrini. Graduated from Kristianstad in 1918. Studied at KTH (Royal Institute of Technology) in mechanical engineering from 1919 to 1924. Assistant at KTH's steam technology laboratory from 1924 to 1927. Deputy to the rector for teaching in steam technology at KTH from 1927 to 1931. Also taught heat engines in the autumn of 1928. Engineer at AB Ljungström's Steam Turbine from 1928 to 1931. Engineer at IVA's (Royal Swedish Academy of Engineering Sciences) steam heating institute from 1931 to 1933. Head of the same institute from 1934 to 1940. Currently a professor at KTH. Published works include: \"The flame radiation in water-cooled boiler furnaces\" (co-authored with T. Lindmark in IVA's proceedings in 1927), \"Laboratory test results with different types of heating elements for Ljungström's air preheaters\" (co-authored with A. Lysholm, presented at the International Power Conference in Tokyo in 1929), and several articles in technical journals from 1934 to 1938. Member of the Royal Swedish Academy of Engineering Sciences.",
    "structured": {
        "@context": "https://schema.org",
        "@type": "Person",
        "name": "Ivar Henrik Verner Edenholm",
        "jobTitle": "Professor",
        "address": {
            "@type": "PostalAddress",
            "addressLocality": "Stockholm"
        },
        "birthPlace": {
            "@type": "Place",
            "address": {
                "@type": "PostalAddress",
                "addressLocality": "Göteryd",
                "addressRegion": "Kronoberg county"
            }
        },
        "birthDate": "1901-08-19",
        "parent": [
            {
                "@type": "Person",
                "name": "E. G. Swensson",
                "jobTitle": "disposition",
                "familyName": "Swensson"
            },
            {
                "@type": "Person",
                "name": "Hulda Edenholm",
                "familyName": "Edenholm"
            }
        ],
        "spouse": {
            "@type": "Person",
            "name": "Anna-Greta Petrini"
        },
        "alumniOf": [
            {
                "@type": "School",
                "name": "Kristianstad",
                "startDate": "1918"
            },
            {
                "@type": "EducationalOrganization",
                "name": "KTH (Royal Institute of Technology)",
                "startDate": "1919",
                "endDate": "1924",
                "department": {
                    "@type": "Organization",
                    "name": "Mechanical Engineering"
                }
            }
        ],
        "worksFor": [
            {
                "@type": "Organization",
                "name": "KTH (Royal Institute of Technology)",
                "jobTitle": "Assistant",
                "startDate": "1924",
                "endDate": "1927",
                "department": {
                    "@type": "Organization",
                    "name": "Steam Technology Laboratory"
                }
            },
            {
                "@type": "Organization",
                "name": "KTH (Royal Institute of Technology)",
                "jobTitle": "Deputy",
                "startDate": "1927",
                "endDate": "1931",
                "department": {
                    "@type": "Organization",
                    "name": "Teaching in Steam Technology"
                }
            },
            {
                "@type": "Organization",
                "name": "AB Ljungström's Steam Turbine",
                "jobTitle": "Engineer",
                "startDate": "1928",
                "endDate": "1931"
            },
            {
                "@type": "Organization",
                "name": "IVA's (Royal Swedish Academy of Engineering Sciences) Steam Heating Institute",
                "jobTitle": "Engineer",
                "startDate": "1931",
                "endDate": "1933"
            },
            {
                "@type": "Organization",
                "name": "IVA's (Royal Swedish Academy of Engineering Sciences) Steam Heating Institute",
                "jobTitle": "Head",
                "startDate": "1934",
                "endDate": "1940"
            }
        ],
        "memberOf": {
            "@type": "Organization",
            "name": "Royal Swedish Academy of Engineering Sciences"
        },
        "works": [
            {
                "@type": "Article",
                "name": "The flame radiation in water-cooled boiler furnaces",
                "coauthor": "T. Lindmark",
                "datePublished": "1927"
            },
            {
                "@type": "Article",
                "name": "Laboratory test results with different types of heating elements for Ljungström's air preheaters",
                "coauthor": "A. Lysholm",
                "conference": "International Power Conference",
                "datePublished": "1929"
            }
        ]
    },
    "occupations": {
        "career": [
            {
                "occupational_title": "Assistant, KTH's steam technology laboratory",
                "workplace": "KTH (Royal Institute of Technology)",
                "industry": "",
                "start_date": "1924"
            },
            {
                "occupational_title": "Deputy to the rector for teaching in steam technology",
                "workplace": "KTH (Royal Institute of Technology)",
                "industry": "",
                "start_date": "1927"
            },
            {
                "occupational_title": "Heat engines instructor",
                "workplace": "KTH (Royal Institute of Technology)",
                "industry": "",
                "start_date": "1928"
            },
            {
                "occupational_title": "Engineer",
                "workplace": "AB Ljungström's Steam Turbine",
                "industry": "",
                "start_date": "1928"
            },
            {
                "occupational_title": "Engineer",
                "workplace": "IVA's (Royal Swedish Academy of Engineering Sciences) steam heating institute",
                "industry": "",
                "start_date": "1931"
            },
            {
                "occupational_title": "Head of IVA's steam heating institute",
                "workplace": "IVA's (Royal Swedish Academy of Engineering Sciences) steam heating institute",
                "industry": "",
                "start_date": "1934"
            },
            {
                "occupational_title": "Professor",
                "workplace": "KTH (Royal Institute of Technology)",
                "industry": "",
                "start_date": ""
            }
        ]
    }
}