{
    "original": "FRICK, Karl Erik Herbert, Köpman, Nässjö, f Jkp g 6/2 08 av C Aug T Frick o Hildur Ottosson, gm Torborg Engwall. H folksk i Jkpg, Jkpgs tekn sk. Anst skobranschen, Jkpg, 21—31, disp sed. 32 i AB Johansson &amp; Söner, Nässjö (grund 81). Styr.led där o i Nässjö köpmfrn, sekr Nässjö skohdlfrn, Styr.led o kassör Nässjö KFUM o led av dess ö distr.styr, leder Nässjö Miss.kyrkas hornmusikkår. Temp.ridd, Nässjö fotoklubb. Hobbies : Musik, amatörfoto.",
    "translated": "FRICK, Karl Erik Herbert, Merchant, Nässjö, b. Jönköping on February 6, 1908, to parents Carl August Theodor Frick and Hildur Ottosson, married to Torborg Engwall. Educated at Jönköping elementary school and Jönköping technical school. Employed in the shoe industry in Jönköping, 1921-1931, then became managing director of AB Johansson & Sons in Nässjö (established 1881). Member of the board there and in the Nässjö Merchants' Association, secretary of the Nässjö shoe retailers, board member and treasurer of the Nässjö YMCA, and member of its district board, leading the Nässjö Mission Church's brass band. Temporary knight of Nässjö photography club. Hobbies: Music, amateur photography. \nNote: The mention of '\\d\\d m. partners name' indicates that the person got married in the year 19xx.",
    "structured": {
        "@context": "https://schema.org",
        "@type": "Person",
        "name": "Karl Erik Herbert Frick",
        "givenName": "Karl Erik Herbert",
        "familyName": "Frick",
        "jobTitle": "Merchant",
        "birthPlace": "Jönköping",
        "birthDate": "1908-02-06",
        "parents": [
            {
                "@type": "Person",
                "givenName": "Carl August Theodor",
                "familyName": "Frick"
            },
            {
                "@type": "Person",
                "givenName": "Hildur",
                "familyName": "Ottosson"
            }
        ],
        "spouse": {
            "@type": "Person",
            "name": "Torborg Engwall"
        },
        "education": [
            {
                "@type": "EducationalOrganization",
                "name": "Jönköping Elementary School"
            },
            {
                "@type": "EducationalOrganization",
                "name": "Jönköping Technical School"
            }
        ],
        "worksFor": [
            {
                "@type": "Organization",
                "name": "AB Johansson & Sons",
                "startDate": "1932",
                "endDate": "present",
                "jobTitle": "Managing Director"
            }
        ],
        "memberOf": [
            {
                "@type": "Organization",
                "name": "Nässjö Merchants' Association",
                "roleName": "Board Member"
            },
            {
                "@type": "Organization",
                "name": "Nässjö Shoe Retailers",
                "roleName": "Secretary"
            },
            {
                "@type": "Organization",
                "name": "Nässjö YMCA",
                "roleName": "Treasurer"
            },
            {
                "@type": "Organization",
                "name": "Nässjö Mission Church's Brass Band",
                "roleName": "Leader"
            }
        ],
        "additionalName": "Temp. knight of Nässjö Photography Club",
        "sameAs": [
            "https://example.com/music",
            "https://example.com/photography"
        ]
    },
    "occupations": {
        "career": [
            {
                "occupational_title": "Merchant",
                "workplace": "Nässjö",
                "industry": "Retail",
                "start_date": "1932"
            },
            {
                "occupational_title": "Managing Director",
                "workplace": "AB Johansson & Sons",
                "industry": "Shoe Manufacturing",
                "start_date": "1932"
            },
            {
                "occupational_title": "Board Member",
                "workplace": "AB Johansson & Sons",
                "industry": "Shoe Manufacturing"
            },
            {
                "occupational_title": "Board Member",
                "workplace": "Nässjö Merchants' Association",
                "industry": "Trade Association"
            },
            {
                "occupational_title": "Secretary",
                "workplace": "Nässjö shoe retailers",
                "industry": "Retail"
            },
            {
                "occupational_title": "Board Member",
                "workplace": "Nässjö YMCA",
                "industry": "Non-profit"
            },
            {
                "occupational_title": "Treasurer",
                "workplace": "Nässjö YMCA",
                "industry": "Non-profit"
            }
        ]
    }
}