{
    "original": "NIELSEN, Octavius Ferdinand, Dr Techn, Äppelviken, f Odense, Danm, 16/12 91 av fabr J N o Kristine Jensen, gm Thyra Nielsen. Stud v Danm Tekn H0isk (VoV), avg.ex där 15. Assist h prof E Suenson i Kphmn 16, stadsing i Lemvig 18, ing v Codavserftet, Kj0ge, 18—19, i AS Nyholm &amp; Co i Kphmn 19—22, i ing.fman Christiani &amp; Nielsen 22, övering v Sv AB Christiani &amp; Nielsen i Sthlm 28, dir där sed. 31. Konsult ing i Sthlm sed. 43. Dr techn v Danm Tekn H0isk 30. Har utarb spec brokonstruktioner, bl a bågar m snedställdahängstag, tillämp i bron öv Ångermanälven v Hammar, bron öv Pite älv v Bergsviken mfl. Av trycket: Föränderlige Systemers statiske Virkemaade (grad.avh 30).",
    "translated": "NIELSEN, Octavius Ferdinand, Dr Techn, Äppelviken, born in Odense, Denmark, on December 16, 1891, to fabricator J N and Kristine Jensen. Married to Thyra Nielsen. Studied at Danm Tekn H0isk (VoV), graduated with a degree from there in 1915. Assisted professor E Suenson in Copenhagen in 1916, served as a city engineer in Lemvig in 1918. Worked as an engineer at Codavserftet, Kjøge, from 1918 to 1919, and at AS Nyholm & Co in Copenhagen from 1919 to 1922. Joined engineering firm Christiani & Nielsen in 1922 and became the chief engineer at Swedish company Sv AB Christiani & Nielsen in Stockholm in 1928. Director there since 1931. Serves as a consulting engineer in Stockholm since 1943. Received a doctorate in technology from Danm Tekn H0isk in 1930. Has developed special bridge constructions, including arches with inclined suspension rods, applied to the bridge over Ångerman River in Hammar, the bridge over Pite River in Bergsviken, among others. Published work: \"Föränderlige Systemers statiske Virkemaade\" (thesis, 1930).",
    "structured": {
        "@context": "http://schema.org",
        "@type": "Person",
        "name": "Octavius Ferdinand Nielsen",
        "givenName": "Octavius Ferdinand",
        "familyName": "Nielsen",
        "birthDate": "1891-12-16",
        "birthPlace": "Odense, Denmark",
        "spouse": {
            "@type": "Person",
            "name": "Thyra Nielsen"
        },
        "education": [
            {
                "@type": "EducationalOrganization",
                "name": "Danm Tekn H0isk",
                "location": "Denmark",
                "startDate": "1915"
            }
        ],
        "alumniOf": [
            {
                "@type": "EducationalOrganization",
                "name": "Danm Tekn H0isk"
            }
        ],
        "worksFor": [
            {
                "@type": "Organization",
                "name": "Codavserftet"
            },
            {
                "@type": "Organization",
                "name": "AS Nyholm & Co",
                "startDate": "1919",
                "endDate": "1922"
            },
            {
                "@type": "Organization",
                "name": "Christiani & Nielsen",
                "startDate": "1922"
            },
            {
                "@type": "Organization",
                "name": "Sv AB Christiani & Nielsen",
                "startDate": "1928",
                "endDate": "1930"
            }
        ],
        "occupation": [
            {
                "@type": "Role",
                "name": "Assistant to Professor",
                "startDate": "1916",
                "endDate": "1918",
                "roleName": "E Suenson"
            },
            {
                "@type": "Role",
                "name": "City Engineer",
                "startDate": "1918",
                "endDate": "1919",
                "roleName": "Lemvig"
            },
            {
                "@type": "Role",
                "name": "Chief Engineer",
                "startDate": "1928",
                "roleName": "Sv AB Christiani & Nielsen"
            },
            {
                "@type": "Role",
                "name": "Director",
                "startDate": "1931",
                "roleName": "Sv AB Christiani & Nielsen"
            },
            {
                "@type": "Role",
                "name": "Consulting Engineer",
                "startDate": "1943"
            }
        ],
        "award": [
            {
                "@type": "EducationalDegree",
                "name": "Doctor of Technology",
                "awardDate": "1930",
                "awardingInstitution": "Danm Tekn Hoisk"
            }
        ],
        "publication": [
            {
                "@type": "PublicationEvent",
                "name": "Föränderlige Systemers statiske Virkemaade",
                "startDate": "1930"
            }
        ]
    },
    "occupations": {
        "career": [
            {
                "occupational_title": "Assistant",
                "workplace": "Professor E Suenson",
                "industry": "Education",
                "start_date": "1916"
            },
            {
                "occupational_title": "City Engineer",
                "workplace": "Lemvig",
                "industry": "Government",
                "start_date": "1918"
            },
            {
                "occupational_title": "Engineer",
                "workplace": "Codavserftet",
                "industry": "Shipbuilding",
                "start_date": "1918"
            },
            {
                "occupational_title": "Engineer",
                "workplace": "AS Nyholm & Co",
                "industry": "Engineering",
                "start_date": "1919"
            },
            {
                "occupational_title": "Engineer",
                "workplace": "Christiani & Nielsen",
                "industry": "Engineering",
                "start_date": "1922"
            },
            {
                "occupational_title": "Chief Engineer",
                "workplace": "Sv AB Christiani & Nielsen",
                "industry": "Engineering",
                "start_date": "1928"
            },
            {
                "occupational_title": "Director",
                "workplace": "Sv AB Christiani & Nielsen",
                "industry": "Engineering",
                "start_date": "1931"
            },
            {
                "occupational_title": "Consulting Engineer",
                "workplace": "Stockholm",
                "industry": "Consulting",
                "start_date": "1943"
            }
        ]
    }
}