{
    "original": "BERGGREN, August M, Civilingenjör, Stockholm, f Urshult, Kronob l, 29/4 76 av lantbr M Jonasson o Johanna Johansson, gm Svea Forsselius. Mogenh.ex Växjö 96, KTH (el-tekn) 96—99. Ing ASEA 99—03, anst General Electric Co, Schenectady, NY, USA, 03, v samma fma i West Lynn, USA, 04—05, förest ASEA:s provn.anst 05—07, ing v konsult ing.-fman Bergman &amp; Co AB Sthlm 07—10, ass i teoret eltekn KTH 08—10, driftsch Trollh kraftvk 10, nu anst h Mell o N:a Sv:s Ång-pannefrn Sthlm. Led Sv Tekn.frn. RVO, RNO.",
    "translated": "BERGGREN, August M, Civil Engineer, Stockholm, born in Urshult, Kronob l, on April 29, 1876, son of farmer M Jonasson and Johanna Johansson, married to Svea Forsselius. Obtained a degree from Växjö High School in 1896 and from the Royal Institute of Technology (electrical engineering) in 1896-1899. Employed by ASEA from 1899 to 1903, then worked for General Electric Co in Schenectady, NY, USA, in 1903. Continued employment with the same company in West Lynn, USA, from 1904 to 1905, and then became the head of ASEA's testing department from 1905 to 1907. Engaged as an engineer consultant in the firm Bergman & Co AB in Stockholm from 1907 to 1910. Served as an assistant in theoretical electrical engineering at the Royal Institute of Technology from 1908 to 1910. Directed the Trollh power plant in 1910, and currently employed by the Central and Northern Sweden Steam Boiler Association in Stockholm. Member of the Swedish Institute of Engineering, recipient of the Royal Swedish Order of the Northern Star and the Order of Vasa.",
    "structured": {
        "@context": "https://schema.org",
        "@type": "Person",
        "name": "August M Berggren",
        "jobTitle": "Civil Engineer",
        "birthPlace": "Urshult, Kronob l",
        "birthDate": "1876-04-29",
        "parent": [
            {
                "@type": "Person",
                "name": "M Jonasson",
                "jobTitle": "Farmer"
            },
            {
                "@type": "Person",
                "name": "Johanna Johansson"
            }
        ],
        "spouse": {
            "@type": "Person",
            "name": "Svea Forsselius"
        },
        "education": [
            {
                "@type": "EducationalOccupationalCredential",
                "credentialCategory": "degree",
                "credential": "Växjö High School",
                "endDate": "1896"
            },
            {
                "@type": "EducationalOccupationalCredential",
                "credentialCategory": "degree",
                "credential": "Royal Institute of Technology (electrical engineering)",
                "startDate": "1896",
                "endDate": "1899"
            }
        ],
        "work": [
            {
                "@type": "Organization",
                "name": "ASEA",
                "startDate": "1899",
                "endDate": "1903"
            },
            {
                "@type": "Organization",
                "name": "General Electric Co",
                "location": "Schenectady, NY, USA",
                "startDate": "1903",
                "endDate": "1905"
            },
            {
                "@type": "Organization",
                "name": "Bergman & Co AB",
                "location": "Stockholm",
                "startDate": "1907",
                "endDate": "1910",
                "jobTitle": "Engineer Consultant"
            },
            {
                "@type": "Organization",
                "name": "The Royal Institute of Technology",
                "location": "Stockholm",
                "startDate": "1908",
                "endDate": "1910",
                "jobTitle": "Assistant in Theoretical Electrical Engineering"
            },
            {
                "@type": "Organization",
                "name": "Central and Northern Sweden Steam Boiler Association",
                "location": "Stockholm",
                "jobTitle": "Engineer"
            }
        ],
        "memberOf": {
            "@type": "Organization",
            "name": "Swedish Institute of Engineering"
        },
        "award": [
            {
                "@type": "Order",
                "name": "Royal Swedish Order of the Northern Star",
                "description": "Recipient"
            },
            {
                "@type": "Order",
                "name": "Order of Vasa",
                "description": "Recipient"
            }
        ]
    },
    "occupations": {
        "career": [
            {
                "occupational_title": "Civil Engineer",
                "workplace": "Stockholm",
                "industry": "Engineering",
                "start_date": "1899"
            },
            {
                "occupational_title": "Employee",
                "workplace": "ASEA",
                "industry": "Engineering",
                "start_date": "1899"
            },
            {
                "occupational_title": "Employee",
                "workplace": "General Electric Co",
                "industry": "Electrical Engineering",
                "start_date": "1903"
            },
            {
                "occupational_title": "Head of Testing Department",
                "workplace": "ASEA",
                "industry": "Engineering",
                "start_date": "1905"
            },
            {
                "occupational_title": "Engineer Consultant",
                "workplace": "Bergman & Co AB",
                "industry": "Engineering",
                "start_date": "1907"
            },
            {
                "occupational_title": "Assistant",
                "workplace": "Royal Institute of Technology",
                "industry": "Education",
                "start_date": "1908"
            },
            {
                "occupational_title": "Director",
                "workplace": "Trollh Power Plant",
                "industry": "Energy",
                "start_date": "1910"
            },
            {
                "occupational_title": "Employee",
                "workplace": "Central and Northern Sweden Steam Boiler Association",
                "industry": "Energy",
                "start_date": "Unknown"
            }
        ]
    }
}