{
    "original": "CHRISTENSSON, Axel Wilhelm, v. Konsul, Lysekil, f Askum, Gbgs o Bohus län, 29/1 75 av byggm Anders C o Anna Henriksson, gm Anna Maria Lundbom. Folksk., byggn.utb h fad. Grund assuransbyrå 97, försäkr.insp 02— 10, gen.agent i samb m ass.byrån ((Skandia, Ocean o Gothia), deläg i fastigh.fma A o R Christensson, start m sön AB Centr kartong-fabr, Ulvsunda, Sthlm, 31, Fastigh.AB Magneten 38, dir där, fd stdsflm, led o kass kyrkoråd, kyrkovärd sed. 19, huv.m o ordf Lysekils’ sparbk, ordf AB Centr kartong, höll v. kons sed. 26. Resor: Medelhavsland 27. Av trycket: Medred i Fornminn.sällsk Vikarvets årsbok. RNedONO, Frimurare (X), init.tag Odd Fellow platsloge, en av stift Bohusl Fornminn.sällsk Vikarvet, Lysekil, 15. Hobby: Fornminnesarbete i Bohuslän.",
    "translated": "CHRISTENSSON, Axel Wilhelm, v. Consul, Lysekil, born in Askum, Gothenburg and Bohus County, on January 29, 1875, to builder Anders C and Anna Henriksson. Married to Anna Maria Lundbom. Completed elementary school and received building education from his father. Started working at an insurance agency in 1897 and became an insurance inspector from 1902 to 1910. Also served as a general agent in association with the insurance company (Skandia, Ocean, and Gothia). Became a part-owner of the real estate company A and R Christensson. Started a company called AB Centr kartong-fabr with his son in Ulvsunda, Stockholm in 1931. Became involved in Fastigh.AB Magneten in 1938 and served as a director there. Former board member and cash keeper of the church council, church warden since 1919. Main manager and chairman of Lysekils' savings bank. Chairman of AB Centr kartong. Held the title of Vice Consul since 1926. Traveled to Mediterranean countries in 1927. Published in the archaeological society Vikarvet's annual book. Member of the Royal Order of Vasa (X), initiated at the Odd Fellow lodge. Founding member of Bohuslän Antiquarian Society Vikarvet in Lysekil. Hobby: archaeological work in Bohuslän.",
    "structured": {
        "@context": "https://schema.org",
        "@type": "Person",
        "name": "Axel Wilhelm Christensson",
        "birthDate": "1875-01-29",
        "birthPlace": {
            "@type": "Place",
            "name": "Askum, Gothenburg and Bohus County, Sweden"
        },
        "father": {
            "@type": "Person",
            "name": "Anders C"
        },
        "mother": {
            "@type": "Person",
            "name": "Anna Henriksson"
        },
        "spouse": {
            "@type": "Person",
            "name": "Anna Maria Lundbom"
        },
        "education": {
            "@type": "EducationalOrganization",
            "name": "Elementary School"
        },
        "occupation": [
            {
                "@type": "Person",
                "name": "v. Consul"
            },
            {
                "@type": "Person",
                "name": "Insurance Inspector",
                "startDate": "1902",
                "endDate": "1910"
            },
            {
                "@type": "Person",
                "name": "General Agent"
            },
            {
                "@type": "Person",
                "name": "Part-Owner"
            },
            {
                "@type": "Person",
                "name": "Director"
            },
            {
                "@type": "Person",
                "name": "Church Warden",
                "startDate": "1919"
            },
            {
                "@type": "Person",
                "name": "Main Manager"
            },
            {
                "@type": "Person",
                "name": "Chairman"
            }
        ],
        "worksFor": [
            {
                "@type": "Organization",
                "name": "Insurance Agency"
            },
            {
                "@type": "Organization",
                "name": "AB Centr kartong-fabr",
                "startDate": "1931"
            },
            {
                "@type": "Organization",
                "name": "Fastigh.AB Magneten",
                "startDate": "1938"
            },
            {
                "@type": "Organization",
                "name": "Lysekils' savings bank"
            }
        ],
        "memberOf": [
            {
                "@type": "Organization",
                "name": "Church Council"
            },
            {
                "@type": "Organization",
                "name": "AB Centr kartong"
            },
            {
                "@type": "Organization",
                "name": "Royal Order of Vasa"
            },
            {
                "@type": "Organization",
                "name": "Odd Fellow lodge"
            },
            {
                "@type": "Organization",
                "name": "Bohuslän Antiquarian Society Vikarvet"
            }
        ],
        "nationality": "Swedish",
        "travel": [
            {
                "@type": "Trip",
                "name": "Mediterranean trip",
                "startDate": "1927"
            }
        ],
        "publications": [
            {
                "@type": "Article",
                "name": "Fornminn.sällsk Vikarvets årsbok"
            }
        ],
        "hobbies": [
            "Archaeological work in Bohuslän"
        ]
    },
    "occupations": {
        "career": [
            {
                "occupational_title": "Insurance Inspector",
                "workplace": "Insurance Agency",
                "industry": "Insurance",
                "start_date": "1902"
            },
            {
                "occupational_title": "General Agent",
                "workplace": "Insurance Company (Skandia, Ocean, and Gothia)",
                "industry": "Insurance",
                "start_date": "Unknown"
            },
            {
                "occupational_title": "Part-owner",
                "workplace": "A and R Christensson Real Estate Company",
                "industry": "Real Estate",
                "start_date": "Unknown"
            },
            {
                "occupational_title": "Director",
                "workplace": "Fastigh.AB Magneten",
                "industry": "Real Estate",
                "start_date": "1938"
            },
            {
                "occupational_title": "Church Warden",
                "workplace": "Church Council",
                "industry": "Religion",
                "start_date": "1919"
            },
            {
                "occupational_title": "Main Manager",
                "workplace": "Lysekils' Savings Bank",
                "industry": "Finance",
                "start_date": "Unknown"
            },
            {
                "occupational_title": "Chairman",
                "workplace": "AB Centr kartong",
                "industry": "Manufacturing",
                "start_date": "Unknown"
            },
            {
                "occupational_title": "Vice Consul",
                "workplace": "Unknown",
                "industry": "Unknown",
                "start_date": "1926"
            }
        ]
    }
}