{
    "original": "GERDNER, Gustaf Oscar, Direktör, Jönköping, f Borgstena, Älvsb län, 6/10 75 av lantbr Johan A o Lovisa Johanson, gm Ester Hansson. Folksk o yrkessk, papp.hdlsprakt. Deläg fma Vilén &amp; Johanson Borås 97—07, ag.aff Gbg 08, sed. 10 eg aff i Jkpg (omb t AB G O Johanson 22), dir f detta. Stdsflm 16—42, Idstm sed. 32, ordf hälsov.beredn, v. ordf förvaltn.utsk, las.direkt mm, ordf bost.-saner.komm, led fi kommun styr o nmdr. Styr.ordf Jkpgsbygd sparbk, styr.led AB Sk bkns avd.kont, fi bol samt Sv Papp.engr.frb, ordf Fp valkr.frb arb.utsk, led Fp vkst utsk. Resor: Tyskl fi ggr sed. 04, Holl 13, Engl 29, Frankr 37, Schweiz 39.",
    "translated": "GERDNER, Gustaf Oscar, Director, Jönköping, born in Borgstena, Älvsborg county, on 6th October 1875, son of farmer Johan A and Lovisa Johanson, married to Ester Hansson. Attended elementary and vocational school, obtained a practical diploma in commerce. Co-owner of Vilén & Johanson in Borås from 1897 to 1907, agricultural agent in Gothenburg from 1908, and since 1910 owner of his own business in Jönköping (currently working as AB G O Johanson's representative since 1922), also serving as the director of the same company. Member of the city council from 1916 to 1942, chairman of the district board since 1932, chairman of the health committee, vice chairman of the administration committee, regional director, etc., chairman of the housing sanitation committee, member of various municipal boards and committees. Chairman of the Jönköping countryside savings bank, board member of the Department of Skaraborg Bank, stock company, and the Swedish Paper Engravers' Association; chairman of the Free Party's election committee work group, member of the Free Party's growth committee. Travelled to Germany several times since 1904, visited the Netherlands in 1913, England in 1929, France in 1937, and Switzerland in 1939.",
    "structured": {
        "@context": "https://schema.org",
        "@type": "Person",
        "name": "Gustaf Oscar Gerdner",
        "jobTitle": "Director",
        "birthDate": "1875-10-06",
        "birthPlace": {
            "@type": "City",
            "name": "Borgstena"
        },
        "nationality": "Swedish",
        "address": {
            "@type": "PostalAddress",
            "addressLocality": "Jönköping"
        },
        "parents": [
            {
                "@type": "Person",
                "name": "Johan A Johanson",
                "jobTitle": "Farmer"
            },
            {
                "@type": "Person",
                "name": "Lovisa Johanson"
            }
        ],
        "spouse": [
            {
                "@type": "Person",
                "name": "Ester Hansson"
            }
        ],
        "education": [
            {
                "@type": "EducationalOccupationalCredential",
                "credentialCategory": "Elementary school"
            },
            {
                "@type": "EducationalOccupationalCredential",
                "credentialCategory": "Vocational school"
            }
        ],
        "worksFor": [
            {
                "@type": "Organization",
                "name": "Vilén & Johanson"
            },
            {
                "@type": "Organization",
                "name": "AB G O Johanson"
            }
        ],
        "owns": {
            "@type": "Organization",
            "name": "AB G O Johanson"
        },
        "memberOf": [
            {
                "@type": "Organization",
                "name": "Jönköping City Council"
            },
            {
                "@type": "Organization",
                "name": "Health Committee"
            },
            {
                "@type": "Organization",
                "name": "Administration Committee"
            },
            {
                "@type": "Organization",
                "name": "Housing Sanitation Committee"
            },
            {
                "@type": "Organization",
                "name": "Jönköping Countryside Savings Bank"
            },
            {
                "@type": "Organization",
                "name": "Department of Skaraborg Bank"
            },
            {
                "@type": "Organization",
                "name": "Swedish Paper Engravers' Association"
            },
            {
                "@type": "Organization",
                "name": "Free Party's Election Committee"
            },
            {
                "@type": "Organization",
                "name": "Free Party's Growth Committee"
            }
        ],
        "travelHistory": [
            {
                "@type": "Place",
                "name": "Germany",
                "startDate": "1904"
            },
            {
                "@type": "Place",
                "name": "Netherlands",
                "startDate": "1913"
            },
            {
                "@type": "Place",
                "name": "England",
                "startDate": "1929"
            },
            {
                "@type": "Place",
                "name": "France",
                "startDate": "1937"
            },
            {
                "@type": "Place",
                "name": "Switzerland",
                "startDate": "1939"
            }
        ]
    },
    "occupations": {
        "career": [
            {
                "occupational_title": "Co-owner",
                "workplace": "Vilén & Johanson",
                "industry": "Commerce",
                "start_date": "1897"
            },
            {
                "occupational_title": "Agricultural Agent",
                "workplace": "Gothenburg",
                "industry": "Agriculture",
                "start_date": "1908"
            },
            {
                "occupational_title": "Owner",
                "workplace": "Jönköping",
                "industry": "Commerce",
                "start_date": "1910"
            },
            {
                "occupational_title": "Representative",
                "workplace": "AB G O Johanson",
                "industry": "Commerce",
                "start_date": "1922"
            },
            {
                "occupational_title": "Director",
                "workplace": "AB G O Johanson",
                "industry": "Commerce",
                "start_date": "1922"
            }
        ]
    }
}