{
    "original": "HAHN, Carl Tage, Civilingenjör, Hällefors, f Sthlm 7/2 00 av grhdl Carl H o Gerda Knaust, gm Inga Strömberg. Studex NReal Sthlm 18, ex KTH (E) 22, Istoff 40. Kontrollant f nybyggn.arb o driftsch.assist v Cama-rasa vattenkraftverk, tillhörigt Riegos y Fuer- za del Ebro SA, Barcelona, 22—24; elev v ASEA :s i Västerås o Ludvika provrum, rit-o beräkn.kont, 24—26; ch f offertbyrån h Sdad Espanola de Electricidad ASEA i Madrid 27— 34; ing v ASEA:s banbyrå i Västerås 34—42; nu eldriftsing v Hellefors Bruks AB i Hällefors. Tf sv v. konsul i Madrid v olika tillf 28 o 29. Skattmäst i Centro Escandinavo i Madrid 28—34. Resor: Tyskl 22, Frankr, Span 0 Marocko 22—24 o 27—34. Av trycket: Artiklar i spanska tekn tidskrifter.",
    "translated": "HAHN, Carl Tage, Civil Engineer, Hällefors, born in Stockholm on February 7th, 1900, son of the late Carl H and Gerda Knaust, married to Inga Strömberg. Studied at NReal Stockholm until 1918, graduated from KTH (Royal Institute of Technology) in 1922, and completed his internship in 1940. Worked as an inspector for new construction projects and assistant to the operations manager at the Cama-rasa hydroelectric power plant, owned by Riegos y Fuerza del Ebro SA, in Barcelona from 1922 to 1924. Was an apprentice in ASEA's testing facilities in Västerås and Ludvika, involved in design and calculation, from 1924 to 1926. Became head of the sales department at H Sdad Espanola de Electricidad ASEA in Madrid from 1927 to 1934. Engaged as an engineer in ASEA's railroad department in Västerås from 1934 to 1942. Currently working as an electrical engineer at Hellefors Bruks AB in Hällefors. Acted as temporary vice-consul in Madrid for various periods in 1928 and 1929. Served as treasurer at Centro Escandinavo in Madrid from 1928 to 1934. Traveled to Germany in 1922, France, Spain, and Morocco from 1922 to 1924 and 1927 to 1934. Published articles in Spanish technical journals.",
    "structured": {
        "@context": "https://schema.org",
        "@type": "Person",
        "name": "Carl Tage HAHN",
        "birthDate": "1900-02-07",
        "birthPlace": "Stockholm",
        "deathDate": "",
        "description": "Civil Engineer",
        "spouse": {
            "@type": "Person",
            "name": "Inga Strömberg"
        },
        "parents": [
            {
                "@type": "Person",
                "name": "Carl HAHN"
            },
            {
                "@type": "Person",
                "name": "Gerda Knaust"
            }
        ],
        "education": [
            {
                "@type": "EducationalOrganization",
                "name": "NReal Stockholm"
            },
            {
                "@type": "EducationalOrganization",
                "name": "KTH (Royal Institute of Technology)",
                "endDate": "1922"
            }
        ],
        "work": [
            {
                "@type": "Organization",
                "name": "Cama-rasa hydroelectric power plant",
                "address": {
                    "@type": "PostalAddress",
                    "addressLocality": "Barcelona"
                },
                "position": "Inspector",
                "startDate": "1922",
                "endDate": "1924"
            },
            {
                "@type": "Organization",
                "name": "ASEA",
                "location": [
                    {
                        "@type": "Place",
                        "name": "Västerås"
                    },
                    {
                        "@type": "Place",
                        "name": "Ludvika"
                    }
                ],
                "position": "Apprentice",
                "startDate": "1924",
                "endDate": "1926"
            },
            {
                "@type": "Organization",
                "name": "H Sdad Espanola de Electricidad ASEA",
                "location": {
                    "@type": "Place",
                    "name": "Madrid"
                },
                "position": "Head of Sales Department",
                "startDate": "1927",
                "endDate": "1934"
            },
            {
                "@type": "Organization",
                "name": "ASEA",
                "location": {
                    "@type": "Place",
                    "name": "Västerås"
                },
                "position": "Engineer",
                "startDate": "1934",
                "endDate": "1942"
            },
            {
                "@type": "Organization",
                "name": "Hellefors Bruks AB",
                "location": {
                    "@type": "Place",
                    "name": "Hällefors"
                },
                "position": "Electrical Engineer"
            }
        ],
        "memberOf": [
            {
                "@type": "Organization",
                "name": "Centro Escandinavo",
                "position": "Treasurer",
                "startDate": "1928",
                "endDate": "1934"
            }
        ],
        "nationality": "Swedish",
        "article": [
            {
                "@type": "Article",
                "name": "Articles in Spanish technical journals"
            }
        ],
        "travel": [
            {
                "@type": "Place",
                "name": "Germany"
            },
            {
                "@type": "Place",
                "name": "France"
            },
            {
                "@type": "Place",
                "name": "Spain"
            },
            {
                "@type": "Place",
                "name": "Morocco"
            }
        ],
        "sameAs": ""
    },
    "occupations": {
        "career": [
            {
                "occupational_title": "Inspector for new construction projects and assistant to the operations manager",
                "workplace": "Cama-rasa hydroelectric power plant",
                "industry": "Hydroelectric Power",
                "start_date": "1922-"
            },
            {
                "occupational_title": "Apprentice in testing facilities",
                "workplace": "ASEA",
                "industry": "Electrical Engineering",
                "start_date": "1924-"
            },
            {
                "occupational_title": "Head of the sales department",
                "workplace": "Sdad Espanola de Electricidad ASEA",
                "industry": "Electrical Engineering",
                "start_date": "1927-"
            },
            {
                "occupational_title": "Engineer in the railroad department",
                "workplace": "ASEA",
                "industry": "Railroad Engineering",
                "start_date": "1934-"
            },
            {
                "occupational_title": "Electrical Engineer",
                "workplace": "Hellefors Bruks AB",
                "industry": "Engineering",
                "start_date": "-"
            }
        ]
    }
}