{
    "original": "FORSMAN, Karl Harald Gunnar, Direktör, Stockholm, f 20/9 92 av tjm A Forsman o The-resia Holmgren, gm Götha Sauer. Hal, Sthlms hdlsgymn. Korresp, kont.ch o deläg AB G A Du Rietz 10—30, sekt.ch FHK 16—18, vkst dir Sv Lantm Riksfrb sed. 30. Styr.led Sv spann-m.AB, Sv lantbr.frb, AB Örebro kvarn, AB John A Fors, Foderintressentfrn, Stråfoder-hdlsfrn, Fröintressentfrn. Led Sv skiljenmd f spannm- o foderämneshdln, exp.kreditnmdn o hästvärder.nmdn; magistratsbesiktn.m. Ag fastigh Kevinge 18 i Stocksund. Resor: Tyskl, Frankr, Schweiz 21, Ital 26, Engl 35, Ryssl 40. RVO, RFinlVROlkl; Frimurare, NeptO, S.H-n, Sällsk S. G. Hobbies: Hästsport, bridge.",
    "translated": "FORSMAN, Karl Harald Gunnar, Director, Stockholm, b. 20/9 92 to Lieutenant A. Forsman and Theresa Holmgren, m. Götha Sauer. Graduate of Stockholm Commercial Gymnasium. Correspondent and assistant accountant, co-owner of AB G A Du Rietz 10-30, secretary of FHK 16-18, deputy director of the Swedish National Land Survey since 1930. Board member of the Swedish Harnessing Company AB, Swedish Agricultural Association, AB Örebro Mill, AB John A Fors, Feed Interests Association, Straw Feed Trade Association, Seed Interests Association. Member of the Swedish Arbitration Board for Grain and Feed, Export Credit Committee, and Horse Appraisal Committee; magistrate's appraiser for the Kevinge 18 property in Stocksund. Travel: Germany, France, Switzerland in 1921, Italy in 1926, England in 1935, Russia in 1940. Holder of the Royal Order of Vasa, Royal Finnish Order of the White Rose (knight class); Freemason, member of the Neptune Order, Society of Hiddenmists, and S.G. society. Hobbies: Horse riding, bridge.",
    "structured": {
        "@context": "https://schema.org",
        "@type": "Person",
        "name": "Karl Harald Gunnar Forsman",
        "birthDate": "1892-09-20",
        "birthPlace": "Stockholm",
        "parents": [
            {
                "@type": "Person",
                "name": "A. Forsman",
                "jobTitle": "Lieutenant"
            },
            {
                "@type": "Person",
                "name": "Theresa Holmgren"
            }
        ],
        "spouse": {
            "@type": "Person",
            "name": "Götha Sauer"
        },
        "education": {
            "@type": "EducationalOrganization",
            "name": "Stockholm Commercial Gymnasium"
        },
        "occupation": "Director",
        "address": {
            "@type": "PostalAddress",
            "addressLocality": "Stockholm"
        },
        "workHistory": [
            {
                "@type": "Organization",
                "name": "AB G A Du Rietz",
                "founders": [
                    {
                        "@type": "Person",
                        "name": "Karl Harald Gunnar Forsman"
                    }
                ],
                "startDate": "1910-01-01",
                "endDate": "1930-12-31",
                "jobTitle": "Co-owner"
            },
            {
                "@type": "Organization",
                "name": "Swedish National Land Survey",
                "startDate": "1930-01-01",
                "jobTitle": "Deputy Director"
            }
        ],
        "memberships": [
            {
                "@type": "Organization",
                "name": "Swedish Harnessing Company AB",
                "position": "Board Member"
            },
            {
                "@type": "Organization",
                "name": "Swedish Agricultural Association",
                "position": "Board Member"
            },
            {
                "@type": "Organization",
                "name": "AB Örebro Mill",
                "position": "Board Member"
            },
            {
                "@type": "Organization",
                "name": "AB John A Fors",
                "position": "Board Member"
            },
            {
                "@type": "Organization",
                "name": "Feed Interests Association",
                "position": "Board Member"
            },
            {
                "@type": "Organization",
                "name": "Straw Feed Trade Association",
                "position": "Board Member"
            },
            {
                "@type": "Organization",
                "name": "Seed Interests Association",
                "position": "Board Member"
            },
            {
                "@type": "Organization",
                "name": "Swedish Arbitration Board for Grain and Feed"
            },
            {
                "@type": "Organization",
                "name": "Export Credit Committee"
            },
            {
                "@type": "Organization",
                "name": "Horse Appraisal Committee"
            }
        ],
        "alumniOf": [
            {
                "@type": "EducationalOrganization",
                "name": "Stockholm Commercial Gymnasium"
            }
        ],
        "honorificSuffix": "RVO, RFinlVROlkl",
        "memberOf": [
            {
                "@type": "Organization",
                "name": "Freemasons"
            },
            {
                "@type": "Organization",
                "name": "Neptune Order"
            },
            {
                "@type": "Organization",
                "name": "Society of Hiddenmists"
            },
            {
                "@type": "Organization",
                "name": "S.G. society"
            }
        ],
        "description": "Hobbies: Horse riding, bridge",
        "hasOccupation": {
            "@type": "Occupation",
            "name": "Director"
        },
        "hasGender": "Male",
        "hasHobby": [
            {
                "@type": "Thing",
                "name": "Horse riding"
            },
            {
                "@type": "Thing",
                "name": "Bridge"
            }
        ]
    },
    "occupations": {
        "career": [
            {
                "occupational_title": "Correspondent and assistant accountant",
                "workplace": "AB G A Du Rietz",
                "industry": "Unknown",
                "start_date": "10-30"
            },
            {
                "occupational_title": "Secretary",
                "workplace": "FHK",
                "industry": "Unknown",
                "start_date": "16-18"
            },
            {
                "occupational_title": "Deputy Director",
                "workplace": "Swedish National Land Survey",
                "industry": "Government",
                "start_date": "1930"
            }
        ]
    }
}