{
    "original": "HENWER, Per Johan Algot, Färghandlare, Trelleborg, f Trbg 10/6 88, gm Frida Thorell. Anst h konsul Gustaf Smith i Tbg 03—19, i Oljeraffinaderi Union i Malmö 19—26, start färg-, tapet- o kemikalieaff i Tbg 23, alltj inneh av denna, tillika vkst dir i AB Tbgs Motorimp. Styr.led i Skånes Färghandl.frn i fi år, dess sekr sed. 40, styr.led i Skånes Tapethandl.frn sed. bild, medverk v bild av Tbgs Köpm.frn 34 o dess ordf sed. dess. Led av hdls- o sjöf.nmd samt tax.nmdn. Medl av Tbgs Friv Skyttefrn sed. 04, styr.led sed. 06, sekr 07—19, v. ordf 19—26 o ordf 26—40, rev i Malmöh Läns Skyttefrb, fanj i SvRK, styr.led i Tbgs RK-kår sed. 29 samt kassa-förvalt i tio år. Medl av Druidorden sed. 13 o Odd Fellow sed. 21. Malmöh Läns Skytte-frbs ftjSM, SvRK:s ftjSM, Tbgs Friv Skytte-frns ftjGM o GMM. Hobby: Skytte.",
    "translated": "HENWER, Per Johan Algot, Merchant, Trelleborg, born in Trelleborg on June 10, 1888, married to Frida Thorell. Employed at consul Gustaf Smith's in Trelleborg from 1903 to 1919, at the Union Oil Refinery in Malmö from 1919 to 1926. Started a paint, wallpaper, and chemical store in Trelleborg in 1923, of which he was the sole owner. Also served as the managing director of AB Trelleborgs Motorimport. Served on the board of directors of Skånes Färghandlare for five years and was secretary from 1940. Served on the board of directors of Skånes Tapethandlare since its establishment and became its chairman. Participated in the establishment of Trelleborgs Köpmannaförening in 1934 and has been its chairman since then. Member of the trade and maritime council and the tax committee. Member of Trelleborgs Frivilliga Skytteförening since 1904, served on the board since 1906, was secretary from 1907 to 1919, vice chairman from 1919 to 1926, and chairman from 1926 to 1940. Auditor of Malmö County Shooting Association. Served as a corporal in the Swedish Red Cross. Served on the board of Trelleborgs RK corps since 1929 and was the treasurer for ten years. Member of the Druid Order since 1913 and the Odd Fellows since 1921. Swedish Red Cross's shooting championship, Malmö County Shooting Association's shooting championship, Trelleborgs Frivilliga Skytteförening's shooting championship, gold and silver medal. Hobby: Shooting.",
    "structured": {
        "@context": "https://schema.org",
        "@type": "Person",
        "name": "Per Johan Algot Henwer",
        "jobTitle": "Merchant",
        "birthDate": "1888-06-10",
        "birthPlace": "Trelleborg, Sweden",
        "spouse": "Frida Thorell",
        "memberOf": [
            {
                "@type": "Organization",
                "name": "Trelleborgs Frivilliga Skytteförening",
                "startDate": "1904",
                "position": [
                    {
                        "@type": "Role",
                        "roleName": "Secretary",
                        "startDate": "1907",
                        "endDate": "1919"
                    },
                    {
                        "@type": "Role",
                        "roleName": "Vice Chairman",
                        "startDate": "1919",
                        "endDate": "1926"
                    },
                    {
                        "@type": "Role",
                        "roleName": "Chairman",
                        "startDate": "1926",
                        "endDate": "1940"
                    }
                ],
                "event": [
                    {
                        "@type": "Event",
                        "name": "Swedish Red Cross's shooting championship",
                        "startDate": "Year of participation"
                    },
                    {
                        "@type": "Event",
                        "name": "Malmö County Shooting Association's shooting championship",
                        "startDate": "Year of participation"
                    },
                    {
                        "@type": "Event",
                        "name": "Trelleborgs Frivilliga Skytteförening's shooting championship",
                        "startDate": "Year of participation"
                    }
                ],
                "award": [
                    {
                        "@type": "Medal",
                        "name": "gold",
                        "description": "Swedish Red Cross's shooting championship"
                    },
                    {
                        "@type": "Medal",
                        "name": "silver",
                        "description": "Malmö County Shooting Association's shooting championship"
                    }
                ]
            },
            {
                "@type": "Organization",
                "name": "Skånes Färghandlare",
                "startDate": "Year Per Johan Algot Henwer served on the board",
                "endDate": "Year Per Johan Algot Henwer left the board",
                "position": [
                    {
                        "@type": "Role",
                        "roleName": "Secretary",
                        "startDate": "1940"
                    }
                ]
            },
            {
                "@type": "Organization",
                "name": "Skånes Tapethandlare",
                "startDate": "Year of establishment",
                "position": [
                    {
                        "@type": "Role",
                        "roleName": "Chairman"
                    }
                ]
            },
            {
                "@type": "Organization",
                "name": "Trelleborgs Köpmannaförening",
                "startDate": "1934",
                "position": [
                    {
                        "@type": "Role",
                        "roleName": "Chairman",
                        "startDate": "1934"
                    }
                ]
            }
        ],
        "worksFor": [
            {
                "@type": "Organization",
                "name": "Consul Gustaf Smith's",
                "startDate": "1903",
                "endDate": "1919"
            },
            {
                "@type": "Organization",
                "name": "Union Oil Refinery",
                "startDate": "1919",
                "endDate": "1926"
            },
            {
                "@type": "Organization",
                "name": "AB Trelleborgs Motorimport",
                "startDate": "Year Per Johan Algot Henwer started as managing director"
            }
        ],
        "gender": "Male",
        "hobby": "Shooting"
    },
    "occupations": {
        "career": [
            {
                "occupational_title": "Merchant",
                "workplace": "Consul Gustaf Smith's",
                "industry": "Retail",
                "start_date": "1903"
            },
            {
                "occupational_title": "Employee",
                "workplace": "Union Oil Refinery",
                "industry": "Oil Refining",
                "start_date": "1919"
            },
            {
                "occupational_title": "Owner",
                "workplace": "Paint, Wallpaper, and Chemical Store",
                "industry": "Retail",
                "start_date": "1923"
            },
            {
                "occupational_title": "Managing Director",
                "workplace": "AB Trelleborgs Motorimport",
                "industry": "Automotive",
                "start_date": "N/A"
            }
        ]
    }
}