{
    "original": "BLOMBERG, Knut Hugo, Civilingenjör, Direktörsassistent, Stockholm, f Sthlm 25/10 97 av sjökapt J G B o Cecilia Palman, gm Eva Westergren. Studex NReal 16, KTH (el-tekn) 16—20. Anst v Vattenf.styr 21, Pat- o Registr.vkt 22—23, Telegraf styr :s linjebyrås konstr.avd 23—29, Telef.AB L M Ericsson Sthlm sed. 30, ch f dess tekn avd sed. 36. Av trycket: Telegrafi, Elektr bildöverf o Telefoni i Uppfinn :s bok III (27) mm. Led Sv Tekn.frn.",
    "translated": "BLOMBERG, Knut Hugo, Civil Engineer, Director's Assistant, Stockholm, born in Stockholm on October 25, 1897, to sea captain J G B and Cecilia Palman, married Eva Westergren. Studied at NReal 16, KTH (electrical engineering) 16-20. Employed at Vattenf.styr 21, Pat- o Registr.vkt 22-23, Telegraf styr :s linjebyrås konstr.avd 23-29, Telef.AB L M Ericsson Stockholm since 30, appointed head of its technical department since 36. Published works include: Telegrafi, Elektr bildöverf o Telefoni i Uppfinn :s bok III (27) etc. Member of the Swedish Technical Association.\n\nNote: \"ch f dess tekn avd sed. 36\" indicates that the person became the head of the technical department in the year 1936.",
    "structured": {
        "name": "Knut Hugo Blomberg",
        "givenName": "Knut",
        "familyName": "Blomberg",
        "jobTitle": "Civil Engineer, Director's Assistant",
        "birthDate": "1897-10-25",
        "birthPlace": "Stockholm",
        "father": {
            "givenName": "J G",
            "familyName": "B"
        },
        "mother": {
            "givenName": "Cecilia",
            "familyName": "Palman"
        },
        "spouse": {
            "givenName": "Eva",
            "familyName": "Westergren"
        },
        "education": [
            {
                "institution": "NReal",
                "studyType": "Studex",
                "startDate": "1916",
                "endDate": "1920"
            },
            {
                "institution": "KTH",
                "studyType": "el-tekn",
                "startDate": "1916",
                "endDate": "1920"
            }
        ],
        "employment": [
            {
                "organization": "Vattenf.styr",
                "startDate": "1921"
            },
            {
                "organization": "Pat- o Registr.vkt",
                "startDate": "1922",
                "endDate": "1923"
            },
            {
                "organization": "Telegraf styr :s linjebyrås konstr.avd",
                "startDate": "1923",
                "endDate": "1929"
            },
            {
                "organization": "Telef.AB L M Ericsson",
                "startDate": "1930",
                "roles": [
                    {
                        "roleName": "Director's Assistant",
                        "startDate": "1936"
                    },
                    {
                        "roleName": "Head of Technical Department",
                        "startDate": "1936"
                    }
                ]
            }
        ],
        "publications": [
            "Telegrafi, Elektr bildöverf o Telefoni i Uppfinn :s bok III (27)"
        ],
        "membership": [
            {
                "organization": "Swedish Technical Association"
            }
        ]
    },
    "occupations": {
        "career": {
            "occupational_title": [
                "Civil Engineer",
                "Director's Assistant"
            ],
            "workplace": [
                "Vattenf.styr",
                "Pat- o Registr.vkt",
                "Telegraf styr :s linjebyrås konstr.avd",
                "Telef.AB L M Ericsson Stockholm"
            ],
            "industry": [
                "Unknown",
                "Unknown",
                "Telecommunications",
                "Telecommunications"
            ],
            "start_date": [
                "1921",
                "1922",
                "1923",
                "1930"
            ]
        }
    }
}