{
    "original": "HOMMEBBEBG, Claes Peter Emil, Fil. Licentiat, Malmö, f Mmö 31/1 01 av assessorn v.hhövd E Ch H o Caroline Bergh. Studex Lund 19, fil kand 26, fil lic 30, färgkemiska studier Frankf a.M 25. Inneh sed. 37 fabr.fma Industrikemikalier, Mmö, som främst spec.prep f järn- o stålbehandl. Styr.led Barnekows tekn.kem lab o Falsterbo museum. Resor: Belg, Danm, Engl, Frankr, Holl, Ital, Jugosl, Luxemb, Monaco, Norge, Schweiz, Tjeckoslov, Tyskl, Ung, Österr. Av trycket: »Zur Kenntnis der Spezifität tierischer Phosphatase» ’29), »tiber tierische Phosphatase und Sulfatase» (31), »tiber Mg-Aktivie-rung etc.» (33), »Studien iiber die Phosphatase der Hefe» (35). Medl Kemistsamf Sthlm, Kem Frn Lund, Sv Kem Industrikontor, Sv Tekn.frn, Kult.hist Frn Lund, Knutsgillet Lund.",
    "translated": "HOMMEBBEBG, Claes Peter Emil, B.A. Licentiate, Malmö, born in Malmö on January 31, 1901, to the assessor renowned E Ch H and Caroline Bergh. Graduated from Lund University in 1919, received a Bachelor's degree in 1926, and a Licentiate degree in 1930. Conducted color chemistry studies in Frankfurt am Main in 1925. Currently holds 37 patents in chemical industry, specializing in the preparation of iron and steel treatments. Serves on the board of Barnekow's technical chemical laboratory and Falsterbo museum. Has traveled to Belgium, Denmark, England, France, the Netherlands, Italy, Yugoslavia, Luxembourg, Monaco, Norway, Switzerland, Czechoslovakia, Germany, Hungary, and Austria. Published works include: \"Zur Kenntnis der Spezifität tierischer Phosphatase\" (1929), \"Über tierische Phosphatase und Sulfatase\" (1931), \"Über Mg-Aktivie-rung etc.\" (1933), and \"Studien über die Phosphatase der Hefe\" (1935). Member of the Swedish Association of Chemists, Chemistry Society of Lund, Swedish Chemical Industry Office, Swedish Technical Research Council, Cultural Historical Society of Lund, and Knut's Guild in Lund. Note: \"m.\" indicates marriage, followed by the partner's name and the year of marriage.",
    "structured": {
        "@context": "https://schema.org",
        "@type": "Person",
        "name": "Claes Peter Emil Hommebbebg",
        "givenName": "Claes Peter Emil",
        "additionalName": "Hommebbebg",
        "birthDate": "1901-01-31",
        "birthPlace": {
            "@type": "Place",
            "address": {
                "@type": "PostalAddress",
                "addressLocality": "Malmö"
            }
        },
        "deathDate": "Unknown",
        "alumniOf": [
            {
                "@type": "Organization",
                "name": "Lund University",
                "startDate": "1919",
                "endDate": null
            }
        ],
        "education": [
            {
                "@type": "EducationalOccupationalCredential",
                "name": "Bachelor's degree",
                "educationalLevel": "B.A.",
                "dateReceived": "1926"
            },
            {
                "@type": "EducationalOccupationalCredential",
                "name": "Licentiate degree",
                "dateReceived": "1930"
            },
            {
                "@type": "EducationalOccupationalCredential",
                "name": "Color chemistry studies",
                "institution": "Frankfurt am Main",
                "dateStarted": "1925",
                "dateCompleted": null
            }
        ],
        "works": [
            {
                "@type": "Article",
                "name": "Zur Kenntnis der Spezifität tierischer Phosphatase",
                "datePublished": "1929"
            },
            {
                "@type": "Article",
                "name": "Über tierische Phosphatase und Sulfatase",
                "datePublished": "1931"
            },
            {
                "@type": "Article",
                "name": "Über Mg-Aktivie-rung etc.",
                "datePublished": "1933"
            },
            {
                "@type": "Article",
                "name": "Studien über die Phosphatase der Hefe",
                "datePublished": "1935"
            }
        ],
        "memberOf": [
            {
                "@type": "Organization",
                "name": "Swedish Association of Chemists"
            },
            {
                "@type": "Organization",
                "name": "Chemistry Society of Lund"
            },
            {
                "@type": "Organization",
                "name": "Swedish Chemical Industry Office"
            },
            {
                "@type": "Organization",
                "name": "Swedish Technical Research Council"
            },
            {
                "@type": "Organization",
                "name": "Cultural Historical Society of Lund"
            },
            {
                "@type": "Organization",
                "name": "Knut's Guild in Lund"
            }
        ],
        "hasOccupation": {
            "@type": "Occupation",
            "name": "Chemist"
        },
        "hasResidence": [
            {
                "@type": "Place",
                "address": {
                    "@type": "PostalAddress",
                    "addressLocality": "Malmö"
                }
            },
            {
                "@type": "Place",
                "address": {
                    "@type": "PostalAddress",
                    "addressLocality": "Falsterbo"
                }
            }
        ],
        "spouse": {
            "@type": "Person",
            "name": "Caroline Bergh",
            "birthDate": null,
            "birthPlace": null,
            "deathDate": null
        },
        "parent": [
            {
                "@type": "Person",
                "name": "E Ch H",
                "birthDate": null,
                "birthPlace": null,
                "deathDate": null
            },
            {
                "@type": "Person",
                "name": "Caroline Bergh",
                "birthDate": null,
                "birthPlace": null,
                "deathDate": null
            }
        ],
        "travel": [
            "Belgium",
            "Denmark",
            "England",
            "France",
            "Netherlands",
            "Italy",
            "Yugoslavia",
            "Luxembourg",
            "Monaco",
            "Norway",
            "Switzerland",
            "Czechoslovakia",
            "Germany",
            "Hungary",
            "Austria"
        ]
    },
    "occupations": {
        "career": [
            {
                "occupational_title": "Assessor",
                "workplace": "Unknown",
                "industry": "Unknown",
                "start_date": "Unknown"
            },
            {
                "occupational_title": "Chemist",
                "workplace": "Industrikemikalier, Malmö",
                "industry": "Chemical manufacturing",
                "start_date": "1937"
            },
            {
                "occupational_title": "Board Member",
                "workplace": "Barnekows tekn.kem. lab",
                "industry": "Chemical research",
                "start_date": "Unknown"
            },
            {
                "occupational_title": "Board Member",
                "workplace": "Falsterbo museum",
                "industry": "Museum",
                "start_date": "Unknown"
            }
        ]
    }
}