{
    "original": "LINDWALL, Eric Efre, överingenjör, Stockholm, f Tierp, Upps l, 23/10 95 av dir E E L o Katarina Söderlund, gm 1) Marion Berg (d), 2) Ulla Hafström. Ex tekn elem.sk i Örebro 16, KTH (maskinbyggn o mek tekn) 18—22. Ing v The Bell Telephone Comp of Pennsylvania i Pittsburgh USA 22—23, verk-st.ing v AB Separator i Sthlm 24—32, drifts-ing v Konfektions AB Junex i Jönkp 32—35, övering v AB Gunnar Collijn i Sthlm 35—37, v AB L &amp; P Widengren i Vingåker o Sthlm sed. 37. Resor: Tyskl 17, USA 22—23. Led Sv Tekn.frn, W6. Hobbies: Segling, golf, jakt. °LINNSKOG, Erik Joh. J:son, Fabrikör, Eskilstuna, f Närkes Täby, öbr l, 10/12 82, gm Amanda Moberg. Anst v Örebro Strå- &amp; Filt-hattfabr 09—18. Gr eg fma, Eskilstuna Strå-&amp; Filthattfabr, 19, inneh dna o fil i Nyköping und fma Linnskogs Hattfabr, gr 33.",
    "translated": "LINDWALL, Eric Efre, chief engineer, Stockholm, born in Tierp, Uppsala County, on October 23rd, 1895. Son of director E.E. Lindwall and Katarina Söderlund. Married 1) Marion Berg (deceased), 2) Ulla Hafström. Went to technical elementary school in Örebro in 1916, studied mechanical engineering at the Royal Institute of Technology (KTH) from 1918 to 1922. Worked as an engineer at The Bell Telephone Company of Pennsylvania in Pittsburgh, USA, from 1922 to 1923. Then employed as a production engineer at AB Separator in Stockholm from 1924 to 1932, as a superintendent at AB Junex in Jönköping from 1932 to 1935, as chief engineer at AB Gunnar Collijn in Stockholm from 1935 to 1937, and at AB L & P Widengren in Vingåker and Stockholm since 1937. Traveled to Germany in 1917 and to the USA in 1922-1923. Member of the Swedish Engineering Association and the W6 Club. Hobbies include sailing, golf, and hunting.\n\nLINNSKOG, Erik Joh. J:son, manufacturer, Eskilstuna, born in Närkes Täby on December 10th, 1882. Married to Amanda Moberg. Employed at Örebro Straw and Felt Hat Factory from 1909 to 1918. Established his own company, Eskilstuna Straw and Felt Hat Factory, in 1919, and acquired Nyköping Hat Factory in 1933.",
    "structured": {
        "@context": "https://schema.org",
        "@type": "Person",
        "name": "Eric Efre Lindwall",
        "birthDate": "1895-10-23",
        "birthPlace": {
            "@type": "City",
            "name": "Tierp",
            "address": "Uppsala County, Sweden"
        },
        "nationality": "Swedish",
        "parents": [
            {
                "@type": "Person",
                "name": "E.E. Lindwall",
                "jobTitle": "Director"
            },
            {
                "@type": "Person",
                "name": "Katarina Söderlund"
            }
        ],
        "spouse": [
            {
                "@type": "Person",
                "name": "Marion Berg",
                "deathDate": "unknown"
            },
            {
                "@type": "Person",
                "name": "Ulla Hafström"
            }
        ],
        "education": [
            {
                "@type": "EducationalOrganization",
                "name": "Technical Elementary School",
                "address": "Örebro, Sweden",
                "startDate": "1916"
            },
            {
                "@type": "EducationalOrganization",
                "name": "Royal Institute of Technology (KTH)",
                "address": "Stockholm, Sweden",
                "studyProgram": "Mechanical Engineering",
                "startDate": "1918",
                "endDate": "1922"
            }
        ],
        "jobTitle": "Chief Engineer",
        "worksFor": [
            {
                "@type": "Organization",
                "name": "The Bell Telephone Company of Pennsylvania",
                "address": "Pittsburgh, USA",
                "startDate": "1922",
                "endDate": "1923"
            },
            {
                "@type": "Organization",
                "name": "AB Separator",
                "address": "Stockholm, Sweden",
                "startDate": "1924",
                "endDate": "1932"
            },
            {
                "@type": "Organization",
                "name": "AB Junex",
                "address": "Jönköping, Sweden",
                "startDate": "1932",
                "endDate": "1935"
            },
            {
                "@type": "Organization",
                "name": "AB Gunnar Collijn",
                "address": "Stockholm, Sweden",
                "startDate": "1935",
                "endDate": "1937"
            },
            {
                "@type": "Organization",
                "name": "AB L & P Widengren",
                "address": [
                    {
                        "@type": "City",
                        "name": "Vingåker",
                        "addressCountry": "Sweden"
                    },
                    {
                        "@type": "City",
                        "name": "Stockholm",
                        "addressCountry": "Sweden"
                    }
                ],
                "startDate": "1937"
            }
        ],
        "travelHistory": [
            {
                "@type": "Place",
                "name": "Germany",
                "startDate": "1917"
            },
            {
                "@type": "Place",
                "name": "USA",
                "startDate": "1922",
                "endDate": "1923"
            }
        ],
        "memberOf": [
            {
                "@type": "Organization",
                "name": "Swedish Engineering Association"
            },
            {
                "@type": "Organization",
                "name": "W6 Club"
            }
        ],
        "hobbies": [
            "Sailing",
            "Golfing",
            "Hunting"
        ]
    },
    "occupations": {
        "career": [
            {
                "occupational_title": "Chief Engineer",
                "workplace": "AB L & P Widengren",
                "industry": "Unknown",
                "start_date": "1937"
            },
            {
                "occupational_title": "Chief Engineer",
                "workplace": "AB Gunnar Collijn",
                "industry": "Unknown",
                "start_date": "1935"
            },
            {
                "occupational_title": "Superintendent",
                "workplace": "AB Junex",
                "industry": "Textiles (Konfektions AB)",
                "start_date": "1932"
            },
            {
                "occupational_title": "Production Engineer",
                "workplace": "AB Separator",
                "industry": "Engineering",
                "start_date": "1924"
            },
            {
                "occupational_title": "Engineer",
                "workplace": "The Bell Telephone Company of Pennsylvania",
                "industry": "Telecommunications",
                "start_date": "1922"
            },
            {
                "occupational_title": "Mechanical Engineering Student",
                "workplace": "Royal Institute of Technology (KTH)",
                "industry": "Education",
                "start_date": "1918"
            },
            {
                "occupational_title": "Technical Elementary School Student",
                "workplace": "Örebro",
                "industry": "Education",
                "start_date": "1916"
            }
        ]
    }
}