{
    "original": "BENSOW, Frank Sigurd, Major, Norrköping, f Gbg 11/3 83 av tandläk V B o Sigrid Boye, gm Sigrid Nauclér. Studex Gbg 01, ex KTH (v o v) 05. Resoffex KS 05, major VVK. Ing öl väg- o vatt.byggn.distr samt väg- o vatt.byggn.styr 05—10, konstr ing.fma Unan-der &amp; Johnson samt Kreuger &amp; Toll 09—10, chefskonstr o avd.ing Sthlms superfosfatfabr v bygg av Ljungav 10—11, avd.ing Nässjö-Sävsjöströms jvgsbyggn 12—13, arb.ch Holmens br o fabr ABs bygg av Hallsta papp.br 13—15, byggn.ch Holmens br i Nrkp 16. l:e v. ordf o åld.pres dräts.kamm, v. ordf dess byggn.avd, d:o byggn.nmdn, led gen.plane-beredn, stadshus-, las- o museibyggn.komm :na, lönenmdn, pens.nmdn, styr.ordf stadsbibl o stadens konstmuseum; styr.led Blomska stift, Frn Gamla Nrkp, Nrkp golfklb, fd v. ordf Po-lytekn frn. Resor: Norge, Danm, Finl, Tyskl, Frankr, Engl, Schweiz, Tjeckoslov, Ital, Belg, Holl, Polen 13—40. Av trycket: Nrkps Stadshus, Antikens väg- o vatt.byggn.konst i nutida belysn. RVO, Ögl IF ftjt. Hobbies: Konsthist, golf, botanik.",
    "translated": "BENSOW, Frank Sigurd, Major, Norrköping, born in Gothenburg on November 3rd, 1883, son of dentist V.B. and Sigrid Boye, married to Sigrid Nauclér. Studied in Gothenburg in 1901, graduated from KTH (Royal Institute of Technology) in 1905. Reserve Officer Candidate in 1905, Major in the Volunteer Reserve Corps. Worked as a civil engineer in road and water construction district as well as road and water construction board from 1905 to 1910, construction engineer at Unander & Johnson and Kreuger & Toll from 1909 to 1910, Chief Engineer and Department Engineer at Stockholm Superphosphate Factory for Ljunga from 1910 to 1911, Department Engineer for Nässjö-Sävsjö Railway Construction from 1912 to 1913, worked at Holmen's Paper Mill AB for the construction of Hallsta paper mill from 1913 to 1915, Construction Manager at Holmen's Paper Mill in Norrköping in 1916. First vice-chairman and senior president of the finance committee, vice-chairman of the building department, all of the building committee, planning committee, City Hall, County Hospital and Museum building committees, Salary Committee, Pension Committee, Chairman of the board for the City Library and the City Art Museum; Board member of the Blom Foundation, Former Residents of Gamla Norrköping Association, Norrköping Golf Club, former vice-chairman of the Polytechnic Association. Traveled to Norway, Denmark, Finland, Germany, France, England, Switzerland, Czechoslovakia, Italy, Belgium, Holland, and Poland from 1913 to 1940. Published works: Norrköping City Hall, Ancient road and water construction art in contemporary lighting. Received the Royal Order of Vasa, member of the Ögl Idrottsförening. Hobbies: Art history, golf, botany.",
    "structured": {
        "@context": "https://schema.org",
        "@type": "Person",
        "name": "Frank Sigurd Bensow",
        "givenName": "Frank Sigurd",
        "familyName": "Bensow",
        "gender": "Male",
        "birthDate": "1883-11-03",
        "birthPlace": "Gothenburg",
        "deathDate": null,
        "nationality": "Swedish",
        "profession": "Major",
        "spouse": {
            "@type": "Person",
            "name": "Sigrid Nauclér"
        },
        "parents": [
            {
                "@type": "Person",
                "name": "V.B. Bensow",
                "jobTitle": "Dentist"
            },
            {
                "@type": "Person",
                "name": "Sigrid Boye"
            }
        ],
        "education": [
            {
                "@type": "EducationalOccupationalCredential",
                "credentialCategory": "Degree",
                "credentialLevel": "Undergraduate",
                "educationalLevel": "Bachelor's degree",
                "educationalProgram": {
                    "@type": "EducationalProgram",
                    "name": "Royal Institute of Technology"
                },
                "endDate": "1905",
                "startDate": "1901"
            }
        ],
        "affiliation": [
            {
                "@type": "Organization",
                "name": "Volunteer Reserve Corps",
                "jobTitle": "Major"
            },
            {
                "@type": "Organization",
                "name": "Unander & Johnson"
            },
            {
                "@type": "Organization",
                "name": "Kreuger & Toll"
            },
            {
                "@type": "Organization",
                "name": "Stockholm Superphosphate Factory",
                "jobTitle": "Chief Engineer"
            },
            {
                "@type": "Organization",
                "name": "Nässjö-Sävsjö Railway Construction",
                "jobTitle": "Department Engineer"
            },
            {
                "@type": "Organization",
                "name": "Holmen's Paper Mill AB",
                "jobTitle": "Construction Manager"
            },
            {
                "@type": "Organization",
                "name": "Norrköping City Library",
                "roleName": "Chairman of the board"
            },
            {
                "@type": "Organization",
                "name": "City Art Museum"
            },
            {
                "@type": "Organization",
                "name": "Blom Foundation"
            },
            {
                "@type": "Organization",
                "name": "Former Residents of Gamla Norrköping Association"
            },
            {
                "@type": "Organization",
                "name": "Norrköping Golf Club"
            },
            {
                "@type": "Organization",
                "name": "Polytechnic Association"
            }
        ],
        "memberOf": [
            {
                "@type": "Organization",
                "name": "Norrköping City Hall",
                "roleName": "First vice-chairman"
            },
            {
                "@type": "Organization",
                "name": "Finance committee",
                "roleName": "Senior president"
            },
            {
                "@type": "Organization",
                "name": "Building committee",
                "roleName": "Vice-chairman"
            },
            {
                "@type": "Organization",
                "name": "Planning committee",
                "roleName": "Member"
            },
            {
                "@type": "Organization",
                "name": "City Hall"
            },
            {
                "@type": "Organization",
                "name": "County Hospital"
            },
            {
                "@type": "Organization",
                "name": "Museum building committee"
            },
            {
                "@type": "Organization",
                "name": "Salary Committee"
            },
            {
                "@type": "Organization",
                "name": "Pension Committee"
            },
            {
                "@type": "Organization",
                "name": "City Library",
                "roleName": "Chairman of the board"
            },
            {
                "@type": "Organization",
                "name": "City Art Museum"
            }
        ],
        "works": [
            {
                "@type": "CreativeWork",
                "name": "Norrköping City Hall"
            },
            {
                "@type": "CreativeWork",
                "name": "Ancient road and water construction art in contemporary lighting"
            }
        ],
        "awards": [
            {
                "@type": "Order",
                "name": "Royal Order of Vasa"
            }
        ],
        "memberOfSportsTeam": [
            {
                "@type": "Organization",
                "name": "Ögl Idrottsförening"
            }
        ],
        "knowsAbout": [
            "Art history",
            "Golf",
            "Botany"
        ],
        "sameAs": "https://example.com/frank_bensow"
    },
    "occupations": {
        "career": [
            {
                "occupational_title": "Civil Engineer",
                "workplace": "Road and Water Construction District",
                "industry": "Construction",
                "start_date": "1905"
            },
            {
                "occupational_title": "Civil Engineer",
                "workplace": "Road and Water Construction Board",
                "industry": "Construction",
                "start_date": "1905"
            },
            {
                "occupational_title": "Construction Engineer",
                "workplace": "Unander & Johnson",
                "industry": "Construction",
                "start_date": "1909"
            },
            {
                "occupational_title": "Construction Engineer",
                "workplace": "Kreuger & Toll",
                "industry": "Construction",
                "start_date": "1909"
            },
            {
                "occupational_title": "Chief Engineer",
                "workplace": "Stockholm Superphosphate Factory",
                "industry": "Construction",
                "start_date": "1910"
            },
            {
                "occupational_title": "Department Engineer",
                "workplace": "Ljunga",
                "industry": "Construction",
                "start_date": "1910"
            },
            {
                "occupational_title": "Department Engineer",
                "workplace": "Nässjö-Sävsjö Railway Construction",
                "industry": "Construction",
                "start_date": "1912"
            },
            {
                "occupational_title": "Construction Chief",
                "workplace": "Holmen's Paper Mill AB",
                "industry": "Construction",
                "start_date": "1913"
            },
            {
                "occupational_title": "Construction Manager",
                "workplace": "Holmen's Paper Mill",
                "industry": "Construction",
                "start_date": "1916"
            }
        ]
    }
}