{
    "original": "EKMAN, Per Johan Gustaf, Disponent, Morgårdshammar, f Norrbärke, Kopparb l, 22/7 01 av bkdir Gust E o Hedvig Larson, gm Carin Eriksen. Studex Karlst 19, KTH (bergsvetensk) 20—25. Anst AB Lindholmen-Motala mtrlprovn 0 valsverk 26—29, valsverksing v Fagersta Br AB 29—32, v Smedjebackens Valsverks AB 32— 36, valsverkskonstr v Morgårdshammar Mek Verkst AB 36—39, disp o vkst dir där sed. 39, tillika vkst dir f AB Arboga Mek Verkst sed. 43. Styr.led Hallstahammars AB, östafors AB o AB Septem. Led Sv Tekn.frn. Resor: Tyskl, Belg o Engl 30, USA 39. Hobbies: Friluftsliv, slöjd.",
    "translated": "EKMAN, Per Johan Gustaf, Manager, Morgårdshammar, born in Norrbärke, Kopparberg County, July 22, 1901, son of bakery owner Gust E and Hedvig Larson, married to Carin Eriksen. Graduated from Karlstad University in 1919, and KTH (Royal Institute of Technology, specializing in mining engineering) from 1920 to 1925. Employed by Lindholmen-Motala AB as a material testing supervisor and in the rolling mill from 1926 to 1929. Worked as a rolling mill engineer at Fagersta Steelworks AB from 1929 to 1932, and at Smedjebackens Valsverks AB from 1932 to 1936. Worked as a rolling mill construction engineer at Morgårdshammar Mekaniska Verkstads AB from 1936 to 1939, then became the manager and director of the same company. Also held the position of director of growth at AB Arboga Mekaniska Verkstads since 1943. Serves on the board of Hallstahammars AB, östafors AB, and AB Septem. Member of the Swedish Technical Association. Traveled to Germany, Belgium, and England in 1930, and to the United States in 1939. Hobbies include outdoor activities and crafts.",
    "structured": {
        "@context": "https://schema.org",
        "@type": "Person",
        "name": "Per Johan Gustaf Ekman",
        "birthDate": "1901-07-22",
        "birthPlace": {
            "@type": "Place",
            "name": "Norrbärke, Kopparberg County"
        },
        "parents": [
            {
                "@type": "Person",
                "name": "Gust E",
                "relation": "father"
            },
            {
                "@type": "Person",
                "name": "Hedvig Larson",
                "relation": "mother"
            }
        ],
        "spouse": {
            "@type": "Person",
            "name": "Carin Eriksen"
        },
        "education": [
            {
                "@type": "CollegeOrUniversity",
                "name": "Karlstad University",
                "startDate": "1919",
                "endDate": "1920"
            },
            {
                "@type": "CollegeOrUniversity",
                "name": "Royal Institute of Technology",
                "specialty": "Mining Engineering",
                "startDate": "1920",
                "endDate": "1925"
            }
        ],
        "jobTitle": "Manager",
        "worksFor": [
            {
                "@type": "Organization",
                "name": "Lindholmen-Motala AB",
                "jobTitle": "Material Testing Supervisor",
                "startDate": "1926",
                "endDate": "1929"
            },
            {
                "@type": "Organization",
                "name": "Fagersta Steelworks AB",
                "jobTitle": "Rolling Mill Engineer",
                "startDate": "1929",
                "endDate": "1932"
            },
            {
                "@type": "Organization",
                "name": "Smedjebackens Valsverks AB",
                "jobTitle": "Rolling Mill Engineer",
                "startDate": "1932",
                "endDate": "1936"
            },
            {
                "@type": "Organization",
                "name": "Morgårdshammar Mekaniska Verkstads AB",
                "jobTitle": "Rolling Mill Construction Engineer",
                "startDate": "1936",
                "endDate": "1939"
            },
            {
                "@type": "Organization",
                "name": "Morgårdshammar Mekaniska Verkstads AB",
                "jobTitle": "Manager and Director",
                "startDate": "1939"
            },
            {
                "@type": "Organization",
                "name": "AB Arboga Mekaniska Verkstads",
                "jobTitle": "Director of Growth",
                "startDate": "1943"
            }
        ],
        "memberOf": [
            {
                "@type": "Organization",
                "name": "Hallstahammars AB",
                "jobTitle": "Board Member"
            },
            {
                "@type": "Organization",
                "name": "östafors AB",
                "jobTitle": "Board Member"
            },
            {
                "@type": "Organization",
                "name": "AB Septem",
                "jobTitle": "Board Member"
            },
            {
                "@type": "Organization",
                "name": "Swedish Technical Association",
                "jobTitle": "Member"
            }
        ],
        "hobbies": [
            "Outdoor activities",
            "Crafts"
        ],
        "knowsAbout": "Swedish family history"
    },
    "occupations": {
        "career": [
            {
                "occupational_title": "Material testing supervisor",
                "workplace": "AB Lindholmen-Motala",
                "industry": "Manufacturing",
                "start_date": "1926"
            },
            {
                "occupational_title": "Rolling mill engineer",
                "workplace": "Fagersta Br AB",
                "industry": "Manufacturing",
                "start_date": "1929"
            },
            {
                "occupational_title": "Rolling mill engineer",
                "workplace": "Smedjebackens Valsverks AB",
                "industry": "Manufacturing",
                "start_date": "1932"
            },
            {
                "occupational_title": "Rolling mill construction engineer",
                "workplace": "Morgårdshammar Mek Verkst AB",
                "industry": "Manufacturing",
                "start_date": "1936"
            },
            {
                "occupational_title": "Manager and director",
                "workplace": "Morgårdshammar Mek Verkst AB",
                "industry": "Manufacturing",
                "start_date": "1939"
            },
            {
                "occupational_title": "Director of growth",
                "workplace": "AB Arboga Mek Verkst",
                "industry": "Manufacturing",
                "start_date": "1943"
            }
        ]
    }
}