{
    "original": "JOHNSSON, Hans Olof Wiking, Direktör, fd Bruksdisponent, Djursholm, f ö Broby, Krstds l, 27/9 78 av riksd.m H J o Elna Ohlsson, gm Eugenie Schull. Studex 97, ex BergsHS 00, stud USA 01—02. Ing v Benraths Masch.fabr i Benrath am Rh 03—06, övering Kohlswa jvk 07—13, vkst dir Smedjebackens valsv 14—23, ch Sv hdlsbkns ind.rev 23—35, flm Jernkont sed. 18, vkst dir sed. 36. Medl jvgsrådet o 27 års bespar.nmd. Ordf Herrängs grufAB, Nord armaturfabr, Smedjebackens valsv AB, brukstjmfrn 18—36, jvksfrn sed. 28, Järnbr.frb sed. 30, järn- o met.varu-lev.frn sed. 32, styr.led AB Optimus, Ränte-o kap.försäkr.anst i Sthlm, Sv arb.giv.frn sed. 25, Sv ind.frb 28—42, Sv allm exp.frn sed. 29. KVO2kl, RNO, LIVA.",
    "translated": "JOHNSSON, Hans Olof Wiking, Director, former Mill Manager, Djursholm, formerly in Broby, Krstds parish, born on September 27th, 1878 to Member of Parliament H J and Elna Ohlsson, married to Eugenie Schull. Graduated with a high school diploma in 1897, completed studies at BergsHS in 1900, studied in the USA from 1901 to 1902. Engineer at Benraths Masch.fabr in Benrath am Rh from 1903 to 1906, superintendent at Kohlswa jvk from 1907 to 1913, growth director at Smedjebackens valsv from 1914 to 1923, chairman of Sv hdlsbkns ind.rev from 1923 to 1935, board member of Jernkont from 1918, growth director since 1936. Member of the railway council and 27-year savings committee. Chairman of Herrängs grufAB, Nord armaturfabr, Smedjebackens valsv AB, and brukstjmfrn from 1918 to 1936, of jvksfrn since 1928, of Järnbr.frb since 1930, and of järn- o met.varu-lev.frn since 1932. Board member of AB Optimus, Ränte-o kap.försäkr.anst in Stockholm, member of Sv arb.giv.frn since 1925, of Sv ind.frb from 1928 to 1942, and of Sv allm exp.frn since 1929. knight of the Royal Order of Vasa (KVO2kl), knight of the North Star Order (RNO), received the Swedish Life Saving Award (LIVA).",
    "structured": {
        "@context": "https://schema.org/",
        "@type": "Person",
        "name": "Hans Olof Wiking Johnsson",
        "givenName": "Hans Olof Wiking",
        "familyName": "Johnsson",
        "birthDate": "1878-09-27",
        "birthPlace": "Broby, Krstds parish",
        "description": "Director, former Mill Manager",
        "spouse": {
            "@type": "Person",
            "name": "Eugenie Schull"
        },
        "parent": [
            {
                "@type": "Person",
                "name": "H J Johnsson",
                "description": "Member of Parliament"
            },
            {
                "@type": "Person",
                "name": "Elna Ohlsson"
            }
        ],
        "education": [
            {
                "@type": "School",
                "name": "Studex",
                "endDate": "1897"
            },
            {
                "@type": "School",
                "name": "BergsHS",
                "endDate": "1900"
            },
            {
                "@type": "School",
                "name": "USA studies",
                "startDate": "1901",
                "endDate": "1902"
            }
        ],
        "jobTitle": "Director",
        "worksFor": {
            "@type": "Organization",
            "name": "Djursholm"
        },
        "memberOf": [
            {
                "@type": "Organization",
                "name": "Herrängs grufAB",
                "roleName": "Chairman"
            },
            {
                "@type": "Organization",
                "name": "Nord armaturfabr",
                "roleName": "Chairman"
            },
            {
                "@type": "Organization",
                "name": "Smedjebackens valsv AB",
                "roleName": "Chairman"
            },
            {
                "@type": "Organization",
                "name": "brukstjmfrn",
                "startDate": "1918",
                "endDate": "1936",
                "roleName": "Chairman"
            },
            {
                "@type": "Organization",
                "name": "jvksfrn",
                "startDate": "1928",
                "roleName": "Chairman"
            },
            {
                "@type": "Organization",
                "name": "Järnbr.frb",
                "startDate": "1930",
                "roleName": "Chairman"
            },
            {
                "@type": "Organization",
                "name": "järn- o met.varu-lev.frn",
                "startDate": "1932",
                "roleName": "Chairman"
            },
            {
                "@type": "Organization",
                "name": "AB Optimus",
                "roleName": "Board member"
            },
            {
                "@type": "Organization",
                "name": "Ränte-o kap.försäkr.anst",
                "roleName": "Board member"
            },
            {
                "@type": "Organization",
                "name": "Sv arb.giv.frn",
                "startDate": "1925",
                "roleName": "Member"
            },
            {
                "@type": "Organization",
                "name": "Sv ind.frb",
                "startDate": "1928",
                "endDate": "1942",
                "roleName": "Member"
            },
            {
                "@type": "Organization",
                "name": "Sv allm exp.frn",
                "startDate": "1929",
                "roleName": "Member"
            }
        ],
        "awards": [
            {
                "@type": "Order",
                "name": "Royal Order of Vasa",
                "description": "KVO2kl"
            },
            {
                "@type": "Order",
                "name": "North Star Order",
                "description": "RNO"
            },
            {
                "@type": "CreativeWork",
                "name": "Swedish Life Saving Award",
                "description": "LIVA"
            }
        ]
    },
    "occupations": {
        "career": [
            {
                "occupational_title": "Mill Manager",
                "workplace": "Unknown",
                "industry": "Unknown",
                "start_date": "Unknown"
            },
            {
                "occupational_title": "Engineer",
                "workplace": "Benraths Masch.fabr, Benrath am Rh",
                "industry": "Machinery manufacturing",
                "start_date": "1903"
            },
            {
                "occupational_title": "Superintendent",
                "workplace": "Kohlswa jvk",
                "industry": "Unknown",
                "start_date": "1907"
            },
            {
                "occupational_title": "Growth Director",
                "workplace": "Smedjebackens valsv",
                "industry": "Unknown",
                "start_date": "1914"
            },
            {
                "occupational_title": "Chairman",
                "workplace": "Sv hdlsbkns ind.rev",
                "industry": "Retail trade",
                "start_date": "1923"
            },
            {
                "occupational_title": "Board member",
                "workplace": "Jernkont",
                "industry": "Iron and steel industry",
                "start_date": "1918"
            },
            {
                "occupational_title": "Growth Director",
                "workplace": "Unknown",
                "industry": "Unknown",
                "start_date": "1936"
            }
        ]
    }
}