{
    "original": "HERMANSON, Karl Erik, överingenjör, Degerfors, f Skredsvik, Gbgs o Boh l, 27/10 94 av godsäg H H o Anna Andersson, gm Ingrid Löfwenström. Realex 09, jordbr- o skogsstud 09—12, ex Borås tekn gymn 15, BergsHS 17—19. Ass v Fagersta Bruks metallab 17, ch f Söderfors Bruks metallab 19— 28, lab.ch v Hellefors Bruks AB 28—35, tilllika martining fr 33 o övering fr 36, övering v Strömsnäs Jvks AB i Degerfors 39, nu övering v Degerfors Jvks AB. Ag gård, Hasselön, Bohusl. Inneh fi kommunala uppdr. Distr.ch f Degerfors luftskyddsort. Resor: Engl 31, USA 33 mfl. Riksluftsskyddsfrbs ftjSM, Uppl Idr.frbs ftjSM o plak br. Hobbies: Friluftsliv, idrott. °HERMANSON, Knut, Grosshandlare, Haparanda, f Hap 9/6 85 av köpm H M H, gm Hilda Wallgren. Studex 03, Schartaus, övert faderns fma H M Hermanson, herrekip-, päls-o garnaff (gr 68) 11, inneh dna. Fd stdsflm-ordf, kronoomb i tax.nmd, ordf i beredn.utsk o hdls- o sjöf.nmd, stadsrev o led kyrkoråd, hamndir mfl styr o nmd, led jurymannakåren, styr.led hal, led folksk.styr. Huv.man i Hap sparbk, styr.led Sv Hdlsbkns Hap.kont. Resor : Ryssl mfl länd 05—10.",
    "translated": "HERMANSON, Karl Erik, Chief Engineer, Degerfors, born in Skredsvik, Gothenburg and Bohus County, on October 27, 1894, to landowner H H and Anna Andersson. Married to Ingrid Löfwenström. Completed junior high school in 1909, studied agriculture and forestry from 1909 to 1912, graduated from Borås Technical High School in 1915, and attended Bergs School of Mining from 1917 to 1919. Assistant at Fagersta Bruk's metallurgical laboratory in 1917, chief of Söderfors Bruk's metallurgical laboratory from 1919 to 1928, laboratory chief at Hellefors Bruks AB from 1928 to 1935, also served as Martinizing chemist from 1933 and Chief Engineer from 1936, Chief Engineer at Strömsnäs Jvks AB in Degerfors from 1939, currently Chief Engineer at Degerfors Jvks AB. Owns a farm in Hasselön, Bohuslän County. Holds various municipal appointments. District Chief of Degerfors air raid defense. Traveled to England in 1931, USA in 1933, and others. National Air Defense Association's silver medal, Uppsala Sports Association's silver medal, and plaque br. Hobbies: Outdoor life, sports.\n\nHERMANSON, Knut, Merchant, Haparanda, born in Haparanda on June 9, 1885, to merchant H M H and Hilda Wallgren. Graduated in 1903 from Schartau's College, took over his father's company H M Hermanson, a gentlemen's clothier, furrier, and yarn shop (established 1868) in 1911, currently proprietor. Former chairman of the city film committee, member of the tax board, chairman of various committees, commerce and maritime board, city auditor, member of the church council, harbor authority, and other boards and committees, member of the jury corps, and board member of the local school board. Main representative of Haparanda Savings Bank, board member of the Swedish Trade Bank's Haparanda branch. Traveled to Russia and other countries from 1905 to 1910.",
    "structured": {
        "@context": "https://schema.org",
        "@type": "Person",
        "name": "Karl Erik Hermanson",
        "jobTitle": "Chief Engineer",
        "birthDate": "1894-10-27",
        "birthPlace": {
            "@type": "City",
            "name": "Skredsvik"
        },
        "address": {
            "@type": "PostalAddress",
            "addressLocality": "Degerfors"
        },
        "nationality": "Swedish",
        "parents": [
            {
                "@type": "Person",
                "name": "H H Hermanson"
            },
            {
                "@type": "Person",
                "name": "Anna Andersson"
            }
        ],
        "spouse": {
            "@type": "Person",
            "name": "Ingrid Löfwenström"
        },
        "education": [
            {
                "@type": "EducationalOrganization",
                "name": "Borås Technical High School",
                "startDate": "1915"
            },
            {
                "@type": "EducationalOrganization",
                "name": "Bergs School of Mining",
                "startDate": "1917",
                "endDate": "1919"
            }
        ],
        "workExperience": [
            {
                "@type": "Organization",
                "name": "Fagersta Bruk",
                "jobTitle": "Metallurgical Laboratory Assistant",
                "startDate": "1917",
                "endDate": "1919"
            },
            {
                "@type": "Organization",
                "name": "Söderfors Bruk",
                "jobTitle": "Chief of Metallurgical Laboratory",
                "startDate": "1919",
                "endDate": "1928"
            },
            {
                "@type": "Organization",
                "name": "Hellefors Bruks AB",
                "jobTitle": "Laboratory Chief",
                "startDate": "1928",
                "endDate": "1935"
            },
            {
                "@type": "Organization",
                "name": "Hellefors Bruks AB",
                "jobTitle": "Martinizing Chemist",
                "startDate": "1933"
            },
            {
                "@type": "Organization",
                "name": "Strömsnäs Jvks AB",
                "jobTitle": "Chief Engineer",
                "startDate": "1939"
            },
            {
                "@type": "Organization",
                "name": "Degerfors Jvks AB",
                "jobTitle": "Chief Engineer"
            }
        ],
        "memberOf": [
            {
                "@type": "SportsTeam",
                "name": "Riksluftsskyddsfrbs"
            },
            {
                "@type": "SportsTeam",
                "name": "Uppl Idr.frbs"
            }
        ],
        "hobbies": [
            "Outdoor life",
            "Sports"
        ],
        "sameAs": [
            "https://example.com/karlerik-hermanson"
        ]
    },
    "occupations": {
        "career": [
            {
                "occupational_title": "Assistant",
                "workplace": "Fagersta Bruks metallab",
                "industry": "Metallurgical",
                "start_date": "1917"
            },
            {
                "occupational_title": "Chief of Söderfors Bruks metallab",
                "workplace": "Söderfors Bruks",
                "industry": "Metallurgical",
                "start_date": "1919"
            },
            {
                "occupational_title": "Laboratory Chief",
                "workplace": "Hellefors Bruks AB",
                "industry": "Metallurgical",
                "start_date": "1928"
            },
            {
                "occupational_title": "Martinizing Chemist",
                "workplace": "Hellefors Bruks AB",
                "industry": "Textile",
                "start_date": "1933"
            },
            {
                "occupational_title": "Chief Engineer",
                "workplace": "Hellefors Bruks AB",
                "industry": "Various",
                "start_date": "1936"
            },
            {
                "occupational_title": "Chief Engineer",
                "workplace": "Strömsnäs Jvks AB",
                "industry": "Various",
                "start_date": "1939"
            },
            {
                "occupational_title": "Chief Engineer",
                "workplace": "Degerfors Jvks AB",
                "industry": "Various",
                "start_date": ""
            }
        ]
    }
}