{
    "original": "NORDQUIST, Elis (Esse), Major, Linköping, f Skön, Vnorrl l, 18/3 88 av sågv.förv A N o Nella Fernlund, gm Lisa Lundgren. Studex 07, Offex 11, AIHS 13—14, flygcertif 15. Uljt A.4 11, ljt 15, kapt v Flygv 26, major 34, ch f Thulins flygsk Ljungbyhed 17—21, verkst.oli’ Flygv :s verkst å Malmen 21—26, ass Flygstyr :s mil.byrå 26—32, i Persisk t j 32—34, överste o insp v Pers flygv 34, ch Sv jvgsverkstäd :s aeroplanavd 34—39, övering Sv aeroplanAB sed. 39. Led flygsäker-hetsutredn 29—31. Stdflm sed. 43. Ordf Linkps flygkl, styr.led Sv aerokl o Flygtekn frn, fd ordf Ögl tekn frn. Uppr res t flert europ länd m flygstud i Engl, Tyskl o Frankr 22— 39, Pers, Irak, Syr, Palest, Egypt, Turk 32— 34, studieres USA 36. RSO, RFinlVROlkl, IranHYO; Iranska luftstridskraft :s flygm; Rotary, SHT, Trav Club, Wiknings-Commis-sionen. Hobbies: Skidlöpning, jakt, fiske, segling.",
    "translated": "NORDQUIST, Elis (Esse), Major, Linköping, born in Skön, Västernorrland County, on March 18, 1888. Son of a sawmill manager A.N. Nordquist and Nella Fernlund. Married to Lisa Lundgren. Graduated high school in 1907, became an officer in 1911, attended the Royal Swedish Army Staff College in 1913-1914, and obtained a pilot's license in 1915. Joined the Swedish Air Force Type A.4 in 1911, promoted to lieutenant in 1915, captain in the Flying Corps in 1926, and major in 1934. Served as chief of Thulin's Flight School in Ljungbyhed from 1917 to 1921, worked in the aviation department at F 2 Malmen from 1921 to 1926, served in the Air Force's military bureau from 1926 to 1932, served in the Persian Army from 1932 to 1934, and became colonel and inspector of the Persian Air Force in 1934. Later became head of the aircraft department at the Swedish Railway Workshop from 1934 to 1939, and chief engineer at the Swedish Aircraft AB from 1939. Led the aviation safety investigation from 1929 to 1931 and chaired the Linköping Flying Club. Also served on the board of the Swedish Aero Club and the Aviation Technology Society, and was a former chairman of the Östergötland Technical Society. Conducted aviation studies in several European countries, including England, Germany, and France, from 1922 to 1939, and studied in Persia, Iraq, Syria, Palestine, Egypt, and Turkey from 1932 to 1934. Continued studies in the United States in 1936. Received the Royal Order of the Sword, Order of the Polar Star, and the Iranian Kurosh Medal. Served in the Iranian Air Force. Member of Rotary, SHT (Swedish Technical Association), and the Travel Club. Also served on the Wikning Commission. Hobbies include skiing, hunting, fishing, and sailing.\n\nNote: The information about marriage is not provided in the abbreviated biography.",
    "structured": {
        "@context": "https://schema.org",
        "@type": "Person",
        "name": "Elis Nordquist",
        "familyName": "Nordquist",
        "givenName": "Elis",
        "additionalName": "Esse",
        "birthDate": "1888-03-18",
        "birthPlace": "Skön, Västernorrland County",
        "deathDate": null,
        "nationality": "Swedish",
        "description": "Major in the Swedish Air Force",
        "spouse": {
            "@type": "Person",
            "name": "Lisa Lundgren"
        },
        "parents": [
            {
                "@type": "Person",
                "name": "A.N. Nordquist"
            },
            {
                "@type": "Person",
                "name": "Nella Fernlund"
            }
        ],
        "education": {
            "@type": "EducationalOccupationalCredential",
            "credentialCategory": "studex",
            "startDate": "1907"
        },
        "alumniOf": {
            "@type": "CollegeOrUniversity",
            "name": "Royal Swedish Army Staff College"
        },
        "worksFor": {
            "@type": "Organization",
            "name": "Swedish Aircraft AB"
        },
        "jobTitle": "Major",
        "affiliation": [
            {
                "@type": "Organization",
                "name": "Thulin's Flight School"
            },
            {
                "@type": "Organization",
                "name": "F 2 Malmen"
            },
            {
                "@type": "Organization",
                "name": "Swedish Railway Workshop",
                "department": "Aircraft Department"
            },
            {
                "@type": "Organization",
                "name": "Swedish Aero Club"
            },
            {
                "@type": "Organization",
                "name": "Aviation Technology Society"
            },
            {
                "@type": "Organization",
                "name": "Wikning Commission"
            }
        ],
        "memberOf": [
            {
                "@type": "Organization",
                "name": "Linköping Flying Club",
                "roleName": "Chairperson"
            },
            {
                "@type": "Organization",
                "name": "Östergötland Technical Society",
                "formerRoleName": "Chairperson"
            },
            {
                "@type": "Organization",
                "name": "Rotary"
            },
            {
                "@type": "Organization",
                "name": "SHT (Swedish Technical Association)"
            },
            {
                "@type": "Organization",
                "name": "Travel Club"
            }
        ],
        "hobbies": [
            "Skiing",
            "Hunting",
            "Fishing",
            "Sailing"
        ],
        "awards": [
            {
                "@type": "Order",
                "name": "Royal Order of the Sword",
                "identifier": "RSO"
            },
            {
                "@type": "Order",
                "name": "Order of the Polar Star",
                "identifier": "RFinlVROlkl"
            },
            {
                "@type": "Order",
                "name": "Iranian Kurosh Medal",
                "identifier": "IranHYO"
            }
        ],
        "hasOccupation": {
            "@type": "Occupation",
            "name": "Inspector of the Persian Air Force",
            "startDate": "1934",
            "endDate": null
        },
        "hasMembership": {
            "@type": "Membership",
            "name": "Iranian Air Force",
            "organization": {
                "@type": "Organization",
                "name": "Iranska luftstridskraft"
            }
        },
        "hasStudy": [
            {
                "@type": "Study",
                "name": "England",
                "startDate": "1922",
                "endDate": "1939",
                "description": "Aviation studies"
            },
            {
                "@type": "Study",
                "name": "Germany",
                "startDate": "1922",
                "endDate": "1939",
                "description": "Aviation studies"
            },
            {
                "@type": "Study",
                "name": "France",
                "startDate": "1922",
                "endDate": "1939",
                "description": "Aviation studies"
            },
            {
                "@type": "Study",
                "name": "Persia",
                "startDate": "1932",
                "endDate": "1934",
                "description": "Aviation studies"
            },
            {
                "@type": "Study",
                "name": "Iraq",
                "startDate": "1932",
                "endDate": "1934",
                "description": "Aviation studies"
            },
            {
                "@type": "Study",
                "name": "Syria",
                "startDate": "1932",
                "endDate": "1934",
                "description": "Aviation studies"
            },
            {
                "@type": "Study",
                "name": "Palestine",
                "startDate": "1932",
                "endDate": "1934",
                "description": "Aviation studies"
            },
            {
                "@type": "Study",
                "name": "Egypt",
                "startDate": "1932",
                "endDate": "1934",
                "description": "Aviation studies"
            },
            {
                "@type": "Study",
                "name": "Turkey",
                "startDate": "1932",
                "endDate": "1934",
                "description": "Aviation studies"
            },
            {
                "@type": "Study",
                "name": "United States",
                "startDate": "1936",
                "endDate": null,
                "description": "Aviation studies"
            }
        ]
    },
    "occupations": {
        "career": [
            {
                "occupational_title": "Sawmill Manager",
                "workplace": "A.N. Nordquist Sawmill",
                "industry": "Forestry",
                "start_date": "Before 1888"
            },
            {
                "occupational_title": "Officer",
                "workplace": "Royal Swedish Army",
                "industry": "Military",
                "start_date": "1911"
            },
            {
                "occupational_title": "Chief of Thulin's Flight School",
                "workplace": "Thulin's Flight School, Ljungbyhed",
                "industry": "Aviation",
                "start_date": "1917"
            },
            {
                "occupational_title": "Aviation Department",
                "workplace": "F 2 Malmen",
                "industry": "Aviation",
                "start_date": "1921"
            },
            {
                "occupational_title": "Air Force's Military Bureau",
                "workplace": "Swedish Air Force",
                "industry": "Defense",
                "start_date": "1926"
            },
            {
                "occupational_title": "Military Service",
                "workplace": "Persian Army",
                "industry": "Defense",
                "start_date": "1932"
            },
            {
                "occupational_title": "Inspector of Persian Air Force",
                "workplace": "Persian Air Force",
                "industry": "Defense",
                "start_date": "1934"
            },
            {
                "occupational_title": "Head of Aircraft Department",
                "workplace": "Swedish Railway Workshop",
                "industry": "Transportation",
                "start_date": "1934"
            },
            {
                "occupational_title": "Chief Engineer",
                "workplace": "Swedish Aircraft AB",
                "industry": "Aviation",
                "start_date": "1939"
            },
            {
                "occupational_title": "Aviation Safety Investigation",
                "workplace": "Swedish Air Force",
                "industry": "Defense",
                "start_date": "1929"
            }
        ]
    }
}