{
    "original": "BANG, August Teodor, Direktör, Stockholm, f oSthlm 10/2 81 av fastigh.äg A W A:son Bång o h h, gm Anna Norberg. Schartaus handelsinst 98. Kont.chef h Gas, Vatten &amp; Värme AB 02—08, h AB Rylander &amp; Asplund 09-—23, deläg o dir i AB Armaturfabr Svea Kungsör sed, 23. Dir i AB Storliens Högfjäll 28—35. Skattmäst i Frn f Skidlöpn :s Främj 17—34, styr.led där sed. 14 o i Sv Skidfrb 14— 42, repr i Sv Skiddeleg sed. 14, ktéled o funkt v Nord Spel o sv rnästersk.tävl i skidlöpn und fi år, en av init.tacr t o styr.led i Sthlms Friv Motorbåtsflottilj 15—25, v. flottiljeh 37 —41, init.tag t sv skidl.m. RNO, RVO. Skid-främj:s GM o IM, Sv Skidfrbs GM o ftjplak g, Sv Idr.frbs ftjt g, skidl.gm o d:o högre klassen, Sv Friv Motorb.kårs GM, Sthlms Motorb.flottiljs ftjt s o g, Sthlms Roddfrns ftjt g. Hobbies: Skidor, segling, resor, foto.",
    "translated": "BANG, August Teodor, Director, Stockholm, b. Stockholm 10/2 1881, son of property owner A W A:son Bång and his wife, married to Anna Norberg. Schartau's Commercial Institute 1898. Head of Accounts at Gas, Water & Heating AB 1902-1908, at AB Rylander & Asplund 1909-1923, co-owner and director at AB Armaturfabrik Svea Kungsör since 1923. Director at AB Storliens Högfjäll 1928-1935. Treasurer of the Swedish Ski Association's Ski Jump Promotion 1917-1934, board member since 1914 and board member of the Swedish Ski Federation 1914-1942, representative in the Swedish Ski Delegation since 1914, chairman and functionary at the Nordic Games and Swedish National Ski Championships for five years. One of the initiators and board members of the Stockholm Free Motorboat Flotilla 1915-1925, vice flotilla commander 1937-1941, initiator of the Swedish Ski School. Recipient of the Order of the North Star, the Royal Order of Vasa. Ski Promotion's Gold and Silver Medals, Swedish Ski Federation's Gold and Silver Medals, Swedish Sports Federation's Silver and Gold Medals, ski jumping Gold and other higher classes, Stockholm Free Motorboat Corps Gold Medal, Stockholm Motorboat Flotilla's Silver and Gold Medals, Stockholm Rowing Society's Gold Medal. Hobbies: Skiing, sailing, travel, photography.",
    "structured": {
        "@context": "https://schema.org",
        "@type": "Person",
        "name": "August Teodor Bang",
        "jobTitle": "Director",
        "address": {
            "@type": "PostalAddress",
            "addressLocality": "Stockholm"
        },
        "birthDate": "1881-02-10",
        "parent": [
            {
                "@type": "Person",
                "name": "A W A:son Bång"
            },
            {
                "@type": "Person",
                "name": "h h"
            }
        ],
        "spouse": {
            "@type": "Person",
            "name": "Anna Norberg"
        },
        "education": {
            "@type": "EducationalOccupationalCredential",
            "credentialCategory": "diploma",
            "educationalLevel": "post-secondary",
            "educationalCredentialAwarded": "Schartau's Commercial Institute",
            "startDate": "1898"
        },
        "workExperience": [
            {
                "@type": "OrganizationRole",
                "startDate": "1902",
                "endDate": "1908",
                "roleName": "Head of Accounts",
                "organization": {
                    "@type": "Organization",
                    "name": "Gas, Water & Heating AB"
                }
            },
            {
                "@type": "OrganizationRole",
                "startDate": "1909",
                "endDate": "1923",
                "roleName": "Head of Accounts",
                "organization": {
                    "@type": "Organization",
                    "name": "AB Rylander & Asplund"
                }
            },
            {
                "@type": "OrganizationRole",
                "startDate": "1923",
                "roleName": "Co-owner and Director",
                "organization": {
                    "@type": "Organization",
                    "name": "AB Armaturfabrik Svea Kungsör"
                }
            },
            {
                "@type": "OrganizationRole",
                "startDate": "1928",
                "endDate": "1935",
                "roleName": "Director",
                "organization": {
                    "@type": "Organization",
                    "name": "AB Storliens Högfjäll"
                }
            }
        ],
        "memberOf": [
            {
                "@type": "Organization",
                "name": "Swedish Ski Association's Ski Jump Promotion",
                "startDate": "1917",
                "endDate": "1934",
                "roleName": "Treasurer"
            },
            {
                "@type": "Organization",
                "name": "Swedish Ski Federation",
                "startDate": "1914",
                "endDate": "1942",
                "roleName": "Board Member"
            },
            {
                "@type": "Organization",
                "name": "Swedish Ski Delegation",
                "startDate": "1914",
                "roleName": "Representative"
            }
        ],
        "skiActivities": [
            "Ski Jumping",
            "Nordic Games",
            "Swedish National Ski Championships"
        ],
        "awards": [
            {
                "@type": "Order",
                "name": "Order of the North Star"
            },
            {
                "@type": "Order",
                "name": "Royal Order of Vasa"
            },
            {
                "@type": "Medal",
                "name": "Ski Promotion's Gold Medal"
            },
            {
                "@type": "Medal",
                "name": "Ski Promotion's Silver Medal"
            },
            {
                "@type": "Medal",
                "name": "Swedish Ski Federation's Gold Medal"
            },
            {
                "@type": "Medal",
                "name": "Swedish Ski Federation's Silver Medal"
            },
            {
                "@type": "Medal",
                "name": "Swedish Sports Federation's Silver Medal"
            },
            {
                "@type": "Medal",
                "name": "Swedish Sports Federation's Gold Medal"
            },
            {
                "@type": "Medal",
                "name": "Stockholm Free Motorboat Corps Gold Medal"
            },
            {
                "@type": "Medal",
                "name": "Stockholm Free Motorboat Corps Silver Medal"
            },
            {
                "@type": "Medal",
                "name": "Stockholm Motorboat Flotilla's Gold Medal"
            },
            {
                "@type": "Medal",
                "name": "Stockholm Motorboat Flotilla's Silver Medal"
            },
            {
                "@type": "Medal",
                "name": "Stockholm Rowing Society's Gold Medal"
            }
        ],
        "hobbies": [
            "Skiing",
            "Sailing",
            "Travel",
            "Photography"
        ]
    },
    "occupations": {
        "career": [
            {
                "occupational_title": "Head of Accounts",
                "workplace": "Gas, Water & Heating AB",
                "industry": "Utilities",
                "start_date": "1902"
            },
            {
                "occupational_title": "Head of Accounts",
                "workplace": "AB Rylander & Asplund",
                "industry": "Unknown",
                "start_date": "1909"
            },
            {
                "occupational_title": "Co-owner and Director",
                "workplace": "AB Armaturfabrik Svea Kungsör",
                "industry": "Manufacturing",
                "start_date": "1923"
            },
            {
                "occupational_title": "Director",
                "workplace": "AB Storliens Högfjäll",
                "industry": "Tourism",
                "start_date": "1928"
            }
        ]
    }
}