{
    "original": "GRÖNKVIST, Gustaf Hilmer, Direktör, Lund, f V Vingåker 11/2 75 av skom.mäst G A G o Lina Lundström, gm Anna Carlson. Priv.stud mm. Anst Krooks bokhdl Vingåker 89—92, C A Rohloffs bokhdl Örebro 92—01, sed. 01 i Gleerupska Univ.bokhdln Lund (gr 1826, AB 10), vkst dir sed. 30 samt v. styr.ordf. Juryman sed. 37. Styr.led Sv Bokhdlfrns Skånekr o suppl i centr.styr, styr.led Frn Det gamla Lund, v. ordf Minnesfdn i Lund. Resor: Norge, Danm, Tyskl, Schweiz, Ital, Belg, Holl, Engl, Frankr, Österr, Palest, Syr, Egypt, Tripolis uppr ggr 06—38. Av trycket: Hans Johan Falkman, En tidsbild fr Säfstaholms glansdagar, 32, Johan Fredrik Bahr o hans beskr ö V Vingåker, 32, art i tidn o tidskr. PatrstGM, Rotary (pres 41—42). Hobbies: Mynt o medaljer, Vingåker, resor.",
    "translated": "GRÖNKVIST, Gustaf Hilmer, Director, Lund, b Vingåker 11/2 75, son of shoemaker G.A.G. and Lina Lundström, m. Anna Carlson. Private studies and more. Employed at Krooks bookstore Vingåker 89-92, C.A. Rohloffs bookstore Örebro 92-01, since 01 at Gleerupska University bookstores Lund (graduated 1826, AB 10), managing director since 30 and vice chairman of the board. Juryman since 37. Board member of the Swedish Booksellers' Skåne chapter and substitute in the central board, board member of Från Det gamla Lund, vice chair of the Lund Memorials Foundation. Travels: Norway, Denmark, Germany, Switzerland, Italy, Belgium, the Netherlands, England, France, Austria, Palestine, Syria, Egypt, Tripoli established in 06-38. Published works: Hans Johan Falkman, En tidsbild fr Säfstaholms glansdagar, 32, Johan Fredrik Bahr and his description of Vingåker, 32, articles in newspapers and magazines. Member of PatrstGM, Rotary (president 41-42). Hobbies: Coins and medals, Vingåker, traveling.",
    "structured": {
        "@context": "https://schema.org/",
        "@type": "Person",
        "name": "Gustaf Hilmer Grönkvist",
        "birthDate": "1875-02-11",
        "birthPlace": "Vingåker",
        "parent": [
            {
                "@type": "Person",
                "name": "G.A.G.",
                "jobTitle": "Shoemaker"
            },
            {
                "@type": "Person",
                "name": "Lina Lundström"
            }
        ],
        "spouse": {
            "@type": "Person",
            "name": "Anna Carlson"
        },
        "education": {
            "@type": "EducationalOccupationalCredential",
            "credentialCategory": "Private Studies"
        },
        "worksFor": [
            {
                "@type": "Organization",
                "name": "Krooks Bokhandel",
                "location": "Vingåker",
                "startDate": "1889",
                "endDate": "1892"
            },
            {
                "@type": "Organization",
                "name": "C.A. Rohloffs Bokhandel",
                "location": "Örebro",
                "startDate": "1892",
                "endDate": "1901"
            },
            {
                "name": "Gleerupska Universitetsbokhandeln",
                "location": "Lund",
                "startDate": "1901"
            }
        ],
        "memberOf": [
            {
                "@type": "Organization",
                "name": "PatrstGM"
            },
            {
                "@type": "Organization",
                "name": "Rotary",
                "roleName": "President",
                "startDate": "1941",
                "endDate": "1942"
            }
        ],
        "jobTitle": "Director",
        "careerStartDate": "1830",
        "event": [
            {
                "@type": "JuryMembership",
                "startDate": "1937"
            }
        ],
        "travelHistory": [
            "Norway",
            "Denmark",
            "Germany",
            "Switzerland",
            "Italy",
            "Belgium",
            "Netherlands",
            "England",
            "France",
            "Austria",
            "Palestine",
            "Syria",
            "Egypt",
            "Tripoli"
        ],
        "publication": [
            {
                "@type": "Article",
                "name": "Hans Johan Falkman, En tidsbild fr Säfstaholms glansdagar",
                "publicationDate": "1932"
            },
            {
                "@type": "Article",
                "name": "Johan Fredrik Bahr and his description of Vingåker",
                "publicationDate": "1932"
            }
        ],
        "hobbies": [
            "Coins and medals",
            "Vingåker",
            "Traveling"
        ]
    },
    "occupations": {
        "career": [
            {
                "occupational_title": "Director",
                "workplace": "Lund",
                "industry": "",
                "start_date": ""
            },
            {
                "occupational_title": "Employee",
                "workplace": "Krooks bookstore",
                "industry": "Bookstore",
                "start_date": "1889"
            },
            {
                "occupational_title": "Employee",
                "workplace": "C.A. Rohloffs bookstore",
                "industry": "Bookstore",
                "start_date": "1892"
            },
            {
                "occupational_title": "Managing Director",
                "workplace": "Gleerupska University bookstores Lund",
                "industry": "Bookstore",
                "start_date": "1901"
            }
        ]
    }
}