{
    "original": "EDLUND, Erik Harald, Köpman, Nordmaling, f Gideå, Vnorr l, 10/8 98 av dir Axel E 0 Hulda Gidlund, gm Tyra Eriksson. Ex från högre hdlsläroverk. Inneh Olofsfors Bruks-handel sed. 26. Ordf i Nordmalings Köpm.frn 28—42, i Västerb Södra Köpm.frb sed. 34, led av Umeå Engrossistfrn :s o Köpm.förbundets Samarbetsnämnd sed. 34, styr.led i Sv Köpm.frb sed. 36, styr.suppl i Sv Speceri- &amp; Livsm.-handl.frb 35—41, led av Sv Köpm.frbs arbets-utsk sed. 41, av dess propagandaråd sed. 42, godeman vid ackordsförhandl utan konkurs sed. 36, styr.led i Stiftelsen Solstickans .Väs-terb.krets sed. 38, led av Västerb kristidsstyr sed. 39, av styr för Hörnefors Nya Handels AB sed. 21, av styr för AB Svenska Handelsbankens avd.kontor i Nordmaling sed. 44. Ordf i Hörnefors Idr.frn 22—26, hedersordf 31. v. ordf i Västerb Fotbollsfrb 24—26, ordf 1 förbundets UK 24—26, ordf i Olofsfors Idr.-klubb sed. 30. Ledareskribent i Västerbottens Köpmannatidning sed. 34, författat artiklar i bokverk o tidningar. Resor: Danm o Tyskl. Riksidrottsfrb :s och Västerb Fotbollsfrb :s diplom, Sv Köpm.frb :s diplom o hederstecken i guld, Hörnefors Idr.frn :s hederstecken i guld o silver. Hobbies: Idrott, journalistik.",
    "translated": "EDLUND, Erik Harald, Merchant, Nordmaling, born in Gideå, Västernorrland county, on October 8, 1898, son of Director Axel E. and Hulda Gidlund, married to Tyra Eriksson. Graduated from a higher business school. Involved in Olofsfors Ironworks trade since 1926. Chairman of Nordmalings Merchants Association from 1928 to 1942, and of Västerbotten South Merchants Association from 1934. Member of the Umeå Wholesale Merchants Association and the Merchants' Association's Cooperation Committee since 1934. Member of the Board of Directors of the Swedish Merchants' Association since 1936 and of the Swedish Grocery and Food Trade Association from 1935 to 1941. Member of the Swedish Merchants' Association's working committee since 1941 and of its propaganda council since 1942. Administrator in bankruptcy reconciliation proceedings since 1936. Member of the Solstickan Foundation's board of directors - Västerbotten district since 1938. Member of the Västerbotten crisis management board since 1939. Member of the board of Hörnefors New Trading AB since 1921 and of the board of Swedish Handelsbanken's branch office in Nordmaling since 1944. Chairman of Hörnefors Sports Club from 1922 to 1926, honorary chairman in 1931. Vice Chairman of the Västerbotten Football Association from 1924 to 1926, Chairman of the Association's Youth Committee from 1924 to 1926, Chairman of Olofsfors Sports Club since 1930. Editorial writer in Västerbottens Merchants' Journal since 1934, author of articles in books and newspapers. Traveled to Denmark and Germany. Received diplomas from the National Sports Association and the Västerbotten Football Association, the Swedish Merchants' Association's diploma and gold medal, and Hörnefors Sports Club's gold and silver medals of honor. Hobbies: Sports, journalism.",
    "structured": {
        "@context": "http://schema.org",
        "@type": "Person",
        "name": "Erik Harald Edlund",
        "birthDate": "1898-08-10",
        "birthPlace": {
            "@type": "Place",
            "address": {
                "@type": "PostalAddress",
                "addressLocality": "Gideå",
                "addressRegion": "Västernorrland",
                "addressCountry": "Sweden"
            }
        },
        "parents": [
            {
                "@type": "Person",
                "name": "Axel E. Edlund",
                "jobTitle": "Director"
            },
            {
                "@type": "Person",
                "name": "Hulda Gidlund"
            }
        ],
        "spouse": {
            "@type": "Person",
            "name": "Tyra Eriksson"
        },
        "education": [
            {
                "@type": "EducationalOrganization",
                "name": "Higher Business School"
            }
        ],
        "occupation": "Merchant",
        "workLocation": {
            "@type": "Place",
            "address": {
                "@type": "PostalAddress",
                "addressLocality": "Nordmaling",
                "addressCountry": "Sweden"
            }
        },
        "workAffiliations": [
            {
                "@type": "Organization",
                "name": "Olofsfors Ironworks"
            },
            {
                "@type": "Organization",
                "name": "Nordmalings Merchants Association",
                "startDate": "1928",
                "endDate": "1942",
                "jobTitle": "Chairman"
            },
            {
                "@type": "Organization",
                "name": "Västerbotten South Merchants Association",
                "startDate": "1934",
                "jobTitle": "Chairman"
            },
            {
                "@type": "Organization",
                "name": "Umeå Wholesale Merchants Association"
            },
            {
                "@type": "Organization",
                "name": "Merchants' Association",
                "jobTitle": "Cooperation Committee Member"
            },
            {
                "@type": "Organization",
                "name": "Swedish Merchants' Association",
                "startDate": "1936",
                "jobTitle": "Board of Directors"
            },
            {
                "@type": "Organization",
                "name": "Swedish Grocery and Food Trade Association",
                "startDate": "1935",
                "endDate": "1941",
                "jobTitle": "Board Member"
            },
            {
                "@type": "Organization",
                "name": "Solstickan Foundation",
                "startDate": "1938",
                "jobTitle": "Board of Directors - Västerbotten district"
            },
            {
                "@type": "Organization",
                "name": "Västerbotten Crisis Management Board",
                "startDate": "1939",
                "jobTitle": "Board Member"
            },
            {
                "@type": "Organization",
                "name": "Hörnefors New Trading AB",
                "startDate": "1921",
                "jobTitle": "Board Member"
            },
            {
                "@type": "Organization",
                "name": "Swedish Handelsbanken",
                "jobTitle": "Branch Office Board Member"
            }
        ],
        "memberships": [
            {
                "@type": "Organization",
                "name": "Hörnefors Sports Club",
                "startDate": "1922",
                "endDate": "1926",
                "jobTitle": "Chairman"
            },
            {
                "@type": "Organization",
                "name": "Västerbotten Football Association",
                "startDate": "1924",
                "endDate": "1926",
                "jobTitle": "Vice Chairman"
            },
            {
                "@type": "Organization",
                "name": "Olofsfors Sports Club",
                "startDate": "1930",
                "jobTitle": "Chairman"
            }
        ],
        "awards": [
            {
                "@type": "Organization",
                "name": "National Sports Association"
            },
            {
                "@type": "Organization",
                "name": "Västerbotten Football Association"
            },
            {
                "@type": "Organization",
                "name": "Swedish Merchants' Association"
            },
            {
                "@type": "Organization",
                "name": "Hörnefors Sports Club"
            }
        ],
        "hobbies": "Sports, journalism"
    },
    "occupations": {
        "career": [
            {
                "occupational_title": "Merchant",
                "workplace": "Olofsfors Bruks-handel",
                "industry": "Ironworks trade",
                "start_date": "1926"
            },
            {
                "occupational_title": "Chairman",
                "workplace": "Nordmalings Köpm.frb",
                "industry": "Merchants Association",
                "start_date": "1928"
            },
            {
                "occupational_title": "Chairman",
                "workplace": "Västerb Södra Köpm.frb",
                "industry": "Merchants Association",
                "start_date": "1934"
            },
            {
                "occupational_title": "Member",
                "workplace": "Umeå Engrossistfrn :s o Köpm.förbundets Samarbetsnämnd",
                "industry": "Wholesale Merchants Association",
                "start_date": "1934"
            },
            {
                "occupational_title": "Member",
                "workplace": "Sv Köpm.frb",
                "industry": "Merchants Association",
                "start_date": "1936"
            },
            {
                "occupational_title": "Member",
                "workplace": "Sv Speceri- &amp; Livsm.-handl.frb",
                "industry": "Grocery and Food Trade Association",
                "start_date": "1935"
            },
            {
                "occupational_title": "Member",
                "workplace": "Sv Köpm.frbs arbets-utsk",
                "industry": "Merchants Association",
                "start_date": "1941"
            },
            {
                "occupational_title": "Member",
                "workplace": "Sv Köpm.frbs propagandaråd",
                "industry": "Merchants Association",
                "start_date": "1942"
            },
            {
                "occupational_title": "Administrator",
                "workplace": "ackordsförhandl utan konkurs",
                "industry": "Bankruptcy reconciliation",
                "start_date": "1936"
            },
            {
                "occupational_title": "Member",
                "workplace": "Stiftelsen Solstickans .Väs-terb.krets",
                "industry": "Non-profit organization",
                "start_date": "1938"
            },
            {
                "occupational_title": "Member",
                "workplace": "Västerb kristidsstyr",
                "industry": "Crisis management",
                "start_date": "1939"
            },
            {
                "occupational_title": "Member",
                "workplace": "Hörnefors Nya Handels AB",
                "industry": "New Trading Company",
                "start_date": "1921"
            },
            {
                "occupational_title": "Member",
                "workplace": "AB Svenska Handelsbankens avd.kontor i Nordmaling",
                "industry": "Swedish Handelsbanken",
                "start_date": "1944"
            },
            {
                "occupational_title": "Chairman",
                "workplace": "Hörnefors Idr.frn",
                "industry": "Sports Club",
                "start_date": "1922"
            },
            {
                "occupational_title": "Vice Chairman",
                "workplace": "Västerb Fotbollsfrb",
                "industry": "Football Association",
                "start_date": "1924"
            },
            {
                "occupational_title": "Chairman",
                "workplace": "Västerb Fotbollsfrb",
                "industry": "Football Association",
                "start_date": "1924"
            },
            {
                "occupational_title": "Chairman",
                "workplace": "Olofsfors Idr.-klubb",
                "industry": "Sports Club",
                "start_date": "1930"
            },
            {
                "occupational_title": "Editorial Writer",
                "workplace": "Västerbottens Köpmannatidning",
                "industry": "Journalism",
                "start_date": "1934"
            }
        ]
    }
}