{
    "original": "HOLMBLAD, David Gideon Anders, Grosshandlare, Stockholm, f Gudhem, Skarab l, 17/7 74 av skollär A H o Sofia Winqvist, gm Dagny Holmquist. Falkps l a 1. Anst i det.hdl Falkp 89—96, i engrosaff Sthlm 97—99, i Tyskl o Engl 99—01, intr i Fma Nilsson &amp; Lindström 01, ag av denna sed. 05. Ordf Sthlms Manuf.hdl.frn 16—30, Sthlms Hdlsmellansk 18—40; styr.led Sv Köpmfrb 18—28; flm Sthlms hdlskainm sed. 16; stdsflm 29—30; led dir f Danviks hem sed. 35. RNO, RVO.",
    "translated": "HOLMBLAD, David Gideon Anders, Merchant, Stockholm, born in Gudhem, Skaraborg county, July 17, 1874, son of schoolteacher A.H. and Sofia Winqvist, married to Dagny Holmquist. \nWorked in the trading company Falköping from 1889-1896, in wholesale trade in Stockholm from 1897-1899, in Germany and England from 1899-1901, joined Firma Nilsson & Lindström in 1901 and became managing director in 1905. Chairman of Stockholm Manufacturers' Trade Association from 1916-1930, Stockholm Commercial Middlemen Association from 1918-1940. Board member of the Swedish Merchants Association from 1918-1928. Member of the board of Stockholm Trade Chamber since 1916. Governor of Stockholm Trade School starting in 1929. Board member of Danviks hem since 1935. Awarded with RNO (Order of the North Star), RVO (Order of Vasa).",
    "structured": {
        "@context": "https://schema.org/",
        "@type": "Person",
        "name": "David Gideon Anders Holmblad",
        "jobTitle": "Merchant",
        "birthPlace": "Gudhem, Skaraborg county",
        "birthDate": "1874-07-17",
        "parents": [
            {
                "@type": "Person",
                "name": "A.H.",
                "jobTitle": "Schoolteacher"
            },
            {
                "@type": "Person",
                "name": "Sofia Winqvist"
            }
        ],
        "spouse": {
            "@type": "Person",
            "name": "Dagny Holmquist"
        },
        "memberOf": [
            {
                "@type": "Organization",
                "name": "Firma Nilsson & Lindström",
                "startDate": "1901"
            },
            {
                "@type": "Organization",
                "name": "Stockholm Manufacturers' Trade Association",
                "startDate": "1916",
                "endDate": "1930"
            },
            {
                "@type": "Organization",
                "name": "Stockholm Commercial Middlemen Association",
                "startDate": "1918",
                "endDate": "1940"
            },
            {
                "@type": "Organization",
                "name": "Swedish Merchants Association",
                "startDate": "1918",
                "endDate": "1928"
            },
            {
                "@type": "Organization",
                "name": "Stockholm Trade Chamber",
                "startDate": "1916"
            },
            {
                "@type": "Organization",
                "name": "Danviks hem",
                "startDate": "1935"
            }
        ],
        "workExperience": [
            {
                "@type": "Organization",
                "name": "Falköping",
                "startDate": "1889",
                "endDate": "1896"
            },
            {
                "@type": "Organization",
                "name": "Wholesale trade in Stockholm",
                "startDate": "1897",
                "endDate": "1899"
            },
            {
                "@type": "Organization",
                "name": "Germany and England",
                "startDate": "1899",
                "endDate": "1901"
            }
        ],
        "honorificPrefix": "RNO, RVO",
        "education": [
            {
                "@type": "Organization",
                "name": "Stockholm Trade School",
                "startDate": "1929"
            }
        ]
    },
    "occupations": {
        "career": [
            {
                "occupational_title": "Merchant",
                "workplace": "Falköping Trading Company",
                "industry": "Trading",
                "start_date": "1889"
            },
            {
                "occupational_title": "Merchant",
                "workplace": "Wholesale trade in Stockholm",
                "industry": "Trading",
                "start_date": "1897"
            },
            {
                "occupational_title": "Merchant",
                "workplace": "Germany and England",
                "industry": "Trading",
                "start_date": "1899"
            },
            {
                "occupational_title": "Managing Director",
                "workplace": "Firma Nilsson & Lindström",
                "industry": "Trading",
                "start_date": "1905"
            }
        ]
    }
}