{
    "original": "KÖNSBERG, Nils Allan, Konsul, Malmö, f Törnevalla, östergötl, 13/3 78, gm Martha 291 KÖRDEI* Lauenstein. Eft slut skolgång o prakt i järn-varubranschen anst ss reseomb i AB Sv Metallverken i Västerås 09, chef f bolagets Mal-mö-kont 14—43. Finsk konsul sed. 19. Har verksamt bidragit till tillk av Frostavallen. RNO, RVO, FinlFrK, FinlVROlkl, ProPstGM, Skidfrämj JM. Hobbies: Friluftsliv, skidlöpning.",
    "translated": "KÖNSBERG, Nils Allan, Consul, Malmö, born in Törnevalla, östergötl, on March 13, 1878, married Martha in 1891 in Lauenstein. After completing his education and gaining practical experience in the iron and hardware industry, he was employed as a traveling salesman for AB Sv Metallverken in Västerås in 1909. He became the head of the company's Malmö office from 1914 to 1943. He served as the Finnish Consul since 1919. He significantly contributed to the development of Frostavallen. He received the Royal Norwegian Order of St. Olav, the Royal Swedish Order of Vasa, the Finnish Order of the White Rose, the Finnish Order of the Cross of Liberty, the Provincial Grand Master of Freemasonry, and was a Promotion member of Skidfrämjande JM (a skiing organization). Hobbies: Outdoor life, skiing.",
    "structured": {
        "@context": "https://schema.org",
        "@type": "Person",
        "name": "Nils Allan Könsberg",
        "jobTitle": "Consul",
        "address": {
            "@type": "PostalAddress",
            "addressLocality": "Malmö"
        },
        "birthDate": "1878-03-13",
        "birthPlace": "Törnevalla, östergötl",
        "spouse": {
            "@type": "Person",
            "name": "Martha",
            "marriageDate": "1891"
        },
        "education": "Completed his education",
        "workExperience": {
            "@type": "OrganizationRole",
            "startDate": "1909",
            "endDate": "1943",
            "roleName": "Traveling Salesman",
            "namedPosition": "AB Sv Metallverken",
            "baseSalary": "Västerås"
        },
        "memberships": [
            {
                "@type": "Organization",
                "name": "Provincial Grand Master of Freemasonry"
            },
            {
                "@type": "Organization",
                "name": "Skidfrämjande JM"
            }
        ],
        "nationality": "Swedish",
        "hasOccupation": "Consul",
        "awards": [
            {
                "@type": "Order",
                "name": "Royal Norwegian Order of St. Olav"
            },
            {
                "@type": "Order",
                "name": "Royal Swedish Order of Vasa"
            },
            {
                "@type": "Order",
                "name": "Finnish Order of the White Rose"
            },
            {
                "@type": "Order",
                "name": "Finnish Order of the Cross of Liberty"
            }
        ],
        "contributions": "Significantly contributed to the development of Frostavallen",
        "hobbies": [
            "Outdoor life",
            "Skiing"
        ]
    },
    "occupations": {
        "career": [
            {
                "occupational_title": "Traveling Salesman",
                "workplace": "AB Sv Metallverken",
                "industry": "Iron and Hardware",
                "start_date": "1909"
            },
            {
                "occupational_title": "Head of Malmö Office",
                "workplace": "AB Sv Metallverken",
                "industry": "Iron and Hardware",
                "start_date": "1914"
            }
        ]
    }
}