{
    "original": "BECKIUS, Ivar Axel Hugo, Civilingenjör, Västerås, f Kungs-Barkarö, Västml l, 20/3 95 av lantbr A Andersson o Carolina Nilsson, gm Ragna Zesch. Ex tekn elem.sk Malmö 14, KTH (E) 15—19. Lab.ing ASEA Ludvika 20—21, led f ASEA:s maskinlab.avd Västerås 21—23, transformatorkonstr v General Electric Co Pittsfield Mäss USA 23—25, konstr f kraft-stnsbygge v Thomas A Murray Inc New York USA 25, konstr o beräkn.ing f transformatorer h ASEA Ludv 25—27, ch f transformator -beräkn v ASEA Electric Ltd Walthamstow Engl 27—31, ASEA Ludv 31—37, tekn ch v ASEA Electric Ltd Walthamstow Works 37— 40, ASEA:s tranformatoravd Ludv o Västerås samt anläggn.avd :s utredn.byrå Västerås sed. 40. Resor: Tyskl, USA, Canada 24, Engl, Frankr 29 o 30, Danm. Led Sv Tekn.frn, Ass Member Inst Electr Eng Great Britain, led Sv Ing.sällsk i Stor britt mfl. Dalarnas DM i tennis 33. Skidl.m g. Hobbies: Tennis, skidor, skridskor, fiske.",
    "translated": "BECKIUS, Ivar Axel Hugo, Civil Engineer, Västerås, born in Kungs-Barkarö, Västmanland county, on March 20, 1895, son of farmer A Andersson and Carolina Nilsson, married to Ragna Zesch. Formerly employed as a technical draftsman in Malmö in 1914, studied at the Royal Institute of Technology (Electrical Engineering) from 1915 to 1919. Worked as a laboratory engineer at ASEA Ludvika from 1920 to 1921, then became the head of ASEA's machine laboratory department in Västerås from 1921 to 1923. Worked as a transformer designer at General Electric Co in Pittsfield, Massachusetts, USA from 1923 to 1925, and worked in power station construction design at Thomas A Murray Inc in New York, USA in 1925. From 1925 to 1927, worked as a designer and estimator of transformers at ASEA Ludvika. From 1927 to 1931, served as chief of transformer calculation at ASEA Electric Ltd in Walthamstow, England. Returned to ASEA Ludvika in 1931 where he continued to work until 1937. From 1937 to 1940, worked as a technical chief at ASEA Electric Ltd Walthamstow Works. Afterwards, he worked in ASEA's transformer division in Ludvika and Västerås, as well as in the plant's investigative department in Västerås since 1940. Traveled to Germany, the USA, and Canada in 1924, to England and France in 1929 and 1930, and to Denmark. Member of the Swedish Association of Engineers, Associate Member of the Institution of Electrical Engineers in Great Britain, and member of the Swedish Engineering Society in Great Britain, among others. Winner of the Dalarna Tennis District Championship in 1933. Interests and hobbies include tennis, skiing, ice-skating, and fishing.",
    "structured": {
        "@context": "http://schema.org",
        "@type": "Person",
        "name": "Ivar Axel Hugo Beckius",
        "birthDate": "1895-03-20",
        "birthPlace": "Kungs-Barkarö, Västmanland County, Sweden",
        "description": "Civil Engineer",
        "nationality": "Swedish",
        "spouse": {
            "@type": "Person",
            "name": "Ragna Zesch"
        },
        "parent": [
            {
                "@type": "Person",
                "name": "A Andersson",
                "description": "Father"
            },
            {
                "@type": "Person",
                "name": "Carolina Nilsson",
                "description": "Mother"
            }
        ],
        "education": [
            {
                "@type": "EducationalOrganization",
                "name": "Royal Institute of Technology",
                "location": "Stockholm, Sweden",
                "startDate": "1915",
                "endDate": "1919"
            }
        ],
        "employmentHistory": [
            {
                "@type": "Organization",
                "name": "Technical draftsman",
                "description": "Malmö",
                "startDate": "1914",
                "endDate": "1914"
            },
            {
                "@type": "Organization",
                "name": "ASEA Ludvika",
                "description": "Laboratory Engineer",
                "startDate": "1920",
                "endDate": "1921"
            },
            {
                "@type": "Organization",
                "name": "ASEA Västerås",
                "description": "Head of Machine Laboratory Department",
                "startDate": "1921",
                "endDate": "1923"
            },
            {
                "@type": "Organization",
                "name": "General Electric Co",
                "description": "Transformer Designer",
                "location": "Pittsfield, Massachusetts, USA",
                "startDate": "1923",
                "endDate": "1925"
            },
            {
                "@type": "Organization",
                "name": "Thomas A Murray Inc",
                "description": "Power Station Construction Design",
                "location": "New York, USA",
                "startDate": "1925",
                "endDate": "1925"
            },
            {
                "@type": "Organization",
                "name": "ASEA Ludvika",
                "description": "Designer and Estimator of Transformers",
                "startDate": "1925",
                "endDate": "1927"
            },
            {
                "@type": "Organization",
                "name": "ASEA Electric Ltd",
                "description": "Chief of Transformer Calculation",
                "location": "Walthamstow, England",
                "startDate": "1927",
                "endDate": "1931"
            },
            {
                "@type": "Organization",
                "name": "ASEA Ludvika",
                "description": "Technical Chief",
                "startDate": "1931",
                "endDate": "1937"
            },
            {
                "@type": "Organization",
                "name": "ASEA Electric Ltd",
                "description": "Technical Chief",
                "location": "Walthamstow, England",
                "startDate": "1937",
                "endDate": "1940"
            },
            {
                "@type": "Organization",
                "name": "ASEA Västerås",
                "description": "Transformer Division",
                "startDate": "1940",
                "endDate": "present"
            }
        ],
        "travelHistory": [
            {
                "@type": "Place",
                "name": "Germany",
                "description": "Visited in 1924"
            },
            {
                "@type": "Place",
                "name": "USA",
                "description": "Visited in 1924"
            },
            {
                "@type": "Place",
                "name": "Canada",
                "description": "Visited in 1924"
            },
            {
                "@type": "Place",
                "name": "England",
                "description": "Visited in 1929, 1930"
            },
            {
                "@type": "Place",
                "name": "France",
                "description": "Visited in 1929, 1930"
            },
            {
                "@type": "Place",
                "name": "Denmark",
                "description": "Visited"
            }
        ],
        "memberOf": [
            {
                "@type": "Organization",
                "name": "Swedish Association of Engineers"
            },
            {
                "@type": "Organization",
                "name": "Institution of Electrical Engineers",
                "location": "Great Britain",
                "description": "Associate Member"
            },
            {
                "@type": "Organization",
                "name": "Swedish Engineering Society",
                "location": "Great Britain"
            }
        ],
        "award": {
            "@type": "SportsEvent",
            "name": "Dalarna Tennis District Championship",
            "description": "Winner in 1933"
        },
        "interests": "Tennis, Skiing, Ice-skating, Fishing"
    },
    "occupations": {
        "career": [
            {
                "occupational_title": "Technical Draftsman",
                "workplace": "Malmö",
                "industry": "Unknown",
                "start_date": "1914"
            },
            {
                "occupational_title": "Laboratory Engineer",
                "workplace": "ASEA Ludvika",
                "industry": "Unknown",
                "start_date": "1920"
            },
            {
                "occupational_title": "Head of ASEA's Machine Laboratory Department",
                "workplace": "Västerås",
                "industry": "Unknown",
                "start_date": "1921"
            },
            {
                "occupational_title": "Transformer Designer",
                "workplace": "General Electric Co",
                "industry": "Electrical",
                "start_date": "1923"
            },
            {
                "occupational_title": "Power Station Construction Designer",
                "workplace": "Thomas A Murray Inc",
                "industry": "Construction",
                "start_date": "1925"
            },
            {
                "occupational_title": "Designer and Estimator of Transformers",
                "workplace": "ASEA Ludvika",
                "industry": "Electrical",
                "start_date": "1925"
            },
            {
                "occupational_title": "Chief of Transformer Calculation",
                "workplace": "ASEA Electric Ltd",
                "industry": "Electrical",
                "start_date": "1927"
            },
            {
                "occupational_title": "Technical Chief",
                "workplace": "ASEA Electric Ltd Walthamstow Works",
                "industry": "Electrical",
                "start_date": "1937"
            },
            {
                "occupational_title": "Transformer Division",
                "workplace": "ASEA",
                "industry": "Electrical",
                "start_date": "1940"
            },
            {
                "occupational_title": "Investigative Department",
                "workplace": "ASEA",
                "industry": "Electrical",
                "start_date": "1940"
            }
        ]
    }
}