{
    "original": "JANSSON, Gustav, Förvaltare, Skoghall, f Gävle 23/12 82 av faktor And J o Margareta Berglund, gm Anna Nyström. Eft slut skolstud anst ss bgkh v Härnäs Bruk, insp v Söderfors Br AB :s brädg- o skeppn.avd o ch f Th Olrogs trävaruskeppn 03, förv v Vifsta-varvs sågvk, hyvl o brädg 07, v Kramfors AB 12, pl.chef v Skoghalls sågvk o bruksförvaltn sed. 19. Komm.flm, led av skol.styr, hälsov.nmd, kristidsnmd, länsprövn.nmd, ordf i Hammarö byggn.nmd, Mellansysslets vägst o ktén f uppf av pensionärshem; styr.led i Karlstads sparbk, vkst led av Hammarö vat-tenvksstyr, v. ordf i Värml l brandkårsfrb o ch f Skoghallsvkns brandkår, förvalt f egnahemsverksamheten. RVO.",
    "translated": "JANSSON, Gustav, Administrator, Skoghall, born in Gävle on December 23rd, 1882, son of factor And J and Margareta Berglund, married to Anna Nyström. After completing school, he was employed at Härnäs Bruk, worked as an inspector at Söderfors Br AB's timber and shipbuilding department, and then at Th Olrog's timber shipping in 1903. He became the administrator of Vifsta varv's sawmill, planing mill, and timber yard in 1907, and later worked at Kramfors AB in 1912. He became the plant manager at Skoghall's sawmill and industrial administration in 1919. He served as a municipal council member and was a member of the school board, health committee, wartime committee, county evaluation committee, and chairman of the Hammarö building committee. He also served on the board of directors of Karlstad savings bank, was a development director at Hammarö water management committee, vice chairman of the Värmland firefighters' association, and the leader of Skoghall firefighters. He managed the company's own-home business. Received the Order of Vasa.",
    "structured": {
        "@context": "https://schema.org",
        "@type": "Person",
        "name": "Gustav Jansson",
        "birthDate": "1882-12-23",
        "birthPlace": "Gävle",
        "parent": [
            {
                "@type": "Person",
                "name": "And Jansson",
                "jobTitle": "Factor"
            },
            {
                "@type": "Person",
                "name": "Margareta Berglund"
            }
        ],
        "spouse": {
            "@type": "Person",
            "name": "Anna Nyström"
        },
        "description": "Administrator at Skoghall",
        "education": "Completed school",
        "employmentHistory": [
            {
                "@type": "OrganizationRole",
                "startDate": "after school",
                "endDate": "Not provided",
                "roleName": "Employed at Härnäs Bruk"
            },
            {
                "@type": "OrganizationRole",
                "startDate": "Not provided",
                "endDate": "Not provided",
                "roleName": "Inspector at Söderfors Br AB's timber and shipbuilding department"
            },
            {
                "@type": "OrganizationRole",
                "startDate": "1903",
                "endDate": "Not provided",
                "roleName": "Th Olrog's timber shipping"
            },
            {
                "@type": "OrganizationRole",
                "startDate": "1907",
                "endDate": "Not provided",
                "roleName": "Administrator at Vifsta varv's sawmill, planing mill, and timber yard"
            },
            {
                "@type": "OrganizationRole",
                "startDate": "1912",
                "endDate": "Not provided",
                "roleName": "Worked at Kramfors AB"
            },
            {
                "@type": "OrganizationRole",
                "startDate": "1919",
                "endDate": "Not provided",
                "roleName": "Plant manager at Skoghall's sawmill and industrial administration"
            }
        ],
        "memberOf": [
            {
                "@type": "Organization",
                "name": "Municipal Council"
            },
            {
                "@type": "Organization",
                "name": "School Board"
            },
            {
                "@type": "Organization",
                "name": "Health Committee"
            },
            {
                "@type": "Organization",
                "name": "Wartime Committee"
            },
            {
                "@type": "Organization",
                "name": "County Evaluation Committee"
            },
            {
                "@type": "Organization",
                "name": "Hammarö Building Committee",
                "roleName": "Chairman"
            }
        ],
        "boardMember": [
            {
                "@type": "Organization",
                "name": "Karlstad Savings Bank"
            },
            {
                "@type": "Organization",
                "name": "Hammarö Water Management Committee",
                "roleName": "Development Director"
            },
            {
                "@type": "Organization",
                "name": "Värmland Firefighters' Association",
                "roleName": "Vice Chairman"
            },
            {
                "@type": "Organization",
                "name": "Skoghall Firefighters",
                "roleName": "Leader"
            }
        ],
        "workLocation": {
            "@type": "Place",
            "name": "Skoghall"
        },
        "achievements": "Received the Order of Vasa"
    },
    "occupations": {
        "career": [
            {
                "occupational_title": "Administrator",
                "workplace": "Skoghall",
                "industry": "Industrial administration",
                "start_date": "1919"
            },
            {
                "occupational_title": "Inspector",
                "workplace": "Söderfors Br AB - Timber and shipbuilding department",
                "industry": "Timber and shipbuilding",
                "start_date": "Unknown"
            },
            {
                "occupational_title": "Timber Shipping",
                "workplace": "Th Olrogs timber shipping",
                "industry": "Timber shipping",
                "start_date": "1903"
            },
            {
                "occupational_title": "Administrator",
                "workplace": "Vifsta varv - Sawmill, Planing mill, and Timber yard",
                "industry": "Sawmill",
                "start_date": "1907"
            },
            {
                "occupational_title": "Administrator",
                "workplace": "Kramfors AB",
                "industry": "Unknown",
                "start_date": "1912"
            },
            {
                "occupational_title": "Unknown",
                "workplace": "Härnäs Bruk",
                "industry": "Unknown",
                "start_date": "Unknown"
            }
        ]
    }
}