{
    "original": "LENANDER, Nils Erik, Disponent, Stockholm, f Västervik 16/4 83 av köpm C E L o Amalia Nordfeldt, gm Minken Torp. Studex Linkp 01, Upps univ 01—05, tillf elev Bergs-högsk 05—06. Anst Imbatem Goldfield, Ashanti, Afr, 06, disp AB Ryllshytte Zink- o Blygruv 10—12, gruving o övering Orkla Grube AB Norge 07—10, disp 12—22, vkst dir 22—38, styr.ordf o ag AB Industrimetoder sed. 38. Styr.ordf AB Smålands Taberg, styr.led Sv Diamantbergborrn.AB. Mer ell mindre årl res Tyskl, Frankr, Holl, Belg, Engl, Irland, Span, Port, Ital, USA 12—39. KVO2kl, KNS :tOO. Hobbies: Golf, jakt, fiske.",
    "translated": "LENANDER, Nils Erik, Manager, Stockholm, b. Västervik 16/4 1883 to merchant C E L and Amalia Nordfeldt, m. Minken Torp. Studied at Linköping University 1901, Uppsala University 1901-1905, temporary student at Berg School of Mining 1905-1906. Employed at Imbatem Goldfield, Ashanti, Africa in 1906, manager at AB Ryllshytte Zinc and Lead Mine 1910-1912, mining and supervisory position at Orkla Grube AB, Norway 1907-1910, manager 1912-1922, director of growth 1922-1938, chairman and managing director of AB Industrimetoder since 1938. Chairman of the board of AB Smålands Taberg, board member of Swedish Diamond Drilling Company AB. More or less yearly trips to Germany, France, the Netherlands, Belgium, England, Ireland, Spain, Portugal, Italy, and the USA 1912-1939. Knight of the Royal Order of the Polar Star - Second Class, Member of the Royal Swedish Yacht Club. Hobbies: Golf, hunting, fishing.",
    "structured": {
        "@context": "https://schema.org",
        "@type": "Person",
        "name": "Nils Erik Lenander",
        "jobTitle": "Manager",
        "birthDate": "1883-04-16",
        "birthPlace": "Västervik",
        "address": {
            "@type": "PostalAddress",
            "addressLocality": "Stockholm"
        },
        "parents": [
            {
                "@type": "Person",
                "name": "C E L"
            },
            {
                "@type": "Person",
                "name": "Amalia Nordfeldt"
            }
        ],
        "spouse": {
            "@type": "Person",
            "name": "Minken Torp"
        },
        "education": [
            {
                "@type": "EducationalOrganization",
                "name": "Linköping University",
                "startDate": "1901",
                "endDate": "1901"
            },
            {
                "@type": "EducationalOrganization",
                "name": "Uppsala University",
                "startDate": "1901",
                "endDate": "1905"
            },
            {
                "@type": "EducationalOrganization",
                "name": "Berg School of Mining",
                "startDate": "1905",
                "endDate": "1906"
            }
        ],
        "employmentHistory": [
            {
                "@type": "Organization",
                "name": "Imbatem Goldfield"
            },
            {
                "@type": "Organization",
                "name": "AB Ryllshytte Zink- o Blygruv",
                "startDate": "1910",
                "endDate": "1912"
            },
            {
                "@type": "Organization",
                "name": "Orkla Grube AB",
                "startDate": "1907",
                "endDate": "1910"
            },
            {
                "@type": "Organization",
                "name": "AB Industrimetoder",
                "startDate": "1938"
            }
        ],
        "positions": [
            {
                "@type": "Role",
                "title": "Manager",
                "startDate": "1912",
                "endDate": "1922"
            },
            {
                "@type": "Role",
                "title": "Director of Growth",
                "startDate": "1922",
                "endDate": "1938"
            }
        ],
        "honorificPrefix": "Knight",
        "memberOf": [
            {
                "@type": "Organization",
                "name": "Royal Order of the Polar Star",
                "honorificSuffix": "Second Class"
            },
            {
                "@type": "Organization",
                "name": "Royal Swedish Yacht Club"
            }
        ],
        "hobbies": [
            "Golf",
            "Hunting",
            "Fishing"
        ],
        "nationality": "Swedish"
    },
    "occupations": {
        "career": [
            {
                "occupational_title": "Disponent",
                "workplace": "Stockholm",
                "industry": "",
                "start_date": ""
            },
            {
                "occupational_title": "Employee at Imbatem Goldfield",
                "workplace": "Ashanti, Africa",
                "industry": "",
                "start_date": "1906"
            },
            {
                "occupational_title": "Manager at AB Ryllshytte Zink- o Blygruv",
                "workplace": "",
                "industry": "",
                "start_date": "1910"
            },
            {
                "occupational_title": "Mining and supervisory position at Orkla Grube AB",
                "workplace": "Norway",
                "industry": "",
                "start_date": "1907"
            },
            {
                "occupational_title": "Manager at Orkla Grube AB",
                "workplace": "",
                "industry": "",
                "start_date": "1912"
            },
            {
                "occupational_title": "Director of growth at Orkla Grube AB",
                "workplace": "",
                "industry": "",
                "start_date": "1922"
            },
            {
                "occupational_title": "Chairman and managing director of AB Industrimetoder",
                "workplace": "",
                "industry": "",
                "start_date": "1938"
            }
        ]
    }
}