{
    "original": "CLIFFORD, Lennart Stig Janne Artur, Direktör, Hindås, f Hbg 13/4 07 av sjökapt J C C o Augusta Andersson, gm Ingrid Westerberg.\" Hbgs hal, hdlsgymn. Kontorist i Skånska Lantmännens Centralfrn i Hbg 25— 26, försälj o resande f fma Fredrik Lindahl 1 Gbg 27, repres f Berg &amp; Co Mek Verkst i Ullersäter 28, f AB Lindholmen-Motala i Gbg 29—31, grund eg fma i kontorsmtrl o papper engros, fma L Clifford, 32, ombild t L Clifford &amp; Co AB 34, bolagets vkst dir o styr.ordf. Styr.led i Sv Kontorsvarufmors Köpm.frn i Sthlm. Resor: Engl 28, Tyskl o Danm 30. Hobby: Smalfilmning.",
    "translated": "CLIFFORD, Lennart Stig Janne Artur, Director, Hindås, born in Helsingborg on April 13, 1907, son of Captain J.C.C and Augusta Andersson, married to Ingrid Westerberg. Completed half of the upper secondary school in Helsingborg. Worked as a clerk at Skånska Lantmännens Centralfrn in Helsingborg from 1925 to 1926, then worked in sales and as a traveling representative for Fredrik Lindahl in Gothenburg in 1927. Represented Berg & Co Mek Verkst in Ullersäter in 1928. Employed at AB Lindholmen-Motala in Gothenburg from 1929 to 1931. Founded his own business in wholesale office supplies and paper in 1932, named L Clifford. The business was reorganized as L Clifford & Co AB in 1934, in which he became the company's Managing Director and Chairman of the Board. Also served on the Board of Directors for Sv Kontorsvarufmors Köpm.frn in Stockholm. Traveled to England in 1928, Germany and Denmark in 1930. Hobby: Filmmaking.",
    "structured": {
        "@context": "http://schema.org",
        "@type": "Person",
        "name": "Lennart Stig Janne Artur Clifford",
        "birthDate": "1907-04-13",
        "birthPlace": "Helsingborg",
        "father": {
            "@type": "Person",
            "name": "J.C.C"
        },
        "mother": {
            "@type": "Person",
            "name": "Augusta Andersson"
        },
        "spouse": {
            "@type": "Person",
            "name": "Ingrid Westerberg"
        },
        "jobTitle": "Director",
        "address": {
            "@type": "PostalAddress",
            "addressLocality": "Hindås"
        },
        "education": [
            {
                "@type": "EducationalOccupationalCredential",
                "educationLevel": "Upper secondary school",
                "educationalRole": "Half"
            }
        ],
        "work": [
            {
                "@type": "Organization",
                "startDate": "1925",
                "endDate": "1926",
                "name": "Skånska Lantmännens Centralfrn",
                "description": "Clerk"
            },
            {
                "@type": "Organization",
                "startDate": "1927",
                "endDate": "1927",
                "name": "Fredrik Lindahl",
                "description": "Sales and Traveling Representative"
            },
            {
                "@type": "Organization",
                "startDate": "1928",
                "endDate": "1928",
                "name": "Berg & Co Mek Verkst",
                "description": "Representative"
            },
            {
                "@type": "Organization",
                "startDate": "1929",
                "endDate": "1931",
                "name": "AB Lindholmen-Motala",
                "description": "Employee"
            },
            {
                "@type": "Organization",
                "startDate": "1932",
                "endDate": "present",
                "name": "L Clifford",
                "description": "Founder"
            },
            {
                "@type": "Organization",
                "startDate": "1934",
                "endDate": "present",
                "name": "L Clifford & Co AB",
                "description": "Managing Director and Chairman of the Board"
            },
            {
                "@type": "Organization",
                "name": "Sv Kontorsvarufmors Köpm.frn",
                "description": "Board of Directors"
            }
        ],
        "nationality": "Swedish",
        "hobby": "Filmmaking",
        "memberOf": {
            "@type": "Country",
            "name": "Sweden"
        },
        "travel": [
            {
                "@type": "Trip",
                "name": "England",
                "startDate": "1928",
                "endDate": "1928"
            },
            {
                "@type": "Trip",
                "name": "Germany",
                "startDate": "1930",
                "endDate": "1930"
            },
            {
                "@type": "Trip",
                "name": "Denmark",
                "startDate": "1930",
                "endDate": "1930"
            }
        ]
    },
    "occupations": {
        "career": [
            {
                "occupational_title": "Clerk",
                "workplace": "Skånska Lantmännens Centralfrn",
                "industry": "Agriculture",
                "start_date": "1925"
            },
            {
                "occupational_title": "Sales representative",
                "workplace": "Fredrik Lindahl",
                "industry": "Sales",
                "start_date": "1927"
            },
            {
                "occupational_title": "Representative",
                "workplace": "Berg & Co Mek Verkst",
                "industry": "Mechanical Engineering",
                "start_date": "1928"
            },
            {
                "occupational_title": "Employee",
                "workplace": "AB Lindholmen-Motala",
                "industry": "Engineering",
                "start_date": "1929"
            },
            {
                "occupational_title": "Founder",
                "workplace": "L Clifford",
                "industry": "Wholesale",
                "start_date": "1932"
            },
            {
                "occupational_title": "Managing Director and Chairman of the Board",
                "workplace": "L Clifford & Co AB",
                "industry": "Wholesale",
                "start_date": "1934"
            }
        ]
    }
}