{
    "original": "EKLUND, Karl Gustaf, Konsulterande Ingenjör för värmeledn-, ventilations- o sanitets-tekn anläggn, Storängen, f Sthlm 1/2 87 av handl A Th E o Wilhelmina Fältström, gm Ester Lindbohm. Ex Tekn sk Sthlm (maskin) 07. Anst Sthlms Allm Tel AB 01—03, prakt E J Petterssons smides- &amp; mek verkst 03—04, rit h AB P A Sjögren Sthlm 07—09, konstr William Anderssons konstr.byrå 09—19; eg fma Karl G Eklunds Ing.byrå sed. 19, AB 41. Konstruktioner f bl a. Grand Hotell Sthlm 25, i Engl 29, Citypalatset Sthlm 32, HSB-husen Kungsklippan 34, Sjöhist Mus 34, Thulehuset Sthlm 41, Riksdagshuset 41, St Eriks sjukh 41, ett flert större arb för Byggnadsstyr o Sthlms stad mfl. Resor: Engl, Tyskl, Frankr, Ital 31—35; USA 37. Av trycket: Upps i »Tidskr f värme- o sanitetsteknik», »Byggmäst» mfl. Led av Sv Tekn.frn, Americ Soc of Heating and Ventilating Engin, Sv Kons Värme o Sanitetsing frn. Timmerman. Hobby: Segling.",
    "translated": "EKLUND, Karl Gustaf, Consulting Engineer for heat conduction, ventilation and sanitary technology systems, Storängen, born in Stockholm on February 1, 1887, son of merchant A Th E and Wilhelmina Fältström, married to Ester Lindbohm. Former student at the Technical School of Stockholm (mechanical engineering) 1907. Employed at Stockholm General Telephone Company 1901-1903, apprentice at E J Pettersson's forge and mechanical workshop 1903-1904, draftsman at AB P A Sjögren Stockholm 1907-1909, designer at William Andersson's design office 1909-1919. Owner of Eklund Engineering Office since 1919, and AB since 1941. Designed constructions such as the Grand Hotel Stockholm 1925, in England 1929, City Palace Stockholm 1932, HSB buildings Kungsklippan 1934, Maritime Museum 1934, Thule House Stockholm 1941, Parliament House 1941, St. Erik's Hospital 1941, several major projects for Building Board and the City of Stockholm, among others. Traveled to England. Germany, France, Italy 1931-1935; USA 1937. Published in \"Journal of Heat and Sanitary Engineering,\" \"Master Builder\" and others. Member of the Swedish Society of Engineers, American Society of Heating and Ventilating Engineers, Swedish Consulting Engineers for Heating and Sanitation. Carpenter. Hobby: Sailing.",
    "structured": {
        "@context": "https://schema.org",
        "@type": "Person",
        "name": "Karl Gustaf Eklund",
        "birthDate": "1887-02-01",
        "birthPlace": "Stockholm",
        "nationality": "Swedish",
        "occupation": "Consulting Engineer",
        "worksFor": "Eklund Engineering Office",
        "education": {
            "@type": "EducationalOccupationalCredential",
            "name": "Technical School of Stockholm"
        },
        "parents": [
            {
                "@type": "Person",
                "name": "A Th E",
                "occupation": "Merchant"
            },
            {
                "@type": "Person",
                "name": "Wilhelmina Fältström"
            }
        ],
        "spouse": {
            "@type": "Person",
            "name": "Ester Lindbohm"
        },
        "employmentHistory": [
            {
                "@type": "OrganizationRole",
                "organization": {
                    "@type": "Organization",
                    "name": "Stockholm General Telephone Company"
                },
                "startDate": "1901",
                "endDate": "1903"
            },
            {
                "@type": "OrganizationRole",
                "title": "Apprentice",
                "startDate": "1903",
                "endDate": "1904",
                "employer": {
                    "@type": "Organization",
                    "name": "E J Pettersson's forge and mechanical workshop"
                }
            },
            {
                "@type": "OrganizationRole",
                "title": "Draftsman",
                "startDate": "1907",
                "endDate": "1909",
                "employer": {
                    "@type": "Organization",
                    "name": "AB P A Sjögren Stockholm"
                }
            },
            {
                "@type": "OrganizationRole",
                "title": "Designer",
                "startDate": "1909",
                "endDate": "1919",
                "employer": {
                    "@type": "Organization",
                    "name": "William Andersson's design office"
                }
            },
            {
                "@type": "OrganizationRole",
                "title": "Owner",
                "startDate": "1919",
                "employer": {
                    "@type": "Organization",
                    "name": "Eklund Engineering Office"
                }
            },
            {
                "@type": "OrganizationRole",
                "title": "Owner",
                "startDate": "1941",
                "employer": {
                    "@type": "Organization",
                    "name": "AB"
                }
            }
        ],
        "designWorks": [
            {
                "@type": "CivicStructure",
                "name": "Grand Hotel Stockholm",
                "constructionStartDate": "1925"
            },
            {
                "@type": "CivicStructure",
                "name": "City Palace Stockholm",
                "constructionStartDate": "1932"
            },
            {
                "@type": "CivicStructure",
                "name": "HSB buildings Kungsklippan",
                "constructionStartDate": "1934"
            },
            {
                "@type": "CivicStructure",
                "name": "Maritime Museum",
                "constructionStartDate": "1934"
            },
            {
                "@type": "CivicStructure",
                "name": "Thule House Stockholm",
                "constructionStartDate": "1941"
            },
            {
                "@type": "CivicStructure",
                "name": "Parliament House",
                "constructionStartDate": "1941"
            },
            {
                "@type": "CivicStructure",
                "name": "St. Erik's Hospital",
                "constructionStartDate": "1941"
            }
        ],
        "hasOccupation": [
            {
                "@type": "TradeOrOccupation",
                "name": "Heat Conduction Engineer"
            },
            {
                "@type": "TradeOrOccupation",
                "name": "Ventilation Engineer"
            },
            {
                "@type": "TradeOrOccupation",
                "name": "Sanitary Technology Engineer"
            }
        ],
        "memberOf": [
            {
                "@type": "Organization",
                "name": "Swedish Society of Engineers"
            },
            {
                "@type": "Organization",
                "name": "American Society of Heating and Ventilating Engineers"
            },
            {
                "@type": "Organization",
                "name": "Swedish Consulting Engineers for Heating and Sanitation"
            }
        ],
        "hobbies": [
            "Sailing"
        ]
    },
    "occupations": {
        "career": [
            {
                "occupational_title": "Consulting Engineer",
                "workplace": "Eklund Engineering Office",
                "industry": "Engineering",
                "start_date": "1919"
            },
            {
                "occupational_title": "Draftsman",
                "workplace": "AB P A Sjögren Stockholm",
                "industry": "Engineering",
                "start_date": "1907"
            },
            {
                "occupational_title": "Designer",
                "workplace": "William Andersson's design office",
                "industry": "Engineering",
                "start_date": "1909"
            },
            {
                "occupational_title": "Employee",
                "workplace": "Stockholm General Telephone Company",
                "industry": "Telecommunications",
                "start_date": "1901"
            },
            {
                "occupational_title": "Apprentice",
                "workplace": "E J Pettersson's forge and mechanical workshop",
                "industry": "Metalworking",
                "start_date": "1903"
            }
        ]
    }
}