{
    "original": "KLINGA, Karl Ivar, överingenjör, Gävle, f Harg, Sthlms l, 17/7 90 av stins Joh K o Hilda Broberg, gm Margareta Steinbeck. Mog.ex Upps 08, ex KTH (kem teknol) 11. Kemist o ing v Skogens Kol AB 11—16, assist åt tekn dir v Helsingborgs Gummifabriks AB 16 —17, anst v Korsnäs Sågv AB, cellulosafabrikerna, sed. 17: chef f biprod.avd o lab, seder-mera chef f kem o elektr avd v cellulosafabr i Karskär, 1:e driftsing där 35, övering sed. 42. Styr.led i Skogsägarnas Olje AB sed. 41. Led av styr f Tekn Frn i Gävle 33—34, led av Sv Pappers- o Cellulosaing.frns Gvlbgskté f standardisering av cellulosaprovn 30—34. Av trycket: Myrsyra i barrvedsträsyra (Bih JKA, 14), Analysmetoder f råa terpentin- o träoljor (ibid, 17), Om tekniska metoder f framställn av absolut alkohol (Tekn Tidskr 34). Led Sv Tekn.frn o Sv Pappers- o Cellulosaing.frn.",
    "translated": "KLINGA, Karl Ivar, chief engineer, Gävle, b. Harg, Stockholm county, 17/7 1890, son of stationmaster Joh K and Hilda Broberg, m. Margareta Steinbeck. Formerly a student at Uppsala University, graduated in 1908, and at the Royal Institute of Technology (chemical technology) in 1911. Chemist and engineer at Skogens Kol AB from 1911 to 1916, assistant to the technical director at Helsingborgs Gummifabriks AB from 1916 to 1917, employed by Korsnäs Sawmill AB, cellulose factories, since 1917: head of by-products department and laboratory, later head of chemical and electrical department at the cellulose factory in Karskär, first operating engineer there in 1935, chief engineer since 1942. Board member of Skogsägarnas Olje AB since 1941. Board member of the Technical Association in Gävle from 1933 to 1934, board member of the Swedish Paper and Cellulose Engineering Association for the standardization of cellulose testing samples from 1930 to 1934. Publications include: \"Formic Acid in Coniferous Wood Acid\" (Bih JKA, 1914), \"Analytical Methods for Crude Turpentine and Wood Oils\" (ibid, 1917), \"Technical Methods for the Production of Absolute Alcohol\" (Tekn Tidskr 1934). Member of the Swedish Engineering Association and the Swedish Paper and Cellulose Engineering Association.",
    "structured": {
        "@context": "http://schema.org",
        "@type": "Person",
        "name": "Klinga, Karl Ivar",
        "jobTitle": "Chief Engineer",
        "birthPlace": "Harg, Stockholm county",
        "birthDate": "1890-07-17",
        "parent": [
            {
                "@type": "Person",
                "name": "Joh K"
            },
            {
                "@type": "Person",
                "name": "Hilda Broberg"
            }
        ],
        "spouse": [
            {
                "@type": "Person",
                "name": "Margareta Steinbeck"
            }
        ],
        "alumniOf": [
            {
                "@type": "CollegeOrUniversity",
                "name": "Uppsala University",
                "startDate": "1908"
            },
            {
                "@type": "CollegeOrUniversity",
                "name": "Royal Institute of Technology",
                "startDate": "1911",
                "endDate": "1911"
            }
        ],
        "worksFor": [
            {
                "@type": "Organization",
                "name": "Skogens Kol AB",
                "startDate": "1911",
                "endDate": "1916",
                "jobTitle": "Chemist and Engineer"
            },
            {
                "@type": "Organization",
                "name": "Helsingborgs Gummifabriks AB",
                "startDate": "1916",
                "endDate": "1917",
                "jobTitle": "Assistant to Technical Director"
            },
            {
                "@type": "Organization",
                "name": "Korsnäs Sawmill AB",
                "startDate": "1917",
                "jobTitle": "Head of By-Products Department and Laboratory"
            }
        ],
        "memberOf": [
            {
                "@type": "Organization",
                "name": "Swedish Engineering Association"
            },
            {
                "@type": "Organization",
                "name": "Swedish Paper and Cellulose Engineering Association"
            }
        ],
        "publication": [
            {
                "@type": "Article",
                "headline": "Myrsyra i barrvedsträsyra",
                "source": "Bih JKA",
                "datePublished": "1914"
            },
            {
                "@type": "Article",
                "headline": "Analysmetoder f råa terpentin- o träoljor",
                "source": "Bih JKA",
                "datePublished": "1917"
            },
            {
                "@type": "Article",
                "headline": "Om tekniska metoder f framställn av absolut alkohol",
                "source": "Tekn Tidskr",
                "datePublished": "1934"
            }
        ]
    },
    "occupations": {
        "career": [
            {
                "occupational_title": "Chemist and engineer",
                "workplace": "Skogens Kol AB",
                "industry": "Chemical technology",
                "start_date": "1911"
            },
            {
                "occupational_title": "Assistant to the technical director",
                "workplace": "Helsingborgs Gummifabriks AB",
                "industry": "Rubber manufacturing",
                "start_date": "1916"
            },
            {
                "occupational_title": "Head of by-products department and laboratory",
                "workplace": "Korsnäs Sawmill AB, cellulose factories",
                "industry": "Wood and cellulose",
                "start_date": "1917"
            },
            {
                "occupational_title": "Head of chemical and electrical department",
                "workplace": "Cellulose factory in Karskär",
                "industry": "Wood and cellulose",
                "start_date": "1935"
            },
            {
                "occupational_title": "Chief engineer",
                "workplace": "Cellulose factory in Karskär",
                "industry": "Wood and cellulose",
                "start_date": "1942"
            }
        ]
    }
}