{
    "original": "EKSTKÖM, Oscar Fredrik, Disponent, Sundsvall, f Björna, Vnorrl, 13/6 82 av jordbr O E o Stina Johansson, gm Elsa Tverling. Folksk, hdlssk. Anst: 08 ss res, 16 kont.ch o 19 disp f Boktr.AB i Sdsv. Ordf Sdsv boktr.klubb, v. ordf Vnorrl o Jämtl l boktr.frn, v. ordf Mell norrl.kr av Sv tidn.utg.frn, styr.led Sv högerpressens ekon frn, styr.suppl Boktr.AB i Sdsv. Vnorrl skyt.frb ftjSM o -GM, d :o Sdsv skyt.-frn. Hobby: Filateli.",
    "translated": "EKSTKÖM, Oscar Fredrik, Manager, Sundsvall, b. Björna, Västernorrland, 13/6 1882, son of farmer Olof Edvard and Stina Johansson, m. Elsa Tverling. Attended elementary school and commercial school. Employed: 1908 as an apprentice, 1916 as an accountant, and 1919 as a manager at the Printing Company Ltd. in Sundsvall. Chairman of the Sundsvall Printing Club, Vice Chairman of the Västernorrland and Jämtland Printing Association, Vice Chairman of the Central Northern Publishers Association, board member of the Swedish Right-Wing Press Economic Association, and board substitute of the Printing Company Ltd. in Sundsvall. Member of the Västernorrland Rifle Association for marksmanship, participant in the Swedish championship and the Nordic Championship, retired from the Sundsvall Rifle Association. Hobby: Philately.",
    "structured": {
        "@context": "https://schema.org",
        "@type": "Person",
        "name": "Oscar Fredrik Ekstköm",
        "birthDate": "1882-06-13",
        "birthPlace": "Björna, Västernorrland",
        "parents": [
            {
                "@type": "Person",
                "name": "Olof Edvard Ekstköm",
                "jobTitle": "Farmer"
            },
            {
                "@type": "Person",
                "name": "Stina Johansson"
            }
        ],
        "spouse": {
            "@type": "Person",
            "name": "Elsa Tverling"
        },
        "education": [
            {
                "@type": "EducationalOrganization",
                "name": "Elementary School"
            },
            {
                "@type": "EducationalOrganization",
                "name": "Commercial School"
            }
        ],
        "employment": [
            {
                "@type": "Organization",
                "name": "Printing Company Ltd.",
                "startDate": "1908",
                "endDate": "1916",
                "jobTitle": "Apprentice"
            },
            {
                "@type": "Organization",
                "name": "Printing Company Ltd.",
                "startDate": "1916",
                "endDate": "1919",
                "jobTitle": "Accountant"
            },
            {
                "@type": "Organization",
                "name": "Printing Company Ltd.",
                "startDate": "1919",
                "jobTitle": "Manager"
            }
        ],
        "affiliations": [
            {
                "@type": "Organization",
                "name": "Sundsvall Printing Club",
                "jobTitle": "Chairman"
            },
            {
                "@type": "Organization",
                "name": "Västernorrland and Jämtland Printing Association",
                "jobTitle": "Vice Chairman"
            },
            {
                "@type": "Organization",
                "name": "Central Northern Publishers Association",
                "jobTitle": "Vice Chairman"
            },
            {
                "@type": "Organization",
                "name": "Swedish Right-Wing Press Economic Association",
                "jobTitle": "Board Member"
            },
            {
                "@type": "Organization",
                "name": "Printing Company Ltd.",
                "jobTitle": "Board Substitute"
            }
        ],
        "activities": [
            {
                "@type": "SportsActivityLocation",
                "name": "Västernorrland Rifle Association",
                "activity": "Marksmanship"
            },
            {
                "@type": "SportsEvent",
                "name": "Swedish Championship"
            },
            {
                "@type": "SportsEvent",
                "name": "Nordic Championship"
            },
            {
                "@type": "Organization",
                "name": "Sundsvall Rifle Association"
            }
        ],
        "memberOf": [
            {
                "@type": "Organization",
                "name": "Swedish Rifle Association"
            }
        ],
        "hobby": "Philately"
    },
    "occupations": {
        "career": [
            {
                "occupational_title": "Apprentice",
                "workplace": "Printing Company Ltd.",
                "industry": "Printing",
                "start_date": "1908"
            },
            {
                "occupational_title": "Accountant",
                "workplace": "Printing Company Ltd.",
                "industry": "Printing",
                "start_date": "1916"
            },
            {
                "occupational_title": "Manager",
                "workplace": "Printing Company Ltd.",
                "industry": "Printing",
                "start_date": "1919"
            }
        ]
    }
}